Workbook
Name OLE_LINK1: 'Annex 3 Preserved charges'!#REF!

Sheet Overview
A2: Company and Licence name, charging year, effective from, status
B3: Company and Licence name | C3: Year | D3: Effective From | E3: Status
A4: Company and Licence name, charging year, effective from, status | B4: Eastern Power Networks | C4: 2020/21 | D4: 1 April 2020 | E4: Final
A6: List of data tables in this workbook
A7: Worksheet | B7: Information
A8: Annex 1 LV and HV charges | B8: Annex 1 contains the charges to LV and HV Designated Properties.
A9: Annex 2 EHV charges | B9: ="Annex 2 contains the charges to Designated EHV Properties and charges applied to LDNOs with Designated EHV Properties/end-users embedded in networks within the " &B4 &" Licence area." -> Annex 2 contains the charges to Designated EHV Properties and charges applied to LDNOs with Designated EHV Properties/end-users embedded in networks within the Eastern Power Networks Licence area.
A10: Annex 3 Preserved charges | B10: Annex 3 contains details of any preserved and additional charges that are valid at this time.
A11: Annex 4 LDNO charges | B11: ="Annex 4 contains charges that are levied on the owner of an embedded network within the "&B4&" Licence area. "&"Electricity suppliers and consumers who have properties connected to an embedded network should contact the embedded network owner to determine their distribution charges."&" The charges listed in this table are not payable by domestic consumers, business consumers or electricity suppliers." -> Annex 4 contains charges that are levied on the owner of an embedded network within the Eastern Power Networks Licence area. Electricity suppliers and consumers who have properties connected to an embedded network should contact the embedded network owner to determine their distribution charges. The charges listed in this table are not payable by domestic consumers, business consumers or electricity suppliers.
A12: Annex 5 LLFs | B12: Annex 5 has been intentionally left blank as this charging statement is published a complete year before the LLFs have been audited. The line loss factors that are approved by the BSC Panel for the applicable year and consequently published on the Elexon website will take precedence and be used in Settlement. This annex will be re-published with these values once they are available.
A13: Annex 6 Charges for New or Amended Designated EHV Properties | B13: ="Annex 6 contains the charges for new or amended Designated EHV Properties and charges applied to LDNOs with new or amended Designated EHV Properties/end-users embedded in networks within the " &B4 &" Licence area." -> Annex 6 contains the charges for new or amended Designated EHV Properties and charges applied to LDNOs with new or amended Designated EHV Properties/end-users embedded in networks within the Eastern Power Networks Licence area.
A14: Nodal prices | B14: Contains the underlying nodal costs used to calculate the current EDCM charges.
A15: SSC TPR to unit rate lookup table | B15: The time periods for the non half hourly metered charge rates in Annex 1 are as specified by the SSC. To determine the appropriate charge rate for each SSC/TPR a lookup table is provided.
A16: Charge calculator | B16: Charge calculator is a tool to help you estimate your distribution charges using current consumption data and forecast consumption data.
A18: Notes to users of this spreadsheet
A20: Please use this spreadsheet with reference to the LC14 use of system charging statement.
A22: Notes to DNOs populating this spreadsheet
A24: DNOs must endeavour to maintain consistency in the structure of this spreadsheet. Any changes to the structure must be noted in the 'Notes to users of this spreadsheet'
A25: The drop down list on the charge calculator can be expanded by unprotecting the charge calculator sheet and selecting 'data', 'data validation...' and then expanding the 'source' data range. The sheet can then be protected.

Sheet Annex 1 LV and HV charges
A1: Back to Overview | B1: Copy All-the-way section from CDCM Ouput 101-A in "Tariff Summary" tab into row 13 below | E1: Note: Where a tariff only has a p/kWh unit rate in Unit Charge 1 then this unit rate applies at all times.
A2: =Overview!B4& " - Effective from "&Overview!D4&" - "&Overview!E4&" LV and HV charges" -> Eastern Power Networks - Effective from 1 April 2020 - Final LV and HV charges
A4: Time Bands for Half Hourly Metered Properties | G4: Time Bands for Half Hourly Unmetered Properties
A5: Time periods | B5: Red Time Band | C5: Amber Time Band | E5: Green Time Band | I5: Black Time Band | J5: Yellow Time Band | K5: Green Time Band
A6: Monday to Friday (Including Bank Holidays) All Year | B6: 16:00 - 19:00 | C6: 07:00 - 16:00 19:00 - 23:00 | E6: 00:00 - 07:00 23:00 - 24:00 | G6: Monday to Friday (Including Bank Holidays) November to February Inclusive | I6: 16:00 - 19:00 | J6: 07:00 - 16:00 19:00 - 23:00 | K6: 00:00 - 07:00 23:00 - 24:00
A7: Saturday and Sunday All Year | E7: 00:00 - 24:00 | G7: Monday to Friday (Including Bank Holidays) March to October Inclusive | J7: 07:00 - 23:00 | K7: 00:00 - 07:00 23:00 - 24:00
A8: Notes | B8: All times are in UK Clock time | G8: Saturday and Sunday All Year | K8: 00:00 - 24:00
G9: Notes | I9: All times are in UK Clock time
A11: Tariff name | B11: Open LLFCs | C11: PCs | D11: Unit charge 1 (NHH) or red/black charge (HH) p/kWh | E11: Unit charge 2 (NHH) or amber/yellow charge (HH) p/kWh | F11: Green charge(HH) p/kWh | G11: Fixed charge p/MPAN/day | H11: Capacity charge p/kVA/day | I11: Exceeded capacity charge p/kVA/day | J11: Reactive power charge p/kVArh | K11: Closed LLFCs
A12: Domestic Unrestricted | B12: 3 | C12: 1 | D12: 2.194 | G12: 4.84 | K12: 40
A13: Domestic Two Rate | B13: 7 | C13: 2 | D13: 2.829 | E13: 0.18 | G13: 4.84 | K13: 11, 25, 43, 46, 58
A14: Domestic Off Peak (related MPAN) | B14: 22 | C14: 2 | D14: 0.242 | K14: 29, 55, 61
A15: Small Non Domestic Unrestricted | B15: 201 | C15: 3 | D15: 1.69 | G15: 4.84 | K15: 237, 238, 239
A16: Small Non Domestic Two Rate | B16: 205 | C16: 4 | D16: 2.052 | E16: 0.16 | G16: 4.84 | K16: 15, 49, 242, 247, 248
A17: Small Non Domestic Off Peak (related MPAN) | B17: 64 | C17: 4 | D17: 0.31 | K17: 33
A18: LV Medium Non-Domestic | B18: 254 | C18: 5-8 | D18: 2.222 | E18: 0.142 | G18: 51.55 | K18: 250
A19: LV Sub Medium Non-Domestic | C19: 5-8 | D19: 1.146 | E19: 0.108 | G19: 7.48
A20: HV Medium Non-Domestic | C20: 5-8 | D20: 0.747 | E20: 0.09 | G20: 102.89
A21: LV Network Domestic | B21: 1 | C21: 0 | D21: 15.283 | E21: 0.486 | F21: 0.135 | G21: 4.84
A22: LV Network Non-Domestic Non-CT | B22: 200 | C22: 0 | D22: 13.13 | E22: 0.429 | F22: 0.127 | G22: 5.42
A23: LV HH Metered | B23: 19, 86 | C23: 0 | D23: 9.8 | E23: 0.314 | F23: 0.11 | G23: 12.76 | H23: 3.64 | I23: 7.56 | J23: 0.315
A24: LV Sub HH Metered | B24: 79, 80 | C24: 0 | D24: 7.104 | E24: 0.215 | F24: 0.096 | G24: 7.48 | H24: 5.18 | I24: 6.8 | J24: 0.208
A25: HV HH Metered | B25: 84, 89 | C25: 0 | D25: 5.765 | E25: 0.174 | F25: 0.09 | G25: 102.89 | H25: 4.28 | I25: 6.02 | J25: 0.167
A26: NHH UMS category A | B26: 100, 110, 150, 160 | C26: 8 | D26: 2.119
A27: NHH UMS category B | B27: 102, 112, 152, 162 | C27: 1 | D27: 2.943
A28: NHH UMS category C | B28: 103, 113, 153, 163 | C28: 1 | D28: 4.869
A29: NHH UMS category D | B29: 101, 111, 151, 161 | C29: 1 | D29: 1.581
A30: LV UMS (Pseudo HH Metered) | B30: 350 | C30: 0 | D30: 40.982 | E30: 1.125 | F30: 0.781
A31: LV Generation NHH or Aggregate HH | B31: 912 | C31: 8 or 0 | D31: -0.983 | G31: 0 | K31: 905, 913
A32: LV Sub Generation NHH | C32: 8 | D32: -0.869 | G32: 0
A33: LV Generation Intermittent | B33: 980 | C33: 0 | D33: -0.983 | G33: 0 | J33: 0.289
A34: LV Generation Intermittent no RP charge | B34: 981 | C34: 0 | D34: -0.983 | G34: 0
A35: LV Generation Non-Intermittent | B35: 982 | C35: 0 | D35: -9.667 | E35: -0.259 | F35: -0.036 | G35: 0 | J35: 0.289
A36: LV Generation Non-Intermittent no RP charge | B36: 983 | C36: 0 | D36: -9.667 | E36: -0.259 | F36: -0.036 | G36: 0
A37: LV Sub Generation Intermittent | B37: 984 | C37: 0 | D37: -0.869 | G37: 0 | J37: 0.255
A38: LV Sub Generation Intermittent no RP charge | B38: 985 | C38: 0 | D38: -0.869 | G38: 0
A39: LV Sub Generation Non-Intermittent | B39: 986 | C39: 0 | D39: -8.618 | E39: -0.217 | F39: -0.029 | G39: 0 | J39: 0.255
A40: LV Sub Generation Non-Intermittent no RP charge | B40: 987 | C40: 0 | D40: -8.618 | E40: -0.217 | F40: -0.029 | G40: 0
A41: HV Generation Intermittent | B41: 988 | C41: 0 | D41: -0.621 | G41: 9.02 | J41: 0.207
A42: HV Generation Intermittent no RP charge | B42: 989 | C42: 0 | D42: -0.621 | G42: 9.02
A43: HV Generation Non-Intermittent | B43: 990 | C43: 0 | D43: -6.343 | E43: -0.12 | F43: -0.014 | G43: 9.02 | J43: 0.207
A44: HV Generation Non-Intermittent no RP charge | B44: 991 | C44: 0 | D44: -6.343 | E44: -0.12 | F44: -0.014 | G44: 9.02

Sheet Annex 2 EHV charges
A1: Back to Overview | C1: Copy data from EDCM Outputs 202-A in "LDNO tariffs transposed" tab into row 11 | F1: Note: The list of MPANs / MSIDs provided may be incomplete; the DNO reserves the right to apply the listed charges to any other MPANs / MSIDs associated with the site.
A2: =Overview!B4& " - Effective from "&Overview!D4&" - "&Overview!E4&" EDCM charges" -> Eastern Power Networks - Effective from 1 April 2020 - Final EDCM charges
A4: Time Periods for Designated EHV Properties
A5: Time periods | D5: Super Red Time Band
A6: Monday to Friday (Including Bank Holidays) November to February Inclusive | D6: 16:00 - 19:00
A7: Notes | D7: All times are in UK Clock time
A9: Import Unique Identifier | B9: LLFC | C9: Import MPANs/MSIDs | D9: Export Unique Identifier | E9: LLFC | F9: Export MPANs/MSIDs | G9: Name | H9: Import Super Red unit charge (p/kWh) | I9: Import fixed charge (p/day) | J9: Import capacity charge (p/kVA/day) | K9: Import exceeded capacity charge (p/kVA/day) | L9: Export Super Red unit charge (p/kWh) | M9: Export fixed charge (p/day) | N9: Export capacity charge (p/kVA/day) | O9: Export exceeded capacity charge (p/kVA/day)
A10: 3VALSW | B10: 585 | C10: 1014569699836 | G10: 3VALSW | I10: 2914.69 | J10: 5.3 | K10: 5.3
A11: ABSRSF | B11: 869 | C11: 1050000574685 | D11: ABSRSF | E11: 744 | F11: 1050000574694 | G11: ABSRSF | H11: 0.173 | I11: 18.4 | J11: 1.73 | K11: 1.73 | M11: 3679.33 | N11: 0.05 | O11: 0.05
A12: ADBRKS | B12: 586 | C12: 1023529546480 | G12: ADBRKS | H12: 0.162 | I12: 3094.55 | J12: 3.51 | K12: 3.51
A13: AIAMAN | B13: 499 | C13: 1014569292506 | D13: AIAMAN | E13: 435 | F13: 1030054607984 | G13: AIAMAN | H13: 0.652 | I13: 8.56 | J13: 8.9 | K13: 8.9 | L13: -0.626 | M13: 171.29 | N13: 0.05 | O13: 0.05
A14: ALCORG | B14: 300 | C14: 1050001015545 | D14: ALCORG | E14: 651 | F14: 1050000998050 | G14: ALCORG | I14: 5.11 | J14: 2.26 | K14: 2.26 | M14: 510.86 | N14: 0.05 | O14: 0.05
A15: ARAMAN | B15: 800 | C15: 1023483097981 | G15: ARAMAN | I15: 6701.37 | J15: 1 | K15: 1
A16: ARDLGH | B16: 564 | C16: 1050001061597 | D16: ARDLGH | E16: 666 | F16: 1050001061602 | G16: ARDLGH | H16: 0.275 | I16: 1.99 | J16: 4 | K16: 4 | M16: 795.65 | N16: 0.05 | O16: 0.05
A17: ARLAFD | B17: 587 | C17: 1030081553176 1030081553404 | D17: ARLAFD | E17: 710 | F17: 1030085114723 1030085114955 | G17: ARLAFD | I17: 3312.05 | J17: 1.7 | K17: 1.7 | M17: 1104.02 | N17: 0.05 | O17: 0.05
A18: ASTONC | B18: 503 | C18: 1050000834246 | D18: ASTONC | E18: 780 | F18: 1050000834255 | G18: ASTONC | H18: 1.797 | I18: 2.6 | J18: 3.6 | K18: 3.6 | M18: 520.15 | N18: 0.05 | O18: 0.05
A19: AVENUE | B19: 504 | C19: 1050000774970 | D19: AVENUE | E19: 781 | F19: 1050000774980 | G19: AVENUE | H19: 0.071 | I19: 17.3 | J19: 3.24 | K19: 3.24 | M19: 1124.59 | N19: 0.05 | O19: 0.05
A20: AWOUSE | B20: 589 | C20: 1023475403798 1014571965793 | G20: AWOUSE | H20: 3.024 | I20: 179.86 | J20: 2.19 | K20: 2.19
A21: BARNFM | B21: 301 | C21: 1050000774999 | D21: BARNFM | E21: 652 | F21: 1050000775005 | G21: BARNFM | H21: 0.334 | I21: 51.03 | J21: 4.18 | K21: 4.18 | M21: 2143.45 | N21: 0.05 | O21: 0.05
A22: BAYFMS | B22: 870 | C22: 1050000579318 | D22: BAYFMS | E22: 745 | F22: 1050000579327 | G22: BAYFMS | H22: 0.107 | I22: 35.35 | J22: 1.55 | K22: 1.55 | M22: 2827.82 | N22: 0.05 | O22: 0.05
A23: BDGHSE | B23: 505 | C23: 1050000669548 | D23: BDGHSE | E23: 782 | F23: 1050000669539 | G23: BDGHSE | I23: 28.47 | J23: 1.48 | K23: 1.48 | M23: 1061.26 | N23: 0.05 | O23: 0.05
A24: BDWLWF | B24: 827 | C24: 1030082700415 | D24: BDWLWF | E24: 734 | F24: 1030082700647 | G24: BDWLWF | H24: 0.013 | I24: 33.48 | J24: 1.97 | K24: 1.97 | M24: 4235.2 | N24: 0.05 | O24: 0.05
A25: BERDHF | B25: 302 | C25: 1050001382522 | D25: BERDHF | E25: 436 | F25: 1050001382531 | G25: BERDHF | I25: 1326 | J25: 1.14 | K25: 1.14 | M25: 1325.75 | N25: 0.05 | O25: 0.05
A26: BERMAT | B26: 590 | C26: 1014571751895 | G26: BERMAT | I26: 89.93 | J26: 5.38 | K26: 5.38
A27: BGWDWF | B27: 871 | C27: 1030083931374 | D27: BGWDWF | E27: 746 | F27: 1030083931142 | G27: BGWDWF | I27: 3.42 | J27: 2.33 | K27: 2.33 | M27: 280.64 | N27: 0.05 | O27: 0.05
A28: BLCAMB | B28: 539 | C28: 1050001036615 | D28: BLCAMB | E28: 653 | F28: 1050001036624 | G28: BLCAMB | I28: 5.06 | J28: 1.68 | K28: 1.68 | M28: 252.93 | N28: 0.05 | O28: 0.05
A29: BLDOCK | C29: MSID: 7308 | D29: BLDOCK | F29: MSID: 7308 | G29: BLDOCK | H29: 1.211 | I29: 37.6 | J29: 1.34 | K29: 1.34 | L29: -1.428 | M29: 752.01 | N29: 0.05 | O29: 0.05
A30: BLGTSF | B30: 534 | C30: 1050000769039 | D30: BLGTSF | E30: 466 | F30: 1050000769048 | G30: BLGTSF | I30: 11.87 | J30: 2.52 | K30: 2.52 | M30: 1127.21 | N30: 0.05 | O30: 0.05
A31: BNNSHL | B31: 540 | C31: 1050001021414 | D31: BNNSHL | E31: 654 | F31: 1050001021423 | G31: BNNSHL | H31: 9.413 | I31: 35.55 | J31: 1.74 | K31: 1.74 | M31: 1520.81 | N31: 0.05 | O31: 0.05
A32: BOCTHA | B32: 803 | C32: 1014572608412 | G32: BOCTHA | H32: 0.654 | I32: 973.99 | J32: 5.37 | K32: 5.37
A33: BOXTED | B33: 506 | C33: 1050000774270 | D33: BOXTED | E33: 783 | F33: 1050000774289 | G33: BOXTED | H33: 0.025 | I33: 1.58 | J33: 2.27 | K33: 2.27 | M33: 256.4 | N33: 0.05 | O33: 0.05
A34: BPA_CO | B34: 804 | C34: 1014572578282 | G34: BPA_CO | H34: 0.168 | I34: 515.97 | J34: 2.64 | K34: 2.64
A35: BPTLTD | B35: 591 | C35: 1023475256360 1014572502380 | G35: BPTLTD | H35: 1.03 | I35: 269.79 | J35: 1.99 | K35: 1.99
A36: BRCHGP | B36: 525 | C36: 1050000961956 | D36: BRCHGP | E36: 457 | F36: 1050000961965 | G36: BRCHGP | H36: 0.405 | I36: 35.84 | J36: 1.67 | K36: 1.67 | M36: 2204.22 | N36: 0.05 | O36: 0.05
A37: BROGB_ | B37: 821 | C37: 1030041592510 1030041592742 1030041592974 1030041593203 | G37: BROGB_ | H37: 0.002 | I37: 246.8 | J37: 1.54 | K37: 1.54
A38: BROXSF | B38: 872 | C38: 1050000521610 | D38: BROXSF | E38: 747 | F38: 1030085039971 | G38: BROXSF | H38: 1.395 | I38: 11.29 | J38: 6.4 | K38: 6.4 | M38: 2596.82 | N38: 0.05 | O38: 0.05
A39: BRTHS2 | B39: 508 | C39: 1050000782944 | D39: BRTHS2 | E39: 785 | F39: 1050000773842 | G39: BRTHS2 | H39: 0.02 | I39: 1.28 | J39: 2.73 | K39: 2.73 | M39: 256.7 | N39: 0.05 | O39: 0.05
A40: BRTHSS | B40: 873 | C40: 1030083941266 | D40: BRTHSS | E40: 735 | F40: 1030083941034 | G40: BRTHSS | H40: 0.007 | I40: 2.85 | J40: 2.09 | K40: 2.09 | M40: 255.14 | N40: 0.05 | O40: 0.05
A41: BRTHSW | B41: 874 | C41: 1030083918035 | D41: BRTHSW | E41: 748 | F41: 1030083917802 | G41: BRTHSW | H41: 0.02 | I41: 7.3 | J41: 1.5 | K41: 1.5 | M41: 250.68 | N41: 0.05 | O41: 0.05
A42: BS_BUR | B42: 805 | C42: 1023485782314 1050000914910 | D42: BS_BUR | E42: 700 | F42: 1023485782546 1050000914900 | G42: BS_BUR | H42: 1.249 | I42: 94.86 | J42: 1.41 | K42: 1.41 | L42: -1.249 | M42: 679.1 | N42: 0.05 | O42: 0.05
A43: BS_WIS | B43: 806 | C43: 1014568635628 | D43: BS_WIS | E43: 719 | F43: 1023470427970 | G43: BS_WIS | H43: 0.004 | I43: 25.8 | J43: 1.7 | K43: 1.7 | L43: -0.419 | M43: 232.19 | N43: 0.05 | O43: 0.05
A44: BSGBRN | B44: 507 | C44: 1050000773851 | D44: BSGBRN | E44: 784 | F44: 1050000773860 | G44: BSGBRN | H44: 0.001 | I44: 12.89 | J44: 2.07 | K44: 2.07 | M44: 1546.29 | N44: 0.05 | O44: 0.05
A45: BTLCOM | B45: 592 | C45: 1050000169030 1014572546086 | G45: BTLCOM | H45: 4.461 | I45: 359.71 | J45: 5.26 | K45: 5.26
A46: BURYLN | B46: 541 | C46: 1050000729676 | D46: BURYLN | E46: 786 | F46: 1050000729667 | G46: BURYLN | H46: 0.002 | I46: 3.13 | J46: 3 | K46: 3 | M46: 781.27 | N46: 0.05 | O46: 0.05
A47: CANTSF | B47: 875 | C47: 1030082355419 | D47: CANTSF | E47: 749 | F47: 1030081926920 | G47: CANTSF | H47: 0.006 | I47: 23.41 | J47: 1.81 | K47: 1.81 | M47: 1170.64 | N47: 0.05 | O47: 0.05
A48: CEMXUK | B48: 593 | C48: 1014571132500 1023474247588 | G48: CEMXUK | H48: 5.242 | I48: 89.93 | J48: 2.63 | K48: 2.63
A49: CHEDSF | B49: 876 | C49: 1030083806488 | D49: CHEDSF | E49: 750 | F49: 1030083806256 | G49: CHEDSF | H49: 0.076 | I49: 8.25 | J49: 3.99 | K49: 3.99 | M49: 1029.32 | N49: 0.05 | O49: 0.05
A50: CHFARM | B50: 542 | C50: 1050000961983 | D50: CHFARM | E50: 683 | F50: 1050000961992 | G50: CHFARM | H50: 1.414 | I50: 49.1 | J50: 2.11 | K50: 2.11 | M50: 2553.27 | N50: 0.05 | O50: 0.05
A51: CHPLOW | B51: 543 | C51: 1050000948022 | D51: CHPLOW | E51: 655 | F51: 1050000948031 | G51: CHPLOW | H51: 0.016 | I51: 49.38 | J51: 1.8 | K51: 1.8 | M51: 4114.98 | N51: 0.05 | O51: 0.05
A52: CLAYPV | B52: 303 | C52: 1050001382337 | D52: CLAYPV | E52: 437 | F52: 1050001382355 | G52: CLAYPV | J52: 1.49 | K52: 1.49 | N52: 0.05 | O52: 0.05
A53: CLDECT | B53: 544 | C53: 1050000714173 | D53: CLDECT | E53: 656 | F53: 1050000714182 | G53: CLDECT | H53: 0.025 | I53: 11.76 | J53: 1.51 | K53: 1.51 | M53: 2587.79 | N53: 0.05 | O53: 0.05
A54: CLFFQY | B54: 304 | C54: 1050001439408 | D54: CLFFQY | E54: 438 | F54: 1050001439417 | G54: CLFFQY | I54: 32.45 | J54: 2.36 | K54: 2.36 | L54: -0.733 | M54: 2496.19 | N54: 0.05 | O54: 0.05
A55: CLRDWN | B55: 305 | C55: 1050001495174 | D55: CLRDWN | E55: 439 | F55: 1050001495183 | G55: CLRDWN | H55: 2.98 | I55: 491.3 | J55: 1.31 | K55: 1.31 | L55: -3.216 | M55: 491.3 | N55: 0.05 | O55: 0.05
A56: CLTSHL | B56: 535 | C56: 1050000841917 | D56: CLTSHL | E56: 467 | F56: 1050000841926 | G56: CLTSHL | H56: 0.194 | I56: 3.02 | J56: 15.04 | K56: 15.04 | M56: 604.23 | N56: 0.05 | O56: 0.05
A57: CMRODC | B57: 594 | C57: 1050001068050 1050001068069 | G57: CMRODC | H57: 0.002 | I57: 257.99 | J57: 3.73 | K57: 3.73
A58: COLDHA | B58: 808 | C58: 1030017556367 | G58: COLDHA | H58: 0.009 | I58: 25.23 | J58: 1.67 | K58: 1.67
A59: CRANHM | B59: 566 | C59: 1050001191792 | D59: CRANHM | E59: 684 | F59: 1050001191808 | G59: CRANHM | H59: 0.128 | I59: 10.18 | J59: 1.6 | K59: 1.6 | M59: 557.95 | N59: 0.05 | O59: 0.05
A60: CROYDN | B60: 509 | C60: 1050000808859 | D60: CROYDN | E60: 787 | F60: 1050000808868 | G60: CROYDN | H60: 0.005 | I60: 2.18 | J60: 3.83 | K60: 3.83 | M60: 1162.98 | N60: 0.05 | O60: 0.05
A61: CRSSNG | B61: 307 | C61: 1050001047087 | D61: CRSSNG | E61: 657 | F61: 1050001047078 | G61: CRSSNG | I61: 1.5 | J61: 7.44 | K61: 7.44 | M61: 749.19 | N61: 0.05 | O61: 0.05
A62: CTWDFM | B62: 835 | C62: 1030079565056 | D62: CTWDFM | E62: 736 | F62: 1030079564823 | G62: CTWDFM | I62: 11.59 | J62: 1.93 | K62: 1.93 | M62: 950.55 | N62: 0.05 | O62: 0.05
A63: DBLANE | B63: 878 | C63: 1050000612950 | D63: DBLANE | E63: 752 | F63: 1050000612940 | G63: DBLANE | H63: 0.171 | I63: 7.75 | J63: 3.51 | K63: 3.51 | M63: 1394.94 | N63: 0.05 | O63: 0.05
A64: DGRLTY | B64: 595 | C64: 1030050289278 1030050289506 | G64: DGRLTY | H64: 2.134 | I64: 6565.89 | J64: 2.1 | K64: 2.1
A65: DRABED | B65: 809 | C65: 1014572509517 | G65: DRABED | I65: 7771.42 | J65: 1.52 | K65: 1.52
A66: DRAPER | B66: 879 | C66: 1050000581432 | D66: DRAPER | E66: 753 | F66: 1050000581441 | G66: DRAPER | I66: 5.34 | J66: 6.89 | K66: 6.89 | M66: 534.1 | N66: 0.05 | O66: 0.05
A67: DRAYTN | B67: 545 | C67: 1050001047272 | D67: DRAYTN | E67: 658 | F67: 1050001047263 | G67: DRAYTN | H67: 2.672 | I67: 11.78 | J67: 1.81 | K67: 1.81 | M67: 530.27 | N67: 0.05 | O67: 0.05
A68: DRYHSE | B68: 877 | C68: 1050000609423 | D68: DRYHSE | E68: 751 | F68: 1050000609380 | G68: DRYHSE | H68: 0.275 | I68: 1.89 | J68: 6.01 | K68: 6.01 | M68: 566.25 | N68: 0.05 | O68: 0.05
A69: EARLHF | B69: 841 | C69: 1030081316739 | D69: EARLHF | E69: 737 | F69: 1030081316960 | G69: EARLHF | H69: 0.005 | I69: 3.59 | J69: 1.63 | K69: 1.63 | M69: 358.72 | N69: 0.05 | O69: 0.05
A70: EBCKHM | B70: 887 | C70: 1050000609441 | D70: EBCKHM | E70: 761 | F70: 1050000563595 | G70: EBCKHM | H70: 0.023 | I70: 2.8 | J70: 15.43 | K70: 15.43 | M70: 534.04 | N70: 0.05 | O70: 0.05
A71: EDLMUC | B71: 810 | C71: 1023497822125 1023497822357 1023514863056 1030010107819 | G71: EDLMUC | H71: 0.067 | I71: 11.06 | J71: 2.84 | K71: 2.84
A72: EDLPIT | B72: 811 | C72: 1030020271288 | G72: EDLPIT | H72: 0.106 | I72: 23.08 | J72: 1.41 | K72: 1.41
A73: EGMRSF | B73: 880 | C73: 1050000567483 | D73: EGMRSF | E73: 754 | F73: 1050000567492 | G73: EGMRSF | H73: 0.016 | I73: 5.11 | J73: 3.54 | K73: 3.54 | M73: 542.15 | N73: 0.05 | O73: 0.05
A74: ELLOSF | B74: 881 | C74: 1050000612880 1050001004933 1050001004942 | D74: ELLOSF | E74: 755 | F74: 1050000612870 1050001004915 1050001004924 | G74: ELLOSF | H74: 0.07 | I74: 4.72 | J74: 4.13 | K74: 4.13 | M74: 1085.01 | N74: 0.05 | O74: 0.05
A75: ELSAGE | B75: 546 | C75: 1050000923668 | D75: ELSAGE | E75: 659 | F75: 1050000923677 | G75: ELSAGE | H75: 0.37 | I75: 15.98 | J75: 19.86 | K75: 19.86 | M75: 959 | N75: 0.05 | O75: 0.05
A76: EMR_TI | B76: 813 | C76: 1023475632649 1014572805060 | G76: EMR_TI | H76: 0.292 | I76: 515.97 | J76: 2.34 | K76: 2.34
A77: EPRSUT | B77: 812 | C77: 1023494988750 | D77: EPRSUT | E77: 705 | F77: 1023503165023 | G77: EPRSUT | H77: 1.258 | I77: 255.86 | J77: 1.52 | K77: 1.52 | L77: -1.334 | M77: 1944.53 | N77: 0.05 | O77: 0.05
A78: ERNUNN | B78: 308 | C78: 1050001440510 | D78: ERNUNN | E78: 441 | F78: 1050001440529 | G78: ERNUNN | I78: 18.98 | J78: 1.73 | K78: 1.73 | L78: -0.096 | M78: 1459.68 | N78: 0.05 | O78: 0.05
A79: ESWMID | B79: 596 | C79: 1014572640842 1014572641075 | D79: ESWMID | E79: 432 | F79: 1023518907371 1023518908064 | G79: ESWMID | H79: 5.671 | I79: 167.87 | J79: 2.64 | K79: 2.64 | L79: -5.599 | M79: 11.99 | N79: 0.05 | O79: 0.05
A80: ESWWIX | B80: 597 | C80: 1014572713989 | G80: ESWWIX | H80: 1.807 | I80: 2398.72 | J80: 4.85 | K80: 4.85
A81: EUSTSF | B81: 882 | C81: 1050000628160 | D81: EUSTSF | E81: 756 | F81: 1050000628170 | G81: EUSTSF | H81: 0.292 | I81: 50.89 | J81: 4.31 | K81: 4.31 | M81: 1221.4 | N81: 0.05 | O81: 0.05
A82: EXNING | B82: 510 | C82: 1050000784384 | D82: EXNING | E82: 788 | F82: 1050000784393 | G82: EXNING | I82: 11.87 | J82: 2.71 | K82: 2.71 | M82: 2848.49 | N82: 0.05 | O82: 0.05
A83: EYEWFM | B83: 883 | C83: 1030085019966 | D83: EYEWFM | E83: 757 | F83: 1030085020190 | G83: EYEWFM | H83: 0.133 | I83: 9.22 | J83: 1.53 | K83: 1.53 | M83: 626.93 | N83: 0.05 | O83: 0.05
A84: FBWTHE | B84: 817 | C84: 1023507304338 | D84: FBWTHE | E84: 718 | F84: 1023507304560 | G84: FBWTHE | H84: 2.817 | I84: 24.29 | J84: 2.38 | K84: 2.38 | L84: -4.109 | M84: 233.69 | N84: 0.05 | O84: 0.05
A85: FENLND | B85: 511 | C85: 1050000774163 | D85: FENLND | E85: 789 | F85: 1050000774172 | G85: FENLND | H85: 0.823 | I85: 37.36 | J85: 1.95 | K85: 1.95 | M85: 3735.8 | N85: 0.05 | O85: 0.05
A86: FIBEYE | B86: 816 | C86: 1023479132092 | D86: FIBEYE | E86: 707 | F86: 1023479132320 | G86: FIBEYE | H86: 1.524 | I86: 17.82 | J86: 1.76 | K86: 1.76 | L86: -1.978 | M86: 302.97 | N86: 0.05 | O86: 0.05
A87: FLYFRM | B87: 512 | C87: 1050000822463 | D87: FLYFRM | E87: 790 | F87: 1050000822472 | G87: FLYFRM | H87: 1.433 | I87: 7.56 | J87: 3.2 | K87: 3.2 | M87: 1134.33 | N87: 0.05 | O87: 0.05
A88: FORD_D | B88: 818 | C88: 1015684515819 | G88: FORD_D | I88: 23890.42 | J88: 3.14 | K88: 3.14
A89: FRDHVS | B89: 598 | C89: 1014572810813 | G89: FRDHVS | H89: 0.748 | I89: 449.64 | J89: 3.52 | K89: 3.52
A90: FUJISL | B90: 599 | C90: 1023526590750 1023526590982 1023526591211 | G90: FUJISL | H90: 1.265 | I90: 269.79 | J90: 3.32 | K90: 3.32
A91: FWINDS | B91: 513 | C91: 1050000709721 | D91: FWINDS | E91: 766 | F91: 1050000709730 | G91: FWINDS | I91: 8.18 | J91: 2.64 | K91: 2.64 | M91: 817.94 | N91: 0.05 | O91: 0.05
A92: FXDFAG | B92: 474 | C92: 1014572633250 1023479907422 | G92: FXDFAG | H92: 5.688 | I92: 2656.71 | J92: 3.49 | K92: 3.49
A93: FXDOYS | B93: 475 | C93: 1023482441566 1023492579962 | G93: FXDOYS | H93: 5.539 | I93: 2656.71 | J93: 3.49 | K93: 3.49
A94: GDE132 | B94: 514 | C94: 1050000738305 | D94: GDE132 | E94: 767 | F94: 1050000738290 | G94: GDE132 | I94: 20.59 | J94: 1.61 | K94: 1.61 | M94: 1027.51 | N94: 0.05 | O94: 0.05
A95: GFTHRN | B95: 567 | C95: 1050000903244 | D95: GFTHRN | E95: 660 | F95: 1050000903253 | G95: GFTHRN | H95: 0.023 | I95: 52.12 | J95: 1.58 | K95: 1.58 | L95: -0.26 | M95: 724.65 | N95: 0.05 | O95: 0.05
A96: GLASM2 | B96: 865 | C96: 1030083962424 | D96: GLASM2 | E96: 738 | F96: 1030083962656 | G96: GLASM2 | H96: 0.09 | I96: 44.57 | J96: 1.78 | K96: 1.78 | M96: 2192.68 | N96: 0.05 | O96: 0.05
A97: GLASSM | B97: 814 | C97: 1030024800679 | G97: GLASSM | H97: 0.114 | I97: 11.48 | J97: 1.82 | K97: 1.82
A98: GLXOST | B98: 476 | C98: 1014569657748 1014569657970 | G98: GLXOST | H98: 3.187 | I98: 179.86 | J98: 3.08 | K98: 3.08
A99: GLXOW2 | B99: 477 | C99: 1023475635409 1023475634488 | G99: GLXOW2 | H99: 5.13 | I99: 179.86 | J99: 1.94 | K99: 1.94
A100: GLXOWR | B100: 478 | C100: 1023484819994 1023475633563 | G100: GLXOWR | H100: 5.13 | I100: 449.64 | J100: 2.28 | K100: 2.28
A101: GOSFLD | B101: 515 | C101: 1050000714216 | D101: GOSFLD | E101: 768 | F101: 1050000714207 | G101: GOSFLD | H101: 0.373 | I101: 191.81 | J101: 2.34 | K101: 2.34 | M101: 2071.52 | N101: 0.05 | O101: 0.05
A102: GREYSH | B102: 310 | C102: 1050001391466 | D102: GREYSH | E102: 443 | F102: 1050001391475 | G102: GREYSH | H102: 7.664 | I102: 101.5 | J102: 2.28 | K102: 2.28 | L102: -7.999 | M102: 1979.27 | N102: 0.05 | O102: 0.05
...

Sheet Annex 2a Import
A1: Note: The list of MPANs / MSIDs provided may be incomplete; the DNO reserves the right to apply the listed charges to any other MPANs / MSIDs associated with the site. Note: This table is automatically populated based on the content of the tab entitled 'Annex 2 EHV Charges'. The timebands are as shown in Annex 2.
A2: =Overview!B4& " - Effective from "&Overview!D4&" - "&Overview!E4&" EDCM import charges" -> Eastern Power Networks - Effective from 1 April 2020 - Final EDCM import charges
A4: Import Unique Identifier | B4: LLFC | C4: Import MPANs/MSIDs | D4: Name | E4: ='Annex 2 EHV charges'!H9 -> Import Super Red unit charge (p/kWh) | F4: ='Annex 2 EHV charges'!I9 -> Import fixed charge (p/day) | G4: ='Annex 2 EHV charges'!J9 -> Import capacity charge (p/kVA/day) | H4: ='Annex 2 EHV charges'!K9 -> Import exceeded capacity charge (p/kVA/day)
A5: {=IFERROR(INDEX('Annex 2 EHV charges'!$A$10:$A$301, MATCH(0, IF(ISBLANK('Annex 2 EHV charges'!$A$10:$A$301),1, COUNTIF(A$4:$A4, 'Annex 2 EHV charges'!$A$10:$A$301)), 0)),"")} -> 3VALSW | B5: =IF($A5="","",VLOOKUP($A5,'Annex 2 EHV charges'!$A:$O,2,0)) -> 585 | C5: =IF($A5="","",VLOOKUP($A5,'Annex 2 EHV charges'!$A:$O,3,0)) -> 1014569699836 | D5: =IF($A5="","",VLOOKUP($A5,'Annex 2 EHV charges'!$A:$O,7,0)) -> 3VALSW | E5: =IFERROR(IF(VLOOKUP($A5,'Annex 2 EHV charges'!$A:$O,8,FALSE)=0,"",VLOOKUP($A5,'Annex 2 EHV charges'!$A:$O,8,FALSE)),"") | F5: =IFERROR(IF(VLOOKUP($A5,'Annex 2 EHV charges'!$A:$O,9,FALSE)=0,"",VLOOKUP($A5,'Annex 2 EHV charges'!$A:$O,9,FALSE)),"") -> 2914.69 | G5: =IFERROR(IF(VLOOKUP($A5,'Annex 2 EHV charges'!$A:$O,10,FALSE)=0,"",VLOOKUP($A5,'Annex 2 EHV charges'!$A:$O,10,FALSE)),"") -> 5.3 | H5: =IFERROR(IF(VLOOKUP($A5,'Annex 2 EHV charges'!$A:$O,11,FALSE)=0,"",VLOOKUP($A5,'Annex 2 EHV charges'!$A:$O,11,FALSE)),"") -> 5.3
A6: {=IFERROR(INDEX('Annex 2 EHV charges'!$A$10:$A$301, MATCH(0, IF(ISBLANK('Annex 2 EHV charges'!$A$10:$A$301),1, COUNTIF(A$4:$A5, 'Annex 2 EHV charges'!$A$10:$A$301)), 0)),"")} -> ABSRSF | B6: =IF($A6="","",VLOOKUP($A6,'Annex 2 EHV charges'!$A:$O,2,0)) -> 869 | C6: =IF($A6="","",VLOOKUP($A6,'Annex 2 EHV charges'!$A:$O,3,0)) -> 1050000574685 | D6: =IF($A6="","",VLOOKUP($A6,'Annex 2 EHV charges'!$A:$O,7,0)) -> ABSRSF | E6: =IFERROR(IF(VLOOKUP($A6,'Annex 2 EHV charges'!$A:$O,8,FALSE)=0,"",VLOOKUP($A6,'Annex 2 EHV charges'!$A:$O,8,FALSE)),"") -> 0.173 | F6: =IFERROR(IF(VLOOKUP($A6,'Annex 2 EHV charges'!$A:$O,9,FALSE)=0,"",VLOOKUP($A6,'Annex 2 EHV charges'!$A:$O,9,FALSE)),"") -> 18.4 | G6: =IFERROR(IF(VLOOKUP($A6,'Annex 2 EHV charges'!$A:$O,10,FALSE)=0,"",VLOOKUP($A6,'Annex 2 EHV charges'!$A:$O,10,FALSE)),"") -> 1.73 | H6: =IFERROR(IF(VLOOKUP($A6,'Annex 2 EHV charges'!$A:$O,11,FALSE)=0,"",VLOOKUP($A6,'Annex 2 EHV charges'!$A:$O,11,FALSE)),"") -> 1.73
A7: {=IFERROR(INDEX('Annex 2 EHV charges'!$A$10:$A$301, MATCH(0, IF(ISBLANK('Annex 2 EHV charges'!$A$10:$A$301),1, COUNTIF(A$4:$A6, 'Annex 2 EHV charges'!$A$10:$A$301)), 0)),"")} -> ADBRKS | B7: =IF($A7="","",VLOOKUP($A7,'Annex 2 EHV charges'!$A:$O,2,0)) -> 586 | C7: =IF($A7="","",VLOOKUP($A7,'Annex 2 EHV charges'!$A:$O,3,0)) -> 1023529546480 | D7: =IF($A7="","",VLOOKUP($A7,'Annex 2 EHV charges'!$A:$O,7,0)) -> ADBRKS | E7: =IFERROR(IF(VLOOKUP($A7,'Annex 2 EHV charges'!$A:$O,8,FALSE)=0,"",VLOOKUP($A7,'Annex 2 EHV charges'!$A:$O,8,FALSE)),"") -> 0.162 | F7: =IFERROR(IF(VLOOKUP($A7,'Annex 2 EHV charges'!$A:$O,9,FALSE)=0,"",VLOOKUP($A7,'Annex 2 EHV charges'!$A:$O,9,FALSE)),"") -> 3094.55 | G7: =IFERROR(IF(VLOOKUP($A7,'Annex 2 EHV charges'!$A:$O,10,FALSE)=0,"",VLOOKUP($A7,'Annex 2 EHV charges'!$A:$O,10,FALSE)),"") -> 3.51 | H7: =IFERROR(IF(VLOOKUP($A7,'Annex 2 EHV charges'!$A:$O,11,FALSE)=0,"",VLOOKUP($A7,'Annex 2 EHV charges'!$A:$O,11,FALSE)),"") -> 3.51
A8: {=IFERROR(INDEX('Annex 2 EHV charges'!$A$10:$A$301, MATCH(0, IF(ISBLANK('Annex 2 EHV charges'!$A$10:$A$301),1, COUNTIF(A$4:$A7, 'Annex 2 EHV charges'!$A$10:$A$301)), 0)),"")} -> AIAMAN | B8: =IF($A8="","",VLOOKUP($A8,'Annex 2 EHV charges'!$A:$O,2,0)) -> 499 | C8: =IF($A8="","",VLOOKUP($A8,'Annex 2 EHV charges'!$A:$O,3,0)) -> 1014569292506 | D8: =IF($A8="","",VLOOKUP($A8,'Annex 2 EHV charges'!$A:$O,7,0)) -> AIAMAN | E8: =IFERROR(IF(VLOOKUP($A8,'Annex 2 EHV charges'!$A:$O,8,FALSE)=0,"",VLOOKUP($A8,'Annex 2 EHV charges'!$A:$O,8,FALSE)),"") -> 0.652 | F8: =IFERROR(IF(VLOOKUP($A8,'Annex 2 EHV charges'!$A:$O,9,FALSE)=0,"",VLOOKUP($A8,'Annex 2 EHV charges'!$A:$O,9,FALSE)),"") -> 8.56 | G8: =IFERROR(IF(VLOOKUP($A8,'Annex 2 EHV charges'!$A:$O,10,FALSE)=0,"",VLOOKUP($A8,'Annex 2 EHV charges'!$A:$O,10,FALSE)),"") -> 8.9 | H8: =IFERROR(IF(VLOOKUP($A8,'Annex 2 EHV charges'!$A:$O,11,FALSE)=0,"",VLOOKUP($A8,'Annex 2 EHV charges'!$A:$O,11,FALSE)),"") -> 8.9
A9: {=IFERROR(INDEX('Annex 2 EHV charges'!$A$10:$A$301, MATCH(0, IF(ISBLANK('Annex 2 EHV charges'!$A$10:$A$301),1, COUNTIF(A$4:$A8, 'Annex 2 EHV charges'!$A$10:$A$301)), 0)),"")} -> ALCORG | B9: =IF($A9="","",VLOOKUP($A9,'Annex 2 EHV charges'!$A:$O,2,0)) -> 300 | C9: =IF($A9="","",VLOOKUP($A9,'Annex 2 EHV charges'!$A:$O,3,0)) -> 1050001015545 | D9: =IF($A9="","",VLOOKUP($A9,'Annex 2 EHV charges'!$A:$O,7,0)) -> ALCORG | E9: =IFERROR(IF(VLOOKUP($A9,'Annex 2 EHV charges'!$A:$O,8,FALSE)=0,"",VLOOKUP($A9,'Annex 2 EHV charges'!$A:$O,8,FALSE)),"") | F9: =IFERROR(IF(VLOOKUP($A9,'Annex 2 EHV charges'!$A:$O,9,FALSE)=0,"",VLOOKUP($A9,'Annex 2 EHV charges'!$A:$O,9,FALSE)),"") -> 5.11 | G9: =IFERROR(IF(VLOOKUP($A9,'Annex 2 EHV charges'!$A:$O,10,FALSE)=0,"",VLOOKUP($A9,'Annex 2 EHV charges'!$A:$O,10,FALSE)),"") -> 2.26 | H9: =IFERROR(IF(VLOOKUP($A9,'Annex 2 EHV charges'!$A:$O,11,FALSE)=0,"",VLOOKUP($A9,'Annex 2 EHV charges'!$A:$O,11,FALSE)),"") -> 2.26
A10: {=IFERROR(INDEX('Annex 2 EHV charges'!$A$10:$A$301, MATCH(0, IF(ISBLANK('Annex 2 EHV charges'!$A$10:$A$301),1, COUNTIF(A$4:$A9, 'Annex 2 EHV charges'!$A$10:$A$301)), 0)),"")} -> ARAMAN | B10: =IF($A10="","",VLOOKUP($A10,'Annex 2 EHV charges'!$A:$O,2,0)) -> 800 | C10: =IF($A10="","",VLOOKUP($A10,'Annex 2 EHV charges'!$A:$O,3,0)) -> 1023483097981 | D10: =IF($A10="","",VLOOKUP($A10,'Annex 2 EHV charges'!$A:$O,7,0)) -> ARAMAN | E10: =IFERROR(IF(VLOOKUP($A10,'Annex 2 EHV charges'!$A:$O,8,FALSE)=0,"",VLOOKUP($A10,'Annex 2 EHV charges'!$A:$O,8,FALSE)),"") | F10: =IFERROR(IF(VLOOKUP($A10,'Annex 2 EHV charges'!$A:$O,9,FALSE)=0,"",VLOOKUP($A10,'Annex 2 EHV charges'!$A:$O,9,FALSE)),"") -> 6701.37 | G10: =IFERROR(IF(VLOOKUP($A10,'Annex 2 EHV charges'!$A:$O,10,FALSE)=0,"",VLOOKUP($A10,'Annex 2 EHV charges'!$A:$O,10,FALSE)),"") -> 1 | H10: =IFERROR(IF(VLOOKUP($A10,'Annex 2 EHV charges'!$A:$O,11,FALSE)=0,"",VLOOKUP($A10,'Annex 2 EHV charges'!$A:$O,11,FALSE)),"") -> 1
A11: {=IFERROR(INDEX('Annex 2 EHV charges'!$A$10:$A$301, MATCH(0, IF(ISBLANK('Annex 2 EHV charges'!$A$10:$A$301),1, COUNTIF(A$4:$A10, 'Annex 2 EHV charges'!$A$10:$A$301)), 0)),"")} -> ARDLGH | B11: =IF($A11="","",VLOOKUP($A11,'Annex 2 EHV charges'!$A:$O,2,0)) -> 564 | C11: =IF($A11="","",VLOOKUP($A11,'Annex 2 EHV charges'!$A:$O,3,0)) -> 1050001061597 | D11: =IF($A11="","",VLOOKUP($A11,'Annex 2 EHV charges'!$A:$O,7,0)) -> ARDLGH | E11: =IFERROR(IF(VLOOKUP($A11,'Annex 2 EHV charges'!$A:$O,8,FALSE)=0,"",VLOOKUP($A11,'Annex 2 EHV charges'!$A:$O,8,FALSE)),"") -> 0.275 | F11: =IFERROR(IF(VLOOKUP($A11,'Annex 2 EHV charges'!$A:$O,9,FALSE)=0,"",VLOOKUP($A11,'Annex 2 EHV charges'!$A:$O,9,FALSE)),"") -> 1.99 | G11: =IFERROR(IF(VLOOKUP($A11,'Annex 2 EHV charges'!$A:$O,10,FALSE)=0,"",VLOOKUP($A11,'Annex 2 EHV charges'!$A:$O,10,FALSE)),"") -> 4 | H11: =IFERROR(IF(VLOOKUP($A11,'Annex 2 EHV charges'!$A:$O,11,FALSE)=0,"",VLOOKUP($A11,'Annex 2 EHV charges'!$A:$O,11,FALSE)),"") -> 4
A12: {=IFERROR(INDEX('Annex 2 EHV charges'!$A$10:$A$301, MATCH(0, IF(ISBLANK('Annex 2 EHV charges'!$A$10:$A$301),1, COUNTIF(A$4:$A11, 'Annex 2 EHV charges'!$A$10:$A$301)), 0)),"")} -> ARLAFD | B12: =IF($A12="","",VLOOKUP($A12,'Annex 2 EHV charges'!$A:$O,2,0)) -> 587 | C12: =IF($A12="","",VLOOKUP($A12,'Annex 2 EHV charges'!$A:$O,3,0)) -> 1030081553176 1030081553404 | D12: =IF($A12="","",VLOOKUP($A12,'Annex 2 EHV charges'!$A:$O,7,0)) -> ARLAFD | E12: =IFERROR(IF(VLOOKUP($A12,'Annex 2 EHV charges'!$A:$O,8,FALSE)=0,"",VLOOKUP($A12,'Annex 2 EHV charges'!$A:$O,8,FALSE)),"") | F12: =IFERROR(IF(VLOOKUP($A12,'Annex 2 EHV charges'!$A:$O,9,FALSE)=0,"",VLOOKUP($A12,'Annex 2 EHV charges'!$A:$O,9,FALSE)),"") -> 3312.05 | G12: =IFERROR(IF(VLOOKUP($A12,'Annex 2 EHV charges'!$A:$O,10,FALSE)=0,"",VLOOKUP($A12,'Annex 2 EHV charges'!$A:$O,10,FALSE)),"") -> 1.7 | H12: =IFERROR(IF(VLOOKUP($A12,'Annex 2 EHV charges'!$A:$O,11,FALSE)=0,"",VLOOKUP($A12,'Annex 2 EHV charges'!$A:$O,11,FALSE)),"") -> 1.7
A13: {=IFERROR(INDEX('Annex 2 EHV charges'!$A$10:$A$301, MATCH(0, IF(ISBLANK('Annex 2 EHV charges'!$A$10:$A$301),1, COUNTIF(A$4:$A12, 'Annex 2 EHV charges'!$A$10:$A$301)), 0)),"")} -> ASTONC | B13: =IF($A13="","",VLOOKUP($A13,'Annex 2 EHV charges'!$A:$O,2,0)) -> 503 | C13: =IF($A13="","",VLOOKUP($A13,'Annex 2 EHV charges'!$A:$O,3,0)) -> 1050000834246 | D13: =IF($A13="","",VLOOKUP($A13,'Annex 2 EHV charges'!$A:$O,7,0)) -> ASTONC | E13: =IFERROR(IF(VLOOKUP($A13,'Annex 2 EHV charges'!$A:$O,8,FALSE)=0,"",VLOOKUP($A13,'Annex 2 EHV charges'!$A:$O,8,FALSE)),"") -> 1.797 | F13: =IFERROR(IF(VLOOKUP($A13,'Annex 2 EHV charges'!$A:$O,9,FALSE)=0,"",VLOOKUP($A13,'Annex 2 EHV charges'!$A:$O,9,FALSE)),"") -> 2.6 | G13: =IFERROR(IF(VLOOKUP($A13,'Annex 2 EHV charges'!$A:$O,10,FALSE)=0,"",VLOOKUP($A13,'Annex 2 EHV charges'!$A:$O,10,FALSE)),"") -> 3.6 | H13: =IFERROR(IF(VLOOKUP($A13,'Annex 2 EHV charges'!$A:$O,11,FALSE)=0,"",VLOOKUP($A13,'Annex 2 EHV charges'!$A:$O,11,FALSE)),"") -> 3.6
A14: {=IFERROR(INDEX('Annex 2 EHV charges'!$A$10:$A$301, MATCH(0, IF(ISBLANK('Annex 2 EHV charges'!$A$10:$A$301),1, COUNTIF(A$4:$A13, 'Annex 2 EHV charges'!$A$10:$A$301)), 0)),"")} -> AVENUE | B14: =IF($A14="","",VLOOKUP($A14,'Annex 2 EHV charges'!$A:$O,2,0)) -> 504 | C14: =IF($A14="","",VLOOKUP($A14,'Annex 2 EHV charges'!$A:$O,3,0)) -> 1050000774970 | D14: =IF($A14="","",VLOOKUP($A14,'Annex 2 EHV charges'!$A:$O,7,0)) -> AVENUE | E14: =IFERROR(IF(VLOOKUP($A14,'Annex 2 EHV charges'!$A:$O,8,FALSE)=0,"",VLOOKUP($A14,'Annex 2 EHV charges'!$A:$O,8,FALSE)),"") -> 0.071 | F14: =IFERROR(IF(VLOOKUP($A14,'Annex 2 EHV charges'!$A:$O,9,FALSE)=0,"",VLOOKUP($A14,'Annex 2 EHV charges'!$A:$O,9,FALSE)),"") -> 17.3 | G14: =IFERROR(IF(VLOOKUP($A14,'Annex 2 EHV charges'!$A:$O,10,FALSE)=0,"",VLOOKUP($A14,'Annex 2 EHV charges'!$A:$O,10,FALSE)),"") -> 3.24 | H14: =IFERROR(IF(VLOOKUP($A14,'Annex 2 EHV charges'!$A:$O,11,FALSE)=0,"",VLOOKUP($A14,'Annex 2 EHV charges'!$A:$O,11,FALSE)),"") -> 3.24
A15: {=IFERROR(INDEX('Annex 2 EHV charges'!$A$10:$A$301, MATCH(0, IF(ISBLANK('Annex 2 EHV charges'!$A$10:$A$301),1, COUNTIF(A$4:$A14, 'Annex 2 EHV charges'!$A$10:$A$301)), 0)),"")} -> AWOUSE | B15: =IF($A15="","",VLOOKUP($A15,'Annex 2 EHV charges'!$A:$O,2,0)) -> 589 | C15: =IF($A15="","",VLOOKUP($A15,'Annex 2 EHV charges'!$A:$O,3,0)) -> 1023475403798 1014571965793 | D15: =IF($A15="","",VLOOKUP($A15,'Annex 2 EHV charges'!$A:$O,7,0)) -> AWOUSE | E15: =IFERROR(IF(VLOOKUP($A15,'Annex 2 EHV charges'!$A:$O,8,FALSE)=0,"",VLOOKUP($A15,'Annex 2 EHV charges'!$A:$O,8,FALSE)),"") -> 3.024 | F15: =IFERROR(IF(VLOOKUP($A15,'Annex 2 EHV charges'!$A:$O,9,FALSE)=0,"",VLOOKUP($A15,'Annex 2 EHV charges'!$A:$O,9,FALSE)),"") -> 179.86 | G15: =IFERROR(IF(VLOOKUP($A15,'Annex 2 EHV charges'!$A:$O,10,FALSE)=0,"",VLOOKUP($A15,'Annex 2 EHV charges'!$A:$O,10,FALSE)),"") -> 2.19 | H15: =IFERROR(IF(VLOOKUP($A15,'Annex 2 EHV charges'!$A:$O,11,FALSE)=0,"",VLOOKUP($A15,'Annex 2 EHV charges'!$A:$O,11,FALSE)),"") -> 2.19
A16: {=IFERROR(INDEX('Annex 2 EHV charges'!$A$10:$A$301, MATCH(0, IF(ISBLANK('Annex 2 EHV charges'!$A$10:$A$301),1, COUNTIF(A$4:$A15, 'Annex 2 EHV charges'!$A$10:$A$301)), 0)),"")} -> BARNFM | B16: =IF($A16="","",VLOOKUP($A16,'Annex 2 EHV charges'!$A:$O,2,0)) -> 301 | C16: =IF($A16="","",VLOOKUP($A16,'Annex 2 EHV charges'!$A:$O,3,0)) -> 1050000774999 | D16: =IF($A16="","",VLOOKUP($A16,'Annex 2 EHV charges'!$A:$O,7,0)) -> BARNFM | E16: =IFERROR(IF(VLOOKUP($A16,'Annex 2 EHV charges'!$A:$O,8,FALSE)=0,"",VLOOKUP($A16,'Annex 2 EHV charges'!$A:$O,8,FALSE)),"") -> 0.334 | F16: =IFERROR(IF(VLOOKUP($A16,'Annex 2 EHV charges'!$A:$O,9,FALSE)=0,"",VLOOKUP($A16,'Annex 2 EHV charges'!$A:$O,9,FALSE)),"") -> 51.03 | G16: =IFERROR(IF(VLOOKUP($A16,'Annex 2 EHV charges'!$A:$O,10,FALSE)=0,"",VLOOKUP($A16,'Annex 2 EHV charges'!$A:$O,10,FALSE)),"") -> 4.18 | H16: =IFERROR(IF(VLOOKUP($A16,'Annex 2 EHV charges'!$A:$O,11,FALSE)=0,"",VLOOKUP($A16,'Annex 2 EHV charges'!$A:$O,11,FALSE)),"") -> 4.18
... A259: {=IFERROR(INDEX('Annex 2 EHV charges'!$A$10:$A$301, MATCH(0, IF(ISBLANK('Annex 2 EHV charges'!$A$10:$A$301),1, COUNTIF(A$4:$A258, 'Annex 2 EHV charges'!$A$10:$A$301)), 0)),"")} | B259: =IF($A259="","",VLOOKUP($A259,'Annex 2 EHV charges'!$A:$O,2,0)) | C259: =IF($A259="","",VLOOKUP($A259,'Annex 2 EHV charges'!$A:$O,3,0)) | D259: =IF($A259="","",VLOOKUP($A259,'Annex 2 EHV charges'!$A:$O,7,0)) | E259: =IFERROR(IF(VLOOKUP($A259,'Annex 2 EHV charges'!$A:$O,8,FALSE)=0,"",VLOOKUP($A259,'Annex 2 EHV charges'!$A:$O,8,FALSE)),"") | F259: =IFERROR(IF(VLOOKUP($A259,'Annex 2 EHV charges'!$A:$O,9,FALSE)=0,"",VLOOKUP($A259,'Annex 2 EHV charges'!$A:$O,9,FALSE)),"") | G259: =IFERROR(IF(VLOOKUP($A259,'Annex 2 EHV charges'!$A:$O,10,FALSE)=0,"",VLOOKUP($A259,'Annex 2 EHV charges'!$A:$O,10,FALSE)),"") | H259: =IFERROR(IF(VLOOKUP($A259,'Annex 2 EHV charges'!$A:$O,11,FALSE)=0,"",VLOOKUP($A259,'Annex 2 EHV charges'!$A:$O,11,FALSE)),"")

Sheet Annex 2b Export
A1: Note: The list of MPANs / MSIDs provided may be incomplete; the DNO reserves the right to apply the listed charges to any other MPANs / MSIDs associated with the site. Note: This table is automatically populated based on the content of the tab entitled 'Annex 2 EHV Charges'. The timebands are as shown in Annex 2.
A2: =Overview!B4& " - Effective from "&Overview!D4&" - "&Overview!E4&" EDCM export charges" -> Eastern Power Networks - Effective from 1 April 2020 - Final EDCM export charges
A4: Export Unique Identifier | B4: LLFC | C4: Export MPANs/MSIDs | D4: Name | E4: ='Annex 2 EHV charges'!L9 -> Export Super Red unit charge (p/kWh) | F4: ='Annex 2 EHV charges'!M9 -> Export fixed charge (p/day) | G4: ='Annex 2 EHV charges'!N9 -> Export capacity charge (p/kVA/day) | H4: ='Annex 2 EHV charges'!O9 -> Export exceeded capacity charge (p/kVA/day)
A5: {=IFERROR(INDEX('Annex 2 EHV charges'!$D$10:$D$301, MATCH(0, IF(ISBLANK('Annex 2 EHV charges'!$D$10:$D$301),1, COUNTIF(A$4:$A4, 'Annex 2 EHV charges'!$D$10:$D$301)), 0)),"")} -> ABSRSF | B5: =IF($A5="","",VLOOKUP($A5,'Annex 2 EHV charges'!$D:$O,2,0)) -> 744 | C5: =IF($A5="","",VLOOKUP($A5,'Annex 2 EHV charges'!$D:$O,3,0)) -> 1050000574694 | D5: =IF($A5="","",VLOOKUP($A5,'Annex 2 EHV charges'!$D:$O,4,0)) -> ABSRSF | E5: =IFERROR(IF(VLOOKUP($A5,'Annex 2 EHV charges'!$D:$O,9,FALSE)=0,"",VLOOKUP($A5,'Annex 2 EHV charges'!$D:$O,9,FALSE)),"") | F5: =IFERROR(IF(VLOOKUP($A5,'Annex 2 EHV charges'!$D:$O,10,FALSE)=0,"",VLOOKUP($A5,'Annex 2 EHV charges'!$D:$O,10,FALSE)),"") -> 3679.33 | G5: =IFERROR(IF(VLOOKUP($A5,'Annex 2 EHV charges'!$D:$O,11,FALSE)=0,"",VLOOKUP($A5,'Annex 2 EHV charges'!$D:$O,11,FALSE)),"") -> 0.05 | H5: =IFERROR(IF(VLOOKUP($A5,'Annex 2 EHV charges'!$D:$O,12,FALSE)=0,"",VLOOKUP($A5,'Annex 2 EHV charges'!$D:$O,12,FALSE)),"") -> 0.05
A6: {=IFERROR(INDEX('Annex 2 EHV charges'!$D$10:$D$301, MATCH(0, IF(ISBLANK('Annex 2 EHV charges'!$D$10:$D$301),1, COUNTIF(A$4:$A5, 'Annex 2 EHV charges'!$D$10:$D$301)), 0)),"")} -> AIAMAN | B6: =IF($A6="","",VLOOKUP($A6,'Annex 2 EHV charges'!$D:$O,2,0)) -> 435 | C6: =IF($A6="","",VLOOKUP($A6,'Annex 2 EHV charges'!$D:$O,3,0)) -> 1030054607984 | D6: =IF($A6="","",VLOOKUP($A6,'Annex 2 EHV charges'!$D:$O,4,0)) -> AIAMAN | E6: =IFERROR(IF(VLOOKUP($A6,'Annex 2 EHV charges'!$D:$O,9,FALSE)=0,"",VLOOKUP($A6,'Annex 2 EHV charges'!$D:$O,9,FALSE)),"") -> -0.626 | F6: =IFERROR(IF(VLOOKUP($A6,'Annex 2 EHV charges'!$D:$O,10,FALSE)=0,"",VLOOKUP($A6,'Annex 2 EHV charges'!$D:$O,10,FALSE)),"") -> 171.29 | G6: =IFERROR(IF(VLOOKUP($A6,'Annex 2 EHV charges'!$D:$O,11,FALSE)=0,"",VLOOKUP($A6,'Annex 2 EHV charges'!$D:$O,11,FALSE)),"") -> 0.05 | H6: =IFERROR(IF(VLOOKUP($A6,'Annex 2 EHV charges'!$D:$O,12,FALSE)=0,"",VLOOKUP($A6,'Annex 2 EHV charges'!$D:$O,12,FALSE)),"") -> 0.05
A7: {=IFERROR(INDEX('Annex 2 EHV charges'!$D$10:$D$301, MATCH(0, IF(ISBLANK('Annex 2 EHV charges'!$D$10:$D$301),1, COUNTIF(A$4:$A6, 'Annex 2 EHV charges'!$D$10:$D$301)), 0)),"")} -> ALCORG | B7: =IF($A7="","",VLOOKUP($A7,'Annex 2 EHV charges'!$D:$O,2,0)) -> 651 | C7: =IF($A7="","",VLOOKUP($A7,'Annex 2 EHV charges'!$D:$O,3,0)) -> 1050000998050 | D7: =IF($A7="","",VLOOKUP($A7,'Annex 2 EHV charges'!$D:$O,4,0)) -> ALCORG | E7: =IFERROR(IF(VLOOKUP($A7,'Annex 2 EHV charges'!$D:$O,9,FALSE)=0,"",VLOOKUP($A7,'Annex 2 EHV charges'!$D:$O,9,FALSE)),"") | F7: =IFERROR(IF(VLOOKUP($A7,'Annex 2 EHV charges'!$D:$O,10,FALSE)=0,"",VLOOKUP($A7,'Annex 2 EHV charges'!$D:$O,10,FALSE)),"") -> 510.86 | G7: =IFERROR(IF(VLOOKUP($A7,'Annex 2 EHV charges'!$D:$O,11,FALSE)=0,"",VLOOKUP($A7,'Annex 2 EHV charges'!$D:$O,11,FALSE)),"") -> 0.05 | H7: =IFERROR(IF(VLOOKUP($A7,'Annex 2 EHV charges'!$D:$O,12,FALSE)=0,"",VLOOKUP($A7,'Annex 2 EHV charges'!$D:$O,12,FALSE)),"") -> 0.05
A8: {=IFERROR(INDEX('Annex 2 EHV charges'!$D$10:$D$301, MATCH(0, IF(ISBLANK('Annex 2 EHV charges'!$D$10:$D$301),1, COUNTIF(A$4:$A7, 'Annex 2 EHV charges'!$D$10:$D$301)), 0)),"")} -> ARDLGH | B8: =IF($A8="","",VLOOKUP($A8,'Annex 2 EHV charges'!$D:$O,2,0)) -> 666 | C8: =IF($A8="","",VLOOKUP($A8,'Annex 2 EHV charges'!$D:$O,3,0)) -> 1050001061602 | D8: =IF($A8="","",VLOOKUP($A8,'Annex 2 EHV charges'!$D:$O,4,0)) -> ARDLGH | E8: =IFERROR(IF(VLOOKUP($A8,'Annex 2 EHV charges'!$D:$O,9,FALSE)=0,"",VLOOKUP($A8,'Annex 2 EHV charges'!$D:$O,9,FALSE)),"") | F8: =IFERROR(IF(VLOOKUP($A8,'Annex 2 EHV charges'!$D:$O,10,FALSE)=0,"",VLOOKUP($A8,'Annex 2 EHV charges'!$D:$O,10,FALSE)),"") -> 795.65 | G8: =IFERROR(IF(VLOOKUP($A8,'Annex 2 EHV charges'!$D:$O,11,FALSE)=0,"",VLOOKUP($A8,'Annex 2 EHV charges'!$D:$O,11,FALSE)),"") -> 0.05 | H8: =IFERROR(IF(VLOOKUP($A8,'Annex 2 EHV charges'!$D:$O,12,FALSE)=0,"",VLOOKUP($A8,'Annex 2 EHV charges'!$D:$O,12,FALSE)),"") -> 0.05
A9: {=IFERROR(INDEX('Annex 2 EHV charges'!$D$10:$D$301, MATCH(0, IF(ISBLANK('Annex 2 EHV charges'!$D$10:$D$301),1, COUNTIF(A$4:$A8, 'Annex 2 EHV charges'!$D$10:$D$301)), 0)),"")} -> ARLAFD | B9: =IF($A9="","",VLOOKUP($A9,'Annex 2 EHV charges'!$D:$O,2,0)) -> 710 | C9: =IF($A9="","",VLOOKUP($A9,'Annex 2 EHV charges'!$D:$O,3,0)) -> 1030085114723 1030085114955 | D9: =IF($A9="","",VLOOKUP($A9,'Annex 2 EHV charges'!$D:$O,4,0)) -> ARLAFD | E9: =IFERROR(IF(VLOOKUP($A9,'Annex 2 EHV charges'!$D:$O,9,FALSE)=0,"",VLOOKUP($A9,'Annex 2 EHV charges'!$D:$O,9,FALSE)),"") | F9: =IFERROR(IF(VLOOKUP($A9,'Annex 2 EHV charges'!$D:$O,10,FALSE)=0,"",VLOOKUP($A9,'Annex 2 EHV charges'!$D:$O,10,FALSE)),"") -> 1104.02 | G9: =IFERROR(IF(VLOOKUP($A9,'Annex 2 EHV charges'!$D:$O,11,FALSE)=0,"",VLOOKUP($A9,'Annex 2 EHV charges'!$D:$O,11,FALSE)),"") -> 0.05 | H9: =IFERROR(IF(VLOOKUP($A9,'Annex 2 EHV charges'!$D:$O,12,FALSE)=0,"",VLOOKUP($A9,'Annex 2 EHV charges'!$D:$O,12,FALSE)),"") -> 0.05
A10: {=IFERROR(INDEX('Annex 2 EHV charges'!$D$10:$D$301, MATCH(0, IF(ISBLANK('Annex 2 EHV charges'!$D$10:$D$301),1, COUNTIF(A$4:$A9, 'Annex 2 EHV charges'!$D$10:$D$301)), 0)),"")} -> ASTONC | B10: =IF($A10="","",VLOOKUP($A10,'Annex 2 EHV charges'!$D:$O,2,0)) -> 780 | C10: =IF($A10="","",VLOOKUP($A10,'Annex 2 EHV charges'!$D:$O,3,0)) -> 1050000834255 | D10: =IF($A10="","",VLOOKUP($A10,'Annex 2 EHV charges'!$D:$O,4,0)) -> ASTONC | E10: =IFERROR(IF(VLOOKUP($A10,'Annex 2 EHV charges'!$D:$O,9,FALSE)=0,"",VLOOKUP($A10,'Annex 2 EHV charges'!$D:$O,9,FALSE)),"") | F10: =IFERROR(IF(VLOOKUP($A10,'Annex 2 EHV charges'!$D:$O,10,FALSE)=0,"",VLOOKUP($A10,'Annex 2 EHV charges'!$D:$O,10,FALSE)),"") -> 520.15 | G10: =IFERROR(IF(VLOOKUP($A10,'Annex 2 EHV charges'!$D:$O,11,FALSE)=0,"",VLOOKUP($A10,'Annex 2 EHV charges'!$D:$O,11,FALSE)),"") -> 0.05 | H10: =IFERROR(IF(VLOOKUP($A10,'Annex 2 EHV charges'!$D:$O,12,FALSE)=0,"",VLOOKUP($A10,'Annex 2 EHV charges'!$D:$O,12,FALSE)),"") -> 0.05
A11: {=IFERROR(INDEX('Annex 2 EHV charges'!$D$10:$D$301, MATCH(0, IF(ISBLANK('Annex 2 EHV charges'!$D$10:$D$301),1, COUNTIF(A$4:$A10, 'Annex 2 EHV charges'!$D$10:$D$301)), 0)),"")} -> AVENUE | B11: =IF($A11="","",VLOOKUP($A11,'Annex 2 EHV charges'!$D:$O,2,0)) -> 781 | C11: =IF($A11="","",VLOOKUP($A11,'Annex 2 EHV charges'!$D:$O,3,0)) -> 1050000774980 | D11: =IF($A11="","",VLOOKUP($A11,'Annex 2 EHV charges'!$D:$O,4,0)) -> AVENUE | E11: =IFERROR(IF(VLOOKUP($A11,'Annex 2 EHV charges'!$D:$O,9,FALSE)=0,"",VLOOKUP($A11,'Annex 2 EHV charges'!$D:$O,9,FALSE)),"") | F11: =IFERROR(IF(VLOOKUP($A11,'Annex 2 EHV charges'!$D:$O,10,FALSE)=0,"",VLOOKUP($A11,'Annex 2 EHV charges'!$D:$O,10,FALSE)),"") -> 1124.59 | G11: =IFERROR(IF(VLOOKUP($A11,'Annex 2 EHV charges'!$D:$O,11,FALSE)=0,"",VLOOKUP($A11,'Annex 2 EHV charges'!$D:$O,11,FALSE)),"") -> 0.05 | H11: =IFERROR(IF(VLOOKUP($A11,'Annex 2 EHV charges'!$D:$O,12,FALSE)=0,"",VLOOKUP($A11,'Annex 2 EHV charges'!$D:$O,12,FALSE)),"") -> 0.05
A12: {=IFERROR(INDEX('Annex 2 EHV charges'!$D$10:$D$301, MATCH(0, IF(ISBLANK('Annex 2 EHV charges'!$D$10:$D$301),1, COUNTIF(A$4:$A11, 'Annex 2 EHV charges'!$D$10:$D$301)), 0)),"")} -> BARNFM | B12: =IF($A12="","",VLOOKUP($A12,'Annex 2 EHV charges'!$D:$O,2,0)) -> 652 | C12: =IF($A12="","",VLOOKUP($A12,'Annex 2 EHV charges'!$D:$O,3,0)) -> 1050000775005 | D12: =IF($A12="","",VLOOKUP($A12,'Annex 2 EHV charges'!$D:$O,4,0)) -> BARNFM | E12: =IFERROR(IF(VLOOKUP($A12,'Annex 2 EHV charges'!$D:$O,9,FALSE)=0,"",VLOOKUP($A12,'Annex 2 EHV charges'!$D:$O,9,FALSE)),"") | F12: =IFERROR(IF(VLOOKUP($A12,'Annex 2 EHV charges'!$D:$O,10,FALSE)=0,"",VLOOKUP($A12,'Annex 2 EHV charges'!$D:$O,10,FALSE)),"") -> 2143.45 | G12: =IFERROR(IF(VLOOKUP($A12,'Annex 2 EHV charges'!$D:$O,11,FALSE)=0,"",VLOOKUP($A12,'Annex 2 EHV charges'!$D:$O,11,FALSE)),"") -> 0.05 | H12: =IFERROR(IF(VLOOKUP($A12,'Annex 2 EHV charges'!$D:$O,12,FALSE)=0,"",VLOOKUP($A12,'Annex 2 EHV charges'!$D:$O,12,FALSE)),"") -> 0.05
A13: {=IFERROR(INDEX('Annex 2 EHV charges'!$D$10:$D$301, MATCH(0, IF(ISBLANK('Annex 2 EHV charges'!$D$10:$D$301),1, COUNTIF(A$4:$A12, 'Annex 2 EHV charges'!$D$10:$D$301)), 0)),"")} -> BAYFMS | B13: =IF($A13="","",VLOOKUP($A13,'Annex 2 EHV charges'!$D:$O,2,0)) -> 745 | C13: =IF($A13="","",VLOOKUP($A13,'Annex 2 EHV charges'!$D:$O,3,0)) -> 1050000579327 | D13: =IF($A13="","",VLOOKUP($A13,'Annex 2 EHV charges'!$D:$O,4,0)) -> BAYFMS | E13: =IFERROR(IF(VLOOKUP($A13,'Annex 2 EHV charges'!$D:$O,9,FALSE)=0,"",VLOOKUP($A13,'Annex 2 EHV charges'!$D:$O,9,FALSE)),"") | F13: =IFERROR(IF(VLOOKUP($A13,'Annex 2 EHV charges'!$D:$O,10,FALSE)=0,"",VLOOKUP($A13,'Annex 2 EHV charges'!$D:$O,10,FALSE)),"") -> 2827.82 | G13: =IFERROR(IF(VLOOKUP($A13,'Annex 2 EHV charges'!$D:$O,11,FALSE)=0,"",VLOOKUP($A13,'Annex 2 EHV charges'!$D:$O,11,FALSE)),"") -> 0.05 | H13: =IFERROR(IF(VLOOKUP($A13,'Annex 2 EHV charges'!$D:$O,12,FALSE)=0,"",VLOOKUP($A13,'Annex 2 EHV charges'!$D:$O,12,FALSE)),"") -> 0.05
A14: {=IFERROR(INDEX('Annex 2 EHV charges'!$D$10:$D$301, MATCH(0, IF(ISBLANK('Annex 2 EHV charges'!$D$10:$D$301),1, COUNTIF(A$4:$A13, 'Annex 2 EHV charges'!$D$10:$D$301)), 0)),"")} -> BDGHSE | B14: =IF($A14="","",VLOOKUP($A14,'Annex 2 EHV charges'!$D:$O,2,0)) -> 782 | C14: =IF($A14="","",VLOOKUP($A14,'Annex 2 EHV charges'!$D:$O,3,0)) -> 1050000669539 | D14: =IF($A14="","",VLOOKUP($A14,'Annex 2 EHV charges'!$D:$O,4,0)) -> BDGHSE | E14: =IFERROR(IF(VLOOKUP($A14,'Annex 2 EHV charges'!$D:$O,9,FALSE)=0,"",VLOOKUP($A14,'Annex 2 EHV charges'!$D:$O,9,FALSE)),"") | F14: =IFERROR(IF(VLOOKUP($A14,'Annex 2 EHV charges'!$D:$O,10,FALSE)=0,"",VLOOKUP($A14,'Annex 2 EHV charges'!$D:$O,10,FALSE)),"") -> 1061.26 | G14: =IFERROR(IF(VLOOKUP($A14,'Annex 2 EHV charges'!$D:$O,11,FALSE)=0,"",VLOOKUP($A14,'Annex 2 EHV charges'!$D:$O,11,FALSE)),"") -> 0.05 | H14: =IFERROR(IF(VLOOKUP($A14,'Annex 2 EHV charges'!$D:$O,12,FALSE)=0,"",VLOOKUP($A14,'Annex 2 EHV charges'!$D:$O,12,FALSE)),"") -> 0.05
A15: {=IFERROR(INDEX('Annex 2 EHV charges'!$D$10:$D$301, MATCH(0, IF(ISBLANK('Annex 2 EHV charges'!$D$10:$D$301),1, COUNTIF(A$4:$A14, 'Annex 2 EHV charges'!$D$10:$D$301)), 0)),"")} -> BDWLWF | B15: =IF($A15="","",VLOOKUP($A15,'Annex 2 EHV charges'!$D:$O,2,0)) -> 734 | C15: =IF($A15="","",VLOOKUP($A15,'Annex 2 EHV charges'!$D:$O,3,0)) -> 1030082700647 | D15: =IF($A15="","",VLOOKUP($A15,'Annex 2 EHV charges'!$D:$O,4,0)) -> BDWLWF | E15: =IFERROR(IF(VLOOKUP($A15,'Annex 2 EHV charges'!$D:$O,9,FALSE)=0,"",VLOOKUP($A15,'Annex 2 EHV charges'!$D:$O,9,FALSE)),"") | F15: =IFERROR(IF(VLOOKUP($A15,'Annex 2 EHV charges'!$D:$O,10,FALSE)=0,"",VLOOKUP($A15,'Annex 2 EHV charges'!$D:$O,10,FALSE)),"") -> 4235.2 | G15: =IFERROR(IF(VLOOKUP($A15,'Annex 2 EHV charges'!$D:$O,11,FALSE)=0,"",VLOOKUP($A15,'Annex 2 EHV charges'!$D:$O,11,FALSE)),"") -> 0.05 | H15: =IFERROR(IF(VLOOKUP($A15,'Annex 2 EHV charges'!$D:$O,12,FALSE)=0,"",VLOOKUP($A15,'Annex 2 EHV charges'!$D:$O,12,FALSE)),"") -> 0.05
A16: {=IFERROR(INDEX('Annex 2 EHV charges'!$D$10:$D$301, MATCH(0, IF(ISBLANK('Annex 2 EHV charges'!$D$10:$D$301),1, COUNTIF(A$4:$A15, 'Annex 2 EHV charges'!$D$10:$D$301)), 0)),"")} -> BERDHF | B16: =IF($A16="","",VLOOKUP($A16,'Annex 2 EHV charges'!$D:$O,2,0)) -> 436 | C16: =IF($A16="","",VLOOKUP($A16,'Annex 2 EHV charges'!$D:$O,3,0)) -> 1050001382531 | D16: =IF($A16="","",VLOOKUP($A16,'Annex 2 EHV charges'!$D:$O,4,0)) -> BERDHF | E16: =IFERROR(IF(VLOOKUP($A16,'Annex 2 EHV charges'!$D:$O,9,FALSE)=0,"",VLOOKUP($A16,'Annex 2 EHV charges'!$D:$O,9,FALSE)),"") | F16: =IFERROR(IF(VLOOKUP($A16,'Annex 2 EHV charges'!$D:$O,10,FALSE)=0,"",VLOOKUP($A16,'Annex 2 EHV charges'!$D:$O,10,FALSE)),"") -> 1325.75 | G16: =IFERROR(IF(VLOOKUP($A16,'Annex 2 EHV charges'!$D:$O,11,FALSE)=0,"",VLOOKUP($A16,'Annex 2 EHV charges'!$D:$O,11,FALSE)),"") -> 0.05 | H16: =IFERROR(IF(VLOOKUP($A16,'Annex 2 EHV charges'!$D:$O,12,FALSE)=0,"",VLOOKUP($A16,'Annex 2 EHV charges'!$D:$O,12,FALSE)),"") -> 0.05
... A161: {=IFERROR(INDEX('Annex 2 EHV charges'!$D$10:$D$301, MATCH(0, IF(ISBLANK('Annex 2 EHV charges'!$D$10:$D$301),1, COUNTIF(A$4:$A160, 'Annex 2 EHV charges'!$D$10:$D$301)), 0)),"")} | B161: =IF($A161="","",VLOOKUP($A161,'Annex 2 EHV charges'!$D:$O,2,0)) | C161: =IF($A161="","",VLOOKUP($A161,'Annex 2 EHV charges'!$D:$O,3,0)) | D161: =IF($A161="","",VLOOKUP($A161,'Annex 2 EHV charges'!$D:$O,4,0)) | E161: =IFERROR(IF(VLOOKUP($A161,'Annex 2 EHV charges'!$D:$O,9,FALSE)=0,"",VLOOKUP($A161,'Annex 2 EHV charges'!$D:$O,9,FALSE)),"") | F161: =IFERROR(IF(VLOOKUP($A161,'Annex 2 EHV charges'!$D:$O,10,FALSE)=0,"",VLOOKUP($A161,'Annex 2 EHV charges'!$D:$O,10,FALSE)),"") | G161: =IFERROR(IF(VLOOKUP($A161,'Annex 2 EHV charges'!$D:$O,11,FALSE)=0,"",VLOOKUP($A161,'Annex 2 EHV charges'!$D:$O,11,FALSE)),"") | H161: =IFERROR(IF(VLOOKUP($A161,'Annex 2 EHV charges'!$D:$O,12,FALSE)=0,"",VLOOKUP($A161,'Annex 2 EHV charges'!$D:$O,12,FALSE)),"")

Sheet Annex 3 Preserved charges
A1: Back to Overview
A2: =Overview!B4& " - Effective from "&Overview!D4&" - "&Overview!E4&" LV and HV tariffs" -> Eastern Power Networks - Effective from 1 April 2020 - Final LV and HV tariffs
A3: NHH preserved charges/additional LLFCs
B4: Closed LLFCs | C4: PCs | D4: Unit charge 1 (NHH) p/kWh | E4: Unit charge 2 (NHH) p/kWh | F4: Fixed charge p/MPAN/day
A6: Notes: | B6: Eastern Power Networks has no Preserved NHH Tariffs/Additional LLFC classes
A11: HH preserved charges/additional LLFCs
B12: Closed LLFCs | C12: PCs | D12: Red/black charge (HH) p/kWh | E12: Amber/yellow charge (HH) p/kWh | F12: Green charge (HH) p/kWh | G12: Fixed charge p/MPAN/day | H12: Capacity charge p/kVA/day | I12: Exceeded capacity charge p/kVA/day | J12: Reactive power charge p/kVArh
A14: Notes: | B14: Eastern Power Networks has no Preserved HH Tariffs/Additional LLFC classes

Sheet Annex 4 LDNO charges
A1: Back to Overview | B1: Copy LDNO sections from CDCM Ouput 101-A in "Tariff Summary" tab for rows 13 to 55 | F1: Copy data from EDCM Outputs 204-A to 204-E in "LDNO tariffs transposed" tab for rows 56 and below
A2: =Overview!B4& " - Effective from "&Overview!D4&" - "&Overview!E4&" LDNO tariffs" -> Eastern Power Networks - Effective from 1 April 2020 - Final LDNO tariffs
A4: Time Bands for Half Hourly Metered Properties | F4: Time Bands for Half Hourly Unmetered Properties
A5: Time periods | B5: Red Time Band | C5: Amber Time Band | D5: Green Time Band | H5: Black Time Band | I5: Yellow Time Band | J5: Green Time Band
A6: Monday to Friday (Including Bank Holidays) All Year | B6: 16:00 - 19:00 | C6: 07:00 - 16:00 19:00 - 23:00 | D6: 00:00 - 07:00 23:00 - 24:00 | F6: Monday to Friday (Including Bank Holidays) November to February Inclusive | H6: 16:00 - 19:00 | I6: 07:00 - 16:00 19:00 - 23:00 | J6: 00:00 - 07:00 23:00 - 24:00
A7: Saturday and Sunday All Year | D7: 00:00 - 24:00 | F7: Monday to Friday (Including Bank Holidays) March to October Inclusive | I7: 07:00 - 23:00 | J7: 00:00 - 07:00 23:00 - 24:00
A8: Notes | B8: All times are in UK Clock time | F8: Saturday and Sunday All Year | J8: 00:00 - 24:00
F9: Notes | H9: All times are in UK Clock time
A11: Tariff name | B11: Unique billing identifier | C11: PCs | D11: ='Annex 1 LV and HV charges'!D11 -> Unit charge 1 (NHH) or red/black charge (HH) p/kWh | E11: ='Annex 1 LV and HV charges'!E11 -> Unit charge 2 (NHH) or amber/yellow charge (HH) p/kWh | F11: ='Annex 1 LV and HV charges'!F11 -> Green charge(HH) p/kWh | G11: ='Annex 1 LV and HV charges'!G11 -> Fixed charge p/MPAN/day | H11: ='Annex 1 LV and HV charges'!H11 -> Capacity charge p/kVA/day | I11: ='Annex 1 LV and HV charges'!I11 -> Exceeded capacity charge p/kVA/day | J11: ='Annex 1 LV and HV charges'!J11 -> Reactive power charge p/kVArh
A12: LDNO LV: Domestic Unrestricted | B12: 101 | C12: 1 | D12: 1.51 | G12: 3.33
A13: LDNO LV: Domestic Two Rate | B13: 111 | C13: 2 | D13: 1.947 | E13: 0.124 | G13: 3.33
A14: LDNO LV: Domestic Off Peak (related MPAN) | B14: 121 | C14: 2 | D14: 0.167
A15: LDNO LV: Small Non Domestic Unrestricted | B15: 131 | C15: 3 | D15: 1.163 | G15: 3.33
A16: LDNO LV: Small Non Domestic Two Rate | B16: 141 | C16: 4 | D16: 1.412 | E16: 0.11 | G16: 3.33
A17: LDNO LV: Small Non Domestic Off Peak (related MPAN) | B17: 151 | C17: 4 | D17: 0.213
A18: LDNO LV: LV Medium Non-Domestic | B18: 161 | C18: 5-8 | D18: 1.529 | E18: 0.098 | G18: 35.47
A19: LDNO LV: LV Network Domestic | B19: 318 | C19: 0 | D19: 10.517 | E19: 0.334 | F19: 0.093 | G19: 3.33
A20: LDNO LV: LV Network Non-Domestic Non-CT | B20: 325 | C20: 0 | D20: 9.035 | E20: 0.295 | F20: 0.087 | G20: 3.73
A21: LDNO LV: LV HH Metered | B21: 181 | C21: 0 | D21: 6.744 | E21: 0.216 | F21: 0.076 | G21: 8.78 | H21: 2.5 | I21: 5.2 | J21: 0.217
A22: LDNO LV: NHH UMS category A | B22: 201 | C22: 8 | D22: 1.458
A23: LDNO LV: NHH UMS category B | B23: 201 | C23: 1 | D23: 2.025
A24: LDNO LV: NHH UMS category C | B24: 201 | C24: 1 | D24: 3.351
A25: LDNO LV: NHH UMS category D | B25: 201 | C25: 1 | D25: 1.088
A26: LDNO LV: LV UMS (Pseudo HH Metered) | B26: 211 | C26: 0 | D26: 28.202 | E26: 0.774 | F26: 0.537
A27: LDNO LV: LV Generation NHH or Aggregate HH | B27: 221 | C27: 8 or 0 | D27: -0.983 | G27: 0
A28: LDNO LV: LV Generation Intermittent | B28: 231 | C28: 0 | D28: -0.983 | G28: 0 | J28: 0.289
A29: LDNO LV: LV Generation Non-Intermittent | B29: 241 | C29: 0 | D29: -9.667 | E29: -0.259 | F29: -0.036 | G29: 0 | J29: 0.289
A30: LDNO HV: Domestic Unrestricted | B30: 102 | C30: 1 | D30: 1.15 | G30: 2.54
A31: LDNO HV: Domestic Two Rate | B31: 112 | C31: 2 | D31: 1.483 | E31: 0.094 | G31: 2.54
A32: LDNO HV: Domestic Off Peak (related MPAN) | B32: 122 | C32: 2 | D32: 0.127
A33: LDNO HV: Small Non Domestic Unrestricted | B33: 132 | C33: 3 | D33: 0.886 | G33: 2.54
A34: LDNO HV: Small Non Domestic Two Rate | B34: 142 | C34: 4 | D34: 1.076 | E34: 0.084 | G34: 2.54
A35: LDNO HV: Small Non Domestic Off Peak (related MPAN) | B35: 152 | C35: 4 | D35: 0.163
A36: LDNO HV: LV Medium Non-Domestic | B36: 162 | C36: 5-8 | D36: 1.165 | E36: 0.074 | G36: 27.03
A37: LDNO HV: LV Network Domestic | B37: 319 | C37: 0 | D37: 8.013 | E37: 0.255 | F37: 0.071 | G37: 2.54
A38: LDNO HV: LV Network Non-Domestic Non-CT | B38: 326 | C38: 0 | D38: 6.884 | E38: 0.224 | F38: 0.067 | G38: 2.84
A39: LDNO HV: LV HH Metered | B39: 182 | C39: 0 | D39: 5.138 | E39: 0.165 | F39: 0.058 | G39: 6.69 | H39: 1.91 | I39: 3.96 | J39: 0.165
A40: LDNO HV: LV Sub HH Metered | B40: 172 | C40: 0 | D40: 5.562 | E40: 0.168 | F40: 0.074 | G40: 5.86 | H40: 4.06 | I40: 5.32 | J40: 0.163
A41: LDNO HV: HV HH Metered | B41: 192 | C41: 0 | D41: 5.019 | E41: 0.152 | F41: 0.078 | G41: 89.57 | H41: 3.73 | I41: 5.24 | J41: 0.145
A42: LDNO HV: NHH UMS category A | B42: 202 | C42: 8 | D42: 1.111
A43: LDNO HV: NHH UMS category B | B43: 202 | C43: 1 | D43: 1.543
A44: LDNO HV: NHH UMS category C | B44: 202 | C44: 1 | D44: 2.553
A45: LDNO HV: NHH UMS category D | B45: 202 | C45: 1 | D45: 0.829
A46: LDNO HV: LV UMS (Pseudo HH Metered) | B46: 212 | C46: 0 | D46: 21.488 | E46: 0.59 | F46: 0.41
A47: LDNO HV: LV Generation NHH or Aggregate HH | B47: 222 | C47: 8 or 0 | D47: -0.983 | G47: 0
A48: LDNO HV: LV Sub Generation NHH | C48: 8 | D48: -0.869 | G48: 0
A49: LDNO HV: LV Generation Intermittent | B49: 232 | C49: 0 | D49: -0.983 | G49: 0 | J49: 0.289
A50: LDNO HV: LV Generation Non-Intermittent | B50: 242 | C50: 0 | D50: -9.667 | E50: -0.259 | F50: -0.036 | G50: 0 | J50: 0.289
A51: LDNO HV: LV Sub Generation Intermittent | B51: 252 | C51: 0 | D51: -0.869 | G51: 0 | J51: 0.255
A52: LDNO HV: LV Sub Generation Non-Intermittent | B52: 262 | C52: 0 | D52: -8.618 | E52: -0.217 | F52: -0.029 | G52: 0 | J52: 0.255
A53: LDNO HV: HV Generation Intermittent | B53: 272 | C53: 0 | D53: -0.621 | G53: 0 | J53: 0.207
A54: LDNO HV: HV Generation Non-Intermittent | B54: 282 | C54: 0 | D54: -6.343 | E54: -0.12 | F54: -0.014 | G54: 0 | J54: 0.207
A55: LDNO HVplus: Domestic Unrestricted | B55: 103 | C55: 1 | D55: 0.996 | G55: 2.2
A56: LDNO HVplus: Domestic Two Rate | B56: 113 | C56: 2 | D56: 1.284 | E56: 0.082 | G56: 2.2
A57: LDNO HVplus: Domestic Off Peak (related MPAN) | B57: 123 | C57: 2 | D57: 0.11
A58: LDNO HVplus: Small Non Domestic Unrestricted | B58: 133 | C58: 3 | D58: 0.767 | G58: 2.2
A59: LDNO HVplus: Small Non Domestic Two Rate | B59: 143 | C59: 4 | D59: 0.931 | E59: 0.073 | G59: 2.2
A60: LDNO HVplus: Small Non Domestic Off Peak (related MPAN) | B60: 153 | C60: 4 | D60: 0.141
A61: LDNO HVplus: LV Medium Non-Domestic | B61: 163 | C61: 5-8 | D61: 1.009 | E61: 0.064 | G61: 23.4
A62: LDNO HVplus: LV Sub Medium Non-Domestic | C62: 5-8 | D62: 0.761 | E62: 0.072 | G62: 4.96
A63: LDNO HVplus: HV Medium Non-Domestic | C63: 5-8 | D63: 0.548 | E63: 0.066 | G63: 75.43
A64: LDNO HVplus: LV Network Domestic | B64: 320 | C64: 0 | D64: 6.937 | E64: 0.221 | F64: 0.061 | G64: 2.2
A65: LDNO HVplus: LV Network Non-Domestic Non-CT | B65: 327 | C65: 0 | D65: 5.96 | E65: 0.195 | F65: 0.058 | G65: 2.46
A66: LDNO HVplus: LV HH Metered | B66: 183 | C66: 0 | D66: 4.448 | E66: 0.143 | F66: 0.05 | G66: 5.79 | H66: 1.65 | I66: 3.43 | J66: 0.143
A67: LDNO HVplus: LV Sub HH Metered | B67: 173 | C67: 0 | D67: 4.715 | E67: 0.143 | F67: 0.064 | G67: 4.96 | H67: 3.44 | I67: 4.51 | J67: 0.138
A68: LDNO HVplus: HV HH Metered | B68: 193 | C68: 0 | D68: 4.226 | E68: 0.128 | F68: 0.066 | G68: 75.43 | H68: 3.14 | I68: 4.41 | J68: 0.122
A69: LDNO HVplus: NHH UMS category A | B69: 203 | C69: 8 | D69: 0.962
A70: LDNO HVplus: NHH UMS category B | B70: 203 | C70: 1 | D70: 1.336
A71: LDNO HVplus: NHH UMS category C | B71: 203 | C71: 1 | D71: 2.21
A72: LDNO HVplus: NHH UMS category D | B72: 203 | C72: 1 | D72: 0.718
A73: LDNO HVplus: LV UMS (Pseudo HH Metered) | B73: 213 | C73: 0 | D73: 18.602 | E73: 0.511 | F73: 0.354
A74: LDNO HVplus: LV Generation NHH or Aggregate HH | B74: 223 | C74: 8 | D74: -0.652 | G74: 0
A75: LDNO HVplus: LV Sub Generation NHH | C75: 8 | D75: -0.637 | G75: 0
A76: LDNO HVplus: LV Generation Intermittent | B76: 233 | C76: 0 | D76: -0.652 | G76: 0 | J76: 0.192
A77: LDNO HVplus: LV Generation Non-Intermittent | B77: 243 | C77: 0 | D77: -6.416 | E77: -0.172 | F77: -0.024 | G77: 0 | J77: 0.192
A78: LDNO HVplus: LV Sub Generation Intermittent | B78: 253 | C78: 0 | D78: -0.637 | G78: 0 | J78: 0.187
A79: LDNO HVplus: LV Sub Generation Non-Intermittent | B79: 263 | C79: 0 | D79: -6.318 | E79: -0.159 | F79: -0.021 | G79: 0 | J79: 0.187
A80: LDNO HVplus: HV Generation Intermittent | B80: 273 | C80: 0 | D80: -0.621 | G80: 9.02 | J80: 0.207
A81: LDNO HVplus: HV Generation Non-Intermittent | B81: 283 | C81: 0 | D81: -6.343 | E81: -0.12 | F81: -0.014 | G81: 9.02 | J81: 0.207
A82: LDNO EHV: Domestic Unrestricted | B82: 104 | C82: 1 | D82: 0.773 | G82: 1.71
A83: LDNO EHV: Domestic Two Rate | B83: 114 | C83: 2 | D83: 0.997 | E83: 0.063 | G83: 1.71
A84: LDNO EHV: Domestic Off Peak (related MPAN) | B84: 124 | C84: 2 | D84: 0.085
A85: LDNO EHV: Small Non Domestic Unrestricted | B85: 134 | C85: 3 | D85: 0.596 | G85: 1.71
A86: LDNO EHV: Small Non Domestic Two Rate | B86: 144 | C86: 4 | D86: 0.723 | E86: 0.056 | G86: 1.71
A87: LDNO EHV: Small Non Domestic Off Peak (related MPAN) | B87: 154 | C87: 4 | D87: 0.109
A88: LDNO EHV: LV Medium Non-Domestic | B88: 164 | C88: 5-8 | D88: 0.783 | E88: 0.05 | G88: 18.17
A89: LDNO EHV: LV Sub Medium Non-Domestic | B89: 294 | C89: 5-8 | D89: 0.591 | E89: 0.056 | G89: 3.85
A90: LDNO EHV: HV Medium Non-Domestic | B90: 304 | C90: 5-8 | D90: 0.425 | E90: 0.051 | G90: 58.56
A91: LDNO EHV: LV Network Domestic | B91: 321 | C91: 0 | D91: 5.386 | E91: 0.171 | F91: 0.048 | G91: 1.71
A92: LDNO EHV: LV Network Non-Domestic Non-CT | B92: 328 | C92: 0 | D92: 4.627 | E92: 0.151 | F92: 0.045 | G92: 1.91
A93: LDNO EHV: LV HH Metered | B93: 184 | C93: 0 | D93: 3.454 | E93: 0.111 | F93: 0.039 | G93: 4.5 | H93: 1.28 | I93: 2.66 | J93: 0.111
A94: LDNO EHV: LV Sub HH Metered | B94: 174 | C94: 0 | D94: 3.661 | E94: 0.111 | F94: 0.049 | G94: 3.85 | H94: 2.67 | I94: 3.5 | J94: 0.107
A95: LDNO EHV: HV HH Metered | B95: 194 | C95: 0 | D95: 3.281 | E95: 0.099 | F95: 0.051 | G95: 58.56 | H95: 2.44 | I95: 3.43 | J95: 0.095
A96: LDNO EHV: NHH UMS category A | B96: 204 | C96: 8 | D96: 0.747
A97: LDNO EHV: NHH UMS category B | B97: 204 | C97: 1 | D97: 1.037
A98: LDNO EHV: NHH UMS category C | B98: 204 | C98: 1 | D98: 1.716
A99: LDNO EHV: NHH UMS category D | B99: 204 | C99: 1 | D99: 0.557
A100: LDNO EHV: LV UMS (Pseudo HH Metered) | B100: 214 | C100: 0 | D100: 14.442 | E100: 0.396 | F100: 0.275
A101: LDNO EHV: LV Generation NHH or Aggregate HH | B101: 224 | C101: 8 | D101: -0.507 | G101: 0
A102: LDNO EHV: LV Sub Generation NHH | C102: 8 | D102: -0.495 | G102: 0
...

Sheet Annex 5 LLFs
A1: Back to Overview
A2: These line loss factors are illustrative based on the latest calculated values and are published in good faith. However, the line loss factors that are approved by the BSC Panel for the applicable year and consequently published on the Elexon website will take precedence and will be used in Settlement if they differ from these values.
A3: =Overview!B4& " - Illustrative LLFs for year beginning "&Overview!D4 -> Eastern Power Networks - Illustrative LLFs for year beginning 1 April 2020
A4: Time periods | C4: Period 1 | D4: Period 2 | E4: Period 3 | F4: Period 4 | G4: Period 5
C5: Winter Peak | D5: Summer Peak | E5: Winter Shoulder | F5: Night | G5: Other
A6: Monday to Friday November to February | C6: 16:00 - 19:59 | E6: 07:00 - 15:59
A7: Monday to Friday June to August | D7: 07:00 - 19:59
A8: Monday to Friday March | E8: 07:00 - 19:59
A9: All Year | F9: 00:00 - 06:59 | G9: All Other Times
A10: Notes | C10: All times are in UK Clock time
A12: Generic demand and generation LLFs
A13: Metered voltage, respective periods and associated LLFCs
A14: Metered voltage | C14: Period 1 | D14: Period 2 | E14: Period 3 | F14: Period 4 | G14: Period 5 | H14: Associated LLFC
A15: Low Voltage Network | C15: 1.111 | D15: 1.081 | E15: 1.099 | F15: 1.075 | G15: 1.086 | H15: 1, 3, 7, 19, 22, 64, 86, 100, 101, 102, 103, 110, 111, 112, 113, 150, 151, 152, 153, 160, 161, 162, 163, 200, 201, 205, 254, 350, 901, 912, 915, 980, 981, 982, 983 | L15: `
A16: Low Voltage Substation | C16: 1.08 | D16: 1.061 | E16: 1.072 | F16: 1.057 | G16: 1.064 | H16: 79, 80, 902, 916, 984, 985, 986, 987
A17: High Voltage Network | C17: 1.052 | D17: 1.039 | E17: 1.047 | F17: 1.036 | G17: 1.041 | H17: 84, 89, 903, 918, 988, 989, 990, 991
A18: High Voltage Substation | C18: 1.051 | D18: 1.039 | E18: 1.046 | F18: 1.035 | G18: 1.04 | H18: 771, 791, 792
A19: 33kV Generic | C19: 1.016 | D19: 1.013 | E19: 1.015 | F19: 1.013 | G19: 1.013 | H19: 796, 797
A20: 132kV Generic | C20: 1.004 | D20: 1.003 | E20: 1.003 | F20: 1.002 | G20: 1.003 | H20: 798, 799
A22: EHV site specific LLFs
A23: Demand
A24: LLFC | B24: Site | D24: Period 1 | E24: Period 2 | F24: Period 3 | G24: Period 4 | H24: Period 5
A25: 300 | B25: ALCORG - Import | D25: 1.016 | E25: 1.013 | F25: 1.015 | G25: 1.013 | H25: 1.013
A26: 301 | B26: BARNFM - Import | D26: 0.992 | E26: 1 | F26: 0.995 | G26: 1.003 | H26: 0.996
A27: 302 | B27: BERDHF - Import | D27: 1 | E27: 1 | F27: 1 | G27: 1 | H27: 1
A28: 303 | B28: CLAYPV - Import | D28: 1.051 | E28: 1.051 | F28: 1.051 | G28: 1.051 | H28: 1.051
A29: 304 | B29: CLFFQY - Import | D29: 1.005 | E29: 1.004 | F29: 1.005 | G29: 1.004 | H29: 1.004
A30: 305 | B30: CLRDWN - Import | D30: 1.033 | E30: 1.005 | F30: 1.024 | G30: 1.012 | H30: 1.012
A31: 307 | B31: CRSSNG - Import | D31: 1.084 | E31: 1.083 | F31: 1.084 | G31: 1.083 | H31: 1.084
A32: 308 | B32: ERNUNN - Import | D32: 1.008 | E32: 1.007 | F32: 1.007 | G32: 1.007 | H32: 1.007
A33: 310 | B33: GREYSH - Import | D33: 1.016 | E33: 1.013 | F33: 1.015 | G33: 1.013 | H33: 1.013
A34: 311 | B34: GRNFRM - Import | D34: 1 | E34: 1.002 | F34: 1.001 | G34: 1.022 | H34: 1.002
A35: 312 | B35: HRMT_B - Import | D35: 1.024 | E35: 1.022 | F35: 1.018 | G35: 1.022 | H35: 1.022
A36: 313 | B36: HRSFEN - Import | D36: 1.023 | E36: 1.013 | F36: 1.016 | G36: 1.015 | H36: 1.015
... A265: 898 | B265: STWBRG - Import | D265: 1.014 | E265: 1.008 | F265: 1.012 | G265: 1.011 | H265: 1.013
A267: EHV site specific LLFs
A268: Generation
A269: LLFC | B269: Site | D269: Period 1 | E269: Period 2 | F269: Period 3 | G269: Period 4 | H269: Period 5
A270: 432 | B270: ESWMID - Export | D270: 1.051 | E270: 1.039 | F270: 1.046 | G270: 1.035 | H270: 1.04
A271: 434 | B271: PLMPPR - Export | D271: 0.996 | E271: 0.997 | F271: 0.997 | G271: 0.997 | H271: 0.997
A272: 435 | B272: AIAMAN - Export | D272: 1.051 | E272: 1.039 | F272: 1.046 | G272: 1.035 | H272: 1.04
A273: 436 | B273: BERDHF - Export | D273: 0.999 | E273: 0.999 | F273: 1 | G273: 1 | H273: 1
A274: 437 | B274: CLAYPV - Export | D274: 0.999 | E274: 0.999 | F274: 1 | G274: 1 | H274: 0.999
A275: 438 | B275: CLFFQY - Export | D275: 0.999 | E275: 0.998 | F275: 0.998 | G275: 0.998 | H275: 0.998
A276: 439 | B276: CLRDWN - Export | D276: 1.022 | E276: 1.003 | F276: 1.014 | G276: 1.004 | H276: 1.012
A277: 441 | B277: ERNUNN - Export | D277: 1 | E277: 0.998 | F277: 0.999 | G277: 0.998 | H277: 1
A278: 443 | B278: GREYSH - Export | D278: 1.016 | E278: 1.013 | F278: 1.015 | G278: 1.013 | H278: 1.013
A279: 444 | B279: HDATTP - Export | D279: 1.016 | E279: 1.013 | F279: 1.015 | G279: 1.013 | H279: 1.013
A280: 445 | B280: HRMT_B - Export | D280: 1.002 | E280: 1 | F280: 1.001 | G280: 1 | H280: 1.001
A281: 446 | B281: NEVEDN - Export | D281: 1.001 | E281: 1.001 | F281: 1.002 | G281: 1.001 | H281: 1
... A444: 790 | B444: FLYFRM - Export | D444: 1.009 | E444: 1.003 | F444: 1.004 | G444: 1.006 | H444: 1.004
A446: CVA site specific LLFs
A447: MSID | B447: Site | D447: Period 1 | E447: Period 2 | F447: Period 3 | G447: Period 4 | H447: Period 5
A448: 1413 | B448: NORM_1 | D448: 0.999 | E448: 1 | F448: 1 | G448: 0.999 | H448: 1
A449: 1414 | B449: NORM_1 | D449: 0.999 | E449: 1 | F449: 0.999 | G449: 1 | H449: 0.999
A450: 1419 | B450: SUND_1 | D450: 1 | E450: 1 | F450: 1 | G450: 1 | H450: 1
A451: 1440 | B451: AMEM_1 | D451: 1.005 | E451: 1.003 | F451: 1.004 | G451: 1.003 | H451: 1.003
A452: 1622 | B452: BARKC_A | D452: 1.005 | E452: 1.004 | F452: 1.005 | G452: 1.003 | H452: 1.004
A453: 2035 | B453: STMFRD | D453: 1.006 | E453: 1.003 | F453: 1.005 | G453: 1.004 | H453: 1.005
A454: 7006 | B454: PTRBRO | D454: 0.993 | E454: 0.986 | F454: 0.995 | G454: 0.997 | H454: 0.996
A455: 7044 | B455: KLYN33/KNGSLN | D455: 1.001 | E455: 0.999 | F455: 1.001 | G455: 1.001 | H455: 1.001
A456: 7074 | B456: T_EECL-1 | D456: 1.052 | E456: 1.039 | F456: 1.047 | G456: 1.036 | H456: 1.041
A457: 7111 | B457: GRTYAR | D457: 0.995 | E457: 1 | F457: 0.993 | G457: 0.991 | H457: 0.994
A458: 7277 | B458: GUNFL3 | D458: 1.017 | E458: 1.007 | F458: 1.019 | G458: 1.01 | H458: 1.017
A459: 7308 | B459: BLDOCK | D459: 1.006 | E459: 1.001 | F459: 1.003 | G459: 1.002 | H459: 1.003
... A462: 7369 | B462: E_PEAKGEN | D462: 1.052 | E462: 1.039 | F462: 1.047 | G462: 1.036 | H462: 1.041

Sheet Annex 6 new or amended EHV
A1: Back to Overview | G1: Note: The list of MPANs/MSIDs provided may be incomplete; the DNO reserves the right to apply the listed charges to any other MPANs/MSIDs associated with the site.
A2: Annex 6 - Charges for New or Amended Designated EHV Properties
A4: =Overview!B4& " - Effective from "&Overview!D4&" - "&Overview!E4&" new designated EHV charges" -> Eastern Power Networks - Effective from 1 April 2020 - Final new designated EHV charges
A5: Import Unique Identifier | B5: LLFC | C5: Import MPANs/MSIDs | D5: Export Unique Identifier | E5: LLFC | F5: Export MPANs/MSIDs | G5: Name | H5: Import Super Red unit charge (p/kWh) | I5: Import fixed charge (p/day) | J5: Import capacity charge (p/kVA/day) | K5: Import exceeded capacity charge (p/kVA/day) | L5: Export Super Red unit charge (p/kWh) | M5: Export fixed charge (p/day) | N5: Export capacity charge (p/kVA/day) | O5: Export exceeded capacity charge (p/kVA/day)
A6: ARLBES | C6: MSID: 7401 | D6: ARLBES | F6: MSID: 7402 | G6: ARLBES | H6: 0 | I6: 1700.44 | J6: 1.27 | K6: 1.27 | L6: -0.002 | M6: 1700.44 | N6: 0.05 | O6: 0.05
A7: AW_GRA | B7: 588 | C7: 1014571445536 1023477037942 | D7: AW_GRA | E7: 400 | F7: 1050001872410 1050001872400 | G7: AW_GRA | H7: 4.441 | I7: 89.93 | J7: 4.22 | K7: 4.22 | L7: 0 | M7: 0.00 | N7: 0.05 | O7: 0.05
A8: CAVDRD | B8: 429 | C8: 1050001791569 | D8: CAVDRD | E8: 773 | F8: 1050001791578 | G8: CAVDRD | H8: 0.816 | I8: 31.13 | J8: 1.46 | K8: 1.46 | L8: -1.031 | M8: 785.64 | N8: 0.05 | O8: 0.05
A9: COMBRN | B9: 306 | C9: 1050001662241 | D9: COMBRN | E9: 440 | F9: 1050001662250 | G9: COMBRN | H9: 0.473 | I9: 12.57 | J9: 4.9 | K9: 4.9 | L9: 0 | M9: 1546.27 | N9: 0.05 | O9: 0.05
A10: GOOSFM | B10: 309 | C10: 1050001727953 | D10: GOOSFM | E10: 442 | F10: 1050001727962 | G10: GOOSFM | H10: 0 | I10: 12.23 | J10: 2.13 | K10: 2.13 | L10: 0 | M10: 2139.61 | N10: 0.05 | O10: 0.05
A11: LITSTA | B11: 427 | C11: 1050001858070 | D11: LITSTA | E11: 648 | F11: 1050001858080 | G11: LITSTA | H11: 0.132 | I11: 33.85 | J11: 2.16 | K11: 2.16 | L11: 0 | M11: 6770 | N11: 0.05 | O11: 0.05
A12: MOLLAV | B12: 428 | C12: 1050001620710 | D12: MOLLAV | E12: 774 | F12: 1050001620720 | G12: MOLLAV | H12: 0 | I12: 9.12 | J12: 1.38 | K12: 1.38 | L12: -0.101 | M12: 911.78 | N12: 0.05 | O12: 0.05
A13: RAINDC | B13: 483 | C13: 1050001877738 1050001878244 | D13: RAINDC | E13: 772 | F13: 1050001877747 1050001878253 | G13: RAINDC | H13: 0 | I13: 19016.97 | J13: 2.14 | K13: 2.14 | L13: 0 | M13: 11861.83 | N13: 0.05 | O13: 0.05
A14: ICGLTD | B14: 866 | C14: 1030075706342 | D14: ICGLTD | E14: 649 | F14: 1050001431630 | G14: ICGLTD | I14: 947.65 | J14: 1.97 | K14: 1.97 | L14: 0 | M14: 0 | N14: 0.05 | O14: 0.05
A15: STA33E | B15: 802 | C15: 1050001977780 | G15: STA33E | H15: 0.018 | I15: 0.00 | J15: 0.00 | K15: 0.00
A18: =Overview!B4& " - Effective from "&Overview!D4&" - "&Overview!E4&" new designated EHV line loss factors" -> Eastern Power Networks - Effective from 1 April 2020 - Final new designated EHV line loss factors
A19: Import Unique Identifier | B19: LLFC | C19: Import MPANs/MSIDs | D19: Export Unique Identifier | E19: LLFC | F19: Export MPANs/MSIDs | G19: Name | H19: Import LLF period 1 | I19: Import LLF period 2 | J19: Import LLF period 3 | K19: Import LLF period 4 | L19: Import LLF period 5 | M19: Export LLF period 1 | N19: Export LLF period 2 | O19: Export LLF period 3 | P19: Export LLF period 4 | Q19: Export LLF period 5
A20: ARLBES | B20: 604 | C20: MSID: 7401 | D20: ARLBES | E20: 612 | F20: MSID: 7402 | G20: ARLBES | H20: 1.004 | I20: 1.003 | J20: 1.003 | K20: 1.002 | L20: 1.003 | M20: 1.004 | N20: 1.003 | O20: 1.003 | P20: 1.002 | Q20: 1.003
A21: AW_GRA | B21: 588 | C21: 1014571445536 1023477037942 | D21: AW_GRA | E21: 400 | F21: 1050001872410 1050001872400 | G21: AW_GRA | H21: 1.051 | I21: 1.039 | J21: 1.046 | K21: 1.035 | L21: 1.04 | M21: 1.051 | N21: 1.039 | O21: 1.046 | P21: 1.035 | Q21: 1.04
A22: CAVDRD | B22: 429 | C22: 1050001791569 | D22: CAVDRD | E22: 773 | F22: 1050001791578 | G22: CAVDRD | H22: 1.016 | I22: 1.013 | J22: 1.015 | K22: 1.013 | L22: 1.013 | M22: 1.016 | N22: 1.013 | O22: 1.015 | P22: 1.013 | Q22: 1.013
A23: COMBRN | B23: 306 | C23: 1050001662241 | D23: COMBRN | E23: 440 | F23: 1050001662250 | G23: COMBRN | H23: 1.016 | I23: 1.013 | J23: 1.015 | K23: 1.013 | L23: 1.013 | M23: 1.016 | N23: 1.013 | O23: 1.015 | P23: 1.013 | Q23: 1.013
A24: GOOSFM | B24: 309 | C24: 1050001727953 | D24: GOOSFM | E24: 442 | F24: 1050001727962 | G24: GOOSFM | H24: 1.016 | I24: 1.013 | J24: 1.015 | K24: 1.013 | L24: 1.013 | M24: 1.016 | N24: 1.013 | O24: 1.015 | P24: 1.013 | Q24: 1.013
A25: LITSTA | B25: 427 | C25: 1050001858070 | D25: LITSTA | E25: 648 | F25: 1050001858080 | G25: LITSTA | H25: 1.004 | I25: 1.003 | J25: 1.003 | K25: 1.002 | L25: 1.003 | M25: 1.004 | N25: 1.003 | O25: 1.003 | P25: 1.002 | Q25: 1.003
A26: MOLLAV | B26: 428 | C26: 1050001620710 | D26: MOLLAV | E26: 774 | F26: 1050001620720 | G26: MOLLAV | H26: 1.016 | I26: 1.013 | J26: 1.015 | K26: 1.013 | L26: 1.013 | M26: 1.016 | N26: 1.013 | O26: 1.015 | P26: 1.013 | Q26: 1.013
A27: RAINDC | B27: 483 | C27: 1050001877738 1050001878244 | D27: RAINDC | E27: 772 | F27: 1050001877747 1050001878253 | G27: RAINDC | H27: 1.004 | I27: 1.003 | J27: 1.003 | K27: 1.002 | L27: 1.003 | M27: 1.004 | N27: 1.003 | O27: 1.003 | P27: 1.002 | Q27: 1.003
A28: ICGLTD | B28: 866 | C28: 1030075706342 | D28: ICGLTD | E28: 649 | F28: 1050001431630 | G28: ICGLTD | H28: 1.004 | I28: 1.003 | J28: 1.004 | K28: 1.003 | L28: 1.004 | M28: 1.016 | N28: 1.013 | O28: 1.015 | P28: 1.013 | Q28: 1.013
A29: STA33E | B29: 802 | C29: 1050001977780 | G29: STA33E | H29: 1.009 | I29: 1.011 | J29: 1.014 | K29: 1.009 | L29: 1.009
A32: These line loss factors are illustrative based on the latest calculated values and are published in good faith. However, the line loss factors that are approved by the BSC Panel for the applicable year and consequently published on the Elexon website will take precedence and will be used in Settlement if they differ from these values.

Sheet Nodal prices
A1: Back to Overview
A2: =Overview!B4& " - Effective from "&Overview!D4&" - "&Overview!E4&" Nodal/Zonal charges" -> Eastern Power Networks - Effective from 1 April 2020 - Final Nodal/Zonal charges
A3: Node/Zone ID | B3: Geographical name | C3: Local charge 1 £/kVA | D3: Remote charge 1 £/kVA
A4: ABBE31 | B4: Abberton Grid | C4: 0 | D4: 0.50176557
A5: ABCS31 | B5: EPN 0005 | C5: 0.014467147 | D5: 0.0079070149
A6: ABCS32 | B6: EPN 0005 | C6: 0.70398725 | D6: 0.07700614
A7: ACRO51 | B7: Acrows Primary | C7: 0.071151757 | D7: 1.7710341
A8: ADEB51 | B8: Addenbrookes Primary | C8: 0.056383375 | D8: 0.39681067
A9: ADEL51 | B9: Adelaide St Primary | C9: 2.0265111 | D9: 5.2606403
A10: ADPT31 | B10: British Sugar | C10: -5.5541103 | D10: 3.1840921
A11: ALDA51 | B11: Arla Dairies Primary | C11: 0 | D11: 0
A12: ALDR51 | B12: Aldreth Primary | C12: 0.14686465 | D12: 2.133179
A13: ALDR52 | B13: Aldreth Primary | C13: 0.13159423 | D13: 0.18083343
A14: ALPI51 | B14: Alpington Primary | C14: 0.3146074 | D14: 1.0487375
A15: AMEP51 | B15: Amersham Primary | C15: 0.0090464312 | D15: 1.6463593
... A758: WTMI31 | B758: EPN 0119 | C758: -0.57132501 | D758: -0.00023582194

Sheet SSC TPR unit rate lookup
A1: Back to Overview
A28: Standard Settlement Configuration Id | B28: Time Pattern Regime Id | C28: Standard Settlement Configuration Desc | D28: Common Decode | G28: Change implemented | H28: Date | I28: Comments
A29: 3 | B29: 166 | C29: 10-hour OP | D29: O | H29: 40057 | I29: First published spreadsheet
A30: 4 | B30: 168 | C30: 10-hour OP | D30: O | G30: SSC 0330 charge rates corrected | H30: 40275 | I30: Previous Off-peak rate corrected to charge 2
A31: 5 | B31: 100 | C31: 10-hour OP + w/e | D31: O | G31: SSC 0250 charge rate corrected | H31: 40347 | I31: Previous rate 1 corrected to Off Peak O
A32: 6 | B32: 257 | C32: 10.5-hour OP | D32: O | G32: SSC 0134 charge rate corrected | H32: 41166 | I32: TPR 00101 corrected from Off Peak O to Rate 1
A33: 7 | B33: 158 | C33: 10.5-hour OP | D33: O | G33: New SSCs added | H33: 41178 | I33: New SSCs from 0953 added.
A34: 8 | B34: 159 | C34: 10.5-hour OP | D34: O | G34: SSC 0394 charge rate corrected | H34: 41758 | I34: TPR 01177 corrected to rate 2
A35: 9 | B35: 1111 | C35: 10.5-hour OP | D35: O | G35: Table reviewed and updated | H35: 41758 | I35: New SSCs from 0949 to 0952, 0975 & 0976 and 0982 & 0983 added.
A36: 10 | B36: 1104 | C36: 10.5-hour OP | D36: O | G36: Table reviewed and updated | H36: 41944 | I36: New SSCs from 0984 and 0985 added.
A37: 11 | B37: 1112 | C37: 10.5-hour OP | D37: O | G37: SSC 0313 charge code corrected | H37: 42081 | I37: TPR 01006 corrected to code O
A38: 12 | B38: 1116 | C38: 10.5-hour OP | D38: O | G38: SSC 0320 charge code corrected | H38: 42081 | I38: TPR 00072 corrected to code 2
A39: 13 | B39: 139 | C39: 11 Hour OP | D39: EMEB or MIDE only | G39: SSC 0781 charge code corrected | H39: 42081 | I39: TPR 00327 corrected to code O
A40: 15 | B40: 152 | C40: 11 Hour OP | D40: EMEB or MIDE only | G40: SSC 0935 charge code corrected | H40: 42081 | I40: TPR 00375 corrected to code 1 or Unsupported (SWAE and SWEB)
A41: 16 | B41: 113 | C41: 11.5-hour OP | D41: Unsupported (SWEB) | G41: SSC 0953 charge code corrected | H41: 42081 | I41: TPR 00424 corrected to code 1 or Unsupported (SWAE and SWEB)
... A74: 50 | B74: 14 | C74: 12-hour OP + w/e & Summer | D74: O | G74: SSC 0942 charge code corrected | H74: 42166 | I74: TPR 00400 corrected to code 1
A75: 51 | B75: 112 | C75: 12-hour night | D75: 1 | G75: SSC 0943 charge code corrected | H75: 42166 | I75: TPR 00404 corrected to code 1
A76: 51 | B76: 120 | C76: 12-hour night | D76: 2 | G76: SSC 0944 charge code corrected | H76: 42166 | I76: TPR 00406 corrected to code 1
A77: 52 | B77: 114 | C77: 12-hour OP | D77: EMEB or MIDE only | G77: SSC 0945 charge code corrected | H77: 42166 | I77: TPR 00408 corrected to code 1
A78: 53 | B78: 115 | C78: 12-hour OP | D78: EMEB or MIDE only | G78: SSC 0946 charge code corrected | H78: 42166 | I78: TPR 00410 corrected to code 1
A79: 55 | B79: 117 | C79: 12-hour OP | D79: EMEB or MIDE only | G79: SSC 0954 charge code corrected | H79: 42166 | I79: TPR 00426 corrected to code 1
A80: 56 | B80: 118 | C80: 12-hour OP | D80: EMEB or MIDE only | G80: SSC 0967 charge code corrected | H80: 42166 | I80: TPR 00442 corrected to code 1
A81: 57 | B81: 119 | C81: 12-hour OP | D81: O | G81: SSC 0970 charge code corrected | H81: 42166 | I81: TPR 00447 corrected to code 2
A82: 58 | B82: 21 | C82: Key Meter pseudo 2-rate | D82: 1 | G82: SSC 0970 charge code corrected | H82: 42166 | I82: TPR 00448 corrected to code 1
A83: 58 | B83: 175 | C83: Key Meter pseudo 2-rate | D83: 1 | G83: SSC 0971 charge code corrected | H83: 42166 | I83: TPR 00493 corrected to code 1
A84: 59 | B84: 121 | C84: 12-hour OP | D84: EMEB or MIDE only
A85: 60 | B85: 122 | C85: 12-hour OP | D85: O
A86: 62 | B86: 1119 | C86: 8-hour OP (see also SSC 427) | D86: 2 or Unsupported (SWEB)
A87: 63 | B87: 172 | C87: 9-hour OP | D87: EMEB or MIDE only
A88: 64 | B88: 1105 | C88: 12-hour OP | D88: O
A89: 65 | B89: 10 | C89: 12-hour OP + Summer | D89: O
A90: 66 | B90: 1106 | C90: 12-hour OP + Summer | D90: O
A91: 67 | B91: 102 | C91: 12.5-hour OP | D91: Unsupported (SWEB)
A92: 71 | B92: 109 | C92: 12.5-hour OP | D92: O
A93: 72 | B93: 111 | C93: 12.5-hour OP | D93: O
A94: 73 | B94: 156 | C94: 12.5-hour OP | D94: Unsupported (SWEB)
A95: 74 | B95: 17 | C95: 12.5-hour OP + Summer | D95: O
... A99: 78 | B99: 13 | C99: 12.5-hour OP + w/e & Summer | D99: O
A100: 79 | B100: 97 | C100: 14-hour E7 | D100: 2
A101: 79 | B101: 164 | C101: 14-hour E7 | D101: 1
A102: 80 | B102: 96 | C102: 14-hour Off Peak | D102: O
A103: 81 | B103: 60 | C103: 14-hour OP + Sun | D103: O
A104: 82 | B104: 83 | C104: 14.5-hour OP | D104: O
A105: 83 | B105: 84 | C105: 14.5-hour OP | D105: O
A106: 84 | B106: 85 | C106: 14.5-hour OP | D106: O
A107: 85 | B107: 86 | C107: 14.5-hour OP | D107: O
A108: 86 | B108: 1107 | C108: 14.5-hour OP | D108: O
A109: 87 | B109: 1109 | C109: 14.5-hour OP | D109: O
A110: 88 | B110: 1113 | C110: 14.5-hour OP | D110: O
A111: 91 | B111: 3 | C111: 14.5-hour OP + Summer | D111: O
A112: 92 | B112: 4 | C112: 14.5-hour OP + Summer | D112: O
A113: 93 | B113: 30 | C113: split 7-hour E7 | D113: 1
A114: 93 | B114: 214 | C114: split 7-hour E7 | D114: 2
A115: 94 | B115: 1108 | C115: 14.5-hour OP + Summer | D115: O
A116: 95 | B116: 1110 | C116: 14.5-hour OP + Summer | D116: O
A117: 96 | B117: 1114 | C117: 14.5-hour OP + Summer | D117: O
A118: 97 | B118: 54 | C118: 14.5-hour OP + w/e | D118: O
A119: 98 | B119: 12 | C119: 14.5-hour OP + w/e & Summer | D119: O
A120: 99 | B120: 75 | C120: 15-hour OP | D120: EMEB or MIDE only
A121: 100 | B121: 76 | C121: 15-hour OP | D121: EMEB or MIDE only
A122: 101 | B122: 7 | C122: 15-hour OP + w/e & Summer | D122: O
A123: 102 | B123: 8 | C123: 15-hour OP + w/e & Summer | D123: O
A124: 103 | B124: 9 | C124: 15-hour OP + w/e & Summer | D124: O
A125: 104 | B125: 61 | C125: 15.5-hour OP | D125: Unsupported (SWEB)
A126: 105 | B126: 65 | C126: 15.5-hour OP | D126: O
... A140: 120 | B140: 11 | C140: 9-hour OP | D140: O
A141: 121 | B141: 26 | C141: 2-rate terms | D141: 2
A142: 121 | B142: 224 | C142: 2-rate terms | D142: 1
A143: 122 | B143: 201 | C143: 2-rate SToD | D143: 1
A144: 122 | B144: 245 | C144: 2-rate SToD | D144: 2
A145: 123 | B145: 1307 | C145: 2-rate variable SToD | D145: 1
A146: 124 | B146: 1319 | C146: 2-rate variable SToD | D146: 1
A147: 125 | B147: 1315 | C147: 2-rate variable SToD | D147: 1
A148: 126 | B148: 1193 | C148: 7-hour E7 | D148: 1
A149: 126 | B149: 1194 | C149: 7-hour E7 | D149: 2
A150: 127 | B150: 80 | C150: 3-rate SToD | D150: Unsupported (SWEB)
A151: 127 | B151: 148 | C151: 3-rate SToD | D151: 1
A152: 127 | B152: 221 | C152: 3-rate SToD | D152: 2 or Unsupported (SWEB)
A153: 128 | B153: 1120 | C153: Dom/Non-dom Seasonal (link SSC 0342) | D153: 1
A154: 128 | B154: 1121 | C154: Dom/Non-dom Seasonal (link SSC 0342) | D154: 1
A155: 128 | B155: 1122 | C155: Dom/Non-dom Seasonal (link SSC 0342) | D155: 2
A156: 129 | B156: 169 | C156: 3-rate SToD | D156: 1
A157: 129 | B157: 202 | C157: 3-rate SToD | D157: 1
A158: 129 | B158: 222 | C158: 3-rate SToD | D158: 2
A159: 130 | B159: 1308 | C159: 3-rate variable | D159: 1
A160: 130 | B160: 1309 | C160: 3-rate variable | D160: 1
A161: 130 | B161: 1310 | C161: 3-rate variable | D161: 2
A162: 131 | B162: 1311 | C162: 3-rate variable | D162: 1
A163: 131 | B163: 1312 | C163: 3-rate variable | D163: 1
A164: 131 | B164: 1313 | C164: 3-rate variable | D164: 2
A165: 132 | B165: 92 | C165: 4-rate SToD | D165: EMEB or MIDE only
A166: 132 | B166: 210 | C166: 4-rate SToD | D166: 2
A167: 132 | B167: 234 | C167: 4-rate SToD | D167: EMEB or MIDE only
A168: 132 | B168: 236 | C168: 4-rate SToD | D168: EMEB or MIDE only
A169: 133 | B169: 92 | C169: 4-rate SToD | D169: 1
A170: 133 | B170: 210 | C170: 4-rate SToD | D170: 2
A171: 133 | B171: 233 | C171: 4-rate SToD | D171: 1
A172: 133 | B172: 246 | C172: 4-rate SToD | D172: 1
A173: 134 | B173: 101 | C173: 4-rate SToD | D173: 1
A174: 134 | B174: 210 | C174: 4-rate SToD | D174: 2
...

Sheet Charge Calculator
B1: Back to Overview
B2: =Overview!B4& " - Effective from "&Overview!D4&" - "&Overview!E4 -> Eastern Power Networks - Effective from 1 April 2020 - Final
B4: LV and HV tariff calculator | L4: EHV site calculator
B5: Step 1, Choose your tariff using the drop down list in cell B10 | L5: Step 1, Choose your tariff using the drop down list in cell L10
B6: Step 2, After selecting a tariff in step 1, Cells C12-I12 will generate headings, please enter your consumption in cells C13:I13 underneath each heading generated (if no heading leave cell blank) | L6: Step 2, After selecting a tariff in step 1, Cells M12-T12 will generate headings, please enter your consumption in cells M13:T13 underneath each heading generated (if no heading leave cell blank)
B7: Step 3, Enter a forecast of consumption if required in cells C14:I14 | L7: Step 3, Enter a forecast of consumption if required in cells M14:T14
B9: Tariff details Choose tariff name from drop down box below | C9: ='Annex 1 LV and HV charges'!D11 -> Unit charge 1 (NHH) or red/black charge (HH) p/kWh | D9: ='Annex 1 LV and HV charges'!E11 -> Unit charge 2 (NHH) or amber/yellow charge (HH) p/kWh | E9: ='Annex 1 LV and HV charges'!F11 -> Green charge(HH) p/kWh | F9: ='Annex 1 LV and HV charges'!G11 -> Fixed charge p/MPAN/day | G9: ='Annex 1 LV and HV charges'!H11 -> Capacity charge p/kVA/day | H9: ='Annex 1 LV and HV charges'!I11 -> Exceeded capacity charge p/kVA/day | I9: ='Annex 1 LV and HV charges'!J11 -> Reactive power charge p/kVArh | L9: Site details Choose the site name from the drop down box below | M9: ='Annex 2 EHV charges'!H9 -> Import Super Red unit charge (p/kWh) | N9: ='Annex 2 EHV charges'!I9 -> Import fixed charge (p/day) | O9: ='Annex 2 EHV charges'!J9 -> Import capacity charge (p/kVA/day) | P9: ='Annex 2 EHV charges'!K9 -> Import exceeded capacity charge (p/kVA/day) | Q9: ='Annex 2 EHV charges'!L9 -> Export Super Red unit charge (p/kWh) | R9: ='Annex 2 EHV charges'!M9 -> Export fixed charge (p/day) | S9: ='Annex 2 EHV charges'!N9 -> Export capacity charge (p/kVA/day) | T9: ='Annex 2 EHV charges'!O9 -> Export exceeded capacity charge (p/kVA/day)
C10: =IFERROR(VLOOKUP($B$10,'Annex 1 LV and HV charges'!$A:$K,4,FALSE),"") | D10: =IFERROR(VLOOKUP($B$10,'Annex 1 LV and HV charges'!$A:$K,5,FALSE),"") | E10: =IFERROR(VLOOKUP($B$10,'Annex 1 LV and HV charges'!$A:$K,6,FALSE),"") | F10: =IFERROR(VLOOKUP($B$10,'Annex 1 LV and HV charges'!$A:$K,7,FALSE),"") | G10: =IFERROR(VLOOKUP($B$10,'Annex 1 LV and HV charges'!$A:$K,8,FALSE),"") | H10: =IFERROR(VLOOKUP($B$10,'Annex 1 LV and HV charges'!$A:$K,9,FALSE),"") | I10: =IFERROR(VLOOKUP($B$10,'Annex 1 LV and HV charges'!$A:$K,10,FALSE),"") | M10: =IFERROR(VLOOKUP($L$10,'Annex 2 EHV charges'!$G:$O,2,FALSE),"") | N10: =IFERROR(VLOOKUP($L$10,'Annex 2 EHV charges'!$G:$O,3,FALSE),"") | O10: =IFERROR(VLOOKUP($L$10,'Annex 2 EHV charges'!$G:$O,4,FALSE),"") | P10: =IFERROR(VLOOKUP($L$10,'Annex 2 EHV charges'!$G:$O,5,FALSE),"") | Q10: =IFERROR(VLOOKUP($L$10,'Annex 2 EHV charges'!$G:$O,6,FALSE),"") | R10: =IFERROR(VLOOKUP($L$10,'Annex 2 EHV charges'!$G:$O,7,FALSE),"") | S10: =IFERROR(VLOOKUP($L$10,'Annex 2 EHV charges'!$G:$O,8,FALSE),"") | T10: =IFERROR(VLOOKUP($L$10,'Annex 2 EHV charges'!$G:$O,9,FALSE),"")
B12: Tariff components | C12: Unit 1 kWh (red/black/day) | D12: Unit 2 kWh (amber/yellow /night) | E12: Unit 3 kWh (green) | F12: Number of days in consumption period i.e. 365 if one year | G12: Maximum import or export capacity kVA | H12: Average daily exceeded capacity kVA | I12: Excess reactive units kVArh | L12: Tariff components | M12: Import super red kWh | N12: Number of days in consumption period i.e. 365 if one year | O12: Maximum import capacity kVA | P12: Average daily exceeded capacity kVA | Q12: Export Super Red kWh | R12: Number of days in consumption period i.e. 365 if one year | S12: Maximum export capacity kVA | T12: Average daily exceeded capacity kVA
B13: Enter current consumption details | L13: Enter current consumption details | R13: =N13 -> 0
B14: Enter forecast consumption details (if different) | C14: =C13 -> 0 | D14: =D13 -> 0 | E14: =E13 -> 0 | F14: =F13 -> 0 | G14: =G13 -> 0 | H14: =H13 -> 0 | I14: =I13 -> 0 | L14: Enter forecast consumption details (if different) | M14: =M13 -> 0 | N14: =N13 -> 0 | O14: =O13 -> 0 | P14: =P13 -> 0 | Q14: =Q13 -> 0 | R14: =R13 -> 0 | S14: =S13 -> 0 | T14: =T13 -> 0
B16: Charge components | C16: Unit 1 £ | D16: Unit 2 £ | E16: Unit 3 £ | F16: Fixed charge £ | G16: Capacity charge £ | H16: Exceeded capacity charge £ | I16: Reactive power charge £ | L16: Charge components | M16: Import super red charge £ | N16: Import fixed charge £ | O16: Import capacity charge £ | P16: Import exceeded capacity charge £ | Q16: Export super red charge £ | R16: Export fixed charge £ | S16: Export capacity charge £ | T16: Export exceeded capacity charge £
B17: Current consumption period charges | C17: =IFERROR(C10*C13/100,"") | D17: =IFERROR(D10*D13/100,"") | E17: =IFERROR(E10*E13/100,"") | F17: =IFERROR(F10*F13/100,"") | G17: =IFERROR(G10*G13*F13/100,"") | H17: =IFERROR(H10*H13*F13/100,"") | I17: =IFERROR(I10*I13/100,"") | L17: Current consumption period charges | M17: =IFERROR(M10*M13/100,"") | N17: =IFERROR(N10*N13/100,"") | O17: =IFERROR(O10*O13*N13/100,"") | P17: =IFERROR(P10*P13*N13/100,"") | Q17: =IFERROR(Q10*Q13/100,"") | R17: =IFERROR(R10*R13/100,"") | S17: =IFERROR(S10*S13*R13/100,"") | T17: =IFERROR(T10*T13*R13/100,"")
B18: Forecast consumption period charges | C18: =IFERROR(C10*C14/100,"") | D18: =IFERROR(D10*D14/100,"") | E18: =IFERROR(E10*E14/100,"") | F18: =IFERROR(F10*F14/100,"") | G18: =IFERROR(G10*G14*F14/100,"") | H18: =IFERROR(H10*H14*F14/100,"") | I18: =IFERROR(I10*I14/100,"") | L18: Forecast consumption period charges | M18: =IFERROR(M10*M14/100,"") | N18: =IFERROR(N10*N14/100,"") | O18: =IFERROR(O10*O14*N14/100,"") | P18: =IFERROR(P10*P14*N14/100,"") | Q18: =IFERROR(Q10*Q14/100,"") | R18: =IFERROR(R10*R14/100,"") | S18: =IFERROR(S10*S14*R14/100,"") | T18: =IFERROR(T10*T14*R14/100,"")
C20: Total charge £ | M20: Import total charge £ | N20: Export total charge £
B21: Current consumption period charges | C21: =SUM(C17:I17) -> 0 | L21: Current consumption period charges | M21: =SUM(M17:P17) -> 0 | N21: =SUM(Q17:T17) -> 0
B22: Forecast consumption period charges | C22: =SUM(C18:I18) -> 0 | L22: Forecast consumption period charges | M22: =SUM(M18:P18) -> 0 | N22: =SUM(Q18:T18) -> 0
B24: These charges are estimates based on tariff selected and consumption values entered. | L24: These charges are estimates based on site selected and consumption values entered.
