Workbook
Name OLE_LINK1: 'Annex 3 Preserved charges'!#REF!
Name YesNo: '[1]CSAD 2.1 Site Specific&EHV'!$AG$54:$AG$54

Sheet Overview
A2: Company and Licence name, charging year, effective from, status
B3: Company and Licence name | C3: Year | D3: Effective From | E3: Status
A4: Company and Licence name, charging year, effective from, status | B4: Southern Electric Power Distribution plc | C4: 2020/21 | D4: 1 April 2020 | E4: Final
A6: List of data tables in this workbook
A7: Worksheet | B7: Information
A8: Annex 1 LV and HV charges | B8: Annex 1 contains the charges to LV and HV Designated Properties.
A9: Annex 2 EHV charges | B9: ="Annex 2 contains the charges to Designated EHV Properties and charges applied to LDNOs with Designated EHV Properties/end-users embedded in networks within the " &B4 &" Licence area." -> Annex 2 contains the charges to Designated EHV Properties and charges applied to LDNOs with Designated EHV Properties/end-users embedded in networks within the Southern Electric Power Distribution plc Licence area.
A10: Annex 3 Preserved charges | B10: Annex 3 contains details of any preserved and additional charges that are valid at this time.
A11: Annex 4 LDNO charges | B11: ="Annex 4 contains charges that are levied on the owner of an embedded network within the "&B4&" Licence area. "&"Electricity suppliers and consumers who have properties connected to an embedded network should contact the embedded network owner to determine their distribution charges."&" The charges listed in this table are not payable by domestic consumers, business consumers or electricity suppliers." -> Annex 4 contains charges that are levied on the owner of an embedded network within the Southern Electric Power Distribution plc Licence area. Electricity suppliers and consumers who have properties connected to an embedded network should contact the embedded network owner to determine their distribution charges. The charges listed in this table are not payable by domestic consumers, business consumers or electricity suppliers.
A12: Annex 5 LLFs | B12: Annex 5 has been intentionally left blank as this Statement of Charges and Other Tables document is published a complete year before the LLFs have been audited. The line loss factors that are approved by the BSC Panel for the applicable year and consequently published on the Elexon website will take precedence and be used in Settlement. This annex will be re-published with these values once they are available.
A13: Annex 6 Charges for New or Amended Designated EHV Properties | B13: ="Annex 6 contains the charges for new or amended Designated EHV Properties and charges applied to LDNOs with new or amended Designated EHV Properties/end-users embedded in networks within the " &B4 &" Licence area." -> Annex 6 contains the charges for new or amended Designated EHV Properties and charges applied to LDNOs with new or amended Designated EHV Properties/end-users embedded in networks within the Southern Electric Power Distribution plc Licence area.
A14: Nodal prices | B14: Contains the underlying [nodal/network group] costs used to calculate the current EDCM charges.
A15: SSC TPR to unit rate lookup table | B15: The time periods for the non half hourly metered charge rates in Annex 1 are as specified by the SSC. To determine the appropriate charge rate for each SSC/TPR a lookup table is provided.
A16: Charge calculator | B16: Charge calculator is a tool to help you estimate your distribution charges using current consumption data and forecast consumption data.
A18: Notes to users of this spreadsheet
A20: Please use this spreadsheet with reference to the LC14 use of system charging statement.
A21: Annex 2 and Annex 6 - Import/Export unique identifier columns removed.
A23: Annex 4 -The LDNO HV Demand tariffs have been updated in compliance with Ofgem’s direction published 13-02-20. Details of the direction can be found at:
A24: https://www.ofgem.gov.uk/publications-and-updates/decision-grant-derogations-all-distribution-network-operators-distribution-use-system-charges-202021
A25: No other tariffs are affected by this change
A27: Version: 1.2 - 01/04/20
A29: Notes to DNOs populating this spreadsheet
A31: DNOs must endeavour to maintain consistency in the structure of this spreadsheet. Any changes to the structure must be noted in the 'Notes to users of this spreadsheet'
A32: The drop down list on the charge calculator can be expanded by unprotecting the charge calculator sheet and selecting 'data', 'data validation...' and then expanding the 'source' data range. The sheet can then be protected.

Sheet Annex 1 LV and HV charges
A1: Back to Overview | E1: Note: Where a tariff only has a p/kWh unit rate in Unit Charge 1 then this unit rate applies at all times.
A2: =Overview!B4& " - Effective from "&Overview!D4&" - "&Overview!E4&" LV and HV charges" -> Southern Electric Power Distribution plc - Effective from 1 April 2020 - Final LV and HV charges
A4: Time Bands for Half Hourly Metered Properties | G4: Time Bands for Half Hourly Unmetered Properties
A5: Time periods | B5: Red Time Band | C5: Amber Time Band | E5: Green Time Band | I5: Black Time Band | J5: Yellow Time Band | K5: Green Time Band
A6: Monday to Friday (Including Bank Holidays) All Year | B6: 16:30 - 19:30 | G6: Monday to Friday (Including Bank Holidays) March to October | J6: 07:00 - 22:00
A7: Monday to Friday (Including Bank Holidays) All Year | C7: 07:00 - 16:30 19:30 - 22:00 | G7: Monday to Friday (Including Bank Holidays) November to February | I7: 16:30 - 19:30 | J7: 07:00 - 16:30 19:30 - 22:00
A8: Monday to Friday (Including Bank Holidays) All Year | E8: 00:00 - 07:00 22:00 - 24:00 | G8: Monday to Friday (Including Bank Holidays) April to March | K8: 00:00 - 07:00 22:00 - 24:00
A9: Saturday and Sunday All Year | C9: 09:30 - 21:30 | E9: 00:00 - 09:30 21:30 - 24:00 | G9: Saturday and Sunday All Year | J9: 09:30 - 21:30 | K9: 00:00 - 09:30 21:30 - 24:00
A10: Notes | B10: All the above times are in UK Clock time | G10: Notes | I10: All the above times are in UK Clock time
A13: Tariff name | B13: Open LLFCs | C13: PCs | D13: Unit charge 1 (NHH) or red/black charge (HH) p/kWh | E13: Unit charge 2 (NHH) or amber/yellow charge (HH) p/kWh | F13: Green charge(HH) p/kWh | G13: Fixed charge p/MPAN/day | H13: Capacity charge p/kVA/day | I13: Exceeded capacity charge p/kVA/day | J13: Reactive power charge p/kVArh | K13: Closed LLFCs
A14: Domestic Unrestricted | B14: 100-103, 108-111, 154-155, 160 | C14: 1 | D14: 1.934 | G14: 3.51
A15: Domestic Two Rate | B15: 104-107, 156-157, 161 | C15: 2 | D15: 2.387 | E15: 0.441 | G15: 3.51 | K15: 124-125
A16: Domestic Off Peak (related MPAN) | B16: 115, 121, 150-153 | C16: 2 | D16: 0.537 | K16: 112-114, 116-120, 122-123
A17: Small Non Domestic Unrestricted | B17: 126-128, 133-134, 162, 473 | C17: 3 | D17: 1.777 | G17: 5.25
A18: Small Non Domestic Two Rate | B18: 129-131, 135-136, 163, 474 | C18: 4 | D18: 2.59 | E18: 0.591 | G18: 5.25
A19: Small Non Domestic Off Peak (related MPAN) | B19: 140, 144 | C19: 4 | D19: 0.665 | K19: 138-139, 141-143, 145
A20: LV Medium Non-Domestic | B20: 164, 400-401, 475, 479 | C20: 5-8 | D20: 1.484 | E20: 0.43 | G20: 28.97
A21: LV Sub Medium Non-Domestic | B21: 405 | C21: 5-8 | D21: 1.276 | E21: 0.409 | G21: 25.78
A22: HV Medium Non-Domestic | C22: 5-8 | D22: 0.862 | E22: 0.368 | G22: 288.71 | K22: 605-606
A23: LV Network Domestic | B23: 165, 456 | C23: 0 | D23: 8.7 | E23: 1.199 | F23: 0.386 | G23: 3.51
A24: LV Network Non-Domestic Non-CT | B24: 166, 457 | C24: 0 | D24: 9.165 | E24: 1.247 | F24: 0.389 | G24: 5.25
A25: LV HH Metered | B25: 453, 470 | C25: 0 | D25: 6.27 | E25: 0.866 | F25: 0.365 | G25: 16.49 | H25: 2.42 | I25: 4.58 | J25: 0.204
A26: LV Sub HH Metered | B26: 455, H99 | C26: 0 | D26: 4.864 | E26: 0.605 | F26: 0.347 | G26: 25.78 | H26: 4.28 | I26: 5.77 | J26: 0.129
A27: HV HH Metered | B27: 476, 658 | C27: 0 | D27: 3.544 | E27: 0.498 | F27: 0.342 | G27: 147.36 | H27: 5.28 | I27: 6.55 | J27: 0.086
A28: NHH UMS category A | B28: 500, 586 | C28: 8 | D28: 2.601
A29: NHH UMS category B | B29: 501, 587 | C29: 1 | D29: 2.657
A30: NHH UMS category C | B30: 502, 588 | C30: 1 | D30: 3.401
A31: NHH UMS category D | B31: 503, 589 | C31: 1 | D31: 2.611
A32: LV UMS (Pseudo HH Metered) | B32: 520 | C32: 0 | D32: 13.724 | E32: 2.576 | F32: 1.839
A33: LV Generation NHH or Aggregate HH | B33: 931, 993 | C33: 8&0 | D33: -0.794 | G33: 0
A34: LV Sub Generation NHH | B34: 932 | C34: 8 | D34: -0.695 | G34: 0
A35: LV Generation Intermittent | B35: 1, 477, 909 | C35: 0 | D35: -0.794 | G35: 0 | J35: 0.186
A36: LV Generation Intermittent no RP charge | B36: 7, 79 | C36: 0 | D36: -0.794 | G36: 0
A37: LV Generation Non-Intermittent | B37: 2 | C37: 0 | D37: -5.536 | E37: -0.571 | F37: -0.033 | G37: 0 | J37: 0.186
A38: LV Generation Non-Intermittent no RP charge | B38: 8, 80 | C38: 0 | D38: -5.536 | E38: -0.571 | F38: -0.033 | G38: 0
A39: LV Sub Generation Intermittent | B39: 3 | C39: 0 | D39: -0.695 | G39: 0 | J39: 0.166
A40: LV Sub Generation Intermittent no RP charge | B40: 146, 210 | C40: 0 | D40: -0.695 | G40: 0
A41: LV Sub Generation Non-Intermittent | B41: 4 | C41: 0 | D41: -4.994 | E41: -0.475 | F41: -0.026 | G41: 0 | J41: 0.166
A42: LV Sub Generation Non-Intermittent no RP charge | B42: 147, 211 | C42: 0 | D42: -4.994 | E42: -0.475 | F42: -0.026 | G42: 0
A43: HV Generation Intermittent | B43: 5, H98 | C43: 0 | D43: -0.46 | G43: 242.78 | J43: 0.147
A44: HV Generation Intermittent no RP charge | B44: 148, 212 | C44: 0 | D44: -0.46 | G44: 242.78
A45: HV Generation Non-Intermittent | B45: 6, 478, 910 | C45: 0 | D45: -3.838 | E45: -0.227 | F45: -0.008 | G45: 242.78 | J45: 0.147
A46: HV Generation Non-Intermittent no RP charge | B46: 149, 213 | C46: 0 | D46: -3.838 | E46: -0.227 | F46: -0.008 | G46: 242.78

Sheet Annex 2 EHV charges
A1: Back to Overview | E1: Note: The list of MPANs / MSIDs provided may be incomplete; the DNO reserves the right to apply the listed charges to any other MPANs / MSIDs associated with the site.
A2: =Overview!B4& " - Effective from "&Overview!D4&" - "&Overview!E4&" EDCM charges" -> Southern Electric Power Distribution plc - Effective from 1 April 2020 - Final EDCM charges
A4: Time Periods for Designated EHV Properties
A5: Time periods | D5: Super Red Time Band
A6: Monday to Friday (Including Bank Holidays) November to February Inclusive | D6: 16:30 - 19:30
A7: Notes | D7: All the above times are in UK Clock time
A9: Import LLFC | B9: Import MPANs/MSIDs | C9: Export LLFC | D9: Export MPANs/MSIDs | E9: Tariff | F9: Import Super Red unit charge (p/kWh) | G9: Import fixed charge (p/day) | H9: Import capacity charge (p/kVA/day) | I9: Import exceeded capacity charge (p/kVA/day) | J9: Export Super Red unit charge (p/kWh) | K9: Export fixed charge (p/day) | L9: Export capacity charge (p/kVA/day) | M9: Export exceeded capacity charge (p/kVA/day)
A10: 700 | B10: 2000027373741 | E10: Tariff 001 | F10: 0 | G10: 13766.71 | H10: 1.74 | I10: 1.74 | J10: 0 | K10: 0 | L10: 0 | M10: 0
A11: 701 | B11: 2000027366674 | E11: Tariff 002 | F11: 2.459 | G11: 8394.49 | H11: 2.24 | I11: 2.24 | J11: 0 | K11: 0 | L11: 0 | M11: 0
A12: 702 | B12: 2000027342238 | E12: Tariff 003 | F12: 0.406 | G12: 5159.36 | H12: 1.78 | I12: 1.78 | J12: 0 | K12: 0 | L12: 0 | M12: 0
A13: 704 | B13: 2000027343640 | C13: 734 | D13: 2000050928900 | E13: Tariff 004 | F13: 1.209 | G13: 1.97 | H13: 1.57 | I13: 1.57 | J13: 0 | K13: 269.86 | L13: 0.05 | M13: 0.05
A14: 706 | B14: 2000027419271 | C14: 736 | D14: 2000050932127 | E14: Tariff 005 | F14: 1.014 | G14: 9.4 | H14: 1.44 | I14: 1.44 | J14: 0 | K14: 432.39 | L14: 0.05 | M14: 0.05
A15: 707 | B15: 2000027427398 | C15: 737 | D15: 2000050935800 | E15: Tariff 006 | F15: 0.149 | G15: 52.68 | H15: 2.64 | I15: 2.64 | J15: 0 | K15: 0 | L15: 0 | M15: 0
A16: 708 | B16: 2000052675995 | E16: Tariff 007 | F16: 6.692 | G16: 6470.94 | H16: 1.72 | I16: 1.72 | J16: 0 | K16: 0 | L16: 0 | M16: 0
A17: 709 | B17: 2000054624149 | E17: Tariff 008 | F17: 1.024 | G17: 490.92 | H17: 3.18 | I17: 3.18 | J17: 0 | K17: 0 | L17: 0 | M17: 0
A18: 710 | B18: 2000027387210, 2000054817604, 2000055899218 | C18: 740 | D18: 2000055899236, 2000055899245 | E18: Tariff 009 | F18: 0 | G18: 9674.43 | H18: 2.01 | I18: 2.01 | J18: 0 | K18: 4299.75 | L18: 0.05 | M18: 0.05
A19: 711 | B19: 2000027852497 | E19: Tariff 010 | F19: 0 | G19: 7188.49 | H19: 3.06 | I19: 3.06 | J19: 0 | K19: 0 | L19: 0 | M19: 0
A20: 712 | B20: 2000055085297 | E20: Tariff 011 | F20: 1.055 | G20: 3899.52 | H20: 1.87 | I20: 1.87 | J20: 0 | K20: 0 | L20: 0 | M20: 0
A21: 713 | B21: 2000055085302 | E21: Tariff 012 | F21: 1.03 | G21: 9804.94 | H21: 1.29 | I21: 1.29 | J21: 0 | K21: 0 | L21: 0 | M21: 0
A22: 714 | B22: 2000027366665 | E22: Tariff 013 | F22: 1.285 | G22: 572.74 | H22: 2.56 | I22: 2.56 | J22: 0 | K22: 0 | L22: 0 | M22: 0
A23: 715 | B23: 2000051063430 | E23: Tariff 014 | F23: 2.437 | G23: 175.93 | H23: 2.65 | I23: 2.65 | J23: 0 | K23: 0 | L23: 0 | M23: 0
A24: 716 | B24: 2000027366762 | E24: Tariff 015 | F24: 0 | G24: 81.82 | H24: 5.03 | I24: 5.03 | J24: 0 | K24: 0 | L24: 0 | M24: 0
A25: 717 | B25: 2000027373403 | E25: Tariff 016 | F25: 1.783 | G25: 81.82 | H25: 3.73 | I25: 3.73 | J25: 0 | K25: 0 | L25: 0 | M25: 0
A26: 718 | B26: 2000050571060 | C26: 738 | D26: 2000051080338 | E26: Tariff 017 | F26: 1.067 | G26: 575.45 | H26: 1.28 | I26: 1.28 | J26: 0 | K26: 0 | L26: 0 | M26: 0
A27: 719 | B27: 2000027419449 | E27: Tariff 018 | F27: 1.038 | G27: 81.82 | H27: 2.52 | I27: 2.52 | J27: 0 | K27: 0 | L27: 0 | M27: 0
A28: 800 | B28: 2000050277851 | E28: Tariff 019 | F28: 0 | G28: 697.42 | H28: 1.44 | I28: 1.44 | J28: 0 | K28: 0 | L28: 0 | M28: 0
A29: 801 | B29: 2000050393707 | E29: Tariff 020 | F29: 0 | G29: 697.42 | H29: 1.56 | I29: 1.56 | J29: 0 | K29: 0 | L29: 0 | M29: 0
A30: 802 | B30: 2000027366841 | E30: Tariff 021 | F30: 0.788 | G30: 201.99 | H30: 3.35 | I30: 3.35 | J30: 0 | K30: 0 | L30: 0 | M30: 0
A31: 803 | B31: 2000050277513 | E31: Tariff 022 | F31: 0 | G31: 857.37 | H31: 2.43 | I31: 2.43 | J31: 0 | K31: 0 | L31: 0 | M31: 0
A32: 817 | B32: 2000050481327 | E32: Tariff 023 | F32: 0 | G32: 643.03 | H32: 2.4 | I32: 2.4 | J32: 0 | K32: 0 | L32: 0 | M32: 0
A33: 837 | B33: 2000050481309 | E33: Tariff 024 | F33: 0 | G33: 643.03 | H33: 3.94 | I33: 3.94 | J33: 0 | K33: 0 | L33: 0 | M33: 0
A34: 804 | B34: 2000050275631, 2000056717878, 2000056717887 | E34: Tariff 025 | F34: 1.195 | G34: 1046.13 | H34: 1.23 | I34: 1.23 | J34: 0 | K34: 0 | L34: 0 | M34: 0
A35: 805 | B35: 2000027474820 | E35: Tariff 026 | F35: 0 | G35: 213.67 | H35: 1.97 | I35: 1.97 | J35: 0 | K35: 0 | L35: 0 | M35: 0
A36: 806 | B36: 2000027454188 | E36: Tariff 027 | F36: 4.154 | G36: 697.42 | H36: 1.48 | I36: 1.48 | J36: 0 | K36: 0 | L36: 0 | M36: 0
A37: 807 | B37: 2000027454452 | E37: Tariff 028 | F37: 6.119 | G37: 348.71 | H37: 2.48 | I37: 2.48 | J37: 0 | K37: 0 | L37: 0 | M37: 0
A38: 808 | B38: 2000052503790 | E38: Tariff 029 | F38: 0.762 | G38: 697.42 | H38: 1.55 | I38: 1.55 | J38: 0 | K38: 0 | L38: 0 | M38: 0
A39: 809 | B39: 2000027297816 | E39: Tariff 030 | F39: 0 | G39: 398.35 | H39: 0.34 | I39: 0.34 | J39: 0 | K39: 0 | L39: 0 | M39: 0
A40: 810 | B40: 2000050467030 | C40: 918 | D40: 2000027292534 | E40: Tariff 031 | F40: 0 | G40: 810.41 | H40: 0.45 | I40: 0.45 | J40: 0 | K40: 0 | L40: 0 | M40: 0
A41: 811 | B41: 2000051063927 | E41: Tariff 032 | F41: 0 | G41: 412.74 | H41: 6 | I41: 6 | J41: 0 | K41: 0 | L41: 0 | M41: 0
A42: 812 | B42: 2000027339192 | E42: Tariff 033 | F42: 0.406 | G42: 1.82 | H42: 2.76 | I42: 2.76 | J42: 0 | K42: 0 | L42: 0 | M42: 0
A43: 812 | B43: 2000050544330 | E43: Tariff 034 | F43: 0.399 | G43: 1.82 | H43: 2.78 | I43: 2.78 | J43: 0 | K43: 0 | L43: 0 | M43: 0
A44: 813 | B44: 2000055209191, 2000055209207, 2000055209216, 2000055209225, 2000055209234, 2000055209252, 2000055209243 | E44: Tariff 035 | F44: 0 | G44: 5026.04 | H44: 3.72 | I44: 3.72 | J44: 0 | K44: 0 | L44: 0 | M44: 0
A45: 814 | B45: 2000027340036 | C45: 929 | D45: 2000054899591 | E45: Tariff 036 | F45: 0.404 | G45: 267.91 | H45: 0.69 | I45: 0.69 | J45: 0 | K45: 417.18 | L45: 0.05 | M45: 0.05
A46: 815 | B46: 2000027454648 | C46: 924 | D46: 2000054397290 | E46: Tariff 037 | F46: 0 | G46: 1731.23 | H46: 1.22 | I46: 1.22 | J46: 0 | K46: 946.85 | L46: 0.05 | M46: 0.05
A47: 816 | B47: 2000027306995 | C47: 937 | D47: 2000050795630 | E47: Tariff 038 | F47: 0 | G47: 436.34 | H47: 1.94 | I47: 1.94 | J47: 0 | K47: 545.43 | L47: 0.05 | M47: 0.05
A48: 818 | B48: 2000050277160 | E48: Tariff 039 | F48: 0 | G48: 42902.73 | H48: 9.85 | I48: 9.85 | J48: 0 | K48: 0 | L48: 0 | M48: 0
A49: 819 | B49: 2000027466068 | E49: Tariff 040 | F49: 0 | G49: 84.33 | H49: 2.18 | I49: 2.18 | J49: 0 | K49: 0 | L49: 0 | M49: 0
A50: 7174 | B50: 7174 | C50: 7174 | D50: 7174 | E50: Tariff 041 | F50: 0 | G50: 209.95 | H50: 0.71 | I50: 0.71 | J50: 0 | K50: 0 | L50: 0 | M50: 0
A51: N/A | B51: 2000027462090 | E51: Tariff 042 | F51: 0 | G51: 1055.87 | H51: 1.17 | I51: 1.17 | J51: 0 | K51: 0 | L51: 0 | M51: 0
A52: 823 | B52: 2000053759147 | C52: 923 | D52: 2000053759174 | E52: Tariff 043 | F52: 0 | G52: 150.07 | H52: 0.63 | I52: 0.63 | J52: 0 | K52: 1371.61 | L52: 0.05 | M52: 0.05
A53: 824 | B53: 2000027366498 | E53: Tariff 044 | F53: 1.301 | G53: 1969.92 | H53: 2.92 | I53: 2.92 | J53: 0 | K53: 0 | L53: 0 | M53: 0
A54: 825 | B54: 2000027323866 | E54: Tariff 045 | F54: 0 | G54: 16332.73 | H54: 3.06 | I54: 3.06 | J54: 0 | K54: 0 | L54: 0 | M54: 0
A55: 826 | B55: 2000027318634 | E55: Tariff 046 | F55: 0 | G55: 5860.11 | H55: 2.14 | I55: 2.14 | J55: 0 | K55: 0 | L55: 0 | M55: 0
A56: 827 | B56: 2000052503805 | E56: Tariff 047 | F56: 0.756 | G56: 697.42 | H56: 2.58 | I56: 2.58 | J56: 0 | K56: 0 | L56: 0 | M56: 0
A57: 897 | B57: 2000027877385 | E57: Tariff 048 | F57: 1.785 | G57: 5369.75 | H57: 2.75 | I57: 2.75 | J57: 0 | K57: 0 | L57: 0 | M57: 0
A58: 829 | B58: 2000050275552 | E58: Tariff 049 | F58: 0 | G58: 4007.74 | H58: 1.54 | I58: 1.54 | J58: 0 | K58: 0 | L58: 0 | M58: 0
A59: 820 | B59: 2000052993042 | E59: Tariff 050 | F59: 1.048 | G59: 196.35 | H59: 0.92 | I59: 0.92 | J59: 0 | K59: 0 | L59: 0 | M59: 0
A60: 830 | B60: 2000050277986 | E60: Tariff 051 | F60: 0 | G60: 21776.64 | H60: 0.73 | I60: 0.73 | J60: 0 | K60: 0 | L60: 0 | M60: 0
A61: 854 | B61: 2000052369584 | E61: Tariff 052 | F61: 0 | G61: 21341.5 | H61: 1.7 | I61: 1.7 | J61: 0 | K61: 0 | L61: 0 | M61: 0
A62: 835 | B62: 2000050275543 | E62: Tariff 053 | F62: 0 | G62: 2347.9 | H62: 1.25 | I62: 1.25 | J62: 0 | K62: 0 | L62: 0 | M62: 0
A63: 836 | B63: 2000051425787 | E63: Tariff 054 | F63: 0 | G63: 684.68 | H63: 4.05 | I63: 4.05 | J63: 0 | K63: 0 | L63: 0 | M63: 0
A64: 4033 | B64: 4033 | C64: 4032 | D64: 4032 | E64: Tariff 055 | F64: 0 | G64: 0.14 | H64: 1.69 | I64: 1.69 | J64: 0 | K64: 7.16 | L64: 0.05 | M64: 0.05
A65: 4548 | B65: 4548 | C65: 4548 | D65: 4548 | E65: Tariff 056 | F65: 0 | G65: 0.03 | H65: 1.09 | I65: 1.09 | J65: 0 | K65: 7.27 | L65: 0.05 | M65: 0.05
A66: 839 | B66: 2000053874062 | C66: 925 | D66: 2000053874080 | E66: Tariff 057 | F66: 0 | G66: 1.87 | H66: 2.53 | I66: 2.53 | J66: 0 | K66: 262.12 | L66: 0.05 | M66: 0.05
A67: 505 | B67: 2000053874105 | C67: 521 | D67: 2000053874123 | E67: Tariff 058 | F67: 0 | G67: 2.81 | H67: 2.35 | I67: 2.35 | J67: 0 | K67: 383.75 | L67: 0.05 | M67: 0.05
A68: 840 | B68: 2000051011929 | C68: 930 | D68: 2000051034322 | E68: Tariff 059 | F68: 0 | G68: 22.03 | H68: 0.69 | I68: 0.69 | J68: 0 | K68: 0 | L68: 0 | M68: 0
A69: 7393 | B69: 7393 | C69: 7390 | D69: 7390 | E69: Tariff 060 | F69: 1.116 | G69: 2.6 | H69: 1.25 | I69: 1.25 | J69: 0 | K69: 337.66 | L69: 0.05 | M69: 0.05
A70: 7394 | B70: 7394 | C70: 7391 | D70: 7391 | E70: Tariff 061 | F70: 0 | G70: 1.96 | H70: 1.35 | I70: 1.35 | J70: 0 | K70: 0 | L70: 0 | M70: 0
A71: 844 | B71: 2000027491213 | C71: 917 | D71: 2000050932697 | E71: Tariff 062 | F71: 0 | G71: 15.89 | H71: 0.68 | I71: 0.68 | J71: 0 | K71: 1112.08 | L71: 0.05 | M71: 0.05
A72: 844 | B72: 2000050044320 | C72: 917 | D72: 2000051079954 | E72: Tariff 063 | F72: 0 | G72: 7.39 | H72: 0.68 | I72: 0.68 | J72: 0 | K72: 0 | L72: 0 | M72: 0
A73: 844 | B73: 2000052468930 | C73: 917 | D73: 2000052231228 | E73: Tariff 064 | F73: 0 | G73: 1.91 | H73: 0.68 | I73: 0.68 | J73: 0 | K73: 0 | L73: 0 | M73: 0
A74: 845 | B74: 2000050437959 | E74: Tariff 065 | F74: 0 | G74: 3465.76 | H74: 4.79 | I74: 4.79 | J74: 0 | K74: 0 | L74: 0 | M74: 0
A75: 846 | B75: 2000050552457 | C75: 927 | D75: 2000050570312 | E75: Tariff 066 | F75: 1.428 | G75: 9.6 | H75: 0.69 | I75: 0.69 | J75: 0 | K75: 0 | L75: 0 | M75: 0
A76: 847 | B76: 2000050662007 | C76: 928 | D76: 2000050662016 | E76: Tariff 067 | F76: 0 | G76: 21 | H76: 0.78 | I76: 0.78 | J76: 0 | K76: 0 | L76: 0 | M76: 0
A77: 849 | B77: 2000052866920 | E77: Tariff 068 | F77: 0 | G77: 3957.04 | H77: 3.58 | I77: 3.58 | J77: 0 | K77: 0 | L77: 0 | M77: 0
A78: 851 | B78: 2000051336018 | E78: Tariff 069 | F78: 0 | G78: 843.25 | H78: 1.51 | I78: 1.51 | J78: 0 | K78: 0 | L78: 0 | M78: 0
A79: 853 | B79: 2000052659600 | C79: 938 | D79: 2000052659585 | E79: Tariff 070 | F79: 1.875 | G79: 246.92 | H79: 1.21 | I79: 1.21 | J79: 0 | K79: 0 | L79: 0 | M79: 0
A80: 855 | B80: 2000050276556 | E80: Tariff 071 | F80: 0.727 | G80: 348.71 | H80: 1.68 | I80: 1.68 | J80: 0 | K80: 0 | L80: 0 | M80: 0
A81: 856 | B81: 2000054315483 | E81: Tariff 072 | F81: 0 | G81: 348.71 | H81: 2.12 | I81: 2.12 | J81: 0 | K81: 0 | L81: 0 | M81: 0
A82: 857 | B82: 2000054359392 | E82: Tariff 073 | F82: 0 | G82: 201.99 | H82: 1.88 | I82: 1.88 | J82: 0 | K82: 0 | L82: 0 | M82: 0
A83: 858 | B83: 2000051445019 | C83: 921 | D83: 2000051445143 | E83: Tariff 074 | F83: 0.432 | G83: 4.02 | H83: 0.81 | I83: 0.81 | J83: 0 | K83: 334.7 | L83: 0.05 | M83: 0.05
A84: 859 | B84: 2000054431783 | C84: 922 | D84: 2000054431792 | E84: Tariff 075 | F84: 6.278 | G84: 9.89 | H84: 0.68 | I84: 0.68 | J84: 0 | K84: 197.74 | L84: 0.05 | M84: 0.05
A85: 860 | B85: 2000054674344 | C85: 939 | D85: 2000054674353 | E85: Tariff 076 | F85: 6.525 | G85: 183.47 | H85: 1.09 | I85: 1.09 | J85: 0 | K85: 2038.61 | L85: 0.05 | M85: 0.05
A86: 7303 | B86: 7303 | E86: Tariff 077 | F86: 0.621 | G86: 0 | H86: 6.04 | I86: 6.04 | J86: 0 | K86: 0 | L86: 0 | M86: 0
A87: 863 | B87: 2000055109274 | C87: 941 | D87: 2000055109283 | E87: Tariff 078 | F87: 0 | G87: 0.5 | H87: 4.44 | I87: 4.44 | J87: 0 | K87: 250.6 | L87: 0.05 | M87: 0.05
A88: 852 | B88: 2000055132440 | C88: 926 | D88: 2000055132450 | E88: Tariff 079 | F88: 0 | G88: 2.49 | H88: 1.12 | I88: 1.12 | J88: 0 | K88: 248.61 | L88: 0.05 | M88: 0.05
A89: 862 | B89: 2000055138985 | C89: 940 | D89: 2000055138762 | E89: Tariff 080 | F89: 0 | G89: 1 | H89: 1.46 | I89: 1.46 | J89: 0 | K89: 250.1 | L89: 0.05 | M89: 0.05
A90: 864 | B90: 2000055125815 | C90: 942 | D90: 2000055125824 | E90: Tariff 081 | F90: 0.402 | G90: 5.52 | H90: 1.22 | I90: 1.22 | J90: 0 | K90: 497.22 | L90: 0.05 | M90: 0.05
A91: 865 | B91: 2000055125842 | C91: 943 | D91: 2000055125833 | E91: Tariff 082 | F91: 0.406 | G91: 2.41 | H91: 3.27 | I91: 3.27 | J91: 0 | K91: 723.11 | L91: 0.05 | M91: 0.05
A92: 866 | B92: 2000055213940 | C92: 944 | D92: 2000055213969 | E92: Tariff 083 | F92: 0.406 | G92: 1.15 | H92: 3.55 | I92: 3.55 | J92: 0 | K92: 344.44 | L92: 0.05 | M92: 0.05
A93: 861 | B93: 2000055029502 | E93: Tariff 084 | F93: 0 | G93: 81.82 | H93: 1.37 | I93: 1.37 | J93: 0 | K93: 0 | L93: 0 | M93: 0
A94: 861 | B94: 2000055029511 | E94: Tariff 085 | F94: 0 | G94: 81.82 | H94: 1.36 | I94: 1.36 | J94: 0 | K94: 0 | L94: 0 | M94: 0
A95: 861 | B95: 2000055029520 | E95: Tariff 086 | F95: 0 | G95: 81.82 | H95: 0.88 | I95: 0.88 | J95: 0 | K95: 0 | L95: 0 | M95: 0
A96: 861 | B96: 2000055029530 | E96: Tariff 087 | F96: 0 | G96: 81.82 | H96: 0.88 | I96: 0.88 | J96: 0 | K96: 0 | L96: 0 | M96: 0
A97: 861 | B97: 2000055029549 | E97: Tariff 088 | F97: 0 | G97: 81.82 | H97: 0.88 | I97: 0.88 | J97: 0 | K97: 0 | L97: 0 | M97: 0
A98: 861 | B98: 2000055029558 | E98: Tariff 089 | F98: 0 | G98: 81.82 | H98: 0.88 | I98: 0.88 | J98: 0 | K98: 0 | L98: 0 | M98: 0
A99: 7096 | B99: 7096 | C99: 7081 | D99: 7081 | E99: Tariff 090 | F99: 0 | G99: 2433.39 | H99: 1.5 | I99: 1.5 | J99: 0 | K99: 0 | L99: 0 | M99: 0
C100: 7095 | D100: 7095 | E100: Tariff 091 | F100: 0 | G100: 0 | H100: 0 | I100: 0 | J100: 0 | K100: 4134.83 | L100: 0.05 | M100: 0.05
A101: 7098 | B101: 7098 | E101: Tariff 092 | F101: 0 | G101: 7.3 | H101: 1.36 | I101: 1.36 | J101: 0 | K101: 0 | L101: 0 | M101: 0
A102: 7097 | B102: 7097 | E102: Tariff 093 | F102: 0 | G102: 16614.75 | H102: 1.35 | I102: 1.35 | J102: 0 | K102: 0 | L102: 0 | M102: 0
...

Sheet Annex 2a Import
A1: Note: The list of MPANs / MSIDs provided may be incomplete; the DNO reserves the right to apply the listed charges to any other MPANs / MSIDs associated with the site.
A2: =Overview!B4& " - Effective from "&Overview!D4&" - "&Overview!E4&" EDCM import charges" -> Southern Electric Power Distribution plc - Effective from 1 April 2020 - Final EDCM import charges
A4: Import LLFC | B4: Import MPANs/MSIDs | C4: Tariff | D4: ='Annex 2 EHV charges'!F9 -> Import Super Red unit charge (p/kWh) | E4: ='Annex 2 EHV charges'!G9 -> Import fixed charge (p/day) | F4: ='Annex 2 EHV charges'!H9 -> Import capacity charge (p/kVA/day) | G4: ='Annex 2 EHV charges'!I9 -> Import exceeded capacity charge (p/kVA/day)
A5: 700 | B5: 2000027373741 | C5: Tariff 001 | D5: 0 | E5: 13766.71 | F5: 1.74 | G5: 1.74
A6: 701 | B6: 2000027366674 | C6: Tariff 002 | D6: 2.459 | E6: 8394.49 | F6: 2.24 | G6: 2.24
A7: 702 | B7: 2000027342238 | C7: Tariff 003 | D7: 0.406 | E7: 5159.36 | F7: 1.78 | G7: 1.78
A8: 704 | B8: 2000027343640 | C8: Tariff 004 | D8: 1.209 | E8: 1.97 | F8: 1.57 | G8: 1.57
A9: 706 | B9: 2000027419271 | C9: Tariff 005 | D9: 1.014 | E9: 9.4 | F9: 1.44 | G9: 1.44
A10: 707 | B10: 2000027427398 | C10: Tariff 006 | D10: 0.149 | E10: 52.68 | F10: 2.64 | G10: 2.64
A11: 708 | B11: 2000052675995 | C11: Tariff 007 | D11: 6.692 | E11: 6470.94 | F11: 1.72 | G11: 1.72
A12: 709 | B12: 2000054624149 | C12: Tariff 008 | D12: 1.024 | E12: 490.92 | F12: 3.18 | G12: 3.18
A13: 710 | B13: 2000027387210, 2000054817604, 2000055899218 | C13: Tariff 009 | D13: 0 | E13: 9674.43 | F13: 2.01 | G13: 2.01
A14: 711 | B14: 2000027852497 | C14: Tariff 010 | D14: 0 | E14: 7188.49 | F14: 3.06 | G14: 3.06
A15: 712 | B15: 2000055085297 | C15: Tariff 011 | D15: 1.055 | E15: 3899.52 | F15: 1.87 | G15: 1.87
A16: 713 | B16: 2000055085302 | C16: Tariff 012 | D16: 1.03 | E16: 9804.94 | F16: 1.29 | G16: 1.29
A17: 714 | B17: 2000027366665 | C17: Tariff 013 | D17: 1.285 | E17: 572.74 | F17: 2.56 | G17: 2.56
A18: 715 | B18: 2000051063430 | C18: Tariff 014 | D18: 2.437 | E18: 175.93 | F18: 2.65 | G18: 2.65
A19: 716 | B19: 2000027366762 | C19: Tariff 015 | D19: 0 | E19: 81.82 | F19: 5.03 | G19: 5.03
A20: 717 | B20: 2000027373403 | C20: Tariff 016 | D20: 1.783 | E20: 81.82 | F20: 3.73 | G20: 3.73
A21: 718 | B21: 2000050571060 | C21: Tariff 017 | D21: 1.067 | E21: 575.45 | F21: 1.28 | G21: 1.28
A22: 719 | B22: 2000027419449 | C22: Tariff 018 | D22: 1.038 | E22: 81.82 | F22: 2.52 | G22: 2.52
A23: 800 | B23: 2000050277851 | C23: Tariff 019 | D23: 0 | E23: 697.42 | F23: 1.44 | G23: 1.44
A24: 801 | B24: 2000050393707 | C24: Tariff 020 | D24: 0 | E24: 697.42 | F24: 1.56 | G24: 1.56
A25: 802 | B25: 2000027366841 | C25: Tariff 021 | D25: 0.788 | E25: 201.99 | F25: 3.35 | G25: 3.35
... A28: 837 | B28: 2000050481309 | C28: Tariff 024 | D28: 0 | E28: 643.03 | F28: 3.94 | G28: 3.94
A29: 804 | B29: 2000050275631, 2000056717878, 2000056717887 | C29: Tariff 025 | D29: 1.195 | E29: 1046.13 | F29: 1.23 | G29: 1.23
A30: 805 | B30: 2000027474820 | C30: Tariff 026 | D30: 0 | E30: 213.67 | F30: 1.97 | G30: 1.97
A31: 806 | B31: 2000027454188 | C31: Tariff 027 | D31: 4.154 | E31: 697.42 | F31: 1.48 | G31: 1.48
A32: 807 | B32: 2000027454452 | C32: Tariff 028 | D32: 6.119 | E32: 348.71 | F32: 2.48 | G32: 2.48
A33: 808 | B33: 2000052503790 | C33: Tariff 029 | D33: 0.762 | E33: 697.42 | F33: 1.55 | G33: 1.55
A34: 809 | B34: 2000027297816 | C34: Tariff 030 | D34: 0 | E34: 398.35 | F34: 0.34 | G34: 0.34
A35: 810 | B35: 2000050467030 | C35: Tariff 031 | D35: 0 | E35: 810.41 | F35: 0.45 | G35: 0.45
A36: 811 | B36: 2000051063927 | C36: Tariff 032 | D36: 0 | E36: 412.74 | F36: 6 | G36: 6
A37: 812 | B37: 2000027339192 | C37: Tariff 033 | D37: 0.406 | E37: 1.82 | F37: 2.76 | G37: 2.76
A38: 812 | B38: 2000050544330 | C38: Tariff 034 | D38: 0.399 | E38: 1.82 | F38: 2.78 | G38: 2.78
A39: 813 | B39: 2000055209191, 2000055209207, 2000055209216, 2000055209225, 2000055209234, 2000055209252, 2000055209243 | C39: Tariff 035 | D39: 0 | E39: 5026.04 | F39: 3.72 | G39: 3.72
A40: 814 | B40: 2000027340036 | C40: Tariff 036 | D40: 0.404 | E40: 267.91 | F40: 0.69 | G40: 0.69
A41: 815 | B41: 2000027454648 | C41: Tariff 037 | D41: 0 | E41: 1731.23 | F41: 1.22 | G41: 1.22
A42: 816 | B42: 2000027306995 | C42: Tariff 038 | D42: 0 | E42: 436.34 | F42: 1.94 | G42: 1.94
A43: 818 | B43: 2000050277160 | C43: Tariff 039 | D43: 0 | E43: 42902.73 | F43: 9.85 | G43: 9.85
A44: 819 | B44: 2000027466068 | C44: Tariff 040 | D44: 0 | E44: 84.33 | F44: 2.18 | G44: 2.18
A45: 7174 | B45: 7174 | C45: Tariff 041 | D45: 0 | E45: 209.95 | F45: 0.71 | G45: 0.71
A46: N/A | B46: 2000027462090 | C46: Tariff 042 | D46: 0 | E46: 1055.87 | F46: 1.17 | G46: 1.17
A47: 823 | B47: 2000053759147 | C47: Tariff 043 | D47: 0 | E47: 150.07 | F47: 0.63 | G47: 0.63
A48: 824 | B48: 2000027366498 | C48: Tariff 044 | D48: 1.301 | E48: 1969.92 | F48: 2.92 | G48: 2.92
A49: 825 | B49: 2000027323866 | C49: Tariff 045 | D49: 0 | E49: 16332.73 | F49: 3.06 | G49: 3.06
A50: 826 | B50: 2000027318634 | C50: Tariff 046 | D50: 0 | E50: 5860.11 | F50: 2.14 | G50: 2.14
A51: 827 | B51: 2000052503805 | C51: Tariff 047 | D51: 0.756 | E51: 697.42 | F51: 2.58 | G51: 2.58
A52: 897 | B52: 2000027877385 | C52: Tariff 048 | D52: 1.785 | E52: 5369.75 | F52: 2.75 | G52: 2.75
A53: 829 | B53: 2000050275552 | C53: Tariff 049 | D53: 0 | E53: 4007.74 | F53: 1.54 | G53: 1.54
A54: 820 | B54: 2000052993042 | C54: Tariff 050 | D54: 1.048 | E54: 196.35 | F54: 0.92 | G54: 0.92
A55: 830 | B55: 2000050277986 | C55: Tariff 051 | D55: 0 | E55: 21776.64 | F55: 0.73 | G55: 0.73
A56: 854 | B56: 2000052369584 | C56: Tariff 052 | D56: 0 | E56: 21341.5 | F56: 1.7 | G56: 1.7
A57: 835 | B57: 2000050275543 | C57: Tariff 053 | D57: 0 | E57: 2347.9 | F57: 1.25 | G57: 1.25
A58: 836 | B58: 2000051425787 | C58: Tariff 054 | D58: 0 | E58: 684.68 | F58: 4.05 | G58: 4.05
... A120: 890 | B120: 2000056041556 | C120: Tariff 121 | D120: 6.274 | E120: 42.44 | F120: 0.95 | G120: 0.95
A121: 834 | B121: - | C121: Tariff 122 | D121: 0 | E121: 3669.42 | F121: 2.25 | G121: 2.25
A122: 891 | B122: 2000050363794, 2000056235458 | C122: Tariff 123 | D122: 0 | E122: 2112.42 | F122: 2.22 | G122: 2.22
A123: 892 | B123: 2000055582800 | C123: Tariff 124 | D123: 6.253 | E123: 1.47 | F123: 2.01 | G123: 2.01
A124: 893 | B124: 2000056442147 | C124: Tariff 125 | D124: 6.189 | E124: 2.73 | F124: 0.92 | G124: 0.92
A125: 894 | B125: 2000055894939 | C125: Tariff 126 | D125: 1.872 | E125: 1.36 | F125: 1.65 | G125: 1.65
A126: 895 | B126: 2000055630116 | C126: Tariff 127 | D126: 0 | E126: 3.92 | F126: 0.92 | G126: 0.92
A127: 896 | B127: 2000055845773 | C127: Tariff 128 | D127: 1.173 | E127: 2.12 | F127: 1.06 | G127: 1.06
A128: 720 | B128: 2000055856970 | C128: Tariff 129 | D128: 0 | E128: 5.64 | F128: 2.73 | G128: 2.73
A129: 848 | B129: 2000056875315 | C129: Tariff 131 | D129: 0.569 | E129: 94.47 | F129: 0.94 | G129: 0.94
A130: 722 | B130: 2000027480851 | C130: Tariff 132 | D130: 0 | E130: 95.19 | F130: 1.42 | G130: 1.42
A131: 724 | B131: 2000055874997 | C131: Tariff 134 | D131: 6.278 | E131: 22.56 | F131: 0.68 | G131: 0.68
A132: 725 | B132: 2000055996659 | C132: Tariff 135 | D132: 0 | E132: 5.38 | F132: 1.39 | G132: 1.39
A133: 726 | B133: 2000055627860 | C133: Tariff 136 | D133: 2.334 | E133: 4.3 | F133: 0.94 | G133: 0.94
A134: 727 | B134: 2000055899788 | C134: Tariff 137 | D134: 0.393 | E134: 12.71 | F134: 0.93 | G134: 0.93
... A136: 832 | B136: 2000055878690 | C136: Tariff 139 | D136: 0.405 | E136: 3.19 | F136: 2.55 | G136: 2.55
A137: Y00 | B137: 2000056762133 | C137: Tariff 140 | D137: 0.588 | E137: 9.86 | F137: 1.03 | G137: 1.03
A138: 850 | B138: 2000055901285 | C138: Tariff 143 | D138: 6.046 | E138: 9.01 | F138: 0.8 | G138: 0.8
A139: 661 | B139: 2000055901346 | C139: Tariff 144 | D139: 6.013 | E139: 5.66 | F139: 0.89 | G139: 0.89
A140: 662 | B140: 2000055899389 | C140: Tariff 146 | D140: 0.405 | E140: 6.79 | F140: 1.45 | G140: 1.45
A141: 452 | B141: 2000056479100 | C141: Tariff 147 | D141: 0.591 | E141: 20.73 | F141: 1.17 | G141: 1.17
A142: 663 | B142: 2000055858718 | C142: Tariff 148 | D142: 0.403 | E142: 3.36 | F142: 0.85 | G142: 0.85
A143: 897 | B143: 2000056951250 | C143: Tariff 149 | D143: 0 | E143: 714.33 | F143: 0.9 | G143: 0.9
A144: 458 | B144: 2000056277271 | C144: Tariff 151 | D144: 5.886 | E144: 10.66 | F144: 1.22 | G144: 1.22
A145: 596 | B145: 2000056113290 | C145: Tariff 152 | D145: 1.003 | E145: 3.65 | F145: 1.31 | G145: 1.31
A146: 597 | B146: 2000056188505 | C146: Tariff 153 | D146: 0 | E146: 4.01 | F146: 1.84 | G146: 1.84
A147: 665 | B147: 2000055924023 | C147: Tariff 154 | D147: 6.139 | E147: 17.47 | F147: 1.26 | G147: 1.26
A148: 598 | B148: 2000056127229 | C148: Tariff 155 | D148: 0.603 | E148: 5.94 | F148: 2.22 | G148: 2.22
A149: 459 | B149: 2000056455252 | C149: Tariff 156 | D149: 0.4 | E149: 5.34 | F149: 1 | G149: 1
... A175: 682 | B175: 2000056049305 | C175: Tariff 188 | D175: 6.135 | E175: 2.53 | F175: 0.97 | G175: 0.97
A176: Y01 | B176: 2000056827906 | C176: Tariff 189 | D176: 6.234 | E176: 13.66 | F176: 0.78 | G176: 0.78
A177: 683 | B177: 2000056169804 | C177: Tariff 190 | D177: 2.369 | E177: 3.45 | F177: 1.53 | G177: 1.53
A178: 684 | B178: 2000056179662 | C178: Tariff 191 | D178: 6.251 | E178: 11.3 | F178: 1.23 | G178: 1.23
A179: 685 | B179: 2000056107107 | C179: Tariff 192 | D179: 6.218 | E179: 2.72 | F179: 1.61 | G179: 1.61
A180: 686 | B180: 2000056113954 | C180: Tariff 194 | D180: 0.403 | E180: 3.34 | F180: 1.62 | G180: 1.62
A181: 687 | B181: 2000056138132 | C181: Tariff 196 | D181: 0.404 | E181: 1.22 | F181: 1.53 | G181: 1.53
A182: 688 | B182: 2000056167913 | C182: Tariff 198 | D182: 2.366 | E182: 0.52 | F182: 2.39 | G182: 2.39
A183: 525 | B183: 2000056537756 | C183: Tariff 199 | D183: 0.596 | E183: 16.46 | F183: 1.5 | G183: 1.5
A184: 689 | B184: 2000055874960 | C184: Tariff 201 | D184: 0 | E184: 1156.15 | F184: 0.78 | G184: 0.78
A185: 690 | B185: 2000056147225 | C185: Tariff 202 | D185: 0 | E185: 4.5 | F185: 1.16 | G185: 1.16
A186: 691 | B186: 2000055932200 | C186: Tariff 205 | D186: 0 | E186: 0.73 | F186: 4.37 | G186: 4.37
A187: 729 | B187: 2000055373760, 2000055373779, 2000055373788, 2000055373797, 2000055373802, 2000055373811, 2000055373820, 2000055373830, 2000056698230, 2000056698240, 2000056698259, 2000056698268, 2000056698277, 2000056698286, 2000056793498, 2000056793503 | C187: Tariff 206 | D187: 0.958 | E187: 8805.87 | F187: 1.45 | G187: 1.45
A188: 527 | B188: 2000056441375 | C188: Tariff 208 | D188: 0 | E188: 4 | F188: 1.39 | G188: 1.39
A189: 692 | B189: 2000056204956 | C189: Tariff 209 | D189: 0 | E189: 44.2 | F189: 2.12 | G189: 2.12
A190: 897 | B190: - | C190: Tariff 211 | D190: 0.401 | E190: 3.34 | F190: 1.11 | G190: 1.11
...

Sheet Annex 2b Export
A1: Note: The list of MPANs / MSIDs provided may be incomplete; the DNO reserves the right to apply the listed charges to any other MPANs / MSIDs associated with the site.
A2: =Overview!B4& " - Effective from "&Overview!D4&" - "&Overview!E4&" EDCM export charges" -> Southern Electric Power Distribution plc - Effective from 1 April 2020 - Final EDCM export charges
A4: Export LLFC | B4: Export MPANs/MSIDs | C4: Tariff | D4: ='Annex 2 EHV charges'!J9 -> Export Super Red unit charge (p/kWh) | E4: ='Annex 2 EHV charges'!K9 -> Export fixed charge (p/day) | F4: ='Annex 2 EHV charges'!L9 -> Export capacity charge (p/kVA/day) | G4: ='Annex 2 EHV charges'!M9 -> Export exceeded capacity charge (p/kVA/day)
A5: 734 | B5: 2000050928900 | C5: Tariff 004 | D5: 0 | E5: 269.86 | F5: 0.05 | G5: 0.05
A6: 736 | B6: 2000050932127 | C6: Tariff 005 | D6: 0 | E6: 432.39 | F6: 0.05 | G6: 0.05
A7: 737 | B7: 2000050935800 | C7: Tariff 006 | D7: 0 | E7: 0 | F7: 0 | G7: 0
A8: 740 | B8: 2000055899236, 2000055899245 | C8: Tariff 009 | D8: 0 | E8: 4299.75 | F8: 0.05 | G8: 0.05
A9: 738 | B9: 2000051080338 | C9: Tariff 017 | D9: 0 | E9: 0 | F9: 0 | G9: 0
A10: 918 | B10: 2000027292534 | C10: Tariff 031 | D10: 0 | E10: 0 | F10: 0 | G10: 0
A11: 929 | B11: 2000054899591 | C11: Tariff 036 | D11: 0 | E11: 417.18 | F11: 0.05 | G11: 0.05
A12: 924 | B12: 2000054397290 | C12: Tariff 037 | D12: 0 | E12: 946.85 | F12: 0.05 | G12: 0.05
A13: 937 | B13: 2000050795630 | C13: Tariff 038 | D13: 0 | E13: 545.43 | F13: 0.05 | G13: 0.05
A14: 7174 | B14: 7174 | C14: Tariff 041 | D14: 0 | E14: 0 | F14: 0 | G14: 0
A15: 923 | B15: 2000053759174 | C15: Tariff 043 | D15: 0 | E15: 1371.61 | F15: 0.05 | G15: 0.05
A16: 4032 | B16: 4032 | C16: Tariff 055 | D16: 0 | E16: 7.16 | F16: 0.05 | G16: 0.05
A17: 4548 | B17: 4548 | C17: Tariff 056 | D17: 0 | E17: 7.27 | F17: 0.05 | G17: 0.05
A18: 925 | B18: 2000053874080 | C18: Tariff 057 | D18: 0 | E18: 262.12 | F18: 0.05 | G18: 0.05
A19: 521 | B19: 2000053874123 | C19: Tariff 058 | D19: 0 | E19: 383.75 | F19: 0.05 | G19: 0.05
A20: 930 | B20: 2000051034322 | C20: Tariff 059 | D20: 0 | E20: 0 | F20: 0 | G20: 0
... A61: 629 | B61: 2000056041565 | C61: Tariff 121 | D61: 0 | E61: 2146.98 | F61: 0.05 | G61: 0.05
A62: 914 | B62: - | C62: Tariff 122 | D62: 0 | E62: 1013.38 | F62: 0.05 | G62: 0.05
A63: 630 | B63: 2000055582819 | C63: Tariff 124 | D63: 0 | E63: 366.75 | F63: 0.05 | G63: 0.05
A64: 631 | B64: 2000056442156 | C64: Tariff 125 | D64: 0 | E64: 168.49 | F64: 0.05 | G64: 0.05
A65: 632 | B65: 2000055894948 | C65: Tariff 126 | D65: 0 | E65: 366.86 | F65: 0.05 | G65: 0.05
A66: 633 | B66: 2000055630125 | C66: Tariff 127 | D66: 0 | E66: 247.18 | F66: 0.05 | G66: 0.05
A67: 634 | B67: 2000055845782 | C67: Tariff 128 | D67: 0 | E67: 248.98 | F67: 0.05 | G67: 0.05
A68: 635 | B68: 2000055856989 | C68: Tariff 129 | D68: 0 | E68: 1691.07 | F68: 0.05 | G68: 0.05
A69: 648 | B69: 2000056875324 | C69: Tariff 131 | D69: 0 | E69: 3239.12 | F69: 0.05 | G69: 0.05
A70: 637 | B70: - | C70: Tariff 132 | D70: 0 | E70: 3481.08 | F70: 0.05 | G70: 0.05
A71: 639 | B71: 2000055875003 | C71: Tariff 134 | D71: 0 | E71: 1323.77 | F71: 0.05 | G71: 0.05
A72: 640 | B72: 2000055996668 | C72: Tariff 135 | D72: 0 | E72: 362.84 | F72: 0.05 | G72: 0.05
A73: 641 | B73: 2000055627888 | C73: Tariff 136 | D73: 0 | E73: 246.79 | F73: 0.05 | G73: 0.05
A74: 642 | B74: 2000055899797 | C74: Tariff 137 | D74: 0 | E74: 775.23 | F74: 0.05 | G74: 0.05
A75: 645 | B75: 2000055924014 | C75: Tariff 138 | D75: 0 | E75: 1678.47 | F75: 0.05 | G75: 0.05
A76: 646 | B76: 2000055878705 | C76: Tariff 139 | D76: 0 | E76: 819.41 | F76: 0.05 | G76: 0.05
A77: Z00 | B77: 2000056762142 | C77: Tariff 140 | D77: 0 | E77: 986.11 | F77: 0.05 | G77: 0.05
A78: 649 | B78: 2000055901300 | C78: Tariff 143 | D78: 0 | E78: 324.53 | F78: 0.05 | G78: 0.05
A79: 911 | B79: 2000055901355 | C79: Tariff 144 | D79: 0 | E79: 362.55 | F79: 0.05 | G79: 0.05
A80: 912 | B80: 2000055899398 | C80: Tariff 146 | D80: 0 | E80: 1086.36 | F80: 0.05 | G80: 0.05
A81: 952 | B81: 2000056479110 | C81: Tariff 147 | D81: 0 | E81: 1843.08 | F81: 0.05 | G81: 0.05
A82: 913 | B82: 2000055858727 | C82: Tariff 148 | D82: 0 | E82: 739.13 | F82: 0.05 | G82: 0.05
A83: 933 | B83: 2000056951269 | C83: Tariff 149 | D83: 0 | E83: 6593.8 | F83: 0.05 | G83: 0.05
A84: 958 | B84: 2000056277280 | C84: Tariff 151 | D84: 0 | E84: 357.56 | F84: 0.05 | G84: 0.05
A85: 626 | B85: 2000056113323 | C85: Tariff 152 | D85: 0 | E85: 364.57 | F85: 0.05 | G85: 0.05
A86: 607 | B86: 2000056212628 | C86: Tariff 153 | D86: 0 | E86: 364.21 | F86: 0.05 | G86: 0.05
A87: 915 | B87: 2000055924032 | C87: Tariff 154 | D87: 0 | E87: 978.49 | F87: 0.05 | G87: 0.05
A88: 608 | B88: 2000056127292 | C88: Tariff 155 | D88: 0 | E88: 1319.59 | F88: 0.05 | G88: 0.05
A89: 959 | B89: 2000056455270 | C89: Tariff 156 | D89: 0 | E89: 362.88 | F89: 0.05 | G89: 0.05
... A115: 782 | B115: 2000056049314 | C115: Tariff 188 | D115: 0 | E115: 248.57 | F115: 0.05 | G115: 0.05
A116: Z01 | B116: 2000056827915 | C116: Tariff 189 | D116: 0 | E116: 237.44 | F116: 0.05 | G116: 0.05
A117: 783 | B117: 2000056169822 | C117: Tariff 190 | D117: 0 | E117: 751.64 | F117: 0.05 | G117: 0.05
A118: 784 | B118: 2000056179680 | C118: Tariff 191 | D118: 0 | E118: 1057.66 | F118: 0.05 | G118: 0.05
A119: 785 | B119: 2000056107125 | C119: Tariff 192 | D119: 0 | E119: 365.5 | F119: 0.05 | G119: 0.05
A120: 786 | B120: 2000056113963 | C120: Tariff 194 | D120: 0 | E120: 364.88 | F120: 0.05 | G120: 0.05
A121: 787 | B121: 2000056138160 | C121: Tariff 196 | D121: 0 | E121: 367 | F121: 0.05 | G121: 0.05
A122: 788 | B122: 2000056167922 | C122: Tariff 198 | D122: 0 | E122: 250.58 | F122: 0.05 | G122: 0.05
A123: 956 | B123: 2000056537783 | C123: Tariff 199 | D123: 0 | E123: 2908.37 | F123: 0.05 | G123: 0.05
A124: 789 | B124: 2000055874979 | C124: Tariff 201 | D124: 0 | E124: 7157.12 | F124: 0.05 | G124: 0.05
A125: 790 | B125: 2000056147261 | C125: Tariff 202 | D125: 0 | E125: 750.58 | F125: 0.05 | G125: 0.05
A126: 791 | B126: 2000055932238 | C126: Tariff 205 | D126: 0 | E126: 367.48 | F126: 0.05 | G126: 0.05
A127: 962 | B127: 2000056441384 | C127: Tariff 208 | D127: 0 | E127: 433.56 | F127: 0.05 | G127: 0.05
A128: 792 | B128: 2000056204965 | C128: Tariff 209 | D128: 0 | E128: 5156.23 | F128: 0.05 | G128: 0.05
A129: 933 | B129: - | C129: Tariff 211 | D129: 0 | E129: 364.88 | F129: 0.05 | G129: 0.05
A130: 618 | B130: 2000056439613 | C130: Tariff 212 | D130: 0 | E130: 3478.19 | F130: 0.05 | G130: 0.05
A131: 793 | B131: 2000056147401 | C131: Tariff 213 | D131: 0 | E131: 367.05 | F131: 0.05 | G131: 0.05
A132: 989 | B132: 2000056359863 | C132: Tariff 214 | D132: 0 | E132: 2521.78 | F132: 0.05 | G132: 0.05
A133: 794 | B133: 2000056202407 | C133: Tariff 215 | D133: 0 | E133: 1332.13 | F133: 0.05 | G133: 0.05
A134: 963 | B134: 2000056452118 | C134: Tariff 218 | D134: 0 | E134: 500.22 | F134: 0.05 | G134: 0.05
A135: 795 | B135: 2000056186438 | C135: Tariff 219 | D135: 0 | E135: 6301.16 | F135: 0.05 | G135: 0.05
A136: 796 | B136: 2000056166469 | C136: Tariff 220 | D136: 0 | E136: 3052.74 | F136: 0.05 | G136: 0.05
A137: Z02 | B137: 2000056792661 | C137: Tariff 222 | D137: 0 | E137: 470.28 | F137: 0.05 | G137: 0.05
A138: 933 | B138: - | C138: Tariff 223 | D138: 0 | E138: 637.63 | F138: 0.05 | G138: 0.05
A139: 980 | B139: 2000056384850 | C139: Tariff 225 | D139: 0 | E139: 438.15 | F139: 0.05 | G139: 0.05
A140: 955 | B140: 2000056536121 | C140: Tariff 227 | D140: 0 | E140: 667.94 | F140: 0.05 | G140: 0.05
A141: 957 | B141: 2000056456265 | C141: Tariff 228 | D141: 0 | E141: 228.27 | F141: 0.05 | G141: 0.05
A142: 999 | B142: 2000056440006 | C142: Tariff 229 | D142: 0 | E142: 330.8 | F142: 0.05 | G142: 0.05
A143: 450 | B143: 2000056420348 | C143: Tariff 230 | D143: 0 | E143: 431.22 | F143: 0.05 | G143: 0.05
A144: 797 | B144: 2000056202425 | C144: Tariff 233 | D144: 0 | E144: 637.31 | F144: 0.05 | G144: 0.05
A145: 933 | B145: - | C145: Tariff 234 | D145: 0 | E145: 12187.67 | F145: 0.05 | G145: 0.05
A146: 369 | B146: 2000056532483 | C146: Tariff 235 | D146: 0 | E146: 461.74 | F146: 0.05 | G146: 0.05
A147: 7310 | B147: 7310 | C147: Tariff 238 | D147: 0 | E147: 1002.15 | F147: 0.05 | G147: 0.05
A148: 798 | B148: 2000056199701 | C148: Tariff 240 | D148: 0 | E148: 569.64 | F148: 0.05 | G148: 0.05
A149: 933 | B149: - | C149: Tariff 243 | D149: 0 | E149: 3484.23 | F149: 0.05 | G149: 0.05
A150: 799 | B150: 2000056191535 | C150: Tariff 244 | D150: 0 | E150: 7847.08 | F150: 0.05 | G150: 0.05
A151: 935 | B151: - | C151: Tariff 245 | D151: 0 | E151: 3105.82 | F151: 0.05 | G151: 0.05
A152: 741 | B152: 2000056058763 | C152: Tariff 247 | D152: 0 | E152: 80 | F152: 0.05 | G152: 0.05
A153: 742 | B153: 2000056151115 | C153: Tariff 248 | D153: 0 | E153: 50.65 | F153: 0.05 | G153: 0.05
A154: 743 | B154: 2000056098827 | C154: Tariff 249 | D154: 0 | E154: 80.22 | F154: 0.05 | G154: 0.05
A155: 403 | B155: 2000056551333 | C155: Tariff 250 | D155: 0 | E155: 1082.9 | F155: 0.05 | G155: 0.05
A156: 451 | B156: 2000056562317 | C156: Tariff 251 | D156: 0 | E156: 3393.93 | F156: 0.05 | G156: 0.05
A157: 978 | B157: 2000056194207 | C157: Tariff 252 | D157: 0 | E157: 1452.06 | F157: 0.05 | G157: 0.05
A158: 991 | B158: 2000056139224 | C158: Tariff 253 | D158: 0 | E158: 4679.38 | F158: 0.05 | G158: 0.05
A159: 994 | B159: 2000056219980 | C159: Tariff 254 | D159: 0 | E159: 432.75 | F159: 0.05 | G159: 0.05
A160: 995 | B160: 2000056200029 | C160: Tariff 255 | D160: 0 | E160: 434.53 | F160: 0.05 | G160: 0.05
A161: 996 | B161: 2000056139001 | C161: Tariff 256 | D161: 0 | E161: 435.15 | F161: 0.05 | G161: 0.05
A162: 997 | B162: 2000056212042 | C162: Tariff 257 | D162: 0 | E162: 681.13 | F162: 0.05 | G162: 0.05
A163: 998 | B163: 2000056139438 | C163: Tariff 258 | D163: 0 | E163: 7161.71 | F163: 0.05 | G163: 0.05
... A165: 983 | B165: 2000056469185 | C165: Tariff 262 | D165: 0 | E165: 629.85 | F165: 0.05 | G165: 0.05
A166: Z03 | B166: 2000056842133 | C166: Tariff 264 | D166: 0 | E166: 435.7 | F166: 0.05 | G166: 0.05
A167: Z04 | B167: 2000056642716 | C167: Tariff 265 | D167: 0 | E167: 442.91 | F167: 0.05 | G167: 0.05
...

Sheet Annex 3 Preserved charges
A1: Back to Overview
A2: =Overview!B4& " - Effective from "&Overview!D4&" - "&Overview!E4&" LV and HV tariffs" -> Southern Electric Power Distribution plc - Effective from 1 April 2020 - Final LV and HV tariffs
A3: NHH preserved charges/additional LLFCs
B4: Closed LLFCs | C4: PCs | D4: Unit charge 1 (NHH) p/kWh | E4: Unit charge 2 (NHH) p/kWh | F4: Fixed charge p/MPAN/day
A5: Domestic Two Rate | B5: 124-125 | C5: 2 | D5: 2.387 | E5: 0.441 | F5: 3.51
A6: Domestic Off Peak (related MPAN) | B6: 112-114, 116-120, 122-123 | C6: 2 | D6: 0.537
A7: Small Non Domestic Off Peak (related MPAN) | B7: 138-139, 141-143, 145 | C7: 4 | D7: 0.665
A8: HV Medium Non-Domestic | B8: 605-606 | C8: 5-8 | D8: 0.862 | E8: 0.368 | F8: 288.71
A9: Notes: | B9: Unit time periods are as specified in the SSC.
A12: HH preserved charges/additional LLFCs
B13: Closed LLFCs | C13: PCs | D13: Red/black charge (HH) p/kWh | E13: Amber/yellow charge (HH) p/kWh | F13: Green charge (HH) p/kWh | G13: Fixed charge p/MPAN/day | H13: Capacity charge p/kVA/day | I13: Exceeded capacity charge p/kVA/day | J13: Reactive power charge p/kVArh
C14: 0
A15: Notes: | B15: Time periods
B16: Unit charges in the Red Time Band apply – between [16:30] and [19:30], Monday to Friday including bank holidays.
B17: Unit charges in the Amber Time Band apply – between [07:00] and [16:30] and [19:30] and [22:00], Monday to Friday including bank holidays, and [09:30] and [21:30] Saturday and Sunday.
B18: Unit charges in the Green Time Band apply – between [00:00] and [07:00] and [22:00] and [24:00], Monday to Friday including bank holidays, and [00:00] and [09:30] and [21:30] and [24:00], Saturday and Sunday.
B19: All times are UK clock-time.

Sheet Annex 4 LDNO charges
A1: Back to Overview
A2: =Overview!B4& " - Effective from "&Overview!D4&" - "&Overview!E4&" LDNO tariffs" -> Southern Electric Power Distribution plc - Effective from 1 April 2020 - Final LDNO tariffs
A4: Time Bands for Half Hourly Metered Properties | F4: Time Bands for Half Hourly Unmetered Properties
A5: Time periods | B5: Red Time Band | C5: Amber Time Band | D5: Green Time Band | H5: Black Time Band | I5: Yellow Time Band | J5: Green Time Band
A6: Monday to Friday (Including Bank Holidays) All Year | B6: 16:30 - 19:30 | F6: Monday to Friday (Including Bank Holidays) March to October | I6: 07:00 - 22:00
A7: Monday to Friday (Including Bank Holidays) All Year | C7: 07:00 - 16:30 19:30 - 22:00 | F7: Monday to Friday (Including Bank Holidays) November to February | H7: 16:30 - 19:30 | I7: 07:00 - 16:30 19:30 - 22:00
A8: Monday to Friday (Including Bank Holidays) All Year | D8: 00:00 - 07:00 22:00 - 24:00 | F8: Monday to Friday (Including Bank Holidays) April to March | J8: 00:00 - 07:00 22:00 - 24:00
A9: Saturday and Sunday All Year | C9: 09:30 - 21:30 | D9: 00:00 - 09:30 21:30 - 24:00 | F9: Saturday and Sunday All Year | I9: 09:30 - 21:30 | J9: 00:00 - 09:30 21:30 - 24:00
A10: Notes | B10: All the above times are in UK Clock time | F10: Notes | H10: All the above times are in UK Clock time
A13: Tariff name | B13: Unique billing identifier | C13: PCs | D13: ='Annex 1 LV and HV charges'!D13 -> Unit charge 1 (NHH) or red/black charge (HH) p/kWh | E13: ='Annex 1 LV and HV charges'!E13 -> Unit charge 2 (NHH) or amber/yellow charge (HH) p/kWh | F13: ='Annex 1 LV and HV charges'!F13 -> Green charge(HH) p/kWh | G13: ='Annex 1 LV and HV charges'!G13 -> Fixed charge p/MPAN/day | H13: ='Annex 1 LV and HV charges'!H13 -> Capacity charge p/kVA/day | I13: ='Annex 1 LV and HV charges'!I13 -> Exceeded capacity charge p/kVA/day | J13: ='Annex 1 LV and HV charges'!J13 -> Reactive power charge p/kVArh
A14: LDNO LV: Domestic Unrestricted | C14: 1 | D14: 1.262 | G14: 2.29
A15: LDNO LV: Domestic Two Rate | C15: 2 | D15: 1.557 | E15: 0.288 | G15: 2.29
A16: LDNO LV: Domestic Off Peak (related MPAN) | C16: 2 | D16: 0.35
A17: LDNO LV: Small Non Domestic Unrestricted | C17: 3 | D17: 1.159 | G17: 3.43
A18: LDNO LV: Small Non Domestic Two Rate | C18: 4 | D18: 1.69 | E18: 0.386 | G18: 3.43
A19: LDNO LV: Small Non Domestic Off Peak (related MPAN) | C19: 4 | D19: 0.434
A20: LDNO LV: LV Medium Non-Domestic | C20: 5-8 | D20: 0.968 | E20: 0.281 | G20: 18.9
A21: LDNO LV: LV Network Domestic | C21: 0 | D21: 5.676 | E21: 0.782 | F21: 0.252 | G21: 2.29
A22: LDNO LV: LV Network Non-Domestic Non-CT | C22: 0 | D22: 5.98 | E22: 0.814 | F22: 0.254 | G22: 3.43
A23: LDNO LV: LV HH Metered | C23: 0 | D23: 4.091 | E23: 0.565 | F23: 0.238 | G23: 10.76 | H23: 1.58 | I23: 2.99 | J23: 0.133
A24: LDNO LV: NHH UMS category A | C24: 8 | D24: 1.697
A25: LDNO LV: NHH UMS category B | C25: 1 | D25: 1.734
A26: LDNO LV: NHH UMS category C | C26: 1 | D26: 2.219
A27: LDNO LV: NHH UMS category D | C27: 1 | D27: 1.704
A28: LDNO LV: LV UMS (Pseudo HH Metered) | C28: 0 | D28: 8.954 | E28: 1.681 | F28: 1.2
A29: LDNO LV: LV Generation NHH or Aggregate HH | C29: 8&0 | D29: -0.794 | G29: 0
A30: LDNO LV: LV Generation Intermittent | C30: 0 | D30: -0.794 | G30: 0 | J30: 0.186
A31: LDNO LV: LV Generation Non-Intermittent | C31: 0 | D31: -5.536 | E31: -0.571 | F31: -0.033 | G31: 0 | J31: 0.186
A32: LDNO HV: Domestic Unrestricted | C32: 1 | D32: 0.87 | G32: 1.58
A33: LDNO HV: Domestic Two Rate | C33: 2 | D33: 1.073 | E33: 0.198 | G33: 1.58
A34: LDNO HV: Domestic Off Peak (related MPAN) | C34: 2 | D34: 0.241
A35: LDNO HV: Small Non Domestic Unrestricted | C35: 3 | D35: 0.799 | G35: 2.36
A36: LDNO HV: Small Non Domestic Two Rate | C36: 4 | D36: 1.165 | E36: 0.266 | G36: 2.36
A37: LDNO HV: Small Non Domestic Off Peak (related MPAN) | C37: 4 | D37: 0.299
A38: LDNO HV: LV Medium Non-Domestic | C38: 5-8 | D38: 0.668 | E38: 0.193 | G38: 13.03
A39: LDNO HV: LV Network Domestic | C39: 0 | D39: 3.913 | E39: 0.539 | F39: 0.173 | G39: 1.58
A40: LDNO HV: LV Network Non-Domestic Non-CT | C40: 0 | D40: 4.122 | E40: 0.561 | F40: 0.175 | G40: 2.36
A41: LDNO HV: LV HH Metered | C41: 0 | D41: 2.82 | E41: 0.39 | F41: 0.164 | G41: 7.41 | H41: 1.09 | I41: 2.06 | J41: 0.092
A42: LDNO HV: LV Sub HH Metered | C42: 0 | D42: 3.487 | E42: 0.434 | F42: 0.248 | G42: 18.48 | H42: 3.07 | I42: 4.14 | J42: 0.093
A43: LDNO HV: HV HH Metered | C43: 0 | D43: 2.909 | E43: 0.408 | F43: 0.28 | G43: 120.97 | H43: 4.34 | I43: 5.38 | J43: 0.071
A44: LDNO HV: NHH UMS category A | C44: 8 | D44: 1.17
A45: LDNO HV: NHH UMS category B | C45: 1 | D45: 1.195
A46: LDNO HV: NHH UMS category C | C46: 1 | D46: 1.529
A47: LDNO HV: NHH UMS category D | C47: 1 | D47: 1.174
A48: LDNO HV: LV UMS (Pseudo HH Metered) | C48: 0 | D48: 6.172 | E48: 1.158 | F48: 0.827
A49: LDNO HV: LV Generation NHH or Aggregate HH | C49: 8&0 | D49: -0.794 | G49: 0
A50: LDNO HV: LV Sub Generation NHH | C50: 8 | D50: -0.695 | G50: 0
A51: LDNO HV: LV Generation Intermittent | C51: 0 | D51: -0.794 | G51: 0 | J51: 0.186
A52: LDNO HV: LV Generation Non-Intermittent | C52: 0 | D52: -5.536 | E52: -0.571 | F52: -0.033 | G52: 0 | J52: 0.186
A53: LDNO HV: LV Sub Generation Intermittent | C53: 0 | D53: -0.695 | G53: 0 | J53: 0.166
A54: LDNO HV: LV Sub Generation Non-Intermittent | C54: 0 | D54: -4.994 | E54: -0.475 | F54: -0.026 | G54: 0 | J54: 0.166
A55: LDNO HV: HV Generation Intermittent | C55: 0 | D55: -0.46 | G55: 0 | J55: 0.147
A56: LDNO HV: HV Generation Non-Intermittent | C56: 0 | D56: -3.838 | E56: -0.227 | F56: -0.008 | G56: 0 | J56: 0.147
A57: LDNO HVplus: Domestic Unrestricted | C57: 1 | D57: 0.644 | G57: 1.17
A58: LDNO HVplus: Domestic Two Rate | C58: 2 | D58: 0.795 | E58: 0.147 | G58: 1.17
A59: LDNO HVplus: Domestic Off Peak (related MPAN) | C59: 2 | D59: 0.179
A60: LDNO HVplus: Small Non Domestic Unrestricted | C60: 3 | D60: 0.592 | G60: 1.75
A61: LDNO HVplus: Small Non Domestic Two Rate | C61: 4 | D61: 0.863 | E61: 0.197 | G61: 1.75
A62: LDNO HVplus: Small Non Domestic Off Peak (related MPAN) | C62: 4 | D62: 0.221
A63: LDNO HVplus: LV Medium Non-Domestic | C63: 5-8 | D63: 0.494 | E63: 0.143 | G63: 9.65
A64: LDNO HVplus: LV Sub Medium Non-Domestic | C64: 5-8 | D64: 0.665 | E64: 0.213 | G64: 13.44
A65: LDNO HVplus: HV Medium Non-Domestic | C65: 5-8 | D65: 0.51 | E65: 0.218 | G65: 170.85
A66: LDNO HVplus: LV Network Domestic | C66: - | D66: 2.897 | E66: 0.399 | F66: 0.129 | G66: 1.17
A67: LDNO HVplus: LV Network Non-Domestic Non-CT | C67: - | D67: 3.052 | E67: 0.415 | F67: 0.13 | G67: 1.75
A68: LDNO HVplus: LV HH Metered | C68: 0 | D68: 2.088 | E68: 0.288 | F68: 0.122 | G68: 5.49 | H68: 0.81 | I68: 1.53 | J68: 0.068
A69: LDNO HVplus: LV Sub HH Metered | C69: 0 | D69: 2.535 | E69: 0.315 | F69: 0.181 | G69: 13.44 | H69: 2.23 | I69: 3.01 | J69: 0.067
A70: LDNO HVplus: HV HH Metered | C70: 0 | D70: 2.097 | E70: 0.295 | F70: 0.202 | G70: 87.2 | H70: 3.12 | I70: 3.88 | J70: 0.051
A71: LDNO HVplus: NHH UMS category A | C71: 8 | D71: 0.866
A72: LDNO HVplus: NHH UMS category B | C72: 1 | D72: 0.885
A73: LDNO HVplus: NHH UMS category C | C73: 1 | D73: 1.133
A74: LDNO HVplus: NHH UMS category D | C74: 1 | D74: 0.87
A75: LDNO HVplus: LV UMS (Pseudo HH Metered) | C75: 0 | D75: 4.57 | E75: 0.858 | F75: 0.612
A76: LDNO HVplus: LV Generation NHH or Aggregate HH | C76: 8 | D76: -0.414 | G76: 0
A77: LDNO HVplus: LV Sub Generation NHH | C77: 8 | D77: -0.411 | G77: 0
A78: LDNO HVplus: LV Generation Intermittent | C78: 0 | D78: -0.414 | G78: 0 | J78: 0.097
A79: LDNO HVplus: LV Generation Non-Intermittent | C79: 0 | D79: -2.885 | E79: -0.298 | F79: -0.017 | G79: 0 | J79: 0.097
A80: LDNO HVplus: LV Sub Generation Intermittent | C80: 0 | D80: -0.411 | G80: 0 | J80: 0.098
A81: LDNO HVplus: LV Sub Generation Non-Intermittent | C81: 0 | D81: -2.955 | E81: -0.281 | F81: -0.015 | G81: 0 | J81: 0.098
A82: LDNO HVplus: HV Generation Intermittent | C82: 0 | D82: -0.46 | G82: 242.78 | J82: 0.147
A83: LDNO HVplus: HV Generation Non-Intermittent | C83: 0 | D83: -3.838 | E83: -0.227 | F83: -0.008 | G83: 242.78 | J83: 0.147
A84: LDNO EHV: Domestic Unrestricted | C84: 1 | D84: 0.499 | G84: 0.91
A85: LDNO EHV: Domestic Two Rate | C85: 2 | D85: 0.616 | E85: 0.114 | G85: 0.91
A86: LDNO EHV: Domestic Off Peak (related MPAN) | C86: 2 | D86: 0.139
A87: LDNO EHV: Small Non Domestic Unrestricted | C87: 3 | D87: 0.459 | G87: 1.35
A88: LDNO EHV: Small Non Domestic Two Rate | C88: 4 | D88: 0.668 | E88: 0.153 | G88: 1.35
A89: LDNO EHV: Small Non Domestic Off Peak (related MPAN) | C89: 4 | D89: 0.172
A90: LDNO EHV: LV Medium Non-Domestic | C90: 5-8 | D90: 0.383 | E90: 0.111 | G90: 7.48
A91: LDNO EHV: LV Sub Medium Non-Domestic | C91: 5-8 | D91: 0.515 | E91: 0.165 | G91: 10.41
A92: LDNO EHV: HV Medium Non-Domestic | C92: 5-8 | D92: 0.395 | E92: 0.169 | G92: 132.4
A93: LDNO EHV: LV Network Domestic | C93: - | D93: 2.245 | E93: 0.309 | F93: 0.1 | G93: 0.91
A94: LDNO EHV: LV Network Non-Domestic Non-CT | C94: - | D94: 2.365 | E94: 0.322 | F94: 0.1 | G94: 1.35
A95: LDNO EHV: LV HH Metered | C95: 0 | D95: 1.618 | E95: 0.223 | F95: 0.094 | G95: 4.26 | H95: 0.62 | I95: 1.18 | J95: 0.053
A96: LDNO EHV: LV Sub HH Metered | C96: 0 | D96: 1.964 | E96: 0.244 | F96: 0.14 | G96: 10.41 | H96: 1.73 | I96: 2.33 | J96: 0.052
A97: LDNO EHV: HV HH Metered | C97: 0 | D97: 1.625 | E97: 0.228 | F97: 0.157 | G97: 67.58 | H97: 2.42 | I97: 3 | J97: 0.039
A98: LDNO EHV: NHH UMS category A | C98: 8 | D98: 0.671
A99: LDNO EHV: NHH UMS category B | C99: 1 | D99: 0.686
A100: LDNO EHV: NHH UMS category C | C100: 1 | D100: 0.878
A101: LDNO EHV: NHH UMS category D | C101: 1 | D101: 0.674
A102: LDNO EHV: LV UMS (Pseudo HH Metered) | C102: 0 | D102: 3.542 | E102: 0.665 | F102: 0.475
A103: LDNO EHV: LV Generation NHH or Aggregate HH | C103: 8 | D103: -0.321 | G103: 0
...

Sheet Annex 5 LLFs
A1: Back to Overview
A2: This table has intentionally been left blank. The line loss factors that are approved by the BSC Panel for the applicable year and consequently published on the Elexon website will take precedence and be used in Settlement. This annex will be re-published once these values are available.
A3: =Overview!B4& " - Illustrative LLFs for year beginning "&Overview!D4 -> Southern Electric Power Distribution plc - Illustrative LLFs for year beginning 1 April 2020
A4: Time periods | B4: Period 1 | C4: Period 2 | D4: Period 3 | E4: Period 4
B5: Winter Weekday Peak | C5: Winter Weekday | D5: Other | E5: Night
A6: Monday to Friday Nov to Feb | B6: 16:00 – 19:00 | C6: 07:30 – 16:00 19:00 – 20:00 | D6: 20:00 – 00:30 | E6: 00:30 – 07:30
A7: Saturday and Sunday All Year and Monday to Friday Mar to Oct | D7: 07:30 – 00:30 | E7: 00:30 – 07:30
A8: Notes | B8: All the above times are in UK Clock time
A11: Generic demand and generation LLFs
A12: Metered voltage, respective periods and associated LLFCs
A13: Metered voltage | B13: Period 1 | C13: Period 2 | D13: Period 3 | E13: Period 4 | F13: Associated LLFC
A14: Low-voltage network | B14: 1.094 | C14: 1.085 | D14: 1.076 | E14: 1.072 | F14: 100-131, 133-136, 138-145, 150-157, 160-166, 400-401, 453, 456-457, 470,473-475, 479, 500-503, 520, 586-589 / 1, 2, 7, 8, 79, 80, 477, 909, 931, 993
A15: Low-voltage substation | B15: 1.047 | C15: 1.045 | D15: 1.044 | E15: 1.047 | F15: 405, 455, H99 / 3, 4, 146, 147, 210, 211, 932
A16: High-voltage network | B16: 1.032 | C16: 1.029 | D16: 1.024 | E16: 1.022 | F16: 476, 605, 606, 658 / 5, 6, 148, 149, 212, 213, 478, 910, H98
A17: High-voltage substation | B17: 1.022 | C17: 1.02 | D17: 1.018 | E17: 1.017 | F17: 700-719, 729-732, 735, 739, 745, 746, H96 / 734, 736, 737, 738, 740-743, 748, 749, H97
A18: 33kV generic | B18: 1.016 | C18: 1.015 | D18: 1.012 | E18: 1.011 | F18: 897 / 933
A19: 132/33kV generic | B19: 1.009 | C19: 1.008 | D19: 1.007 | E19: 1.007 | F19: 898 / 934
A20: 132kV generic | B20: 1.005 | C20: 1.004 | D20: 1.003 | E20: 1.003 | F20: 899 / 935
A22: EHV site specific LLFs
A23: Demand
A24: Tariff | B24: Period 1 | C24: Period 2 | D24: Period 3 | E24: Period 4 | F24: Associated LLFC
A25: Tariff 001 | B25: 1.022 | C25: 1.02 | D25: 1.018 | E25: 1.017 | F25: 700
A26: Tariff 002 | B26: 1.022 | C26: 1.02 | D26: 1.018 | E26: 1.017 | F26: 701
A27: Tariff 003 | B27: 1.022 | C27: 1.02 | D27: 1.018 | E27: 1.017 | F27: 702
A28: Tariff 004 | B28: 1.022 | C28: 1.02 | D28: 1.018 | E28: 1.017 | F28: 704
A29: Tariff 005 | B29: 1.022 | C29: 1.02 | D29: 1.018 | E29: 1.017 | F29: 706
A30: Tariff 006 | B30: 1.022 | C30: 1.02 | D30: 1.018 | E30: 1.017 | F30: 707
A31: Tariff 007 | B31: 1.022 | C31: 1.02 | D31: 1.018 | E31: 1.017 | F31: 708
A32: Tariff 008 | B32: 1.022 | C32: 1.02 | D32: 1.018 | E32: 1.017 | F32: 709
A33: Tariff 009 | B33: 1.022 | C33: 1.02 | D33: 1.018 | E33: 1.017 | F33: 710
A34: Tariff 010 | B34: 1.022 | C34: 1.02 | D34: 1.018 | E34: 1.017 | F34: 711
A35: Tariff 011 | B35: 1.022 | C35: 1.02 | D35: 1.018 | E35: 1.017 | F35: 712
A36: Tariff 012 | B36: 1.022 | C36: 1.02 | D36: 1.018 | E36: 1.017 | F36: 713
... A65: Tariff 041 | B65: 0.999 | C65: 0.999 | D65: 0.999 | E65: 0.999 | F65: 7174
A66: Tariff 042 | B66: N/A | C66: N/A | D66: N/A | E66: N/A | F66: N/A
A67: Tariff 043 | B67: 1 | C67: 1 | D67: 1.001 | E67: 1 | F67: 823
A68: Tariff 044 | B68: 1.04 | C68: 1.039 | D68: 1.088 | E68: 1.042 | F68: 824
A69: Tariff 045 | B69: 1.008 | C69: 1.008 | D69: 1.008 | E69: 1.007 | F69: 825
A70: Tariff 046 | B70: 1.006 | C70: 1.006 | D70: 1.006 | E70: 1.005 | F70: 826
A71: Tariff 047 | B71: 1.013 | C71: 1.013 | D71: 1.014 | E71: 1.016 | F71: 827
A72: Tariff 048 | B72: 1.016 | C72: 1.015 | D72: 1.012 | E72: 1.011 | F72: 897
A73: Tariff 049 | B73: 1.005 | C73: 1.005 | D73: 1.005 | E73: 1.005 | F73: 829
A74: Tariff 050 | B74: 1.006 | C74: 1.007 | D74: 1.008 | E74: 1.006 | F74: 820
A75: Tariff 051 | B75: 1.003 | C75: 1.003 | D75: 1.003 | E75: 1.003 | F75: 830
A76: Tariff 052 | B76: 1.004 | C76: 1.004 | D76: 1.003 | E76: 1.004 | F76: 854
A77: Tariff 053 | B77: 0.999 | C77: 0.999 | D77: 0.999 | E77: 0.999 | F77: 835
A78: Tariff 054 | B78: 1.021 | C78: 1.021 | D78: 1.026 | E78: 1.019 | F78: 836
... A156: Tariff 139 | B156: 1.046 | C156: 1.033 | D156: 1.028 | E156: 1.038 | F156: 832
A157: Tariff 140 | B157: 1.034 | C157: 1.024 | D157: 1.019 | E157: 1.032 | F157: Y00
A158: Tariff 143 | B158: 1.016 | C158: 1.011 | D158: 1.023 | E158: 1.022 | F158: 850
A159: Tariff 144 | B159: 1.016 | C159: 1.008 | D159: 1.007 | E159: 1.015 | F159: 661
A160: Tariff 146 | B160: 1.019 | C160: 1.015 | D160: 1.012 | E160: 1.016 | F160: 662
A161: Tariff 147 | B161: 1.01 | C161: 1.004 | D161: 1.001 | E161: 1.011 | F161: 452
A162: Tariff 148 | B162: 1.015 | C162: 0.999 | D162: 0.996 | E162: 1.014 | F162: 663
A163: Tariff 149 | B163: 1.016 | C163: 1.015 | D163: 1.012 | E163: 1.011 | F163: 897
A164: Tariff 151 | B164: 1.02 | C164: 1.014 | D164: 1.012 | E164: 1.016 | F164: 458
A165: Tariff 152 | B165: 1.016 | C165: 1.013 | D165: 1.011 | E165: 1.013 | F165: 596
A166: Tariff 153 | B166: 1.024 | C166: 1.011 | D166: 1.01 | E166: 1.02 | F166: 597
A167: Tariff 154 | B167: 1.008 | C167: 1.004 | D167: 1.003 | E167: 1.006 | F167: 665
A168: Tariff 155 | B168: 1.006 | C168: 1.001 | D168: 0.994 | E168: 1.006 | F168: 598
A169: Tariff 156 | B169: 1.012 | C169: 1.017 | D169: 1.027 | E169: 1.01 | F169: 459
... A195: Tariff 188 | B195: 1.01 | C195: 1.011 | D195: 1.018 | E195: 1.016 | F195: 682
A196: Tariff 189 | B196: 1.02 | C196: 1.011 | D196: 1.017 | E196: 1.01 | F196: Y01
A197: Tariff 190 | B197: 1.01 | C197: 1.015 | D197: 1.015 | E197: 1.008 | F197: 683
A198: Tariff 191 | B198: 1.037 | C198: 1.02 | D198: 1.016 | E198: 1.033 | F198: 684
A199: Tariff 192 | B199: 1.007 | C199: 1.004 | D199: 1.003 | E199: 1.006 | F199: 685
A200: Tariff 194 | B200: 1.019 | C200: 1.017 | D200: 1.016 | E200: 1.017 | F200: 686
A201: Tariff 196 | B201: 1.027 | C201: 1.02 | D201: 1.018 | E201: 1.024 | F201: 687
A202: Tariff 198 | B202: 1.012 | C202: 1.022 | D202: 1.042 | E202: 1.01 | F202: 688
A203: Tariff 199 | B203: 1.013 | C203: 1.004 | D203: 1.001 | E203: 1.012 | F203: 525
A204: Tariff 201 | B204: 1.008 | C204: 1.008 | D204: 1.008 | E204: 1.007 | F204: 689
A205: Tariff 202 | B205: 1.001 | C205: 0.998 | D205: 0.999 | E205: 1.007 | F205: 690
A206: Tariff 205 | B206: 1.009 | C206: 1.005 | D206: 1.002 | E206: 1.007 | F206: 691
A207: Tariff 206 | B207: 1.022 | C207: 1.02 | D207: 1.018 | E207: 1.017 | F207: 729
A208: Tariff 208 | B208: 1.024 | C208: 1.035 | D208: 1.037 | E208: 1.03 | F208: 527
... A217: Tariff 220 | B217: 1.002 | C217: 0.992 | D217: 0.99 | E217: 1.003 | F217: 696
A218: Tariff 222 | B218: 1.038 | C218: 1.038 | D218: 1.04 | E218: 1.034 | F218: Y02
A219: Tariff 223 | B219: 1.016 | C219: 1.015 | D219: 1.012 | E219: 1.011 | F219: 897
A220: Tariff 225 | B220: 1.019 | C220: 1.018 | D220: 1.016 | E220: 1.015 | F220: 595
A221: Tariff 227 | B221: 1.001 | C221: 1 | D221: 0.999 | E221: 1.001 | F221: 655
A222: Tariff 228 | B222: 1.024 | C222: 1.016 | D222: 1.015 | E222: 1.032 | F222: 657
A223: Tariff 229 | B223: 1.008 | C223: 1.005 | D223: 1.005 | E223: 1.013 | F223: 659
A224: Tariff 230 | B224: 1.031 | C224: 1.026 | D224: 1.025 | E224: 1.026 | F224: 660
A225: Tariff 233 | B225: 1.023 | C225: 1.01 | D225: 1.009 | E225: 1.008 | F225: 697
A226: Tariff 234 | B226: 1.016 | C226: 1.015 | D226: 1.012 | E226: 1.011 | F226: 897
A227: Tariff 235 | B227: 1.033 | C227: 1.027 | D227: 1.023 | E227: 1.03 | F227: 669
A228: Tariff 238 | B228: 1.012 | C228: 1.022 | D228: 1.03 | E228: 1.015 | F228: 7311
A229: Tariff 240 | B229: 1.021 | C229: 1.014 | D229: 1.014 | E229: 1.019 | F229: 698
A230: Tariff 243 | B230: 1.016 | C230: 1.015 | D230: 1.012 | E230: 1.011 | F230: 897
... A247: Tariff 262 | B247: 1.011 | C247: 1.009 | D247: 1.008 | E247: 1.009 | F247: 765
A248: Tariff 264 | B248: 1.025 | C248: 1.009 | D248: 1.006 | E248: 1.023 | F248: Y03
A249: Tariff 265 | B249: 1.006 | C249: 1.007 | D249: 1.007 | E249: 1.008 | F249: Y04
A250: Tariff 269 | B250: 1.016 | C250: 1.015 | D250: 1.012 | E250: 1.011 | F250: 897
A251: Tariff 270 | B251: 1.015 | C251: 1.014 | D251: 1.013 | E251: 1.014 | F251: Y05
A252: Tariff 271 | B252: 1.016 | C252: 1.015 | D252: 1.012 | E252: 1.011 | F252: 897
A253: Tariff 275 | B253: 1.055 | C253: 1.036 | D253: 1.037 | E253: 1.04 | F253: 766
A254: Tariff 276 | B254: 1.002 | C254: 1.002 | D254: 1.002 | E254: 1.001 | F254: Y06
A255: Tariff 277 | B255: 1.046 | C255: 1.036 | D255: 1.039 | E255: 1.042 | F255: Y26
A256: Tariff 279 | B256: 1.016 | C256: 1.015 | D256: 1.012 | E256: 1.011 | F256: 897
A257: Tariff 280 | B257: 1.074 | C257: 1.065 | D257: 1.057 | E257: 1.062 | F257: 767
...

Sheet Annex 6 new or amended EHV
A1: Back to Overview | F1: Note: The list of MPANs/MSIDs provided may be incomplete; the DNO reserves the right to apply the listed charges to any other MPANs/MSIDs associated with the site. If sites appear in both Annex 2 and Annex 6, the charges in Annex 6 take precedence. Where an existing Designated EHV Property is modified and energised in the charging year, we may revise the EDCM charges for the modified Designated EHV Property.
A2: Annex 6 - Charges for New or Amended Designated EHV Properties
A4: =Overview!B4& " - Effective from "&Overview!D4&" - "&Overview!E4&" new or amended designated EHV charges" -> Southern Electric Power Distribution plc - Effective from 1 April 2020 - Final new or amended designated EHV charges
A5: Effective from date | B5: Import LLFC | C5: Import MPANs/MSIDs | D5: Export LLFC | E5: Export MPANs/MSIDs | F5: Tariff | G5: ='Annex 2 EHV charges'!F9 -> Import Super Red unit charge (p/kWh) | H5: ='Annex 2 EHV charges'!G9 -> Import fixed charge (p/day) | I5: ='Annex 2 EHV charges'!H9 -> Import capacity charge (p/kVA/day) | J5: ='Annex 2 EHV charges'!I9 -> Import exceeded capacity charge (p/kVA/day) | K5: ='Annex 2 EHV charges'!J9 -> Export Super Red unit charge (p/kWh) | L5: ='Annex 2 EHV charges'!K9 -> Export fixed charge (p/day) | M5: ='Annex 2 EHV charges'!L9 -> Export capacity charge (p/kVA/day) | N5: ='Annex 2 EHV charges'!M9 -> Export exceeded capacity charge (p/kVA/day)
A17: =Overview!B4& " - Effective from "&Overview!D4&" - "&Overview!E4&" new or amended designated EHV line loss factors" -> Southern Electric Power Distribution plc - Effective from 1 April 2020 - Final new or amended designated EHV line loss factors
A18: Effective from date | B18: Import LLFC | C18: Import MPANs/MSIDs | D18: Export LLFC | E18: Export MPANs/MSIDs | F18: Tariff | G18: Import LLF period 1 | H18: Import LLF period 2 | I18: Import LLF period 3 | J18: Import LLF period 4 | K18: Export LLF period 1 | L18: Export LLF period 2 | M18: Export LLF period 3 | N18: Export LLF period 4

Sheet Nodal prices
A1: Back to Overview
A2: =Overview!B4& " - Effective from "&Overview!D4&" - "&Overview!E4&" Nodal/Zonal charges" -> Southern Electric Power Distribution plc - Effective from 1 April 2020 - Final Nodal/Zonal charges
A3: Node/Zone ID | B3: Geographical name | C3: Local charge 1 £/kVA | D3: Remote charge 1 £/kVA
A4: 1 | B4: Mannington | C4: 16.339175 | D4: 0
A5: 2 | B5: Melksham | C5: 1.0642836 | D5: 0
A6: 3 | B6: Fleet & Bramley | C6: 2.6414871 | D6: 0
A7: 4 | B7: Amersham | C7: 0 | D7: 0
A8: 5 | B8: Bramley (ANDO & THAT) | C8: 0 | D8: 0
A9: 6 | B9: Axminster | C9: 1.5710959 | D9: 0
A10: 7 | B10: Bramley (BASI) | C10: 0 | D10: 0
A11: 8 | B11: Minety | C11: 0 | D11: 0
A12: 9 | B12: Fawley & Nursling | C12: 0 | D12: 0
A13: 10 | B13: Botley Wood | C13: 0 | D13: 0
A14: 11 | B14: Iver 132 | C14: 0 | D14: 0
A15: 12 | B15: Lovedean A2 | C15: 0 | D15: 0
... A784: 851 | B784: DELT-E 11.000 | C784: 0 | D784: 0

Sheet SSC TPR unit rate lookup
A1: Back to Overview
A28: Standard Settlement Configuration Id | B28: Time Pattern Regime Id | C28: Standard Settlement Configuration Desc | D28: Common Decode | G28: Change implemented | H28: Date | I28: Comments
A29: 3 | B29: 166 | C29: 10-hour OP | D29: O | H29: 40057 | I29: First published spreadsheet
A30: 4 | B30: 168 | C30: 10-hour OP | D30: O | G30: SSC 0330 charge rates corrected | H30: 40275 | I30: Previous Off-peak rate corrected to charge 2
A31: 5 | B31: 100 | C31: 10-hour OP + w/e | D31: O | G31: SSC 0250 charge rate corrected | H31: 40347 | I31: Previous rate 1 corrected to Off Peak O
A32: 6 | B32: 257 | C32: 10.5-hour OP | D32: O | G32: SSC 0134 charge rate corrected | H32: 41166 | I32: TPR 00101 corrected from Off Peak O to Rate 1
A33: 7 | B33: 158 | C33: 10.5-hour OP | D33: O | G33: New SSCs added | H33: 41178 | I33: New SSCs from 0953 added.
A34: 8 | B34: 159 | C34: 10.5-hour OP | D34: O | G34: SSC 0394 charge rate corrected | H34: 41758 | I34: TPR 01177 corrected to rate 2
A35: 9 | B35: 1111 | C35: 10.5-hour OP | D35: O | G35: Table reviewed and updated | H35: 41758 | I35: New SSCs from 0949 to 0952, 0975 & 0976 and 0982 & 0983 added.
A36: 10 | B36: 1104 | C36: 10.5-hour OP | D36: O | G36: Table reviewed and updated | H36: 41944 | I36: New SSCs from 0984 and 0985 added.
A37: 11 | B37: 1112 | C37: 10.5-hour OP | D37: O | G37: SSC 0313 charge code corrected | H37: 42081 | I37: TPR 01006 corrected to code O
A38: 12 | B38: 1116 | C38: 10.5-hour OP | D38: O | G38: SSC 0320 charge code corrected | H38: 42081 | I38: TPR 00072 corrected to code 2
A39: 13 | B39: 139 | C39: 11 Hour OP | D39: EMEB or MIDE only | G39: SSC 0781 charge code corrected | H39: 42081 | I39: TPR 00327 corrected to code O
A40: 15 | B40: 152 | C40: 11 Hour OP | D40: EMEB or MIDE only | G40: SSC 0935 charge code corrected | H40: 42081 | I40: TPR 00375 corrected to code 1 or Unsupported (SWAE and SWEB)
A41: 16 | B41: 113 | C41: 11.5-hour OP | D41: Unsupported (SWEB) | G41: SSC 0953 charge code corrected | H41: 42081 | I41: TPR 00424 corrected to code 1 or Unsupported (SWAE and SWEB)
... A74: 50 | B74: 14 | C74: 12-hour OP + w/e & Summer | D74: O | G74: SSC 0942 charge code corrected | H74: 42166 | I74: TPR 00400 corrected to code 1
A75: 51 | B75: 112 | C75: 12-hour night | D75: 1 | G75: SSC 0943 charge code corrected | H75: 42166 | I75: TPR 00404 corrected to code 1
A76: 51 | B76: 120 | C76: 12-hour night | D76: 2 | G76: SSC 0944 charge code corrected | H76: 42166 | I76: TPR 00406 corrected to code 1
A77: 52 | B77: 114 | C77: 12-hour OP | D77: EMEB or MIDE only | G77: SSC 0945 charge code corrected | H77: 42166 | I77: TPR 00408 corrected to code 1
A78: 53 | B78: 115 | C78: 12-hour OP | D78: EMEB or MIDE only | G78: SSC 0946 charge code corrected | H78: 42166 | I78: TPR 00410 corrected to code 1
A79: 55 | B79: 117 | C79: 12-hour OP | D79: EMEB or MIDE only | G79: SSC 0954 charge code corrected | H79: 42166 | I79: TPR 00426 corrected to code 1
A80: 56 | B80: 118 | C80: 12-hour OP | D80: EMEB or MIDE only | G80: SSC 0967 charge code corrected | H80: 42166 | I80: TPR 00442 corrected to code 1
A81: 57 | B81: 119 | C81: 12-hour OP | D81: O | G81: SSC 0970 charge code corrected | H81: 42166 | I81: TPR 00447 corrected to code 2
A82: 58 | B82: 21 | C82: Key Meter pseudo 2-rate | D82: 1 | G82: SSC 0970 charge code corrected | H82: 42166 | I82: TPR 00448 corrected to code 1
A83: 58 | B83: 175 | C83: Key Meter pseudo 2-rate | D83: 1 | G83: SSC 0971 charge code corrected | H83: 42166 | I83: TPR 00493 corrected to code 1
A84: 59 | B84: 121 | C84: 12-hour OP | D84: EMEB or MIDE only
A85: 60 | B85: 122 | C85: 12-hour OP | D85: O
A86: 62 | B86: 1119 | C86: 8-hour OP (see also SSC 427) | D86: 2 or Unsupported (SWEB)
A87: 63 | B87: 172 | C87: 9-hour OP | D87: EMEB or MIDE only
A88: 64 | B88: 1105 | C88: 12-hour OP | D88: O
A89: 65 | B89: 10 | C89: 12-hour OP + Summer | D89: O
A90: 66 | B90: 1106 | C90: 12-hour OP + Summer | D90: O
A91: 67 | B91: 102 | C91: 12.5-hour OP | D91: Unsupported (SWEB)
A92: 71 | B92: 109 | C92: 12.5-hour OP | D92: O
A93: 72 | B93: 111 | C93: 12.5-hour OP | D93: O
A94: 73 | B94: 156 | C94: 12.5-hour OP | D94: Unsupported (SWEB)
A95: 74 | B95: 17 | C95: 12.5-hour OP + Summer | D95: O
... A99: 78 | B99: 13 | C99: 12.5-hour OP + w/e & Summer | D99: O
A100: 79 | B100: 97 | C100: 14-hour E7 | D100: 2
A101: 79 | B101: 164 | C101: 14-hour E7 | D101: 1
A102: 80 | B102: 96 | C102: 14-hour Off Peak | D102: O
A103: 81 | B103: 60 | C103: 14-hour OP + Sun | D103: O
A104: 82 | B104: 83 | C104: 14.5-hour OP | D104: O
A105: 83 | B105: 84 | C105: 14.5-hour OP | D105: O
A106: 84 | B106: 85 | C106: 14.5-hour OP | D106: O
A107: 85 | B107: 86 | C107: 14.5-hour OP | D107: O
A108: 86 | B108: 1107 | C108: 14.5-hour OP | D108: O
A109: 87 | B109: 1109 | C109: 14.5-hour OP | D109: O
A110: 88 | B110: 1113 | C110: 14.5-hour OP | D110: O
A111: 91 | B111: 3 | C111: 14.5-hour OP + Summer | D111: O
A112: 92 | B112: 4 | C112: 14.5-hour OP + Summer | D112: O
A113: 93 | B113: 30 | C113: split 7-hour E7 | D113: 1
A114: 93 | B114: 214 | C114: split 7-hour E7 | D114: 2
A115: 94 | B115: 1108 | C115: 14.5-hour OP + Summer | D115: O
A116: 95 | B116: 1110 | C116: 14.5-hour OP + Summer | D116: O
A117: 96 | B117: 1114 | C117: 14.5-hour OP + Summer | D117: O
A118: 97 | B118: 54 | C118: 14.5-hour OP + w/e | D118: O
A119: 98 | B119: 12 | C119: 14.5-hour OP + w/e & Summer | D119: O
A120: 99 | B120: 75 | C120: 15-hour OP | D120: EMEB or MIDE only
A121: 100 | B121: 76 | C121: 15-hour OP | D121: EMEB or MIDE only
A122: 101 | B122: 7 | C122: 15-hour OP + w/e & Summer | D122: O
A123: 102 | B123: 8 | C123: 15-hour OP + w/e & Summer | D123: O
A124: 103 | B124: 9 | C124: 15-hour OP + w/e & Summer | D124: O
A125: 104 | B125: 61 | C125: 15.5-hour OP | D125: Unsupported (SWEB)
A126: 105 | B126: 65 | C126: 15.5-hour OP | D126: O
... A140: 120 | B140: 11 | C140: 9-hour OP | D140: O
A141: 121 | B141: 26 | C141: 2-rate terms | D141: 2
A142: 121 | B142: 224 | C142: 2-rate terms | D142: 1
A143: 122 | B143: 201 | C143: 2-rate SToD | D143: 1
A144: 122 | B144: 245 | C144: 2-rate SToD | D144: 2
A145: 123 | B145: 1307 | C145: 2-rate variable SToD | D145: 1
A146: 124 | B146: 1319 | C146: 2-rate variable SToD | D146: 1
A147: 125 | B147: 1315 | C147: 2-rate variable SToD | D147: 1
A148: 126 | B148: 1193 | C148: 7-hour E7 | D148: 1
A149: 126 | B149: 1194 | C149: 7-hour E7 | D149: 2
A150: 127 | B150: 80 | C150: 3-rate SToD | D150: Unsupported (SWEB)
A151: 127 | B151: 148 | C151: 3-rate SToD | D151: 1
A152: 127 | B152: 221 | C152: 3-rate SToD | D152: 2 or Unsupported (SWEB)
A153: 128 | B153: 1120 | C153: Dom/Non-dom Seasonal (link SSC 0342) | D153: 1
A154: 128 | B154: 1121 | C154: Dom/Non-dom Seasonal (link SSC 0342) | D154: 1
A155: 128 | B155: 1122 | C155: Dom/Non-dom Seasonal (link SSC 0342) | D155: 2
A156: 129 | B156: 169 | C156: 3-rate SToD | D156: 1
A157: 129 | B157: 202 | C157: 3-rate SToD | D157: 1
A158: 129 | B158: 222 | C158: 3-rate SToD | D158: 2
A159: 130 | B159: 1308 | C159: 3-rate variable | D159: 1
A160: 130 | B160: 1309 | C160: 3-rate variable | D160: 1
A161: 130 | B161: 1310 | C161: 3-rate variable | D161: 2
A162: 131 | B162: 1311 | C162: 3-rate variable | D162: 1
A163: 131 | B163: 1312 | C163: 3-rate variable | D163: 1
A164: 131 | B164: 1313 | C164: 3-rate variable | D164: 2
A165: 132 | B165: 92 | C165: 4-rate SToD | D165: EMEB or MIDE only
A166: 132 | B166: 210 | C166: 4-rate SToD | D166: 2
A167: 132 | B167: 234 | C167: 4-rate SToD | D167: EMEB or MIDE only
A168: 132 | B168: 236 | C168: 4-rate SToD | D168: EMEB or MIDE only
A169: 133 | B169: 92 | C169: 4-rate SToD | D169: 1
A170: 133 | B170: 210 | C170: 4-rate SToD | D170: 2
A171: 133 | B171: 233 | C171: 4-rate SToD | D171: 1
A172: 133 | B172: 246 | C172: 4-rate SToD | D172: 1
A173: 134 | B173: 101 | C173: 4-rate SToD | D173: 1
A174: 134 | B174: 210 | C174: 4-rate SToD | D174: 2
...

Sheet Charge Calculator
B1: Back to Overview
B2: =Overview!B4& " - Effective from "&Overview!D4&" - "&Overview!E4 -> Southern Electric Power Distribution plc - Effective from 1 April 2020 - Final
B4: LV and HV tariff calculator | L4: EHV site calculator
B5: Step 1, Choose your tariff using the drop down list in cell B10 | L5: Step 1, Choose your tariff using the drop down list in cell L10
B6: Step 2, After selecting a tariff in step 1, Cells C12-I12 will generate headings, please enter your consumption in cells C13:I13 underneath each heading generated (if no heading leave cell blank) | L6: Step 2, After selecting a tariff in step 1, Cells M12-T12 will generate headings, please enter your consumption in cells M13:T13 underneath each heading generated (if no heading leave cell blank)
B7: Step 3, Enter a forecast of consumption if required in cells C14:I14 | L7: Step 3, Enter a forecast of consumption if required in cells M14:T14
B9: Tariff details Choose tariff name from drop down box below | C9: ='Annex 1 LV and HV charges'!D13 -> Unit charge 1 (NHH) or red/black charge (HH) p/kWh | D9: ='Annex 1 LV and HV charges'!E13 -> Unit charge 2 (NHH) or amber/yellow charge (HH) p/kWh | E9: ='Annex 1 LV and HV charges'!F13 -> Green charge(HH) p/kWh | F9: ='Annex 1 LV and HV charges'!G13 -> Fixed charge p/MPAN/day | G9: ='Annex 1 LV and HV charges'!H13 -> Capacity charge p/kVA/day | H9: ='Annex 1 LV and HV charges'!I13 -> Exceeded capacity charge p/kVA/day | I9: ='Annex 1 LV and HV charges'!J13 -> Reactive power charge p/kVArh | L9: Site details Choose the site name from the drop down box below | M9: ='Annex 2 EHV charges'!F9 -> Import Super Red unit charge (p/kWh) | N9: ='Annex 2 EHV charges'!G9 -> Import fixed charge (p/day) | O9: ='Annex 2 EHV charges'!H9 -> Import capacity charge (p/kVA/day) | P9: ='Annex 2 EHV charges'!I9 -> Import exceeded capacity charge (p/kVA/day) | Q9: ='Annex 2 EHV charges'!J9 -> Export Super Red unit charge (p/kWh) | R9: ='Annex 2 EHV charges'!K9 -> Export fixed charge (p/day) | S9: ='Annex 2 EHV charges'!L9 -> Export capacity charge (p/kVA/day) | T9: ='Annex 2 EHV charges'!M9 -> Export exceeded capacity charge (p/kVA/day)
C10: =IFERROR(VLOOKUP($B$10,'Annex 1 LV and HV charges'!$A:$K,4,FALSE),"") | D10: =IFERROR(VLOOKUP($B$10,'Annex 1 LV and HV charges'!$A:$K,5,FALSE),"") | E10: =IFERROR(VLOOKUP($B$10,'Annex 1 LV and HV charges'!$A:$K,6,FALSE),"") | F10: =IFERROR(VLOOKUP($B$10,'Annex 1 LV and HV charges'!$A:$K,7,FALSE),"") | G10: =IFERROR(VLOOKUP($B$10,'Annex 1 LV and HV charges'!$A:$K,8,FALSE),"") | H10: =IFERROR(VLOOKUP($B$10,'Annex 1 LV and HV charges'!$A:$K,9,FALSE),"") | I10: =IFERROR(VLOOKUP($B$10,'Annex 1 LV and HV charges'!$A:$K,10,FALSE),"") | M10: =IFERROR(VLOOKUP($L$10,'Annex 2 EHV charges'!$G:$M,2,FALSE),"") -> 6.04 | N10: =IFERROR(VLOOKUP($L$10,'Annex 2 EHV charges'!$G:$M,3,FALSE),"") -> 6.04 | O10: =IFERROR(VLOOKUP($L$10,'Annex 2 EHV charges'!$G:$M,4,FALSE),"") -> 0 | P10: =IFERROR(VLOOKUP($L$10,'Annex 2 EHV charges'!$G:$M,5,FALSE),"") -> 0 | Q10: =IFERROR(VLOOKUP($L$10,'Annex 2 EHV charges'!$G:$M,6,FALSE),"") -> 0 | R10: =IFERROR(VLOOKUP($L$10,'Annex 2 EHV charges'!$G:$M,7,FALSE),"") -> 0 | S10: =IFERROR(VLOOKUP($L$10,'Annex 2 EHV charges'!$G:$M,8,FALSE),"") | T10: =IFERROR(VLOOKUP($L$10,'Annex 2 EHV charges'!$G:$M,9,FALSE),"")
B12: Tariff components | C12: Unit 1 kWh (red/black/day) | D12: Unit 2 kWh (amber/yellow /night) | E12: Unit 3 kWh (green) | F12: Number of days in consumption period i.e. 365 if one year | G12: Maximum import or export capacity kVA | H12: Average daily exceeded capacity kVA | I12: Excess reactive units kVArh | L12: Tariff components | M12: Import super red kWh | N12: Number of days in consumption period i.e. 365 if one year | O12: Maximum import capacity kVA | P12: Average daily exceeded capacity kVA | Q12: Export Super Red kWh | R12: Number of days in consumption period i.e. 365 if one year | S12: Maximum export capacity kVA | T12: Average daily exceeded capacity kVA
B13: Enter current consumption details | L13: Enter current consumption details | R13: =N13 -> 0
B14: Enter forecast consumption details (if different) | C14: =C13 -> 0 | D14: =D13 -> 0 | E14: =E13 -> 0 | F14: =F13 -> 0 | G14: =G13 -> 0 | H14: =H13 -> 0 | I14: =I13 -> 0 | L14: Enter forecast consumption details (if different) | M14: =M13 -> 0 | N14: =N13 -> 0 | O14: =O13 -> 0 | P14: =P13 -> 0 | Q14: =Q13 -> 0 | R14: =R13 -> 0 | S14: =S13 -> 0 | T14: =T13 -> 0
B16: Charge components | C16: Unit 1 £ | D16: Unit 2 £ | E16: Unit 3 £ | F16: Fixed charge £ | G16: Capacity charge £ | H16: Exceeded capacity charge £ | I16: Reactive power charge £ | L16: Charge components | M16: Import super red charge £ | N16: Import fixed charge £ | O16: Import capacity charge £ | P16: Import exceeded capacity charge £ | Q16: Export super red charge £ | R16: Export fixed charge £ | S16: Export capacity charge £ | T16: Export exceeded capacity charge £
B17: Current consumption period charges | C17: =IFERROR(C10*C13/100,"") | D17: =IFERROR(D10*D13/100,"") | E17: =IFERROR(E10*E13/100,"") | F17: =IFERROR(F10*F13/100,"") | G17: =IFERROR(G10*G13*F13/100,"") | H17: =IFERROR(H10*H13*F13/100,"") | I17: =IFERROR(I10*I13/100,"") | L17: Current consumption period charges | M17: =IFERROR(M10*M13/100,"") -> 0 | N17: =IFERROR(N10*N13/100,"") -> 0 | O17: =IFERROR(O10*O13*N13/100,"") -> 0 | P17: =IFERROR(P10*P13*N13/100,"") -> 0 | Q17: =IFERROR(Q10*Q13/100,"") -> 0 | R17: =IFERROR(R10*R13/100,"") -> 0 | S17: =IFERROR(S10*S13*R13/100,"") | T17: =IFERROR(T10*T13*R13/100,"")
B18: Forecast consumption period charges | C18: =IFERROR(C10*C14/100,"") | D18: =IFERROR(D10*D14/100,"") | E18: =IFERROR(E10*E14/100,"") | F18: =IFERROR(F10*F14/100,"") | G18: =IFERROR(G10*G14*F14/100,"") | H18: =IFERROR(H10*H14*F14/100,"") | I18: =IFERROR(I10*I14/100,"") | L18: Forecast consumption period charges | M18: =IFERROR(M10*M14/100,"") -> 0 | N18: =IFERROR(N10*N14/100,"") -> 0 | O18: =IFERROR(O10*O14*N14/100,"") -> 0 | P18: =IFERROR(P10*P14*N14/100,"") -> 0 | Q18: =IFERROR(Q10*Q14/100,"") -> 0 | R18: =IFERROR(R10*R14/100,"") -> 0 | S18: =IFERROR(S10*S14*R14/100,"") | T18: =IFERROR(T10*T14*R14/100,"")
C20: Total charge £ | M20: Import total charge £ | N20: Export total charge £
B21: Current consumption period charges | C21: =SUM(C17:I17) -> 0 | L21: Current consumption period charges | M21: =SUM(M17:P17) -> 0 | N21: =SUM(Q17:T17) -> 0
B22: Forecast consumption period charges | C22: =SUM(C18:I18) -> 0 | L22: Forecast consumption period charges | M22: =SUM(M18:P18) -> 0 | N22: =SUM(Q18:T18) -> 0
B24: These charges are estimates based on tariff selected and consumption values entered. | L24: These charges are estimates based on site selected and consumption values entered.
