Workbook

Sheet Overview
A2: Company and Licence name, charging year, effective from, status
B3: Company and Licence name | C3: Year | D3: Effective From | E3: Status
A4: Company and Licence name, charging year, effective from, status | B4: Northern Powergrid (Yorkshire) Plc | C4: 2026/27 | D4: 1 April 2026 | E4: Final
A6: List of data tables in this workbook
A7: Worksheet | B7: Information
A8: Annex 1 LV, HV and Unmetered Supplies charges | B8: Annex 1 contains the charges to LV and HV Designated Properties and Unmetered Supplies.
A9: Annex 2 Designated EHV charges | B9: ="Annex 2 contains the charges to Designated EHV Properties and charges applied to LDNOs with Designated EHV Properties/end-users embedded in networks within the " &B4 &" Licence area." -> Annex 2 contains the charges to Designated EHV Properties and charges applied to LDNOs with Designated EHV Properties/end-users embedded in networks within the Northern Powergrid (Yorkshire) Plc Licence area.
A10: Annex 3 Preserved charges | B10: Annex 3 contains details of any preserved and additional charges that are valid at this time.
A11: Annex 4 LDNO charges | B11: ="Annex 4 contains charges that are levied on the owner of an embedded network within the "&B4&" Licence area. "&"Electricity suppliers and consumers who have properties connected to an embedded network should contact the embedded network owner to determine their distribution charges."&" The charges listed in this table are not payable by domestic consumers, business consumers or electricity suppliers." -> Annex 4 contains charges that are levied on the owner of an embedded network within the Northern Powergrid (Yorkshire) Plc Licence area. Electricity suppliers and consumers who have properties connected to an embedded network should contact the embedded network owner to determine their distribution charges. The charges listed in this table are not payable by domestic consumers, business consumers or electricity suppliers.
A12: Annex 5 LLFs | B12: Annex 5 has been intentionally left blank as this charging statement is published a complete year before the LLFs have been audited. The line loss factors that are approved by the BSC Panel for the applicable year and consequently published on the Elexon website will take precedence and be used in Settlement. This annex will be re-published with these values once they are available.
A13: Annex 6 Charges for New or Amended Designated EHV Properties | B13: ="Annex 6 contains the charges for new or amended Designated EHV Properties and charges applied to LDNOs with new or amended Designated EHV Properties/end-users embedded in networks within the " &B4 &" Licence area." -> Annex 6 contains the charges for new or amended Designated EHV Properties and charges applied to LDNOs with new or amended Designated EHV Properties/end-users embedded in networks within the Northern Powergrid (Yorkshire) Plc Licence area.
A14: Annex 7 Fixed adders for Supplier of Last Resort and Eligible Bad Debt pass-through costs | B14: Annex 7 contains the fixed adders to recover Supplier of Last Resort and Eligible Bad Debt pass-through costs.
A15: Nodal prices | B15: Contains the underlying [nodal/network group] costs used to calculate the current Designated EHV Properties charges.
A16: Residual Charging Bandings | B16: Contains the four Residual charging band allocation for Customers
A17: TNUoS Mapping | B17: Contains the mapping between DUoS tariff names and expected TNUoS charging bands
A18: Charge calculator | B18: Charge calculator is a tool to help you estimate your distribution charges using current consumption data and forecast consumption data.
A20: Notes to users of this spreadsheet
A22: Please use this spreadsheet with reference to the LC14 use of system charging statement.
A24: Notes to DNOs populating this spreadsheet
A26: DNOs must endeavour to maintain consistency in the structure of this spreadsheet. Any changes to the structure must be noted in the 'Notes to users of this spreadsheet'
A27: The drop down list on the charge calculator can be expanded by unprotecting the charge calculator sheet and selecting 'data', 'data validation...' and then expanding the 'source' data range. The sheet can then be protected.

Sheet Annex 1 LV, HV and UMS charges
A1: Back to Overview
A2: =Overview!B4& " - Effective from "&Overview!D4&" - "&Overview!E4&" LV and HV charges" -> Northern Powergrid (Yorkshire) Plc - Effective from 1 April 2026 - Final LV and HV charges
A4: Time Bands for LV and HV Designated Properties | G4: Time Bands for Unmetered Properties
A5: Time periods | B5: Red Time Band | C5: Amber Time Band | E5: Green Time Band | I5: Black Time Band | J5: Yellow Time Band | K5: Green Time Band
A6: Monday to Friday (Including Bank Holidays) All Year | B6: 16:00 to 19:30 | C6: 08:00 to 16:00 19:30 to 22:00 | E6: 00:00 to 08:00 22:00 to 24:00 | G6: Monday to Friday (Including Bank Holidays) November to February Inclusive | I6: 16:00 to 19:30 | J6: 08:00 to 16:00 19:30 to 22:00 | K6: 00:00 to 08:00 22:00 to 24:00
A7: Saturday and Sunday All Year | B7: 0 | C7: 0 | E7: 00:00 to 24:00 | G7: Monday to Friday (Including Bank Holidays) April to October Inclusive and March | I7: 0 | J7: 08:00 to 22:00 | K7: 00:00 to 08:00 22:00 to 24:00
A8: Notes | B8: All the above times are in UK Clock time | G8: Saturday and Sunday All year | I8: 0 | J8: 0 | K8: 00:00 to 24:00
G9: Notes | I9: All the above times are in UK Clock time
A11: Tariff name | B11: Open LLFCs | C11: PCs | D11: Red/black unit charge p/kWh | E11: Amber/yellow unit charge p/kWh | F11: Green unit charge p/kWh | G11: Fixed charge p/MPAN/day | H11: Capacity charge p/kVA/day | I11: Exceeded capacity charge p/kVA/day | J11: Reactive power charge p/kVArh | K11: Closed LLFCs
A12: Domestic Aggregated or CT with Residual | B12: 1A, 1AH, 100, 120, 279 | C12: 0, 1, 2 | D12: 6.786 | E12: 1.819 | F12: 0.212 | G12: 18.03 | H12: 0 | I12: 0 | J12: 0 | K12: 999
A13: Domestic Aggregated (Related MPAN) | B13: 3A, 111 | C13: 2 | D13: 6.786 | E13: 1.819 | F13: 0.212 | G13: 0 | H13: 0 | I13: 0 | J13: 0
A14: Non-Domestic Aggregated or CT No Residual | B14: 2Z, 2ZH | C14: 0, 3, 4, 5-8 | D14: 8.165 | E14: 2.188 | F14: 0.255 | G14: 12.11 | H14: 0 | I14: 0 | J14: 0
A15: Non-Domestic Aggregated or CT Band 1 | B15: 2A, 2AH | C15: 0, 3, 4, 5-8 | D15: 8.165 | E15: 2.188 | F15: 0.255 | G15: 17.83 | H15: 0 | I15: 0 | J15: 0
A16: Non-Domestic Aggregated or CT Band 2 | B16: 2B, 2BH | C16: 0, 3, 4, 5-8 | D16: 8.165 | E16: 2.188 | F16: 0.255 | G16: 26.38 | H16: 0 | I16: 0 | J16: 0
A17: Non-Domestic Aggregated or CT Band 3 | B17: 2C, 2CH | C17: 0, 3, 4, 5-8 | D17: 8.165 | E17: 2.188 | F17: 0.255 | G17: 41.96 | H17: 0 | I17: 0 | J17: 0
A18: Non-Domestic Aggregated or CT Band 4 | B18: 2D, 2DH | C18: 0, 3, 4, 5-8 | D18: 8.165 | E18: 2.188 | F18: 0.255 | G18: 95.09 | H18: 0 | I18: 0 | J18: 0
A19: Non-Domestic Aggregated (related MPAN) | B19: 4A | C19: 4 | D19: 8.165 | E19: 2.188 | F19: 0.255 | G19: 0 | H19: 0 | I19: 0 | J19: 0
A20: LV Site Specific No Residual | B20: 5Z | C20: 0 | D20: 5.829 | E20: 1.528 | F20: 0.172 | G20: 16.1 | H20: 3.82 | I20: 3.82 | J20: 0.118
A21: LV Site Specific Band 1 | B21: 5A | C21: 0 | D21: 5.829 | E21: 1.528 | F21: 0.172 | G21: 154.8 | H21: 3.82 | I21: 3.82 | J21: 0.118
A22: LV Site Specific Band 2 | B22: 5B | C22: 0 | D22: 5.829 | E22: 1.528 | F22: 0.172 | G22: 293.65 | H22: 3.82 | I22: 3.82 | J22: 0.118
A23: LV Site Specific Band 3 | B23: 5C | C23: 0 | D23: 5.829 | E23: 1.528 | F23: 0.172 | G23: 433.95 | H23: 3.82 | I23: 3.82 | J23: 0.118
A24: LV Site Specific Band 4 | B24: 5D | C24: 0 | D24: 5.829 | E24: 1.528 | F24: 0.172 | G24: 886.25 | H24: 3.82 | I24: 3.82 | J24: 0.118
A25: LV Sub Site Specific No Residual | B25: 6Z | C25: 0 | D25: 3.714 | E25: 0.923 | F25: 0.094 | G25: 16.1 | H25: 3.07 | I25: 3.07 | J25: 0.068
A26: LV Sub Site Specific Band 1 | B26: 6A | C26: 0 | D26: 3.714 | E26: 0.923 | F26: 0.094 | G26: 154.8 | H26: 3.07 | I26: 3.07 | J26: 0.068
A27: LV Sub Site Specific Band 2 | B27: 6B | C27: 0 | D27: 3.714 | E27: 0.923 | F27: 0.094 | G27: 293.65 | H27: 3.07 | I27: 3.07 | J27: 0.068
A28: LV Sub Site Specific Band 3 | B28: 6C | C28: 0 | D28: 3.714 | E28: 0.923 | F28: 0.094 | G28: 433.95 | H28: 3.07 | I28: 3.07 | J28: 0.068
A29: LV Sub Site Specific Band 4 | B29: 6D | C29: 0 | D29: 3.714 | E29: 0.923 | F29: 0.094 | G29: 886.25 | H29: 3.07 | I29: 3.07 | J29: 0.068
A30: HV Site Specific No Residual | B30: 7Z | C30: 0 | D30: 2.514 | E30: 0.588 | F30: 0.052 | G30: 421.64 | H30: 3.78 | I30: 3.78 | J30: 0.041
... A34: HV Site Specific Band 4 | B34: 7D | C34: 0 | D34: 2.514 | E34: 0.588 | F34: 0.052 | G34: 12820.57 | H34: 3.78 | I34: 3.78 | J34: 0.041
A35: Unmetered Supplies | B35: 8A | C35: 0, 1, 8 | D35: 20.504 | E35: 2.393 | F35: 0.89 | G35: 0 | H35: 0 | I35: 0 | J35: 0
A36: LV Generation Aggregated | B36: 20 | C36: 0 | D36: -4.895 | E36: -1.312 | F36: -0.153 | G36: 0 | H36: 0 | I36: 0 | J36: 0
A37: LV Sub Generation Aggregated | B37: 30 | C37: 0 | D37: -4.046 | E37: -1.07 | F37: -0.122 | G37: 0 | H37: 0 | I37: 0 | J37: 0
A38: LV Generation Site Specific | B38: 24, 22 | C38: 0 | D38: -4.895 | E38: -1.312 | F38: -0.153 | G38: 0 | H38: 0 | I38: 0 | J38: 0.091
A39: LV Generation Site Specific no RP charge | B39: 222, 224 | C39: 0 | D39: -4.895 | E39: -1.312 | F39: -0.153 | G39: 0 | H39: 0 | I39: 0 | J39: 0
A40: LV Sub Generation Site Specific | B40: 23, 25 | C40: 0 | D40: -4.046 | E40: -1.07 | F40: -0.122 | G40: 0 | H40: 0 | I40: 0 | J40: 0.083
A41: LV Sub Generation Site Specific no RP charge | B41: 223, 225 | C41: 0 | D41: -4.046 | E41: -1.07 | F41: -0.122 | G41: 0 | H41: 0 | I41: 0 | J41: 0
A42: HV Generation Site Specific | B42: 26, 28 | C42: 0 | D42: -2.826 | E42: -0.702 | F42: -0.071 | G42: 93.7 | H42: 0 | I42: 0 | J42: 0.073
A43: HV Generation Site Specific no RP charge | B43: 226, 228 | C43: 0 | D43: -2.826 | E43: -0.702 | F43: -0.071 | G43: 93.7 | H43: 0 | I43: 0 | J43: 0

Sheet Annex 2 Designated EHV charges
A1: Back to Overview | F1: Note: The list of MPANs / MSIDs provided may be incomplete; the DNO reserves the right to apply the listed charges to any other MPANs / MSIDs associated with the site.
A2: =Overview!B4& " - Effective from "&Overview!D4&" - "&Overview!E4&" Designated EHV charges" -> Northern Powergrid (Yorkshire) Plc - Effective from 1 April 2026 - Final Designated EHV charges
A4: Time Periods for Designated EHV Properties
A5: Time periods | D5: Super Red Time Band
A6: Monday to Friday (Including Bank Holidays) November to February Inclusive | D6: 1600 - 1930
A7: Notes | D7: All the above times are in UK Clock time
A9: Import Unique Identifier | B9: LLFC | C9: Import MPANs/MSIDs | D9: Export Unique Identifier | E9: LLFC | F9: Export MPANs/MSIDs | G9: Name | H9: Residual Charging Band | I9: Import Super Red unit charge (p/kWh) | J9: Import fixed charge (p/day) | K9: Import capacity charge (p/kVA/day) | L9: Import exceeded capacity charge (p/kVA/day) | M9: Export Super Red unit charge (p/kWh) | N9: Export fixed charge (p/day) | O9: Export capacity charge (p/kVA/day) | P9: Export exceeded capacity charge (p/kVA/day)
A10: 750 | B10: 750 | C10: 2300000599657 2336541294017 | E10: 0 | G10: EHV Site Specific (LLFC 750) | H10: 4 | I10: 0.045 | J10: 103218.15 | K10: 2.85 | L10: 2.85 | M10: 0 | N10: 0 | O10: 0 | P10: 0
A11: 751 | B11: 751 | C11: 2300000702517 2300000702526 2300000702535 2376555002010 2376555002029 2376555002038 | E11: 0 | G11: EHV Site Specific (LLFC 751) | H11: 4 | I11: 0.001 | J11: 108020.24 | K11: 0.92 | L11: 0.92 | M11: 0 | N11: 0 | O11: 0 | P11: 0
A12: 753 | B12: 753 | C12: 2356555555010 | D12: 90 | E12: 90 | F12: 2394000039650 | G12: EHV Site Specific (LLFC 753 & 90) | H12: 3 | I12: 0.042 | J12: 47306.88 | K12: 0.75 | L12: 0.75 | M12: 0 | N12: 183.27 | O12: 0.05 | P12: 0.05
A13: 754 | B13: 754 | C13: 2356555554017 2380002015807 | D13: 82 | E13: 82 | F13: 2394000039660 2394000110620 | G13: EHV Site Specific (LLFC 754 & 82) | H13: 2 | I13: 0.161 | J13: 25592.75 | K13: 0.68 | L13: 0.68 | M13: 0 | N13: 621.12 | O13: 0.05 | P13: 0.05
A14: 755 | B14: 755 | C14: 2316521850010 | D14: 76 | E14: 76 | F14: 2394000039641 | G14: EHV Site Specific (LLFC 755 & 76) | H14: 2 | I14: 0.027 | J14: 18816.11 | K14: 0.95 | L14: 0.95 | M14: 0 | N14: 564.58 | O14: 0.05 | P14: 0.05
A15: 756 | B15: 756 | C15: 2346540436013 | D15: 75 | E15: 75 | F15: 2394000039679 | G15: EHV Site Specific (LLFC 756 & 75) | H15: 2 | I15: 0.014 | J15: 23569.63 | K15: 1.1 | L15: 1.1 | M15: 0 | N15: 779.95 | O15: 0.05 | P15: 0.05
A16: 757 | B16: 757 | C16: 2336566756217 | D16: 95 | E16: 95 | F16: 2394000060226 | G16: EHV Site Specific (LLFC 757 & 95) | H16: 1 | I16: 0 | J16: 2293.86 | K16: 0.35 | L16: 0.35 | M16: -0.001 | N16: 1100.61 | O16: 0.05 | P16: 0.05
A17: 804 | B17: 804 | C17: MSID_0645 | D17: 800 | E17: 800 | F17: MSID_0645 | G17: EHV Site Specific (LLFC 804 & 800) | H17: 4 | I17: 0.01 | J17: 119342.94 | K17: 1.14 | L17: 1.14 | M17: -0.008 | N17: 2782.58 | O17: 0.05 | P17: 0.05
A18: 760 | B18: 760 | C18: 2300000880966 2376509001013 | D18: 60 | E18: 60 | F18: 2300000233736 2300000880975 | G18: EHV Site Specific (LLFC 760 & 60) | H18: 4 | I18: 0 | J18: 105037.14 | K18: 0.87 | L18: 0.87 | M18: 0 | N18: 1212.66 | O18: 0.05 | P18: 0.05
A19: 761 | B19: 761 | C19: 2300000526686 2336518071011 | E19: 0 | G19: EHV Site Specific (LLFC 761) | H19: 3 | I19: 0 | J19: 36679.86 | K19: 0.67 | L19: 0.67 | M19: 0 | N19: 0 | O19: 0 | P19: 0
A20: 762 | B20: 762 | C20: 2300000457400 | D20: 62 | E20: 62 | F20: 2300000457410 | G20: EHV Site Specific (LLFC 762 & 62) | H20: 0 | I20: 0 | J20: 40.02 | K20: 0.42 | L20: 0.42 | M20: -0.032 | N20: 453.52 | O20: 0.05 | P20: 0.05
A21: 763 | B21: 763 | C21: MSID_7376 MSID_7542 | D21: 80 | E21: 80 | F21: MSID_7377 MSID_7543 | G21: EHV Site Specific (LLFC 763 & 80) | H21: 0 | I21: 0.003 | J21: 101.82 | K21: 0.5 | L21: 0.5 | M21: -0.002 | N21: 1694.65 | O21: 0.05 | P21: 0.05
A22: 764 | B22: 764 | C22: 2300000233959 2300000233968 2300000233977 | E22: 0 | G22: EHV Site Specific (LLFC 764) | H22: 4 | I22: 0 | J22: 107168.57 | K22: 0.44 | L22: 0.44 | M22: 0 | N22: 0 | O22: 0 | P22: 0
A23: 765 | B23: 765 | C23: 2300000457084 2390000010840 2390000010859 | E23: 0 | G23: EHV Site Specific (LLFC 765) | H23: 4 | I23: 0.042 | J23: 105486.6 | K23: 0.86 | L23: 0.86 | M23: 0 | N23: 0 | O23: 0 | P23: 0
A24: 766 | B24: 766 | C24: 2376508030013 2376508030022 | D24: 66 | E24: 66 | F24: 2300000233912 2300000996990 | G24: EHV Site Specific (LLFC 766 & 66) | H24: 4 | I24: 0 | J24: 103377.23 | K24: 1.59 | L24: 1.59 | M24: 0 | N24: 209.85 | O24: 0.05 | P24: 0.05
A25: 769 | B25: 769 | C25: 2346526241119 2390000139108 | D25: 128 | E25: 128 | F25: 2394000133317 2394000139114 | G25: EHV Site Specific (LLFC 769 & 128) | H25: 1 | I25: 0 | J25: 2194.53 | K25: 0.53 | L25: 0.53 | M25: 0 | N25: 0 | O25: 0.05 | P25: 0.05
A26: 771 | B26: 771 | C26: 2366591376117 | D26: 92 | E26: 92 | F26: 2394000019176 | G26: EHV Site Specific (LLFC 771 & 92) | H26: 0 | I26: 0 | J26: 0 | K26: 0.35 | L26: 0.35 | M26: 0 | N26: 0 | O26: 0.05 | P26: 0.05
A27: 772 | B27: 772 | C27: 2366591373116 | E27: 0 | G27: EHV Site Specific (LLFC 772) | H27: 1 | I27: 0 | J27: 2194.53 | K27: 1.04 | L27: 1.04 | M27: 0 | N27: 0 | O27: 0 | P27: 0
A28: 773 | B28: 773 | C28: 2366591486111 2380002104680 | D28: 65 | E28: 65 | F28: 2394000117991 | G28: EHV Site Specific (LLFC 773 & 65) | H28: 1 | I28: 0 | J28: 2194.53 | K28: 0.91 | L28: 0.91 | M28: 0 | N28: 0 | O28: 0.05 | P28: 0.05
A29: 774 | B29: 774 | C29: 2326522910011 2326522910020 | D29: 74 | E29: 74 | F29: 2394000002925 2394100008408 | G29: EHV Site Specific (LLFC 774 & 74) | H29: 3 | I29: 0.322 | J29: 36408.15 | K29: 0.37 | L29: 0.37 | M29: 0 | N29: 0 | O29: 0 | P29: 0
A30: 775 | B30: 775 | C30: 2380000531989 | D30: 87 | E30: 87 | F30: 2394000024440 | G30: EHV Site Specific (LLFC 775 & 87) | H30: 0 | I30: 0.052 | J30: 281.82 | K30: 0.49 | L30: 0.49 | M30: -0.222 | N30: 1078.61 | O30: 0.05 | P30: 0.05
A31: 777 | B31: 777 | C31: MSID_7430 | D31: 77 | E31: 77 | F31: MSID_7431 | G31: EHV Site Specific (LLFC 777 & 77) | H31: 0 | I31: 0.067 | J31: 6.15 | K31: 0.55 | L31: 0.55 | M31: -0.101 | N31: 178.32 | O31: 0.05 | P31: 0.05
A32: 778 | B32: 778 | C32: 2300000443816 | D32: 78 | E32: 78 | F32: 2300000443825 | G32: EHV Site Specific (LLFC 778 & 78) | H32: 0 | I32: 0 | J32: 12.87 | K32: 1.55 | L32: 1.55 | M32: 0 | N32: 1354.6 | O32: 0.05 | P32: 0.05
A33: 780 | B33: 780 | C33: 2380000825051 | E33: 0 | G33: EHV Site Specific (LLFC 780) | H33: 4 | I33: 0 | J33: 104316.26 | K33: 0.43 | L33: 0.43 | M33: 0 | N33: 0 | O33: 0 | P33: 0
A34: 782 | B34: 782 | C34: 2300001016288 2300001016297 | E34: 0 | G34: EHV Site Specific (LLFC 782) | H34: 2 | I34: 0.777 | J34: 13539.29 | K34: 0.53 | L34: 0.53 | M34: 0 | N34: 0 | O34: 0 | P34: 0
A35: 783 | B35: 783 | C35: 2300000974268 | D35: 83 | E35: 83 | F35: 2300000974408 2394000113560 2394000135253 | G35: EHV Site Specific (LLFC 783 & 83) | H35: 0 | I35: 0.011 | J35: 4.92 | K35: 0.6 | L35: 0.6 | M35: 0 | N35: 0 | O35: 0 | P35: 0
A36: 784 | B36: 784 | C36: 2300001007247 | D36: 84 | E36: 84 | F36: 2300001007256 | G36: EHV Site Specific (LLFC 784 & 84) | H36: 0 | I36: 0.012 | J36: 0.61 | K36: 0.69 | L36: 0.69 | M36: 0 | N36: 0 | O36: 0 | P36: 0
A37: 785 | B37: 785 | C37: 2380000151720 | D37: 85 | E37: 85 | F37: 2394000011646 | G37: EHV Site Specific (LLFC 785 & 85) | H37: 0 | I37: 0.046 | J37: 1.72 | K37: 0.45 | L37: 0.45 | M37: 0 | N37: 0 | O37: 0 | P37: 0
A38: 786 | B38: 786 | C38: 2380000148115 | D38: 86 | E38: 86 | F38: 2391100013704 2394000011502 | G38: EHV Site Specific (LLFC 786 & 86) | H38: 0 | I38: 0 | J38: 1.16 | K38: 0.37 | L38: 0.37 | M38: 0 | N38: 0 | O38: 0 | P38: 0
A39: 787 | B39: 787 | C39: 2380000123421 2380000123430 | D39: 129 | E39: 129 | F39: 2394000134454 2394000134463 | G39: EHV Site Specific (LLFC 787 & 129) | H39: 3 | I39: 0 | J39: 37260.87 | K39: 1.18 | L39: 1.18 | M39: 0 | N39: 249.99 | O39: 0.05 | P39: 0.05
A40: 788 | B40: 788 | C40: 2380000654644 | D40: 88 | E40: 88 | F40: 2394000027673 | G40: EHV Site Specific (LLFC 788 & 88) | H40: 0 | I40: 0.002 | J40: 32.05 | K40: 0.76 | L40: 0.76 | M40: -0.332 | N40: 854.62 | O40: 0.05 | P40: 0.05
A41: 789 | B41: 789 | C41: 2380001118812 | D41: 89 | E41: 89 | F41: 2394000043364 2394000138110 | G41: EHV Site Specific (LLFC 789 & 89) | H41: 0 | I41: 0.001 | J41: 20.57 | K41: 0.94 | L41: 0.94 | M41: -0.175 | N41: 866.11 | O41: 0.05 | P41: 0.05
A42: 790 | B42: 790 | C42: 2380001476585 | D42: 94 | E42: 94 | F42: 2394000056790 | G42: EHV Site Specific (LLFC 790 & 94) | H42: 0 | I42: 0.001 | J42: 23.77 | K42: 0.4 | L42: 0.4 | M42: 0 | N42: 1601.1 | O42: 0.05 | P42: 0.05
A43: 791 | B43: 791 | C43: 2380001494334 | D43: 93 | E43: 93 | F43: 2394000058333 | G43: EHV Site Specific (LLFC 791 & 93) | H43: 1 | I43: 0.014 | J43: 2198.12 | K43: 0.43 | L43: 0.43 | M43: -0.105 | N43: 180.88 | O43: 0.05 | P43: 0.05
A44: 793 | B44: 793 | C44: 2380001252829 2380001252838 2380001767827 | D44: 91 | E44: 91 | F44: 2394000047581 2394000047590 2394000047606 | G44: EHV Site Specific (LLFC 793 & 91) | H44: 0 | I44: 0.094 | J44: 114.84 | K44: 0.37 | L44: 0.37 | M44: 0 | N44: 1951.69 | O44: 0.05 | P44: 0.05
A45: 794 | B45: 794 | C45: 2380001458911 | D45: 97 | E45: 97 | F45: 2394000055174 | G45: EHV Site Specific (LLFC 794 & 97) | H45: 0 | I45: 0.152 | J45: 390.65 | K45: 0.45 | L45: 0.45 | M45: 0 | N45: 12336.31 | O45: 0.05 | P45: 0.05
A46: 795 | B46: 795 | C46: 2380001532167 2380001532176 | E46: 0 | G46: EHV Site Specific (LLFC 795) | H46: 3 | I46: 0.012 | J46: 37731.77 | K46: 0.45 | L46: 0.45 | M46: 0 | N46: 0 | O46: 0 | P46: 0
A47: 796 | B47: 796 | C47: 2380001635401 | D47: 98 | E47: 98 | F47: 2394000072198 | G47: EHV Site Specific (LLFC 796 & 98) | H47: 0 | I47: 0 | J47: 53.55 | K47: 0.37 | L47: 0.37 | M47: 0 | N47: 5377.15 | O47: 0.05 | P47: 0.05
A48: 831 | B48: 831 | C48: 2316530305110 2316530305129 | E48: 0 | G48: EHV Site Specific (LLFC 831) | H48: 1 | I48: 3.787 | J48: 2335.94 | K48: 1.11 | L48: 1.11 | M48: 0 | N48: 0 | O48: 0 | P48: 0
A49: 832 | B49: 832 | C49: 2316541311014 | E49: 0 | G49: EHV Site Specific (LLFC 832) | H49: 2 | I49: 1.39 | J49: 13311.76 | K49: 1.79 | L49: 1.79 | M49: 0 | N49: 0 | O49: 0 | P49: 0
A50: 833 | B50: 833 | C50: 2326511015014 2326511015023 | E50: 0 | G50: EHV Site Specific (LLFC 833) | H50: 2 | I50: 0.477 | J50: 13311.76 | K50: 1.09 | L50: 1.09 | M50: 0 | N50: 0 | O50: 0 | P50: 0
A51: 834 | B51: 834 | C51: 2300000456903 2300000516605 2326531140128 | E51: 0 | G51: EHV Site Specific (LLFC 834) | H51: 1 | I51: 0.034 | J51: 2406.65 | K51: 1.59 | L51: 1.59 | M51: 0 | N51: 0 | O51: 0 | P51: 0
A52: 835 | B52: 835 | C52: 2300000473625 2336505790019 | E52: 0 | G52: EHV Site Specific (LLFC 835) | H52: 3 | I52: 0.073 | J52: 36452.34 | K52: 2.14 | L52: 2.14 | M52: 0 | N52: 0 | O52: 0 | P52: 0
A53: 836 | B53: 836 | C53: 2300000473616 2336506255013 | E53: 0 | G53: EHV Site Specific (LLFC 836) | H53: 2 | I53: 0.042 | J53: 13311.76 | K53: 1.96 | L53: 1.96 | M53: 0 | N53: 0 | O53: 0 | P53: 0
A54: 837 | B54: 837 | C54: 2300000473634 2336526022010 | D54: 34 | E54: 34 | F54: 2394000106234 | G54: EHV Site Specific (LLFC 837 & 34) | H54: 2 | I54: 0.106 | J54: 13254.85 | K54: 1.42 | L54: 1.42 | M54: -0.158 | N54: 56.92 | O54: 0.05 | P54: 0.05
A55: 838 | B55: 838 | C55: 2300000584925 2336559992019 | E55: 0 | G55: EHV Site Specific (LLFC 838) | H55: 1 | I55: 0.142 | J55: 2335.94 | K55: 0.68 | L55: 0.68 | M55: 0 | N55: 0 | O55: 0 | P55: 0
A56: 839 | B56: 839 | C56: 2300000233833 | D56: 68 | E56: 68 | F56: 2300000233898 | G56: EHV Site Specific (LLFC 839 & 68) | H56: 0 | I56: 0.001 | J56: 29.78 | K56: 0.32 | L56: 0.32 | M56: -0.001 | N56: 40.93 | O56: 0.05 | P56: 0.05
A57: 840 | B57: 840 | C57: 2336566566018 | E57: 0 | G57: EHV Site Specific (LLFC 840) | H57: 1 | I57: 0.854 | J57: 2265.24 | K57: 1.94 | L57: 1.94 | M57: 0 | N57: 0 | O57: 0 | P57: 0
A58: 841 | B58: 841 | C58: 2300000539365 2300000539374 2336590660028 2336590660037 | E58: 0 | G58: EHV Site Specific (LLFC 841) | H58: 3 | I58: 0.264 | J58: 36593.75 | K58: 3.74 | L58: 3.74 | M58: 0 | N58: 0 | O58: 0 | P58: 0
A59: 842 | B59: 842 | C59: TBC | E59: 0 | G59: EHV Site Specific (LLFC 842) | H59: 2 | I59: 0.087 | J59: 13311.76 | K59: 0.5 | L59: 0.5 | M59: 0 | N59: 0 | O59: 0 | P59: 0
A60: 844 | B60: 844 | C60: 2356530330014 2356530330023 | E60: 0 | G60: EHV Site Specific (LLFC 844) | H60: 3 | I60: 0.256 | J60: 36452.34 | K60: 2.28 | L60: 2.28 | M60: 0 | N60: 0 | O60: 0 | P60: 0
A61: 845 | B61: 845 | C61: 2356562495011 | E61: 0 | G61: EHV Site Specific (LLFC 845) | H61: 3 | I61: 0.508 | J61: 36381.63 | K61: 1.63 | L61: 1.63 | M61: 0 | N61: 0 | O61: 0 | P61: 0
A62: 846 | B62: 846 | C62: 2300000601321 | E62: 0 | G62: EHV Site Specific (LLFC 846) | H62: 1 | I62: 1.452 | J62: 2265.24 | K62: 0.93 | L62: 0.93 | M62: 0 | N62: 0 | O62: 0 | P62: 0
A63: 847 | B63: 847 | C63: 2366560261014 | E63: 0 | G63: EHV Site Specific (LLFC 847) | H63: 1 | I63: 0.178 | J63: 2265.24 | K63: 0.44 | L63: 0.44 | M63: 0 | N63: 0 | O63: 0 | P63: 0
A64: 848 | B64: 848 | C64: 2300000457377 2366560264112 | E64: 0 | G64: EHV Site Specific (LLFC 848) | H64: 2 | I64: 0.178 | J64: 13311.76 | K64: 1.88 | L64: 1.88 | M64: 0 | N64: 0 | O64: 0 | P64: 0
A65: 849 | B65: 849 | C65: 2300000652292 2376503256010 | E65: 0 | G65: EHV Site Specific (LLFC 849) | H65: 1 | I65: 0.003 | J65: 2335.94 | K65: 0.63 | L65: 0.63 | M65: 0 | N65: 0 | O65: 0 | P65: 0
A66: 850 | B66: 850 | C66: 2300000647051 2300000647060 2376552920013 2376552920022 | E66: 0 | G66: EHV Site Specific (LLFC 850) | H66: 3 | I66: 0.017 | J66: 36593.75 | K66: 0.41 | L66: 0.41 | M66: 0 | N66: 0 | O66: 0 | P66: 0
A67: 851 | B67: 851 | C67: 2376550825013 2380000000543 2380000004097 | E67: 0 | G67: EHV Site Specific (LLFC 851) | H67: 2 | I67: 0.193 | J67: 13311.76 | K67: 1.11 | L67: 1.11 | M67: 0 | N67: 0 | O67: 0 | P67: 0
A68: 852 | B68: 852 | C68: 2380000257932 | D68: 71 | E68: 71 | F68: 2394000016040 | G68: EHV Site Specific (LLFC 852 & 71) | H68: 1 | I68: 0.006 | J68: 2198.49 | K68: 0.36 | L68: 0.36 | M68: -0.006 | N68: 66.74 | O68: 0.05 | P68: 0.05
A69: 853 | B69: 853 | C69: 2380000428837 2380000428846 | E69: 0 | G69: EHV Site Specific (LLFC 853) | H69: 1 | I69: 0.005 | J69: 2335.94 | K69: 2.88 | L69: 2.88 | M69: 0 | N69: 0 | O69: 0 | P69: 0
A70: 854 | B70: 854 | C70: 2380000476088 | D70: 72 | E70: 72 | F70: 2394000022132 | G70: EHV Site Specific (LLFC 854 & 72) | H70: 1 | I70: 0.006 | J70: 2196.17 | K70: 0.36 | L70: 0.36 | M70: -0.006 | N70: 69.07 | O70: 0.05 | P70: 0.05
A71: 855 | B71: 855 | C71: 2380000724195 2380001078977 2380001078986 2380001078995 2380001079001 2380001079321 | E71: 0 | G71: EHV Site Specific (LLFC 855) | H71: 2 | I71: 0.001 | J71: 13594.59 | K71: 1.77 | L71: 1.77 | M71: 0 | N71: 0 | O71: 0 | P71: 0
A72: 856 | B72: 856 | C72: 2380001519750 2380001519760 2380001519779 2380001519788 | E72: 0 | G72: EHV Site Specific (LLFC 856) | H72: 4 | I72: 0.077 | J72: 110728.66 | K72: 0.76 | L72: 0.76 | M72: 0 | N72: 0 | O72: 0 | P72: 0
A73: 857 | B73: 857 | C73: 2300000526046 | E73: 0 | G73: EHV Site Specific (LLFC 857) | H73: 1 | I73: 1.072 | J73: 2265.24 | K73: 0.55 | L73: 0.55 | M73: 0 | N73: 0 | O73: 0 | P73: 0
A74: 858 | B74: 858 | C74: 2326526290016 2326526290025 2380002292920 | E74: 0 | G74: EHV Site Specific (LLFC 858) | H74: 2 | I74: 0.597 | J74: 13311.76 | K74: 0.77 | L74: 0.77 | M74: 0 | N74: 0 | O74: 0 | P74: 0
A75: 859 | B75: 859 | C75: 2336525711011 2336525711020 | E75: 0 | G75: EHV Site Specific (LLFC 859) | H75: 2 | I75: 0.033 | J75: 13311.76 | K75: 0.74 | L75: 0.74 | M75: 0 | N75: 0 | O75: 0 | P75: 0
A76: 861 | B76: 861 | C76: 2300000493180 2300000552125 2336552115017 2336552115026 | E76: 0 | G76: EHV Site Specific (LLFC 861) | H76: 2 | I76: 0.003 | J76: 13453.18 | K76: 1.01 | L76: 1.01 | M76: 0 | N76: 0 | O76: 0 | P76: 0
A77: 862 | B77: 862 | C77: 2300000234163 2300000234172 2336590770013 2336590770022 | E77: 0 | G77: EHV Site Specific (LLFC 862) | H77: 2 | I77: 0 | J77: 13453.18 | K77: 1.6 | L77: 1.6 | M77: 0 | N77: 0 | O77: 0 | P77: 0
A78: 863 | B78: 863 | C78: 2300000234066 2300000234075 2300000234084 2336590810010 | E78: 0 | G78: EHV Site Specific (LLFC 863) | H78: 2 | I78: 0.452 | J78: 13453.18 | K78: 1.65 | L78: 1.65 | M78: 0 | N78: 0 | O78: 0 | P78: 0
A79: 865 | B79: 865 | C79: 2346530035017 2346530035026 | E79: 0 | G79: EHV Site Specific (LLFC 865) | H79: 2 | I79: 0.31 | J79: 13311.76 | K79: 1.94 | L79: 1.94 | M79: 0 | N79: 0 | O79: 0 | P79: 0
A80: 867 | B80: 867 | C80: 2346534433019 2346534433028 | E80: 0 | G80: EHV Site Specific (LLFC 867) | H80: 1 | I80: 0.222 | J80: 2335.94 | K80: 0.95 | L80: 0.95 | M80: 0 | N80: 0 | O80: 0 | P80: 0
A81: 868 | B81: 868 | C81: 2356530030015 2356530030024 | E81: 0 | G81: EHV Site Specific (LLFC 868) | H81: 1 | I81: 0.015 | J81: 2335.94 | K81: 0.96 | L81: 0.96 | M81: 0 | N81: 0 | O81: 0 | P81: 0
A82: 869 | B82: 869 | C82: 2356530321010 2356530321029 | E82: 0 | G82: EHV Site Specific (LLFC 869) | H82: 2 | I82: 0.256 | J82: 13311.76 | K82: 1.87 | L82: 1.87 | M82: 0 | N82: 0 | O82: 0 | P82: 0
A83: 870 | B83: 870 | C83: 2356530620210 2356530620229 | D83: 36 | E83: 36 | F83: 2394000129436 2394000132527 | G83: EHV Site Specific (LLFC 870 & 36) | H83: 0 | I83: 0.016 | J83: 114.34 | K83: 0.35 | L83: 0.35 | M83: -0.016 | N83: 168.49 | O83: 0.05 | P83: 0.05
A84: 871 | B84: 871 | C84: 2366540061017 2366540061026 | E84: 0 | G84: EHV Site Specific (LLFC 871) | H84: 1 | I84: 0.367 | J84: 2335.94 | K84: 1.28 | L84: 1.28 | M84: 0 | N84: 0 | O84: 0 | P84: 0
A85: 872 | B85: 872 | C85: 2300000674055 2300000674064 | E85: 0 | G85: EHV Site Specific (LLFC 872) | H85: 2 | I85: 0.046 | J85: 13311.76 | K85: 1.37 | L85: 1.37 | M85: 0 | N85: 0 | O85: 0 | P85: 0
A86: 873 | B86: 873 | C86: 2300000777530 2366540110116 | E86: 0 | G86: EHV Site Specific (LLFC 873) | H86: 2 | I86: 0.047 | J86: 13311.76 | K86: 0.86 | L86: 0.86 | M86: 0 | N86: 0 | O86: 0 | P86: 0
A87: 874 | B87: 874 | C87: 2300000542828 | D87: 32 | E87: 32 | F87: 2300000542819 | G87: EHV Site Specific (LLFC 874 & 32) | H87: 1 | I87: 0 | J87: 2197.11 | K87: 0.65 | L87: 0.65 | M87: 0 | N87: 68.13 | O87: 0.05 | P87: 0.05
A88: 875 | B88: 875 | C88: 2366560263119 | E88: 0 | G88: EHV Site Specific (LLFC 875) | H88: 2 | I88: 0.178 | J88: 13311.76 | K88: 1.13 | L88: 1.13 | M88: 0 | N88: 0 | O88: 0 | P88: 0
A89: 876 | B89: 876 | C89: 2300000699565 | E89: 0 | G89: EHV Site Specific (LLFC 876) | H89: 1 | I89: 0.031 | J89: 2335.94 | K89: 1.81 | L89: 1.81 | M89: 0 | N89: 0 | O89: 0 | P89: 0
A90: 877 | B90: 877 | C90: 2366591617013 | E90: 0 | G90: EHV Site Specific (LLFC 877) | H90: 2 | I90: 0.045 | J90: 13311.76 | K90: 1.67 | L90: 1.67 | M90: 0 | N90: 0 | O90: 0 | P90: 0
A91: 880 | B91: 880 | C91: 2300000792050 | E91: 0 | G91: EHV Site Specific (LLFC 880) | H91: 1 | I91: 0.039 | J91: 2335.94 | K91: 1.28 | L91: 1.28 | M91: 0 | N91: 0 | O91: 0 | P91: 0
A92: 881 | B92: 881 | C92: 2300000634415 2376552766015 | E92: 0 | G92: EHV Site Specific (LLFC 881) | H92: 2 | I92: 0.039 | J92: 13311.76 | K92: 1.9 | L92: 1.9 | M92: 0 | N92: 0 | O92: 0 | P92: 0
A93: 882 | B93: 882 | C93: 2300000826383 | D93: 69 | E93: 69 | F93: 2300000930377 | G93: EHV Site Specific (LLFC 882 & 69) | H93: 1 | I93: 0.653 | J93: 2480.7 | K93: 0.42 | L93: 0.42 | M93: -0.653 | N93: 2128.76 | O93: 0.05 | P93: 0.05
A94: 883 | B94: 883 | C94: 2376503230011 2376508010017 2390000002440 2390000002459 | E94: 0 | G94: EHV Site Specific (LLFC 883) | H94: 3 | I94: 0.07 | J94: 36452.34 | K94: 1 | L94: 1 | M94: 0 | N94: 0 | O94: 0 | P94: 0
A95: 884 | B95: 884 | C95: 2300000233754 | E95: 0 | G95: EHV Site Specific (LLFC 884) | H95: 1 | I95: 0.01 | J95: 2265.24 | K95: 1.42 | L95: 1.42 | M95: 0 | N95: 0 | O95: 0 | P95: 0
A96: 886 | B96: 886 | C96: 2380001187667 | E96: 0 | G96: EHV Site Specific (LLFC 886) | H96: 1 | I96: 0.142 | J96: 2265.24 | K96: 1.01 | L96: 1.01 | M96: 0 | N96: 0 | O96: 0 | P96: 0
A97: 888 | B97: 888 | C97: 2380001448611 2380001448620 2380001448630 2380001448649 2380001448658 | E97: 0 | G97: EHV Site Specific (LLFC 888) | H97: 3 | I97: 0.129 | J97: 36664.46 | K97: 1.45 | L97: 1.45 | M97: 0 | N97: 0 | O97: 0 | P97: 0
A98: 797 | B98: 797 | C98: 2390000079381 | D98: 99 | E98: 99 | F98: 2394000079398 | G98: EHV Site Specific (LLFC 797 & 99) | H98: 0 | I98: 0.033 | J98: 1.8 | K98: 1.59 | L98: 1.59 | M98: 0 | N98: 0 | O98: 0 | P98: 0
A99: 798 | B99: 798 | C99: 2380001746400 | D99: 61 | E99: 61 | F99: 2394000083311 | G99: EHV Site Specific (LLFC 798 & 61) | H99: 0 | I99: 0.053 | J99: 41.76 | K99: 0.45 | L99: 0.45 | M99: 0 | N99: 3374.26 | O99: 0.05 | P99: 0.05
A100: 799 | B100: 799 | C100: 2380001812550 | D100: 51 | E100: 51 | F100: 2394000089457 | G100: EHV Site Specific (LLFC 799 & 51) | H100: 1 | I100: 0 | J100: 2221.35 | K100: 0.36 | L100: 0.36 | M100: 0 | N100: 2682.26 | O100: 0.05 | P100: 0.05
A101: 821 | B101: 821 | C101: 2380001851381 | D101: 52 | E101: 52 | F101: 2394000093027 | G101: EHV Site Specific (LLFC 821 & 52) | H101: 0 | I101: 0.082 | J101: 2.73 | K101: 0.79 | L101: 0.79 | M101: 0 | N101: 181.74 | O101: 0.05 | P101: 0.05
A102: 822 | B102: 822 | C102: 2380001883036 2380001883045 | D102: 53 | E102: 53 | F102: 2394000095831 2394000095840 | G102: EHV Site Specific (LLFC 822 & 53) | H102: 0 | I102: 0.081 | J102: 8.53 | K102: 0.74 | L102: 0.74 | M102: 0 | N102: 360.41 | O102: 0.05 | P102: 0.05
...

Sheet Annex 2a Import
A1: Note: The list of MPANs / MSIDs provided may be incomplete; the DNO reserves the right to apply the listed charges to any other MPANs / MSIDs associated with the site. Note: This table is automatically populated based on the content of the tab entitled 'Annex 2 Designated EHV Charges'. The timebands are as shown in Annex 2.
A2: =Overview!B4& " - Effective from "&Overview!D4&" - "&Overview!E4&" Designated EHV import charges" -> Northern Powergrid (Yorkshire) Plc - Effective from 1 April 2026 - Final Designated EHV import charges
A4: Import Unique Identifier | B4: LLFC | C4: Import MPANs/MSIDs | D4: Name | E4: ='Annex 2 Designated EHV charges'!I9 -> Import Super Red unit charge (p/kWh) | F4: ='Annex 2 Designated EHV charges'!J9 -> Import fixed charge (p/day) | G4: ='Annex 2 Designated EHV charges'!K9 -> Import capacity charge (p/kVA/day) | H4: ='Annex 2 Designated EHV charges'!L9 -> Import exceeded capacity charge (p/kVA/day)
A5: 750 | B5: =IF($A5="","",VLOOKUP($A5,'Annex 2 Designated EHV charges'!$A:$P,2,0)) -> 750 | C5: =IF($A5="","",VLOOKUP($A5,'Annex 2 Designated EHV charges'!$A:$P,3,0)) -> 2300000599657 2336541294017 | D5: =IF($A5="","",VLOOKUP($A5,'Annex 2 Designated EHV charges'!$A:$P,7,0)) -> EHV Site Specific (LLFC 750) | E5: =IFERROR(IF(VLOOKUP($A5,'Annex 2 Designated EHV charges'!$A:$P,9,FALSE)=0,"",VLOOKUP($A5,'Annex 2 Designated EHV charges'!$A:$P,9,FALSE)),"") -> 0.045 | F5: =IFERROR(IF(VLOOKUP($A5,'Annex 2 Designated EHV charges'!$A:$P,10,FALSE)=0,"",VLOOKUP($A5,'Annex 2 Designated EHV charges'!$A:$P,10,FALSE)),"") -> 103218.15 | G5: =IFERROR(IF(VLOOKUP($A5,'Annex 2 Designated EHV charges'!$A:$P,11,FALSE)=0,"",VLOOKUP($A5,'Annex 2 Designated EHV charges'!$A:$P,11,FALSE)),"") -> 2.85 | H5: =IFERROR(IF(VLOOKUP($A5,'Annex 2 Designated EHV charges'!$A:$P,12,FALSE)=0,"",VLOOKUP($A5,'Annex 2 Designated EHV charges'!$A:$P,12,FALSE)),"") -> 2.85
A6: 751 | B6: =IF($A6="","",VLOOKUP($A6,'Annex 2 Designated EHV charges'!$A:$P,2,0)) -> 751 | C6: =IF($A6="","",VLOOKUP($A6,'Annex 2 Designated EHV charges'!$A:$P,3,0)) -> 2300000702517 2300000702526 2300000702535 2376555002010 2376555002029 2376555002038 | D6: =IF($A6="","",VLOOKUP($A6,'Annex 2 Designated EHV charges'!$A:$P,7,0)) -> EHV Site Specific (LLFC 751) | E6: =IFERROR(IF(VLOOKUP($A6,'Annex 2 Designated EHV charges'!$A:$P,9,FALSE)=0,"",VLOOKUP($A6,'Annex 2 Designated EHV charges'!$A:$P,9,FALSE)),"") -> 0.001 | F6: =IFERROR(IF(VLOOKUP($A6,'Annex 2 Designated EHV charges'!$A:$P,10,FALSE)=0,"",VLOOKUP($A6,'Annex 2 Designated EHV charges'!$A:$P,10,FALSE)),"") -> 108020.24 | G6: =IFERROR(IF(VLOOKUP($A6,'Annex 2 Designated EHV charges'!$A:$P,11,FALSE)=0,"",VLOOKUP($A6,'Annex 2 Designated EHV charges'!$A:$P,11,FALSE)),"") -> 0.92 | H6: =IFERROR(IF(VLOOKUP($A6,'Annex 2 Designated EHV charges'!$A:$P,12,FALSE)=0,"",VLOOKUP($A6,'Annex 2 Designated EHV charges'!$A:$P,12,FALSE)),"") -> 0.92
A7: 753 | B7: =IF($A7="","",VLOOKUP($A7,'Annex 2 Designated EHV charges'!$A:$P,2,0)) -> 753 | C7: =IF($A7="","",VLOOKUP($A7,'Annex 2 Designated EHV charges'!$A:$P,3,0)) -> 2356555555010 | D7: =IF($A7="","",VLOOKUP($A7,'Annex 2 Designated EHV charges'!$A:$P,7,0)) -> EHV Site Specific (LLFC 753 & 90) | E7: =IFERROR(IF(VLOOKUP($A7,'Annex 2 Designated EHV charges'!$A:$P,9,FALSE)=0,"",VLOOKUP($A7,'Annex 2 Designated EHV charges'!$A:$P,9,FALSE)),"") -> 0.042 | F7: =IFERROR(IF(VLOOKUP($A7,'Annex 2 Designated EHV charges'!$A:$P,10,FALSE)=0,"",VLOOKUP($A7,'Annex 2 Designated EHV charges'!$A:$P,10,FALSE)),"") -> 47306.88 | G7: =IFERROR(IF(VLOOKUP($A7,'Annex 2 Designated EHV charges'!$A:$P,11,FALSE)=0,"",VLOOKUP($A7,'Annex 2 Designated EHV charges'!$A:$P,11,FALSE)),"") -> 0.75 | H7: =IFERROR(IF(VLOOKUP($A7,'Annex 2 Designated EHV charges'!$A:$P,12,FALSE)=0,"",VLOOKUP($A7,'Annex 2 Designated EHV charges'!$A:$P,12,FALSE)),"") -> 0.75
A8: 754 | B8: =IF($A8="","",VLOOKUP($A8,'Annex 2 Designated EHV charges'!$A:$P,2,0)) -> 754 | C8: =IF($A8="","",VLOOKUP($A8,'Annex 2 Designated EHV charges'!$A:$P,3,0)) -> 2356555554017 2380002015807 | D8: =IF($A8="","",VLOOKUP($A8,'Annex 2 Designated EHV charges'!$A:$P,7,0)) -> EHV Site Specific (LLFC 754 & 82) | E8: =IFERROR(IF(VLOOKUP($A8,'Annex 2 Designated EHV charges'!$A:$P,9,FALSE)=0,"",VLOOKUP($A8,'Annex 2 Designated EHV charges'!$A:$P,9,FALSE)),"") -> 0.161 | F8: =IFERROR(IF(VLOOKUP($A8,'Annex 2 Designated EHV charges'!$A:$P,10,FALSE)=0,"",VLOOKUP($A8,'Annex 2 Designated EHV charges'!$A:$P,10,FALSE)),"") -> 25592.75 | G8: =IFERROR(IF(VLOOKUP($A8,'Annex 2 Designated EHV charges'!$A:$P,11,FALSE)=0,"",VLOOKUP($A8,'Annex 2 Designated EHV charges'!$A:$P,11,FALSE)),"") -> 0.68 | H8: =IFERROR(IF(VLOOKUP($A8,'Annex 2 Designated EHV charges'!$A:$P,12,FALSE)=0,"",VLOOKUP($A8,'Annex 2 Designated EHV charges'!$A:$P,12,FALSE)),"") -> 0.68
A9: 755 | B9: =IF($A9="","",VLOOKUP($A9,'Annex 2 Designated EHV charges'!$A:$P,2,0)) -> 755 | C9: =IF($A9="","",VLOOKUP($A9,'Annex 2 Designated EHV charges'!$A:$P,3,0)) -> 2316521850010 | D9: =IF($A9="","",VLOOKUP($A9,'Annex 2 Designated EHV charges'!$A:$P,7,0)) -> EHV Site Specific (LLFC 755 & 76) | E9: =IFERROR(IF(VLOOKUP($A9,'Annex 2 Designated EHV charges'!$A:$P,9,FALSE)=0,"",VLOOKUP($A9,'Annex 2 Designated EHV charges'!$A:$P,9,FALSE)),"") -> 0.027 | F9: =IFERROR(IF(VLOOKUP($A9,'Annex 2 Designated EHV charges'!$A:$P,10,FALSE)=0,"",VLOOKUP($A9,'Annex 2 Designated EHV charges'!$A:$P,10,FALSE)),"") -> 18816.11 | G9: =IFERROR(IF(VLOOKUP($A9,'Annex 2 Designated EHV charges'!$A:$P,11,FALSE)=0,"",VLOOKUP($A9,'Annex 2 Designated EHV charges'!$A:$P,11,FALSE)),"") -> 0.95 | H9: =IFERROR(IF(VLOOKUP($A9,'Annex 2 Designated EHV charges'!$A:$P,12,FALSE)=0,"",VLOOKUP($A9,'Annex 2 Designated EHV charges'!$A:$P,12,FALSE)),"") -> 0.95
A10: 756 | B10: =IF($A10="","",VLOOKUP($A10,'Annex 2 Designated EHV charges'!$A:$P,2,0)) -> 756 | C10: =IF($A10="","",VLOOKUP($A10,'Annex 2 Designated EHV charges'!$A:$P,3,0)) -> 2346540436013 | D10: =IF($A10="","",VLOOKUP($A10,'Annex 2 Designated EHV charges'!$A:$P,7,0)) -> EHV Site Specific (LLFC 756 & 75) | E10: =IFERROR(IF(VLOOKUP($A10,'Annex 2 Designated EHV charges'!$A:$P,9,FALSE)=0,"",VLOOKUP($A10,'Annex 2 Designated EHV charges'!$A:$P,9,FALSE)),"") -> 0.014 | F10: =IFERROR(IF(VLOOKUP($A10,'Annex 2 Designated EHV charges'!$A:$P,10,FALSE)=0,"",VLOOKUP($A10,'Annex 2 Designated EHV charges'!$A:$P,10,FALSE)),"") -> 23569.63 | G10: =IFERROR(IF(VLOOKUP($A10,'Annex 2 Designated EHV charges'!$A:$P,11,FALSE)=0,"",VLOOKUP($A10,'Annex 2 Designated EHV charges'!$A:$P,11,FALSE)),"") -> 1.1 | H10: =IFERROR(IF(VLOOKUP($A10,'Annex 2 Designated EHV charges'!$A:$P,12,FALSE)=0,"",VLOOKUP($A10,'Annex 2 Designated EHV charges'!$A:$P,12,FALSE)),"") -> 1.1
A11: 757 | B11: =IF($A11="","",VLOOKUP($A11,'Annex 2 Designated EHV charges'!$A:$P,2,0)) -> 757 | C11: =IF($A11="","",VLOOKUP($A11,'Annex 2 Designated EHV charges'!$A:$P,3,0)) -> 2336566756217 | D11: =IF($A11="","",VLOOKUP($A11,'Annex 2 Designated EHV charges'!$A:$P,7,0)) -> EHV Site Specific (LLFC 757 & 95) | E11: =IFERROR(IF(VLOOKUP($A11,'Annex 2 Designated EHV charges'!$A:$P,9,FALSE)=0,"",VLOOKUP($A11,'Annex 2 Designated EHV charges'!$A:$P,9,FALSE)),"") | F11: =IFERROR(IF(VLOOKUP($A11,'Annex 2 Designated EHV charges'!$A:$P,10,FALSE)=0,"",VLOOKUP($A11,'Annex 2 Designated EHV charges'!$A:$P,10,FALSE)),"") -> 2293.86 | G11: =IFERROR(IF(VLOOKUP($A11,'Annex 2 Designated EHV charges'!$A:$P,11,FALSE)=0,"",VLOOKUP($A11,'Annex 2 Designated EHV charges'!$A:$P,11,FALSE)),"") -> 0.35 | H11: =IFERROR(IF(VLOOKUP($A11,'Annex 2 Designated EHV charges'!$A:$P,12,FALSE)=0,"",VLOOKUP($A11,'Annex 2 Designated EHV charges'!$A:$P,12,FALSE)),"") -> 0.35
A12: 804 | B12: =IF($A12="","",VLOOKUP($A12,'Annex 2 Designated EHV charges'!$A:$P,2,0)) -> 804 | C12: =IF($A12="","",VLOOKUP($A12,'Annex 2 Designated EHV charges'!$A:$P,3,0)) -> MSID_0645 | D12: =IF($A12="","",VLOOKUP($A12,'Annex 2 Designated EHV charges'!$A:$P,7,0)) -> EHV Site Specific (LLFC 804 & 800) | E12: =IFERROR(IF(VLOOKUP($A12,'Annex 2 Designated EHV charges'!$A:$P,9,FALSE)=0,"",VLOOKUP($A12,'Annex 2 Designated EHV charges'!$A:$P,9,FALSE)),"") -> 0.01 | F12: =IFERROR(IF(VLOOKUP($A12,'Annex 2 Designated EHV charges'!$A:$P,10,FALSE)=0,"",VLOOKUP($A12,'Annex 2 Designated EHV charges'!$A:$P,10,FALSE)),"") -> 119342.94 | G12: =IFERROR(IF(VLOOKUP($A12,'Annex 2 Designated EHV charges'!$A:$P,11,FALSE)=0,"",VLOOKUP($A12,'Annex 2 Designated EHV charges'!$A:$P,11,FALSE)),"") -> 1.14 | H12: =IFERROR(IF(VLOOKUP($A12,'Annex 2 Designated EHV charges'!$A:$P,12,FALSE)=0,"",VLOOKUP($A12,'Annex 2 Designated EHV charges'!$A:$P,12,FALSE)),"") -> 1.14
A13: 760 | B13: =IF($A13="","",VLOOKUP($A13,'Annex 2 Designated EHV charges'!$A:$P,2,0)) -> 760 | C13: =IF($A13="","",VLOOKUP($A13,'Annex 2 Designated EHV charges'!$A:$P,3,0)) -> 2300000880966 2376509001013 | D13: =IF($A13="","",VLOOKUP($A13,'Annex 2 Designated EHV charges'!$A:$P,7,0)) -> EHV Site Specific (LLFC 760 & 60) | E13: =IFERROR(IF(VLOOKUP($A13,'Annex 2 Designated EHV charges'!$A:$P,9,FALSE)=0,"",VLOOKUP($A13,'Annex 2 Designated EHV charges'!$A:$P,9,FALSE)),"") | F13: =IFERROR(IF(VLOOKUP($A13,'Annex 2 Designated EHV charges'!$A:$P,10,FALSE)=0,"",VLOOKUP($A13,'Annex 2 Designated EHV charges'!$A:$P,10,FALSE)),"") -> 105037.14 | G13: =IFERROR(IF(VLOOKUP($A13,'Annex 2 Designated EHV charges'!$A:$P,11,FALSE)=0,"",VLOOKUP($A13,'Annex 2 Designated EHV charges'!$A:$P,11,FALSE)),"") -> 0.87 | H13: =IFERROR(IF(VLOOKUP($A13,'Annex 2 Designated EHV charges'!$A:$P,12,FALSE)=0,"",VLOOKUP($A13,'Annex 2 Designated EHV charges'!$A:$P,12,FALSE)),"") -> 0.87
A14: 761 | B14: =IF($A14="","",VLOOKUP($A14,'Annex 2 Designated EHV charges'!$A:$P,2,0)) -> 761 | C14: =IF($A14="","",VLOOKUP($A14,'Annex 2 Designated EHV charges'!$A:$P,3,0)) -> 2300000526686 2336518071011 | D14: =IF($A14="","",VLOOKUP($A14,'Annex 2 Designated EHV charges'!$A:$P,7,0)) -> EHV Site Specific (LLFC 761) | E14: =IFERROR(IF(VLOOKUP($A14,'Annex 2 Designated EHV charges'!$A:$P,9,FALSE)=0,"",VLOOKUP($A14,'Annex 2 Designated EHV charges'!$A:$P,9,FALSE)),"") | F14: =IFERROR(IF(VLOOKUP($A14,'Annex 2 Designated EHV charges'!$A:$P,10,FALSE)=0,"",VLOOKUP($A14,'Annex 2 Designated EHV charges'!$A:$P,10,FALSE)),"") -> 36679.86 | G14: =IFERROR(IF(VLOOKUP($A14,'Annex 2 Designated EHV charges'!$A:$P,11,FALSE)=0,"",VLOOKUP($A14,'Annex 2 Designated EHV charges'!$A:$P,11,FALSE)),"") -> 0.67 | H14: =IFERROR(IF(VLOOKUP($A14,'Annex 2 Designated EHV charges'!$A:$P,12,FALSE)=0,"",VLOOKUP($A14,'Annex 2 Designated EHV charges'!$A:$P,12,FALSE)),"") -> 0.67
A15: 762 | B15: =IF($A15="","",VLOOKUP($A15,'Annex 2 Designated EHV charges'!$A:$P,2,0)) -> 762 | C15: =IF($A15="","",VLOOKUP($A15,'Annex 2 Designated EHV charges'!$A:$P,3,0)) -> 2300000457400 | D15: =IF($A15="","",VLOOKUP($A15,'Annex 2 Designated EHV charges'!$A:$P,7,0)) -> EHV Site Specific (LLFC 762 & 62) | E15: =IFERROR(IF(VLOOKUP($A15,'Annex 2 Designated EHV charges'!$A:$P,9,FALSE)=0,"",VLOOKUP($A15,'Annex 2 Designated EHV charges'!$A:$P,9,FALSE)),"") | F15: =IFERROR(IF(VLOOKUP($A15,'Annex 2 Designated EHV charges'!$A:$P,10,FALSE)=0,"",VLOOKUP($A15,'Annex 2 Designated EHV charges'!$A:$P,10,FALSE)),"") -> 40.02 | G15: =IFERROR(IF(VLOOKUP($A15,'Annex 2 Designated EHV charges'!$A:$P,11,FALSE)=0,"",VLOOKUP($A15,'Annex 2 Designated EHV charges'!$A:$P,11,FALSE)),"") -> 0.42 | H15: =IFERROR(IF(VLOOKUP($A15,'Annex 2 Designated EHV charges'!$A:$P,12,FALSE)=0,"",VLOOKUP($A15,'Annex 2 Designated EHV charges'!$A:$P,12,FALSE)),"") -> 0.42
A16: 763 | B16: =IF($A16="","",VLOOKUP($A16,'Annex 2 Designated EHV charges'!$A:$P,2,0)) -> 763 | C16: =IF($A16="","",VLOOKUP($A16,'Annex 2 Designated EHV charges'!$A:$P,3,0)) -> MSID_7376 MSID_7542 | D16: =IF($A16="","",VLOOKUP($A16,'Annex 2 Designated EHV charges'!$A:$P,7,0)) -> EHV Site Specific (LLFC 763 & 80) | E16: =IFERROR(IF(VLOOKUP($A16,'Annex 2 Designated EHV charges'!$A:$P,9,FALSE)=0,"",VLOOKUP($A16,'Annex 2 Designated EHV charges'!$A:$P,9,FALSE)),"") -> 0.003 | F16: =IFERROR(IF(VLOOKUP($A16,'Annex 2 Designated EHV charges'!$A:$P,10,FALSE)=0,"",VLOOKUP($A16,'Annex 2 Designated EHV charges'!$A:$P,10,FALSE)),"") -> 101.82 | G16: =IFERROR(IF(VLOOKUP($A16,'Annex 2 Designated EHV charges'!$A:$P,11,FALSE)=0,"",VLOOKUP($A16,'Annex 2 Designated EHV charges'!$A:$P,11,FALSE)),"") -> 0.5 | H16: =IFERROR(IF(VLOOKUP($A16,'Annex 2 Designated EHV charges'!$A:$P,12,FALSE)=0,"",VLOOKUP($A16,'Annex 2 Designated EHV charges'!$A:$P,12,FALSE)),"") -> 0.5
... A172: 725 | B172: =IF($A172="","",VLOOKUP($A172,'Annex 2 Designated EHV charges'!$A:$P,2,0)) -> 725 | C172: =IF($A172="","",VLOOKUP($A172,'Annex 2 Designated EHV charges'!$A:$P,3,0)) -> MSID_7588 | D172: =IF($A172="","",VLOOKUP($A172,'Annex 2 Designated EHV charges'!$A:$P,7,0)) -> EHV Site Specific (LLFC 725 & 510) | E172: =IFERROR(IF(VLOOKUP($A172,'Annex 2 Designated EHV charges'!$A:$P,9,FALSE)=0,"",VLOOKUP($A172,'Annex 2 Designated EHV charges'!$A:$P,9,FALSE)),"") | F172: =IFERROR(IF(VLOOKUP($A172,'Annex 2 Designated EHV charges'!$A:$P,10,FALSE)=0,"",VLOOKUP($A172,'Annex 2 Designated EHV charges'!$A:$P,10,FALSE)),"") -> 3009.74 | G172: =IFERROR(IF(VLOOKUP($A172,'Annex 2 Designated EHV charges'!$A:$P,11,FALSE)=0,"",VLOOKUP($A172,'Annex 2 Designated EHV charges'!$A:$P,11,FALSE)),"") -> 1.33 | H172: =IFERROR(IF(VLOOKUP($A172,'Annex 2 Designated EHV charges'!$A:$P,12,FALSE)=0,"",VLOOKUP($A172,'Annex 2 Designated EHV charges'!$A:$P,12,FALSE)),"") -> 1.33

Sheet Annex 2b Export
A1: Note: The list of MPANs / MSIDs provided may be incomplete; the DNO reserves the right to apply the listed charges to any other MPANs / MSIDs associated with the site. Note: This table is automatically populated based on the content of the tab entitled 'Annex 2 Designated EHV Charges'. The timebands are as shown in Annex 2.
A2: =Overview!B4& " - Effective from "&Overview!D4&" - "&Overview!E4&" Designated EHV export charges" -> Northern Powergrid (Yorkshire) Plc - Effective from 1 April 2026 - Final Designated EHV export charges
A4: Export Unique Identifier | B4: LLFC | C4: Export MPANs/MSIDs | D4: Name | E4: ='Annex 2 Designated EHV charges'!M9 -> Export Super Red unit charge (p/kWh) | F4: ='Annex 2 Designated EHV charges'!N9 -> Export fixed charge (p/day) | G4: ='Annex 2 Designated EHV charges'!O9 -> Export capacity charge (p/kVA/day) | H4: ='Annex 2 Designated EHV charges'!P9 -> Export exceeded capacity charge (p/kVA/day)
A5: 90 | B5: =IF($A5="","",VLOOKUP($A5,'Annex 2 Designated EHV charges'!$D:$P,2,0)) -> 90 | C5: =IF($A5="","",VLOOKUP($A5,'Annex 2 Designated EHV charges'!$D:$P,3,0)) -> 2394000039650 | D5: =IF($A5="","",VLOOKUP($A5,'Annex 2 Designated EHV charges'!$D:$P,4,0)) -> EHV Site Specific (LLFC 753 & 90) | E5: =IFERROR(IF(VLOOKUP($A5,'Annex 2 Designated EHV charges'!$D:$P,10,FALSE)=0,0,VLOOKUP($A5,'Annex 2 Designated EHV charges'!$D:$P,10,FALSE)),"") -> 0 | F5: =IFERROR(IF(VLOOKUP($A5,'Annex 2 Designated EHV charges'!$D:$P,11,FALSE)=0,0,VLOOKUP($A5,'Annex 2 Designated EHV charges'!$D:$P,11,FALSE)),"") -> 183.27 | G5: =IFERROR(IF(VLOOKUP($A5,'Annex 2 Designated EHV charges'!$D:$P,12,FALSE)=0,0,VLOOKUP($A5,'Annex 2 Designated EHV charges'!$D:$P,12,FALSE)),"") -> 0.05 | H5: =IFERROR(IF(VLOOKUP($A5,'Annex 2 Designated EHV charges'!$D:$P,13,FALSE)=0,0,VLOOKUP($A5,'Annex 2 Designated EHV charges'!$D:$P,13,FALSE)),"") -> 0.05
A6: 82 | B6: =IF($A6="","",VLOOKUP($A6,'Annex 2 Designated EHV charges'!$D:$P,2,0)) -> 82 | C6: =IF($A6="","",VLOOKUP($A6,'Annex 2 Designated EHV charges'!$D:$P,3,0)) -> 2394000039660 2394000110620 | D6: =IF($A6="","",VLOOKUP($A6,'Annex 2 Designated EHV charges'!$D:$P,4,0)) -> EHV Site Specific (LLFC 754 & 82) | E6: =IFERROR(IF(VLOOKUP($A6,'Annex 2 Designated EHV charges'!$D:$P,10,FALSE)=0,0,VLOOKUP($A6,'Annex 2 Designated EHV charges'!$D:$P,10,FALSE)),"") -> 0 | F6: =IFERROR(IF(VLOOKUP($A6,'Annex 2 Designated EHV charges'!$D:$P,11,FALSE)=0,0,VLOOKUP($A6,'Annex 2 Designated EHV charges'!$D:$P,11,FALSE)),"") -> 621.12 | G6: =IFERROR(IF(VLOOKUP($A6,'Annex 2 Designated EHV charges'!$D:$P,12,FALSE)=0,0,VLOOKUP($A6,'Annex 2 Designated EHV charges'!$D:$P,12,FALSE)),"") -> 0.05 | H6: =IFERROR(IF(VLOOKUP($A6,'Annex 2 Designated EHV charges'!$D:$P,13,FALSE)=0,0,VLOOKUP($A6,'Annex 2 Designated EHV charges'!$D:$P,13,FALSE)),"") -> 0.05
A7: 76 | B7: =IF($A7="","",VLOOKUP($A7,'Annex 2 Designated EHV charges'!$D:$P,2,0)) -> 76 | C7: =IF($A7="","",VLOOKUP($A7,'Annex 2 Designated EHV charges'!$D:$P,3,0)) -> 2394000039641 | D7: =IF($A7="","",VLOOKUP($A7,'Annex 2 Designated EHV charges'!$D:$P,4,0)) -> EHV Site Specific (LLFC 755 & 76) | E7: =IFERROR(IF(VLOOKUP($A7,'Annex 2 Designated EHV charges'!$D:$P,10,FALSE)=0,0,VLOOKUP($A7,'Annex 2 Designated EHV charges'!$D:$P,10,FALSE)),"") -> 0 | F7: =IFERROR(IF(VLOOKUP($A7,'Annex 2 Designated EHV charges'!$D:$P,11,FALSE)=0,0,VLOOKUP($A7,'Annex 2 Designated EHV charges'!$D:$P,11,FALSE)),"") -> 564.58 | G7: =IFERROR(IF(VLOOKUP($A7,'Annex 2 Designated EHV charges'!$D:$P,12,FALSE)=0,0,VLOOKUP($A7,'Annex 2 Designated EHV charges'!$D:$P,12,FALSE)),"") -> 0.05 | H7: =IFERROR(IF(VLOOKUP($A7,'Annex 2 Designated EHV charges'!$D:$P,13,FALSE)=0,0,VLOOKUP($A7,'Annex 2 Designated EHV charges'!$D:$P,13,FALSE)),"") -> 0.05
A8: 75 | B8: =IF($A8="","",VLOOKUP($A8,'Annex 2 Designated EHV charges'!$D:$P,2,0)) -> 75 | C8: =IF($A8="","",VLOOKUP($A8,'Annex 2 Designated EHV charges'!$D:$P,3,0)) -> 2394000039679 | D8: =IF($A8="","",VLOOKUP($A8,'Annex 2 Designated EHV charges'!$D:$P,4,0)) -> EHV Site Specific (LLFC 756 & 75) | E8: =IFERROR(IF(VLOOKUP($A8,'Annex 2 Designated EHV charges'!$D:$P,10,FALSE)=0,0,VLOOKUP($A8,'Annex 2 Designated EHV charges'!$D:$P,10,FALSE)),"") -> 0 | F8: =IFERROR(IF(VLOOKUP($A8,'Annex 2 Designated EHV charges'!$D:$P,11,FALSE)=0,0,VLOOKUP($A8,'Annex 2 Designated EHV charges'!$D:$P,11,FALSE)),"") -> 779.95 | G8: =IFERROR(IF(VLOOKUP($A8,'Annex 2 Designated EHV charges'!$D:$P,12,FALSE)=0,0,VLOOKUP($A8,'Annex 2 Designated EHV charges'!$D:$P,12,FALSE)),"") -> 0.05 | H8: =IFERROR(IF(VLOOKUP($A8,'Annex 2 Designated EHV charges'!$D:$P,13,FALSE)=0,0,VLOOKUP($A8,'Annex 2 Designated EHV charges'!$D:$P,13,FALSE)),"") -> 0.05
A9: 95 | B9: =IF($A9="","",VLOOKUP($A9,'Annex 2 Designated EHV charges'!$D:$P,2,0)) -> 95 | C9: =IF($A9="","",VLOOKUP($A9,'Annex 2 Designated EHV charges'!$D:$P,3,0)) -> 2394000060226 | D9: =IF($A9="","",VLOOKUP($A9,'Annex 2 Designated EHV charges'!$D:$P,4,0)) -> EHV Site Specific (LLFC 757 & 95) | E9: =IFERROR(IF(VLOOKUP($A9,'Annex 2 Designated EHV charges'!$D:$P,10,FALSE)=0,0,VLOOKUP($A9,'Annex 2 Designated EHV charges'!$D:$P,10,FALSE)),"") -> -0.001 | F9: =IFERROR(IF(VLOOKUP($A9,'Annex 2 Designated EHV charges'!$D:$P,11,FALSE)=0,0,VLOOKUP($A9,'Annex 2 Designated EHV charges'!$D:$P,11,FALSE)),"") -> 1100.61 | G9: =IFERROR(IF(VLOOKUP($A9,'Annex 2 Designated EHV charges'!$D:$P,12,FALSE)=0,0,VLOOKUP($A9,'Annex 2 Designated EHV charges'!$D:$P,12,FALSE)),"") -> 0.05 | H9: =IFERROR(IF(VLOOKUP($A9,'Annex 2 Designated EHV charges'!$D:$P,13,FALSE)=0,0,VLOOKUP($A9,'Annex 2 Designated EHV charges'!$D:$P,13,FALSE)),"") -> 0.05
A10: 800 | B10: =IF($A10="","",VLOOKUP($A10,'Annex 2 Designated EHV charges'!$D:$P,2,0)) -> 800 | C10: =IF($A10="","",VLOOKUP($A10,'Annex 2 Designated EHV charges'!$D:$P,3,0)) -> MSID_0645 | D10: =IF($A10="","",VLOOKUP($A10,'Annex 2 Designated EHV charges'!$D:$P,4,0)) -> EHV Site Specific (LLFC 804 & 800) | E10: =IFERROR(IF(VLOOKUP($A10,'Annex 2 Designated EHV charges'!$D:$P,10,FALSE)=0,0,VLOOKUP($A10,'Annex 2 Designated EHV charges'!$D:$P,10,FALSE)),"") -> -0.008 | F10: =IFERROR(IF(VLOOKUP($A10,'Annex 2 Designated EHV charges'!$D:$P,11,FALSE)=0,0,VLOOKUP($A10,'Annex 2 Designated EHV charges'!$D:$P,11,FALSE)),"") -> 2782.58 | G10: =IFERROR(IF(VLOOKUP($A10,'Annex 2 Designated EHV charges'!$D:$P,12,FALSE)=0,0,VLOOKUP($A10,'Annex 2 Designated EHV charges'!$D:$P,12,FALSE)),"") -> 0.05 | H10: =IFERROR(IF(VLOOKUP($A10,'Annex 2 Designated EHV charges'!$D:$P,13,FALSE)=0,0,VLOOKUP($A10,'Annex 2 Designated EHV charges'!$D:$P,13,FALSE)),"") -> 0.05
A11: 60 | B11: =IF($A11="","",VLOOKUP($A11,'Annex 2 Designated EHV charges'!$D:$P,2,0)) -> 60 | C11: =IF($A11="","",VLOOKUP($A11,'Annex 2 Designated EHV charges'!$D:$P,3,0)) -> 2300000233736 2300000880975 | D11: =IF($A11="","",VLOOKUP($A11,'Annex 2 Designated EHV charges'!$D:$P,4,0)) -> EHV Site Specific (LLFC 760 & 60) | E11: =IFERROR(IF(VLOOKUP($A11,'Annex 2 Designated EHV charges'!$D:$P,10,FALSE)=0,0,VLOOKUP($A11,'Annex 2 Designated EHV charges'!$D:$P,10,FALSE)),"") -> 0 | F11: =IFERROR(IF(VLOOKUP($A11,'Annex 2 Designated EHV charges'!$D:$P,11,FALSE)=0,0,VLOOKUP($A11,'Annex 2 Designated EHV charges'!$D:$P,11,FALSE)),"") -> 1212.66 | G11: =IFERROR(IF(VLOOKUP($A11,'Annex 2 Designated EHV charges'!$D:$P,12,FALSE)=0,0,VLOOKUP($A11,'Annex 2 Designated EHV charges'!$D:$P,12,FALSE)),"") -> 0.05 | H11: =IFERROR(IF(VLOOKUP($A11,'Annex 2 Designated EHV charges'!$D:$P,13,FALSE)=0,0,VLOOKUP($A11,'Annex 2 Designated EHV charges'!$D:$P,13,FALSE)),"") -> 0.05
A12: 62 | B12: =IF($A12="","",VLOOKUP($A12,'Annex 2 Designated EHV charges'!$D:$P,2,0)) -> 62 | C12: =IF($A12="","",VLOOKUP($A12,'Annex 2 Designated EHV charges'!$D:$P,3,0)) -> 2300000457410 | D12: =IF($A12="","",VLOOKUP($A12,'Annex 2 Designated EHV charges'!$D:$P,4,0)) -> EHV Site Specific (LLFC 762 & 62) | E12: =IFERROR(IF(VLOOKUP($A12,'Annex 2 Designated EHV charges'!$D:$P,10,FALSE)=0,0,VLOOKUP($A12,'Annex 2 Designated EHV charges'!$D:$P,10,FALSE)),"") -> -0.032 | F12: =IFERROR(IF(VLOOKUP($A12,'Annex 2 Designated EHV charges'!$D:$P,11,FALSE)=0,0,VLOOKUP($A12,'Annex 2 Designated EHV charges'!$D:$P,11,FALSE)),"") -> 453.52 | G12: =IFERROR(IF(VLOOKUP($A12,'Annex 2 Designated EHV charges'!$D:$P,12,FALSE)=0,0,VLOOKUP($A12,'Annex 2 Designated EHV charges'!$D:$P,12,FALSE)),"") -> 0.05 | H12: =IFERROR(IF(VLOOKUP($A12,'Annex 2 Designated EHV charges'!$D:$P,13,FALSE)=0,0,VLOOKUP($A12,'Annex 2 Designated EHV charges'!$D:$P,13,FALSE)),"") -> 0.05
A13: 80 | B13: =IF($A13="","",VLOOKUP($A13,'Annex 2 Designated EHV charges'!$D:$P,2,0)) -> 80 | C13: =IF($A13="","",VLOOKUP($A13,'Annex 2 Designated EHV charges'!$D:$P,3,0)) -> MSID_7377 MSID_7543 | D13: =IF($A13="","",VLOOKUP($A13,'Annex 2 Designated EHV charges'!$D:$P,4,0)) -> EHV Site Specific (LLFC 763 & 80) | E13: =IFERROR(IF(VLOOKUP($A13,'Annex 2 Designated EHV charges'!$D:$P,10,FALSE)=0,0,VLOOKUP($A13,'Annex 2 Designated EHV charges'!$D:$P,10,FALSE)),"") -> -0.002 | F13: =IFERROR(IF(VLOOKUP($A13,'Annex 2 Designated EHV charges'!$D:$P,11,FALSE)=0,0,VLOOKUP($A13,'Annex 2 Designated EHV charges'!$D:$P,11,FALSE)),"") -> 1694.65 | G13: =IFERROR(IF(VLOOKUP($A13,'Annex 2 Designated EHV charges'!$D:$P,12,FALSE)=0,0,VLOOKUP($A13,'Annex 2 Designated EHV charges'!$D:$P,12,FALSE)),"") -> 0.05 | H13: =IFERROR(IF(VLOOKUP($A13,'Annex 2 Designated EHV charges'!$D:$P,13,FALSE)=0,0,VLOOKUP($A13,'Annex 2 Designated EHV charges'!$D:$P,13,FALSE)),"") -> 0.05
A14: 66 | B14: =IF($A14="","",VLOOKUP($A14,'Annex 2 Designated EHV charges'!$D:$P,2,0)) -> 66 | C14: =IF($A14="","",VLOOKUP($A14,'Annex 2 Designated EHV charges'!$D:$P,3,0)) -> 2300000233912 2300000996990 | D14: =IF($A14="","",VLOOKUP($A14,'Annex 2 Designated EHV charges'!$D:$P,4,0)) -> EHV Site Specific (LLFC 766 & 66) | E14: =IFERROR(IF(VLOOKUP($A14,'Annex 2 Designated EHV charges'!$D:$P,10,FALSE)=0,0,VLOOKUP($A14,'Annex 2 Designated EHV charges'!$D:$P,10,FALSE)),"") -> 0 | F14: =IFERROR(IF(VLOOKUP($A14,'Annex 2 Designated EHV charges'!$D:$P,11,FALSE)=0,0,VLOOKUP($A14,'Annex 2 Designated EHV charges'!$D:$P,11,FALSE)),"") -> 209.85 | G14: =IFERROR(IF(VLOOKUP($A14,'Annex 2 Designated EHV charges'!$D:$P,12,FALSE)=0,0,VLOOKUP($A14,'Annex 2 Designated EHV charges'!$D:$P,12,FALSE)),"") -> 0.05 | H14: =IFERROR(IF(VLOOKUP($A14,'Annex 2 Designated EHV charges'!$D:$P,13,FALSE)=0,0,VLOOKUP($A14,'Annex 2 Designated EHV charges'!$D:$P,13,FALSE)),"") -> 0.05
A15: 128 | B15: =IF($A15="","",VLOOKUP($A15,'Annex 2 Designated EHV charges'!$D:$P,2,0)) -> 128 | C15: =IF($A15="","",VLOOKUP($A15,'Annex 2 Designated EHV charges'!$D:$P,3,0)) -> 2394000133317 2394000139114 | D15: =IF($A15="","",VLOOKUP($A15,'Annex 2 Designated EHV charges'!$D:$P,4,0)) -> EHV Site Specific (LLFC 769 & 128) | E15: =IFERROR(IF(VLOOKUP($A15,'Annex 2 Designated EHV charges'!$D:$P,10,FALSE)=0,0,VLOOKUP($A15,'Annex 2 Designated EHV charges'!$D:$P,10,FALSE)),"") -> 0 | F15: =IFERROR(IF(VLOOKUP($A15,'Annex 2 Designated EHV charges'!$D:$P,11,FALSE)=0,0,VLOOKUP($A15,'Annex 2 Designated EHV charges'!$D:$P,11,FALSE)),"") -> 0 | G15: =IFERROR(IF(VLOOKUP($A15,'Annex 2 Designated EHV charges'!$D:$P,12,FALSE)=0,0,VLOOKUP($A15,'Annex 2 Designated EHV charges'!$D:$P,12,FALSE)),"") -> 0.05 | H15: =IFERROR(IF(VLOOKUP($A15,'Annex 2 Designated EHV charges'!$D:$P,13,FALSE)=0,0,VLOOKUP($A15,'Annex 2 Designated EHV charges'!$D:$P,13,FALSE)),"") -> 0.05
A16: 92 | B16: =IF($A16="","",VLOOKUP($A16,'Annex 2 Designated EHV charges'!$D:$P,2,0)) -> 92 | C16: =IF($A16="","",VLOOKUP($A16,'Annex 2 Designated EHV charges'!$D:$P,3,0)) -> 2394000019176 | D16: =IF($A16="","",VLOOKUP($A16,'Annex 2 Designated EHV charges'!$D:$P,4,0)) -> EHV Site Specific (LLFC 771 & 92) | E16: =IFERROR(IF(VLOOKUP($A16,'Annex 2 Designated EHV charges'!$D:$P,10,FALSE)=0,0,VLOOKUP($A16,'Annex 2 Designated EHV charges'!$D:$P,10,FALSE)),"") -> 0 | F16: =IFERROR(IF(VLOOKUP($A16,'Annex 2 Designated EHV charges'!$D:$P,11,FALSE)=0,0,VLOOKUP($A16,'Annex 2 Designated EHV charges'!$D:$P,11,FALSE)),"") -> 0 | G16: =IFERROR(IF(VLOOKUP($A16,'Annex 2 Designated EHV charges'!$D:$P,12,FALSE)=0,0,VLOOKUP($A16,'Annex 2 Designated EHV charges'!$D:$P,12,FALSE)),"") -> 0.05 | H16: =IFERROR(IF(VLOOKUP($A16,'Annex 2 Designated EHV charges'!$D:$P,13,FALSE)=0,0,VLOOKUP($A16,'Annex 2 Designated EHV charges'!$D:$P,13,FALSE)),"") -> 0.05
... A111: 510 | B111: =IF($A111="","",VLOOKUP($A111,'Annex 2 Designated EHV charges'!$D:$P,2,0)) -> 510 | C111: =IF($A111="","",VLOOKUP($A111,'Annex 2 Designated EHV charges'!$D:$P,3,0)) -> MSID_7589 | D111: =IF($A111="","",VLOOKUP($A111,'Annex 2 Designated EHV charges'!$D:$P,4,0)) -> EHV Site Specific (LLFC 725 & 510) | E111: =IFERROR(IF(VLOOKUP($A111,'Annex 2 Designated EHV charges'!$D:$P,10,FALSE)=0,0,VLOOKUP($A111,'Annex 2 Designated EHV charges'!$D:$P,10,FALSE)),"") -> 0 | F111: =IFERROR(IF(VLOOKUP($A111,'Annex 2 Designated EHV charges'!$D:$P,11,FALSE)=0,0,VLOOKUP($A111,'Annex 2 Designated EHV charges'!$D:$P,11,FALSE)),"") -> 3009.74 | G111: =IFERROR(IF(VLOOKUP($A111,'Annex 2 Designated EHV charges'!$D:$P,12,FALSE)=0,0,VLOOKUP($A111,'Annex 2 Designated EHV charges'!$D:$P,12,FALSE)),"") -> 0.05 | H111: =IFERROR(IF(VLOOKUP($A111,'Annex 2 Designated EHV charges'!$D:$P,13,FALSE)=0,0,VLOOKUP($A111,'Annex 2 Designated EHV charges'!$D:$P,13,FALSE)),"") -> 0.05

Sheet Annex 3 Preserved charges
A1: Back to Overview
A2: =Overview!B4& " - Effective from "&Overview!D4&" - "&Overview!E4&" LV and HV tariffs" -> Northern Powergrid (Yorkshire) Plc - Effective from 1 April 2026 - Final LV and HV tariffs
A3: NHH preserved charges/additional LLFCs
B4: Closed LLFCs | C4: PCs | D4: Unit charge 1 (NHH) p/kWh | E4: Unit charge 2 (NHH) p/kWh | F4: Fixed charge p/MPAN/day
A6: Notes:
A11: HH preserved charges/additional LLFCs
B12: Closed LLFCs | C12: PCs | D12: Red/black charge (HH) p/kWh | E12: Amber/yellow charge (HH) p/kWh | F12: Green charge (HH) p/kWh | G12: Fixed charge p/MPAN/day | H12: Capacity charge p/kVA/day | I12: Exceeded capacity charge p/kVA/day | J12: Reactive power charge p/kVArh
A14: Notes: | B14: Time periods
A24: =Overview!B4&" has no preserved charges/additional LLFCs" -> Northern Powergrid (Yorkshire) Plc has no preserved charges/additional LLFCs

Sheet Annex 4 LDNO charges
A1: Back to Overview
A2: =Overview!B4& " - Effective from "&Overview!D4&" - "&Overview!E4&" LDNO tariffs" -> Northern Powergrid (Yorkshire) Plc - Effective from 1 April 2026 - Final LDNO tariffs
A4: Time Bands for LV and HV Designated Properties | F4: Time Bands for Unmetered Properties
A5: Time periods | B5: Red Time Band | C5: Amber Time Band | D5: Green Time Band | H5: Black Time Band | I5: Yellow Time Band | J5: Green Time Band
A6: Monday to Friday (Including Bank Holidays) All Year | B6: 16:00 to 19:30 | C6: 08:00 to 16:00 19:30 to 22:00 | D6: 00:00 to 08:00 22:00 to 24:00 | F6: Monday to Friday (Including Bank Holidays) November to February Inclusive | H6: 16:00 to 19:30 | I6: 08:00 to 16:00 19:30 to 22:00 | J6: 00:00 to 08:00 22:00 to 24:00
A7: Saturday and Sunday All Year | B7: 0 | C7: 0 | D7: 00:00 to 24:00 | F7: Monday to Friday (Including Bank Holidays) April to October Inclusive and March | H7: 0 | I7: 08:00 to 22:00 | J7: 00:00 to 08:00 22:00 to 24:00
A8: Notes | B8: All the above times are in UK Clock time | F8: Saturday and Sunday All year | H8: 0 | I8: 0 | J8: 00:00 to 24:00
F9: Notes | H9: All the above times are in UK Clock time
A11: Tariff name | B11: Unique billing identifier | C11: PCs | D11: ='Annex 1 LV, HV and UMS charges'!D11 -> Red/black unit charge p/kWh | E11: ='Annex 1 LV, HV and UMS charges'!E11 -> Amber/yellow unit charge p/kWh | F11: ='Annex 1 LV, HV and UMS charges'!F11 -> Green unit charge p/kWh | G11: ='Annex 1 LV, HV and UMS charges'!G11 -> Fixed charge p/MPAN/day | H11: ='Annex 1 LV, HV and UMS charges'!H11 -> Capacity charge p/kVA/day | I11: ='Annex 1 LV, HV and UMS charges'!I11 -> Exceeded capacity charge p/kVA/day | J11: ='Annex 1 LV, HV and UMS charges'!J11 -> Reactive power charge p/kVArh
A12: LDNO LV: Domestic Aggregated or CT with Residual | B12: 150, 151, 148 | C12: 0, 1, 2 | D12: 4.034 | E12: 1.081 | F12: 0.126 | G12: 10.72 | H12: 0 | I12: 0 | J12: 0
A13: LDNO LV: Domestic Aggregated (related MPAN) | B13: 152 | C13: 2 | D13: 4.034 | E13: 1.081 | F13: 0.126 | G13: 0 | H13: 0 | I13: 0 | J13: 0
A14: LDNO LV: Non-Domestic Aggregated or CT No Residual | B14: 201 | C14: 0, 3, 4, 5-8 | D14: 4.854 | E14: 1.301 | F14: 0.152 | G14: 7.2 | H14: 0 | I14: 0 | J14: 0
A15: LDNO LV: Non-Domestic Aggregated or CT Band 1 | B15: 153, 154, 156, 149 | C15: 0, 3, 4, 5-8 | D15: 4.854 | E15: 1.301 | F15: 0.152 | G15: 10.6 | H15: 0 | I15: 0 | J15: 0
A16: LDNO LV: Non-Domestic Aggregated or CT Band 2 | B16: 202 | C16: 0, 3, 4, 5-8 | D16: 4.854 | E16: 1.301 | F16: 0.152 | G16: 15.68 | H16: 0 | I16: 0 | J16: 0
A17: LDNO LV: Non-Domestic Aggregated or CT Band 3 | B17: 203 | C17: 0, 3, 4, 5-8 | D17: 4.854 | E17: 1.301 | F17: 0.152 | G17: 24.94 | H17: 0 | I17: 0 | J17: 0
A18: LDNO LV: Non-Domestic Aggregated or CT Band 4 | B18: 204 | C18: 0, 3, 4, 5-8 | D18: 4.854 | E18: 1.301 | F18: 0.152 | G18: 56.53 | H18: 0 | I18: 0 | J18: 0
A19: LDNO LV: Non-Domestic Aggregated (related MPAN) | B19: 155 | C19: 4 | D19: 4.854 | E19: 1.301 | F19: 0.152 | G19: 0 | H19: 0 | I19: 0 | J19: 0
A20: LDNO LV: LV Site Specific No Residual | B20: 205 | C20: 0 | D20: 3.465 | E20: 0.908 | F20: 0.102 | G20: 9.57 | H20: 2.27 | I20: 2.27 | J20: 0.07
A21: LDNO LV: LV Site Specific Band 1 | B21: 157 | C21: 0 | D21: 3.465 | E21: 0.908 | F21: 0.102 | G21: 92.03 | H21: 2.27 | I21: 2.27 | J21: 0.07
A22: LDNO LV: LV Site Specific Band 2 | B22: 206 | C22: 0 | D22: 3.465 | E22: 0.908 | F22: 0.102 | G22: 174.57 | H22: 2.27 | I22: 2.27 | J22: 0.07
A23: LDNO LV: LV Site Specific Band 3 | B23: 207 | C23: 0 | D23: 3.465 | E23: 0.908 | F23: 0.102 | G23: 257.98 | H23: 2.27 | I23: 2.27 | J23: 0.07
A24: LDNO LV: LV Site Specific Band 4 | B24: 208 | C24: 0 | D24: 3.465 | E24: 0.908 | F24: 0.102 | G24: 526.87 | H24: 2.27 | I24: 2.27 | J24: 0.07
A25: LDNO LV: Unmetered Supplies | B25: 132, 133, 134, 135, 170 | C25: 0, 1, 8 | D25: 12.19 | E25: 1.423 | F25: 0.529 | G25: 0 | H25: 0 | I25: 0 | J25: 0
A26: LDNO LV: LV Generation Aggregated | B26: 172 | C26: 0, 8 | D26: -4.895 | E26: -1.312 | F26: -0.153 | G26: 0 | H26: 0 | I26: 0 | J26: 0
A27: LDNO LV: LV Generation Site Specific | B27: 173, 174 | C27: 0 | D27: -4.895 | E27: -1.312 | F27: -0.153 | G27: 0 | H27: 0 | I27: 0 | J27: 0.091
A28: LDNO HV: Domestic Aggregated or CT with Residual | B28: 158, 159, 398 | C28: 0, 1, 2 | D28: 2.787 | E28: 0.747 | F28: 0.087 | G28: 7.41 | H28: 0 | I28: 0 | J28: 0
A29: LDNO HV: Domestic Aggregated (Related MPAN) | B29: 160 | C29: 2 | D29: 2.787 | E29: 0.747 | F29: 0.087 | G29: 0 | H29: 0 | I29: 0 | J29: 0
A30: LDNO HV: Non-Domestic Aggregated or CT No Residual | B30: 209 | C30: 0, 3, 4, 5-8 | D30: 3.353 | E30: 0.899 | F30: 0.105 | G30: 4.98 | H30: 0 | I30: 0 | J30: 0
A31: LDNO HV: Non-Domestic Aggregated or CT Band 1 | B31: 161, 162, 164, 399 | C31: 0, 3, 4, 5-8 | D31: 3.353 | E31: 0.899 | F31: 0.105 | G31: 7.32 | H31: 0 | I31: 0 | J31: 0
A32: LDNO HV: Non-Domestic Aggregated or CT Band 2 | B32: 210 | C32: 0, 3, 4, 5-8 | D32: 3.353 | E32: 0.899 | F32: 0.105 | G32: 10.83 | H32: 0 | I32: 0 | J32: 0
A33: LDNO HV: Non-Domestic Aggregated or CT Band 3 | B33: 211 | C33: 0, 3, 4, 5-8 | D33: 3.353 | E33: 0.899 | F33: 0.105 | G33: 17.23 | H33: 0 | I33: 0 | J33: 0
A34: LDNO HV: Non-Domestic Aggregated or CT Band 4 | B34: 212 | C34: 0, 3, 4, 5-8 | D34: 3.353 | E34: 0.899 | F34: 0.105 | G34: 39.05 | H34: 0 | I34: 0 | J34: 0
A35: LDNO HV: Non-Domestic Aggregated (related MPAN) | B35: 163 | C35: 4 | D35: 3.353 | E35: 0.899 | F35: 0.105 | G35: 0 | H35: 0 | I35: 0 | J35: 0
A36: LDNO HV: LV Site Specific No Residual | B36: 213 | C36: 0 | D36: 2.394 | E36: 0.627 | F36: 0.07 | G36: 6.61 | H36: 1.57 | I36: 1.57 | J36: 0.049
A37: LDNO HV: LV Site Specific Band 1 | B37: 165 | C37: 0 | D37: 2.394 | E37: 0.627 | F37: 0.07 | G37: 63.58 | H37: 1.57 | I37: 1.57 | J37: 0.049
A38: LDNO HV: LV Site Specific Band 2 | B38: 215 | C38: 0 | D38: 2.394 | E38: 0.627 | F38: 0.07 | G38: 120.6 | H38: 1.57 | I38: 1.57 | J38: 0.049
A39: LDNO HV: LV Site Specific Band 3 | B39: 216 | C39: 0 | D39: 2.394 | E39: 0.627 | F39: 0.07 | G39: 178.22 | H39: 1.57 | I39: 1.57 | J39: 0.049
A40: LDNO HV: LV Site Specific Band 4 | B40: 217 | C40: 0 | D40: 2.394 | E40: 0.627 | F40: 0.07 | G40: 363.97 | H40: 1.57 | I40: 1.57 | J40: 0.049
A41: LDNO HV: LV Sub Site Specific No Residual | B41: 218 | C41: 0 | D41: 2.578 | E41: 0.64 | F41: 0.065 | G41: 11.18 | H41: 2.13 | I41: 2.13 | J41: 0.047
A42: LDNO HV: LV Sub Site Specific Band 1 | B42: 166 | C42: 0 | D42: 2.578 | E42: 0.64 | F42: 0.065 | G42: 107.44 | H42: 2.13 | I42: 2.13 | J42: 0.047
A43: LDNO HV: LV Sub Site Specific Band 2 | B43: 219 | C43: 0 | D43: 2.578 | E43: 0.64 | F43: 0.065 | G43: 203.81 | H43: 2.13 | I43: 2.13 | J43: 0.047
A44: LDNO HV: LV Sub Site Specific Band 3 | B44: 220 | C44: 0 | D44: 2.578 | E44: 0.64 | F44: 0.065 | G44: 301.18 | H44: 2.13 | I44: 2.13 | J44: 0.047
A45: LDNO HV: LV Sub Site Specific Band 4 | B45: 221 | C45: 0 | D45: 2.578 | E45: 0.64 | F45: 0.065 | G45: 615.11 | H45: 2.13 | I45: 2.13 | J45: 0.047
A46: LDNO HV: HV Site Specific No Residual | B46: 227 | C46: 0 | D46: 2.187 | E46: 0.512 | F46: 0.045 | G46: 366.83 | H46: 3.29 | I46: 3.29 | J46: 0.036
... A50: LDNO HV: HV Site Specific Band 4 | B50: 231 | C50: 0 | D50: 2.187 | E50: 0.512 | F50: 0.045 | G50: 11153.86 | H50: 3.29 | I50: 3.29 | J50: 0.036
A51: LDNO HV: Unmetered Supplies | B51: 136, 137, 138, 139, 171 | C51: 0, 1, 8 | D51: 8.421 | E51: 0.983 | F51: 0.366 | G51: 0 | H51: 0 | I51: 0 | J51: 0
A52: LDNO HV: LV Generation Aggregated | B52: 175 | C52: 0, 8 | D52: -4.895 | E52: -1.312 | F52: -0.153 | G52: 0 | H52: 0 | I52: 0 | J52: 0
A53: LDNO HV: LV Sub Generation Aggregated | B53: 176 | C53: 8 | D53: -4.046 | E53: -1.07 | F53: -0.122 | G53: 0 | H53: 0 | I53: 0 | J53: 0
A54: LDNO HV: LV Generation Site Specific | B54: 177, 178 | C54: 0 | D54: -4.895 | E54: -1.312 | F54: -0.153 | G54: 0 | H54: 0 | I54: 0 | J54: 0.091
A55: LDNO HV: LV Sub Generation Site Specific | B55: 179, 180 | C55: 0 | D55: -4.046 | E55: -1.07 | F55: -0.122 | G55: 0 | H55: 0 | I55: 0 | J55: 0.083
A56: LDNO HV: HV Generation Site Specific | B56: 181, 182 | C56: 0 | D56: -2.826 | E56: -0.702 | F56: -0.071 | G56: 0 | H56: 0 | I56: 0 | J56: 0.073
A57: LDNO HVplus: Domestic Aggregated or CT with Residual | B57: 183, 184, 422 | C57: 0, 1, 2 | D57: 1.913 | E57: 0.513 | F57: 0.06 | G57: 5.08 | H57: 0 | I57: 0 | J57: 0
A58: LDNO HVplus: Domestic Aggregated (related MPAN) | B58: 185 | C58: 2 | D58: 1.913 | E58: 0.513 | F58: 0.06 | G58: 0 | H58: 0 | I58: 0 | J58: 0
A59: LDNO HVplus: Non-Domestic Aggregated or CT No Residual | B59: 232 | C59: 0, 3, 4, 5-8 | D59: 2.302 | E59: 0.617 | F59: 0.072 | G59: 3.42 | H59: 0 | I59: 0 | J59: 0
A60: LDNO HVplus: Non-Domestic Aggregated or CT Band 1 | B60: 186, 187, 189, 423 | C60: 0, 3, 4, 5-8 | D60: 2.302 | E60: 0.617 | F60: 0.072 | G60: 5.03 | H60: 0 | I60: 0 | J60: 0
A61: LDNO HVplus: Non-Domestic Aggregated or CT Band 2 | B61: 233 | C61: 0, 3, 4, 5-8 | D61: 2.302 | E61: 0.617 | F61: 0.072 | G61: 7.44 | H61: 0 | I61: 0 | J61: 0
A62: LDNO HVplus: Non-Domestic Aggregated or CT Band 3 | B62: 234 | C62: 0, 3, 4, 5-8 | D62: 2.302 | E62: 0.617 | F62: 0.072 | G62: 11.83 | H62: 0 | I62: 0 | J62: 0
A63: LDNO HVplus: Non-Domestic Aggregated or CT Band 4 | B63: 235 | C63: 0, 3, 4, 5-8 | D63: 2.302 | E63: 0.617 | F63: 0.072 | G63: 26.81 | H63: 0 | I63: 0 | J63: 0
A64: LDNO HVplus: Non-Domestic Aggregated (related MPAN) | B64: 188 | C64: 4 | D64: 2.302 | E64: 0.617 | F64: 0.072 | G64: 0 | H64: 0 | I64: 0 | J64: 0
A65: LDNO HVplus: LV Site Specific No Residual | B65: 236 | C65: 0 | D65: 1.643 | E65: 0.431 | F65: 0.048 | G65: 4.54 | H65: 1.08 | I65: 1.08 | J65: 0.033
A66: LDNO HVplus: LV Site Specific Band 1 | B66: 190 | C66: 0 | D66: 1.643 | E66: 0.431 | F66: 0.048 | G66: 43.64 | H66: 1.08 | I66: 1.08 | J66: 0.033
A67: LDNO HVplus: LV Site Specific Band 2 | B67: 237 | C67: 0 | D67: 1.643 | E67: 0.431 | F67: 0.048 | G67: 82.78 | H67: 1.08 | I67: 1.08 | J67: 0.033
A68: LDNO HVplus: LV Site Specific Band 3 | B68: 238 | C68: 0 | D68: 1.643 | E68: 0.431 | F68: 0.048 | G68: 122.34 | H68: 1.08 | I68: 1.08 | J68: 0.033
A69: LDNO HVplus: LV Site Specific Band 4 | B69: 239 | C69: 0 | D69: 1.643 | E69: 0.431 | F69: 0.048 | G69: 249.85 | H69: 1.08 | I69: 1.08 | J69: 0.033
A70: LDNO HVplus: LV Sub Site Specific No Residual | B70: 242 | C70: 0 | D70: 1.746 | E70: 0.434 | F70: 0.044 | G70: 7.57 | H70: 1.44 | I70: 1.44 | J70: 0.032
A71: LDNO HVplus: LV Sub Site Specific Band 1 | B71: 191 | C71: 0 | D71: 1.746 | E71: 0.434 | F71: 0.044 | G71: 72.76 | H71: 1.44 | I71: 1.44 | J71: 0.032
A72: LDNO HVplus: LV Sub Site Specific Band 2 | B72: 243 | C72: 0 | D72: 1.746 | E72: 0.434 | F72: 0.044 | G72: 138.02 | H72: 1.44 | I72: 1.44 | J72: 0.032
A73: LDNO HVplus: LV Sub Site Specific Band 3 | B73: 245 | C73: 0 | D73: 1.746 | E73: 0.434 | F73: 0.044 | G73: 203.96 | H73: 1.44 | I73: 1.44 | J73: 0.032
A74: LDNO HVplus: LV Sub Site Specific Band 4 | B74: 247 | C74: 0 | D74: 1.746 | E74: 0.434 | F74: 0.044 | G74: 416.55 | H74: 1.44 | I74: 1.44 | J74: 0.032
A75: LDNO HVplus: HV Site Specific No Residual | B75: 251 | C75: 0 | D75: 1.464 | E75: 0.343 | F75: 0.03 | G75: 245.63 | H75: 2.2 | I75: 2.2 | J75: 0.024
... A79: LDNO HVplus: HV Site Specific Band 4 | B79: 254 | C79: 0 | D79: 1.464 | E79: 0.343 | F79: 0.03 | G79: 7468.7 | H79: 2.2 | I79: 2.2 | J79: 0.024
A80: LDNO HVplus: Unmetered Supplies | B80: 140, 141, 142, 143, 194 | C80: 0, 1, 8 | D80: 5.781 | E80: 0.675 | F80: 0.251 | G80: 0 | H80: 0 | I80: 0 | J80: 0
A81: LDNO HVplus: LV Generation Aggregated | B81: 195 | C81: 0, 8 | D81: -2.301 | E81: -0.617 | F81: -0.072 | G81: 0 | H81: 0 | I81: 0 | J81: 0
A82: LDNO HVplus: LV Sub Generation Aggregated | B82: 196 | C82: 8 | D82: -2.357 | E82: -0.623 | F82: -0.071 | G82: 0 | H82: 0 | I82: 0 | J82: 0
A83: LDNO HVplus: LV Generation Site Specific | B83: 197, 198 | C83: 0 | D83: -2.301 | E83: -0.617 | F83: -0.072 | G83: 0 | H83: 0 | I83: 0 | J83: 0.043
A84: LDNO HVplus: LV Sub Generation Site Specific | B84: 199, 315 | C84: 0 | D84: -2.357 | E84: -0.623 | F84: -0.071 | G84: 0 | H84: 0 | I84: 0 | J84: 0.048
A85: LDNO HVplus: HV Generation Site Specific | B85: 316, 317 | C85: 0 | D85: -2.826 | E85: -0.702 | F85: -0.071 | G85: 93.7 | H85: 0 | I85: 0 | J85: 0.073
A86: LDNO EHV: Domestic Aggregated or CT with Residual | B86: 318, 319, 424 | C86: 0, 1, 2 | D86: 1.325 | E86: 0.355 | F86: 0.041 | G86: 3.52 | H86: 0 | I86: 0 | J86: 0
A87: LDNO EHV: Domestic Aggregated (related MPAN) | B87: 320 | C87: 2 | D87: 1.325 | E87: 0.355 | F87: 0.041 | G87: 0 | H87: 0 | I87: 0 | J87: 0
A88: LDNO EHV: Non-Domestic Aggregated or CT No Residual | B88: 255 | C88: 0, 3, 4, 5-8 | D88: 1.594 | E88: 0.427 | F88: 0.05 | G88: 2.36 | H88: 0 | I88: 0 | J88: 0
A89: LDNO EHV: Non-Domestic Aggregated or CT Band 1 | B89: 321, 322, 324, 425 | C89: 0, 3, 4, 5-8 | D89: 1.594 | E89: 0.427 | F89: 0.05 | G89: 3.48 | H89: 0 | I89: 0 | J89: 0
A90: LDNO EHV: Non-Domestic Aggregated or CT Band 2 | B90: 256 | C90: 0, 3, 4, 5-8 | D90: 1.594 | E90: 0.427 | F90: 0.05 | G90: 5.15 | H90: 0 | I90: 0 | J90: 0
A91: LDNO EHV: Non-Domestic Aggregated or CT Band 3 | B91: 258 | C91: 0, 3, 4, 5-8 | D91: 1.594 | E91: 0.427 | F91: 0.05 | G91: 8.19 | H91: 0 | I91: 0 | J91: 0
A92: LDNO EHV: Non-Domestic Aggregated or CT Band 4 | B92: 259 | C92: 0, 3, 4, 5-8 | D92: 1.594 | E92: 0.427 | F92: 0.05 | G92: 18.56 | H92: 0 | I92: 0 | J92: 0
A93: LDNO EHV: Non-Domestic Aggregated (related MPAN) | B93: 323 | C93: 4 | D93: 1.594 | E93: 0.427 | F93: 0.05 | G93: 0 | H93: 0 | I93: 0 | J93: 0
A94: LDNO EHV: LV Site Specific No Residual | B94: 260 | C94: 0 | D94: 1.138 | E94: 0.298 | F94: 0.034 | G94: 3.14 | H94: 0.75 | I94: 0.75 | J94: 0.023
A95: LDNO EHV: LV Site Specific Band 1 | B95: 325 | C95: 0 | D95: 1.138 | E95: 0.298 | F95: 0.034 | G95: 30.22 | H95: 0.75 | I95: 0.75 | J95: 0.023
A96: LDNO EHV: LV Site Specific Band 2 | B96: 261 | C96: 0 | D96: 1.138 | E96: 0.298 | F96: 0.034 | G96: 57.32 | H96: 0.75 | I96: 0.75 | J96: 0.023
A97: LDNO EHV: LV Site Specific Band 3 | B97: 262 | C97: 0 | D97: 1.138 | E97: 0.298 | F97: 0.034 | G97: 84.71 | H97: 0.75 | I97: 0.75 | J97: 0.023
A98: LDNO EHV: LV Site Specific Band 4 | B98: 263 | C98: 0 | D98: 1.138 | E98: 0.298 | F98: 0.034 | G98: 173 | H98: 0.75 | I98: 0.75 | J98: 0.023
A99: LDNO EHV: LV Sub Site Specific No Residual | B99: 264 | C99: 0 | D99: 1.209 | E99: 0.3 | F99: 0.03 | G99: 5.24 | H99: 1 | I99: 1 | J99: 0.022
A100: LDNO EHV: LV Sub Site Specific Band 1 | B100: 326 | C100: 0 | D100: 1.209 | E100: 0.3 | F100: 0.03 | G100: 50.38 | H100: 1 | I100: 1 | J100: 0.022
A101: LDNO EHV: LV Sub Site Specific Band 2 | B101: 265 | C101: 0 | D101: 1.209 | E101: 0.3 | F101: 0.03 | G101: 95.57 | H101: 1 | I101: 1 | J101: 0.022
A102: LDNO EHV: LV Sub Site Specific Band 3 | B102: 266 | C102: 0 | D102: 1.209 | E102: 0.3 | F102: 0.03 | G102: 141.23 | H102: 1 | I102: 1 | J102: 0.022
A103: LDNO EHV: LV Sub Site Specific Band 4 | B103: 267 | C103: 0 | D103: 1.209 | E103: 0.3 | F103: 0.03 | G103: 288.43 | H103: 1 | I103: 1 | J103: 0.022
A104: LDNO EHV: HV Site Specific No Residual | B104: 269 | C104: 0 | D104: 1.014 | E104: 0.237 | F104: 0.021 | G104: 170.08 | H104: 1.53 | I104: 1.53 | J104: 0.017
... A108: LDNO EHV: HV Site Specific Band 4 | B108: 272 | C108: 0 | D108: 1.014 | E108: 0.237 | F108: 0.021 | G108: 5171.59 | H108: 1.53 | I108: 1.53 | J108: 0.017
A109: LDNO EHV: Unmetered Supplies | B109: 144, 145, 146, 147, 329 | C109: 0, 1, 8 | D109: 4.003 | E109: 0.467 | F109: 0.174 | G109: 0 | H109: 0 | I109: 0 | J109: 0
A110: LDNO EHV: LV Generation Aggregated | B110: 330 | C110: 0, 8 | D110: -1.593 | E110: -0.427 | F110: -0.05 | G110: 0 | H110: 0 | I110: 0 | J110: 0
A111: LDNO EHV: LV Sub Generation Aggregated | B111: 331 | C111: 8 | D111: -1.632 | E111: -0.432 | F111: -0.049 | G111: 0 | H111: 0 | I111: 0 | J111: 0
...

Sheet Annex 5 LLFs
A1: Back to Overview
A2: This table has intentionally been left blank. The line loss factors that are approved by the BSC Panel for the applicable year and consequently published on the Elexon website will take precedence and be used in Settlement. This annex will be re-published once these values are available.
A3: =Overview!B4& " - Illustrative LLFs for year beginning "&Overview!D4 -> Northern Powergrid (Yorkshire) Plc - Illustrative LLFs for year beginning 1 April 2026
A4: Time periods | B4: Period 1 | C4: Period 2 | D4: Period 3 | E4: Period 4
A5: Monday – Friday (Apr – Oct) | B5: 0 | C5: 0 | D5: 00:00 – 07:00 | E5: 07:00 – 24:00
A6: Monday – Friday (Nov – Feb) | B6: 16:00 – 19:00 | C6: 07:00 – 16:00 19:00 – 20:00 | D6: 00:00 – 07:00 | E6: 20:00 – 24:00
A7: Monday – Friday (Mar) | B7: 0 | C7: 0 | D7: 00:00 – 07:00 | E7: 07:00 – 24:00
A8: Saturday and Sunday (All Year) | B8: 0 | C8: 0 | D8: 00:00 – 07:00 | E8: 07:00 – 24:00
A9: Notes | B9: All the above times are in UK Clock time
A12: Generic demand and generation LLFs
A13: Metered voltage, respective periods and associated LLFCs
A14: Metered voltage | B14: Period 1 | C14: Period 2 | D14: Period 3 | E14: Period 4 | F14: Associated LLFC
A15: Low Voltage Network | B15: 1.172 | C15: 1.153 | D15: 1.107 | E15: 1.128 | F15: 100, 111, 120, 1A, 1AH, 20, 22, 222, 224, 24, 279, 2A, 2AH, 2B, 2BH, 2C, 2CH, 2D, 2DH, 2Z, 2ZH, 3A, 4A, 5A, 5B, 5C, 5D, 5Z, 8A, 995, 999
A16: Low Voltage Substation | B16: 1.045 | C16: 1.045 | D16: 1.047 | E16: 1.044 | F16: 223, 225, 23, 25, 30, 6A, 6B, 6C, 6D, 6Z
A17: High Voltage Network | B17: 1.029 | C17: 1.028 | D17: 1.022 | E17: 1.024 | F17: 226, 228, 26, 28, 7A, 7B, 7C, 7D, 7Z
A18: High Voltage Substation | B18: 1.019 | C18: 1.019 | D18: 1.016 | E18: 1.017 | F18: 31, 32, 34, 36, 37, 38, 39, 68, 69, 71, 72, 831, 832, 833, 834, 835, 836, 837, 838, 839, 840, 841, 842, 844, 845, 846, 847, 848, 849, 850, 851, 852, 853, 854, 855, 856, 858, 859, 861, 862, 863, 865, 866, 867, 868, 869, 870, 871, 872, 873, 874, 875, 876, 877, 880, 881, 882, 883, 884, 885, 886, 888, 892, 893, 894, 895, 896, 897, 898, 899, 900
A19: Greater than 22kV connected - generation | B19: 1.013 | C19: 1.012 | D19: 1.009 | E19: 1.01 | F19: 699, 700, 701, 702, 703, 704, 705, 706, 707, 708, 709, 710, 711, 712, 713, 714, 715, 716, 717, 718, 719, 720, 721, 722, 723, 724, 818, 819, 820, 911, 914, 915, 934, 935, 936, 937, 938, 939, 940, 941, 942, 943, 944, 945, 949, 950, 951, 952, 953, 954, 955, 956, 957, 958, 959, 960, 961, 962, 963, 964, 965, 966, 967, 968, 969, 970, 971, 972, 973, 974, 975, 976, 977, 978, 979, 980, 981, 982, 983, 984, 985, 986, 987, 988, 989, 990, 994, ME1, MX1
A20: Greater than 22kV connected - demand | B20: 1.013 | C20: 1.012 | D20: 1.009 | E20: 1.01 | F20: 129, 455, 456, 457, 458, 459, 460, 461, 462, 463, 464, 465, 466, 467, 468, 469, 470, 473, 474, 475, 476, 477, 478, 479, 482, 483, 484, 485, 486, 487, 488, 489, 490, 491, 492, 493, 494, 495, 496, 497, 498, 499, 503, 504, 505, 506, 507, 508, 509, 540, 541, 542, 543, 544, 545, 546, 547, 548, 549, 550, 554, 555, 556, 557, 558, 559, 560, 561, 562, 563, 564, 565, 566, 567, 568, 569, 570, 571, 572, 573, 574, 575, 576, 577, 578, 579, 582, ME2, MX2
A22: Designated EHV site specific LLFs
A23: Demand
A24: Site | B24: Period 1 | C24: Period 2 | D24: Period 3 | E24: Period 4 | F24: Associated LLFC
A25: Site 1 | B25: 1.026 | C25: 1.026 | D25: 1.025 | E25: 1.026 | F25: 750
A26: Site 2 | B26: 1.004 | C26: 1.004 | D26: 1.004 | E26: 1.004 | F26: 751
A27: Site 3 | B27: 1.033 | C27: 1.031 | D27: 1.032 | E27: 1.025 | F27: 753
A28: Site 4 | B28: 1.009 | C28: 1.009 | D28: 1.016 | E28: 1.009 | F28: 754
A29: Site 5 | B29: 1.01 | C29: 1.01 | D29: 1.019 | E29: 1.01 | F29: 755
A30: Site 6 | B30: 1.005 | C30: 1.005 | D30: 1.01 | E30: 1.007 | F30: 756
A31: Site 7 | B31: 1 | C31: 1.004 | D31: 1.002 | E31: 1.002 | F31: 757
A32: Site 8 | B32: 1.007 | C32: 1.007 | D32: 1.007 | E32: 1.007 | F32: 804
A33: Site 9 | B33: 1.004 | C33: 1.004 | D33: 1.005 | E33: 1.005 | F33: 760
A34: Site 10 | B34: 1 | C34: 1 | D34: 1 | E34: 1 | F34: 761
A35: Site 11 | B35: 1.008 | C35: 1.008 | D35: 1.006 | E35: 1.007 | F35: 762
A36: Site 12 | B36: 1.01 | C36: 1.005 | D36: 1.004 | E36: 1.006 | F36: 763
... A136: Site 112 | B136: 1.013 | C136: 1.012 | D136: 1.009 | E136: 1.01 | F136: 725
A139: EHV site specific LLFs
A140: Generation
A141: Site | B141: Period 1 | C141: Period 2 | D141: Period 3 | E141: Period 4 | F141: Associated LLFC
A142: Site 1 | B142: 1.052 | C142: 1.046 | D142: 1.014 | E142: 1.026 | F142: 90
A143: Site 2 | B143: 1.004 | C143: 1.004 | D143: 0.993 | E143: 1.001 | F143: 82
A144: Site 3 | B144: 0.993 | C144: 0.993 | D144: 0.981 | E144: 0.992 | F144: 76
A145: Site 4 | B145: 0.995 | C145: 0.995 | D145: 0.987 | E145: 0.994 | F145: 75
A146: Site 5 | B146: 1.004 | C146: 1.004 | D146: 1.002 | E146: 1.003 | F146: 95
A147: Site 6 | B147: 1.007 | C147: 1.007 | D147: 1.007 | E147: 1.007 | F147: 800
A148: Site 7 | B148: 1 | C148: 1 | D148: 1 | E148: 1.003 | F148: 60
A149: Site 8 | B149: 1.005 | C149: 1.005 | D149: 1.001 | E149: 1.003 | F149: 62
A150: Site 9 | B150: 1.003 | C150: 1.002 | D150: 1.001 | E150: 1.001 | F150: 80
A151: Site 10 | B151: 0.998 | C151: 0.997 | D151: 0.995 | E151: 0.996 | F151: 66
A152: Site 11 | B152: 0.967 | C152: 0.962 | D152: 0.987 | E152: 0.975 | F152: 128
A153: Site 12 | B153: 0.995 | C153: 0.994 | D153: 0.993 | E153: 0.994 | F153: 92
... A239: Site 98 | B239: 1.013 | C239: 1.012 | D239: 1.009 | E239: 1.01 | F239: 510

Sheet Annex 6 New or Amended EHV
A1: Back to Overview | C1: Note: The list of MPANs/MSIDs provided may be incomplete; the DNO reserves the right to apply the listed charges to any other MPANs/MSIDs associated with the site. If sites appear in both Annex 2 and Annex 6, the charges in Annex 6 take precedence. Where an existing Designated EHV Property is modified and energised in the charging year, we may revise the EDCM charges for the modified Designated EHV Property.
A2: Annex 6 - Charges for New or Amended Designated EHV Properties
A4: =Overview!B4& " - Effective from "&Overview!D4&" - "&Overview!E4&" new Designated EHV charges" -> Northern Powergrid (Yorkshire) Plc - Effective from 1 April 2026 - Final new Designated EHV charges
A5: Effective from date | B5: Import Unique Identifier | C5: LLFC | D5: Import MPANs/MSIDs | E5: Export Unique Identifier | F5: LLFC | G5: Export MPANs/MSIDs | H5: Name | I5: ='Annex 2 Designated EHV charges'!I9 -> Import Super Red unit charge (p/kWh) | J5: ='Annex 2 Designated EHV charges'!J9 -> Import fixed charge (p/day) | K5: ='Annex 2 Designated EHV charges'!K9 -> Import capacity charge (p/kVA/day) | L5: ='Annex 2 Designated EHV charges'!L9 -> Import exceeded capacity charge (p/kVA/day) | M5: ='Annex 2 Designated EHV charges'!M9 -> Export Super Red unit charge (p/kWh) | N5: ='Annex 2 Designated EHV charges'!N9 -> Export fixed charge (p/day) | O5: ='Annex 2 Designated EHV charges'!O9 -> Export capacity charge (p/kVA/day) | P5: ='Annex 2 Designated EHV charges'!P9 -> Export exceeded capacity charge (p/kVA/day)
A17: =Overview!B4& " - Effective from "&Overview!D4&" - "&Overview!E4&" new Designated EHV line loss factors" -> Northern Powergrid (Yorkshire) Plc - Effective from 1 April 2026 - Final new Designated EHV line loss factors
A18: Effective from date | B18: Import Unique Identifier | C18: LLFC | D18: Import MPANs/MSIDs | E18: Export Unique Identifier | F18: LLFC | G18: Export MPANs/MSIDs | H18: Name | I18: Import LLF period 1 | J18: Import LLF period 2 | K18: Import LLF period 3 | L18: Import LLF period 4 | M18: Import LLF period 5 | N18: Export LLF period 1 | O18: Export LLF period 2 | P18: Export LLF period 3 | Q18: Export LLF period 4 | R18: Export LLF period 5
A32: New or Amended Charges for Designated EHV Properties can be found in the relevant 'Addendum' spreadsheet published on our website, as updated from time to time.

Sheet Annex 7 Pass-Through Costs
A1: Back to Overview
A2: =Overview!B4& " - Effective from "&Overview!D4&" - "&Overview!E4&" Supplier of Last Resort and Eligible Bad Debt Pass-Through Costs" -> Northern Powergrid (Yorkshire) Plc - Effective from 1 April 2026 - Final Supplier of Last Resort and Eligible Bad Debt Pass-Through Costs
A4: Tariff name | B4: Open LLFCs / LDNO unique billing identifier | C4: PCs | D4: Supplier of Last Resort Fixed charge adder* p/MPAN/day | E4: Eligible Bad Debt Fixed charge adder** p/MPAN/day
A5: Domestic Aggregated or CT with Residual | B5: 1A, 1AH, 100, 120, 279 | C5: 0, 1, 2 | D5: 0 | E5: 0
A6: Non-Domestic Aggregated or CT No Residual | B6: 2Z, 2ZH | C6: 0, 3, 4, 5-8 | D6: 0 | E6: 0
A7: Non-Domestic Aggregated or CT Band 1 | B7: 2A, 2AH | C7: 0, 3, 4, 5-8 | D7: 0 | E7: 0
A8: Non-Domestic Aggregated or CT Band 2 | B8: 2B, 2BH | C8: 0, 3, 4, 5-8 | D8: 0 | E8: 0
A9: Non-Domestic Aggregated or CT Band 3 | B9: 2C, 2CH | C9: 0, 3, 4, 5-8 | D9: 0 | E9: 0
A10: Non-Domestic Aggregated or CT Band 4 | B10: 2D, 2DH | C10: 0, 3, 4, 5-8 | D10: 0 | E10: 0
A11: LV Site Specific No Residual | B11: 5Z | C11: 0 | D11: 0 | E11: 0
A12: LV Site Specific Band 1 | B12: 5A | C12: 0 | D12: 0 | E12: 0
A13: LV Site Specific Band 2 | B13: 5B | C13: 0 | D13: 0 | E13: 0
A14: LV Site Specific Band 3 | B14: 5C | C14: 0 | D14: 0 | E14: 0
A15: LV Site Specific Band 4 | B15: 5D | C15: 0 | D15: 0 | E15: 0
A16: LV Sub Site Specific No Residual | B16: 6Z | C16: 0 | D16: 0 | E16: 0
A17: LV Sub Site Specific Band 1 | B17: 6A | C17: 0 | D17: 0 | E17: 0
A18: LV Sub Site Specific Band 2 | B18: 6B | C18: 0 | D18: 0 | E18: 0
A19: LV Sub Site Specific Band 3 | B19: 6C | C19: 0 | D19: 0 | E19: 0
A20: LV Sub Site Specific Band 4 | B20: 6D | C20: 0 | D20: 0 | E20: 0
A21: HV Site Specific No Residual | B21: 7Z | C21: 0 | D21: 0 | E21: 0
A22: HV Site Specific Band 1 | B22: 7A | C22: 0 | D22: 0 | E22: 0
... A25: HV Site Specific Band 4 | B25: 7D | C25: 0 | D25: 0 | E25: 0
A26: LDNO LV: Domestic Aggregated or CT with Residual | B26: 150, 151, 148 | C26: 0, 1, 2 | D26: 0 | E26: 0
A27: LDNO LV: Non-Domestic Aggregated or CT No Residual | B27: 201 | C27: 0, 3, 4, 5-8 | D27: 0 | E27: 0
A28: LDNO LV: Non-Domestic Aggregated or CT Band 1 | B28: 153, 154, 156, 149 | C28: 0, 3, 4, 5-8 | D28: 0 | E28: 0
A29: LDNO LV: Non-Domestic Aggregated or CT Band 2 | B29: 202 | C29: 0, 3, 4, 5-8 | D29: 0 | E29: 0
A30: LDNO LV: Non-Domestic Aggregated or CT Band 3 | B30: 203 | C30: 0, 3, 4, 5-8 | D30: 0 | E30: 0
A31: LDNO LV: Non-Domestic Aggregated or CT Band 4 | B31: 204 | C31: 0, 3, 4, 5-8 | D31: 0 | E31: 0
A32: LDNO LV: LV Site Specific No Residual | B32: 205 | C32: 0 | D32: 0 | E32: 0
A33: LDNO LV: LV Site Specific Band 1 | B33: 157 | C33: 0 | D33: 0 | E33: 0
A34: LDNO LV: LV Site Specific Band 2 | B34: 206 | C34: 0 | D34: 0 | E34: 0
A35: LDNO LV: LV Site Specific Band 3 | B35: 207 | C35: 0 | D35: 0 | E35: 0
A36: LDNO LV: LV Site Specific Band 4 | B36: 208 | C36: 0 | D36: 0 | E36: 0
A37: LDNO HV: Domestic Aggregated or CT with Residual | B37: 158, 159, 398 | C37: 0, 1, 2 | D37: 0 | E37: 0
A38: LDNO HV: Non-Domestic Aggregated or CT No Residual | B38: 209 | C38: 0, 3, 4, 5-8 | D38: 0 | E38: 0
A39: LDNO HV: Non-Domestic Aggregated or CT Band 1 | B39: 161, 162, 164, 399 | C39: 0, 3, 4, 5-8 | D39: 0 | E39: 0
A40: LDNO HV: Non-Domestic Aggregated or CT Band 2 | B40: 210 | C40: 0, 3, 4, 5-8 | D40: 0 | E40: 0
A41: LDNO HV: Non-Domestic Aggregated or CT Band 3 | B41: 211 | C41: 0, 3, 4, 5-8 | D41: 0 | E41: 0
A42: LDNO HV: Non-Domestic Aggregated or CT Band 4 | B42: 212 | C42: 0, 3, 4, 5-8 | D42: 0 | E42: 0
A43: LDNO HV: LV Site Specific No Residual | B43: 213 | C43: 0 | D43: 0 | E43: 0
A44: LDNO HV: LV Site Specific Band 1 | B44: 165 | C44: 0 | D44: 0 | E44: 0
A45: LDNO HV: LV Site Specific Band 2 | B45: 215 | C45: 0 | D45: 0 | E45: 0
A46: LDNO HV: LV Site Specific Band 3 | B46: 216 | C46: 0 | D46: 0 | E46: 0
A47: LDNO HV: LV Site Specific Band 4 | B47: 217 | C47: 0 | D47: 0 | E47: 0
A48: LDNO HV: LV Sub Site Specific No Residual | B48: 218 | C48: 0 | D48: 0 | E48: 0
A49: LDNO HV: LV Sub Site Specific Band 1 | B49: 166 | C49: 0 | D49: 0 | E49: 0
A50: LDNO HV: LV Sub Site Specific Band 2 | B50: 219 | C50: 0 | D50: 0 | E50: 0
A51: LDNO HV: LV Sub Site Specific Band 3 | B51: 220 | C51: 0 | D51: 0 | E51: 0
A52: LDNO HV: LV Sub Site Specific Band 4 | B52: 221 | C52: 0 | D52: 0 | E52: 0
A53: LDNO HV: HV Site Specific No Residual | B53: 227 | C53: 0 | D53: 0 | E53: 0
A54: LDNO HV: HV Site Specific Band 1 | B54: 167 | C54: 0 | D54: 0 | E54: 0
... A57: LDNO HV: HV Site Specific Band 4 | B57: 231 | C57: 0 | D57: 0 | E57: 0
A58: LDNO HVplus: Domestic Aggregated or CT with Residual | B58: 183, 184, 422 | C58: 0, 1, 2 | D58: 0 | E58: 0
A59: LDNO HVplus: Non-Domestic Aggregated or CT No Residual | B59: 232 | C59: 0, 3, 4, 5-8 | D59: 0 | E59: 0
A60: LDNO HVplus: Non-Domestic Aggregated or CT Band 1 | B60: 186, 187, 189, 423 | C60: 0, 3, 4, 5-8 | D60: 0 | E60: 0
A61: LDNO HVplus: Non-Domestic Aggregated or CT Band 2 | B61: 233 | C61: 0, 3, 4, 5-8 | D61: 0 | E61: 0
A62: LDNO HVplus: Non-Domestic Aggregated or CT Band 3 | B62: 234 | C62: 0, 3, 4, 5-8 | D62: 0 | E62: 0
A63: LDNO HVplus: Non-Domestic Aggregated or CT Band 4 | B63: 235 | C63: 0, 3, 4, 5-8 | D63: 0 | E63: 0
A64: LDNO HVplus: LV Site Specific No Residual | B64: 236 | C64: 0 | D64: 0 | E64: 0
A65: LDNO HVplus: LV Site Specific Band 1 | B65: 190 | C65: 0 | D65: 0 | E65: 0
A66: LDNO HVplus: LV Site Specific Band 2 | B66: 237 | C66: 0 | D66: 0 | E66: 0
A67: LDNO HVplus: LV Site Specific Band 3 | B67: 238 | C67: 0 | D67: 0 | E67: 0
A68: LDNO HVplus: LV Site Specific Band 4 | B68: 239 | C68: 0 | D68: 0 | E68: 0
A69: LDNO HVplus: LV Sub Site Specific No Residual | B69: 242 | C69: 0 | D69: 0 | E69: 0
A70: LDNO HVplus: LV Sub Site Specific Band 1 | B70: 191 | C70: 0 | D70: 0 | E70: 0
A71: LDNO HVplus: LV Sub Site Specific Band 2 | B71: 243 | C71: 0 | D71: 0 | E71: 0
A72: LDNO HVplus: LV Sub Site Specific Band 3 | B72: 245 | C72: 0 | D72: 0 | E72: 0
A73: LDNO HVplus: LV Sub Site Specific Band 4 | B73: 247 | C73: 0 | D73: 0 | E73: 0
A74: LDNO HVplus: HV Site Specific No Residual | B74: 251 | C74: 0 | D74: 0 | E74: 0
A75: LDNO HVplus: HV Site Specific Band 1 | B75: 192 | C75: 0 | D75: 0 | E75: 0
... A78: LDNO HVplus: HV Site Specific Band 4 | B78: 254 | C78: 0 | D78: 0 | E78: 0
A79: LDNO EHV: Domestic Aggregated or CT with Residual | B79: 318, 319, 424 | C79: 0, 1, 2 | D79: 0 | E79: 0
A80: LDNO EHV: Non-Domestic Aggregated or CT No Residual | B80: 255 | C80: 0, 3, 4, 5-8 | D80: 0 | E80: 0
A81: LDNO EHV: Non-Domestic Aggregated or CT Band 1 | B81: 321, 322, 324, 425 | C81: 0, 3, 4, 5-8 | D81: 0 | E81: 0
A82: LDNO EHV: Non-Domestic Aggregated or CT Band 2 | B82: 256 | C82: 0, 3, 4, 5-8 | D82: 0 | E82: 0
A83: LDNO EHV: Non-Domestic Aggregated or CT Band 3 | B83: 258 | C83: 0, 3, 4, 5-8 | D83: 0 | E83: 0
A84: LDNO EHV: Non-Domestic Aggregated or CT Band 4 | B84: 259 | C84: 0, 3, 4, 5-8 | D84: 0 | E84: 0
A85: LDNO EHV: LV Site Specific No Residual | B85: 260 | C85: 0 | D85: 0 | E85: 0
A86: LDNO EHV: LV Site Specific Band 1 | B86: 325 | C86: 0 | D86: 0 | E86: 0
A87: LDNO EHV: LV Site Specific Band 2 | B87: 261 | C87: 0 | D87: 0 | E87: 0
A88: LDNO EHV: LV Site Specific Band 3 | B88: 262 | C88: 0 | D88: 0 | E88: 0
A89: LDNO EHV: LV Site Specific Band 4 | B89: 263 | C89: 0 | D89: 0 | E89: 0
A90: LDNO EHV: LV Sub Site Specific No Residual | B90: 264 | C90: 0 | D90: 0 | E90: 0
A91: LDNO EHV: LV Sub Site Specific Band 1 | B91: 326 | C91: 0 | D91: 0 | E91: 0
A92: LDNO EHV: LV Sub Site Specific Band 2 | B92: 265 | C92: 0 | D92: 0 | E92: 0
A93: LDNO EHV: LV Sub Site Specific Band 3 | B93: 266 | C93: 0 | D93: 0 | E93: 0
A94: LDNO EHV: LV Sub Site Specific Band 4 | B94: 267 | C94: 0 | D94: 0 | E94: 0
A95: LDNO EHV: HV Site Specific No Residual | B95: 269 | C95: 0 | D95: 0 | E95: 0
A96: LDNO EHV: HV Site Specific Band 1 | B96: 327 | C96: 0 | D96: 0 | E96: 0
... A99: LDNO EHV: HV Site Specific Band 4 | B99: 272 | C99: 0 | D99: 0 | E99: 0
A100: LDNO 132kV/EHV: Domestic Aggregated or CT with Residual | B100: 338, 339, 426 | C100: 0, 1, 2 | D100: 0 | E100: 0
A101: LDNO 132kV/EHV: Non-Domestic Aggregated or CT No Residual | B101: 273 | C101: 0, 3, 4, 5-8 | D101: 0 | E101: 0
A102: LDNO 132kV/EHV: Non-Domestic Aggregated or CT Band 1 | B102: 341, 342, 344, 427 | C102: 0, 3, 4, 5-8 | D102: 0 | E102: 0
A103: LDNO 132kV/EHV: Non-Domestic Aggregated or CT Band 2 | B103: 274 | C103: 0, 3, 4, 5-8 | D103: 0 | E103: 0
A104: LDNO 132kV/EHV: Non-Domestic Aggregated or CT Band 3 | B104: 276 | C104: 0, 3, 4, 5-8 | D104: 0 | E104: 0
A105: LDNO 132kV/EHV: Non-Domestic Aggregated or CT Band 4 | B105: 277 | C105: 0, 3, 4, 5-8 | D105: 0 | E105: 0
A106: LDNO 132kV/EHV: LV Site Specific No Residual | B106: 278 | C106: 0 | D106: 0 | E106: 0
A107: LDNO 132kV/EHV: LV Site Specific Band 1 | B107: 345 | C107: 0 | D107: 0 | E107: 0
A108: LDNO 132kV/EHV: LV Site Specific Band 2 | B108: 282 | C108: 0 | D108: 0 | E108: 0
A109: LDNO 132kV/EHV: LV Site Specific Band 3 | B109: 283 | C109: 0 | D109: 0 | E109: 0
...

Sheet Nodal prices
A1: Back to Overview
A2: =Overview!B4& " - Effective from "&Overview!D4&" - "&Overview!E4&" Nodal/Zonal charges" -> Northern Powergrid (Yorkshire) Plc - Effective from 1 April 2026 - Final Nodal/Zonal charges
A3: Node/Zone ID | B3: Geographical name | C3: Local charge 1 £/kVA | D3: Remote charge 1 £/kVA
A4: Girlington Stor | B4: Bradford West | C4: 0.10863642 | D4: 0.0072257567
A5: ovenden moor | B5: Bradford West | C5: 0.4063892 | D5: 0.35090323
A6: airedale road 11 (1001) | B6: Bradford West | C6: 0.40260602 | D6: 0.98236301
A7: balme street 11 (1006) | B7: Bradford West | C7: 0.28494129 | D7: 1.1506384
A8: barnoldswick 11 (1014) | B8: Bradford West | C8: 0.37399325 | D8: 7.0841763
A9: bingley 11 (1018) | B9: Bradford West | C9: 0.16825483 | D9: 0.33064929
A10: bolton road 11 (1026) | B10: Bradford West | C10: 0.33513403 | D10: 3.8647313
A11: br bingley 25 (1029) | B11: Bradford West | C11: 0 | D11: 0.075379941
A12: bramhope 11 (1034) | B12: Bradford West | C12: 0.001861697 | D12: 1.3642852
A13: chelker reservoir 11 (1038) | B13: Bradford West | C13: -0.00047253414 | D13: 4.0506643
A14: chevin end 11 (1040) | B14: Bradford West | C14: 0.015648923 | D14: 1.3176772
A15: cracoe 11 (1045) | B15: Bradford West | C15: 0.35823809 | D15: 11.039088
... A493: waverley (7011) | B493: Wincobank | C493: 0.0054899282 | D493: 0.020431552

Sheet SSC unit rate lookup
A1: Back to Overview
A28: Standard Settlement Configuration Id | B28: Standard Settlement Configuration Desc | C28: Common Decode | F28: Change implemented | G28: Date | H28: Comments
A29: 3 | B29: 10-hour OP | C29: A/R | F29: Notes updated | G29: 43626 | H29: Updated to reflect DCP 268 which delinks all tariffs from the TPR bands
A30: 4 | B30: 10-hour OP | C30: A/R | F30: Code 1 & 2 changed to A | G30: 43626 | H30: Updated to reflect DCP 268 which delinks all tariffs from the TPR bands
A31: 5 | B31: 10-hour OP + w/e | C31: A/R | F31: Code O changed to A/R | G31: 43626 | H31: Updated to reflect DCP 268 which delinks all tariffs from the TPR bands
A32: 6 | B32: 10.5-hour OP | C32: A/R | F32: Removed TPR | G32: 43626 | H32: Removed TPR lookup element as this no longer effects which rate to apply
A33: 7 | B33: 10.5-hour OP | C33: A/R
A34: 8 | B34: 10.5-hour OP | C34: A/R
A35: 9 | B35: 10.5-hour OP | C35: A/R
A36: 10 | B36: 10.5-hour OP | C36: A/R
A37: 11 | B37: 10.5-hour OP | C37: A/R
A38: 12 | B38: 10.5-hour OP | C38: A/R
A39: 13 | B39: 11 Hour OP | C39: A/R
A40: 15 | B40: 11 Hour OP | C40: A/R
A41: 16 | B41: 11.5-hour OP | C41: A/R
A42: 17 | B42: 11.5-hour OP | C42: A/R
A43: 18 | B43: 11.5-hour OP | C43: A/R
A44: 19 | B44: 11.5-hour OP | C44: A/R
... A763: 997 | B763: Evening/Weekend - BST | C763: A

Sheet Residual Charging Bands
A1: Back to Overview
A2: =Overview!B4& " - Effective from "&Overview!C4&" - "&Overview!E4&" Residual Charging Bands" -> Northern Powergrid (Yorkshire) Plc - Effective from 2026/27 - Final Residual Charging Bands
A4: Voltage of Connection | B4: Band | C4: Units | D4: Lower Threshold* | E4: Upper Threshold* | F4: Residual Charge per MPAN (£) per year
A5: Domestic Aggregated | B5: Single band | C5: - | D5: - | E5: - | F5: 19.165619
A6: Designated Properties connected at LV, billing with no MIC | B6: 1 | C6: kWh | D6: 0 | E6: 3986 | F6: 20.856112
B7: 2 | C7: kWh | D7: 3986 | E7: 13677 | F7: 52.071101
B8: 3 | C8: kWh | D8: 13677 | E8: 27543 | F8: 108.92262
B9: 4 | C9: kWh | D9: 27543 | E9: ∞ | F9: 302.85002
A10: Designated Properties connected at LV, billing with MIC | B10: 1 | C10: kVA | D10: 0 | E10: 90 | F10: 506.25155
B11: 2 | C11: kVA | D11: 90 | E11: 150 | F11: 1013.0305
B12: 3 | C12: kVA | D12: 150 | E12: 250 | F12: 1525.1239
B13: 4 | C13: kVA | D13: 250 | E13: ∞ | F13: 3176.0294
A14: Designated Properties connected at HV | B14: 1 | C14: kVA | D14: 0 | E14: 500 | F14: 3028.6338
B15: 2 | C15: kVA | D15: 500 | E15: 1100 | F15: 9076.2361
B16: 3 | C16: kVA | D16: 1100 | E16: 2000 | F16: 18559.785
B17: 4 | C17: kVA | D17: 2000 | E17: ∞ | F17: 45256.099
A18: Designated EHV Properties | B18: 1 | C18: kVA | D18: 0 | E18: 3500 | F18: 8010.0251
B19: 2 | C19: kVA | D19: 3500 | E19: 11000 | F19: 48071.768
B20: 3 | C20: kVA | D20: 11000 | E20: 20000 | F20: 132534.86
B21: 4 | C21: kVA | D21: 20000 | E21: ∞ | F21: 376746.25
A22: * All boundaries are inclusive of the upper threshold and exclusive of the lower threshold i.e. Lower < x ≤ Upper.

Sheet TNUoS Mapping
A1: Back to Overview
A2: =Overview!B4& " - Effective from "&Overview!C4&" -"&" TNUoS Mapping" -> Northern Powergrid (Yorkshire) Plc - Effective from 2026/27 - TNUoS Mapping
A4: DUoS Tariff name | B4: TNUoS Site Charging Band
A5: Domestic Aggregated or CT with Residual | B5: Domestic
A6: Domestic Aggregated (Related MPAN) | B6: n/a (Non-Final Demand Site)
A7: Non-Domestic Aggregated or CT No Residual | B7: =$B$6 -> n/a (Non-Final Demand Site)
A8: Non-Domestic Aggregated or CT Band 1 | B8: LV_NoMIC_1
A9: Non-Domestic Aggregated or CT Band 2 | B9: LV_NoMIC_2
A10: Non-Domestic Aggregated or CT Band 3 | B10: LV_NoMIC_3
A11: Non-Domestic Aggregated or CT Band 4 | B11: LV_NoMIC_4
A12: Non-Domestic Aggregated (related MPAN) | B12: =$B$6 -> n/a (Non-Final Demand Site)
A13: LV Site Specific No Residual | B13: =$B$6 -> n/a (Non-Final Demand Site)
A14: LV Site Specific Band 1 | B14: LV1
A15: LV Site Specific Band 2 | B15: LV2
A16: LV Site Specific Band 3 | B16: LV3
A17: LV Site Specific Band 4 | B17: LV4
A18: LV Sub Site Specific No Residual | B18: =$B$6 -> n/a (Non-Final Demand Site)
A19: LV Sub Site Specific Band 1 | B19: LV1
A20: LV Sub Site Specific Band 2 | B20: LV2
A21: LV Sub Site Specific Band 3 | B21: LV3
A22: LV Sub Site Specific Band 4 | B22: LV4
A23: HV Site Specific No Residual | B23: =$B$6 -> n/a (Non-Final Demand Site)
A24: HV Site Specific Band 1 | B24: HV1
A25: HV Site Specific Band 2 | B25: HV2
A26: HV Site Specific Band 3 | B26: HV3
A27: HV Site Specific Band 4 | B27: HV4
A28: Unmetered Supplies | B28: n/a (p/kWh charge)
A29: LV Generation Aggregated | B29: =$B$6 -> n/a (Non-Final Demand Site)
A30: LV Sub Generation Aggregated | B30: =$B$6 -> n/a (Non-Final Demand Site)
A31: LV Generation Site Specific | B31: =$B$6 -> n/a (Non-Final Demand Site)
A32: LV Generation Site Specific no RP charge | B32: =$B$6 -> n/a (Non-Final Demand Site)
A33: LV Sub Generation Site Specific | B33: =$B$6 -> n/a (Non-Final Demand Site)
A34: LV Sub Generation Site Specific no RP charge | B34: =$B$6 -> n/a (Non-Final Demand Site)
A35: HV Generation Site Specific | B35: =$B$6 -> n/a (Non-Final Demand Site)
A36: HV Generation Site Specific no RP charge | B36: =$B$6 -> n/a (Non-Final Demand Site)
A37: Designated EHV Site Specific No Residual | B37: =$B$6 -> n/a (Non-Final Demand Site)
A38: Designated EHV Site Specific Band 1 | B38: EHV1
A39: Designated EHV Site Specific Band 2 | B39: EHV2
A40: Designated EHV Site Specific Band 3 | B40: EHV3
A41: Designated EHV Site Specific Band 4 | B41: EHV4

Sheet Charge Calculator
B1: Back to Overview
B2: =Overview!B4& " - Effective from "&Overview!D4&" - "&Overview!E4 -> Northern Powergrid (Yorkshire) Plc - Effective from 1 April 2026 - Final
B4: LV and HV designated properties and Unmetered Supplies tariff calculator | L4: EHV designated property calculator
B5: Step 1, Choose your tariff using the drop down list in cell B10 | L5: Step 1, Choose your tariff using the drop down list in cell L10
B6: Step 2, After selecting a tariff in step 1, Cells C12-I12 will generate headings, please enter your consumption in cells C13:I13 underneath each heading generated (if no heading leave cell blank) | L6: Step 2, After selecting a tariff in step 1, Cells M12-T12 will generate headings, please enter your consumption in cells M13:T13 underneath each heading generated (if no heading leave cell blank)
B7: Step 3, Enter a forecast of consumption if required in cells C14:I14 | L7: Step 3, Enter a forecast of consumption if required in cells M14:T14
B9: Tariff details Choose tariff name from drop down box below | C9: ='Annex 1 LV, HV and UMS charges'!D11 -> Red/black unit charge p/kWh | D9: ='Annex 1 LV, HV and UMS charges'!E11 -> Amber/yellow unit charge p/kWh | E9: ='Annex 1 LV, HV and UMS charges'!F11 -> Green unit charge p/kWh | F9: ='Annex 1 LV, HV and UMS charges'!G11 -> Fixed charge p/MPAN/day | G9: ='Annex 1 LV, HV and UMS charges'!H11 -> Capacity charge p/kVA/day | H9: ='Annex 1 LV, HV and UMS charges'!I11 -> Exceeded capacity charge p/kVA/day | I9: ='Annex 1 LV, HV and UMS charges'!J11 -> Reactive power charge p/kVArh | L9: Site details Choose the site name from the drop down box below | M9: ='Annex 2 Designated EHV charges'!I9 -> Import Super Red unit charge (p/kWh) | N9: ='Annex 2 Designated EHV charges'!J9 -> Import fixed charge (p/day) | O9: ='Annex 2 Designated EHV charges'!K9 -> Import capacity charge (p/kVA/day) | P9: ='Annex 2 Designated EHV charges'!L9 -> Import exceeded capacity charge (p/kVA/day) | Q9: ='Annex 2 Designated EHV charges'!M9 -> Export Super Red unit charge (p/kWh) | R9: ='Annex 2 Designated EHV charges'!N9 -> Export fixed charge (p/day) | S9: ='Annex 2 Designated EHV charges'!O9 -> Export capacity charge (p/kVA/day) | T9: ='Annex 2 Designated EHV charges'!P9 -> Export exceeded capacity charge (p/kVA/day)
C10: =IFERROR(VLOOKUP($B$10,'Annex 1 LV, HV and UMS charges'!$A:$K,4,FALSE),"") | D10: =IFERROR(VLOOKUP($B$10,'Annex 1 LV, HV and UMS charges'!$A:$K,5,FALSE),"") | E10: =IFERROR(VLOOKUP($B$10,'Annex 1 LV, HV and UMS charges'!$A:$K,6,FALSE),"") | F10: =IFERROR(VLOOKUP($B$10,'Annex 1 LV, HV and UMS charges'!$A:$K,7,FALSE),"") | G10: =IFERROR(VLOOKUP($B$10,'Annex 1 LV, HV and UMS charges'!$A:$K,8,FALSE),"") | H10: =IFERROR(VLOOKUP($B$10,'Annex 1 LV, HV and UMS charges'!$A:$K,9,FALSE),"") | I10: =IFERROR(VLOOKUP($B$10,'Annex 1 LV, HV and UMS charges'!$A:$K,10,FALSE),"") | M10: =IFERROR(VLOOKUP($L$10,'Annex 2 Designated EHV charges'!$G:$P,3,FALSE),"") | N10: =IFERROR(VLOOKUP($L$10,'Annex 2 Designated EHV charges'!$G:$P,4,FALSE),"") | O10: =IFERROR(VLOOKUP($L$10,'Annex 2 Designated EHV charges'!$G:$P,5,FALSE),"") | P10: =IFERROR(VLOOKUP($L$10,'Annex 2 Designated EHV charges'!$G:$P,6,FALSE),"") | Q10: =IFERROR(VLOOKUP($L$10,'Annex 2 Designated EHV charges'!$G:$P,7,FALSE),"") | R10: =IFERROR(VLOOKUP($L$10,'Annex 2 Designated EHV charges'!$G:$P,8,FALSE),"") | S10: =IFERROR(VLOOKUP($L$10,'Annex 2 Designated EHV charges'!$G:$P,9,FALSE),"") | T10: =IFERROR(VLOOKUP($L$10,'Annex 2 Designated EHV charges'!$G:$P,10,FALSE),"")
B12: Tariff components | C12: =C9 -> Red/black unit charge p/kWh | D12: =D9 -> Amber/yellow unit charge p/kWh | E12: =E9 -> Green unit charge p/kWh | F12: Number of days in consumption period i.e. 365 if one year | G12: Maximum import or export capacity kVA | H12: Average daily exceeded capacity kVA | I12: Excess reactive units kVArh | L12: Tariff components | M12: Import super red kWh | N12: Number of days in consumption period i.e. 365 if one year | O12: Maximum import capacity kVA | P12: Average daily exceeded capacity kVA | Q12: Export Super Red kWh | R12: Number of days in consumption period i.e. 365 if one year | S12: Maximum export capacity kVA | T12: Average daily exceeded capacity kVA
B13: Enter current consumption details | L13: Enter current consumption details | R13: =N13 -> 0
B14: Enter forecast consumption details (if different) | C14: =C13 -> 0 | D14: =D13 -> 0 | E14: =E13 -> 0 | F14: =F13 -> 0 | G14: =G13 -> 0 | H14: =H13 -> 0 | I14: =I13 -> 0 | L14: Enter forecast consumption details (if different) | M14: =M13 -> 0 | N14: =N13 -> 0 | O14: =O13 -> 0 | P14: =P13 -> 0 | Q14: =Q13 -> 0 | R14: =R13 -> 0 | S14: =S13 -> 0 | T14: =T13 -> 0
B16: Charge components | C16: Unit 1 £ | D16: Unit 2 £ | E16: Unit 3 £ | F16: Fixed charge £ | G16: Capacity charge £ | H16: Exceeded capacity charge £ | I16: Reactive power charge £ | L16: Charge components | M16: Import super red charge £ | N16: Import fixed charge £ | O16: Import capacity charge £ | P16: Import exceeded capacity charge £ | Q16: Export super red charge £ | R16: Export fixed charge £ | S16: Export capacity charge £ | T16: Export exceeded capacity charge £
B17: Current consumption period charges | C17: =IFERROR(C10*C13/100,"") | D17: =IFERROR(D10*D13/100,"") | E17: =IFERROR(E10*E13/100,"") | F17: =IFERROR(F10*F13/100,"") | G17: =IFERROR(G10*G13*F13/100,"") | H17: =IFERROR(H10*H13*F13/100,"") | I17: =IFERROR(I10*I13/100,"") | L17: Current consumption period charges | M17: =IFERROR(M10*M13/100,"") | N17: =IFERROR(N10*N13/100,"") | O17: =IFERROR(O10*O13*N13/100,"") | P17: =IFERROR(P10*P13*N13/100,"") | Q17: =IFERROR(Q10*Q13/100,"") | R17: =IFERROR(R10*R13/100,"") | S17: =IFERROR(S10*S13*R13/100,"") | T17: =IFERROR(T10*T13*R13/100,"")
B18: Forecast consumption period charges | C18: =IFERROR(C10*C14/100,"") | D18: =IFERROR(D10*D14/100,"") | E18: =IFERROR(E10*E14/100,"") | F18: =IFERROR(F10*F14/100,"") | G18: =IFERROR(G10*G14*F14/100,"") | H18: =IFERROR(H10*H14*F14/100,"") | I18: =IFERROR(I10*I14/100,"") | L18: Forecast consumption period charges | M18: =IFERROR(M10*M14/100,"") | N18: =IFERROR(N10*N14/100,"") | O18: =IFERROR(O10*O14*N14/100,"") | P18: =IFERROR(P10*P14*N14/100,"") | Q18: =IFERROR(Q10*Q14/100,"") | R18: =IFERROR(R10*R14/100,"") | S18: =IFERROR(S10*S14*R14/100,"") | T18: =IFERROR(T10*T14*R14/100,"")
C20: Total charge £ | M20: Import total charge £ | N20: Export total charge £
B21: Current consumption period charges | C21: =SUM(C17:I17) -> 0 | L21: Current consumption period charges | M21: =SUM(M17:P17) -> 0 | N21: =SUM(Q17:T17) -> 0
B22: Forecast consumption period charges | C22: =SUM(C18:I18) -> 0 | L22: Forecast consumption period charges | M22: =SUM(M18:P18) -> 0 | N22: =SUM(Q18:T18) -> 0
B24: These charges are estimates based on tariff selected and consumption values entered. | L24: These charges are estimates based on site selected and consumption values entered.
