Workbook
Name OLE_LINK1: 'Annex 3 Preserved charges'!#REF!

Sheet Overview
A2: Company and Licence name, charging year, effective from, status
B3: Company and Licence name | C3: Year | D3: Effective From | E3: Status
A4: Company and Licence name, charging year, effective from, status | B4: Eastern Power Networks | C4: 2017/2018 | D4: 01/04/2017 | E4: Final
A6: List of data tables in this workbook
A7: Worksheet | B7: Information
A8: Annex 1 LV and HV charges | B8: Annex 1 contains charges to LV and HV Designated Properties.
A9: Annex 2 EHV charges | B9: ="Annex 2 contains the charges to Designated EHV Properties and charges applied to LDNOs with Designated EHV Properties/end-users embedded in networks within the " &B4 &" Licence area." -> Annex 2 contains the charges to Designated EHV Properties and charges applied to LDNOs with Designated EHV Properties/end-users embedded in networks within the Eastern Power Networks Licence area.
A10: Annex 3 Preserved charges | B10: Annex 3 contains details of any preserved and additional charges that are valid at this time.
A11: Annex 4 LDNO charges | B11: ="Annex 4 contains charges that are levied on the owner of an embedded network within the "&B4&" Licence area. "&"Electricity suppliers and consumers who have properties connected to an embedded network should contact the embedded network owner to determine their distribution charges."&" The charges listed in this table are not payable by domestic consumers, business consumers or electricity suppliers." -> Annex 4 contains charges that are levied on the owner of an embedded network within the Eastern Power Networks Licence area. Electricity suppliers and consumers who have properties connected to an embedded network should contact the embedded network owner to determine their distribution charges. The charges listed in this table are not payable by domestic consumers, business consumers or electricity suppliers.
A12: Annex 5 LLFs | B12: Annex 5 contains illustrative LLFs. LLFs are used in Settlement to adjust the metering system volumes to take account of losses on the distribution network. Illustrative LLFs are provided with reference to the metered voltage or associated LLFC for generic LLFs and by reference to the LLFCs for site specific LLFs. Each LLF is applicable to a defined time period. The LLFs used in Settlement are published on the Elexon portal website, www.elexonportal.co.uk. The website contains the LLFs in standard industry data formats and in a summary form. A user guide with details on registering and using the portal is also available.
A13: Annex 6 new Designated EHV Properties | B13: ="Annex 6 contains the charges to new Designated EHV Properties and charges applied to LDNOs with new Designated EHV Properties/end-users embedded in networks within the " &B4 &" Licence area." -> Annex 6 contains the charges to new Designated EHV Properties and charges applied to LDNOs with new Designated EHV Properties/end-users embedded in networks within the Eastern Power Networks Licence area.
A14: Nodal prices | B14: Contains the underlying [nodal/network group] costs used to calculate the current EDCM charges.
A15: SSC TPR to unit rate lookup table | B15: The time periods for the non half hourly metered charge rates in Annex 1 are as specified by the SSC. To determine the appropriate charge rate for each SSC/TPR a lookup table is provided.
A16: Charge calculator | B16: Charge calculator is a tool to help you estimate your distribution charges using current consumption data and forecast consumption data.
A18: Notes to users of this spreadsheet
A20: Please use this spreadsheet with reference to the LC14 use of system charging statement.
A22: Notes to DNOs populating this spreadsheet
A24: DNOs must endeavour to maintain consistency in the structure of this spreadsheet. Any changes to the structure must be noted in the 'Notes to users of this spreadsheet'
A25: The drop down list on the charge calculator can be expanded by unprotecting the charge calculator sheet and selecting 'data', 'data validation...' and then expanding the 'source' data range. The sheet can then be protected.

Sheet Annex 1 LV and HV charges
A1: Back to Overview | B1: 'DNOs paste value cells A15:I41 from CDCM 3701 into cells A14:I40
A2: =Overview!B4& " - Effective from "&Overview!D4&" - "&Overview!E4&" LV and HV charges" -> Eastern Power Networks - Effective from 01/04/2017 - Final LV and HV charges
A4: Time Bands for Half Hourly Metered Properties | G4: Time Bands for Half Hourly Unmetered Properties
A5: Time periods | B5: Red Time Band | C5: Amber Time Band | E5: Green Time Band | I5: Black Time Band | J5: Yellow Time Band | K5: Green Time Band
A6: Monday to Friday (Including Bank Holidays) All Year | B6: 16:00 - 19:00 | C6: 07:00 - 16:00 19.00 - 23.00 | E6: 00:00 - 07:00 23:00 - 24:00 | G6: Monday to Friday (Including Bank Holidays) November to February Inclusive | I6: 16:00 - 19:00 | J6: 07:00 - 16:00 19:00 - 23:00 | K6: 00:00 - 07:00 23:00 - 24:00
A7: Saturday and Sunday All Year | E7: 00:00 - 24:00 | G7: Monday to Friday (Including Bank Holidays) March to October Inclusive | J7: 07:00 - 23:00 | K7: 00:00 - 07:00 23:00 - 24:00
A8: Notes | B8: All times are in UK Clock time | G8: Saturday and Sunday All Year | K8: 00:00 - 24:00
G9: Notes | I9: All times are in UK Clock time
A13: Tariff name | B13: Open LLFCs | C13: PCs | D13: Unit charge 1 (NHH) or red/black charge (HH) p/kWh | E13: Unit charge 2 (NHH) or amber/yellow charge (HH) p/kWh | F13: Green charge(HH) p/kWh | G13: Fixed charge p/MPAN/day | H13: Capacity charge p/kVA/day | I13: Reactive power charge p/kVArh | J13: Exceeded capacity charge p/kVA/day | K13: Closed LLFCs
A14: Domestic Unrestricted | B14: 3, 40 | C14: 1 | D14: 1.998 | E14: 0 | F14: 0 | G14: 4.69 | H14: 0 | I14: 0
A15: Domestic Two Rate | B15: 7, 11, 25, 43, 46, 58 | C15: 2 | D15: 2.396 | E15: 0.03 | F15: 0 | G15: 4.69 | H15: 0 | I15: 0
A16: Domestic Off Peak (related MPAN) | B16: 22, 29, 55, 61 | C16: 2 | D16: 0.092 | E16: 0 | F16: 0 | G16: 0 | H16: 0 | I16: 0
A17: Small Non Domestic Unrestricted | B17: 201, 237, 238, 239 | C17: 3 | D17: 1.535 | E17: 0 | F17: 0 | G17: 5.05 | H17: 0 | I17: 0
A18: Small Non Domestic Two Rate | B18: 15, 49, 205, 242, 247, 248 | C18: 4 | D18: 1.838 | E18: 0.03 | F18: 0 | G18: 5.05 | H18: 0 | I18: 0
A19: Small Non Domestic Off Peak (related MPAN) | B19: 33, 64 | C19: 4 | D19: 0.18 | E19: 0 | F19: 0 | G19: 0 | H19: 0 | I19: 0
A20: LV Medium Non-Domestic | B20: 250, 254 | C20: 5-8 | D20: 1.733 | E20: 0.023 | F20: 0 | G20: 32.92 | H20: 0 | I20: 0
A21: LV Sub Medium Non-Domestic | D21: 1.044 | E21: 0.013 | F21: 0 | G21: 10.19 | H21: 0 | I21: 0
A22: HV Medium Non-Domestic | D22: 0.685 | E22: 0.004 | F22: 0 | G22: 102.52 | H22: 0 | I22: 0
A23: LV Network Domestic | B23: 1 | C23: 0 | D23: 15.253 | E23: 0.131 | F23: 0.023 | G23: 4.69 | H23: 0 | I23: 0
A24: LV Network Non-Domestic Non-CT | B24: 200 | C24: 0 | D24: 13.855 | E24: 0.119 | F24: 0.021 | G24: 5.37 | H24: 0 | I24: 0
A25: LV HH Metered | B25: 86 | C25: 0 | D25: 10.911 | E25: 0.078 | F25: 0.014 | G25: 14.87 | H25: 3.15 | I25: 0.332 | J25: =H25 -> 3.15
A26: LV Sub HH Metered | B26: 80 | C26: 0 | D26: 7.717 | E26: 0.035 | F26: 0.007 | G26: 10.19 | H26: 4.67 | I26: 0.215 | J26: =H26 -> 4.67
A27: HV HH Metered | B27: 84 | C27: 0 | D27: 6.384 | E27: 0.02 | F27: 0.004 | G27: 102.52 | H27: 3.87 | I27: 0.179 | J27: =H27 -> 3.87
A28: NHH UMS category A | B28: 100, 110, 150, 160 | C28: 8 | D28: 1.749 | E28: 0 | F28: 0 | G28: 0 | H28: 0 | I28: 0
A29: NHH UMS category B | B29: 102, 112, 152, 162 | C29: 1 | D29: 2.604 | E29: 0 | F29: 0 | G29: 0 | H29: 0 | I29: 0
A30: NHH UMS category C | B30: 103, 113, 153, 163 | C30: 1 | D30: 4.43 | E30: 0 | F30: 0 | G30: 0 | H30: 0 | I30: 0
A31: NHH UMS category D | B31: 101, 111, 151, 161 | C31: 1 | D31: 1.181 | E31: 0 | F31: 0 | G31: 0 | H31: 0 | I31: 0
A32: LV UMS (Pseudo HH Metered) | B32: 350 | C32: 0 | D32: 39.655 | E32: 0.653 | F32: 0.552 | G32: 0 | H32: 0 | I32: 0
A33: LV Generation NHH or Aggregate HH | B33: 905, 912, 913 | C33: 8 or 0 | D33: -0.905 | E33: 0 | F33: 0 | G33: 0 | H33: 0 | I33: 0
A34: LV Sub Generation NHH | D34: -0.802 | E34: 0 | F34: 0 | G34: 0 | H34: 0 | I34: 0
A35: LV Generation Intermittent | B35: 901 | C35: 0 | D35: -0.905 | E35: 0 | F35: 0 | G35: 0 | H35: 0 | I35: 0.289
A36: LV Generation Non-Intermittent | B36: 915 | C36: 0 | D36: -9.684 | E36: -0.09 | F36: -0.016 | G36: 0 | H36: 0 | I36: 0.289
A37: LV Sub Generation Intermittent | B37: 902 | C37: 0 | D37: -0.802 | E37: 0 | F37: 0 | G37: 0 | H37: 0 | I37: 0.259
A38: LV Sub Generation Non-Intermittent | B38: 916 | C38: 0 | D38: -8.626 | E38: -0.072 | F38: -0.013 | G38: 0 | H38: 0 | I38: 0.259
A39: HV Generation Intermittent | B39: 903 | C39: 0 | D39: -0.577 | E39: 0 | F39: 0 | G39: 48.95 | H39: 0 | I39: 0.211
A40: HV Generation Non-Intermittent | B40: 918 | C40: 0 | D40: -6.312 | E40: -0.03 | F40: -0.006 | G40: 48.95 | H40: 0 | I40: 0.211

Sheet Annex 2 EHV charges
A1: Back to Overview | C1: Copy EDCM table 5001 range starting B101 and paste into G11. Extend or reduce print area as required. | F1: Note: The list of MPANs / MSIDs provided may be incomplete; the DNO reserves the right to apply the listed charges to any other MPANs / MSIDs associated with the site.
A2: =Overview!B4& " - Effective from "&Overview!D4&" - "&Overview!E4&" EDCM charges" -> Eastern Power Networks - Effective from 01/04/2017 - Final EDCM charges
A4: Time Periods for Designated EHV Properties
A5: Time periods | D5: Super Red Time Band
A6: Monday to Friday (Including Bank Holidays) November to February Inclusive | D6: 16:00 - 19:00
A7: Notes | D7: All times are in UK Clock time
A10: Import Unique Identifier | B10: LLFC | C10: Import MPANs/MSIDs | D10: Export Unique Identifier | E10: LLFC | F10: Export MPANs/MSIDs | G10: Name | H10: Import Super Red unit charge (p/kWh) | I10: Import fixed charge (p/day) | J10: Import capacity charge (p/kVA/day) | K10: Import exceeded capacity charge (p/kVA/day) | L10: Export Super Red unit charge (p/kWh) | M10: Export fixed charge (p/day) | N10: Export capacity charge (p/kVA/day) | O10: Export exceeded capacity charge (p/kVA/day)
A11: 3VALSW | B11: 771 | C11: 1014569699836 | G11: AFFINITY WATER LIMITED | H11: 0.717 | I11: 178.32 | J11: 5.56 | K11: 5.56 | L11: 0 | M11: 0 | N11: 0 | O11: 0
A12: ABSRSF | B12: 869 | C12: 1050000574685 | D12: ABSRSF | E12: 744 | F12: 1050000574694 | G12: ABBOTS RIPTON SOLAR ENERGY LIMITED | H12: 1.908 | I12: 18.24 | J12: 3 | K12: 3 | L12: 0 | M12: 3647.93 | N12: 0.05 | O12: 0.05
A13: ADBRKS | B13: 771 | C13: 1023529546480 | G13: ADDENBROOKES NHS TRUST | H13: 1.414 | I13: 3068.14 | J13: 3.93 | K13: 3.93 | L13: 0 | M13: 0 | N13: 0 | O13: 0
A14: AIAMAN | B14: 771 | C14: 1014569292506 | D14: AIAMAN | E14: 792 | F14: 1030054607984 | G14: A I A MANAGEMENT LTD | H14: 2.944 | I14: 8.49 | J14: 19.01 | K14: 19.01 | L14: -2.844 | M14: 169.83 | N14: 0.05 | O14: 0.05
A15: ARAMAN | B15: 800 | C15: 1023483097981 | G15: AIRCRAFT RESEARCH ASSOCIATION LIMITED | H15: 0.111 | I15: 6644.17 | J15: 0.95 | K15: 0.95 | L15: 0 | M15: 0 | N15: 0 | O15: 0
A16: ARLAFD | B16: 771 | C16: 1030081553176 1030081553404 | D16: ARLAFD | E16: 792 | F16: 1030085114723 1030085114955 | G16: ARLA FOODS LIMITED | H16: 4.172 | I16: 3283.78 | J16: 1.78 | K16: 1.78 | L16: 0 | M16: 1094.59 | N16: 0.05 | O16: 0.05
A17: ASTONC | B17: 503 | C17: 1050000834246 | D17: ASTONC | E17: 780 | F17: 1050000834255 | G17: ASTON CLINTON | H17: 5.981 | I17: 2.58 | J17: 3.14 | K17: 3.14 | L17: 0 | M17: 515.71 | N17: 0.05 | O17: 0.05
A18: AVENUE | B18: 504 | C18: 1050000774970 | D18: AVENUE | E18: 781 | F18: 1050000774980 | G18: LIGHTSOURCE SPV 15 LIMITED | H18: 0.064 | I18: 17.15 | J18: 4.11 | K18: 4.11 | L18: 0 | M18: 1114.99 | N18: 0.05 | O18: 0.05
A19: AW_GRA | B19: 771 | C19: 1023477037942 1014571445536 | G19: ANGLIAN WATER SERVICES | H19: 2.419 | I19: 178.32 | J19: 6.81 | K19: 6.81 | L19: 0 | M19: 0 | N19: 0 | O19: 0
A20: AWOUSE | B20: 771 | C20: 1023475403798 1014571965793 | G20: ANGLIAN WATER SERVICES | H20: 2.605 | I20: 178.32 | J20: 4.15 | K20: 4.15 | L20: 0 | M20: 0 | N20: 0 | O20: 0
A21: BARNFM | B21: 796 | C21: 1050000774999 | D21: BARNFM | E21: 797 | F21: 1050000775005 | G21: BARN FARM SOLAR | H21: 4.001 | I21: 44.65 | J21: 6.69 | K21: 6.69 | L21: 0 | M21: 1875.31 | N21: 0.05 | O21: 0.05
A22: BAYFMS | B22: 870 | C22: 1050000579318 | D22: BAYFMS | E22: 745 | F22: 1050000579327 | G22: BAY FARM IMPORT | H22: 2.292 | I22: 31.89 | J22: 4.26 | K22: 4.26 | L22: 0 | M22: 2551.06 | N22: 0.05 | O22: 0.05
A23: BDGHSE | B23: 505 | C23: 1050000669548 | D23: BDGHSE | E23: 782 | F23: 1050000669539 | G23: BOARDINGHOUSE WINDFARM LIMITED | H23: 0.926 | I23: 28.23 | J23: 1.66 | K23: 1.66 | L23: 0 | M23: 1052.2 | N23: 0.05 | O23: 0.05
A24: BDWLWF | B24: 827 | C24: 1030082700415 | D24: BDWLWF | E24: 734 | F24: 1030082700647 | G24: RWE INNOGY UK LIMITED | H24: 2.857 | I24: 38.42 | J24: 2.59 | K24: 2.59 | L24: 0 | M24: 3938.04 | N24: 0.05 | O24: 0.05
A25: BERMAT | B25: 771 | C25: 1014571751895 | G25: BERNARD MATTHEWS LIMITED | H25: 0.474 | I25: 89.16 | J25: 6.61 | K25: 6.61 | L25: 0 | M25: 0 | N25: 0 | O25: 0
A26: BGWDWF | B26: 871 | C26: 1030083931374 | D26: BGWDWF | E26: 746 | F26: 1030083931142 | G26: BIGGLESWADE WIND FARM LIMITED | H26: 1.302 | I26: 3.39 | J26: 4.27 | K26: 4.27 | L26: 0 | M26: 278.25 | N26: 0.05 | O26: 0.05
A27: BLGTSF | B27: 534 | C27: 1050000769039 | D27: BLGTSF | E27: 466 | F27: 1050000769048 | G27: SOLAR CENTURY | H27: 4.192 | I27: 11.76 | J27: 2.87 | K27: 2.87 | L27: 0 | M27: 1117.59 | N27: 0.05 | O27: 0.05
A28: BOCTHA | B28: 803 | C28: 1014572608412 | G28: BOC LTD | H28: 2.91 | I28: 965.67 | J28: 5.03 | K28: 5.03 | L28: 0 | M28: 0 | N28: 0 | O28: 0
A29: BOXTED | B29: 506 | C29: 1050000774270 | D29: BOXTED | E29: 783 | F29: 1050000774289 | G29: PUSH ENERGY (BOXTED AIRFIELD) LIMITED | H29: 4.797 | I29: 5.88 | J29: 3.23 | K29: 3.23 | L29: 0 | M29: 952.82 | N29: 0.05 | O29: 0.05
A30: BPA_CO | B30: 804 | C30: 1014572578282 | G30: BRITISH PIPELINE AGENCY LTD | H30: 0.626 | I30: 511.57 | J30: 1.64 | K30: 1.64 | L30: 0 | M30: 0 | N30: 0 | O30: 0
A31: BPTLTD | B31: 771 | C31: 1023475256360 1014572502380 | G31: ZURICH ASSURANCE LTD | H31: 2.09 | I31: 178.32 | J31: 1.93 | K31: 1.93 | L31: 0 | M31: 0 | N31: 0 | O31: 0
A32: BRCHGP | B32: 525 | C32: 1050000961956 | D32: BRCHGP | E32: 457 | F32: 1050000961965 | G32: BIRCH GRAVEL PIT SOLAR | H32: 3.597 | I32: 43.72 | J32: 2.82 | K32: 2.82 | L32: 0 | M32: 2688.79 | N32: 0.05 | O32: 0.05
A33: BROGB_ | B33: 821 | C33: 1030041592510 1030041592742 1030041592974 1030041593203 | G33: INFINIS ENERGY SERVICES LIMITED | H33: 0.03 | I33: 228.45 | J33: 1.58 | K33: 1.58 | L33: 0 | M33: 0 | N33: 0 | O33: 0
A34: BROXSF | B34: 872 | C34: 1050000521610 | D34: BROXSF | E34: 747 | F34: 1030085039971 | G34: BROXTED SOLAR CO LTD | H34: 5.277 | I34: 11.19 | J34: 6.12 | K34: 6.12 | L34: 0 | M34: 2574.65 | N34: 0.05 | O34: 0.05
A35: BRTHS2 | B35: 508 | C35: 1050000782944 | D35: BRTHS2 | E35: 785 | F35: 1050000773842 | G35: BURNTHOUSE SOLAR LIMITED | H35: 0.521 | I35: 1.27 | J35: 3.12 | K35: 3.12 | L35: 0 | M35: 254.51 | N35: 0.05 | O35: 0.05
A36: BRTHSS | B36: 873 | C36: 1030083941266 | D36: BRTHSS | E36: 735 | F36: 1030083941034 | G36: TURVES SOLAR LTD | H36: 0.521 | I36: 2.82 | J36: 2.84 | K36: 2.84 | L36: 0 | M36: 252.96 | N36: 0.05 | O36: 0.05
A37: BRTHSW | B37: 874 | C37: 1030083918035 | D37: BRTHSW | E37: 748 | F37: 1030083917802 | G37: REG BURNHOUSE FARM LTD | H37: 0.521 | I37: 7.24 | J37: 2.13 | K37: 2.13 | L37: 0 | M37: 248.54 | N37: 0.05 | O37: 0.05
A38: BS_BUR | B38: 805 | C38: 1023485782314 | D38: BS_BUR | E38: 700 | F38: 1023485782546 | G38: ASSOCIATED BRITISH FOODS PLC | H38: 1.932 | I38: 62.7 | J38: 1.52 | K38: 1.52 | L38: -2.113 | M38: 448.87 | N38: 0.05 | O38: 0.05
A39: BS_WIS | B39: 806 | C39: 1014568635628 | D39: BS_WIS | E39: 719 | F39: 1023470427970 | G39: ASSOCIATED BRITISH FOODS PLC | H39: 0.997 | I39: 25.58 | J39: 1.39 | K39: 1.39 | L39: -0.997 | M39: 230.21 | N39: 0.05 | O39: 0.05
A40: BSBURY | B40: 796 | C40: 1050000914910 | D40: BSBURY | E40: 797 | F40: 1050000914900 | G40: ASSOCIATED BRITISH FOODS PLC | H40: 1.932 | I40: 23.25 | J40: 2.63 | K40: 2.63 | L40: -2.113 | M40: 232.53 | N40: 0.05 | O40: 0.05
A41: BSGBRN | B41: 507 | C41: 1050000773851 | D41: BSGBRN | E41: 784 | F41: 1050000773860 | G41: PUSH ENERGY (BASSINGBOURN) | H41: 0.932 | I41: 12.78 | J41: 2.16 | K41: 2.16 | L41: 0 | M41: 1533.09 | N41: 0.05 | O41: 0.05
A42: BTLCOM | B42: 771 | C42: 1050000169030 1014572546086 | G42: BRITISH TELECOMMUNICATIONS PLC | H42: 4.824 | I42: 178.32 | J42: 9.13 | K42: 9.13 | L42: 0 | M42: 0 | N42: 0 | O42: 0
A43: BURYLN | B43: 796 | C43: 1050000729676 | D43: BURYLN | E43: 786 | F43: 1050000729667 | G43: SE BURY LANE SOLAR LTD | H43: 0.862 | I43: 2.08 | J43: 2.37 | K43: 2.37 | L43: 0 | M43: 519.83 | N43: 0.05 | O43: 0.05
A44: CANTSF | B44: 875 | C44: 1030082355419 | D44: CANTSF | E44: 749 | F44: 1030081926920 | G44: HASLINGFIELD SOLAR PARK LIMITED | H44: 0.105 | I44: 23.21 | J44: 2.45 | K44: 2.45 | L44: 0 | M44: 1160.65 | N44: 0.05 | O44: 0.05
A45: CHEDSF | B45: 876 | C45: 1030083806488 | D45: CHEDSF | E45: 750 | F45: 1030083806256 | G45: ADALINDA SOLAR SPV1 LTD | H45: 0.722 | I45: 8.18 | J45: 3.16 | K45: 3.16 | L45: 0 | M45: 1020.54 | N45: 0.05 | O45: 0.05
A46: CHFARM | B46: 796 | C46: 1050000961983 | D46: CHFARM | E46: 797 | F46: 1050000961992 | G46: CHURCH FARM SOLAR | H46: 0.292 | I46: 48.68 | J46: 5.49 | K46: 5.49 | L46: 0 | M46: 2531.48 | N46: 0.05 | O46: 0.05
A47: CHPLOW | B47: 796 | C47: 1050000948022 | D47: CHPLOW | E47: 797 | F47: 1050000948031 | G47: CHIPLOW WIND FARM | H47: 1.718 | I47: 29.89 | J47: 3.68 | K47: 3.68 | L47: 0 | M47: 3587.35 | N47: 0.05 | O47: 0.05
A48: CLTSHL | B48: 535 | C48: 1050000841917 | D48: CLTSHL | E48: 467 | F48: 1050000841926 | G48: SCOTTOW MOOR SOLAR LIMITED | H48: 0.121 | I48: 6.79 | J48: 8.02 | K48: 8.02 | L48: 0 | M48: 339.5 | N48: 0.05 | O48: 0.05
A49: CMEXUK | B49: 771 | C49: 1014571132500 1023474247588 | G49: CEMEX UK OPERATIONS LIMITED | H49: 4.266 | I49: 178.32 | J49: 3.06 | K49: 3.06 | L49: 0 | M49: 0 | N49: 0 | O49: 0
A50: COLDHA | B50: 808 | C50: 1030017556367 | G50: SCOTTISHPOWER STRATEGIC TRANSACTIONS | H50: 0.622 | I50: 25.02 | J50: 2.95 | K50: 2.95 | L50: 0 | M50: 0 | N50: 0 | O50: 0
A51: CROYDN | B51: 509 | C51: 1050000808859 | D51: CROYDN | E51: 787 | F51: 1050000808868 | G51: PUSH ENERGY (CROYDON) LIMITED | H51: 0.104 | I51: 1.68 | J51: 1.92 | K51: 1.92 | L51: 0 | M51: 897.75 | N51: 0.05 | O51: 0.05
A52: CTWDFM | B52: 835 | C52: 1030079565056 | D52: CTWDFM | E52: 736 | F52: 1030079564823 | G52: COTTON FARM WIND FARM LIMITED | H52: 0.129 | I52: 11.49 | J52: 2.15 | K52: 2.15 | L52: 0 | M52: 942.44 | N52: 0.05 | O52: 0.05
A53: DBLANE | B53: 878 | C53: 1050000612950 | D53: DBLANE | E53: 752 | F53: 1050000612940 | G53: SOLAR WOODWALTON LIMITED | H53: 1.97 | I53: 7.68 | J53: 4.34 | K53: 4.34 | L53: 0 | M53: 1383.04 | N53: 0.05 | O53: 0.05
A54: DGRLTY | B54: 771 | C54: 1030050289278 1030050289506 | G54: HSBC BANK PLC | H54: 1.552 | I54: 6509.85 | J54: 1.69 | K54: 1.69 | L54: 0 | M54: 0 | N54: 0 | O54: 0
A55: DRABED | B55: 809 | C55: 1014572509517 | G55: BAP LOAN CO LIMITED | H55: 0.093 | I55: 7705.09 | J55: 1.35 | K55: 1.35 | L55: 0 | M55: 0 | N55: 0 | O55: 0
A56: DRAPER | B56: 879 | C56: 1050000581432 | D56: DRAPER | E56: 753 | F56: 1050000581441 | G56: DRAPERS FARM SOLAR | H56: 0 | I56: 5.3 | J56: 2.23 | K56: 2.23 | L56: 0 | M56: 529.55 | N56: 0.05 | O56: 0.05
A57: DRYHSE | B57: 877 | C57: 1050000609423 | D57: DRYHSE | E57: 751 | F57: 1050000609380 | G57: SUNSAVE 25 (WIX LODGE FARM) LIMITED | H57: 3.983 | I57: 1.87 | J57: 8.22 | K57: 8.22 | L57: 0 | M57: 561.41 | N57: 0.05 | O57: 0.05
A58: EARLHF | B58: 841 | C58: 1030081316739 | D58: EARLHF | E58: 737 | F58: 1030081316960 | G58: GEM WIND FARM 2 LIMITED | H58: 4.055 | I58: 3.56 | J58: 2.03 | K58: 2.03 | L58: 0 | M58: 355.66 | N58: 0.05 | O58: 0.05
A59: EBCKHM | B59: 887 | C59: 1050000609441 | D59: EBCKHM | E59: 761 | F59: 1050000563595 | G59: HALL SOLAR LIMITED | H59: 0.047 | I59: 1.44 | J59: 7.71 | K59: 7.71 | L59: 0 | M59: 275.03 | N59: 0.05 | O59: 0.05
A60: EDLMUC | B60: 810 | C60: 1023497822125 1023497822357 1023514863056 1030010107819 | G60: NON FOSSIL PURCHASING AGENCY | H60: 0.058 | I60: 7.31 | J60: 1.65 | K60: 1.65 | L60: 0 | M60: 0 | N60: 0 | O60: 0
A61: EDLPIT | B61: 811 | C61: 1030020271288 | G61: NON FOSSIL PURCHASING AGENCY | H61: 0.904 | I61: 22.89 | J61: 1.63 | K61: 1.63 | L61: 0 | M61: 0 | N61: 0 | O61: 0
A62: EGMRSF | B62: 880 | C62: 1050000567483 | D62: EGMRSF | E62: 754 | F62: 1050000567492 | G62: EGMERE AIRFIELD SOLAR PARK LIMITED | H62: 1.727 | I62: 5.07 | J62: 3.42 | K62: 3.42 | L62: 0 | M62: 537.53 | N62: 0.05 | O62: 0.05
A63: ELLOSF | B63: 881 | C63: 1050000612880 | D63: ELLOSF | E63: 755 | F63: 1050000612870 | G63: ELLOUGH SOLAR LLP | H63: 0.51 | I63: 4.68 | J63: 3.15 | K63: 3.15 | L63: 0 | M63: 1075.75 | N63: 0.05 | O63: 0.05
A64: ELSAGE | B64: 796 | C64: 1050000923668 | D64: ELSAGE | E64: 797 | F64: 1050000923677 | G64: MAGNETAR SOLAR (UK) LTD | H64: 0.308 | I64: 15.85 | J64: 5.62 | K64: 5.62 | L64: 0 | M64: 950.81 | N64: 0.05 | O64: 0.05
A65: EMR_TI | B65: 813 | C65: 1023475632649 1014572805060 | G65: EUROPEAN METAL RECYCLING LTD | H65: 0.046 | I65: 511.57 | J65: 1.88 | K65: 1.88 | L65: 0 | M65: 0 | N65: 0 | O65: 0
A66: EPRSUT | B66: 812 | C66: 1023494988750 | D66: EPRSUT | E66: 705 | F66: 1023503165023 | G66: ENERGY POWER RESOURCES LTD | H66: 1.424 | I66: 253.68 | J66: 1.41 | K66: 1.41 | L66: -1.424 | M66: 1927.94 | N66: 0.05 | O66: 0.05
A67: ESWMID | B67: 771 | C67: 1014572640842 1014572641075 | D67: ESWMID | E67: 792 | F67: 1023518907371 1023518908064 | G67: NORTHUMBRIAN WATER LIMITED | H67: 6.73 | I67: 166.43 | J67: 2.99 | K67: 2.99 | L67: -6.737 | M67: 11.89 | N67: 0.05 | O67: 0.05
A68: ESWWIX | B68: 771 | C68: 1014572713989 | G68: NORTHUMBRIAN WATER | H68: 5.683 | I68: 2199.93 | J68: 5.72 | K68: 5.72 | L68: 0 | M68: 0 | N68: 0 | O68: 0
A69: EUSTSF | B69: 882 | C69: 1050000628160 | D69: EUSTSF | E69: 797 | F69: 1050000628170 | G69: HONINGTON IMPORT | H69: 3.408 | I69: 40.23 | J69: 2.43 | K69: 2.43 | L69: 0 | M69: 965.42 | N69: 0.05 | O69: 0.05
A70: EXNING | B70: 510 | C70: 1050000784384 | D70: EXNING | E70: 788 | F70: 1050000784393 | G70: DAISY NO 1 LIMITED | H70: 0.029 | I70: 10.71 | J70: 2.06 | K70: 2.06 | L70: 0 | M70: 2569.45 | N70: 0.05 | O70: 0.05
A71: EYEWFM | B71: 883 | C71: 1030085019966 | D71: EYEWFM | E71: 757 | F71: 1030085020190 | G71: EYE WIND POWER LIMITED | H71: 2.228 | I71: 9.14 | J71: 1.96 | K71: 1.96 | L71: 0 | M71: 621.58 | N71: 0.05 | O71: 0.05
A72: FBWTHE | B72: 817 | C72: 1023507304338 | D72: FBWTHE | E72: 718 | F72: 1023507304560 | G72: CEMG EXPORT PORTFOLIO | H72: 3.73 | I72: 72.26 | J72: 3.16 | K72: 3.16 | L72: -5.994 | M72: 695.1 | N72: 0.05 | O72: 0.05
A73: FENLND | B73: 511 | C73: 1050000774163 | D73: FENLND | E73: 789 | F73: 1050000774172 | G73: FENLAND SOLAR FARM | H73: 1.345 | I73: 34.51 | J73: 1.44 | K73: 1.44 | L73: 0 | M73: 3450.66 | N73: 0.05 | O73: 0.05
A74: FIBEYE | B74: 816 | C74: 1023479132092 | D74: FIBEYE | E74: 707 | F74: 1023479132320 | G74: EPR EYE POWER STATION | H74: 2.228 | I74: 17.67 | J74: 1.92 | K74: 1.92 | L74: -2.872 | M74: 300.39 | N74: 0.05 | O74: 0.05
A75: FLYFRM | B75: 512 | C75: 1050000822463 | D75: FLYFRM | E75: 790 | F75: 1050000822472 | G75: FOLLY FARM SOLAR PARK LTD | H75: 6.033 | I75: 7.5 | J75: 3.58 | K75: 3.58 | L75: 0 | M75: 1124.65 | N75: 0.05 | O75: 0.05
A76: FORD_D | B76: 818 | C76: 1015684515819 | G76: FORD MOTOR COMPANY LTD | H76: 0 | I76: 23686.5 | J76: 2.08 | K76: 2.08 | L76: 0 | M76: 0 | N76: 0 | O76: 0
A77: FRDHVS | B77: 771 | C77: 1014572810813 | G77: FORD MOTOR COMPANY LTD | H77: 0.215 | I77: 178.32 | J77: 3.72 | K77: 3.72 | L77: 0 | M77: 0 | N77: 0 | O77: 0
A78: FUJISL | B78: 771 | C78: 1023526590750 1023526590982 1023526591211 | G78: FUJITSU SERVICES LIMITED | H78: 2.634 | I78: 267.48 | J78: 3.37 | K78: 3.37 | L78: 0 | M78: 0 | N78: 0 | O78: 0
A79: FWINDS | B79: 513 | C79: 1050000709721 | D79: FWINDS | E79: 766 | F79: 1050000709730 | G79: MSP FAIRWIND LIMITED | H79: 0.107 | I79: 3.04 | J79: 2.01 | K79: 2.01 | L79: 0 | M79: 304.45 | N79: 0.05 | O79: 0.05
A80: FXDFAG | B80: 771 | C80: 1014572633250 1023479907422 | G80: HUTCHISON PORTS (UK) LTD | H80: 0.545 | I80: 178.32 | J80: 4.33 | K80: 4.33 | L80: 0 | M80: 0 | N80: 0 | O80: 0
A81: FXDOYS | B81: 771 | C81: 1023482441566 1023492579962 | G81: HUTCHISON PORTS (UK) LTD | H81: 0.545 | I81: 178.32 | J81: 4.24 | K81: 4.24 | L81: 0 | M81: 0 | N81: 0 | O81: 0
A82: GDE132 | B82: 514 | C82: 1050000738305 | D82: GDE132 | E82: 767 | F82: 1050000738290 | G82: GOOD ENERGY WEST RAYNHAM SOLAR PARK (030) LTD | H82: 0.143 | I82: 20.42 | J82: 2.41 | K82: 2.41 | L82: 0 | M82: 1018.74 | N82: 0.05 | O82: 0.05
A83: GFTHRN | B83: 796 | C83: 1050000903244 | D83: GFTHRN | E83: 797 | F83: 1050000903253 | G83: REDSTOW RENEWABLES LIMITED | H83: 1.565 | I83: 51.68 | J83: 3.84 | K83: 3.84 | L83: 0 | M83: 718.47 | N83: 0.05 | O83: 0.05
A84: GLASM2 | B84: 865 | C84: 1030083962424 | D84: GLASM2 | E84: 738 | F84: 1030083962656 | G84: GLASS MOOR 2 WIND FARM LTD | H84: 0.465 | I84: 44.19 | J84: 2.15 | K84: 2.15 | L84: 0 | M84: 2173.97 | N84: 0.05 | O84: 0.05
A85: GLASSM | B85: 814 | C85: 1030024800679 | G85: GLASS MOOR WINDFARM | H85: 0.463 | I85: 11.39 | J85: 2.17 | K85: 2.17 | L85: 0 | M85: 0 | N85: 0 | O85: 0
A86: GLXOST | B86: 771 | C86: 1014569657748 1014569657970 | G86: GLAXOSMITHKLINE SERVICES UNLIMITED | H86: 1.717 | I86: 178.32 | J86: 4.76 | K86: 4.76 | L86: 0 | M86: 0 | N86: 0 | O86: 0
A87: GLXOWR | B87: 771 | C87: 1023475635409 1023475634488 1023484819994 1023475633563 | D87: GLXOWR | E87: 792 | F87: 1030074763340 1030074763118 | G87: GLAXOSMITHKLINE SERVICES UNLIMITED | H87: 2.603 | I87: 624.13 | J87: 1.73 | K87: 1.73 | L87: -2.611 | M87: 0 | N87: 0.05 | O87: 0.05
A88: GOSFLD | B88: 515 | C88: 1050000714216 | D88: GOSFLD | E88: 768 | F88: 1050000714207 | G88: PUSH ENERGY (GOSFIELD AIRFIELD) LIMITED | H88: 1.324 | I88: 190.17 | J88: 5.49 | K88: 5.49 | L88: 0 | M88: 2053.84 | N88: 0.05 | O88: 0.05
A89: GRNEND | B89: 516 | C89: 1050000774215 | D89: GRNEND | E89: 769 | F89: 1050000774224 | G89: GREEN END SOLAR FARM | H89: 1.345 | I89: 39.93 | J89: 1.42 | K89: 1.42 | L89: 0 | M89: 3993.41 | N89: 0.05 | O89: 0.05
A90: GRNFRM | B90: 796 | C90: 1050001003248 | D90: GRNFRM | E90: 797 | F90: 1050001003257 | G90: GREEN FARM SOLAR | H90: 4.001 | I90: 7.05 | J90: 6.69 | K90: 6.69 | L90: 0 | M90: 1127.89 | N90: 0.05 | O90: 0.05
A91: GRTYAR | B91: 7111 | C91: MSID: 7111 | G91: RWE GENERATION UK PLC | H91: 0 | I91: 11.27 | J91: 1.35 | K91: 1.35 | L91: 0 | M91: 0 | N91: 0 | O91: 0
A92: GUNFL3 | B92: 7277 | C92: MSID: 7277 | D92: GUNFL3 | E92: 7277 | F92: MSID: 7277 | G92: DONG ENERGY GUNFLEET SANDS DEMO (UK) LTD | H92: 4.043 | I92: 305.13 | J92: 2.79 | K92: 2.79 | L92: 0 | M92: 982.16 | N92: 0.05 | O92: 0.05
A93: GUNFLT | B93: 7211 | C93: MSID: 7211;7213 | G93: NATIONAL GRID ELECTRICITY TRANSMISSION PLC | H93: 0.017 | I93: 241.06 | J93: 3.89 | K93: 3.89 | L93: 0 | M93: 0 | N93: 0 | O93: 0
A94: HALLFM | B94: 536 | C94: 1050000834219 | D94: HALLFM | E94: 468 | F94: 1050000834228 | G94: SOLAR PARK DEVELOPMENTS 2 LTD | H94: 0.102 | I94: 9.58 | J94: 7.52 | K94: 7.52 | L94: 0 | M94: 1280.5 | N94: 0.05 | O94: 0.05
A95: HDGMSF | B95: 884 | C95: 1050000521726 | D95: HDGMSF | E95: 758 | F95: 1050000521735 | G95: SOLAR CENTURY | H95: 0.097 | I95: 5.15 | J95: 8.59 | K95: 8.59 | L95: 0 | M95: 622.78 | N95: 0.05 | O95: 0.05
A96: HEINZF | B96: 771 | C96: 1014573127752 | G96: ALBERT BARTLETT & SONS (AIRDRIE) LIMITED | H96: 5.404 | I96: 89.16 | J96: 9.65 | K96: 9.65 | L96: 0 | M96: 0 | N96: 0 | O96: 0
A97: HGHFLD | B97: 885 | C97: 1050000563150 | D97: HGHFLD | E97: 759 | F97: 1050000563169 | G97: HIGHFIELDS SOLAR LTD | H97: 3.518 | I97: 6.36 | J97: 3.68 | K97: 3.68 | L97: 0 | M97: 2004.94 | N97: 0.05 | O97: 0.05
A98: HOBACK | B98: 517 | C98: 1050000708514 | D98: HOBACK | E98: 770 | F98: 1050000698405 | G98: HOBACK SOLAR LIMITED | H98: 0.104 | I98: 4.61 | J98: 3.14 | K98: 3.14 | L98: 0 | M98: 852.42 | N98: 0.05 | O98: 0.05
A99: HOLTON | B99: 796 | C99: 1050000769118 | D99: HOLTON | E99: 797 | F99: 1050000769127 | G99: BERNARD MATTHEWS GREEN ENERGY HALESWORTH LIMITED | H99: 0.641 | I99: 17.52 | J99: 2.99 | K99: 2.99 | L99: 0 | M99: 700.91 | N99: 0.05 | O99: 0.05
A100: HTFD_L | B100: 820 | C100: 1014569896484 | G100: HAYWARD TYLER LIMITED | H100: 0.268 | I100: 1290.08 | J100: 2.08 | K100: 2.08 | L100: 0 | M100: 0 | N100: 0 | O100: 0
A101: HYDESF | B101: 518 | C101: 1050000759713 | D101: HYDESF | E101: 450 | F101: 1050000759722 | G101: MTS RYDON SOLAR LIMITED | H101: 1.304 | I101: 11.87 | J101: 2.49 | K101: 2.49 | L101: 0 | M101: 1068.56 | N101: 0.05 | O101: 0.05
A102: ICGLTD | B102: 866 | C102: 1030075706342 | G102: INDUSTRIAL CHEMICALS LTD | H102: 0 | I102: 939.56 | J102: 2.44 | K102: 2.44 | L102: 0 | M102: 0 | N102: 0 | O102: 0
A103: INFSSE | B103: ENET | C103: 1099000001162 1099000001171 | G103: SOUTHERN ELECTRIC POWER DISTRIBUTION PLC | H103: 2.818 | I103: 5033.08 | J103: 1.99 | K103: 1.99 | L103: 0 | M103: 0 | N103: 0 | O103: 0
...

Sheet Annex 2a Import
A1: Note: The list of MPANs / MSIDs provided may be incomplete; the DNO reserves the right to apply the listed charges to any other MPANs / MSIDs associated with the site. Note: This table is automatically populated based on the content of the tab entitled 'Annex 2 EHV Charges'. The timebands are as shown in Annex 2.
A2: =Overview!B4& " - Effective from "&Overview!D4&" - "&Overview!E4&" EDCM import charges" -> Eastern Power Networks - Effective from 01/04/2017 - Final EDCM import charges
A4: Import Unique Identifier | B4: LLFC | C4: Import MPANs/MSIDs | D4: Name | E4: ='Annex 2 EHV charges'!H10 -> Import Super Red unit charge (p/kWh) | F4: ='Annex 2 EHV charges'!I10 -> Import fixed charge (p/day) | G4: ='Annex 2 EHV charges'!J10 -> Import capacity charge (p/kVA/day) | H4: ='Annex 2 EHV charges'!K10 -> Import exceeded capacity charge (p/kVA/day)
A5: {=IFERROR(INDEX('Annex 2 EHV charges'!$A$11:$A$218, MATCH(0, IF(ISBLANK('Annex 2 EHV charges'!$A$11:$A$218),1, COUNTIF(A$4:$A4, 'Annex 2 EHV charges'!$A$11:$A$218)), 0)),"")} -> 3VALSW | B5: =IF($A5="","",VLOOKUP($A5,'Annex 2 EHV charges'!$A:$O,2,0)) -> 771 | C5: =IF($A5="","",VLOOKUP($A5,'Annex 2 EHV charges'!$A:$O,3,0)) -> 1014569699836 | D5: =IF($A5="","",VLOOKUP($A5,'Annex 2 EHV charges'!$A:$O,7,0)) -> AFFINITY WATER LIMITED | E5: =IFERROR(IF(VLOOKUP($A5,'Annex 2 EHV charges'!$A:$O,8,FALSE)=0,"",VLOOKUP($A5,'Annex 2 EHV charges'!$A:$O,8,FALSE)),"") -> 0.717 | F5: =IFERROR(IF(VLOOKUP($A5,'Annex 2 EHV charges'!$A:$O,9,FALSE)=0,"",VLOOKUP($A5,'Annex 2 EHV charges'!$A:$O,9,FALSE)),"") -> 178.32 | G5: =IFERROR(IF(VLOOKUP($A5,'Annex 2 EHV charges'!$A:$O,10,FALSE)=0,"",VLOOKUP($A5,'Annex 2 EHV charges'!$A:$O,10,FALSE)),"") -> 5.56 | H5: =IFERROR(IF(VLOOKUP($A5,'Annex 2 EHV charges'!$A:$O,11,FALSE)=0,"",VLOOKUP($A5,'Annex 2 EHV charges'!$A:$O,11,FALSE)),"") -> 5.56
A6: {=IFERROR(INDEX('Annex 2 EHV charges'!$A$11:$A$218, MATCH(0, IF(ISBLANK('Annex 2 EHV charges'!$A$11:$A$218),1, COUNTIF(A$4:$A5, 'Annex 2 EHV charges'!$A$11:$A$218)), 0)),"")} -> ABSRSF | B6: =IF($A6="","",VLOOKUP($A6,'Annex 2 EHV charges'!$A:$O,2,0)) -> 869 | C6: =IF($A6="","",VLOOKUP($A6,'Annex 2 EHV charges'!$A:$O,3,0)) -> 1050000574685 | D6: =IF($A6="","",VLOOKUP($A6,'Annex 2 EHV charges'!$A:$O,7,0)) -> ABBOTS RIPTON SOLAR ENERGY LIMITED | E6: =IFERROR(IF(VLOOKUP($A6,'Annex 2 EHV charges'!$A:$O,8,FALSE)=0,"",VLOOKUP($A6,'Annex 2 EHV charges'!$A:$O,8,FALSE)),"") -> 1.908 | F6: =IFERROR(IF(VLOOKUP($A6,'Annex 2 EHV charges'!$A:$O,9,FALSE)=0,"",VLOOKUP($A6,'Annex 2 EHV charges'!$A:$O,9,FALSE)),"") -> 18.24 | G6: =IFERROR(IF(VLOOKUP($A6,'Annex 2 EHV charges'!$A:$O,10,FALSE)=0,"",VLOOKUP($A6,'Annex 2 EHV charges'!$A:$O,10,FALSE)),"") -> 3 | H6: =IFERROR(IF(VLOOKUP($A6,'Annex 2 EHV charges'!$A:$O,11,FALSE)=0,"",VLOOKUP($A6,'Annex 2 EHV charges'!$A:$O,11,FALSE)),"") -> 3
A7: {=IFERROR(INDEX('Annex 2 EHV charges'!$A$11:$A$218, MATCH(0, IF(ISBLANK('Annex 2 EHV charges'!$A$11:$A$218),1, COUNTIF(A$4:$A6, 'Annex 2 EHV charges'!$A$11:$A$218)), 0)),"")} -> ADBRKS | B7: =IF($A7="","",VLOOKUP($A7,'Annex 2 EHV charges'!$A:$O,2,0)) -> 771 | C7: =IF($A7="","",VLOOKUP($A7,'Annex 2 EHV charges'!$A:$O,3,0)) -> 1023529546480 | D7: =IF($A7="","",VLOOKUP($A7,'Annex 2 EHV charges'!$A:$O,7,0)) -> ADDENBROOKES NHS TRUST | E7: =IFERROR(IF(VLOOKUP($A7,'Annex 2 EHV charges'!$A:$O,8,FALSE)=0,"",VLOOKUP($A7,'Annex 2 EHV charges'!$A:$O,8,FALSE)),"") -> 1.414 | F7: =IFERROR(IF(VLOOKUP($A7,'Annex 2 EHV charges'!$A:$O,9,FALSE)=0,"",VLOOKUP($A7,'Annex 2 EHV charges'!$A:$O,9,FALSE)),"") -> 3068.14 | G7: =IFERROR(IF(VLOOKUP($A7,'Annex 2 EHV charges'!$A:$O,10,FALSE)=0,"",VLOOKUP($A7,'Annex 2 EHV charges'!$A:$O,10,FALSE)),"") -> 3.93 | H7: =IFERROR(IF(VLOOKUP($A7,'Annex 2 EHV charges'!$A:$O,11,FALSE)=0,"",VLOOKUP($A7,'Annex 2 EHV charges'!$A:$O,11,FALSE)),"") -> 3.93
A8: {=IFERROR(INDEX('Annex 2 EHV charges'!$A$11:$A$218, MATCH(0, IF(ISBLANK('Annex 2 EHV charges'!$A$11:$A$218),1, COUNTIF(A$4:$A7, 'Annex 2 EHV charges'!$A$11:$A$218)), 0)),"")} -> AIAMAN | B8: =IF($A8="","",VLOOKUP($A8,'Annex 2 EHV charges'!$A:$O,2,0)) -> 771 | C8: =IF($A8="","",VLOOKUP($A8,'Annex 2 EHV charges'!$A:$O,3,0)) -> 1014569292506 | D8: =IF($A8="","",VLOOKUP($A8,'Annex 2 EHV charges'!$A:$O,7,0)) -> A I A MANAGEMENT LTD | E8: =IFERROR(IF(VLOOKUP($A8,'Annex 2 EHV charges'!$A:$O,8,FALSE)=0,"",VLOOKUP($A8,'Annex 2 EHV charges'!$A:$O,8,FALSE)),"") -> 2.944 | F8: =IFERROR(IF(VLOOKUP($A8,'Annex 2 EHV charges'!$A:$O,9,FALSE)=0,"",VLOOKUP($A8,'Annex 2 EHV charges'!$A:$O,9,FALSE)),"") -> 8.49 | G8: =IFERROR(IF(VLOOKUP($A8,'Annex 2 EHV charges'!$A:$O,10,FALSE)=0,"",VLOOKUP($A8,'Annex 2 EHV charges'!$A:$O,10,FALSE)),"") -> 19.01 | H8: =IFERROR(IF(VLOOKUP($A8,'Annex 2 EHV charges'!$A:$O,11,FALSE)=0,"",VLOOKUP($A8,'Annex 2 EHV charges'!$A:$O,11,FALSE)),"") -> 19.01
A9: {=IFERROR(INDEX('Annex 2 EHV charges'!$A$11:$A$218, MATCH(0, IF(ISBLANK('Annex 2 EHV charges'!$A$11:$A$218),1, COUNTIF(A$4:$A8, 'Annex 2 EHV charges'!$A$11:$A$218)), 0)),"")} -> ARAMAN | B9: =IF($A9="","",VLOOKUP($A9,'Annex 2 EHV charges'!$A:$O,2,0)) -> 800 | C9: =IF($A9="","",VLOOKUP($A9,'Annex 2 EHV charges'!$A:$O,3,0)) -> 1023483097981 | D9: =IF($A9="","",VLOOKUP($A9,'Annex 2 EHV charges'!$A:$O,7,0)) -> AIRCRAFT RESEARCH ASSOCIATION LIMITED | E9: =IFERROR(IF(VLOOKUP($A9,'Annex 2 EHV charges'!$A:$O,8,FALSE)=0,"",VLOOKUP($A9,'Annex 2 EHV charges'!$A:$O,8,FALSE)),"") -> 0.111 | F9: =IFERROR(IF(VLOOKUP($A9,'Annex 2 EHV charges'!$A:$O,9,FALSE)=0,"",VLOOKUP($A9,'Annex 2 EHV charges'!$A:$O,9,FALSE)),"") -> 6644.17 | G9: =IFERROR(IF(VLOOKUP($A9,'Annex 2 EHV charges'!$A:$O,10,FALSE)=0,"",VLOOKUP($A9,'Annex 2 EHV charges'!$A:$O,10,FALSE)),"") -> 0.95 | H9: =IFERROR(IF(VLOOKUP($A9,'Annex 2 EHV charges'!$A:$O,11,FALSE)=0,"",VLOOKUP($A9,'Annex 2 EHV charges'!$A:$O,11,FALSE)),"") -> 0.95
A10: {=IFERROR(INDEX('Annex 2 EHV charges'!$A$11:$A$218, MATCH(0, IF(ISBLANK('Annex 2 EHV charges'!$A$11:$A$218),1, COUNTIF(A$4:$A9, 'Annex 2 EHV charges'!$A$11:$A$218)), 0)),"")} -> ARLAFD | B10: =IF($A10="","",VLOOKUP($A10,'Annex 2 EHV charges'!$A:$O,2,0)) -> 771 | C10: =IF($A10="","",VLOOKUP($A10,'Annex 2 EHV charges'!$A:$O,3,0)) -> 1030081553176 1030081553404 | D10: =IF($A10="","",VLOOKUP($A10,'Annex 2 EHV charges'!$A:$O,7,0)) -> ARLA FOODS LIMITED | E10: =IFERROR(IF(VLOOKUP($A10,'Annex 2 EHV charges'!$A:$O,8,FALSE)=0,"",VLOOKUP($A10,'Annex 2 EHV charges'!$A:$O,8,FALSE)),"") -> 4.172 | F10: =IFERROR(IF(VLOOKUP($A10,'Annex 2 EHV charges'!$A:$O,9,FALSE)=0,"",VLOOKUP($A10,'Annex 2 EHV charges'!$A:$O,9,FALSE)),"") -> 3283.78 | G10: =IFERROR(IF(VLOOKUP($A10,'Annex 2 EHV charges'!$A:$O,10,FALSE)=0,"",VLOOKUP($A10,'Annex 2 EHV charges'!$A:$O,10,FALSE)),"") -> 1.78 | H10: =IFERROR(IF(VLOOKUP($A10,'Annex 2 EHV charges'!$A:$O,11,FALSE)=0,"",VLOOKUP($A10,'Annex 2 EHV charges'!$A:$O,11,FALSE)),"") -> 1.78
A11: {=IFERROR(INDEX('Annex 2 EHV charges'!$A$11:$A$218, MATCH(0, IF(ISBLANK('Annex 2 EHV charges'!$A$11:$A$218),1, COUNTIF(A$4:$A10, 'Annex 2 EHV charges'!$A$11:$A$218)), 0)),"")} -> ASTONC | B11: =IF($A11="","",VLOOKUP($A11,'Annex 2 EHV charges'!$A:$O,2,0)) -> 503 | C11: =IF($A11="","",VLOOKUP($A11,'Annex 2 EHV charges'!$A:$O,3,0)) -> 1050000834246 | D11: =IF($A11="","",VLOOKUP($A11,'Annex 2 EHV charges'!$A:$O,7,0)) -> ASTON CLINTON | E11: =IFERROR(IF(VLOOKUP($A11,'Annex 2 EHV charges'!$A:$O,8,FALSE)=0,"",VLOOKUP($A11,'Annex 2 EHV charges'!$A:$O,8,FALSE)),"") -> 5.981 | F11: =IFERROR(IF(VLOOKUP($A11,'Annex 2 EHV charges'!$A:$O,9,FALSE)=0,"",VLOOKUP($A11,'Annex 2 EHV charges'!$A:$O,9,FALSE)),"") -> 2.58 | G11: =IFERROR(IF(VLOOKUP($A11,'Annex 2 EHV charges'!$A:$O,10,FALSE)=0,"",VLOOKUP($A11,'Annex 2 EHV charges'!$A:$O,10,FALSE)),"") -> 3.14 | H11: =IFERROR(IF(VLOOKUP($A11,'Annex 2 EHV charges'!$A:$O,11,FALSE)=0,"",VLOOKUP($A11,'Annex 2 EHV charges'!$A:$O,11,FALSE)),"") -> 3.14
A12: {=IFERROR(INDEX('Annex 2 EHV charges'!$A$11:$A$218, MATCH(0, IF(ISBLANK('Annex 2 EHV charges'!$A$11:$A$218),1, COUNTIF(A$4:$A11, 'Annex 2 EHV charges'!$A$11:$A$218)), 0)),"")} -> AVENUE | B12: =IF($A12="","",VLOOKUP($A12,'Annex 2 EHV charges'!$A:$O,2,0)) -> 504 | C12: =IF($A12="","",VLOOKUP($A12,'Annex 2 EHV charges'!$A:$O,3,0)) -> 1050000774970 | D12: =IF($A12="","",VLOOKUP($A12,'Annex 2 EHV charges'!$A:$O,7,0)) -> LIGHTSOURCE SPV 15 LIMITED | E12: =IFERROR(IF(VLOOKUP($A12,'Annex 2 EHV charges'!$A:$O,8,FALSE)=0,"",VLOOKUP($A12,'Annex 2 EHV charges'!$A:$O,8,FALSE)),"") -> 0.064 | F12: =IFERROR(IF(VLOOKUP($A12,'Annex 2 EHV charges'!$A:$O,9,FALSE)=0,"",VLOOKUP($A12,'Annex 2 EHV charges'!$A:$O,9,FALSE)),"") -> 17.15 | G12: =IFERROR(IF(VLOOKUP($A12,'Annex 2 EHV charges'!$A:$O,10,FALSE)=0,"",VLOOKUP($A12,'Annex 2 EHV charges'!$A:$O,10,FALSE)),"") -> 4.11 | H12: =IFERROR(IF(VLOOKUP($A12,'Annex 2 EHV charges'!$A:$O,11,FALSE)=0,"",VLOOKUP($A12,'Annex 2 EHV charges'!$A:$O,11,FALSE)),"") -> 4.11
A13: {=IFERROR(INDEX('Annex 2 EHV charges'!$A$11:$A$218, MATCH(0, IF(ISBLANK('Annex 2 EHV charges'!$A$11:$A$218),1, COUNTIF(A$4:$A12, 'Annex 2 EHV charges'!$A$11:$A$218)), 0)),"")} -> AW_GRA | B13: =IF($A13="","",VLOOKUP($A13,'Annex 2 EHV charges'!$A:$O,2,0)) -> 771 | C13: =IF($A13="","",VLOOKUP($A13,'Annex 2 EHV charges'!$A:$O,3,0)) -> 1023477037942 1014571445536 | D13: =IF($A13="","",VLOOKUP($A13,'Annex 2 EHV charges'!$A:$O,7,0)) -> ANGLIAN WATER SERVICES | E13: =IFERROR(IF(VLOOKUP($A13,'Annex 2 EHV charges'!$A:$O,8,FALSE)=0,"",VLOOKUP($A13,'Annex 2 EHV charges'!$A:$O,8,FALSE)),"") -> 2.419 | F13: =IFERROR(IF(VLOOKUP($A13,'Annex 2 EHV charges'!$A:$O,9,FALSE)=0,"",VLOOKUP($A13,'Annex 2 EHV charges'!$A:$O,9,FALSE)),"") -> 178.32 | G13: =IFERROR(IF(VLOOKUP($A13,'Annex 2 EHV charges'!$A:$O,10,FALSE)=0,"",VLOOKUP($A13,'Annex 2 EHV charges'!$A:$O,10,FALSE)),"") -> 6.81 | H13: =IFERROR(IF(VLOOKUP($A13,'Annex 2 EHV charges'!$A:$O,11,FALSE)=0,"",VLOOKUP($A13,'Annex 2 EHV charges'!$A:$O,11,FALSE)),"") -> 6.81
A14: {=IFERROR(INDEX('Annex 2 EHV charges'!$A$11:$A$218, MATCH(0, IF(ISBLANK('Annex 2 EHV charges'!$A$11:$A$218),1, COUNTIF(A$4:$A13, 'Annex 2 EHV charges'!$A$11:$A$218)), 0)),"")} -> AWOUSE | B14: =IF($A14="","",VLOOKUP($A14,'Annex 2 EHV charges'!$A:$O,2,0)) -> 771 | C14: =IF($A14="","",VLOOKUP($A14,'Annex 2 EHV charges'!$A:$O,3,0)) -> 1023475403798 1014571965793 | D14: =IF($A14="","",VLOOKUP($A14,'Annex 2 EHV charges'!$A:$O,7,0)) -> ANGLIAN WATER SERVICES | E14: =IFERROR(IF(VLOOKUP($A14,'Annex 2 EHV charges'!$A:$O,8,FALSE)=0,"",VLOOKUP($A14,'Annex 2 EHV charges'!$A:$O,8,FALSE)),"") -> 2.605 | F14: =IFERROR(IF(VLOOKUP($A14,'Annex 2 EHV charges'!$A:$O,9,FALSE)=0,"",VLOOKUP($A14,'Annex 2 EHV charges'!$A:$O,9,FALSE)),"") -> 178.32 | G14: =IFERROR(IF(VLOOKUP($A14,'Annex 2 EHV charges'!$A:$O,10,FALSE)=0,"",VLOOKUP($A14,'Annex 2 EHV charges'!$A:$O,10,FALSE)),"") -> 4.15 | H14: =IFERROR(IF(VLOOKUP($A14,'Annex 2 EHV charges'!$A:$O,11,FALSE)=0,"",VLOOKUP($A14,'Annex 2 EHV charges'!$A:$O,11,FALSE)),"") -> 4.15
A15: {=IFERROR(INDEX('Annex 2 EHV charges'!$A$11:$A$218, MATCH(0, IF(ISBLANK('Annex 2 EHV charges'!$A$11:$A$218),1, COUNTIF(A$4:$A14, 'Annex 2 EHV charges'!$A$11:$A$218)), 0)),"")} -> BARNFM | B15: =IF($A15="","",VLOOKUP($A15,'Annex 2 EHV charges'!$A:$O,2,0)) -> 796 | C15: =IF($A15="","",VLOOKUP($A15,'Annex 2 EHV charges'!$A:$O,3,0)) -> 1050000774999 | D15: =IF($A15="","",VLOOKUP($A15,'Annex 2 EHV charges'!$A:$O,7,0)) -> BARN FARM SOLAR | E15: =IFERROR(IF(VLOOKUP($A15,'Annex 2 EHV charges'!$A:$O,8,FALSE)=0,"",VLOOKUP($A15,'Annex 2 EHV charges'!$A:$O,8,FALSE)),"") -> 4.001 | F15: =IFERROR(IF(VLOOKUP($A15,'Annex 2 EHV charges'!$A:$O,9,FALSE)=0,"",VLOOKUP($A15,'Annex 2 EHV charges'!$A:$O,9,FALSE)),"") -> 44.65 | G15: =IFERROR(IF(VLOOKUP($A15,'Annex 2 EHV charges'!$A:$O,10,FALSE)=0,"",VLOOKUP($A15,'Annex 2 EHV charges'!$A:$O,10,FALSE)),"") -> 6.69 | H15: =IFERROR(IF(VLOOKUP($A15,'Annex 2 EHV charges'!$A:$O,11,FALSE)=0,"",VLOOKUP($A15,'Annex 2 EHV charges'!$A:$O,11,FALSE)),"") -> 6.69
A16: {=IFERROR(INDEX('Annex 2 EHV charges'!$A$11:$A$218, MATCH(0, IF(ISBLANK('Annex 2 EHV charges'!$A$11:$A$218),1, COUNTIF(A$4:$A15, 'Annex 2 EHV charges'!$A$11:$A$218)), 0)),"")} -> BAYFMS | B16: =IF($A16="","",VLOOKUP($A16,'Annex 2 EHV charges'!$A:$O,2,0)) -> 870 | C16: =IF($A16="","",VLOOKUP($A16,'Annex 2 EHV charges'!$A:$O,3,0)) -> 1050000579318 | D16: =IF($A16="","",VLOOKUP($A16,'Annex 2 EHV charges'!$A:$O,7,0)) -> BAY FARM IMPORT | E16: =IFERROR(IF(VLOOKUP($A16,'Annex 2 EHV charges'!$A:$O,8,FALSE)=0,"",VLOOKUP($A16,'Annex 2 EHV charges'!$A:$O,8,FALSE)),"") -> 2.292 | F16: =IFERROR(IF(VLOOKUP($A16,'Annex 2 EHV charges'!$A:$O,9,FALSE)=0,"",VLOOKUP($A16,'Annex 2 EHV charges'!$A:$O,9,FALSE)),"") -> 31.89 | G16: =IFERROR(IF(VLOOKUP($A16,'Annex 2 EHV charges'!$A:$O,10,FALSE)=0,"",VLOOKUP($A16,'Annex 2 EHV charges'!$A:$O,10,FALSE)),"") -> 4.26 | H16: =IFERROR(IF(VLOOKUP($A16,'Annex 2 EHV charges'!$A:$O,11,FALSE)=0,"",VLOOKUP($A16,'Annex 2 EHV charges'!$A:$O,11,FALSE)),"") -> 4.26
... A212: {=IFERROR(INDEX('Annex 2 EHV charges'!$A$11:$A$218, MATCH(0, IF(ISBLANK('Annex 2 EHV charges'!$A$11:$A$218),1, COUNTIF(A$4:$A211, 'Annex 2 EHV charges'!$A$11:$A$218)), 0)),"")} -> WWYNDC | B212: =IF($A212="","",VLOOKUP($A212,'Annex 2 EHV charges'!$A:$O,2,0)) -> 771 | C212: =IF($A212="","",VLOOKUP($A212,'Annex 2 EHV charges'!$A:$O,3,0)) -> 1030059750786 1030059751015 | D212: =IF($A212="","",VLOOKUP($A212,'Annex 2 EHV charges'!$A:$O,7,0)) -> COLT TECHNOLOGY SERVICES | E212: =IFERROR(IF(VLOOKUP($A212,'Annex 2 EHV charges'!$A:$O,8,FALSE)=0,"",VLOOKUP($A212,'Annex 2 EHV charges'!$A:$O,8,FALSE)),"") -> 0.04 | F212: =IFERROR(IF(VLOOKUP($A212,'Annex 2 EHV charges'!$A:$O,9,FALSE)=0,"",VLOOKUP($A212,'Annex 2 EHV charges'!$A:$O,9,FALSE)),"") -> 19880.33 | G212: =IFERROR(IF(VLOOKUP($A212,'Annex 2 EHV charges'!$A:$O,10,FALSE)=0,"",VLOOKUP($A212,'Annex 2 EHV charges'!$A:$O,10,FALSE)),"") -> 3.97 | H212: =IFERROR(IF(VLOOKUP($A212,'Annex 2 EHV charges'!$A:$O,11,FALSE)=0,"",VLOOKUP($A212,'Annex 2 EHV charges'!$A:$O,11,FALSE)),"") -> 3.97

Sheet Annex 2b Export
A1: Note: The list of MPANs / MSIDs provided may be incomplete; the DNO reserves the right to apply the listed charges to any other MPANs / MSIDs associated with the site. Note: This table is automatically populated based on the content of the tab entitled 'Annex 2 EHV Charges'. The timebands are as shown in Annex 2.
A2: =Overview!B4& " - Effective from "&Overview!D4&" - "&Overview!E4&" EDCM export charges" -> Eastern Power Networks - Effective from 01/04/2017 - Final EDCM export charges
A4: Export Unique Identifier | B4: LLFC | C4: Export MPANs/MSIDs | D4: Name | E4: ='Annex 2 EHV charges'!L10 -> Export Super Red unit charge (p/kWh) | F4: ='Annex 2 EHV charges'!M10 -> Export fixed charge (p/day) | G4: ='Annex 2 EHV charges'!N10 -> Export capacity charge (p/kVA/day) | H4: ='Annex 2 EHV charges'!O10 -> Export exceeded capacity charge (p/kVA/day)
A5: {=IFERROR(INDEX('Annex 2 EHV charges'!$D$11:$D$218, MATCH(0, IF(ISBLANK('Annex 2 EHV charges'!$D$11:$D$218),1, COUNTIF(A$4:$A4, 'Annex 2 EHV charges'!$D$11:$D$218)), 0)),"")} -> ABSRSF | B5: =IF($A5="","",VLOOKUP($A5,'Annex 2 EHV charges'!$D:$O,2,0)) -> 744 | C5: =IF($A5="","",VLOOKUP($A5,'Annex 2 EHV charges'!$D:$O,3,0)) -> 1050000574694 | D5: =IF($A5="","",VLOOKUP($A5,'Annex 2 EHV charges'!$D:$O,4,0)) -> ABBOTS RIPTON SOLAR ENERGY LIMITED | E5: =IFERROR(IF(VLOOKUP($A5,'Annex 2 EHV charges'!$D:$O,9,FALSE)=0,"",VLOOKUP($A5,'Annex 2 EHV charges'!$D:$O,9,FALSE)),"") | F5: =IFERROR(IF(VLOOKUP($A5,'Annex 2 EHV charges'!$D:$O,10,FALSE)=0,"",VLOOKUP($A5,'Annex 2 EHV charges'!$D:$O,10,FALSE)),"") -> 3647.93 | G5: =IFERROR(IF(VLOOKUP($A5,'Annex 2 EHV charges'!$D:$O,11,FALSE)=0,"",VLOOKUP($A5,'Annex 2 EHV charges'!$D:$O,11,FALSE)),"") -> 0.05 | H5: =IFERROR(IF(VLOOKUP($A5,'Annex 2 EHV charges'!$D:$O,12,FALSE)=0,"",VLOOKUP($A5,'Annex 2 EHV charges'!$D:$O,12,FALSE)),"") -> 0.05
A6: {=IFERROR(INDEX('Annex 2 EHV charges'!$D$11:$D$218, MATCH(0, IF(ISBLANK('Annex 2 EHV charges'!$D$11:$D$218),1, COUNTIF(A$4:$A5, 'Annex 2 EHV charges'!$D$11:$D$218)), 0)),"")} -> AIAMAN | B6: =IF($A6="","",VLOOKUP($A6,'Annex 2 EHV charges'!$D:$O,2,0)) -> 792 | C6: =IF($A6="","",VLOOKUP($A6,'Annex 2 EHV charges'!$D:$O,3,0)) -> 1030054607984 | D6: =IF($A6="","",VLOOKUP($A6,'Annex 2 EHV charges'!$D:$O,4,0)) -> A I A MANAGEMENT LTD | E6: =IFERROR(IF(VLOOKUP($A6,'Annex 2 EHV charges'!$D:$O,9,FALSE)=0,"",VLOOKUP($A6,'Annex 2 EHV charges'!$D:$O,9,FALSE)),"") -> -2.844 | F6: =IFERROR(IF(VLOOKUP($A6,'Annex 2 EHV charges'!$D:$O,10,FALSE)=0,"",VLOOKUP($A6,'Annex 2 EHV charges'!$D:$O,10,FALSE)),"") -> 169.83 | G6: =IFERROR(IF(VLOOKUP($A6,'Annex 2 EHV charges'!$D:$O,11,FALSE)=0,"",VLOOKUP($A6,'Annex 2 EHV charges'!$D:$O,11,FALSE)),"") -> 0.05 | H6: =IFERROR(IF(VLOOKUP($A6,'Annex 2 EHV charges'!$D:$O,12,FALSE)=0,"",VLOOKUP($A6,'Annex 2 EHV charges'!$D:$O,12,FALSE)),"") -> 0.05
A7: {=IFERROR(INDEX('Annex 2 EHV charges'!$D$11:$D$218, MATCH(0, IF(ISBLANK('Annex 2 EHV charges'!$D$11:$D$218),1, COUNTIF(A$4:$A6, 'Annex 2 EHV charges'!$D$11:$D$218)), 0)),"")} -> ARLAFD | B7: =IF($A7="","",VLOOKUP($A7,'Annex 2 EHV charges'!$D:$O,2,0)) -> 792 | C7: =IF($A7="","",VLOOKUP($A7,'Annex 2 EHV charges'!$D:$O,3,0)) -> 1030085114723 1030085114955 | D7: =IF($A7="","",VLOOKUP($A7,'Annex 2 EHV charges'!$D:$O,4,0)) -> ARLA FOODS LIMITED | E7: =IFERROR(IF(VLOOKUP($A7,'Annex 2 EHV charges'!$D:$O,9,FALSE)=0,"",VLOOKUP($A7,'Annex 2 EHV charges'!$D:$O,9,FALSE)),"") | F7: =IFERROR(IF(VLOOKUP($A7,'Annex 2 EHV charges'!$D:$O,10,FALSE)=0,"",VLOOKUP($A7,'Annex 2 EHV charges'!$D:$O,10,FALSE)),"") -> 1094.59 | G7: =IFERROR(IF(VLOOKUP($A7,'Annex 2 EHV charges'!$D:$O,11,FALSE)=0,"",VLOOKUP($A7,'Annex 2 EHV charges'!$D:$O,11,FALSE)),"") -> 0.05 | H7: =IFERROR(IF(VLOOKUP($A7,'Annex 2 EHV charges'!$D:$O,12,FALSE)=0,"",VLOOKUP($A7,'Annex 2 EHV charges'!$D:$O,12,FALSE)),"") -> 0.05
A8: {=IFERROR(INDEX('Annex 2 EHV charges'!$D$11:$D$218, MATCH(0, IF(ISBLANK('Annex 2 EHV charges'!$D$11:$D$218),1, COUNTIF(A$4:$A7, 'Annex 2 EHV charges'!$D$11:$D$218)), 0)),"")} -> ASTONC | B8: =IF($A8="","",VLOOKUP($A8,'Annex 2 EHV charges'!$D:$O,2,0)) -> 780 | C8: =IF($A8="","",VLOOKUP($A8,'Annex 2 EHV charges'!$D:$O,3,0)) -> 1050000834255 | D8: =IF($A8="","",VLOOKUP($A8,'Annex 2 EHV charges'!$D:$O,4,0)) -> ASTON CLINTON | E8: =IFERROR(IF(VLOOKUP($A8,'Annex 2 EHV charges'!$D:$O,9,FALSE)=0,"",VLOOKUP($A8,'Annex 2 EHV charges'!$D:$O,9,FALSE)),"") | F8: =IFERROR(IF(VLOOKUP($A8,'Annex 2 EHV charges'!$D:$O,10,FALSE)=0,"",VLOOKUP($A8,'Annex 2 EHV charges'!$D:$O,10,FALSE)),"") -> 515.71 | G8: =IFERROR(IF(VLOOKUP($A8,'Annex 2 EHV charges'!$D:$O,11,FALSE)=0,"",VLOOKUP($A8,'Annex 2 EHV charges'!$D:$O,11,FALSE)),"") -> 0.05 | H8: =IFERROR(IF(VLOOKUP($A8,'Annex 2 EHV charges'!$D:$O,12,FALSE)=0,"",VLOOKUP($A8,'Annex 2 EHV charges'!$D:$O,12,FALSE)),"") -> 0.05
A9: {=IFERROR(INDEX('Annex 2 EHV charges'!$D$11:$D$218, MATCH(0, IF(ISBLANK('Annex 2 EHV charges'!$D$11:$D$218),1, COUNTIF(A$4:$A8, 'Annex 2 EHV charges'!$D$11:$D$218)), 0)),"")} -> AVENUE | B9: =IF($A9="","",VLOOKUP($A9,'Annex 2 EHV charges'!$D:$O,2,0)) -> 781 | C9: =IF($A9="","",VLOOKUP($A9,'Annex 2 EHV charges'!$D:$O,3,0)) -> 1050000774980 | D9: =IF($A9="","",VLOOKUP($A9,'Annex 2 EHV charges'!$D:$O,4,0)) -> LIGHTSOURCE SPV 15 LIMITED | E9: =IFERROR(IF(VLOOKUP($A9,'Annex 2 EHV charges'!$D:$O,9,FALSE)=0,"",VLOOKUP($A9,'Annex 2 EHV charges'!$D:$O,9,FALSE)),"") | F9: =IFERROR(IF(VLOOKUP($A9,'Annex 2 EHV charges'!$D:$O,10,FALSE)=0,"",VLOOKUP($A9,'Annex 2 EHV charges'!$D:$O,10,FALSE)),"") -> 1114.99 | G9: =IFERROR(IF(VLOOKUP($A9,'Annex 2 EHV charges'!$D:$O,11,FALSE)=0,"",VLOOKUP($A9,'Annex 2 EHV charges'!$D:$O,11,FALSE)),"") -> 0.05 | H9: =IFERROR(IF(VLOOKUP($A9,'Annex 2 EHV charges'!$D:$O,12,FALSE)=0,"",VLOOKUP($A9,'Annex 2 EHV charges'!$D:$O,12,FALSE)),"") -> 0.05
A10: {=IFERROR(INDEX('Annex 2 EHV charges'!$D$11:$D$218, MATCH(0, IF(ISBLANK('Annex 2 EHV charges'!$D$11:$D$218),1, COUNTIF(A$4:$A9, 'Annex 2 EHV charges'!$D$11:$D$218)), 0)),"")} -> BARNFM | B10: =IF($A10="","",VLOOKUP($A10,'Annex 2 EHV charges'!$D:$O,2,0)) -> 797 | C10: =IF($A10="","",VLOOKUP($A10,'Annex 2 EHV charges'!$D:$O,3,0)) -> 1050000775005 | D10: =IF($A10="","",VLOOKUP($A10,'Annex 2 EHV charges'!$D:$O,4,0)) -> BARN FARM SOLAR | E10: =IFERROR(IF(VLOOKUP($A10,'Annex 2 EHV charges'!$D:$O,9,FALSE)=0,"",VLOOKUP($A10,'Annex 2 EHV charges'!$D:$O,9,FALSE)),"") | F10: =IFERROR(IF(VLOOKUP($A10,'Annex 2 EHV charges'!$D:$O,10,FALSE)=0,"",VLOOKUP($A10,'Annex 2 EHV charges'!$D:$O,10,FALSE)),"") -> 1875.31 | G10: =IFERROR(IF(VLOOKUP($A10,'Annex 2 EHV charges'!$D:$O,11,FALSE)=0,"",VLOOKUP($A10,'Annex 2 EHV charges'!$D:$O,11,FALSE)),"") -> 0.05 | H10: =IFERROR(IF(VLOOKUP($A10,'Annex 2 EHV charges'!$D:$O,12,FALSE)=0,"",VLOOKUP($A10,'Annex 2 EHV charges'!$D:$O,12,FALSE)),"") -> 0.05
A11: {=IFERROR(INDEX('Annex 2 EHV charges'!$D$11:$D$218, MATCH(0, IF(ISBLANK('Annex 2 EHV charges'!$D$11:$D$218),1, COUNTIF(A$4:$A10, 'Annex 2 EHV charges'!$D$11:$D$218)), 0)),"")} -> BAYFMS | B11: =IF($A11="","",VLOOKUP($A11,'Annex 2 EHV charges'!$D:$O,2,0)) -> 745 | C11: =IF($A11="","",VLOOKUP($A11,'Annex 2 EHV charges'!$D:$O,3,0)) -> 1050000579327 | D11: =IF($A11="","",VLOOKUP($A11,'Annex 2 EHV charges'!$D:$O,4,0)) -> BAY FARM IMPORT | E11: =IFERROR(IF(VLOOKUP($A11,'Annex 2 EHV charges'!$D:$O,9,FALSE)=0,"",VLOOKUP($A11,'Annex 2 EHV charges'!$D:$O,9,FALSE)),"") | F11: =IFERROR(IF(VLOOKUP($A11,'Annex 2 EHV charges'!$D:$O,10,FALSE)=0,"",VLOOKUP($A11,'Annex 2 EHV charges'!$D:$O,10,FALSE)),"") -> 2551.06 | G11: =IFERROR(IF(VLOOKUP($A11,'Annex 2 EHV charges'!$D:$O,11,FALSE)=0,"",VLOOKUP($A11,'Annex 2 EHV charges'!$D:$O,11,FALSE)),"") -> 0.05 | H11: =IFERROR(IF(VLOOKUP($A11,'Annex 2 EHV charges'!$D:$O,12,FALSE)=0,"",VLOOKUP($A11,'Annex 2 EHV charges'!$D:$O,12,FALSE)),"") -> 0.05
A12: {=IFERROR(INDEX('Annex 2 EHV charges'!$D$11:$D$218, MATCH(0, IF(ISBLANK('Annex 2 EHV charges'!$D$11:$D$218),1, COUNTIF(A$4:$A11, 'Annex 2 EHV charges'!$D$11:$D$218)), 0)),"")} -> BDGHSE | B12: =IF($A12="","",VLOOKUP($A12,'Annex 2 EHV charges'!$D:$O,2,0)) -> 782 | C12: =IF($A12="","",VLOOKUP($A12,'Annex 2 EHV charges'!$D:$O,3,0)) -> 1050000669539 | D12: =IF($A12="","",VLOOKUP($A12,'Annex 2 EHV charges'!$D:$O,4,0)) -> BOARDINGHOUSE WINDFARM LIMITED | E12: =IFERROR(IF(VLOOKUP($A12,'Annex 2 EHV charges'!$D:$O,9,FALSE)=0,"",VLOOKUP($A12,'Annex 2 EHV charges'!$D:$O,9,FALSE)),"") | F12: =IFERROR(IF(VLOOKUP($A12,'Annex 2 EHV charges'!$D:$O,10,FALSE)=0,"",VLOOKUP($A12,'Annex 2 EHV charges'!$D:$O,10,FALSE)),"") -> 1052.2 | G12: =IFERROR(IF(VLOOKUP($A12,'Annex 2 EHV charges'!$D:$O,11,FALSE)=0,"",VLOOKUP($A12,'Annex 2 EHV charges'!$D:$O,11,FALSE)),"") -> 0.05 | H12: =IFERROR(IF(VLOOKUP($A12,'Annex 2 EHV charges'!$D:$O,12,FALSE)=0,"",VLOOKUP($A12,'Annex 2 EHV charges'!$D:$O,12,FALSE)),"") -> 0.05
A13: {=IFERROR(INDEX('Annex 2 EHV charges'!$D$11:$D$218, MATCH(0, IF(ISBLANK('Annex 2 EHV charges'!$D$11:$D$218),1, COUNTIF(A$4:$A12, 'Annex 2 EHV charges'!$D$11:$D$218)), 0)),"")} -> BDWLWF | B13: =IF($A13="","",VLOOKUP($A13,'Annex 2 EHV charges'!$D:$O,2,0)) -> 734 | C13: =IF($A13="","",VLOOKUP($A13,'Annex 2 EHV charges'!$D:$O,3,0)) -> 1030082700647 | D13: =IF($A13="","",VLOOKUP($A13,'Annex 2 EHV charges'!$D:$O,4,0)) -> RWE INNOGY UK LIMITED | E13: =IFERROR(IF(VLOOKUP($A13,'Annex 2 EHV charges'!$D:$O,9,FALSE)=0,"",VLOOKUP($A13,'Annex 2 EHV charges'!$D:$O,9,FALSE)),"") | F13: =IFERROR(IF(VLOOKUP($A13,'Annex 2 EHV charges'!$D:$O,10,FALSE)=0,"",VLOOKUP($A13,'Annex 2 EHV charges'!$D:$O,10,FALSE)),"") -> 3938.04 | G13: =IFERROR(IF(VLOOKUP($A13,'Annex 2 EHV charges'!$D:$O,11,FALSE)=0,"",VLOOKUP($A13,'Annex 2 EHV charges'!$D:$O,11,FALSE)),"") -> 0.05 | H13: =IFERROR(IF(VLOOKUP($A13,'Annex 2 EHV charges'!$D:$O,12,FALSE)=0,"",VLOOKUP($A13,'Annex 2 EHV charges'!$D:$O,12,FALSE)),"") -> 0.05
A14: {=IFERROR(INDEX('Annex 2 EHV charges'!$D$11:$D$218, MATCH(0, IF(ISBLANK('Annex 2 EHV charges'!$D$11:$D$218),1, COUNTIF(A$4:$A13, 'Annex 2 EHV charges'!$D$11:$D$218)), 0)),"")} -> BGWDWF | B14: =IF($A14="","",VLOOKUP($A14,'Annex 2 EHV charges'!$D:$O,2,0)) -> 746 | C14: =IF($A14="","",VLOOKUP($A14,'Annex 2 EHV charges'!$D:$O,3,0)) -> 1030083931142 | D14: =IF($A14="","",VLOOKUP($A14,'Annex 2 EHV charges'!$D:$O,4,0)) -> BIGGLESWADE WIND FARM LIMITED | E14: =IFERROR(IF(VLOOKUP($A14,'Annex 2 EHV charges'!$D:$O,9,FALSE)=0,"",VLOOKUP($A14,'Annex 2 EHV charges'!$D:$O,9,FALSE)),"") | F14: =IFERROR(IF(VLOOKUP($A14,'Annex 2 EHV charges'!$D:$O,10,FALSE)=0,"",VLOOKUP($A14,'Annex 2 EHV charges'!$D:$O,10,FALSE)),"") -> 278.25 | G14: =IFERROR(IF(VLOOKUP($A14,'Annex 2 EHV charges'!$D:$O,11,FALSE)=0,"",VLOOKUP($A14,'Annex 2 EHV charges'!$D:$O,11,FALSE)),"") -> 0.05 | H14: =IFERROR(IF(VLOOKUP($A14,'Annex 2 EHV charges'!$D:$O,12,FALSE)=0,"",VLOOKUP($A14,'Annex 2 EHV charges'!$D:$O,12,FALSE)),"") -> 0.05
A15: {=IFERROR(INDEX('Annex 2 EHV charges'!$D$11:$D$218, MATCH(0, IF(ISBLANK('Annex 2 EHV charges'!$D$11:$D$218),1, COUNTIF(A$4:$A14, 'Annex 2 EHV charges'!$D$11:$D$218)), 0)),"")} -> BLGTSF | B15: =IF($A15="","",VLOOKUP($A15,'Annex 2 EHV charges'!$D:$O,2,0)) -> 466 | C15: =IF($A15="","",VLOOKUP($A15,'Annex 2 EHV charges'!$D:$O,3,0)) -> 1050000769048 | D15: =IF($A15="","",VLOOKUP($A15,'Annex 2 EHV charges'!$D:$O,4,0)) -> SOLAR CENTURY | E15: =IFERROR(IF(VLOOKUP($A15,'Annex 2 EHV charges'!$D:$O,9,FALSE)=0,"",VLOOKUP($A15,'Annex 2 EHV charges'!$D:$O,9,FALSE)),"") | F15: =IFERROR(IF(VLOOKUP($A15,'Annex 2 EHV charges'!$D:$O,10,FALSE)=0,"",VLOOKUP($A15,'Annex 2 EHV charges'!$D:$O,10,FALSE)),"") -> 1117.59 | G15: =IFERROR(IF(VLOOKUP($A15,'Annex 2 EHV charges'!$D:$O,11,FALSE)=0,"",VLOOKUP($A15,'Annex 2 EHV charges'!$D:$O,11,FALSE)),"") -> 0.05 | H15: =IFERROR(IF(VLOOKUP($A15,'Annex 2 EHV charges'!$D:$O,12,FALSE)=0,"",VLOOKUP($A15,'Annex 2 EHV charges'!$D:$O,12,FALSE)),"") -> 0.05
A16: {=IFERROR(INDEX('Annex 2 EHV charges'!$D$11:$D$218, MATCH(0, IF(ISBLANK('Annex 2 EHV charges'!$D$11:$D$218),1, COUNTIF(A$4:$A15, 'Annex 2 EHV charges'!$D$11:$D$218)), 0)),"")} -> BOXTED | B16: =IF($A16="","",VLOOKUP($A16,'Annex 2 EHV charges'!$D:$O,2,0)) -> 783 | C16: =IF($A16="","",VLOOKUP($A16,'Annex 2 EHV charges'!$D:$O,3,0)) -> 1050000774289 | D16: =IF($A16="","",VLOOKUP($A16,'Annex 2 EHV charges'!$D:$O,4,0)) -> PUSH ENERGY (BOXTED AIRFIELD) LIMITED | E16: =IFERROR(IF(VLOOKUP($A16,'Annex 2 EHV charges'!$D:$O,9,FALSE)=0,"",VLOOKUP($A16,'Annex 2 EHV charges'!$D:$O,9,FALSE)),"") | F16: =IFERROR(IF(VLOOKUP($A16,'Annex 2 EHV charges'!$D:$O,10,FALSE)=0,"",VLOOKUP($A16,'Annex 2 EHV charges'!$D:$O,10,FALSE)),"") -> 952.82 | G16: =IFERROR(IF(VLOOKUP($A16,'Annex 2 EHV charges'!$D:$O,11,FALSE)=0,"",VLOOKUP($A16,'Annex 2 EHV charges'!$D:$O,11,FALSE)),"") -> 0.05 | H16: =IFERROR(IF(VLOOKUP($A16,'Annex 2 EHV charges'!$D:$O,12,FALSE)=0,"",VLOOKUP($A16,'Annex 2 EHV charges'!$D:$O,12,FALSE)),"") -> 0.05
... A123: {=IFERROR(INDEX('Annex 2 EHV charges'!$D$11:$D$218, MATCH(0, IF(ISBLANK('Annex 2 EHV charges'!$D$11:$D$218),1, COUNTIF(A$4:$A122, 'Annex 2 EHV charges'!$D$11:$D$218)), 0)),"")} -> WSTNLV | B123: =IF($A123="","",VLOOKUP($A123,'Annex 2 EHV charges'!$D:$O,2,0)) -> 471 | C123: =IF($A123="","",VLOOKUP($A123,'Annex 2 EHV charges'!$D:$O,3,0)) -> 1050000811601 | D123: =IF($A123="","",VLOOKUP($A123,'Annex 2 EHV charges'!$D:$O,4,0)) -> WESTON LONGVILLE G1 SOLAR FARM LIMITED | E123: =IFERROR(IF(VLOOKUP($A123,'Annex 2 EHV charges'!$D:$O,9,FALSE)=0,"",VLOOKUP($A123,'Annex 2 EHV charges'!$D:$O,9,FALSE)),"") | F123: =IFERROR(IF(VLOOKUP($A123,'Annex 2 EHV charges'!$D:$O,10,FALSE)=0,"",VLOOKUP($A123,'Annex 2 EHV charges'!$D:$O,10,FALSE)),"") -> 708.76 | G123: =IFERROR(IF(VLOOKUP($A123,'Annex 2 EHV charges'!$D:$O,11,FALSE)=0,"",VLOOKUP($A123,'Annex 2 EHV charges'!$D:$O,11,FALSE)),"") -> 0.05 | H123: =IFERROR(IF(VLOOKUP($A123,'Annex 2 EHV charges'!$D:$O,12,FALSE)=0,"",VLOOKUP($A123,'Annex 2 EHV charges'!$D:$O,12,FALSE)),"") -> 0.05

Sheet Annex 3 Preserved charges
A1: Back to Overview
A2: =Overview!B4& " - Effective from "&Overview!D4&" - "&Overview!E4&" LV and HV tariffs" -> Eastern Power Networks - Effective from 01/04/2017 - Final LV and HV tariffs
A3: NHH preserved charges/additional LLFCs
B4: Closed LLFCs | C4: PCs | D4: Unit charge 1 (NHH) p/kWh | E4: Unit charge 2 (NHH) p/kWh | F4: Fixed charge p/MPAN/day
A6: Notes: | B6: =Overview!B4& " has no Preserved NHH Tariffs/Additional LLFC classes" -> Eastern Power Networks has no Preserved NHH Tariffs/Additional LLFC classes
A11: HH preserved charges/additional LLFCs
B12: Closed LLFCs | C12: PCs | D12: Red/black charge (HH) p/kWh | E12: Amber/yellow charge (HH) p/kWh | F12: Green charge (HH) p/kWh | G12: Fixed charge p/MPAN/day | H12: Capacity charge p/kVA/day | I12: Reactive power charge p/kVArh | J12: Exceeded capacity charge p/kVA/day
C13: 0
A14: Notes: | B14: =Overview!B4& " has no Preserved HH Tariffs/Additional LLFC classes" -> Eastern Power Networks has no Preserved HH Tariffs/Additional LLFC classes

Sheet Annex 4 LDNO charges
A1: Back to Overview | B1: Copy from CDCM table 3701 "Tariffs!A42:I84" and paste values into A14 | F1: Copy from EDCM table 6005 "LDNORev!B549:G683" and paste values into D57
A2: =Overview!B4& " - Effective from "&Overview!D4&" - "&Overview!E4&" LDNO tariffs" -> Eastern Power Networks - Effective from 01/04/2017 - Final LDNO tariffs
A4: Time Bands for Half Hourly Metered Properties | F4: Time Bands for Half Hourly Unmetered Properties
A5: Time periods | B5: Red Time Band | C5: Amber Time Band | D5: Green Time Band | H5: Black Time Band | I5: Yellow Time Band | J5: Green Time Band
A6: Monday to Friday (Including Bank Holidays) All Year | B6: 16:00 - 19:00 | C6: 07:00 - 16:00 19:00 - 23:00 | D6: 00:00 - 07:00 23:00 - 24:00 | F6: Monday to Friday (Including Bank Holidays) November to February Inclusive | H6: 16:00 - 19:00 | I6: 07:00 - 16:00 19:00 - 23:00 | J6: 00:00 - 07:00 23:00 - 24:00
A7: Saturday and Sunday All Year | D7: 00:00 - 24:00 | F7: Monday to Friday (Including Bank Holidays) March to October Inclusive | I7: 07:00 - 23:00 | J7: 00:00 - 07:00 23:00 - 24:00
A8: Notes | B8: All times are in UK Clock time | F8: Saturday and Sunday All Year | J8: 00:00 - 24:00
F9: Notes | H9: All times are in UK Clock time
A13: Tariff name | B13: Unique billing identifier | C13: PCs | D13: ='Annex 1 LV and HV charges'!D13 -> Unit charge 1 (NHH) or red/black charge (HH) p/kWh | E13: ='Annex 1 LV and HV charges'!E13 -> Unit charge 2 (NHH) or amber/yellow charge (HH) p/kWh | F13: ='Annex 1 LV and HV charges'!F13 -> Green charge(HH) p/kWh | G13: ='Annex 1 LV and HV charges'!G13 -> Fixed charge p/MPAN/day | H13: ='Annex 1 LV and HV charges'!H13 -> Capacity charge p/kVA/day | I13: ='Annex 1 LV and HV charges'!I13 -> Reactive power charge p/kVArh | J13: ='Annex 1 LV and HV charges'!J13 -> Exceeded capacity charge p/kVA/day
A14: LDNO LV: Domestic Unrestricted | C14: 1 | D14: 1.352 | E14: 0 | F14: 0 | G14: 3.17 | H14: 0 | I14: 0
A15: LDNO LV: Domestic Two Rate | C15: 2 | D15: 1.622 | E15: 0.02 | F15: 0 | G15: 3.17 | H15: 0 | I15: 0
A16: LDNO LV: Domestic Off Peak (related MPAN) | C16: 2 | D16: 0.062 | E16: 0 | F16: 0 | G16: 0 | H16: 0 | I16: 0
A17: LDNO LV: Small Non Domestic Unrestricted | C17: 3 | D17: 1.039 | E17: 0 | F17: 0 | G17: 3.42 | H17: 0 | I17: 0
A18: LDNO LV: Small Non Domestic Two Rate | C18: 4 | D18: 1.244 | E18: 0.02 | F18: 0 | G18: 3.42 | H18: 0 | I18: 0
A19: LDNO LV: Small Non Domestic Off Peak (related MPAN) | C19: 4 | D19: 0.122 | E19: 0 | F19: 0 | G19: 0 | H19: 0 | I19: 0
A20: LDNO LV: LV Medium Non-Domestic | C20: 5-8 | D20: 1.173 | E20: 0.016 | F20: 0 | G20: 22.28 | H20: 0 | I20: 0
A21: LDNO LV: LV Network Domestic | C21: 0 | D21: 10.324 | E21: 0.089 | F21: 0.016 | G21: 3.17 | H21: 0 | I21: 0
A22: LDNO LV: LV Network Non-Domestic Non-CT | C22: 0 | D22: 9.377 | E22: 0.081 | F22: 0.014 | G22: 3.63 | H22: 0 | I22: 0
A23: LDNO LV: LV HH Metered | C23: 0 | D23: 7.385 | E23: 0.053 | F23: 0.009 | G23: 10.06 | H23: 2.13 | I23: 0.225 | J23: =H23 -> 2.13
A24: LDNO LV: NHH UMS category A | C24: 8 | D24: 1.184 | E24: 0 | F24: 0 | G24: 0 | H24: 0 | I24: 0
A25: LDNO LV: NHH UMS category B | C25: 1 | D25: 1.762 | E25: 0 | F25: 0 | G25: 0 | H25: 0 | I25: 0
A26: LDNO LV: NHH UMS category C | C26: 1 | D26: 2.998 | E26: 0 | F26: 0 | G26: 0 | H26: 0 | I26: 0
A27: LDNO LV: NHH UMS category D | C27: 1 | D27: 0.799 | E27: 0 | F27: 0 | G27: 0 | H27: 0 | I27: 0
A28: LDNO LV: LV UMS (Pseudo HH Metered) | C28: 0 | D28: 26.839 | E28: 0.442 | F28: 0.374 | G28: 0 | H28: 0 | I28: 0
A29: LDNO LV: LV Generation NHH or Aggregate HH | C29: 8 or 0 | D29: -0.905 | E29: 0 | F29: 0 | G29: 0 | H29: 0 | I29: 0
A30: LDNO LV: LV Generation Intermittent | C30: 0 | D30: -0.905 | E30: 0 | F30: 0 | G30: 0 | H30: 0 | I30: 0.289
A31: LDNO LV: LV Generation Non-Intermittent | C31: 0 | D31: -9.684 | E31: -0.09 | F31: -0.016 | G31: 0 | H31: 0 | I31: 0.289
A32: LDNO HV: Domestic Unrestricted | C32: 1 | D32: 0.947 | E32: 0 | F32: 0 | G32: 2.22 | H32: 0 | I32: 0
A33: LDNO HV: Domestic Two Rate | C33: 2 | D33: 1.136 | E33: 0.014 | F33: 0 | G33: 2.22 | H33: 0 | I33: 0
A34: LDNO HV: Domestic Off Peak (related MPAN) | C34: 2 | D34: 0.044 | E34: 0 | F34: 0 | G34: 0 | H34: 0 | I34: 0
A35: LDNO HV: Small Non Domestic Unrestricted | C35: 3 | D35: 0.728 | E35: 0 | F35: 0 | G35: 2.39 | H35: 0 | I35: 0
A36: LDNO HV: Small Non Domestic Two Rate | C36: 4 | D36: 0.871 | E36: 0.014 | F36: 0 | G36: 2.39 | H36: 0 | I36: 0
A37: LDNO HV: Small Non Domestic Off Peak (related MPAN) | C37: 4 | D37: 0.085 | E37: 0 | F37: 0 | G37: 0 | H37: 0 | I37: 0
A38: LDNO HV: LV Medium Non-Domestic | C38: 5-8 | D38: 0.822 | E38: 0.011 | F38: 0 | G38: 15.61 | H38: 0 | I38: 0
A39: LDNO HV: LV Network Domestic | C39: 0 | D39: 7.232 | E39: 0.062 | F39: 0.011 | G39: 2.22 | H39: 0 | I39: 0
A40: LDNO HV: LV Network Non-Domestic Non-CT | C40: 0 | D40: 6.569 | E40: 0.056 | F40: 0.01 | G40: 2.55 | H40: 0 | I40: 0
A41: LDNO HV: LV HH Metered | C41: 0 | D41: 5.173 | E41: 0.037 | F41: 0.007 | G41: 7.05 | H41: 1.49 | I41: 0.157 | J41: =H41 -> 1.49
A42: LDNO HV: LV Sub HH Metered | C42: 0 | D42: 5.603 | E42: 0.025 | F42: 0.005 | G42: 7.4 | H42: 3.39 | I42: 0.156 | J42: =H42 -> 3.39
A43: LDNO HV: HV HH Metered | C43: 0 | D43: 5.225 | E43: 0.016 | F43: 0.003 | G43: 83.91 | H43: 3.17 | I43: 0.147 | J43: =H43 -> 3.17
A44: LDNO HV: NHH UMS category A | C44: 8 | D44: 0.829 | E44: 0 | F44: 0 | G44: 0 | H44: 0 | I44: 0
A45: LDNO HV: NHH UMS category B | C45: 1 | D45: 1.235 | E45: 0 | F45: 0 | G45: 0 | H45: 0 | I45: 0
A46: LDNO HV: NHH UMS category C | C46: 1 | D46: 2.1 | E46: 0 | F46: 0 | G46: 0 | H46: 0 | I46: 0
A47: LDNO HV: NHH UMS category D | C47: 1 | D47: 0.56 | E47: 0 | F47: 0 | G47: 0 | H47: 0 | I47: 0
A48: LDNO HV: LV UMS (Pseudo HH Metered) | C48: 0 | D48: 18.802 | E48: 0.31 | F48: 0.262 | G48: 0 | H48: 0 | I48: 0
A49: LDNO HV: LV Generation NHH or Aggregate HH | C49: 8 or 0 | D49: -0.905 | E49: 0 | F49: 0 | G49: 0 | H49: 0 | I49: 0
A50: LDNO HV: LV Sub Generation NHH | C50: 8 | D50: -0.802 | E50: 0 | F50: 0 | G50: 0 | H50: 0 | I50: 0
A51: LDNO HV: LV Generation Intermittent | C51: 0 | D51: -0.905 | E51: 0 | F51: 0 | G51: 0 | H51: 0 | I51: 0.289
A52: LDNO HV: LV Generation Non-Intermittent | C52: 0 | D52: -9.684 | E52: -0.09 | F52: -0.016 | G52: 0 | H52: 0 | I52: 0.289
A53: LDNO HV: LV Sub Generation Intermittent | C53: 0 | D53: -0.802 | E53: 0 | F53: 0 | G53: 0 | H53: 0 | I53: 0.259
A54: LDNO HV: LV Sub Generation Non-Intermittent | C54: 0 | D54: -8.626 | E54: -0.072 | F54: -0.013 | G54: 0 | H54: 0 | I54: 0.259
A55: LDNO HV: HV Generation Intermittent | C55: 0 | D55: -0.577 | E55: 0 | F55: 0 | G55: 0 | H55: 0 | I55: 0.211
A56: LDNO HV: HV Generation Non-Intermittent | C56: 0 | D56: -6.312 | E56: -0.03 | F56: -0.006 | G56: 0 | H56: 0 | I56: 0.211
A57: LDNO HVplus: Domestic Unrestricted | C57: 1 | D57: 0.866 | G57: 2.03
A58: LDNO HVplus: Domestic Two Rate | C58: 2 | D58: 1.039 | E58: 0.013 | G58: 2.03
A59: LDNO HVplus: Domestic Off Peak (related MPAN) | C59: 2 | D59: 0.04
A60: LDNO HVplus: Small Non Domestic Unrestricted | C60: 3 | D60: 0.665 | G60: 2.19
A61: LDNO HVplus: Small Non Domestic Two Rate | C61: 4 | D61: 0.797 | E61: 0.013 | G61: 2.19
A62: LDNO HVplus: Small Non Domestic Off Peak (related MPAN) | C62: 4 | D62: 0.078
A63: LDNO HVplus: LV Medium Non-Domestic | C63: 5-8 | D63: 0.751 | E63: 0.01 | G63: 14.27
A64: LDNO HVplus: LV Sub Medium Non-Domestic | C64: 5-8 | D64: 0.673 | E64: 0.008 | G64: 6.57
A65: LDNO HVplus: HV Medium Non-Domestic | C65: 5-8 | D65: 0.493 | E65: 0.003 | G65: 73.77
A66: LDNO HVplus: LV Network Domestic | C66: 0 | D66: 6.611 | E66: 0.057 | F66: 0.01 | G66: 2.03
A67: LDNO HVplus: LV Network Non-Domestic Non-CT | C67: 0 | D67: 6.005 | E67: 0.052 | F67: 0.009 | G67: 2.33
A68: LDNO HVplus: LV HH Metered | C68: 0 | D68: 4.729 | E68: 0.034 | F68: 0.006 | G68: 6.45 | H68: 1.37 | I68: 0.144 | J68: =H68 -> 1.37
A69: LDNO HVplus: LV Sub HH Metered | C69: 0 | D69: 4.973 | E69: 0.023 | F69: 0.005 | G69: 6.57 | H69: 3.01 | I69: 0.139 | J69: =H69 -> 3.01
A70: LDNO HVplus: HV HH Metered | C70: 0 | D70: 4.594 | E70: 0.014 | F70: 0.003 | G70: 73.77 | H70: 2.78 | I70: 0.129 | J70: =H70 -> 2.78
A71: LDNO HVplus: NHH UMS category A | C71: 8 | D71: 0.758
A72: LDNO HVplus: NHH UMS category B | C72: 1 | D72: 1.129
A73: LDNO HVplus: NHH UMS category C | C73: 1 | D73: 1.92
A74: LDNO HVplus: NHH UMS category D | C74: 1 | D74: 0.512
A75: LDNO HVplus: LV UMS (Pseudo HH Metered) | C75: 0 | D75: 17.188 | E75: 0.283 | F75: 0.239
A76: LDNO HVplus: LV Generation NHH or Aggregate HH | C76: 8 | D76: -0.583 | G76: 0
A77: LDNO HVplus: LV Sub Generation NHH | C77: 8 | D77: -0.577 | G77: 0
A78: LDNO HVplus: LV Generation Intermittent | C78: 0 | D78: -0.583 | G78: 0 | I78: 0.186
A79: LDNO HVplus: LV Generation Non-Intermittent | C79: 0 | D79: -6.24 | E79: -0.058 | F79: -0.01 | G79: 0 | I79: 0.186
A80: LDNO HVplus: LV Sub Generation Intermittent | C80: 0 | D80: -0.577 | G80: 0 | I80: 0.186
A81: LDNO HVplus: LV Sub Generation Non-Intermittent | C81: 0 | D81: -6.207 | E81: -0.052 | F81: -0.009 | G81: 0 | I81: 0.186
A82: LDNO HVplus: HV Generation Intermittent | C82: 0 | D82: -0.577 | G82: 48.95 | I82: 0.211
A83: LDNO HVplus: HV Generation Non-Intermittent | C83: 0 | D83: -6.312 | E83: -0.03 | F83: -0.006 | G83: 48.95 | I83: 0.211
A84: LDNO EHV: Domestic Unrestricted | C84: 1 | D84: 0.656 | G84: 1.54
A85: LDNO EHV: Domestic Two Rate | C85: 2 | D85: 0.787 | E85: 0.01 | G85: 1.54
A86: LDNO EHV: Domestic Off Peak (related MPAN) | C86: 2 | D86: 0.03
A87: LDNO EHV: Small Non Domestic Unrestricted | C87: 3 | D87: 0.504 | G87: 1.66
A88: LDNO EHV: Small Non Domestic Two Rate | C88: 4 | D88: 0.604 | E88: 0.01 | G88: 1.66
A89: LDNO EHV: Small Non Domestic Off Peak (related MPAN) | C89: 4 | D89: 0.059
A90: LDNO EHV: LV Medium Non-Domestic | C90: 5-8 | D90: 0.569 | E90: 0.008 | G90: 10.81
A91: LDNO EHV: LV Sub Medium Non-Domestic | C91: 5-8 | D91: 0.51 | E91: 0.006 | G91: 4.98
A92: LDNO EHV: HV Medium Non-Domestic | C92: 5-8 | D92: 0.374 | E92: 0.002 | G92: 55.91
A93: LDNO EHV: LV Network Domestic | C93: 0 | D93: 5.01 | E93: 0.043 | F93: 0.008 | G93: 1.54
A94: LDNO EHV: LV Network Non-Domestic Non-CT | C94: 0 | D94: 4.551 | E94: 0.039 | F94: 0.007 | G94: 1.76
A95: LDNO EHV: LV HH Metered | C95: 0 | D95: 3.584 | E95: 0.026 | F95: 0.005 | G95: 4.88 | H95: 1.03 | I95: 0.109 | J95: =H95 -> 1.03
A96: LDNO EHV: LV Sub HH Metered | C96: 0 | D96: 3.769 | E96: 0.017 | F96: 0.003 | G96: 4.98 | H96: 2.28 | I96: 0.105 | J96: =H96 -> 2.28
A97: LDNO EHV: HV HH Metered | C97: 0 | D97: 3.481 | E97: 0.011 | F97: 0.002 | G97: 55.91 | H97: 2.11 | I97: 0.098 | J97: =H97 -> 2.11
A98: LDNO EHV: NHH UMS category A | C98: 8 | D98: 0.574
A99: LDNO EHV: NHH UMS category B | C99: 1 | D99: 0.855
A100: LDNO EHV: NHH UMS category C | C100: 1 | D100: 1.455
A101: LDNO EHV: NHH UMS category D | C101: 1 | D101: 0.388
A102: LDNO EHV: LV UMS (Pseudo HH Metered) | C102: 0 | D102: 13.025 | E102: 0.214 | F102: 0.181
A103: LDNO EHV: LV Generation NHH or Aggregate HH | C103: 8 | D103: -0.442 | G103: 0
A104: LDNO EHV: LV Sub Generation NHH | C104: 8 | D104: -0.437 | G104: 0
...

Sheet Annex 5 LLFs
A1: Back to Overview
A2: These line loss factors are illustrative based on the latest calculated values and are published in good faith. However, the line loss factors that are approved by the BSC Panel for the applicable year and consequently published on the Elexon website will take precedence and be used in Settlement if they differ from these values.
A3: =Overview!B4& " - Illustrative LLFs for year beginning "&Overview!D4 -> Eastern Power Networks - Illustrative LLFs for year beginning 01/04/2017
A4: Time periods | C4: Period 1 | D4: Period 2 | E4: Period 3 | F4: Period 4 | G4: Period 5
C5: Winter Peak | D5: Summer Peak | E5: Winter Shoulder | F5: Night | G5: Other
A6: Monday to Friday November to February | C6: 16:00 - 19:59 | E6: 07:00 - 15:59
A7: Monday to Friday June to August | D7: 07:00 - 19:59
A8: Monday to Friday March | E8: 07:00 - 19:59
A9: All Year | F9: 00:00 - 06:59 | G9: All Other Times
A10: Notes | C10: All times are in UK Clock time
A12: Generic demand and generation LLFs
A13: Metered voltage, respective periods and associated LLFCs
A14: Metered voltage | C14: Period 1 | D14: Period 2 | E14: Period 3 | F14: Period 4 | G14: Period 5 | H14: Associated LLFC
A15: Low-voltage network | C15: 1.117 | D15: 1.08 | E15: 1.087 | F15: 1.079 | G15: 1.1 | H15: 1, 3, 7, 11, 15, 22, 25, 29, 33, 40, 43, 46, 49, 55, 58, 61, 64, 86, 100, 101, 102, 103, 110, 111, 112, 113, 150, 151, 152, 153, 160, 161, 162, 163, 200, 201, 205, 237, 238, 239, 242, 247, 248, 250, 254, 350, 901, 905, 912, 913, 915
A16: Low-voltage substation | C16: 1.085 | D16: 1.063 | E16: 1.074 | F16: 1.058 | G16: 1.066 | H16: 80, 902, 916
A17: High-voltage network | C17: 1.053 | D17: 1.04 | E17: 1.046 | F17: 1.035 | G17: 1.041 | H17: 84, 903, 918
A18: High-voltage substation | C18: 1.052 | D18: 1.039 | E18: 1.046 | F18: 1.035 | G18: 1.04 | H18: 771, 791, 792
A19: 33kV generic | C19: 1.017 | D19: 1.014 | E19: 1.016 | F19: 1.013 | G19: 1.014 | H19: 796, 797
A20: 132kV generic | C20: 1.004 | D20: 1.003 | E20: 1.003 | F20: 1.002 | G20: 1.003 | H20: 798, 799
A22: EHV site specific LLFs
A23: Demand
A24: LLFC | B24: Site | D24: Period 1 | E24: Period 2 | F24: Period 3 | G24: Period 4 | H24: Period 5
A25: 500 | B25: Stratton Hall Solar - IMPORT | D25: 1.06 | E25: 1.024 | F25: 1.039 | G25: 1.042 | H25: 1.055
A26: 501 | B26: Weston Airfield - IMPORT | D26: 1.064 | E26: 1.045 | F26: 1.042 | G26: 1.038 | H26: 1.046
A27: 502 | B27: Suffolk EFW - IMPORT | D27: 1.056 | E27: 1.05 | F27: 1.015 | G27: 1.072 | H27: 1.036
A28: 503 | B28: Aston Clinton SF - IMPORT | D28: 1.032 | E28: 1.031 | F28: 1.03 | G28: 1.023 | H28: 1.026
A29: 504 | B29: Avenue Farm - IMPORT | D29: 1.021 | E29: 1.022 | F29: 1.023 | G29: 1.02 | H29: 1.02
A30: 505 | B30: Boardinghouse Wind - IMPORT | D30: 1.144 | E30: 1.133 | F30: 1.137 | G30: 1.132 | H30: 1.134
A31: 506 | B31: Boxted Airfield SF - IMPORT | D31: 1.051 | E31: 1.028 | F31: 1.043 | G31: 1.036 | H31: 1.044
A32: 507 | B32: Bassingbourn Solar - IMPORT | D32: 1.012 | E32: 1.012 | F32: 1.013 | G32: 1.012 | H32: 1.012
A33: 508 | B33: Burnthouse Solar II - IMPORT | D33: 1.029 | E33: 1.02 | F33: 1.027 | G33: 1.023 | H33: 1.027
A34: 509 | B34: Croydon Solar Farm - IMPORT | D34: 0.999 | E34: 1 | F34: 1 | G34: 0.999 | H34: 1.004
A35: 510 | B35: Exning Solar Farm - IMPORT | D35: 1.006 | E35: 1.006 | F35: 1.006 | G35: 1.006 | H35: 1.006
A36: 511 | B36: Fenland Solar Farm - IMPORT | D36: 1.037 | E36: 1.023 | F36: 1.033 | G36: 1.028 | H36: 1.032
... A162: 898 | B162: Stowbridge Solar Farm - IMPORT | D162: 1.021 | E162: 1.016 | F162: 1.019 | G162: 1.02 | H162: 1.02
A164: EHV site specific LLFs
A165: Generation
A166: LLFC | B166: Site | D166: Period 1 | E166: Period 2 | F166: Period 3 | G166: Period 4 | H166: Period 5
A167: 450 | B167: Hydes Farm - EXPORT | D167: 1.008 | E167: 0.996 | F167: 1.003 | G167: 1.004 | H167: 1
A168: 451 | B168: Jacks Lane Wind Farm - EXPORT | D168: 1.004 | E168: 0.994 | F168: 1.007 | G168: 0.994 | H168: 1.003
A169: 452 | B169: Kenninghall Solar - EXPORT | D169: 1.012 | E169: 1.012 | F169: 1.033 | G169: 1.019 | H169: 1.034
A170: 453 | B170: Langford Solar Farm - EXPORT | D170: 1.023 | E170: 1.01 | F170: 1.016 | G170: 1.015 | H170: 1.017
A171: 454 | B171: Langenhoe Solar Farm - EXPORT | D171: 1.01 | E171: 0.997 | F171: 1.003 | G171: 1.003 | H171: 1
A172: 455 | B172: Langenhoe Solar II - EXPORT | D172: 1.022 | E172: 1.011 | F172: 1.019 | G172: 1.013 | H172: 1.02
A173: 456 | B173: Manor Farm Eggington - EXPORT | D173: 1.027 | E173: 1.015 | F173: 1.023 | G173: 1.013 | H173: 1.024
A174: 457 | B174: Old Airfield (Birch) - EXPORT | D174: 1.028 | E174: 1.013 | F174: 1.019 | G174: 1.015 | H174: 1.023
A175: 458 | B175: Quarrendon Wind - EXPORT | D175: 1.055 | E175: 1.022 | F175: 1.046 | G175: 1.025 | H175: 1.029
A176: 459 | B176: Scottow Estate SF - EXPORT | D176: 1.021 | E176: 1.015 | F176: 1.018 | G176: 1.017 | H176: 1.021
A177: 460 | B177: St. Osyth PV Farm - EXPORT | D177: 1.011 | E177: 0.99 | F177: 0.995 | G177: 1.007 | H177: 0.995
A178: 461 | B178: Wiggin Hill Farm - EXPORT | D178: 1.014 | E178: 1.005 | F178: 1.009 | G178: 1.005 | H178: 1.009
... A277: 790 | B277: Folly Solar Farm - EXPORT | D277: 1.028 | E277: 1.012 | F277: 1.018 | G277: 1.01 | H277: 1.012
A279: CVA site specific LLFs
A280: MSID | B280: Site | D280: Period 1 | E280: Period 2 | F280: Period 3 | G280: Period 4 | H280: Period 5
A281: 1413 | B281: Norwich Main SGT 1 and 2 | D281: 0.999 | E281: 1 | F281: 1 | G281: 1 | H281: 1
A282: 1414 | B282: Norwich Main SGT 3 and 4 | D282: 0.999 | E282: 1 | F282: 0.999 | G282: 1 | H282: 1
A283: 1440 | B283: Amersham/Ilmer | D283: 1.005 | E283: 1.003 | F283: 1.004 | G283: 1.003 | H283: 1.004
A284: 7006 | B284: Peterborough Power Station | D284: 1.014 | E284: 1.005 | F284: 1.011 | G284: 1.011 | H284: 1.01
A285: 2035 | B285: WPD Stamford | D285: 1.012 | E285: 1.007 | F285: 1.009 | G285: 1.008 | H285: 1.009
A286: 1419 | B286: Sundon | D286: 1 | E286: 1 | F286: 1 | G286: 1 | H286: 1
A287: 7044 | B287: King's Lynn Power Station | D287: 1.008 | E287: 1 | F287: 1.003 | G287: 1.005 | H287: 1.006
A288: 7074 | B288: Enfield Energy Centre | D288: 1.053 | E288: 1.04 | F288: 1.046 | G288: 1.035 | H288: 1.041
A289: 7111 | B289: Great Yarmouth Power Station | D289: 1 | E289: 1 | F289: 0.997 | G289: 0.995 | H289: 0.998
A290: 7277 | B290: Gunfleet Sands 33kV | D290: 0.946 | E290: 0.976 | F290: 0.952 | G290: 0.965 | H290: 0.956
A291: 7308 / 7309 | B291: Green Frog Power Ltd | D291: 1.017 | E291: 1.014 | F291: 1.016 | G291: 1.013 | H291: 1.014

Sheet Annex 6 New Designated EHV Prop
A1: Back to Overview | G1: Note: The list of MPANs/MSIDs provided may be incomplete; the DNO reserves the right to apply the listed charges to any other MPANs/MSIDs associated with the site.
A2: Annex 6 - Addendum to Annex 2 EHV charges
A4: =Overview!B4& " - Effective from "&Overview!D4&" - "&Overview!E4&" new designated EHV charges" -> Eastern Power Networks - Effective from 01/04/2017 - Final new designated EHV charges
A5: Import Unique Identifier | B5: LLFC | C5: Import MPANs/MSIDs | D5: Export Unique Identifier | E5: LLFC | F5: Export MPANs/MSIDs | G5: Name | H5: ='Annex 2 EHV charges'!H10 -> Import Super Red unit charge (p/kWh) | I5: ='Annex 2 EHV charges'!I10 -> Import fixed charge (p/day) | J5: ='Annex 2 EHV charges'!J10 -> Import capacity charge (p/kVA/day) | K5: ='Annex 2 EHV charges'!K10 -> Import exceeded capacity charge (p/kVA/day) | L5: ='Annex 2 EHV charges'!L10 -> Export Super Red unit charge (p/kWh) | M5: ='Annex 2 EHV charges'!M10 -> Export fixed charge (p/day) | N5: ='Annex 2 EHV charges'!N10 -> Export capacity charge (p/kVA/day) | O5: ='Annex 2 EHV charges'!O10 -> Export exceeded capacity charge (p/kVA/day)
A6: ALCORG | B6: 796 | C6: 1050001015545 | D6: =A6 -> ALCORG | E6: 797 | F6: 1050000998050 | G6: ALCOR LSPV LTD | H6: 4.113 | I6: 5.06 | J6: 3.81 | K6: =J6 -> 3.81 | L6: 0 | M6: 506.26 | N6: 0.05 | O6: 0.05
A7: ARDLGH | B7: 796 | C7: 1050001061597 | D7: =A7 -> ARDLGH | E7: 797 | F7: 1050001061602 | G7: SUNSAVE 28 (ARDLEIGH) LIMITED | H7: 3.983 | I7: 1.33 | J7: 4.98 | K7: =J7 -> 4.98 | L7: 0 | M7: 533.31 | N7: 0.05 | O7: 0.05
A8: BERDHF | B8: 798 | C8: 1050001382522 | D8: BERDHF | E8: 799 | F8: 1050001382531 | G8: STATERA ENERGY LIMITED | H8: 0 | I8: 1308.59 | J8: 1.15 | K8: 1.15 | L8: 0 | M8: 1308.59 | N8: 0.05 | O8: 0.05
A9: BLCAMB | B9: 796 | C9: 1050001036615 | D9: =A9 -> BLCAMB | E9: 797 | F9: 1050001036624 | G9: BURY GREEN FARM SOLAR LIMITED | H9: 0.463 | I9: 5.01 | J9: 1.9 | K9: =J9 -> 1.9 | M9: 250.7 | N9: 0.05 | O9: 0.05
A10: BLDOCK | B10: MSID 7308 | C10: 1097000000183 | D10: =A10 -> BLDOCK | E10: MSID 7309 | F10: 1097000000192 | G10: GREEN FROG POWER LTD | H10: 1.095 | I10: 5.22 | J10: 1.42 | K10: =J10 -> 1.42 | L10: -1.553 | M10: 521.85 | N10: 0.05 | O10: 0.05
A11: BNNSHL | B11: 796 | C11: 1050001021414 | D11: =A11 -> BNNSHL | E11: 797 | F11: 1050001021423 | G11: BUNNS HILL SOLAR LIMITED | H11: 0.311 | I11: 35.24 | J11: 5.59 | K11: =J11 -> 5.59 | L11: 0 | M11: 1507.7 | N11: 0.05 | O11: 0.05
A12: CLAYBT | B12: 796 | C12: 1050001382364 | D12: CLAYBT | E12: 797 | F12: 1050001382373 | G12: ANESCO LIMITED | H12: 0.244 | I12: 0 | J12: 1.49 | K12: 1.49 | L12: -0.288 | M12: 0 | N12: 0.05 | O12: 0.05
A13: CLAYPV | B13: 796 | C13: 1050001382337 | D13: CLAYPV | E13: 797 | F13: 1050001382355 | G13: ANESCO LIMITED | H13: 0.244 | I13: 0 | J13: 1.49 | K13: 1.49 | L13: 0 | M13: 0 | N13: 0.05 | O13: 0.05
A14: CLDECT | B14: 796 | C14: 1050000714173 | D14: =A14 -> CLDECT | E14: 797 | F14: 1050000714182 | G14: AMP GM005 | H14: 0.21 | I14: 11.66 | J14: 1.42 | K14: =J14 -> 1.42 | L14: 0 | M14: 2565.22 | N14: 0.05 | O14: 0.05
A15: CLRDWN | B15: 796 | C15: 1050001495174 | D15: CLRDWN | E15: 797 | F15: 1050001495183 | G15: BESS CLAREDWON LTD | H15: 5.386 | I15: 484.99 | J15: 1 | K15: 1 | L15: -5.386 | M15: 484.99 | N15: 0.05 | O15: 0.05
A16: CRANHM | B16: 796 | C16: 1050001191792 | D16: =A16 -> CRANHM | E16: 797 | F16: 1050001191808 | G16: WEL SOLAR PARK 12 LTD | H16: 0.619 | I16: 10.06 | J16: 1.98 | K16: 1.98 | M16: 551.09 | N16: 0.05 | O16: 0.05
A17: CRSSNG | B17: 796 | C17: 1050001047087 | D17: =A17 -> CRSSNG | E17: 797 | F17: 1050001047078 | G17: CRESSING SOLAR FARM LIMITED | I17: 0.97 | J17: 1.98 | K17: 1.98 | M17: 486.04 | N17: 0.05 | O17: 0.05
A18: DRAYTN | B18: 796 | C18: 1050001047272 | D18: =A18 -> DRAYTN | E18: 797 | F18: 1050001047263 | G18: HAYMAKER (SIXTEEN) LTD | H18: 5.981 | I18: 11.68 | J18: 2.11 | K18: =J18 -> 2.11 | L18: 0 | M18: 525.43 | N18: 0.05 | O18: 0.05
A19: ERNUNN | B19: 798 | C19: 1050001440510 | D19: ERNUNN | E19: 799 | F19: 1050001440529 | G19: PLUTUS POWERGEN | H19: 0 | I19: 18.73 | J19: 2.22 | K19: 2.22 | L19: -0.615 | M19: 1440.53 | N19: 0.05 | O19: 0.05
A20: GREYSH | B20: 796 | C20: 1050001391466 | D20: GREYSH | E20: 797 | F20: 1050001391475 | G20: PUSH ENERGY LTD | H20: 11.997 | I20: 100.18 | J20: 2.17 | K20: 2.17 | L20: -11.532 | M20: 1953.53 | N20: 0.05 | O20: 0.05
A21: HDATTP | B21: 796 | C21: 1050001197873 | D21: =A21 -> HDATTP | E21: 797 | F21: 1050001197864 | G21: HODDESDON ADVANCED THERMAL TREATMENT WKS | H21: 0.002 | I21: 110.21 | J21: 1.74 | K21: 1.74 | L21: -0.721 | M21: 734.74 | N21: 0.05 | O21: 0.05
A22: HHFARM | B22: 796 | C22: 1050001231451 | D22: =A22 -> HHFARM | E22: 797 | F22: 1050001231460 | G22: LIGHTSOURCE SPV 9 LIMITED | H22: 1.527 | I22: 18.43 | J22: 1.51 | K22: 1.51 | L22: 0 | M22: 552.98 | N22: 0.05 | O22: 0.05
A23: HONYSM | B23: 796 | C23: 1050001036670 | D23: =A23 -> HONYSM | E23: 797 | F23: 1050001036689 | G23: HONEYSOME ROAD SOLAR LIMITED | H23: 0.541 | I23: 11.24 | J23: 4.71 | K23: =J23 -> 4.71 | L23: 0 | M23: 562.19 | N23: 0.05 | O23: 0.05
A24: HRLWDC | B24: 771 | C24: 1050001003372 1050001003381 1050001003390 | G24: HARLOW PROPERTIES LIMITED (KAO DATA CAMPUS) | H24: 0.233 | I24: 6998.05 | J24: 1.33 | K24: 1.33
A25: HRMTGE | B25: 796 | C25: 1050001129980 | D25: =A25 -> HRMTGE | E25: 797 | F25: 1050001129999 | G25: HERMITAGE SOLAR PARK LTD | H25: 0.244 | I25: 11.52 | J25: 1.48 | K25: 1.48 | M25: 576.07 | N25: 0.05 | O25: 0.05
A26: HRSFEN | B26: 796 | C26: 1050001041642 | D26: =A26 -> HRSFEN | E26: 797 | F26: 1050001041651 | G26: PRETORIA ENERGY COMPANY (MEPAL) LIMITED | H26: 0.533 | I26: 637.41 | J26: 3.16 | K26: 3.16 | L26: -2.542 | M26: 3187.07 | N26: 0.05 | O26: 0.05
A27: LBZSNS | B27: 771 | C27: 1050000687486 | D27: LBZSNS | E27: 792 | F27: 1050000687495 | G27: UK POWER NETWORKS OPERATIONS LTD | H27: 5.427 | I27: 133.74 | J27: 1.32 | K27: 1.32 | L27: -5.564 | M27: 133.74 | N27: 0.05 | O27: 0.05
A28: LEICSQ | B28: 798 | C28: 1050001008681 | D28: =A28 -> LEICSQ | E28: 799 | F28: 1050001008690 | G28: SOUTH CREAKE SOLAR COMPANY LIMITED | H28: 0.046 | I28: 6.15 | J28: 2.04 | K28: =J28 -> 2.04 | L28: 0 | M28: 2621.06 | N28: 0.05 | O28: 0.05
A29: LWRNCE | B29: 796 | C29: 1050001008645 | D29: =A29 -> LWRNCE | E29: 797 | F29: 1050001008636 | G29: LIGHTSOURCE SPV180 LTD | H29: 0.268 | I29: 20.74 | J29: 1.6 | K29: =J29 -> 1.6 | L29: 0 | M29: 1783.35 | N29: 0.05 | O29: 0.05
A30: LYONSH | B30: 796 | C30: 1050001205345 | D30: =A30 -> LYONSH | E30: 797 | F30: 1050001205354 | G30: PUSH ENERGY (KENTISHES) LIMITED | H30: 1.324 | I30: 5.31 | J30: 5.49 | K30: 5.49 | L30: 0 | M30: 578.99 | N30: 0.05 | O30: 0.05
A31: MILLDR | B31: 796 | C31: 1050001197855 | D31: =A31 -> MILLDR | E31: 797 | F31: 1050001197846 | G31: CAMBRIDGESHIRE COUNTY COUNCIL | H31: 0.029 | I31: 12.1 | J31: 1.47 | K31: 1.47 | L31: 0 | M31: 756.18 | N31: 0.05 | O31: 0.05
A32: MILLFM | B32: 796 | C32: 1050001261465 | D32: =A32 -> MILLFM | E32: 797 | F32: 1050001261429 | G32: PUSH ENERGY (MILL FARM) LIMITED | H32: 2.551 | I32: 13.14 | J32: 2.55 | K32: 2.55 | M32: 1051.23 | N32: 0.05 | O32: 0.05
A33: MLLFLD | B33: 796 | C33: 1050001060050 | D33: =A33 -> MLLFLD | E33: 797 | F33: 1050001060060 | G33: MILLFIELD SOLAR FARM | H33: 0.308 | I33: 17.12 | J33: 4.59 | K33: =J33 -> 4.59 | L33: 0 | M33: 854.46 | N33: 0.05 | O33: 0.05
A34: MOWLEM | B34: 796 | C34: 1050001054233 | D34: =A34 -> MOWLEM | E34: 797 | F34: 1050001054242 | G34: MOWLEM TRADING ESTATE | H34: 0.004 | I34: 23.03 | J34: 1.12 | K34: 1.12 | L34: -0.047 | M34: 921.24 | N34: 0.05 | O34: 0.05
A35: NEWTON | B35: 796 | C35: 1050001042238 | D35: =A35 -> NEWTON | E35: 797 | F35: 1050001042229 | G35: WEL SOLAR PARK 6 LIMITED | H35: 0.064 | I35: 1.48 | J35: 3.08 | K35: =J35 -> 3.08 | L35: 0 | M35: 591.84 | N35: 0.05 | O35: 0.05
A36: OULTON | B36: 796 | C36: 1050001028544 | D36: =A36 -> OULTON | E36: 797 | F36: 1050001028553 | G36: OULTON SOLAR LIMITED | H36: 0.081 | I36: 2.28 | J36: 3.49 | K36: =J36 -> 3.49 | L36: 0 | M36: 253.43 | N36: 0.05 | O36: 0.05
A37: OUTWDS | B37: 796 | C37: 1050001054190 | D37: =A37 -> OUTWDS | E37: 797 | F37: 1050001054206 | G37: WEL SOLAR PARK 5 LIMITED | H37: 1.014 | I37: 5.29 | J37: 1.66 | K37: =J37 -> 1.66 | L37: 0 | M37: 953 | N37: 0.05 | O37: 0.05
A38: POBAIL | B38: 796 | C38: 1050001118598 | D38: =A38 -> POBAIL | E38: 797 | F38: 1050001118490 | G38: CANEWDON SOLAR FARM | H38: 4.113 | I38: 5.06 | J38: 3.81 | K38: 3.81 | L38: 0 | M38: 506.26 | N38: 0.05 | O38: 0.05
A39: RANDCS | B39: 796 | C39: 1050001041962 | D39: =A39 -> RANDCS | E39: 797 | F39: 1050001041935 | G39: ROSE AND CROWN SOLAR FARM | H39: 1.098 | I39: 3.34 | J39: 3.01 | K39: 3.01 | M39: 1280.59 | N39: 0.05 | O39: 0.05
A40: RMSYSF | B40: 796 | C40: 1050001036651 | D40: =A40 -> RMSYSF | E40: 797 | F40: 1050001036660 | G40: RAMSEY SOLAR LIMITED | H40: 0.463 | I40: 185.09 | J40: 1.9 | K40: =J40 -> 1.9 | L40: 0 | M40: 2290.53 | N40: 0.05 | O40: 0.05
A41: ROOKRY | B41: 796 | C41: 1050001028465 | D41: =A41 -> ROOKRY | E41: 797 | F41: 1050001028474 | G41: ROOKERY SOLAR LIMITED | H41: 2.545 | I41: 11.24 | J41: 1.47 | K41: =J41 -> 1.47 | L41: 0 | M41: 244.41 | N41: 0.05 | O41: 0.05
A42: SCMOOR | B42: 796 | C42: 1050001073468 | D42: =A42 -> SCMOOR | E42: 797 | F42: 1050001073500 | G42: SCOTTOW MOOR SOLAR LIMITED | H42: 5.404 | I42: 55.12 | J42: 2.19 | K42: =J42 -> 2.19 | L42: 0 | M42: 2756.18 | N42: 0.05 | O42: 0.05
A43: SNTBRE | B43: 796 | C43: 1050001084200 | D43: =A43 -> SNTBRE | E43: 797 | F43: 1050001084229 | G43: BWSC EAST ANGLIA LIMITED | H43: 1.173 | I43: 1130.79 | J43: 1.82 | K43: =J43 -> 1.82 | L43: -1.173 | M43: 12721.43 | N43: 0.05 | O43: 0.05
A44: STNPTS | B44: 796 | C44: 1050001232428 | D44: =A44 -> STNPTS | E44: 797 | F44: 1050001232437 | G44: BELECTRIC SOLAR LTD | H44: 2.91 | I44: 6.58 | J44: 1.47 | K44: 1.47 | M44: 658.49 | N44: 0.05 | O44: 0.05
A45: SWNLND | B45: 796 | C45: 1050001290011 | D45: SWNLND | E45: 797 | F45: 1050001290020 | G45: SWANLAND ROAD SOLAR LTD | H45: 0 | I45: 66.12 | J45: 2.22 | K45: 2.22 | L45: 0 | M45: 541.11 | N45: 0.05 | O45: 0.05
A46: TILGRN | B46: 798 | C46: 1050001109352 | D46: =A46 -> TILGRN | E46: 799 | F46: 1050001109361 | G46: TILBURY GREEN POWER | H46: 0.278 | I46: 2908 | J46: 1.14 | K46: 1.14 | L46: -0.267 | M46: 14216.89 | N46: 0.05 | O46: 0.05
A47: TOGGAM | B47: 796 | C47: 1050001059393 | D47: =A47 -> TOGGAM | E47: 797 | F47: 1050001059384 | G47: GREENHEATH ENERGY LIMITED | H47: 11.698 | I47: 40.08 | J47: 2.77 | K47: =J47 -> 2.77 | L47: 0 | M47: 3823.81 | N47: 0.05 | O47: 0.05
A48: TRNCLE | B48: 796 | C48: 1050001078642 | D48: =A48 -> TRNCLE | E48: 797 | F48: 1050001078651 | G48: TURNCOLE WIND FARM LIMITED | H48: 2.371 | I48: 95.33 | J48: 1.09 | K48: 1.09 | L48: 0 | M48: 8859.11 | N48: 0.05 | O48: 0.05
A49: UKPRST | B49: 796 | C49: 1050001052193 | D49: =A49 -> UKPRST | E49: 797 | F49: 1050001052184 | G49: UK POWER RESERVE EASTMAN WAY | H49: 0.525 | I49: 3.16 | J49: 1.54 | K49: =J49 -> 1.54 | L49: -0.624 | M49: 252.48 | N49: 0.05 | O49: 0.05
A51: =Overview!B4& " - Effective from "&Overview!D4&" - "&Overview!F4&" new designated EHV line loss factors" -> Eastern Power Networks - Effective from 01/04/2017 - new designated EHV line loss factors
A52: Import Unique Identifier | B52: LLFC | C52: Import MPANs/MSIDs | D52: Export Unique Identifier | E52: LLFC | F52: Export MPANs/MSIDs | G52: Name | H52: Import LLF period 1 | I52: Import LLF period 2 | J52: Import LLF period 3 | K52: Import LLF period 4 | L52: Import LLF period 5 | M52: Export LLF period 1 | N52: Export LLF period 2 | O52: Export LLF period 3 | P52: Export LLF period 4 | Q52: Export LLF period 5
A53: ALCORG | B53: 796 | C53: 1050001015545 | D53: ALCORG | E53: 797 | F53: 1050000998050 | G53: ALCOR LSPV LTD | H53: 1.017 | I53: 1.014 | J53: 1.016 | K53: 1.013 | L53: 1.014 | M53: 1.017 | N53: 1.014 | O53: 1.016 | P53: 1.013 | Q53: 1.014
A54: ARDLGH | B54: 796 | C54: 1050001061597 | D54: ARDLGH | E54: 797 | F54: 1050001061602 | G54: SUNSAVE 28 (ARDLEIGH) LIMITED | H54: 1.017 | I54: 1.014 | J54: 1.016 | K54: 1.013 | L54: 1.014 | M54: 1.017 | N54: 1.014 | O54: 1.016 | P54: 1.013 | Q54: 1.014
A55: BERDHF | B55: 798 | C55: 1050001382522 | D55: BERDHF | E55: 799 | F55: 1050001382531 | G55: STATERA ENERGY LIMITED | H55: 1.004 | I55: 1.003 | J55: 1.003 | K55: 1.002 | L55: 1.003 | M55: 1.004 | N55: 1.003 | O55: 1.003 | P55: 1.002 | Q55: 1.003
A56: BLCAMB | B56: 796 | C56: 1050001036615 | D56: BLCAMB | E56: 797 | F56: 1050001036624 | G56: BURY GREEN FARM SOLAR LIMITED | H56: 1.017 | I56: 1.014 | J56: 1.016 | K56: 1.013 | L56: 1.014 | M56: 1.017 | N56: 1.014 | O56: 1.016 | P56: 1.013 | Q56: 1.014
A57: BLDOCK | B57: MSID 7308 | C57: 1097000000183 | D57: BLDOCK | E57: MSID 7309 | F57: 1097000000192 | G57: GREEN FROG POWER LTD | H57: 1.017 | I57: 1.014 | J57: 1.016 | K57: 1.013 | L57: 1.014 | M57: 1.017 | N57: 1.014 | O57: 1.016 | P57: 1.013 | Q57: 1.014
A58: BNNSHL | B58: 796 | C58: 1050001021414 | D58: BNNSHL | E58: 797 | F58: 1050001021423 | G58: BUNNS HILL SOLAR LIMITED | H58: 1.017 | I58: 1.014 | J58: 1.016 | K58: 1.013 | L58: 1.014 | M58: 1.017 | N58: 1.014 | O58: 1.016 | P58: 1.013 | Q58: 1.014
A59: CLAYBT | B59: 796 | C59: 1050001382364 | D59: CLAYBT | E59: 797 | F59: 1050001382373 | G59: ANESCO LIMITED | H59: 1.017 | I59: 1.014 | J59: 1.016 | K59: 1.013 | L59: 1.014 | M59: 1.017 | N59: 1.014 | O59: 1.016 | P59: 1.013 | Q59: 1.014
A60: CLAYPV | B60: 796 | C60: 1050001382337 | D60: CLAYPV | E60: 797 | F60: 1050001382355 | G60: ANESCO LIMITED | H60: 1.017 | I60: 1.014 | J60: 1.016 | K60: 1.013 | L60: 1.014 | M60: 1.017 | N60: 1.014 | O60: 1.016 | P60: 1.013 | Q60: 1.014
A61: CLDECT | B61: 796 | C61: 1050000714173 | D61: CLDECT | E61: 797 | F61: 1050000714182 | G61: AMP GM005 | H61: 1.017 | I61: 1.014 | J61: 1.016 | K61: 1.013 | L61: 1.014 | M61: 1.017 | N61: 1.014 | O61: 1.016 | P61: 1.013 | Q61: 1.014
A62: CLRDWN | B62: 796 | C62: 1050001495174 | D62: CLRDWN | E62: 797 | F62: 1050001495183 | G62: BESS CLAREDWON LTD | H62: 1.017 | I62: 1.014 | J62: 1.016 | K62: 1.013 | L62: 1.014 | M62: 1.017 | N62: 1.014 | O62: 1.016 | P62: 1.013 | Q62: 1.014
A63: CRANHM | B63: 796 | C63: 1050001191792 | D63: CRANHM | E63: 797 | F63: 1050001191808 | G63: WEL SOLAR PARK 12 LTD | H63: 1.017 | I63: 1.014 | J63: 1.016 | K63: 1.013 | L63: 1.014 | M63: 1.017 | N63: 1.014 | O63: 1.016 | P63: 1.013 | Q63: 1.014
A64: CRSSNG | B64: 796 | C64: 1050001047087 | D64: CRSSNG | E64: 797 | F64: 1050001047078 | G64: CRESSING SOLAR FARM LIMITED | H64: 1.017 | I64: 1.014 | J64: 1.016 | K64: 1.013 | L64: 1.014 | M64: 1.017 | N64: 1.014 | O64: 1.016 | P64: 1.013 | Q64: 1.014
A65: DRAYTN | B65: 796 | C65: 1050001047272 | D65: DRAYTN | E65: 797 | F65: 1050001047263 | G65: HAYMAKER (SIXTEEN) LTD | H65: 1.017 | I65: 1.014 | J65: 1.016 | K65: 1.013 | L65: 1.014 | M65: 1.017 | N65: 1.014 | O65: 1.016 | P65: 1.013 | Q65: 1.014
A66: ERNUNN | B66: 798 | C66: 1050001440510 | D66: ERNUNN | E66: 799 | F66: 1050001440529 | G66: PLUTUS POWERGEN | H66: 1.004 | I66: 1.003 | J66: 1.003 | K66: 1.002 | L66: 1.003 | M66: 1.004 | N66: 1.003 | O66: 1.003 | P66: 1.002 | Q66: 1.003
A67: GREYSH | B67: 796 | C67: 1050001391466 | D67: GREYSH | E67: 797 | F67: 1050001391475 | G67: PUSH ENERGY LTD | H67: 1.017 | I67: 1.014 | J67: 1.016 | K67: 1.013 | L67: 1.014 | M67: 1.017 | N67: 1.014 | O67: 1.016 | P67: 1.013 | Q67: 1.014
A68: HDATTP | B68: 796 | C68: 1050001197873 | D68: HDATTP | E68: 797 | F68: 1050001197864 | G68: HODDESDON ADVANCED THERMAL TREATMENT WKS | H68: 1.017 | I68: 1.014 | J68: 1.016 | K68: 1.013 | L68: 1.014 | M68: 1.017 | N68: 1.014 | O68: 1.016 | P68: 1.013 | Q68: 1.014
A69: HHFARM | B69: 796 | C69: 1050001231451 | D69: HHFARM | E69: 797 | F69: 1050001231460 | G69: LIGHTSOURCE SPV 9 LIMITED | H69: 1.017 | I69: 1.014 | J69: 1.016 | K69: 1.013 | L69: 1.014 | M69: 1.017 | N69: 1.014 | O69: 1.016 | P69: 1.013 | Q69: 1.014
A70: HONYSM | B70: 796 | C70: 1050001036670 | D70: HONYSM | E70: 797 | F70: 1050001036689 | G70: HONEYSOME ROAD SOLAR LIMITED | H70: 1.017 | I70: 1.014 | J70: 1.016 | K70: 1.013 | L70: 1.014 | M70: 1.017 | N70: 1.014 | O70: 1.016 | P70: 1.013 | Q70: 1.014
A71: HRLWDC | B71: 771 | C71: 1050001003372 1050001003381 1050001003390 | G71: HARLOW PROPERTIES LIMITED (KAO DATA CAMPUS) | H71: 1.052 | I71: 1.039 | J71: 1.046 | K71: 1.035 | L71: 1.04
A72: HRMTGE | B72: 796 | C72: 1050001129980 | D72: HRMTGE | E72: 797 | F72: 1050001129999 | G72: HERMITAGE SOLAR PARK LTD | H72: 1.017 | I72: 1.014 | J72: 1.016 | K72: 1.013 | L72: 1.014 | M72: 1.017 | N72: 1.014 | O72: 1.016 | P72: 1.013 | Q72: 1.014
A73: HRSFEN | B73: 796 | C73: 1050001041642 | D73: HRSFEN | E73: 797 | F73: 1050001041651 | G73: PRETORIA ENERGY COMPANY (MEPAL) LIMITED | H73: 1.017 | I73: 1.014 | J73: 1.016 | K73: 1.013 | L73: 1.014 | M73: 1.017 | N73: 1.014 | O73: 1.016 | P73: 1.013 | Q73: 1.014
A74: LBZSNS | B74: 771 | C74: 1050000687486 | D74: LBZSNS | E74: 792 | F74: 1050000687495 | G74: UK POWER NETWORKS OPERATIONS LTD | H74: 1.052 | I74: 1.039 | J74: 1.046 | K74: 1.035 | L74: 1.04 | M74: 1.052 | N74: 1.039 | O74: 1.046 | P74: 1.035 | Q74: 1.04
A75: LEICSQ | B75: 798 | C75: 1050001008681 | D75: LEICSQ | E75: 799 | F75: 1050001008690 | G75: SOUTH CREAKE SOLAR COMPANY LIMITED | H75: 1.004 | I75: 1.003 | J75: 1.003 | K75: 1.002 | L75: 1.003 | M75: 1.004 | N75: 1.003 | O75: 1.003 | P75: 1.002 | Q75: 1.003
A76: LWRNCE | B76: 796 | C76: 1050001008645 | D76: LWRNCE | E76: 797 | F76: 1050001008636 | G76: LIGHTSOURCE SPV180 LTD | H76: 1.017 | I76: 1.014 | J76: 1.016 | K76: 1.013 | L76: 1.014 | M76: 1.017 | N76: 1.014 | O76: 1.016 | P76: 1.013 | Q76: 1.014
A77: LYONSH | B77: 796 | C77: 1050001205345 | D77: LYONSH | E77: 797 | F77: 1050001205354 | G77: PUSH ENERGY (KENTISHES) LIMITED | H77: 1.017 | I77: 1.014 | J77: 1.016 | K77: 1.013 | L77: 1.014 | M77: 1.017 | N77: 1.014 | O77: 1.016 | P77: 1.013 | Q77: 1.014
A78: MILLDR | B78: 796 | C78: 1050001197855 | D78: MILLDR | E78: 797 | F78: 1050001197846 | G78: CAMBRIDGESHIRE COUNTY COUNCIL | H78: 1.017 | I78: 1.014 | J78: 1.016 | K78: 1.013 | L78: 1.014 | M78: 1.017 | N78: 1.014 | O78: 1.016 | P78: 1.013 | Q78: 1.014
A79: MILLFM | B79: 796 | C79: 1050001261465 | D79: MILLFM | E79: 797 | F79: 1050001261429 | G79: PUSH ENERGY (MILL FARM) LIMITED | H79: 1.017 | I79: 1.014 | J79: 1.016 | K79: 1.013 | L79: 1.014 | M79: 1.017 | N79: 1.014 | O79: 1.016 | P79: 1.013 | Q79: 1.014
A80: MLLFLD | B80: 796 | C80: 1050001060050 | D80: MLLFLD | E80: 797 | F80: 1050001060060 | G80: MILLFIELD SOLAR FARM | H80: 1.017 | I80: 1.014 | J80: 1.016 | K80: 1.013 | L80: 1.014 | M80: 1.017 | N80: 1.014 | O80: 1.016 | P80: 1.013 | Q80: 1.014
A81: MOWLEM | B81: 796 | C81: 1050001054233 | D81: MOWLEM | E81: 797 | F81: 1050001054242 | G81: MOWLEM TRADING ESTATE | H81: 1.017 | I81: 1.014 | J81: 1.016 | K81: 1.013 | L81: 1.014 | M81: 1.017 | N81: 1.014 | O81: 1.016 | P81: 1.013 | Q81: 1.014
A82: NEWTON | B82: 796 | C82: 1050001042238 | D82: NEWTON | E82: 797 | F82: 1050001042229 | G82: WEL SOLAR PARK 6 LIMITED | H82: 1.017 | I82: 1.014 | J82: 1.016 | K82: 1.013 | L82: 1.014 | M82: 1.017 | N82: 1.014 | O82: 1.016 | P82: 1.013 | Q82: 1.014
A83: OULTON | B83: 796 | C83: 1050001028544 | D83: OULTON | E83: 797 | F83: 1050001028553 | G83: OULTON SOLAR LIMITED | H83: 1.017 | I83: 1.014 | J83: 1.016 | K83: 1.013 | L83: 1.014 | M83: 1.017 | N83: 1.014 | O83: 1.016 | P83: 1.013 | Q83: 1.014
... A96: UKPRST | B96: 796 | C96: 1050001052193 | D96: UKPRST | E96: 797 | F96: 1050001052184 | G96: UK POWER RESERVE EASTMAN WAY | H96: 1.017 | I96: 1.014 | J96: 1.016 | K96: 1.013 | L96: 1.014 | M96: 1.017 | N96: 1.014 | O96: 1.016 | P96: 1.013 | Q96: 1.014

Sheet Nodal prices
A1: Back to Overview
A2: =Overview!B4& " - Effective from "&Overview!D4&" - "&Overview!E4&" Nodal charges" -> Eastern Power Networks - Effective from 01/04/2017 - Final Nodal charges
A3: Node ID | B3: Geographical name | C3: Local charge 1 £/kVA | D3: Remote charge 1 £/kVA
A4: 1005 | B4: BERECHURCH 11 BB | C4: 0.071599148 | D4: 6.433992
A5: 1040 | B5: LEXDEN 11 BB | C5: 1.7304464 | D5: 9.0928291
A6: 1055 | B6: MARKS TEY 11 BB | C6: 0.66217692 | D6: 9.4618579
A7: 1091 | B7: CUSTOMER | C7: 1.1788295 | D7: 9.2796389
A8: 1120 | B8: PELDON 11 BB | C8: 4.1966792 | D8: 16.808294
A9: 1125 | B9: CUSTOMER | C9: 27.717084 | D9: 10.6003
A10: 1130 | B10: CUSTOMER | C10: 28.299578 | D10: 10.588648
A11: 1135 | B11: SHRUB END 11 BB | C11: 0.070205334 | D11: 8.3613155
A12: 1150 | B12: TIPTREE 11 BB | C12: 0.440467 | D12: 9.1159581
A13: 1160 | B13: CUSTOMER | C13: 1.8397152 | D13: 9.0768548
A14: 1185 | B14: AUSTIN CANONS 11KV BB | C14: 1.3510564 | D14: 3.4458215
A15: 1215 | B15: HARROWDEN 11 BB | C15: 0.021850819 | D15: 3.6479321
... A735: 15655 | B735: CUSTOMER | C735: 0.75375904 | D735: 0.24353804

Sheet SSC TPR unit rate lookup
A1: Back to Overview
H2: Dummy SSCs for Measurement Class F & G Half Hourly data aggregation
H4: GSP Group ID | I4: GSP Group Name | J4: Dummy SSC | K4: "Red" period TPR | L4: "Amber" period TPR | M4: "Green" Period TPR
H5: _A | I5: Eastern | J5: 9101 | K5: 91011 | L5: 91012 | M5: 91013
H6: _B | I6: East Midlands | J6: 9111 | K6: 91111 | L6: 91112 | M6: 91113
H7: _C | I7: London | J7: 9121 | K7: 91211 | L7: 91212 | M7: 91213
H8: _D | I8: Merseyside and North Wales | J8: 9131 | K8: 91311 | L8: 91312 | M8: 91313
H9: _E | I9: Midlands | J9: 9141 | K9: 91411 | L9: 91412 | M9: 91413
H10: _F | I10: Northern | J10: 9151 | K10: 91511 | L10: 91512 | M10: 91513
H11: _G | I11: North Western | J11: 9161 | K11: 91611 | L11: 91612 | M11: 91613
H12: _H | I12: Southern | J12: 9201 | K12: 92011 | L12: 92012 | M12: 92013
H13: _J | I13: South Eastern | J13: 9191 | K13: 91911 | L13: 91912 | M13: 91913
H14: _K | I14: South Wales | J14: 9211 | K14: 92111 | L14: 92112 | M14: 92113
H15: _L | I15: South Western | J15: 9221 | K15: 92211 | L15: 92212 | M15: 92213
H16: _M | I16: Yorkshire | J16: 9231 | K16: 92311 | L16: 92312 | M16: 92313
... H18: _P | I18: North Scotland | J18: 9171 | K18: 91711 | L18: 91712 | M18: 91713
A28: Standard Settlement Configuration Id | B28: Time Pattern Regime Id | C28: Standard Settlement Configuration Desc | D28: Common Decode | G28: Change implemented | H28: Date | I28: Comments
A29: 3 | B29: 166 | C29: 10-hour OP | D29: O | H29: 40057 | I29: First published spreadsheet
A30: 4 | B30: 168 | C30: 10-hour OP | D30: O | G30: SSC 0330 charge rates corrected | H30: 40275 | I30: Previous Off-peak rate corrected to charge 2
A31: 5 | B31: 100 | C31: 10-hour OP + w/e | D31: O | G31: SSC 0250 charge rate corrected | H31: 40347 | I31: Previous rate 1 corrected to Off Peak O
A32: 6 | B32: 257 | C32: 10.5-hour OP | D32: O | G32: SSC 0134 charge rate corrected | H32: 41166 | I32: TPR 00101 corrected from Off Peak O to Rate 1
A33: 7 | B33: 158 | C33: 10.5-hour OP | D33: O | G33: New SSCs added | H33: 41178 | I33: New SSCs from 0953 added.
A34: 8 | B34: 159 | C34: 10.5-hour OP | D34: O | G34: SSC 0394 charge rate corrected | H34: 41758 | I34: TPR 01177 corrected to rate 2
A35: 9 | B35: 1111 | C35: 10.5-hour OP | D35: O | G35: Table reviewed and updated | H35: 41758 | I35: New SSCs from 0949 to 0952, 0975 & 0976 and 0982 & 0983 added.
A36: 10 | B36: 1104 | C36: 10.5-hour OP | D36: O | G36: Table reviewed and updated | H36: 41944 | I36: New SSCs from 0984 and 0985 added.
A37: 11 | B37: 1112 | C37: 10.5-hour OP | D37: O | G37: SSC 0313 charge code corrected | H37: 42081 | I37: TPR 01006 corrected to code O
A38: 12 | B38: 1116 | C38: 10.5-hour OP | D38: O | G38: SSC 0320 charge code corrected | H38: 42081 | I38: TPR 00072 corrected to code 2
A39: 13 | B39: 139 | C39: 11 Hour OP | D39: EMEB or MIDE only | G39: SSC 0781 charge code corrected | H39: 42081 | I39: TPR 00327 corrected to code O
A40: 15 | B40: 152 | C40: 11 Hour OP | D40: EMEB or MIDE only | G40: SSC 0935 charge code corrected | H40: 42081 | I40: TPR 00375 corrected to code 1 or Unsupported (SWAE and SWEB)
A41: 16 | B41: 113 | C41: 11.5-hour OP | D41: Unsupported (SWEB) | G41: SSC 0953 charge code corrected | H41: 42081 | I41: TPR 00424 corrected to code 1 or Unsupported (SWAE and SWEB)
... A74: 50 | B74: 14 | C74: 12-hour OP + w/e & Summer | D74: O | G74: SSC 0942 charge code corrected | H74: 42166 | I74: TPR 00400 corrected to code 1
A75: 51 | B75: 112 | C75: 12-hour night | D75: 1 | G75: SSC 0943 charge code corrected | H75: 42166 | I75: TPR 00404 corrected to code 1
A76: 51 | B76: 120 | C76: 12-hour night | D76: 2 | G76: SSC 0944 charge code corrected | H76: 42166 | I76: TPR 00406 corrected to code 1
A77: 52 | B77: 114 | C77: 12-hour OP | D77: EMEB or MIDE only | G77: SSC 0945 charge code corrected | H77: 42166 | I77: TPR 00408 corrected to code 1
A78: 53 | B78: 115 | C78: 12-hour OP | D78: EMEB or MIDE only | G78: SSC 0946 charge code corrected | H78: 42166 | I78: TPR 00410 corrected to code 1
A79: 55 | B79: 117 | C79: 12-hour OP | D79: EMEB or MIDE only | G79: SSC 0954 charge code corrected | H79: 42166 | I79: TPR 00426 corrected to code 1
A80: 56 | B80: 118 | C80: 12-hour OP | D80: EMEB or MIDE only | G80: SSC 0967 charge code corrected | H80: 42166 | I80: TPR 00442 corrected to code 1
A81: 57 | B81: 119 | C81: 12-hour OP | D81: O | G81: SSC 0970 charge code corrected | H81: 42166 | I81: TPR 00447 corrected to code 2
A82: 58 | B82: 21 | C82: Key Meter pseudo 2-rate | D82: 1 | G82: SSC 0970 charge code corrected | H82: 42166 | I82: TPR 00448 corrected to code 1
A83: 58 | B83: 175 | C83: Key Meter pseudo 2-rate | D83: 1 | G83: SSC 0971 charge code corrected | H83: 42166 | I83: TPR 00493 corrected to code 1
A84: 59 | B84: 121 | C84: 12-hour OP | D84: EMEB or MIDE only
A85: 60 | B85: 122 | C85: 12-hour OP | D85: O
A86: 62 | B86: 1119 | C86: 8-hour OP (see also SSC 427) | D86: 2 or Unsupported (SWEB)
A87: 63 | B87: 172 | C87: 9-hour OP | D87: EMEB or MIDE only
A88: 64 | B88: 1105 | C88: 12-hour OP | D88: O
A89: 65 | B89: 10 | C89: 12-hour OP + Summer | D89: O
A90: 66 | B90: 1106 | C90: 12-hour OP + Summer | D90: O
A91: 67 | B91: 102 | C91: 12.5-hour OP | D91: Unsupported (SWEB)
A92: 71 | B92: 109 | C92: 12.5-hour OP | D92: O
A93: 72 | B93: 111 | C93: 12.5-hour OP | D93: O
A94: 73 | B94: 156 | C94: 12.5-hour OP | D94: Unsupported (SWEB)
A95: 74 | B95: 17 | C95: 12.5-hour OP + Summer | D95: O
... A99: 78 | B99: 13 | C99: 12.5-hour OP + w/e & Summer | D99: O
A100: 79 | B100: 97 | C100: 14-hour E7 | D100: 2
A101: 79 | B101: 164 | C101: 14-hour E7 | D101: 1
A102: 80 | B102: 96 | C102: 14-hour Off Peak | D102: O
A103: 81 | B103: 60 | C103: 14-hour OP + Sun | D103: O
A104: 82 | B104: 83 | C104: 14.5-hour OP | D104: O
A105: 83 | B105: 84 | C105: 14.5-hour OP | D105: O
A106: 84 | B106: 85 | C106: 14.5-hour OP | D106: O
A107: 85 | B107: 86 | C107: 14.5-hour OP | D107: O
A108: 86 | B108: 1107 | C108: 14.5-hour OP | D108: O
A109: 87 | B109: 1109 | C109: 14.5-hour OP | D109: O
A110: 88 | B110: 1113 | C110: 14.5-hour OP | D110: O
A111: 91 | B111: 3 | C111: 14.5-hour OP + Summer | D111: O
A112: 92 | B112: 4 | C112: 14.5-hour OP + Summer | D112: O
A113: 93 | B113: 30 | C113: split 7-hour E7 | D113: 1
A114: 93 | B114: 214 | C114: split 7-hour E7 | D114: 2
A115: 94 | B115: 1108 | C115: 14.5-hour OP + Summer | D115: O
A116: 95 | B116: 1110 | C116: 14.5-hour OP + Summer | D116: O
A117: 96 | B117: 1114 | C117: 14.5-hour OP + Summer | D117: O
A118: 97 | B118: 54 | C118: 14.5-hour OP + w/e | D118: O
A119: 98 | B119: 12 | C119: 14.5-hour OP + w/e & Summer | D119: O
A120: 99 | B120: 75 | C120: 15-hour OP | D120: EMEB or MIDE only
A121: 100 | B121: 76 | C121: 15-hour OP | D121: EMEB or MIDE only
A122: 101 | B122: 7 | C122: 15-hour OP + w/e & Summer | D122: O
A123: 102 | B123: 8 | C123: 15-hour OP + w/e & Summer | D123: O
A124: 103 | B124: 9 | C124: 15-hour OP + w/e & Summer | D124: O
A125: 104 | B125: 61 | C125: 15.5-hour OP | D125: Unsupported (SWEB)
A126: 105 | B126: 65 | C126: 15.5-hour OP | D126: O
... A140: 120 | B140: 11 | C140: 9-hour OP | D140: O
A141: 121 | B141: 26 | C141: 2-rate terms | D141: 2
A142: 121 | B142: 224 | C142: 2-rate terms | D142: 1
A143: 122 | B143: 201 | C143: 2-rate SToD | D143: 1
A144: 122 | B144: 245 | C144: 2-rate SToD | D144: 2
A145: 123 | B145: 1307 | C145: 2-rate variable SToD | D145: 1
A146: 124 | B146: 1319 | C146: 2-rate variable SToD | D146: 1
A147: 125 | B147: 1315 | C147: 2-rate variable SToD | D147: 1
A148: 126 | B148: 1193 | C148: 7-hour E7 | D148: 1
A149: 126 | B149: 1194 | C149: 7-hour E7 | D149: 2
A150: 127 | B150: 80 | C150: 3-rate SToD | D150: Unsupported (SWEB)
A151: 127 | B151: 148 | C151: 3-rate SToD | D151: 1
A152: 127 | B152: 221 | C152: 3-rate SToD | D152: 2 or Unsupported (SWEB)
A153: 128 | B153: 1120 | C153: Dom/Non-dom Seasonal (link SSC 0342) | D153: 1
A154: 128 | B154: 1121 | C154: Dom/Non-dom Seasonal (link SSC 0342) | D154: 1
A155: 128 | B155: 1122 | C155: Dom/Non-dom Seasonal (link SSC 0342) | D155: 2
A156: 129 | B156: 169 | C156: 3-rate SToD | D156: 1
A157: 129 | B157: 202 | C157: 3-rate SToD | D157: 1
A158: 129 | B158: 222 | C158: 3-rate SToD | D158: 2
A159: 130 | B159: 1308 | C159: 3-rate variable | D159: 1
...

Sheet Charge Calculator
B1: Back to Overview
B2: =Overview!B4& " - Effective from "&Overview!D4&" - "&Overview!E4 -> Eastern Power Networks - Effective from 01/04/2017 - Final
B4: LV and HV tariff calculator | L4: EHV site calculator
B5: Step 1, Choose your tariff using the drop down list in cell B10 | L5: Step 1, Choose your tariff using the drop down list in cell L10
B6: Step 2, After selecting a tariff in step 1, Cells C12-I12 will generate headings, please enter your consumption in cells C13:I13 underneath each heading generated (if no heading leave cell blank) | L6: Step 2, After selecting a tariff in step 1, Cells M12-T12 will generate headings, please enter your consumption in cells M13:T13 underneath each heading generated (if no heading leave cell blank)
B7: Step 3, Enter a forecast of consumption if required in cells C14:I14 | L7: Step 3, Enter a forecast of consumption if required in cells M14:T14
B9: Tariff details Choose tariff name from drop down box below | C9: ='Annex 1 LV and HV charges'!D13 -> Unit charge 1 (NHH) or red/black charge (HH) p/kWh | D9: ='Annex 1 LV and HV charges'!E13 -> Unit charge 2 (NHH) or amber/yellow charge (HH) p/kWh | E9: ='Annex 1 LV and HV charges'!F13 -> Green charge(HH) p/kWh | F9: ='Annex 1 LV and HV charges'!G13 -> Fixed charge p/MPAN/day | G9: ='Annex 1 LV and HV charges'!H13 -> Capacity charge p/kVA/day | H9: ='Annex 1 LV and HV charges'!I13 -> Reactive power charge p/kVArh | I9: ='Annex 1 LV and HV charges'!J13 -> Exceeded capacity charge p/kVA/day | L9: Site details Choose the site name from the drop down box below | M9: ='Annex 2 EHV charges'!H10 -> Import Super Red unit charge (p/kWh) | N9: ='Annex 2 EHV charges'!I10 -> Import fixed charge (p/day) | O9: ='Annex 2 EHV charges'!J10 -> Import capacity charge (p/kVA/day) | P9: ='Annex 2 EHV charges'!K10 -> Import exceeded capacity charge (p/kVA/day) | Q9: ='Annex 2 EHV charges'!L10 -> Export Super Red unit charge (p/kWh) | R9: ='Annex 2 EHV charges'!M10 -> Export fixed charge (p/day) | S9: ='Annex 2 EHV charges'!N10 -> Export capacity charge (p/kVA/day) | T9: ='Annex 2 EHV charges'!O10 -> Export exceeded capacity charge (p/kVA/day)
C10: =IFERROR(VLOOKUP($B$10,'Annex 1 LV and HV charges'!$A:$K,4,FALSE),"") | D10: =IFERROR(VLOOKUP($B$10,'Annex 1 LV and HV charges'!$A:$K,5,FALSE),"") | E10: =IFERROR(VLOOKUP($B$10,'Annex 1 LV and HV charges'!$A:$K,6,FALSE),"") | F10: =IFERROR(VLOOKUP($B$10,'Annex 1 LV and HV charges'!$A:$K,7,FALSE),"") | G10: =IFERROR(VLOOKUP($B$10,'Annex 1 LV and HV charges'!$A:$K,8,FALSE),"") | H10: =IFERROR(VLOOKUP($B$10,'Annex 1 LV and HV charges'!$A:$K,9,FALSE),"") | I10: =IFERROR(VLOOKUP($B$10,'Annex 1 LV and HV charges'!$A:$K,10,FALSE),"") | M10: =IFERROR(VLOOKUP($L$10,'Annex 2 EHV charges'!$G:$O,2,FALSE),"") | N10: =IFERROR(VLOOKUP($L$10,'Annex 2 EHV charges'!$G:$O,3,FALSE),"") | O10: =IFERROR(VLOOKUP($L$10,'Annex 2 EHV charges'!$G:$O,4,FALSE),"") | P10: =IFERROR(VLOOKUP($L$10,'Annex 2 EHV charges'!$G:$O,5,FALSE),"") | Q10: =IFERROR(VLOOKUP($L$10,'Annex 2 EHV charges'!$G:$O,6,FALSE),"") | R10: =IFERROR(VLOOKUP($L$10,'Annex 2 EHV charges'!$G:$O,7,FALSE),"") | S10: =IFERROR(VLOOKUP($L$10,'Annex 2 EHV charges'!$G:$O,8,FALSE),"") | T10: =IFERROR(VLOOKUP($L$10,'Annex 2 EHV charges'!$G:$O,9,FALSE),"")
B12: Tariff components | C12: Unit 1 kWh (red/black/day) | D12: Unit 2 kWh (amber/yellow /night) | E12: Unit 3 kWh (green) | F12: Number of days in consumption period i.e. 365 if one year | G12: Maximum import or export capacity kVA | H12: Excess reactive units kVArh | I12: Average daily exceded capacity kVA | L12: Tariff components | M12: Import super red kWh | N12: Number of days in consumption period i.e. 365 if one year | O12: Maximum import capacity kVA | P12: Average daily exceeded capacity kVA | Q12: Export Super Red kWh | R12: Number of days in consumption period i.e. 365 if one year | S12: Maximum export capacity kVA | T12: Average daily exceeded capacity kVA
B13: Enter current consumption details | L13: Enter current consumption details | R13: =N13 -> 0
B14: Enter forecast consumption details (if different) | C14: =C13 -> 0 | D14: =D13 -> 0 | E14: =E13 -> 0 | F14: =F13 -> 0 | G14: =G13 -> 0 | H14: =H13 -> 0 | I14: =I13 -> 0 | L14: Enter forecast consumption details (if different) | M14: =M13 -> 0 | N14: =N13 -> 0 | O14: =O13 -> 0 | P14: =P13 -> 0 | Q14: =Q13 -> 0 | R14: =R13 -> 0 | S14: =S13 -> 0 | T14: =T13 -> 0
B16: Charge components | C16: Unit 1 £ | D16: Unit 2 £ | E16: Unit 3 £ | F16: Fixed charge £ | G16: Capacity charge £ | H16: Reactive power charge £ | I16: Exceeded capacity charge £ | L16: Charge components | M16: Import super red charge £ | N16: Import fixed charge £ | O16: Import capacity charge £ | P16: Import exceeded capacity charge £ | Q16: Export super red charge £ | R16: Export fixed charge £ | S16: Export capacity charge £ | T16: Export exceeded capacity charge £
B17: Current consumption period charges | C17: =IFERROR(C10*C13/100,"") | D17: =IFERROR(D10*D13/100,"") | E17: =IFERROR(E10*E13/100,"") | F17: =IFERROR(F10*F13/100,"") | G17: =IFERROR(G10*G13*F13/100,"") | H17: =IFERROR(H10*H13/100,"") | I17: =IFERROR(I10*I13*F13/100,"") | L17: Current consumption period charges | M17: =IFERROR(M10*M13/100,"") | N17: =IFERROR(N10*N13/100,"") | O17: =IFERROR(O10*O13*N13/100,"") | P17: =IFERROR(P10*P13*N13/100,"") | Q17: =IFERROR(Q10*Q13/100,"") | R17: =IFERROR(R10*R13/100,"") | S17: =IFERROR(S10*S13*R13/100,"") | T17: =IFERROR(T10*T13*R13/100,"")
B18: Forecast consumption period charges | C18: =IFERROR(C10*C14/100,"") | D18: =IFERROR(D10*D14/100,"") | E18: =IFERROR(E10*E14/100,"") | F18: =IFERROR(F10*F14/100,"") | G18: =IFERROR(G10*G14*F14/100,"") | H18: =IFERROR(H10*H14/100,"") | I18: =IFERROR(I10*I14*F14/100,"") | L18: Forecast consumption period charges | M18: =IFERROR(M10*M14/100,"") | N18: =IFERROR(N10*N14/100,"") | O18: =IFERROR(O10*O14*N14/100,"") | P18: =IFERROR(P10*P14*N14/100,"") | Q18: =IFERROR(Q10*Q14/100,"") | R18: =IFERROR(R10*R14/100,"") | S18: =IFERROR(S10*S14*R14/100,"") | T18: =IFERROR(T10*T14*R14/100,"")
C20: Total charge £ | M20: Import total charge £ | N20: Export total charge £
B21: Current consumption period charges | C21: =SUM(C17:I17) -> 0 | L21: Current consumption period charges | M21: =SUM(M17:P17) -> 0 | N21: =SUM(Q17:T17) -> 0
B22: Forecast consumption period charges | C22: =SUM(C18:I18) -> 0 | L22: Forecast consumption period charges | M22: =SUM(M18:P18) -> 0 | N22: =SUM(Q18:T18) -> 0
B24: These charges are estimates based on tariff selected and consumption values entered. | L24: These charges are estimates based on site selected and consumption values entered.
