Workbook
Name days_in_year: '[1]General inputs'!$H$25
Name OLE_LINK1: 'Annex 3 Preserved charges'!#REF!

Sheet Overview
A2: Company and Licence name, charging year, effective from, status
B3: Company and Licence name | C3: Year | D3: Effective From | E3: Status
A4: Company and Licence name, charging year, effective from, status | B4: SP Distribution | C4: 2022/23 | D4: 1 April 2022 | E4: Final
A6: List of data tables in this workbook
A7: Worksheet | B7: Information
A8: Annex 1 LV, HV and Unmetered Supplies charges | B8: Annex 1 contains the charges to LV and HV Designated Properties and Unmetered Supplies.
A9: Annex 2 EHV charges | B9: ="Annex 2 contains the charges to Designated EHV Properties and charges applied to LDNOs with Designated EHV Properties/end-users embedded in networks within the " &B4 &" Licence area." -> Annex 2 contains the charges to Designated EHV Properties and charges applied to LDNOs with Designated EHV Properties/end-users embedded in networks within the SP Distribution Licence area.
A10: Annex 3 Preserved charges | B10: Annex 3 contains details of any preserved and additional charges that are valid at this time.
A11: Annex 4 LDNO charges | B11: ="Annex 4 contains charges that are levied on the owner of an embedded network within the "&B4&" Licence area. "&"Electricity suppliers and consumers who have properties connected to an embedded network should contact the embedded network owner to determine their distribution charges."&" The charges listed in this table are not payable by domestic consumers, business consumers or electricity suppliers." -> Annex 4 contains charges that are levied on the owner of an embedded network within the SP Distribution Licence area. Electricity suppliers and consumers who have properties connected to an embedded network should contact the embedded network owner to determine their distribution charges. The charges listed in this table are not payable by domestic consumers, business consumers or electricity suppliers.
A12: Annex 5 LLFs | B12: Annex 5 has been intentionally left blank as this charging statement is published a complete year before the LLFs have been audited. The line loss factors that are approved by the BSC Panel for the applicable year and consequently published on the Elexon website will take precedence and be used in Settlement. This annex will be re-published with these values once they are available.
A13: Annex 6 Charges for New or Amended Designated EHV Properties | B13: ="Annex 6 contains the charges for new or amended Designated EHV Properties and charges applied to LDNOs with new or amended Designated EHV Properties/end-users embedded in networks within the " &B4 &" Licence area." -> Annex 6 contains the charges for new or amended Designated EHV Properties and charges applied to LDNOs with new or amended Designated EHV Properties/end-users embedded in networks within the SP Distribution Licence area.
A14: Annex 7 Fixed adders for Supplier of Last Resort and Eligible Bad Debt pass-through costs | B14: Annex 7 contains the fixed adders to recover Supplier of Last Resort and Eligible Bad Debt pass-through costs. The Excess Supplier of Last Resort fixed adder relates to an increase to previously published charges only.
A15: Nodal prices | B15: Contains the underlying [nodal/network group] costs used to calculate the current EDCM charges.
A16: Residual Charging Bandings | B16: Contains the four Residual charging band allocation for Customers
A17: Charge calculator | B17: Charge calculator is a tool to help you estimate your distribution charges using current consumption data and forecast consumption data.
A19: Notes to users of this spreadsheet
A21: Please use this spreadsheet with reference to the LC14 use of system charging statement.
A23: Notes to DNOs populating this spreadsheet
A25: DNOs must endeavour to maintain consistency in the structure of this spreadsheet. Any changes to the structure must be noted in the 'Notes to users of this spreadsheet'
A26: The drop down list on the charge calculator can be expanded by unprotecting the charge calculator sheet and selecting 'data', 'data validation...' and then expanding the 'source' data range. The sheet can then be protected.

Sheet Annex 1 LV, HV and UMS charges
A1: Back to Overview | B1: 'DNOs paste value cells A15:J47 from CDCM 3701 into cells A14:J46
A2: =Overview!B4& " - Effective from "&Overview!D4&" - "&Overview!E4&" LV and HV charges" -> SP Distribution - Effective from 1 April 2022 - Final LV and HV charges
A4: Time Bands for LV and HV Designated Properties | G4: Time Bands for Unmetered Properties
A5: Time periods | B5: Red Time Band | C5: Amber Time Band | E5: Green Time Band | I5: Black Time Band | J5: Yellow Time Band | K5: Green Time Band
A6: Monday to Friday (Including Bank Holidays) All Year | B6: 16.30 - 19.30 | C6: 08.00 - 16.30 19.30 - 22.30 | E6: 00.00 - 08.00 22.30 - 00.00 | G6: Monday to Friday (Including Bank Holidays) June to August Inclusive | J6: 08.00 - 22.30 | K6: 00.00 - 08.00 22.30 - 00.00
A7: Saturday and Sunday All Year | C7: 16.00 - 20.00 | E7: 00.00 - 16.00 20.00 - 00.00 | G7: Monday to Friday (Including Bank Holidays) November to February Inclusive | I7: 16.30 - 19.30 | J7: 08.00 - 16.30 19.30 - 22.30 | K7: 00.00 - 08.00 22.30 - 00.00
A8: Notes | B8: All the above times are in UK Clock time | G8: Monday to Friday (Including Bank Holidays) March, April, May and September, October | J8: 08.00 - 22.30 | K8: 00.00 - 08.00 22.30 - 00.00
G9: Saturday and Sunday All year | J9: 16.00 - 20.00 | K9: 00:00-16:00 20:00-00:00
G10: Notes | I10: All the above times are in UK Clock time
A13: Tariff name | B13: Open LLFCs | C13: PCs | D13: Red/black unit charge p/kWh | E13: Amber/yellow unit charge p/kWh | F13: Green unit charge p/kWh | G13: Fixed charge p/MPAN/day | H13: Capacity charge p/kVA/day | I13: Exceeded capacity charge p/kVA/day | J13: Reactive power charge p/kVArh | K13: Closed LLFCs
A14: Domestic Aggregated with Residual | B14: 100, 101, 110, 111, 114, 115, 118, 119, 120, 121, 160, 161, 162, 163, 180 | C14: 0, 1, 2 | D14: 8.501 | E14: 0.962 | F14: 0.019 | G14: 27.13
A15: Domestic Aggregated (Related MPAN) | B15: 112, 113, 116, 117, 132, 133, 136, 137, 164, 165, 166 | C15: 2 | D15: 8.501 | E15: 0.962 | F15: 0.019 | K15: 130, 134, 135
A16: Non-Domestic Aggregated No Residual | B16: D00,F00 | C16: 0, 3, 4, 5-8 | D16: 10.706 | E16: 1.212 | F16: 0.024 | G16: 6.37 | K16: 201, 204, 221, 260, 280, 200, 202, 203, 220, 222, 400, 401, 402
A17: Non-Domestic Aggregated Band 1 | B17: D01,F01 | C17: 0, 3, 4, 5-8 | D17: 10.706 | E17: 1.212 | F17: 0.024 | G17: 11.11 | K17: 201, 204, 221, 260, 280, 200, 202, 203, 220, 222, 400, 401, 402
A18: Non-Domestic Aggregated Band 2 | B18: D02,F02 | C18: 0, 3, 4, 5-8 | D18: 10.706 | E18: 1.212 | F18: 0.024 | G18: 32.32 | K18: 201, 204, 221, 260, 280, 200, 202, 203, 220, 222, 400, 401, 402
A19: Non-Domestic Aggregated Band 3 | B19: D03,F03 | C19: 0, 3, 4, 5-8 | D19: 10.706 | E19: 1.212 | F19: 0.024 | G19: 71.14 | K19: 201, 204, 221, 260, 280, 200, 202, 203, 220, 222, 400, 401, 402
A20: Non-Domestic Aggregated Band 4 | B20: D04,F04 | C20: 0, 3, 4, 5-8 | D20: 10.706 | E20: 1.212 | F20: 0.024 | G20: 209.3 | K20: 201, 204, 221, 260, 280, 200, 202, 203, 220, 222, 400, 401, 402
A21: Non-Domestic Aggregated (related MPAN) | B21: 225, 240, 241, 301 | C21: 4 | D21: 10.706 | E21: 1.212 | F21: 0.024 | K21: 223, 242, 243, 245, 246
A22: LV Site Specific No Residual | B22: G00, H00 | C22: 0 | D22: 6.926 | E22: 0.75 | F22: 0.014 | G22: 25.01 | H22: 2.65 | I22: 3.84 | J22: 0.213 | K22: 500, 502, 504
A23: LV Site Specific Band 1 | B23: G01, H01 | C23: 0 | D23: 6.926 | E23: 0.75 | F23: 0.014 | G23: 343.29 | H23: 2.65 | I23: 3.84 | J23: 0.213 | K23: 500, 502, 504
A24: LV Site Specific Band 2 | B24: G02, H02 | C24: 0 | D24: 6.926 | E24: 0.75 | F24: 0.014 | G24: 684.83 | H24: 2.65 | I24: 3.84 | J24: 0.213 | K24: 500, 502, 504
A25: LV Site Specific Band 3 | B25: G03, H03 | C25: 0 | D25: 6.926 | E25: 0.75 | F25: 0.014 | G25: 1126.71 | H25: 2.65 | I25: 3.84 | J25: 0.213 | K25: 500, 502, 504
A26: LV Site Specific Band 4 | B26: G04, H04 | C26: 0 | D26: 6.926 | E26: 0.75 | F26: 0.014 | G26: 2465.99 | H26: 2.65 | I26: 3.84 | J26: 0.213 | K26: 500, 502, 504
A27: LV Sub Site Specific No Residual | B27: K00, L00 | C27: 0 | D27: 4.073 | E27: 0.383 | F27: 0.005 | G27: 8.85 | H27: 4.8 | I27: 5.45 | J27: 0.112 | K27: 506, 507, 508
A28: LV Sub Site Specific Band 1 | B28: K01, L01 | C28: 0 | D28: 4.073 | E28: 0.383 | F28: 0.005 | G28: 327.13 | H28: 4.8 | I28: 5.45 | J28: 0.112 | K28: 506, 507, 508
A29: LV Sub Site Specific Band 2 | B29: K02, L02 | C29: 0 | D29: 4.073 | E29: 0.383 | F29: 0.005 | G29: 668.67 | H29: 4.8 | I29: 5.45 | J29: 0.112 | K29: 506, 507, 508
A30: LV Sub Site Specific Band 3 | B30: K03, L03 | C30: 0 | D30: 4.073 | E30: 0.383 | F30: 0.005 | G30: 1110.54 | H30: 4.8 | I30: 5.45 | J30: 0.112 | K30: 506, 507, 508
A31: LV Sub Site Specific Band 4 | B31: K04, L04 | C31: 0 | D31: 4.073 | E31: 0.383 | F31: 0.005 | G31: 2449.83 | H31: 4.8 | I31: 5.45 | J31: 0.112 | K31: 506, 507, 508
A32: HV Site Specific No Residual | B32: M00, N00 | C32: 0 | D32: 3.029 | E32: 0.262 | F32: 0.003 | G32: 133.52 | H32: 5.3 | I32: 6.49 | J32: 0.077 | K32: 501, 505, 503
A33: HV Site Specific Band 1 | B33: M01, N01 | C33: 0 | D33: 3.029 | E33: 0.262 | F33: 0.003 | G33: 1603.45 | H33: 5.3 | I33: 6.49 | J33: 0.077 | K33: 501, 505, 503
... A36: HV Site Specific Band 4 | B36: M04, N04 | C36: 0 | D36: 3.029 | E36: 0.262 | F36: 0.003 | G36: 31562.57 | H36: 5.3 | I36: 6.49 | J36: 0.077 | K36: 501, 505, 503
A37: Unmetered Supplies | B37: 900, 901, 902, 903, 910 | C37: 0, 1 or 8 | D37: 21.869 | E37: 2.649 | F37: 1.788 | K37: 904, 905, 906, 907, 908, 909
A38: LV Generation Aggregated | B38: 781, 782, 783, 784, 785 | C38: 0 | D38: -6.3 | E38: -0.713 | F38: -0.014
A39: LV Sub Generation Aggregated | B39: 602 | C39: 0 | D39: -5.55 | E39: -0.614 | F39: -0.012
A40: LV Generation Site Specific | B40: 603, 604, 607, 608 | C40: 0 | D40: -6.3 | E40: -0.713 | F40: -0.014 | J40: 0.191
A41: LV Generation Site Specific no RP charge | B41: 794, 795 | C41: 0 | D41: -6.3 | E41: -0.713 | F41: -0.014
A42: LV Sub Generation Site Specific | B42: 609, 610 | C42: 0 | D42: -5.55 | E42: -0.614 | F42: -0.012 | J42: 0.168
A43: LV Sub Generation Site Specific no RP charge | B43: 796, 797 | C43: 0 | D43: -5.55 | E43: -0.614 | F43: -0.012
A44: HV Generation Site Specific | B44: 605, 606, 611, 612 | C44: 0 | D44: -3.601 | E44: -0.337 | F44: -0.004 | G44: 97.47 | J44: 0.14
A45: HV Generation Site Specific no RP charge | B45: 798, 799 | C45: 0 | D45: -3.601 | E45: -0.337 | F45: -0.004 | G45: 97.47

Sheet Annex 2 EHV charges
A1: Back to Overview | C1: Copy EDCM table 5001 range starting B101 and paste into G11. Extend or reduce print area as required. | F1: Note: The list of MPANs / MSIDs provided may be incomplete; the DNO reserves the right to apply the listed charges to any other MPANs / MSIDs associated with the site.
A2: =Overview!B4& " - Effective from "&Overview!D4&" - "&Overview!E4&" EDCM charges" -> SP Distribution - Effective from 1 April 2022 - Final EDCM charges | P2: 1
P3: 1
A4: Time Periods for Designated EHV Properties | P4: 1
A5: Time periods | D5: Super Red Time Band | P5: 1
A6: Monday to Friday (Including Bank Holidays) June to August Inclusive | P6: 1
A7: Monday to Friday (Including Bank Holidays) November to February Inclusive | D7: 16:30 - 19:30 | P7: 1
A8: Notes | D8: All the above times are in UK Clock time | P8: 1
P9: 1
A10: Import Unique Identifier | B10: LLFC | C10: Import MPANs/MSIDs | D10: Export Unique Identifier | E10: LLFC | F10: Export MPANs/MSIDs | G10: Name | H10: Import Super Red unit charge (p/kWh) | I10: Import fixed charge (p/day) | J10: Import capacity charge (p/kVA/day) | K10: Import exceeded capacity charge (p/kVA/day) | L10: Export Super Red unit charge (p/kWh) | M10: Export fixed charge (p/day) | N10: Export capacity charge (p/kVA/day) | O10: Export exceeded capacity charge (p/kVA/day) | P10: x
A11: 800 | B11: 800 | C11: 1800060775972 | D11: 644 | E11: 644 | F11: 1800060775990 | G11: Rhodders | H11: - | I11: 253.25 | J11: 0.66 | K11: 0.66 | L11: - | M11: 5687.62 | N11: 0.05 | O11: 0.05 | P11: 1
A12: 801 | B12: 801 | C12: 1800060004220 | D12: MSID 8182 | E12: MSID 8182 | F12: MSID 8182 | G12: Minsca | H12: - | I12: 419.5 | J12: - | K12: - | L12: - | M12: - | N12: - | O12: - | P12: 1
A13: 802 | B13: 802 | C13: 1800060539962 | D13: 683 | E13: 683 | F13: 1800060539971 | G13: Bankend Rig | H13: - | I13: 131.36 | J13: 2.69 | K13: 2.69 | L13: - | M13: 4944.09 | N13: 0.05 | O13: 0.05 | P13: 1
A14: 803 | B14: 803 | C14: 1800060532708 | D14: 684 | E14: 684 | F14: 1800060532717 | G14: Barlockhart Moor | H14: - | I14: 160.43 | J14: 0.84 | K14: 0.84 | L14: - | M14: 8983 | N14: 0.05 | O14: 0.05 | P14: 1
A15: 804 | B15: 804 | C15: 1800060532726 | D15: 685 | E15: 685 | F15: 1800060532735 | G15: Blantyre Muir | H15: - | I15: 370.62 | J15: 0.66 | K15: 0.66 | L15: - | M15: 5840.28 | N15: 0.05 | O15: 0.05 | P15: 1
A16: 805 | B16: 805 | C16: 1800060587850 | D16: 693 | E16: 693 | F16: 1800060587869 | G16: Hunterston WF | H16: - | I16: 10916.73 | J16: 0.63 | K16: 0.63 | L16: - | M16: - | N16: - | O16: - | P16: 1
A17: 806 | B17: 806 | C17: 1800060532647 | D17: 688 | E17: 688 | F17: 1800060532656 | G17: Middleton Farm | H17: - | I17: 229.85 | J17: 0.85 | K17: 0.85 | L17: - | M17: 5222.16 | N17: 0.05 | O17: 0.05 | P17: 1
A18: 807 | B18: 807 | C18: 1800060532665 | D18: 689 | E18: 689 | F18: 1800060532674 | G18: Neilston Community | H18: - | I18: 135.72 | J18: 0.94 | K18: 0.94 | L18: - | M18: 6406.7 | N18: 0.05 | O18: 0.05 | P18: 1
A19: 808 | B19: 808 | C19: 1800053653870 | D19: 681 | E19: 681 | F19: 1800053653880 | G19: Garlaff Landfill | H19: - | I19: 104.76 | J19: 0.63 | K19: 0.63 | L19: - | M19: - | N19: - | O19: - | P19: 1
A20: 809 | B20: 809 | C20: 1800054992968 | D20: 629 | E20: 629 | F20: 1800054992977 | G20: Hagshaw Hill Extension | H20: - | I20: 718.91 | J20: 0.66 | K20: 0.66 | L20: - | M20: 18154.96 | N20: 0.05 | O20: 0.05 | P20: 1
A21: 811 | B21: 811 | C21: 1800060328035 | D21: 671 | E21: 671 | F21: 1800060328044 | G21: Muirhall | H21: - | I21: 341.85 | J21: 0.83 | K21: 0.83 | L21: - | M21: 8204.45 | N21: 0.05 | O21: 0.05 | P21: 1
A22: 812 | B22: 812 | C22: 1800060372113 | D22: 672 | E22: 672 | F22: 1800060372122 | G22: Burnfoot | H22: - | I22: 114.9 | J22: 0.7 | K22: 0.7 | L22: - | M22: 8017.86 | N22: 0.05 | O22: 0.05 | P22: 1
A23: 813 | B23: 813 | C23: 1800060532498 | D23: 690 | E23: 690 | F23: 1800060532503 | G23: Westfield WF | H23: - | I23: 60.76 | J23: 0.94 | K23: 0.94 | L23: - | M23: 7138.36 | N23: 0.05 | O23: 0.05 | P23: 1
A24: 814 | B24: 814 | C24: 1800060532683 | D24: 691 | E24: 691 | F24: 1800060532692 | G24: Barmoor WF | H24: - | I24: 201.67 | J24: 0.9 | K24: 0.9 | L24: - | M24: 19067.14 | N24: 0.05 | O24: 0.05 | P24: 1
A25: 815 | B25: 815 | C25: 1800060566984 | D25: 692 | E25: 692 | F25: 1800060566993 | G25: Nutberry WF | H25: - | I25: 811.8 | J25: 0.83 | K25: 0.83 | L25: - | M25: 15368.76 | N25: 0.05 | O25: 0.05 | P25: 1
A26: 816 | B26: 816 | C26: 1800060652454 | D26: 695 | E26: 695 | F26: 1800060652463 | G26: Carcreugh WF | H26: - | I26: 314.69 | J26: 0.65 | K26: 0.65 | L26: - | M26: 6423.35 | N26: 0.05 | O26: 0.05 | P26: 1
A27: 817 | B27: 817 | C27: 1800060567668 | G27: Magnox | H27: - | I27: 3246.12 | J27: 1.74 | K27: 1.74 | P27: 1
A28: 818 | B28: 818 | C28: 1800060642767 | D28: 700 | E28: 700 | F28: 1800060642776 | G28: West Browncastle WF | H28: - | I28: 507.77 | J28: 0.69 | K28: 0.69 | L28: - | M28: 28744.73 | N28: 0.05 | O28: 0.05 | P28: 1
A29: 819 | B29: 819 | C29: 1800060632661 | D29: 699 | E29: 699 | F29: 1800060632670 | G29: Viridor (Waste energy) | H29: - | I29: 1485.96 | J29: 1.01 | K29: 1.01 | L29: - | M29: 8903.35 | N29: 0.05 | O29: 0.05 | P29: 1
A30: 820 | B30: 820 | C30: 1800060289486 | D30: 620 | E30: 620 | F30: 1800060289510 | G30: Craigengelt | H30: - | I30: 151.25 | J30: 0.75 | K30: 0.75 | L30: - | M30: 20660.37 | N30: 0.05 | O30: 0.05 | P30: 1
A31: 821 | B31: 821 | C31: 1800054865132 | D31: 621 | E31: 621 | F31: 1800054865141 | G31: Greenknowes | H31: - | I31: 621.98 | J31: 0.71 | K31: 0.71 | L31: - | M31: 37319.01 | N31: 0.05 | O31: 0.05 | P31: 1
A32: 822 | B32: 822 | C32: 1800060683754 | D32: 703 | E32: 703 | F32: 1800060683763 | G32: Ewe Hill Dumfries WF | H32: - | I32: 474.4 | J32: 0.91 | K32: 0.91 | L32: - | M32: 21402.14 | N32: 0.05 | O32: 0.05 | P32: 1
A33: 823 | B33: 823 | C33: 1800060697223 | D33: 704 | E33: 704 | F33: 1800060697232 | G33: Langhope Rig (D) WF | H33: - | I33: 42.69 | J33: 1.37 | K33: 1.37 | L33: - | M33: 1400.11 | N33: 0.05 | O33: 0.05 | P33: See Annex 6
A34: 824 | B34: 824 | C34: 1800060674253 | D34: 705 | E34: 705 | F34: 1800060674262 | G34: Muirhall Extention WF | H34: - | I34: 54.73 | J34: 0.9 | K34: 0.9 | L34: - | M34: 3261.11 | N34: 0.05 | O34: 0.05 | P34: 1
A35: 825 | B35: 825 | C35: 1800060159192 | D35: 625 | E35: 625 | F35: 1800060159208 | G35: Aikengall | H35: - | I35: 937.97 | J35: - | K35: - | L35: - | M35: 8617.48 | N35: 0.05 | O35: 0.05 | P35: 1
A36: 826 | B36: 826 | C36: 1800053646251 | D36: 626 | E36: 626 | F36: 1800053646260 | G36: Hagshaw Hill | H36: - | I36: 55.88 | J36: 0.9 | K36: 0.9 | L36: - | M36: 1112.01 | N36: 0.05 | O36: 0.05 | P36: 1
A37: 827 | B37: 827 | C37: 1800053646190 | D37: 627 | E37: 627 | F37: 1800053646206 | G37: Gallow Rig | H37: - | I37: 194.88 | J37: 0.86 | K37: 0.86 | L37: - | M37: 4209.3 | N37: 0.05 | O37: 0.05 | P37: 1
A38: 828 | B38: 828 | C38: 1800053646172 | D38: 628 | E38: 628 | F38: 1800053646181 | G38: Polwhat Rig | H38: - | I38: 231.8 | J38: 0.84 | K38: 0.84 | L38: - | M38: 4172.38 | N38: 0.05 | O38: 0.05 | P38: 1
A39: 829 | B39: 829 | C39: 1800054738267 | D39: 624 | E39: 624 | F39: 1800054738276 | G39: Greendykeside | H39: - | I39: 53.18 | J39: 0.93 | K39: 0.93 | L39: - | M39: 3731.55 | N39: 0.05 | O39: 0.05 | P39: 1
A40: 830 | B40: 830 | C40: 1800053647237 | D40: 630 | E40: 630 | F40: 1800053647246 | G40: Dun Law | H40: - | I40: 33.51 | J40: 0.87 | K40: 0.87 | L40: - | M40: - | N40: - | O40: - | P40: 2
A41: 831 | B41: 831 | C41: 1800053647194 | D41: 631 | E41: 631 | F41: 1800053647200 | G41: EPR Scotland Ltd | H41: - | I41: 267.87 | J41: 0.99 | K41: 0.99 | L41: - | M41: - | N41: - | O41: - | P41: 2
A42: 832 | B42: 832 | C42: 1800053648027 | D42: 632 | E42: 632 | F42: 1800053648036 | G42: Bowbeat (Emly Bank) | H42: - | I42: 173.58 | J42: 0.83 | K42: 0.83 | L42: - | M42: - | N42: - | O42: - | P42: 2
A43: 833 | B43: 833 | C43: 1800053648045 | D43: 633 | E43: 633 | F43: 1800053648054 | G43: Bowbeat (Roughsidehill) | H43: - | I43: 121.16 | J43: 0.84 | K43: 0.84 | L43: - | M43: - | N43: - | O43: - | P43: 2
A44: 834 | B44: 834 | C44: 1800053647380 | D44: 634 | E44: 634 | F44: 1800053647399 | G44: Harehill | H44: - | I44: 120.74 | J44: 0.85 | K44: 0.85 | L44: - | M44: - | N44: - | O44: - | P44: 2
A45: 835 | B45: 835 | C45: 1800053647618 | D45: 635 | E45: 635 | F45: 1800053647627 | G45: Shanks & McEwan 3&4 | H45: - | I45: 113.21 | J45: 1.25 | K45: 1.25 | L45: - | M45: - | N45: - | O45: - | P45: 2
A46: 836 | B46: 836 | C46: 1800053647636 | D46: 636 | E46: 636 | F46: 1800053647645 | G46: Shanks & McEwan 5 | H46: - | I46: 26.57 | J46: 0.81 | K46: 0.81 | L46: - | M46: - | N46: - | O46: - | P46: 2
A47: 837 | B47: 837 | C47: 1800053653843 | D47: 637 | E47: 637 | F47: 1800053653852 | G47: Crystal Rig | H47: - | I47: 619.58 | J47: 0.64 | K47: 0.64 | L47: - | M47: - | N47: - | O47: - | P47: 2
A48: 838 | B48: 838 | C48: 1800053694167 | D48: 638 | E48: 638 | F48: 1800053694440 | G48: Haupland Muir (Ardrossan) | H48: - | I48: 7.01 | J48: 0.75 | K48: 0.75 | L48: - | M48: 213.48 | N48: 0.05 | O48: 0.05 | P48: 2
A49: 839 | B49: 839 | C49: 1800053950949 | D49: 639 | E49: 639 | F49: 1800053950958 | G49: Wetherhill | H49: - | I49: 536.2 | J49: - | K49: - | L49: - | M49: - | N49: - | O49: - | P49: 2
A50: 840 | B50: 840 | C50: 1800053434271 | D50: 640 | E50: 640 | F50: 1800053883993 | G50: Artfield WF | H50: - | I50: 761.05 | J50: - | K50: - | L50: - | M50: - | N50: - | O50: - | P50: See Annex 6
A51: 841 | B51: 841 | C51: 1800054152982 | D51: 641 | E51: 641 | F51: 1800054152991 | G51: Wardlaw Wood | H51: - | I51: 80.84 | J51: 0.91 | K51: 0.91 | L51: - | M51: - | N51: - | O51: - | P51: 2
A52: 842 | B52: 842 | C52: 1800054198365 | D52: 642 | E52: 642 | F52: 1800054198374 | G52: Earlsburn | H52: - | I52: 568.36 | J52: - | K52: - | L52: - | M52: - | N52: - | O52: - | P52: 2
A53: 843 | B53: 843 | C53: 1800054244570 | D53: 643 | E53: 643 | F53: 1800054244598 | G53: Blackhill | H53: - | I53: 955.36 | J53: - | K53: - | L53: - | M53: 22685.63 | N53: 0.05 | O53: 0.05 | P53: 2
A54: 844 | B54: 844 | C54: 1800054451603 | D54: MSID 8183 | E54: MSID 8183 | F54: MSID 8183 | G54: Dalswinton | H54: - | I54: 450.09 | J54: 0.74 | K54: 0.74 | L54: - | M54: - | N54: - | O54: - | P54: 2
A55: 845 | B55: 845 | C55: 1800054498470 | D55: 645 | E55: 645 | F55: 1800054498480 | G55: Steven's Croft Biomass | H55: - | I55: 4388.53 | J55: 0.69 | K55: 0.69 | L55: - | M55: - | N55: - | O55: - | P55: 2
A56: 850 | B56: 850 | C56: 1800060251872 | D56: 650 | E56: 650 | F56: 1800060251881 | G56: Longpark | H56: - | I56: 745.87 | J56: - | K56: - | L56: - | M56: 20524.58 | N56: 0.05 | O56: 0.05 | P56: 2
A57: 851 | B57: 851 | C57: 1800035140431 | G57: BOC | H57: - | I57: 27615.15 | J57: 2.41 | K57: 2.41 | P57: 2
A58: 852 | B58: 852 | C58: 1800060642702 | D58: 696 | E58: 696 | F58: 1800060642711 | G58: Calder Water WF | H58: - | I58: 225.36 | J58: 0.8 | K58: 0.8 | L58: - | M58: 27477.16 | N58: 0.05 | O58: 0.05 | P58: 2
A59: 853 | B59: 853 | C59: 1800035234188 | G59: Babcock Thorn | H59: - | I59: 29726.22 | J59: 2.81 | K59: 2.81 | P59: 2
A60: 854 | B60: 854 | C60: 1800035261359 | D60: 654 | E60: 654 | F60: 1800053946507 | G60: Lafarge UK | H60: - | I60: 25406.23 | J60: 2.07 | K60: 2.07 | L60: - | M60: - | N60: - | O60: - | P60: 2
A61: 855 | B61: 855 | C61: 1800060241304 | D61: 655 | E61: 655 | F61: 1800060241313 | G61: Pateshill | H61: - | I61: 22.72 | J61: 0.93 | K61: 0.93 | L61: - | M61: 1272.56 | N61: 0.05 | O61: 0.05 | P61: See Annex 6
A62: 856 | B62: 856 | C62: 1800035239460 | G62: Clydeport | H62: - | I62: 37789.45 | J62: 0.67 | K62: 0.67 | P62: 2
A63: 858 | B63: 858 | C63: 1800035327257 | G63: Tesco | H63: - | I63: 3821.17 | J63: 2.57 | K63: 2.57 | P63: 2
A64: 860 | B64: 860 | C64: 1800060852030 | D64: 666 | E64: 666 | F64: 1800060852049 | G64: Gevens Wind Farm | H64: - | I64: 22.62 | J64: 0.68 | K64: 0.68 | L64: - | M64: 5134.33 | N64: 0.05 | O64: 0.05 | P64: 2
A65: 861 | B65: 861 | C65: 1800035324780 | G65: Weir Pumps | H65: - | I65: 4581.23 | J65: 1.19 | K65: 1.19 | P65: 2
A66: 862 | B66: 862 | C66: 1800035317453 | G66: Dupont (UK) Ltd | H66: - | I66: 91962.67 | J66: 2.85 | K66: 2.85 | P66: 2
A67: 863 | B67: 863 | C67: 1800060207438 | D67: 663 | E67: 663 | F67: 1800060207447 | G67: North Rhins | H67: - | I67: 296.4 | J67: 0.86 | K67: 0.86 | L67: - | M67: 8908.32 | N67: 0.05 | O67: 0.05
A68: 864 | B68: 864 | C68: 1800060709038 | D68: 698 | E68: 698 | F68: 1800060709047 | G68: Tod Hills Windfarm | H68: - | I68: 74.92 | J68: 1.48 | K68: 1.48 | L68: - | M68: 8230.97 | N68: 0.05 | O68: 0.05 | P68: 2
A69: 865 | B69: 865 | C69: 1800060877284 | D69: 670 | E69: 670 | F69: 1800060877293 | G69: Hoprigshiels | H69: - | I69: 249.36 | J69: 0.91 | K69: 0.91 | L69: - | M69: 13122.77 | N69: 0.05 | O69: 0.05 | P69: 2
A70: 867 | B70: 867 | C70: 1800035325436 | G70: Norbord | H70: - | I70: 35607.63 | J70: 1.28 | K70: 1.28 | P70: 2
A71: 868 | B71: 868 | C71: 1800060809025 | D71: 664 | E71: 664 | F71: 1800060809034 | G71: MuirHall Extension II WF | H71: - | I71: 55.71 | J71: 0.9 | K71: 0.9 | L71: - | M71: 4775.4 | N71: 0.05 | O71: 0.05 | P71: 2
A72: 887 | B72: 887 | C72: 1800060749661 | D72: 706 | E72: 706 | F72: 1800060749670 | G72: Polmadie (Waste energy A) | H72: - | I72: 1171.77 | J72: 1.36 | K72: 1.36 | L72: - | M72: 4956.48 | N72: 0.05 | O72: 0.05 | P72: 2
A73: 873 | B73: 873 | C73: 1800060450481 | D73: 673 | E73: 673 | F73: 1800060450490 | G73: Millour Hill | H73: - | I73: 216.38 | J73: 0.69 | K73: 0.69 | L73: - | M73: 14894.93 | N73: 0.05 | O73: 0.05 | P73: 2
A74: 874 | B74: 874 | C74: 1800060441380 | D74: 674 | E74: 674 | F74: 1800060441399 | G74: Glenkerie | H74: - | I74: 383.19 | J74: 0.88 | K74: 0.88 | L74: - | M74: 14844.13 | N74: 0.05 | O74: 0.05 | P74: 2
A75: 875 | B75: 875 | C75: 1800060450524 | D75: 675 | E75: 675 | F75: 1800060450533 | G75: Kelburn (A) | H75: - | I75: 176.73 | J75: 0.92 | K75: 0.92 | L75: - | M75: 8828.47 | N75: 0.05 | O75: 0.05 | P75: See Annex 6
A76: 876 | B76: 876 | C76: 1800060450542 | D76: 676 | E76: 676 | F76: 1800060450551 | G76: Kelburn (B) | H76: - | I76: 176.73 | J76: 0.92 | K76: 0.92 | L76: - | M76: 8828.47 | N76: 0.05 | O76: 0.05 | P76: See Annex 6
A77: 877 | B77: 877 | C77: 1800060450506 | D77: 677 | E77: 677 | F77: 1800060450515 | G77: Little Raith | H77: - | I77: 193.98 | J77: 0.73 | K77: 0.73 | L77: - | M77: 5334.32 | N77: 0.05 | O77: 0.05 | P77: See Annex 6
A78: 878 | B78: 878 | C78: 1800060445640 | D78: 678 | E78: 678 | F78: 1800060445659 | G78: Drone Hill | H78: - | I78: 536.16 | J78: 0.66 | K78: 0.66 | L78: - | M78: 26295.81 | N78: 0.05 | O78: 0.05
A79: 879 | B79: 879 | C79: 1800060845812 | D79: 680 | E79: 680 | F79: 1800060845821 | G79: Pearie Law Wind Farm | H79: - | I79: 307.5 | J79: 0.9 | K79: 0.9 | L79: - | M79: 15935.82 | N79: 0.05 | O79: 0.05 | P79: 2
A80: 880 | B80: 880 | C80: 1800060673222 | D80: 701 | E80: 701 | F80: 1800060673231 | G80: Earlseat WF | H80: - | I80: 158.63 | J80: 1.8 | K80: 1.8 | L80: - | M80: 12034.91 | N80: 0.05 | O80: 0.05 | P80: 2
A81: 881 | B81: 881 | C81: 1800060740288 | D81: 702 | E81: 702 | F81: 1800060740297 | G81: Dungavel WF | H81: - | I81: 529.56 | J81: 0.68 | K81: 0.68 | L81: - | M81: 31667.55 | N81: 0.05 | O81: 0.05 | P81: 2
A82: 882 | B82: 882 | C82: 1800060769738 | D82: 687 | E82: 687 | F82: 1800060769747 | G82: Burnhead Bathgate WF | H82: - | I82: 63.43 | J82: 1.02 | K82: 1.02 | L82: - | M82: 4275.71 | N82: 0.05 | O82: 0.05 | P82: 2
A83: 883 | B83: 883 | C83: 1800053647742 | D83: 636 | E83: 636 | F83: 1800053647751 | G83: Shanks & McEwan 6 | H83: - | I83: 76.84 | J83: 0.81 | K83: 0.81 | L83: - | M83: - | N83: - | O83: - | P83: 2
A84: 884 | B84: 884 | C84: 1800060683693 | D84: 679 | E84: 679 | F84: 1800060683709 | G84: Ardoch & Over Enoch WF | H84: - | I84: 577.31 | J84: 0.68 | K84: 0.68 | L84: - | M84: 11647.13 | N84: 0.05 | O84: 0.05 | P84: 2
A85: 888 | B85: 888 | C85: 1800060817230 | D85: MSID 8732 | E85: MSID 8732 | F85: MSID 8732 | G85: Glenchamber | H85: - | I85: 111.65 | J85: 0.78 | K85: 0.78 | L85: - | M85: 14492.4 | N85: 0.05 | O85: 0.05 | P85: 2
A86: 889 | B86: 889 | C86: 1800060819273 | D86: 708 | E86: 708 | F86: 1800060819282 | G86: Penmansheill | H86: - | I86: 237.54 | J86: 0.69 | K86: 0.69 | L86: - | M86: 35880.37 | N86: 0.05 | O86: 0.05 | P86: 2
A87: 891 | B87: 891 | C87: 1800060863723 | D87: 668 | E87: 668 | F87: 1800060863732 | G87: Tormywheel | H87: - | I87: 58.31 | J87: 0.97 | K87: 0.97 | L87: - | M87: 10354.87 | N87: 0.05 | O87: 0.05 | P87: 2
A88: 892 | B88: 892 | C88: 1800060872755 | D88: 669 | E88: 669 | F88: 1800060872764 | G88: Quixwood Wind Farm | H88: - | I88: 299.93 | J88: 0.66 | K88: 0.66 | L88: - | M88: 27058.24 | N88: 0.05 | O88: 0.05 | P88: 2
A89: MSID 8083 | B89: MSID 8083 | C89: MSID 8083 | G89: Dumbarton | H89: - | I89: 9458.5 | J89: 0.82 | K89: 0.82 | P89: 2
A90: MSID 8085 | B90: MSID 8085 | C90: MSID 8085 | G90: Stirling Road | H90: - | I90: 9458.5 | J90: 0.75 | K90: 0.75 | P90: 2
A91: MSID 8334 | B91: MSID 8334 | C91: MSID 8334 | D91: MSID 8334 | E91: MSID 8334 | F91: MSID 8334 | G91: Markinch | H91: - | I91: 3747.69 | J91: 0.65 | K91: 0.65 | L91: - | M91: 21669.1 | N91: 0.05 | O91: 0.05 | P91: 2
A92: MSID 8339 | B92: MSID 8339 | C92: MSID 8339 | D92: MSID 8339 | E92: MSID 8339 | F92: MSID 8339 | G92: Harehill Extension | H92: - | I92: 239.52 | J92: 1.24 | K92: 1.24 | L92: - | M92: 8437.28 | N92: 0.05 | O92: 0.05 | P92: 2
A93: 847 | B93: 847 | C93: 1800060931899 | D93: MSID 8340 | E93: MSID 8340 | F93: MSID 8340 | G93: Aries | H93: - | I93: 126.81 | J93: 0.8 | K93: 0.8 | L93: - | M93: 13279.68 | N93: 0.05 | O93: 0.05 | P93: 3
A94: MSID 8341 | B94: MSID 8341 | C94: MSID 8341 | D94: MSID 8341 | E94: MSID 8341 | F94: MSID 8341 | G94: Andershaw WF | H94: - | I94: 192.03 | J94: 1.1 | K94: 1.1 | L94: - | M94: 26202.86 | N94: 0.05 | O94: 0.05 | P94: 3
A95: MSID 8347 | B95: MSID 8347 | C95: MSID 8347 | D95: MSID 8347 | E95: MSID 8347 | F95: MSID 8347 | G95: Assel Valley | H95: - | I95: 2010.95 | J95: 0.63 | K95: 0.63 | L95: - | M95: 47580.43 | N95: 0.05 | O95: 0.05 | P95: 3
A96: MSID 8348 | B96: MSID 8348 | C96: MSID 8348 | D96: MSID 8348 | E96: MSID 8348 | F96: MSID 8348 | G96: Auchrobert | H96: - | I96: 324.72 | J96: 0.7 | K96: 0.7 | L96: - | M96: 15816.45 | N96: 0.05 | O96: 0.05 | P96: 3
A97: MSID 8349 | B97: MSID 8349 | C97: MSID 8349 | D97: MSID 8349 | E97: MSID 8349 | F97: MSID 8349 | G97: Harburnhead | H97: - | I97: 45.96 | J97: 0.91 | K97: 0.91 | L97: - | M97: 10828.81 | N97: 0.05 | O97: 0.05 | P97: 3
A98: 310 | B98: 310 | C98: 1800036579036 | G98: Magco | H98: - | I98: 3271.72 | J98: 3.58 | K98: 3.58 | P98: 3
A99: 311 | B99: 311 | C99: 1800035324497 | G99: Stirling University | H99: - | I99: 3271.72 | J99: 1.6 | K99: 1.6 | P99: 3
A100: 312 | B100: 312 | C100: 1800035324530 | G100: Glenochil Distillery | H100: - | I100: 9854.62 | J100: 3.9 | K100: 3.9 | P100: 3
...

Sheet Annex 2a Import
A1: Note: The list of MPANs / MSIDs provided may be incomplete; the DNO reserves the right to apply the listed charges to any other MPANs / MSIDs associated with the site. Note: This table is automatically populated based on the content of the tab entitled 'Annex 2 EHV Charges'. The timebands are as shown in Annex 2.
A2: =Overview!B4& " - Effective from "&Overview!D4&" - "&Overview!E4&" EDCM import charges" -> SP Distribution - Effective from 1 April 2022 - Final EDCM import charges
A4: Import Unique Identifier | B4: LLFC | C4: Import MPANs/MSIDs | D4: Name | E4: ='Annex 2 EHV charges'!H10 -> Import Super Red unit charge (p/kWh) | F4: ='Annex 2 EHV charges'!I10 -> Import fixed charge (p/day) | G4: ='Annex 2 EHV charges'!J10 -> Import capacity charge (p/kVA/day) | H4: ='Annex 2 EHV charges'!K10 -> Import exceeded capacity charge (p/kVA/day)
A5: {=IFERROR(INDEX('Annex 2 EHV charges'!$A$11:$A$260, MATCH(0, IF(ISBLANK('Annex 2 EHV charges'!$A$11:$A$260),1, COUNTIF(A$4:$A4, 'Annex 2 EHV charges'!$A$11:$A$260)), 0)),"")} -> 800 | B5: =IF($A5="","",VLOOKUP($A5,'Annex 2 EHV charges'!$A:$O,2,0)) -> 800 | C5: =IF($A5="","",VLOOKUP($A5,'Annex 2 EHV charges'!$A:$O,3,0)) -> 1800060775972 | D5: =IF($A5="","",VLOOKUP($A5,'Annex 2 EHV charges'!$A:$O,7,0)) -> Rhodders | E5: =IFERROR(IF(VLOOKUP($A5,'Annex 2 EHV charges'!$A:$O,8,FALSE)=0,"",VLOOKUP($A5,'Annex 2 EHV charges'!$A:$O,8,FALSE)),"") -> - | F5: =IFERROR(IF(VLOOKUP($A5,'Annex 2 EHV charges'!$A:$O,9,FALSE)=0,"",VLOOKUP($A5,'Annex 2 EHV charges'!$A:$O,9,FALSE)),"") -> 253.25 | G5: =IFERROR(IF(VLOOKUP($A5,'Annex 2 EHV charges'!$A:$O,10,FALSE)=0,"",VLOOKUP($A5,'Annex 2 EHV charges'!$A:$O,10,FALSE)),"") -> 0.66 | H5: =IFERROR(IF(VLOOKUP($A5,'Annex 2 EHV charges'!$A:$O,11,FALSE)=0,"",VLOOKUP($A5,'Annex 2 EHV charges'!$A:$O,11,FALSE)),"") -> 0.66 | I5: =IF(VLOOKUP(C5,'Annex 2 EHV charges'!$C$11:$P$154,14,FALSE)<=5,"",VLOOKUP(C5,'Annex 2 EHV charges'!$C$11:$P$154,14,FALSE))
A6: {=IFERROR(INDEX('Annex 2 EHV charges'!$A$11:$A$260, MATCH(0, IF(ISBLANK('Annex 2 EHV charges'!$A$11:$A$260),1, COUNTIF(A$4:$A5, 'Annex 2 EHV charges'!$A$11:$A$260)), 0)),"")} -> 801 | B6: =IF($A6="","",VLOOKUP($A6,'Annex 2 EHV charges'!$A:$O,2,0)) -> 801 | C6: =IF($A6="","",VLOOKUP($A6,'Annex 2 EHV charges'!$A:$O,3,0)) -> 1800060004220 | D6: =IF($A6="","",VLOOKUP($A6,'Annex 2 EHV charges'!$A:$O,7,0)) -> Minsca | E6: =IFERROR(IF(VLOOKUP($A6,'Annex 2 EHV charges'!$A:$O,8,FALSE)=0,"",VLOOKUP($A6,'Annex 2 EHV charges'!$A:$O,8,FALSE)),"") -> - | F6: =IFERROR(IF(VLOOKUP($A6,'Annex 2 EHV charges'!$A:$O,9,FALSE)=0,"",VLOOKUP($A6,'Annex 2 EHV charges'!$A:$O,9,FALSE)),"") -> 419.5 | G6: =IFERROR(IF(VLOOKUP($A6,'Annex 2 EHV charges'!$A:$O,10,FALSE)=0,"",VLOOKUP($A6,'Annex 2 EHV charges'!$A:$O,10,FALSE)),"") -> - | H6: =IFERROR(IF(VLOOKUP($A6,'Annex 2 EHV charges'!$A:$O,11,FALSE)=0,"",VLOOKUP($A6,'Annex 2 EHV charges'!$A:$O,11,FALSE)),"") -> - | I6: =IF(VLOOKUP(C6,'Annex 2 EHV charges'!$C$11:$P$154,14,FALSE)<=5,"",VLOOKUP(C6,'Annex 2 EHV charges'!$C$11:$P$154,14,FALSE))
A7: {=IFERROR(INDEX('Annex 2 EHV charges'!$A$11:$A$260, MATCH(0, IF(ISBLANK('Annex 2 EHV charges'!$A$11:$A$260),1, COUNTIF(A$4:$A6, 'Annex 2 EHV charges'!$A$11:$A$260)), 0)),"")} -> 802 | B7: =IF($A7="","",VLOOKUP($A7,'Annex 2 EHV charges'!$A:$O,2,0)) -> 802 | C7: =IF($A7="","",VLOOKUP($A7,'Annex 2 EHV charges'!$A:$O,3,0)) -> 1800060539962 | D7: =IF($A7="","",VLOOKUP($A7,'Annex 2 EHV charges'!$A:$O,7,0)) -> Bankend Rig | E7: =IFERROR(IF(VLOOKUP($A7,'Annex 2 EHV charges'!$A:$O,8,FALSE)=0,"",VLOOKUP($A7,'Annex 2 EHV charges'!$A:$O,8,FALSE)),"") -> - | F7: =IFERROR(IF(VLOOKUP($A7,'Annex 2 EHV charges'!$A:$O,9,FALSE)=0,"",VLOOKUP($A7,'Annex 2 EHV charges'!$A:$O,9,FALSE)),"") -> 131.36 | G7: =IFERROR(IF(VLOOKUP($A7,'Annex 2 EHV charges'!$A:$O,10,FALSE)=0,"",VLOOKUP($A7,'Annex 2 EHV charges'!$A:$O,10,FALSE)),"") -> 2.69 | H7: =IFERROR(IF(VLOOKUP($A7,'Annex 2 EHV charges'!$A:$O,11,FALSE)=0,"",VLOOKUP($A7,'Annex 2 EHV charges'!$A:$O,11,FALSE)),"") -> 2.69 | I7: =IF(VLOOKUP(C7,'Annex 2 EHV charges'!$C$11:$P$154,14,FALSE)<=5,"",VLOOKUP(C7,'Annex 2 EHV charges'!$C$11:$P$154,14,FALSE))
A8: {=IFERROR(INDEX('Annex 2 EHV charges'!$A$11:$A$260, MATCH(0, IF(ISBLANK('Annex 2 EHV charges'!$A$11:$A$260),1, COUNTIF(A$4:$A7, 'Annex 2 EHV charges'!$A$11:$A$260)), 0)),"")} -> 803 | B8: =IF($A8="","",VLOOKUP($A8,'Annex 2 EHV charges'!$A:$O,2,0)) -> 803 | C8: =IF($A8="","",VLOOKUP($A8,'Annex 2 EHV charges'!$A:$O,3,0)) -> 1800060532708 | D8: =IF($A8="","",VLOOKUP($A8,'Annex 2 EHV charges'!$A:$O,7,0)) -> Barlockhart Moor | E8: =IFERROR(IF(VLOOKUP($A8,'Annex 2 EHV charges'!$A:$O,8,FALSE)=0,"",VLOOKUP($A8,'Annex 2 EHV charges'!$A:$O,8,FALSE)),"") -> - | F8: =IFERROR(IF(VLOOKUP($A8,'Annex 2 EHV charges'!$A:$O,9,FALSE)=0,"",VLOOKUP($A8,'Annex 2 EHV charges'!$A:$O,9,FALSE)),"") -> 160.43 | G8: =IFERROR(IF(VLOOKUP($A8,'Annex 2 EHV charges'!$A:$O,10,FALSE)=0,"",VLOOKUP($A8,'Annex 2 EHV charges'!$A:$O,10,FALSE)),"") -> 0.84 | H8: =IFERROR(IF(VLOOKUP($A8,'Annex 2 EHV charges'!$A:$O,11,FALSE)=0,"",VLOOKUP($A8,'Annex 2 EHV charges'!$A:$O,11,FALSE)),"") -> 0.84 | I8: =IF(VLOOKUP(C8,'Annex 2 EHV charges'!$C$11:$P$154,14,FALSE)<=5,"",VLOOKUP(C8,'Annex 2 EHV charges'!$C$11:$P$154,14,FALSE))
A9: {=IFERROR(INDEX('Annex 2 EHV charges'!$A$11:$A$260, MATCH(0, IF(ISBLANK('Annex 2 EHV charges'!$A$11:$A$260),1, COUNTIF(A$4:$A8, 'Annex 2 EHV charges'!$A$11:$A$260)), 0)),"")} -> 804 | B9: =IF($A9="","",VLOOKUP($A9,'Annex 2 EHV charges'!$A:$O,2,0)) -> 804 | C9: =IF($A9="","",VLOOKUP($A9,'Annex 2 EHV charges'!$A:$O,3,0)) -> 1800060532726 | D9: =IF($A9="","",VLOOKUP($A9,'Annex 2 EHV charges'!$A:$O,7,0)) -> Blantyre Muir | E9: =IFERROR(IF(VLOOKUP($A9,'Annex 2 EHV charges'!$A:$O,8,FALSE)=0,"",VLOOKUP($A9,'Annex 2 EHV charges'!$A:$O,8,FALSE)),"") -> - | F9: =IFERROR(IF(VLOOKUP($A9,'Annex 2 EHV charges'!$A:$O,9,FALSE)=0,"",VLOOKUP($A9,'Annex 2 EHV charges'!$A:$O,9,FALSE)),"") -> 370.62 | G9: =IFERROR(IF(VLOOKUP($A9,'Annex 2 EHV charges'!$A:$O,10,FALSE)=0,"",VLOOKUP($A9,'Annex 2 EHV charges'!$A:$O,10,FALSE)),"") -> 0.66 | H9: =IFERROR(IF(VLOOKUP($A9,'Annex 2 EHV charges'!$A:$O,11,FALSE)=0,"",VLOOKUP($A9,'Annex 2 EHV charges'!$A:$O,11,FALSE)),"") -> 0.66 | I9: =IF(VLOOKUP(C9,'Annex 2 EHV charges'!$C$11:$P$154,14,FALSE)<=5,"",VLOOKUP(C9,'Annex 2 EHV charges'!$C$11:$P$154,14,FALSE))
A10: {=IFERROR(INDEX('Annex 2 EHV charges'!$A$11:$A$260, MATCH(0, IF(ISBLANK('Annex 2 EHV charges'!$A$11:$A$260),1, COUNTIF(A$4:$A9, 'Annex 2 EHV charges'!$A$11:$A$260)), 0)),"")} -> 805 | B10: =IF($A10="","",VLOOKUP($A10,'Annex 2 EHV charges'!$A:$O,2,0)) -> 805 | C10: =IF($A10="","",VLOOKUP($A10,'Annex 2 EHV charges'!$A:$O,3,0)) -> 1800060587850 | D10: =IF($A10="","",VLOOKUP($A10,'Annex 2 EHV charges'!$A:$O,7,0)) -> Hunterston WF | E10: =IFERROR(IF(VLOOKUP($A10,'Annex 2 EHV charges'!$A:$O,8,FALSE)=0,"",VLOOKUP($A10,'Annex 2 EHV charges'!$A:$O,8,FALSE)),"") -> - | F10: =IFERROR(IF(VLOOKUP($A10,'Annex 2 EHV charges'!$A:$O,9,FALSE)=0,"",VLOOKUP($A10,'Annex 2 EHV charges'!$A:$O,9,FALSE)),"") -> 10916.73 | G10: =IFERROR(IF(VLOOKUP($A10,'Annex 2 EHV charges'!$A:$O,10,FALSE)=0,"",VLOOKUP($A10,'Annex 2 EHV charges'!$A:$O,10,FALSE)),"") -> 0.63 | H10: =IFERROR(IF(VLOOKUP($A10,'Annex 2 EHV charges'!$A:$O,11,FALSE)=0,"",VLOOKUP($A10,'Annex 2 EHV charges'!$A:$O,11,FALSE)),"") -> 0.63 | I10: =IF(VLOOKUP(C10,'Annex 2 EHV charges'!$C$11:$P$154,14,FALSE)<=5,"",VLOOKUP(C10,'Annex 2 EHV charges'!$C$11:$P$154,14,FALSE))
A11: {=IFERROR(INDEX('Annex 2 EHV charges'!$A$11:$A$260, MATCH(0, IF(ISBLANK('Annex 2 EHV charges'!$A$11:$A$260),1, COUNTIF(A$4:$A10, 'Annex 2 EHV charges'!$A$11:$A$260)), 0)),"")} -> 806 | B11: =IF($A11="","",VLOOKUP($A11,'Annex 2 EHV charges'!$A:$O,2,0)) -> 806 | C11: =IF($A11="","",VLOOKUP($A11,'Annex 2 EHV charges'!$A:$O,3,0)) -> 1800060532647 | D11: =IF($A11="","",VLOOKUP($A11,'Annex 2 EHV charges'!$A:$O,7,0)) -> Middleton Farm | E11: =IFERROR(IF(VLOOKUP($A11,'Annex 2 EHV charges'!$A:$O,8,FALSE)=0,"",VLOOKUP($A11,'Annex 2 EHV charges'!$A:$O,8,FALSE)),"") -> - | F11: =IFERROR(IF(VLOOKUP($A11,'Annex 2 EHV charges'!$A:$O,9,FALSE)=0,"",VLOOKUP($A11,'Annex 2 EHV charges'!$A:$O,9,FALSE)),"") -> 229.85 | G11: =IFERROR(IF(VLOOKUP($A11,'Annex 2 EHV charges'!$A:$O,10,FALSE)=0,"",VLOOKUP($A11,'Annex 2 EHV charges'!$A:$O,10,FALSE)),"") -> 0.85 | H11: =IFERROR(IF(VLOOKUP($A11,'Annex 2 EHV charges'!$A:$O,11,FALSE)=0,"",VLOOKUP($A11,'Annex 2 EHV charges'!$A:$O,11,FALSE)),"") -> 0.85 | I11: =IF(VLOOKUP(C11,'Annex 2 EHV charges'!$C$11:$P$154,14,FALSE)<=5,"",VLOOKUP(C11,'Annex 2 EHV charges'!$C$11:$P$154,14,FALSE))
A12: {=IFERROR(INDEX('Annex 2 EHV charges'!$A$11:$A$260, MATCH(0, IF(ISBLANK('Annex 2 EHV charges'!$A$11:$A$260),1, COUNTIF(A$4:$A11, 'Annex 2 EHV charges'!$A$11:$A$260)), 0)),"")} -> 807 | B12: =IF($A12="","",VLOOKUP($A12,'Annex 2 EHV charges'!$A:$O,2,0)) -> 807 | C12: =IF($A12="","",VLOOKUP($A12,'Annex 2 EHV charges'!$A:$O,3,0)) -> 1800060532665 | D12: =IF($A12="","",VLOOKUP($A12,'Annex 2 EHV charges'!$A:$O,7,0)) -> Neilston Community | E12: =IFERROR(IF(VLOOKUP($A12,'Annex 2 EHV charges'!$A:$O,8,FALSE)=0,"",VLOOKUP($A12,'Annex 2 EHV charges'!$A:$O,8,FALSE)),"") -> - | F12: =IFERROR(IF(VLOOKUP($A12,'Annex 2 EHV charges'!$A:$O,9,FALSE)=0,"",VLOOKUP($A12,'Annex 2 EHV charges'!$A:$O,9,FALSE)),"") -> 135.72 | G12: =IFERROR(IF(VLOOKUP($A12,'Annex 2 EHV charges'!$A:$O,10,FALSE)=0,"",VLOOKUP($A12,'Annex 2 EHV charges'!$A:$O,10,FALSE)),"") -> 0.94 | H12: =IFERROR(IF(VLOOKUP($A12,'Annex 2 EHV charges'!$A:$O,11,FALSE)=0,"",VLOOKUP($A12,'Annex 2 EHV charges'!$A:$O,11,FALSE)),"") -> 0.94 | I12: =IF(VLOOKUP(C12,'Annex 2 EHV charges'!$C$11:$P$154,14,FALSE)<=5,"",VLOOKUP(C12,'Annex 2 EHV charges'!$C$11:$P$154,14,FALSE))
A13: {=IFERROR(INDEX('Annex 2 EHV charges'!$A$11:$A$260, MATCH(0, IF(ISBLANK('Annex 2 EHV charges'!$A$11:$A$260),1, COUNTIF(A$4:$A12, 'Annex 2 EHV charges'!$A$11:$A$260)), 0)),"")} -> 808 | B13: =IF($A13="","",VLOOKUP($A13,'Annex 2 EHV charges'!$A:$O,2,0)) -> 808 | C13: =IF($A13="","",VLOOKUP($A13,'Annex 2 EHV charges'!$A:$O,3,0)) -> 1800053653870 | D13: =IF($A13="","",VLOOKUP($A13,'Annex 2 EHV charges'!$A:$O,7,0)) -> Garlaff Landfill | E13: =IFERROR(IF(VLOOKUP($A13,'Annex 2 EHV charges'!$A:$O,8,FALSE)=0,"",VLOOKUP($A13,'Annex 2 EHV charges'!$A:$O,8,FALSE)),"") -> - | F13: =IFERROR(IF(VLOOKUP($A13,'Annex 2 EHV charges'!$A:$O,9,FALSE)=0,"",VLOOKUP($A13,'Annex 2 EHV charges'!$A:$O,9,FALSE)),"") -> 104.76 | G13: =IFERROR(IF(VLOOKUP($A13,'Annex 2 EHV charges'!$A:$O,10,FALSE)=0,"",VLOOKUP($A13,'Annex 2 EHV charges'!$A:$O,10,FALSE)),"") -> 0.63 | H13: =IFERROR(IF(VLOOKUP($A13,'Annex 2 EHV charges'!$A:$O,11,FALSE)=0,"",VLOOKUP($A13,'Annex 2 EHV charges'!$A:$O,11,FALSE)),"") -> 0.63 | I13: =IF(VLOOKUP(C13,'Annex 2 EHV charges'!$C$11:$P$154,14,FALSE)<=5,"",VLOOKUP(C13,'Annex 2 EHV charges'!$C$11:$P$154,14,FALSE))
A14: {=IFERROR(INDEX('Annex 2 EHV charges'!$A$11:$A$260, MATCH(0, IF(ISBLANK('Annex 2 EHV charges'!$A$11:$A$260),1, COUNTIF(A$4:$A13, 'Annex 2 EHV charges'!$A$11:$A$260)), 0)),"")} -> 809 | B14: =IF($A14="","",VLOOKUP($A14,'Annex 2 EHV charges'!$A:$O,2,0)) -> 809 | C14: =IF($A14="","",VLOOKUP($A14,'Annex 2 EHV charges'!$A:$O,3,0)) -> 1800054992968 | D14: =IF($A14="","",VLOOKUP($A14,'Annex 2 EHV charges'!$A:$O,7,0)) -> Hagshaw Hill Extension | E14: =IFERROR(IF(VLOOKUP($A14,'Annex 2 EHV charges'!$A:$O,8,FALSE)=0,"",VLOOKUP($A14,'Annex 2 EHV charges'!$A:$O,8,FALSE)),"") -> - | F14: =IFERROR(IF(VLOOKUP($A14,'Annex 2 EHV charges'!$A:$O,9,FALSE)=0,"",VLOOKUP($A14,'Annex 2 EHV charges'!$A:$O,9,FALSE)),"") -> 718.91 | G14: =IFERROR(IF(VLOOKUP($A14,'Annex 2 EHV charges'!$A:$O,10,FALSE)=0,"",VLOOKUP($A14,'Annex 2 EHV charges'!$A:$O,10,FALSE)),"") -> 0.66 | H14: =IFERROR(IF(VLOOKUP($A14,'Annex 2 EHV charges'!$A:$O,11,FALSE)=0,"",VLOOKUP($A14,'Annex 2 EHV charges'!$A:$O,11,FALSE)),"") -> 0.66 | I14: =IF(VLOOKUP(C14,'Annex 2 EHV charges'!$C$11:$P$154,14,FALSE)<=5,"",VLOOKUP(C14,'Annex 2 EHV charges'!$C$11:$P$154,14,FALSE))
A15: {=IFERROR(INDEX('Annex 2 EHV charges'!$A$11:$A$260, MATCH(0, IF(ISBLANK('Annex 2 EHV charges'!$A$11:$A$260),1, COUNTIF(A$4:$A14, 'Annex 2 EHV charges'!$A$11:$A$260)), 0)),"")} -> 811 | B15: =IF($A15="","",VLOOKUP($A15,'Annex 2 EHV charges'!$A:$O,2,0)) -> 811 | C15: =IF($A15="","",VLOOKUP($A15,'Annex 2 EHV charges'!$A:$O,3,0)) -> 1800060328035 | D15: =IF($A15="","",VLOOKUP($A15,'Annex 2 EHV charges'!$A:$O,7,0)) -> Muirhall | E15: =IFERROR(IF(VLOOKUP($A15,'Annex 2 EHV charges'!$A:$O,8,FALSE)=0,"",VLOOKUP($A15,'Annex 2 EHV charges'!$A:$O,8,FALSE)),"") -> - | F15: =IFERROR(IF(VLOOKUP($A15,'Annex 2 EHV charges'!$A:$O,9,FALSE)=0,"",VLOOKUP($A15,'Annex 2 EHV charges'!$A:$O,9,FALSE)),"") -> 341.85 | G15: =IFERROR(IF(VLOOKUP($A15,'Annex 2 EHV charges'!$A:$O,10,FALSE)=0,"",VLOOKUP($A15,'Annex 2 EHV charges'!$A:$O,10,FALSE)),"") -> 0.83 | H15: =IFERROR(IF(VLOOKUP($A15,'Annex 2 EHV charges'!$A:$O,11,FALSE)=0,"",VLOOKUP($A15,'Annex 2 EHV charges'!$A:$O,11,FALSE)),"") -> 0.83 | I15: =IF(VLOOKUP(C15,'Annex 2 EHV charges'!$C$11:$P$154,14,FALSE)<=5,"",VLOOKUP(C15,'Annex 2 EHV charges'!$C$11:$P$154,14,FALSE))
A16: {=IFERROR(INDEX('Annex 2 EHV charges'!$A$11:$A$260, MATCH(0, IF(ISBLANK('Annex 2 EHV charges'!$A$11:$A$260),1, COUNTIF(A$4:$A15, 'Annex 2 EHV charges'!$A$11:$A$260)), 0)),"")} -> 812 | B16: =IF($A16="","",VLOOKUP($A16,'Annex 2 EHV charges'!$A:$O,2,0)) -> 812 | C16: =IF($A16="","",VLOOKUP($A16,'Annex 2 EHV charges'!$A:$O,3,0)) -> 1800060372113 | D16: =IF($A16="","",VLOOKUP($A16,'Annex 2 EHV charges'!$A:$O,7,0)) -> Burnfoot | E16: =IFERROR(IF(VLOOKUP($A16,'Annex 2 EHV charges'!$A:$O,8,FALSE)=0,"",VLOOKUP($A16,'Annex 2 EHV charges'!$A:$O,8,FALSE)),"") -> - | F16: =IFERROR(IF(VLOOKUP($A16,'Annex 2 EHV charges'!$A:$O,9,FALSE)=0,"",VLOOKUP($A16,'Annex 2 EHV charges'!$A:$O,9,FALSE)),"") -> 114.9 | G16: =IFERROR(IF(VLOOKUP($A16,'Annex 2 EHV charges'!$A:$O,10,FALSE)=0,"",VLOOKUP($A16,'Annex 2 EHV charges'!$A:$O,10,FALSE)),"") -> 0.7 | H16: =IFERROR(IF(VLOOKUP($A16,'Annex 2 EHV charges'!$A:$O,11,FALSE)=0,"",VLOOKUP($A16,'Annex 2 EHV charges'!$A:$O,11,FALSE)),"") -> 0.7 | I16: =IF(VLOOKUP(C16,'Annex 2 EHV charges'!$C$11:$P$154,14,FALSE)<=5,"",VLOOKUP(C16,'Annex 2 EHV charges'!$C$11:$P$154,14,FALSE))
... A142: {=IFERROR(INDEX('Annex 2 EHV charges'!$A$11:$A$260, MATCH(0, IF(ISBLANK('Annex 2 EHV charges'!$A$11:$A$260),1, COUNTIF(A$4:$A141, 'Annex 2 EHV charges'!$A$11:$A$260)), 0)),"")} | B142: =IF($A142="","",VLOOKUP($A142,'Annex 2 EHV charges'!$A:$O,2,0)) | C142: =IF($A142="","",VLOOKUP($A142,'Annex 2 EHV charges'!$A:$O,3,0)) | D142: =IF($A142="","",VLOOKUP($A142,'Annex 2 EHV charges'!$A:$O,7,0)) | E142: =IFERROR(IF(VLOOKUP($A142,'Annex 2 EHV charges'!$A:$O,8,FALSE)=0,"",VLOOKUP($A142,'Annex 2 EHV charges'!$A:$O,8,FALSE)),"") | F142: =IFERROR(IF(VLOOKUP($A142,'Annex 2 EHV charges'!$A:$O,9,FALSE)=0,"",VLOOKUP($A142,'Annex 2 EHV charges'!$A:$O,9,FALSE)),"") | G142: =IFERROR(IF(VLOOKUP($A142,'Annex 2 EHV charges'!$A:$O,10,FALSE)=0,"",VLOOKUP($A142,'Annex 2 EHV charges'!$A:$O,10,FALSE)),"") | H142: =IFERROR(IF(VLOOKUP($A142,'Annex 2 EHV charges'!$A:$O,11,FALSE)=0,"",VLOOKUP($A142,'Annex 2 EHV charges'!$A:$O,11,FALSE)),"") | I142: =IF(VLOOKUP(C142,'Annex 2 EHV charges'!$C$11:$P$154,14,FALSE)<=5,"",VLOOKUP(C142,'Annex 2 EHV charges'!$C$11:$P$154,14,FALSE))
A143: {=IFERROR(INDEX('Annex 2 EHV charges'!$A$11:$A$260, MATCH(0, IF(ISBLANK('Annex 2 EHV charges'!$A$11:$A$260),1, COUNTIF(A$4:$A142, 'Annex 2 EHV charges'!$A$11:$A$260)), 0)),"")} | B143: =IF($A143="","",VLOOKUP($A143,'Annex 2 EHV charges'!$A:$O,2,0)) | C143: =IF($A143="","",VLOOKUP($A143,'Annex 2 EHV charges'!$A:$O,3,0)) | D143: =IF($A143="","",VLOOKUP($A143,'Annex 2 EHV charges'!$A:$O,7,0)) | E143: =IFERROR(IF(VLOOKUP($A143,'Annex 2 EHV charges'!$A:$O,8,FALSE)=0,"",VLOOKUP($A143,'Annex 2 EHV charges'!$A:$O,8,FALSE)),"") | F143: =IFERROR(IF(VLOOKUP($A143,'Annex 2 EHV charges'!$A:$O,9,FALSE)=0,"",VLOOKUP($A143,'Annex 2 EHV charges'!$A:$O,9,FALSE)),"") | G143: =IFERROR(IF(VLOOKUP($A143,'Annex 2 EHV charges'!$A:$O,10,FALSE)=0,"",VLOOKUP($A143,'Annex 2 EHV charges'!$A:$O,10,FALSE)),"") | H143: =IFERROR(IF(VLOOKUP($A143,'Annex 2 EHV charges'!$A:$O,11,FALSE)=0,"",VLOOKUP($A143,'Annex 2 EHV charges'!$A:$O,11,FALSE)),"")
A144: {=IFERROR(INDEX('Annex 2 EHV charges'!$A$11:$A$260, MATCH(0, IF(ISBLANK('Annex 2 EHV charges'!$A$11:$A$260),1, COUNTIF(A$4:$A143, 'Annex 2 EHV charges'!$A$11:$A$260)), 0)),"")} | B144: =IF($A144="","",VLOOKUP($A144,'Annex 2 EHV charges'!$A:$O,2,0)) | C144: =IF($A144="","",VLOOKUP($A144,'Annex 2 EHV charges'!$A:$O,3,0)) | D144: =IF($A144="","",VLOOKUP($A144,'Annex 2 EHV charges'!$A:$O,7,0)) | E144: =IFERROR(IF(VLOOKUP($A144,'Annex 2 EHV charges'!$A:$O,8,FALSE)=0,"",VLOOKUP($A144,'Annex 2 EHV charges'!$A:$O,8,FALSE)),"") | F144: =IFERROR(IF(VLOOKUP($A144,'Annex 2 EHV charges'!$A:$O,9,FALSE)=0,"",VLOOKUP($A144,'Annex 2 EHV charges'!$A:$O,9,FALSE)),"") | G144: =IFERROR(IF(VLOOKUP($A144,'Annex 2 EHV charges'!$A:$O,10,FALSE)=0,"",VLOOKUP($A144,'Annex 2 EHV charges'!$A:$O,10,FALSE)),"") | H144: =IFERROR(IF(VLOOKUP($A144,'Annex 2 EHV charges'!$A:$O,11,FALSE)=0,"",VLOOKUP($A144,'Annex 2 EHV charges'!$A:$O,11,FALSE)),"")
A145: {=IFERROR(INDEX('Annex 2 EHV charges'!$A$11:$A$260, MATCH(0, IF(ISBLANK('Annex 2 EHV charges'!$A$11:$A$260),1, COUNTIF(A$4:$A144, 'Annex 2 EHV charges'!$A$11:$A$260)), 0)),"")} | B145: =IF($A145="","",VLOOKUP($A145,'Annex 2 EHV charges'!$A:$O,2,0)) | C145: =IF($A145="","",VLOOKUP($A145,'Annex 2 EHV charges'!$A:$O,3,0)) | D145: =IF($A145="","",VLOOKUP($A145,'Annex 2 EHV charges'!$A:$O,7,0)) | E145: =IFERROR(IF(VLOOKUP($A145,'Annex 2 EHV charges'!$A:$O,8,FALSE)=0,"",VLOOKUP($A145,'Annex 2 EHV charges'!$A:$O,8,FALSE)),"") | F145: =IFERROR(IF(VLOOKUP($A145,'Annex 2 EHV charges'!$A:$O,9,FALSE)=0,"",VLOOKUP($A145,'Annex 2 EHV charges'!$A:$O,9,FALSE)),"") | G145: =IFERROR(IF(VLOOKUP($A145,'Annex 2 EHV charges'!$A:$O,10,FALSE)=0,"",VLOOKUP($A145,'Annex 2 EHV charges'!$A:$O,10,FALSE)),"") | H145: =IFERROR(IF(VLOOKUP($A145,'Annex 2 EHV charges'!$A:$O,11,FALSE)=0,"",VLOOKUP($A145,'Annex 2 EHV charges'!$A:$O,11,FALSE)),"")
A146: {=IFERROR(INDEX('Annex 2 EHV charges'!$A$11:$A$260, MATCH(0, IF(ISBLANK('Annex 2 EHV charges'!$A$11:$A$260),1, COUNTIF(A$4:$A145, 'Annex 2 EHV charges'!$A$11:$A$260)), 0)),"")} | B146: =IF($A146="","",VLOOKUP($A146,'Annex 2 EHV charges'!$A:$O,2,0)) | C146: =IF($A146="","",VLOOKUP($A146,'Annex 2 EHV charges'!$A:$O,3,0)) | D146: =IF($A146="","",VLOOKUP($A146,'Annex 2 EHV charges'!$A:$O,7,0)) | E146: =IFERROR(IF(VLOOKUP($A146,'Annex 2 EHV charges'!$A:$O,8,FALSE)=0,"",VLOOKUP($A146,'Annex 2 EHV charges'!$A:$O,8,FALSE)),"") | F146: =IFERROR(IF(VLOOKUP($A146,'Annex 2 EHV charges'!$A:$O,9,FALSE)=0,"",VLOOKUP($A146,'Annex 2 EHV charges'!$A:$O,9,FALSE)),"") | G146: =IFERROR(IF(VLOOKUP($A146,'Annex 2 EHV charges'!$A:$O,10,FALSE)=0,"",VLOOKUP($A146,'Annex 2 EHV charges'!$A:$O,10,FALSE)),"") | H146: =IFERROR(IF(VLOOKUP($A146,'Annex 2 EHV charges'!$A:$O,11,FALSE)=0,"",VLOOKUP($A146,'Annex 2 EHV charges'!$A:$O,11,FALSE)),"")
A147: {=IFERROR(INDEX('Annex 2 EHV charges'!$A$11:$A$260, MATCH(0, IF(ISBLANK('Annex 2 EHV charges'!$A$11:$A$260),1, COUNTIF(A$4:$A146, 'Annex 2 EHV charges'!$A$11:$A$260)), 0)),"")} | B147: =IF($A147="","",VLOOKUP($A147,'Annex 2 EHV charges'!$A:$O,2,0)) | C147: =IF($A147="","",VLOOKUP($A147,'Annex 2 EHV charges'!$A:$O,3,0)) | D147: =IF($A147="","",VLOOKUP($A147,'Annex 2 EHV charges'!$A:$O,7,0)) | E147: =IFERROR(IF(VLOOKUP($A147,'Annex 2 EHV charges'!$A:$O,8,FALSE)=0,"",VLOOKUP($A147,'Annex 2 EHV charges'!$A:$O,8,FALSE)),"") | F147: =IFERROR(IF(VLOOKUP($A147,'Annex 2 EHV charges'!$A:$O,9,FALSE)=0,"",VLOOKUP($A147,'Annex 2 EHV charges'!$A:$O,9,FALSE)),"") | G147: =IFERROR(IF(VLOOKUP($A147,'Annex 2 EHV charges'!$A:$O,10,FALSE)=0,"",VLOOKUP($A147,'Annex 2 EHV charges'!$A:$O,10,FALSE)),"") | H147: =IFERROR(IF(VLOOKUP($A147,'Annex 2 EHV charges'!$A:$O,11,FALSE)=0,"",VLOOKUP($A147,'Annex 2 EHV charges'!$A:$O,11,FALSE)),"")
A148: {=IFERROR(INDEX('Annex 2 EHV charges'!$A$11:$A$260, MATCH(0, IF(ISBLANK('Annex 2 EHV charges'!$A$11:$A$260),1, COUNTIF(A$4:$A147, 'Annex 2 EHV charges'!$A$11:$A$260)), 0)),"")} | B148: =IF($A148="","",VLOOKUP($A148,'Annex 2 EHV charges'!$A:$O,2,0)) | C148: =IF($A148="","",VLOOKUP($A148,'Annex 2 EHV charges'!$A:$O,3,0)) | D148: =IF($A148="","",VLOOKUP($A148,'Annex 2 EHV charges'!$A:$O,7,0)) | E148: =IFERROR(IF(VLOOKUP($A148,'Annex 2 EHV charges'!$A:$O,8,FALSE)=0,"",VLOOKUP($A148,'Annex 2 EHV charges'!$A:$O,8,FALSE)),"") | F148: =IFERROR(IF(VLOOKUP($A148,'Annex 2 EHV charges'!$A:$O,9,FALSE)=0,"",VLOOKUP($A148,'Annex 2 EHV charges'!$A:$O,9,FALSE)),"") | G148: =IFERROR(IF(VLOOKUP($A148,'Annex 2 EHV charges'!$A:$O,10,FALSE)=0,"",VLOOKUP($A148,'Annex 2 EHV charges'!$A:$O,10,FALSE)),"") | H148: =IFERROR(IF(VLOOKUP($A148,'Annex 2 EHV charges'!$A:$O,11,FALSE)=0,"",VLOOKUP($A148,'Annex 2 EHV charges'!$A:$O,11,FALSE)),"")
A149: {=IFERROR(INDEX('Annex 2 EHV charges'!$A$11:$A$260, MATCH(0, IF(ISBLANK('Annex 2 EHV charges'!$A$11:$A$260),1, COUNTIF(A$4:$A148, 'Annex 2 EHV charges'!$A$11:$A$260)), 0)),"")} | B149: =IF($A149="","",VLOOKUP($A149,'Annex 2 EHV charges'!$A:$O,2,0)) | C149: =IF($A149="","",VLOOKUP($A149,'Annex 2 EHV charges'!$A:$O,3,0)) | D149: =IF($A149="","",VLOOKUP($A149,'Annex 2 EHV charges'!$A:$O,7,0)) | E149: =IFERROR(IF(VLOOKUP($A149,'Annex 2 EHV charges'!$A:$O,8,FALSE)=0,"",VLOOKUP($A149,'Annex 2 EHV charges'!$A:$O,8,FALSE)),"") | F149: =IFERROR(IF(VLOOKUP($A149,'Annex 2 EHV charges'!$A:$O,9,FALSE)=0,"",VLOOKUP($A149,'Annex 2 EHV charges'!$A:$O,9,FALSE)),"") | G149: =IFERROR(IF(VLOOKUP($A149,'Annex 2 EHV charges'!$A:$O,10,FALSE)=0,"",VLOOKUP($A149,'Annex 2 EHV charges'!$A:$O,10,FALSE)),"") | H149: =IFERROR(IF(VLOOKUP($A149,'Annex 2 EHV charges'!$A:$O,11,FALSE)=0,"",VLOOKUP($A149,'Annex 2 EHV charges'!$A:$O,11,FALSE)),"")
A150: {=IFERROR(INDEX('Annex 2 EHV charges'!$A$11:$A$260, MATCH(0, IF(ISBLANK('Annex 2 EHV charges'!$A$11:$A$260),1, COUNTIF(A$4:$A149, 'Annex 2 EHV charges'!$A$11:$A$260)), 0)),"")} | B150: =IF($A150="","",VLOOKUP($A150,'Annex 2 EHV charges'!$A:$O,2,0)) | C150: =IF($A150="","",VLOOKUP($A150,'Annex 2 EHV charges'!$A:$O,3,0)) | D150: =IF($A150="","",VLOOKUP($A150,'Annex 2 EHV charges'!$A:$O,7,0)) | E150: =IFERROR(IF(VLOOKUP($A150,'Annex 2 EHV charges'!$A:$O,8,FALSE)=0,"",VLOOKUP($A150,'Annex 2 EHV charges'!$A:$O,8,FALSE)),"") | F150: =IFERROR(IF(VLOOKUP($A150,'Annex 2 EHV charges'!$A:$O,9,FALSE)=0,"",VLOOKUP($A150,'Annex 2 EHV charges'!$A:$O,9,FALSE)),"") | G150: =IFERROR(IF(VLOOKUP($A150,'Annex 2 EHV charges'!$A:$O,10,FALSE)=0,"",VLOOKUP($A150,'Annex 2 EHV charges'!$A:$O,10,FALSE)),"") | H150: =IFERROR(IF(VLOOKUP($A150,'Annex 2 EHV charges'!$A:$O,11,FALSE)=0,"",VLOOKUP($A150,'Annex 2 EHV charges'!$A:$O,11,FALSE)),"")
A151: {=IFERROR(INDEX('Annex 2 EHV charges'!$A$11:$A$260, MATCH(0, IF(ISBLANK('Annex 2 EHV charges'!$A$11:$A$260),1, COUNTIF(A$4:$A150, 'Annex 2 EHV charges'!$A$11:$A$260)), 0)),"")} | B151: =IF($A151="","",VLOOKUP($A151,'Annex 2 EHV charges'!$A:$O,2,0)) | C151: =IF($A151="","",VLOOKUP($A151,'Annex 2 EHV charges'!$A:$O,3,0)) | D151: =IF($A151="","",VLOOKUP($A151,'Annex 2 EHV charges'!$A:$O,7,0)) | E151: =IFERROR(IF(VLOOKUP($A151,'Annex 2 EHV charges'!$A:$O,8,FALSE)=0,"",VLOOKUP($A151,'Annex 2 EHV charges'!$A:$O,8,FALSE)),"") | F151: =IFERROR(IF(VLOOKUP($A151,'Annex 2 EHV charges'!$A:$O,9,FALSE)=0,"",VLOOKUP($A151,'Annex 2 EHV charges'!$A:$O,9,FALSE)),"") | G151: =IFERROR(IF(VLOOKUP($A151,'Annex 2 EHV charges'!$A:$O,10,FALSE)=0,"",VLOOKUP($A151,'Annex 2 EHV charges'!$A:$O,10,FALSE)),"") | H151: =IFERROR(IF(VLOOKUP($A151,'Annex 2 EHV charges'!$A:$O,11,FALSE)=0,"",VLOOKUP($A151,'Annex 2 EHV charges'!$A:$O,11,FALSE)),"")
A152: {=IFERROR(INDEX('Annex 2 EHV charges'!$A$11:$A$260, MATCH(0, IF(ISBLANK('Annex 2 EHV charges'!$A$11:$A$260),1, COUNTIF(A$4:$A151, 'Annex 2 EHV charges'!$A$11:$A$260)), 0)),"")} | B152: =IF($A152="","",VLOOKUP($A152,'Annex 2 EHV charges'!$A:$O,2,0)) | C152: =IF($A152="","",VLOOKUP($A152,'Annex 2 EHV charges'!$A:$O,3,0)) | D152: =IF($A152="","",VLOOKUP($A152,'Annex 2 EHV charges'!$A:$O,7,0)) | E152: =IFERROR(IF(VLOOKUP($A152,'Annex 2 EHV charges'!$A:$O,8,FALSE)=0,"",VLOOKUP($A152,'Annex 2 EHV charges'!$A:$O,8,FALSE)),"") | F152: =IFERROR(IF(VLOOKUP($A152,'Annex 2 EHV charges'!$A:$O,9,FALSE)=0,"",VLOOKUP($A152,'Annex 2 EHV charges'!$A:$O,9,FALSE)),"") | G152: =IFERROR(IF(VLOOKUP($A152,'Annex 2 EHV charges'!$A:$O,10,FALSE)=0,"",VLOOKUP($A152,'Annex 2 EHV charges'!$A:$O,10,FALSE)),"") | H152: =IFERROR(IF(VLOOKUP($A152,'Annex 2 EHV charges'!$A:$O,11,FALSE)=0,"",VLOOKUP($A152,'Annex 2 EHV charges'!$A:$O,11,FALSE)),"")
A153: {=IFERROR(INDEX('Annex 2 EHV charges'!$A$11:$A$260, MATCH(0, IF(ISBLANK('Annex 2 EHV charges'!$A$11:$A$260),1, COUNTIF(A$4:$A152, 'Annex 2 EHV charges'!$A$11:$A$260)), 0)),"")} | B153: =IF($A153="","",VLOOKUP($A153,'Annex 2 EHV charges'!$A:$O,2,0)) | C153: =IF($A153="","",VLOOKUP($A153,'Annex 2 EHV charges'!$A:$O,3,0)) | D153: =IF($A153="","",VLOOKUP($A153,'Annex 2 EHV charges'!$A:$O,7,0)) | E153: =IFERROR(IF(VLOOKUP($A153,'Annex 2 EHV charges'!$A:$O,8,FALSE)=0,"",VLOOKUP($A153,'Annex 2 EHV charges'!$A:$O,8,FALSE)),"") | F153: =IFERROR(IF(VLOOKUP($A153,'Annex 2 EHV charges'!$A:$O,9,FALSE)=0,"",VLOOKUP($A153,'Annex 2 EHV charges'!$A:$O,9,FALSE)),"") | G153: =IFERROR(IF(VLOOKUP($A153,'Annex 2 EHV charges'!$A:$O,10,FALSE)=0,"",VLOOKUP($A153,'Annex 2 EHV charges'!$A:$O,10,FALSE)),"") | H153: =IFERROR(IF(VLOOKUP($A153,'Annex 2 EHV charges'!$A:$O,11,FALSE)=0,"",VLOOKUP($A153,'Annex 2 EHV charges'!$A:$O,11,FALSE)),"")
A154: {=IFERROR(INDEX('Annex 2 EHV charges'!$A$11:$A$260, MATCH(0, IF(ISBLANK('Annex 2 EHV charges'!$A$11:$A$260),1, COUNTIF(A$4:$A153, 'Annex 2 EHV charges'!$A$11:$A$260)), 0)),"")} | B154: =IF($A154="","",VLOOKUP($A154,'Annex 2 EHV charges'!$A:$O,2,0)) | C154: =IF($A154="","",VLOOKUP($A154,'Annex 2 EHV charges'!$A:$O,3,0)) | D154: =IF($A154="","",VLOOKUP($A154,'Annex 2 EHV charges'!$A:$O,7,0)) | E154: =IFERROR(IF(VLOOKUP($A154,'Annex 2 EHV charges'!$A:$O,8,FALSE)=0,"",VLOOKUP($A154,'Annex 2 EHV charges'!$A:$O,8,FALSE)),"") | F154: =IFERROR(IF(VLOOKUP($A154,'Annex 2 EHV charges'!$A:$O,9,FALSE)=0,"",VLOOKUP($A154,'Annex 2 EHV charges'!$A:$O,9,FALSE)),"") | G154: =IFERROR(IF(VLOOKUP($A154,'Annex 2 EHV charges'!$A:$O,10,FALSE)=0,"",VLOOKUP($A154,'Annex 2 EHV charges'!$A:$O,10,FALSE)),"") | H154: =IFERROR(IF(VLOOKUP($A154,'Annex 2 EHV charges'!$A:$O,11,FALSE)=0,"",VLOOKUP($A154,'Annex 2 EHV charges'!$A:$O,11,FALSE)),"")
... A254: {=IFERROR(INDEX('Annex 2 EHV charges'!$A$11:$A$260, MATCH(0, IF(ISBLANK('Annex 2 EHV charges'!$A$11:$A$260),1, COUNTIF(A$4:$A253, 'Annex 2 EHV charges'!$A$11:$A$260)), 0)),"")} | B254: =IF($A254="","",VLOOKUP($A254,'Annex 2 EHV charges'!$A:$O,2,0)) | C254: =IF($A254="","",VLOOKUP($A254,'Annex 2 EHV charges'!$A:$O,3,0)) | D254: =IF($A254="","",VLOOKUP($A254,'Annex 2 EHV charges'!$A:$O,7,0)) | E254: =IFERROR(IF(VLOOKUP($A254,'Annex 2 EHV charges'!$A:$O,8,FALSE)=0,"",VLOOKUP($A254,'Annex 2 EHV charges'!$A:$O,8,FALSE)),"") | F254: =IFERROR(IF(VLOOKUP($A254,'Annex 2 EHV charges'!$A:$O,9,FALSE)=0,"",VLOOKUP($A254,'Annex 2 EHV charges'!$A:$O,9,FALSE)),"") | G254: =IFERROR(IF(VLOOKUP($A254,'Annex 2 EHV charges'!$A:$O,10,FALSE)=0,"",VLOOKUP($A254,'Annex 2 EHV charges'!$A:$O,10,FALSE)),"") | H254: =IFERROR(IF(VLOOKUP($A254,'Annex 2 EHV charges'!$A:$O,11,FALSE)=0,"",VLOOKUP($A254,'Annex 2 EHV charges'!$A:$O,11,FALSE)),"")

Sheet Annex 2b Export
A1: Note: The list of MPANs / MSIDs provided may be incomplete; the DNO reserves the right to apply the listed charges to any other MPANs / MSIDs associated with the site. Note: This table is automatically populated based on the content of the tab entitled 'Annex 2 EHV Charges'. The timebands are as shown in Annex 2.
A2: =Overview!B4& " - Effective from "&Overview!D4&" - "&Overview!E4&" EDCM export charges" -> SP Distribution - Effective from 1 April 2022 - Final EDCM export charges
A4: Export Unique Identifier | B4: LLFC | C4: Export MPANs/MSIDs | D4: Name | E4: ='Annex 2 EHV charges'!L10 -> Export Super Red unit charge (p/kWh) | F4: ='Annex 2 EHV charges'!M10 -> Export fixed charge (p/day) | G4: ='Annex 2 EHV charges'!N10 -> Export capacity charge (p/kVA/day) | H4: ='Annex 2 EHV charges'!O10 -> Export exceeded capacity charge (p/kVA/day)
A5: {=IFERROR(INDEX('Annex 2 EHV charges'!$D$11:$D$260, MATCH(0, IF(ISBLANK('Annex 2 EHV charges'!$D$11:$D$260),1, COUNTIF(A$4:$A4, 'Annex 2 EHV charges'!$D$11:$D$260)), 0)),"")} -> 644 | B5: =IF($A5="","",VLOOKUP($A5,'Annex 2 EHV charges'!$D:$O,2,0)) -> 644 | C5: =IF($A5="","",VLOOKUP($A5,'Annex 2 EHV charges'!$D:$O,3,0)) -> 1800060775990 | D5: =IF($A5="","",VLOOKUP($A5,'Annex 2 EHV charges'!$D:$O,4,0)) -> Rhodders | E5: =IFERROR(IF(VLOOKUP($A5,'Annex 2 EHV charges'!$D:$O,9,FALSE)=0,"",VLOOKUP($A5,'Annex 2 EHV charges'!$D:$O,9,FALSE)),"") -> - | F5: =IFERROR(IF(VLOOKUP($A5,'Annex 2 EHV charges'!$D:$O,10,FALSE)=0,"",VLOOKUP($A5,'Annex 2 EHV charges'!$D:$O,10,FALSE)),"") -> 5687.62 | G5: =IFERROR(IF(VLOOKUP($A5,'Annex 2 EHV charges'!$D:$O,11,FALSE)=0,"",VLOOKUP($A5,'Annex 2 EHV charges'!$D:$O,11,FALSE)),"") -> 0.05 | H5: =IFERROR(IF(VLOOKUP($A5,'Annex 2 EHV charges'!$D:$O,12,FALSE)=0,"",VLOOKUP($A5,'Annex 2 EHV charges'!$D:$O,12,FALSE)),"") -> 0.05 | I5: =IF(VLOOKUP(C5,'Annex 2 EHV charges'!$F$11:$P$157,11,FALSE)<=5,"",VLOOKUP(C5,'Annex 2 EHV charges'!$F$11:$P$157,11,FALSE))
A6: {=IFERROR(INDEX('Annex 2 EHV charges'!$D$11:$D$260, MATCH(0, IF(ISBLANK('Annex 2 EHV charges'!$D$11:$D$260),1, COUNTIF(A$4:$A5, 'Annex 2 EHV charges'!$D$11:$D$260)), 0)),"")} -> MSID 8182 | B6: =IF($A6="","",VLOOKUP($A6,'Annex 2 EHV charges'!$D:$O,2,0)) -> MSID 8182 | C6: =IF($A6="","",VLOOKUP($A6,'Annex 2 EHV charges'!$D:$O,3,0)) -> MSID 8182 | D6: =IF($A6="","",VLOOKUP($A6,'Annex 2 EHV charges'!$D:$O,4,0)) -> Minsca | E6: =IFERROR(IF(VLOOKUP($A6,'Annex 2 EHV charges'!$D:$O,9,FALSE)=0,"",VLOOKUP($A6,'Annex 2 EHV charges'!$D:$O,9,FALSE)),"") -> - | F6: =IFERROR(IF(VLOOKUP($A6,'Annex 2 EHV charges'!$D:$O,10,FALSE)=0,"",VLOOKUP($A6,'Annex 2 EHV charges'!$D:$O,10,FALSE)),"") -> - | G6: =IFERROR(IF(VLOOKUP($A6,'Annex 2 EHV charges'!$D:$O,11,FALSE)=0,"",VLOOKUP($A6,'Annex 2 EHV charges'!$D:$O,11,FALSE)),"") -> - | H6: =IFERROR(IF(VLOOKUP($A6,'Annex 2 EHV charges'!$D:$O,12,FALSE)=0,"",VLOOKUP($A6,'Annex 2 EHV charges'!$D:$O,12,FALSE)),"") -> - | I6: =IF(VLOOKUP(C6,'Annex 2 EHV charges'!$F$11:$P$157,11,FALSE)<=5,"",VLOOKUP(C6,'Annex 2 EHV charges'!$F$11:$P$157,11,FALSE))
A7: {=IFERROR(INDEX('Annex 2 EHV charges'!$D$11:$D$260, MATCH(0, IF(ISBLANK('Annex 2 EHV charges'!$D$11:$D$260),1, COUNTIF(A$4:$A6, 'Annex 2 EHV charges'!$D$11:$D$260)), 0)),"")} -> 683 | B7: =IF($A7="","",VLOOKUP($A7,'Annex 2 EHV charges'!$D:$O,2,0)) -> 683 | C7: =IF($A7="","",VLOOKUP($A7,'Annex 2 EHV charges'!$D:$O,3,0)) -> 1800060539971 | D7: =IF($A7="","",VLOOKUP($A7,'Annex 2 EHV charges'!$D:$O,4,0)) -> Bankend Rig | E7: =IFERROR(IF(VLOOKUP($A7,'Annex 2 EHV charges'!$D:$O,9,FALSE)=0,"",VLOOKUP($A7,'Annex 2 EHV charges'!$D:$O,9,FALSE)),"") -> - | F7: =IFERROR(IF(VLOOKUP($A7,'Annex 2 EHV charges'!$D:$O,10,FALSE)=0,"",VLOOKUP($A7,'Annex 2 EHV charges'!$D:$O,10,FALSE)),"") -> 4944.09 | G7: =IFERROR(IF(VLOOKUP($A7,'Annex 2 EHV charges'!$D:$O,11,FALSE)=0,"",VLOOKUP($A7,'Annex 2 EHV charges'!$D:$O,11,FALSE)),"") -> 0.05 | H7: =IFERROR(IF(VLOOKUP($A7,'Annex 2 EHV charges'!$D:$O,12,FALSE)=0,"",VLOOKUP($A7,'Annex 2 EHV charges'!$D:$O,12,FALSE)),"") -> 0.05 | I7: =IF(VLOOKUP(C7,'Annex 2 EHV charges'!$F$11:$P$157,11,FALSE)<=5,"",VLOOKUP(C7,'Annex 2 EHV charges'!$F$11:$P$157,11,FALSE))
A8: {=IFERROR(INDEX('Annex 2 EHV charges'!$D$11:$D$260, MATCH(0, IF(ISBLANK('Annex 2 EHV charges'!$D$11:$D$260),1, COUNTIF(A$4:$A7, 'Annex 2 EHV charges'!$D$11:$D$260)), 0)),"")} -> 684 | B8: =IF($A8="","",VLOOKUP($A8,'Annex 2 EHV charges'!$D:$O,2,0)) -> 684 | C8: =IF($A8="","",VLOOKUP($A8,'Annex 2 EHV charges'!$D:$O,3,0)) -> 1800060532717 | D8: =IF($A8="","",VLOOKUP($A8,'Annex 2 EHV charges'!$D:$O,4,0)) -> Barlockhart Moor | E8: =IFERROR(IF(VLOOKUP($A8,'Annex 2 EHV charges'!$D:$O,9,FALSE)=0,"",VLOOKUP($A8,'Annex 2 EHV charges'!$D:$O,9,FALSE)),"") -> - | F8: =IFERROR(IF(VLOOKUP($A8,'Annex 2 EHV charges'!$D:$O,10,FALSE)=0,"",VLOOKUP($A8,'Annex 2 EHV charges'!$D:$O,10,FALSE)),"") -> 8983 | G8: =IFERROR(IF(VLOOKUP($A8,'Annex 2 EHV charges'!$D:$O,11,FALSE)=0,"",VLOOKUP($A8,'Annex 2 EHV charges'!$D:$O,11,FALSE)),"") -> 0.05 | H8: =IFERROR(IF(VLOOKUP($A8,'Annex 2 EHV charges'!$D:$O,12,FALSE)=0,"",VLOOKUP($A8,'Annex 2 EHV charges'!$D:$O,12,FALSE)),"") -> 0.05 | I8: =IF(VLOOKUP(C8,'Annex 2 EHV charges'!$F$11:$P$157,11,FALSE)<=5,"",VLOOKUP(C8,'Annex 2 EHV charges'!$F$11:$P$157,11,FALSE))
A9: {=IFERROR(INDEX('Annex 2 EHV charges'!$D$11:$D$260, MATCH(0, IF(ISBLANK('Annex 2 EHV charges'!$D$11:$D$260),1, COUNTIF(A$4:$A8, 'Annex 2 EHV charges'!$D$11:$D$260)), 0)),"")} -> 685 | B9: =IF($A9="","",VLOOKUP($A9,'Annex 2 EHV charges'!$D:$O,2,0)) -> 685 | C9: =IF($A9="","",VLOOKUP($A9,'Annex 2 EHV charges'!$D:$O,3,0)) -> 1800060532735 | D9: =IF($A9="","",VLOOKUP($A9,'Annex 2 EHV charges'!$D:$O,4,0)) -> Blantyre Muir | E9: =IFERROR(IF(VLOOKUP($A9,'Annex 2 EHV charges'!$D:$O,9,FALSE)=0,"",VLOOKUP($A9,'Annex 2 EHV charges'!$D:$O,9,FALSE)),"") -> - | F9: =IFERROR(IF(VLOOKUP($A9,'Annex 2 EHV charges'!$D:$O,10,FALSE)=0,"",VLOOKUP($A9,'Annex 2 EHV charges'!$D:$O,10,FALSE)),"") -> 5840.28 | G9: =IFERROR(IF(VLOOKUP($A9,'Annex 2 EHV charges'!$D:$O,11,FALSE)=0,"",VLOOKUP($A9,'Annex 2 EHV charges'!$D:$O,11,FALSE)),"") -> 0.05 | H9: =IFERROR(IF(VLOOKUP($A9,'Annex 2 EHV charges'!$D:$O,12,FALSE)=0,"",VLOOKUP($A9,'Annex 2 EHV charges'!$D:$O,12,FALSE)),"") -> 0.05 | I9: =IF(VLOOKUP(C9,'Annex 2 EHV charges'!$F$11:$P$157,11,FALSE)<=5,"",VLOOKUP(C9,'Annex 2 EHV charges'!$F$11:$P$157,11,FALSE))
A10: {=IFERROR(INDEX('Annex 2 EHV charges'!$D$11:$D$260, MATCH(0, IF(ISBLANK('Annex 2 EHV charges'!$D$11:$D$260),1, COUNTIF(A$4:$A9, 'Annex 2 EHV charges'!$D$11:$D$260)), 0)),"")} -> 693 | B10: =IF($A10="","",VLOOKUP($A10,'Annex 2 EHV charges'!$D:$O,2,0)) -> 693 | C10: =IF($A10="","",VLOOKUP($A10,'Annex 2 EHV charges'!$D:$O,3,0)) -> 1800060587869 | D10: =IF($A10="","",VLOOKUP($A10,'Annex 2 EHV charges'!$D:$O,4,0)) -> Hunterston WF | E10: =IFERROR(IF(VLOOKUP($A10,'Annex 2 EHV charges'!$D:$O,9,FALSE)=0,"",VLOOKUP($A10,'Annex 2 EHV charges'!$D:$O,9,FALSE)),"") -> - | F10: =IFERROR(IF(VLOOKUP($A10,'Annex 2 EHV charges'!$D:$O,10,FALSE)=0,"",VLOOKUP($A10,'Annex 2 EHV charges'!$D:$O,10,FALSE)),"") -> - | G10: =IFERROR(IF(VLOOKUP($A10,'Annex 2 EHV charges'!$D:$O,11,FALSE)=0,"",VLOOKUP($A10,'Annex 2 EHV charges'!$D:$O,11,FALSE)),"") -> - | H10: =IFERROR(IF(VLOOKUP($A10,'Annex 2 EHV charges'!$D:$O,12,FALSE)=0,"",VLOOKUP($A10,'Annex 2 EHV charges'!$D:$O,12,FALSE)),"") -> - | I10: =IF(VLOOKUP(C10,'Annex 2 EHV charges'!$F$11:$P$157,11,FALSE)<=5,"",VLOOKUP(C10,'Annex 2 EHV charges'!$F$11:$P$157,11,FALSE))
A11: {=IFERROR(INDEX('Annex 2 EHV charges'!$D$11:$D$260, MATCH(0, IF(ISBLANK('Annex 2 EHV charges'!$D$11:$D$260),1, COUNTIF(A$4:$A10, 'Annex 2 EHV charges'!$D$11:$D$260)), 0)),"")} -> 688 | B11: =IF($A11="","",VLOOKUP($A11,'Annex 2 EHV charges'!$D:$O,2,0)) -> 688 | C11: =IF($A11="","",VLOOKUP($A11,'Annex 2 EHV charges'!$D:$O,3,0)) -> 1800060532656 | D11: =IF($A11="","",VLOOKUP($A11,'Annex 2 EHV charges'!$D:$O,4,0)) -> Middleton Farm | E11: =IFERROR(IF(VLOOKUP($A11,'Annex 2 EHV charges'!$D:$O,9,FALSE)=0,"",VLOOKUP($A11,'Annex 2 EHV charges'!$D:$O,9,FALSE)),"") -> - | F11: =IFERROR(IF(VLOOKUP($A11,'Annex 2 EHV charges'!$D:$O,10,FALSE)=0,"",VLOOKUP($A11,'Annex 2 EHV charges'!$D:$O,10,FALSE)),"") -> 5222.16 | G11: =IFERROR(IF(VLOOKUP($A11,'Annex 2 EHV charges'!$D:$O,11,FALSE)=0,"",VLOOKUP($A11,'Annex 2 EHV charges'!$D:$O,11,FALSE)),"") -> 0.05 | H11: =IFERROR(IF(VLOOKUP($A11,'Annex 2 EHV charges'!$D:$O,12,FALSE)=0,"",VLOOKUP($A11,'Annex 2 EHV charges'!$D:$O,12,FALSE)),"") -> 0.05 | I11: =IF(VLOOKUP(C11,'Annex 2 EHV charges'!$F$11:$P$157,11,FALSE)<=5,"",VLOOKUP(C11,'Annex 2 EHV charges'!$F$11:$P$157,11,FALSE))
A12: {=IFERROR(INDEX('Annex 2 EHV charges'!$D$11:$D$260, MATCH(0, IF(ISBLANK('Annex 2 EHV charges'!$D$11:$D$260),1, COUNTIF(A$4:$A11, 'Annex 2 EHV charges'!$D$11:$D$260)), 0)),"")} -> 689 | B12: =IF($A12="","",VLOOKUP($A12,'Annex 2 EHV charges'!$D:$O,2,0)) -> 689 | C12: =IF($A12="","",VLOOKUP($A12,'Annex 2 EHV charges'!$D:$O,3,0)) -> 1800060532674 | D12: =IF($A12="","",VLOOKUP($A12,'Annex 2 EHV charges'!$D:$O,4,0)) -> Neilston Community | E12: =IFERROR(IF(VLOOKUP($A12,'Annex 2 EHV charges'!$D:$O,9,FALSE)=0,"",VLOOKUP($A12,'Annex 2 EHV charges'!$D:$O,9,FALSE)),"") -> - | F12: =IFERROR(IF(VLOOKUP($A12,'Annex 2 EHV charges'!$D:$O,10,FALSE)=0,"",VLOOKUP($A12,'Annex 2 EHV charges'!$D:$O,10,FALSE)),"") -> 6406.7 | G12: =IFERROR(IF(VLOOKUP($A12,'Annex 2 EHV charges'!$D:$O,11,FALSE)=0,"",VLOOKUP($A12,'Annex 2 EHV charges'!$D:$O,11,FALSE)),"") -> 0.05 | H12: =IFERROR(IF(VLOOKUP($A12,'Annex 2 EHV charges'!$D:$O,12,FALSE)=0,"",VLOOKUP($A12,'Annex 2 EHV charges'!$D:$O,12,FALSE)),"") -> 0.05 | I12: =IF(VLOOKUP(C12,'Annex 2 EHV charges'!$F$11:$P$157,11,FALSE)<=5,"",VLOOKUP(C12,'Annex 2 EHV charges'!$F$11:$P$157,11,FALSE))
A13: {=IFERROR(INDEX('Annex 2 EHV charges'!$D$11:$D$260, MATCH(0, IF(ISBLANK('Annex 2 EHV charges'!$D$11:$D$260),1, COUNTIF(A$4:$A12, 'Annex 2 EHV charges'!$D$11:$D$260)), 0)),"")} -> 681 | B13: =IF($A13="","",VLOOKUP($A13,'Annex 2 EHV charges'!$D:$O,2,0)) -> 681 | C13: =IF($A13="","",VLOOKUP($A13,'Annex 2 EHV charges'!$D:$O,3,0)) -> 1800053653880 | D13: =IF($A13="","",VLOOKUP($A13,'Annex 2 EHV charges'!$D:$O,4,0)) -> Garlaff Landfill | E13: =IFERROR(IF(VLOOKUP($A13,'Annex 2 EHV charges'!$D:$O,9,FALSE)=0,"",VLOOKUP($A13,'Annex 2 EHV charges'!$D:$O,9,FALSE)),"") -> - | F13: =IFERROR(IF(VLOOKUP($A13,'Annex 2 EHV charges'!$D:$O,10,FALSE)=0,"",VLOOKUP($A13,'Annex 2 EHV charges'!$D:$O,10,FALSE)),"") -> - | G13: =IFERROR(IF(VLOOKUP($A13,'Annex 2 EHV charges'!$D:$O,11,FALSE)=0,"",VLOOKUP($A13,'Annex 2 EHV charges'!$D:$O,11,FALSE)),"") -> - | H13: =IFERROR(IF(VLOOKUP($A13,'Annex 2 EHV charges'!$D:$O,12,FALSE)=0,"",VLOOKUP($A13,'Annex 2 EHV charges'!$D:$O,12,FALSE)),"") -> - | I13: =IF(VLOOKUP(C13,'Annex 2 EHV charges'!$F$11:$P$157,11,FALSE)<=5,"",VLOOKUP(C13,'Annex 2 EHV charges'!$F$11:$P$157,11,FALSE))
A14: {=IFERROR(INDEX('Annex 2 EHV charges'!$D$11:$D$260, MATCH(0, IF(ISBLANK('Annex 2 EHV charges'!$D$11:$D$260),1, COUNTIF(A$4:$A13, 'Annex 2 EHV charges'!$D$11:$D$260)), 0)),"")} -> 629 | B14: =IF($A14="","",VLOOKUP($A14,'Annex 2 EHV charges'!$D:$O,2,0)) -> 629 | C14: =IF($A14="","",VLOOKUP($A14,'Annex 2 EHV charges'!$D:$O,3,0)) -> 1800054992977 | D14: =IF($A14="","",VLOOKUP($A14,'Annex 2 EHV charges'!$D:$O,4,0)) -> Hagshaw Hill Extension | E14: =IFERROR(IF(VLOOKUP($A14,'Annex 2 EHV charges'!$D:$O,9,FALSE)=0,"",VLOOKUP($A14,'Annex 2 EHV charges'!$D:$O,9,FALSE)),"") -> - | F14: =IFERROR(IF(VLOOKUP($A14,'Annex 2 EHV charges'!$D:$O,10,FALSE)=0,"",VLOOKUP($A14,'Annex 2 EHV charges'!$D:$O,10,FALSE)),"") -> 18154.96 | G14: =IFERROR(IF(VLOOKUP($A14,'Annex 2 EHV charges'!$D:$O,11,FALSE)=0,"",VLOOKUP($A14,'Annex 2 EHV charges'!$D:$O,11,FALSE)),"") -> 0.05 | H14: =IFERROR(IF(VLOOKUP($A14,'Annex 2 EHV charges'!$D:$O,12,FALSE)=0,"",VLOOKUP($A14,'Annex 2 EHV charges'!$D:$O,12,FALSE)),"") -> 0.05 | I14: =IF(VLOOKUP(C14,'Annex 2 EHV charges'!$F$11:$P$157,11,FALSE)<=5,"",VLOOKUP(C14,'Annex 2 EHV charges'!$F$11:$P$157,11,FALSE))
A15: {=IFERROR(INDEX('Annex 2 EHV charges'!$D$11:$D$260, MATCH(0, IF(ISBLANK('Annex 2 EHV charges'!$D$11:$D$260),1, COUNTIF(A$4:$A14, 'Annex 2 EHV charges'!$D$11:$D$260)), 0)),"")} -> 671 | B15: =IF($A15="","",VLOOKUP($A15,'Annex 2 EHV charges'!$D:$O,2,0)) -> 671 | C15: =IF($A15="","",VLOOKUP($A15,'Annex 2 EHV charges'!$D:$O,3,0)) -> 1800060328044 | D15: =IF($A15="","",VLOOKUP($A15,'Annex 2 EHV charges'!$D:$O,4,0)) -> Muirhall | E15: =IFERROR(IF(VLOOKUP($A15,'Annex 2 EHV charges'!$D:$O,9,FALSE)=0,"",VLOOKUP($A15,'Annex 2 EHV charges'!$D:$O,9,FALSE)),"") -> - | F15: =IFERROR(IF(VLOOKUP($A15,'Annex 2 EHV charges'!$D:$O,10,FALSE)=0,"",VLOOKUP($A15,'Annex 2 EHV charges'!$D:$O,10,FALSE)),"") -> 8204.45 | G15: =IFERROR(IF(VLOOKUP($A15,'Annex 2 EHV charges'!$D:$O,11,FALSE)=0,"",VLOOKUP($A15,'Annex 2 EHV charges'!$D:$O,11,FALSE)),"") -> 0.05 | H15: =IFERROR(IF(VLOOKUP($A15,'Annex 2 EHV charges'!$D:$O,12,FALSE)=0,"",VLOOKUP($A15,'Annex 2 EHV charges'!$D:$O,12,FALSE)),"") -> 0.05 | I15: =IF(VLOOKUP(C15,'Annex 2 EHV charges'!$F$11:$P$157,11,FALSE)<=5,"",VLOOKUP(C15,'Annex 2 EHV charges'!$F$11:$P$157,11,FALSE))
A16: {=IFERROR(INDEX('Annex 2 EHV charges'!$D$11:$D$260, MATCH(0, IF(ISBLANK('Annex 2 EHV charges'!$D$11:$D$260),1, COUNTIF(A$4:$A15, 'Annex 2 EHV charges'!$D$11:$D$260)), 0)),"")} -> 672 | B16: =IF($A16="","",VLOOKUP($A16,'Annex 2 EHV charges'!$D:$O,2,0)) -> 672 | C16: =IF($A16="","",VLOOKUP($A16,'Annex 2 EHV charges'!$D:$O,3,0)) -> 1800060372122 | D16: =IF($A16="","",VLOOKUP($A16,'Annex 2 EHV charges'!$D:$O,4,0)) -> Burnfoot | E16: =IFERROR(IF(VLOOKUP($A16,'Annex 2 EHV charges'!$D:$O,9,FALSE)=0,"",VLOOKUP($A16,'Annex 2 EHV charges'!$D:$O,9,FALSE)),"") -> - | F16: =IFERROR(IF(VLOOKUP($A16,'Annex 2 EHV charges'!$D:$O,10,FALSE)=0,"",VLOOKUP($A16,'Annex 2 EHV charges'!$D:$O,10,FALSE)),"") -> 8017.86 | G16: =IFERROR(IF(VLOOKUP($A16,'Annex 2 EHV charges'!$D:$O,11,FALSE)=0,"",VLOOKUP($A16,'Annex 2 EHV charges'!$D:$O,11,FALSE)),"") -> 0.05 | H16: =IFERROR(IF(VLOOKUP($A16,'Annex 2 EHV charges'!$D:$O,12,FALSE)=0,"",VLOOKUP($A16,'Annex 2 EHV charges'!$D:$O,12,FALSE)),"") -> 0.05 | I16: =IF(VLOOKUP(C16,'Annex 2 EHV charges'!$F$11:$P$157,11,FALSE)<=5,"",VLOOKUP(C16,'Annex 2 EHV charges'!$F$11:$P$157,11,FALSE))
... A115: {=IFERROR(INDEX('Annex 2 EHV charges'!$D$11:$D$260, MATCH(0, IF(ISBLANK('Annex 2 EHV charges'!$D$11:$D$260),1, COUNTIF(A$4:$A114, 'Annex 2 EHV charges'!$D$11:$D$260)), 0)),"")} | B115: =IF($A115="","",VLOOKUP($A115,'Annex 2 EHV charges'!$D:$O,2,0)) | C115: =IF($A115="","",VLOOKUP($A115,'Annex 2 EHV charges'!$D:$O,3,0)) | D115: =IF($A115="","",VLOOKUP($A115,'Annex 2 EHV charges'!$D:$O,4,0)) | E115: =IFERROR(IF(VLOOKUP($A115,'Annex 2 EHV charges'!$D:$O,9,FALSE)=0,"",VLOOKUP($A115,'Annex 2 EHV charges'!$D:$O,9,FALSE)),"") | F115: =IFERROR(IF(VLOOKUP($A115,'Annex 2 EHV charges'!$D:$O,10,FALSE)=0,"",VLOOKUP($A115,'Annex 2 EHV charges'!$D:$O,10,FALSE)),"") | G115: =IFERROR(IF(VLOOKUP($A115,'Annex 2 EHV charges'!$D:$O,11,FALSE)=0,"",VLOOKUP($A115,'Annex 2 EHV charges'!$D:$O,11,FALSE)),"") | H115: =IFERROR(IF(VLOOKUP($A115,'Annex 2 EHV charges'!$D:$O,12,FALSE)=0,"",VLOOKUP($A115,'Annex 2 EHV charges'!$D:$O,12,FALSE)),"") | I115: =IF(VLOOKUP(C115,'Annex 2 EHV charges'!$F$11:$P$157,11,FALSE)<=5,"",VLOOKUP(C115,'Annex 2 EHV charges'!$F$11:$P$157,11,FALSE))
A116: {=IFERROR(INDEX('Annex 2 EHV charges'!$D$11:$D$260, MATCH(0, IF(ISBLANK('Annex 2 EHV charges'!$D$11:$D$260),1, COUNTIF(A$4:$A115, 'Annex 2 EHV charges'!$D$11:$D$260)), 0)),"")} | B116: =IF($A116="","",VLOOKUP($A116,'Annex 2 EHV charges'!$D:$O,2,0)) | C116: =IF($A116="","",VLOOKUP($A116,'Annex 2 EHV charges'!$D:$O,3,0)) | D116: =IF($A116="","",VLOOKUP($A116,'Annex 2 EHV charges'!$D:$O,4,0)) | E116: =IFERROR(IF(VLOOKUP($A116,'Annex 2 EHV charges'!$D:$O,9,FALSE)=0,"",VLOOKUP($A116,'Annex 2 EHV charges'!$D:$O,9,FALSE)),"") | F116: =IFERROR(IF(VLOOKUP($A116,'Annex 2 EHV charges'!$D:$O,10,FALSE)=0,"",VLOOKUP($A116,'Annex 2 EHV charges'!$D:$O,10,FALSE)),"") | G116: =IFERROR(IF(VLOOKUP($A116,'Annex 2 EHV charges'!$D:$O,11,FALSE)=0,"",VLOOKUP($A116,'Annex 2 EHV charges'!$D:$O,11,FALSE)),"") | H116: =IFERROR(IF(VLOOKUP($A116,'Annex 2 EHV charges'!$D:$O,12,FALSE)=0,"",VLOOKUP($A116,'Annex 2 EHV charges'!$D:$O,12,FALSE)),"")
A117: {=IFERROR(INDEX('Annex 2 EHV charges'!$D$11:$D$260, MATCH(0, IF(ISBLANK('Annex 2 EHV charges'!$D$11:$D$260),1, COUNTIF(A$4:$A116, 'Annex 2 EHV charges'!$D$11:$D$260)), 0)),"")} | B117: =IF($A117="","",VLOOKUP($A117,'Annex 2 EHV charges'!$D:$O,2,0)) | C117: =IF($A117="","",VLOOKUP($A117,'Annex 2 EHV charges'!$D:$O,3,0)) | D117: =IF($A117="","",VLOOKUP($A117,'Annex 2 EHV charges'!$D:$O,4,0)) | E117: =IFERROR(IF(VLOOKUP($A117,'Annex 2 EHV charges'!$D:$O,9,FALSE)=0,"",VLOOKUP($A117,'Annex 2 EHV charges'!$D:$O,9,FALSE)),"") | F117: =IFERROR(IF(VLOOKUP($A117,'Annex 2 EHV charges'!$D:$O,10,FALSE)=0,"",VLOOKUP($A117,'Annex 2 EHV charges'!$D:$O,10,FALSE)),"") | G117: =IFERROR(IF(VLOOKUP($A117,'Annex 2 EHV charges'!$D:$O,11,FALSE)=0,"",VLOOKUP($A117,'Annex 2 EHV charges'!$D:$O,11,FALSE)),"") | H117: =IFERROR(IF(VLOOKUP($A117,'Annex 2 EHV charges'!$D:$O,12,FALSE)=0,"",VLOOKUP($A117,'Annex 2 EHV charges'!$D:$O,12,FALSE)),"")
A118: {=IFERROR(INDEX('Annex 2 EHV charges'!$D$11:$D$260, MATCH(0, IF(ISBLANK('Annex 2 EHV charges'!$D$11:$D$260),1, COUNTIF(A$4:$A117, 'Annex 2 EHV charges'!$D$11:$D$260)), 0)),"")} | B118: =IF($A118="","",VLOOKUP($A118,'Annex 2 EHV charges'!$D:$O,2,0)) | C118: =IF($A118="","",VLOOKUP($A118,'Annex 2 EHV charges'!$D:$O,3,0)) | D118: =IF($A118="","",VLOOKUP($A118,'Annex 2 EHV charges'!$D:$O,4,0)) | E118: =IFERROR(IF(VLOOKUP($A118,'Annex 2 EHV charges'!$D:$O,9,FALSE)=0,"",VLOOKUP($A118,'Annex 2 EHV charges'!$D:$O,9,FALSE)),"") | F118: =IFERROR(IF(VLOOKUP($A118,'Annex 2 EHV charges'!$D:$O,10,FALSE)=0,"",VLOOKUP($A118,'Annex 2 EHV charges'!$D:$O,10,FALSE)),"") | G118: =IFERROR(IF(VLOOKUP($A118,'Annex 2 EHV charges'!$D:$O,11,FALSE)=0,"",VLOOKUP($A118,'Annex 2 EHV charges'!$D:$O,11,FALSE)),"") | H118: =IFERROR(IF(VLOOKUP($A118,'Annex 2 EHV charges'!$D:$O,12,FALSE)=0,"",VLOOKUP($A118,'Annex 2 EHV charges'!$D:$O,12,FALSE)),"")
A119: {=IFERROR(INDEX('Annex 2 EHV charges'!$D$11:$D$260, MATCH(0, IF(ISBLANK('Annex 2 EHV charges'!$D$11:$D$260),1, COUNTIF(A$4:$A118, 'Annex 2 EHV charges'!$D$11:$D$260)), 0)),"")} | B119: =IF($A119="","",VLOOKUP($A119,'Annex 2 EHV charges'!$D:$O,2,0)) | C119: =IF($A119="","",VLOOKUP($A119,'Annex 2 EHV charges'!$D:$O,3,0)) | D119: =IF($A119="","",VLOOKUP($A119,'Annex 2 EHV charges'!$D:$O,4,0)) | E119: =IFERROR(IF(VLOOKUP($A119,'Annex 2 EHV charges'!$D:$O,9,FALSE)=0,"",VLOOKUP($A119,'Annex 2 EHV charges'!$D:$O,9,FALSE)),"") | F119: =IFERROR(IF(VLOOKUP($A119,'Annex 2 EHV charges'!$D:$O,10,FALSE)=0,"",VLOOKUP($A119,'Annex 2 EHV charges'!$D:$O,10,FALSE)),"") | G119: =IFERROR(IF(VLOOKUP($A119,'Annex 2 EHV charges'!$D:$O,11,FALSE)=0,"",VLOOKUP($A119,'Annex 2 EHV charges'!$D:$O,11,FALSE)),"") | H119: =IFERROR(IF(VLOOKUP($A119,'Annex 2 EHV charges'!$D:$O,12,FALSE)=0,"",VLOOKUP($A119,'Annex 2 EHV charges'!$D:$O,12,FALSE)),"")
A120: {=IFERROR(INDEX('Annex 2 EHV charges'!$D$11:$D$260, MATCH(0, IF(ISBLANK('Annex 2 EHV charges'!$D$11:$D$260),1, COUNTIF(A$4:$A119, 'Annex 2 EHV charges'!$D$11:$D$260)), 0)),"")} | B120: =IF($A120="","",VLOOKUP($A120,'Annex 2 EHV charges'!$D:$O,2,0)) | C120: =IF($A120="","",VLOOKUP($A120,'Annex 2 EHV charges'!$D:$O,3,0)) | D120: =IF($A120="","",VLOOKUP($A120,'Annex 2 EHV charges'!$D:$O,4,0)) | E120: =IFERROR(IF(VLOOKUP($A120,'Annex 2 EHV charges'!$D:$O,9,FALSE)=0,"",VLOOKUP($A120,'Annex 2 EHV charges'!$D:$O,9,FALSE)),"") | F120: =IFERROR(IF(VLOOKUP($A120,'Annex 2 EHV charges'!$D:$O,10,FALSE)=0,"",VLOOKUP($A120,'Annex 2 EHV charges'!$D:$O,10,FALSE)),"") | G120: =IFERROR(IF(VLOOKUP($A120,'Annex 2 EHV charges'!$D:$O,11,FALSE)=0,"",VLOOKUP($A120,'Annex 2 EHV charges'!$D:$O,11,FALSE)),"") | H120: =IFERROR(IF(VLOOKUP($A120,'Annex 2 EHV charges'!$D:$O,12,FALSE)=0,"",VLOOKUP($A120,'Annex 2 EHV charges'!$D:$O,12,FALSE)),"")
A121: {=IFERROR(INDEX('Annex 2 EHV charges'!$D$11:$D$260, MATCH(0, IF(ISBLANK('Annex 2 EHV charges'!$D$11:$D$260),1, COUNTIF(A$4:$A120, 'Annex 2 EHV charges'!$D$11:$D$260)), 0)),"")} | B121: =IF($A121="","",VLOOKUP($A121,'Annex 2 EHV charges'!$D:$O,2,0)) | C121: =IF($A121="","",VLOOKUP($A121,'Annex 2 EHV charges'!$D:$O,3,0)) | D121: =IF($A121="","",VLOOKUP($A121,'Annex 2 EHV charges'!$D:$O,4,0)) | E121: =IFERROR(IF(VLOOKUP($A121,'Annex 2 EHV charges'!$D:$O,9,FALSE)=0,"",VLOOKUP($A121,'Annex 2 EHV charges'!$D:$O,9,FALSE)),"") | F121: =IFERROR(IF(VLOOKUP($A121,'Annex 2 EHV charges'!$D:$O,10,FALSE)=0,"",VLOOKUP($A121,'Annex 2 EHV charges'!$D:$O,10,FALSE)),"") | G121: =IFERROR(IF(VLOOKUP($A121,'Annex 2 EHV charges'!$D:$O,11,FALSE)=0,"",VLOOKUP($A121,'Annex 2 EHV charges'!$D:$O,11,FALSE)),"") | H121: =IFERROR(IF(VLOOKUP($A121,'Annex 2 EHV charges'!$D:$O,12,FALSE)=0,"",VLOOKUP($A121,'Annex 2 EHV charges'!$D:$O,12,FALSE)),"")
A122: {=IFERROR(INDEX('Annex 2 EHV charges'!$D$11:$D$260, MATCH(0, IF(ISBLANK('Annex 2 EHV charges'!$D$11:$D$260),1, COUNTIF(A$4:$A121, 'Annex 2 EHV charges'!$D$11:$D$260)), 0)),"")} | B122: =IF($A122="","",VLOOKUP($A122,'Annex 2 EHV charges'!$D:$O,2,0)) | C122: =IF($A122="","",VLOOKUP($A122,'Annex 2 EHV charges'!$D:$O,3,0)) | D122: =IF($A122="","",VLOOKUP($A122,'Annex 2 EHV charges'!$D:$O,4,0)) | E122: =IFERROR(IF(VLOOKUP($A122,'Annex 2 EHV charges'!$D:$O,9,FALSE)=0,"",VLOOKUP($A122,'Annex 2 EHV charges'!$D:$O,9,FALSE)),"") | F122: =IFERROR(IF(VLOOKUP($A122,'Annex 2 EHV charges'!$D:$O,10,FALSE)=0,"",VLOOKUP($A122,'Annex 2 EHV charges'!$D:$O,10,FALSE)),"") | G122: =IFERROR(IF(VLOOKUP($A122,'Annex 2 EHV charges'!$D:$O,11,FALSE)=0,"",VLOOKUP($A122,'Annex 2 EHV charges'!$D:$O,11,FALSE)),"") | H122: =IFERROR(IF(VLOOKUP($A122,'Annex 2 EHV charges'!$D:$O,12,FALSE)=0,"",VLOOKUP($A122,'Annex 2 EHV charges'!$D:$O,12,FALSE)),"")
A123: {=IFERROR(INDEX('Annex 2 EHV charges'!$D$11:$D$260, MATCH(0, IF(ISBLANK('Annex 2 EHV charges'!$D$11:$D$260),1, COUNTIF(A$4:$A122, 'Annex 2 EHV charges'!$D$11:$D$260)), 0)),"")} | B123: =IF($A123="","",VLOOKUP($A123,'Annex 2 EHV charges'!$D:$O,2,0)) | C123: =IF($A123="","",VLOOKUP($A123,'Annex 2 EHV charges'!$D:$O,3,0)) | D123: =IF($A123="","",VLOOKUP($A123,'Annex 2 EHV charges'!$D:$O,4,0)) | E123: =IFERROR(IF(VLOOKUP($A123,'Annex 2 EHV charges'!$D:$O,9,FALSE)=0,"",VLOOKUP($A123,'Annex 2 EHV charges'!$D:$O,9,FALSE)),"") | F123: =IFERROR(IF(VLOOKUP($A123,'Annex 2 EHV charges'!$D:$O,10,FALSE)=0,"",VLOOKUP($A123,'Annex 2 EHV charges'!$D:$O,10,FALSE)),"") | G123: =IFERROR(IF(VLOOKUP($A123,'Annex 2 EHV charges'!$D:$O,11,FALSE)=0,"",VLOOKUP($A123,'Annex 2 EHV charges'!$D:$O,11,FALSE)),"") | H123: =IFERROR(IF(VLOOKUP($A123,'Annex 2 EHV charges'!$D:$O,12,FALSE)=0,"",VLOOKUP($A123,'Annex 2 EHV charges'!$D:$O,12,FALSE)),"")
A124: {=IFERROR(INDEX('Annex 2 EHV charges'!$D$11:$D$260, MATCH(0, IF(ISBLANK('Annex 2 EHV charges'!$D$11:$D$260),1, COUNTIF(A$4:$A123, 'Annex 2 EHV charges'!$D$11:$D$260)), 0)),"")} | B124: =IF($A124="","",VLOOKUP($A124,'Annex 2 EHV charges'!$D:$O,2,0)) | C124: =IF($A124="","",VLOOKUP($A124,'Annex 2 EHV charges'!$D:$O,3,0)) | D124: =IF($A124="","",VLOOKUP($A124,'Annex 2 EHV charges'!$D:$O,4,0)) | E124: =IFERROR(IF(VLOOKUP($A124,'Annex 2 EHV charges'!$D:$O,9,FALSE)=0,"",VLOOKUP($A124,'Annex 2 EHV charges'!$D:$O,9,FALSE)),"") | F124: =IFERROR(IF(VLOOKUP($A124,'Annex 2 EHV charges'!$D:$O,10,FALSE)=0,"",VLOOKUP($A124,'Annex 2 EHV charges'!$D:$O,10,FALSE)),"") | G124: =IFERROR(IF(VLOOKUP($A124,'Annex 2 EHV charges'!$D:$O,11,FALSE)=0,"",VLOOKUP($A124,'Annex 2 EHV charges'!$D:$O,11,FALSE)),"") | H124: =IFERROR(IF(VLOOKUP($A124,'Annex 2 EHV charges'!$D:$O,12,FALSE)=0,"",VLOOKUP($A124,'Annex 2 EHV charges'!$D:$O,12,FALSE)),"")
A125: {=IFERROR(INDEX('Annex 2 EHV charges'!$D$11:$D$260, MATCH(0, IF(ISBLANK('Annex 2 EHV charges'!$D$11:$D$260),1, COUNTIF(A$4:$A124, 'Annex 2 EHV charges'!$D$11:$D$260)), 0)),"")} | B125: =IF($A125="","",VLOOKUP($A125,'Annex 2 EHV charges'!$D:$O,2,0)) | C125: =IF($A125="","",VLOOKUP($A125,'Annex 2 EHV charges'!$D:$O,3,0)) | D125: =IF($A125="","",VLOOKUP($A125,'Annex 2 EHV charges'!$D:$O,4,0)) | E125: =IFERROR(IF(VLOOKUP($A125,'Annex 2 EHV charges'!$D:$O,9,FALSE)=0,"",VLOOKUP($A125,'Annex 2 EHV charges'!$D:$O,9,FALSE)),"") | F125: =IFERROR(IF(VLOOKUP($A125,'Annex 2 EHV charges'!$D:$O,10,FALSE)=0,"",VLOOKUP($A125,'Annex 2 EHV charges'!$D:$O,10,FALSE)),"") | G125: =IFERROR(IF(VLOOKUP($A125,'Annex 2 EHV charges'!$D:$O,11,FALSE)=0,"",VLOOKUP($A125,'Annex 2 EHV charges'!$D:$O,11,FALSE)),"") | H125: =IFERROR(IF(VLOOKUP($A125,'Annex 2 EHV charges'!$D:$O,12,FALSE)=0,"",VLOOKUP($A125,'Annex 2 EHV charges'!$D:$O,12,FALSE)),"")
A126: {=IFERROR(INDEX('Annex 2 EHV charges'!$D$11:$D$260, MATCH(0, IF(ISBLANK('Annex 2 EHV charges'!$D$11:$D$260),1, COUNTIF(A$4:$A125, 'Annex 2 EHV charges'!$D$11:$D$260)), 0)),"")} | B126: =IF($A126="","",VLOOKUP($A126,'Annex 2 EHV charges'!$D:$O,2,0)) | C126: =IF($A126="","",VLOOKUP($A126,'Annex 2 EHV charges'!$D:$O,3,0)) | D126: =IF($A126="","",VLOOKUP($A126,'Annex 2 EHV charges'!$D:$O,4,0)) | E126: =IFERROR(IF(VLOOKUP($A126,'Annex 2 EHV charges'!$D:$O,9,FALSE)=0,"",VLOOKUP($A126,'Annex 2 EHV charges'!$D:$O,9,FALSE)),"") | F126: =IFERROR(IF(VLOOKUP($A126,'Annex 2 EHV charges'!$D:$O,10,FALSE)=0,"",VLOOKUP($A126,'Annex 2 EHV charges'!$D:$O,10,FALSE)),"") | G126: =IFERROR(IF(VLOOKUP($A126,'Annex 2 EHV charges'!$D:$O,11,FALSE)=0,"",VLOOKUP($A126,'Annex 2 EHV charges'!$D:$O,11,FALSE)),"") | H126: =IFERROR(IF(VLOOKUP($A126,'Annex 2 EHV charges'!$D:$O,12,FALSE)=0,"",VLOOKUP($A126,'Annex 2 EHV charges'!$D:$O,12,FALSE)),"")
A127: {=IFERROR(INDEX('Annex 2 EHV charges'!$D$11:$D$260, MATCH(0, IF(ISBLANK('Annex 2 EHV charges'!$D$11:$D$260),1, COUNTIF(A$4:$A126, 'Annex 2 EHV charges'!$D$11:$D$260)), 0)),"")} | B127: =IF($A127="","",VLOOKUP($A127,'Annex 2 EHV charges'!$D:$O,2,0)) | C127: =IF($A127="","",VLOOKUP($A127,'Annex 2 EHV charges'!$D:$O,3,0)) | D127: =IF($A127="","",VLOOKUP($A127,'Annex 2 EHV charges'!$D:$O,4,0)) | E127: =IFERROR(IF(VLOOKUP($A127,'Annex 2 EHV charges'!$D:$O,9,FALSE)=0,"",VLOOKUP($A127,'Annex 2 EHV charges'!$D:$O,9,FALSE)),"") | F127: =IFERROR(IF(VLOOKUP($A127,'Annex 2 EHV charges'!$D:$O,10,FALSE)=0,"",VLOOKUP($A127,'Annex 2 EHV charges'!$D:$O,10,FALSE)),"") | G127: =IFERROR(IF(VLOOKUP($A127,'Annex 2 EHV charges'!$D:$O,11,FALSE)=0,"",VLOOKUP($A127,'Annex 2 EHV charges'!$D:$O,11,FALSE)),"") | H127: =IFERROR(IF(VLOOKUP($A127,'Annex 2 EHV charges'!$D:$O,12,FALSE)=0,"",VLOOKUP($A127,'Annex 2 EHV charges'!$D:$O,12,FALSE)),"")
... A254: {=IFERROR(INDEX('Annex 2 EHV charges'!$D$11:$D$260, MATCH(0, IF(ISBLANK('Annex 2 EHV charges'!$D$11:$D$260),1, COUNTIF(A$4:$A253, 'Annex 2 EHV charges'!$D$11:$D$260)), 0)),"")} | B254: =IF($A254="","",VLOOKUP($A254,'Annex 2 EHV charges'!$D:$O,2,0)) | C254: =IF($A254="","",VLOOKUP($A254,'Annex 2 EHV charges'!$D:$O,3,0)) | D254: =IF($A254="","",VLOOKUP($A254,'Annex 2 EHV charges'!$D:$O,4,0)) | E254: =IFERROR(IF(VLOOKUP($A254,'Annex 2 EHV charges'!$D:$O,9,FALSE)=0,"",VLOOKUP($A254,'Annex 2 EHV charges'!$D:$O,9,FALSE)),"") | F254: =IFERROR(IF(VLOOKUP($A254,'Annex 2 EHV charges'!$D:$O,10,FALSE)=0,"",VLOOKUP($A254,'Annex 2 EHV charges'!$D:$O,10,FALSE)),"") | G254: =IFERROR(IF(VLOOKUP($A254,'Annex 2 EHV charges'!$D:$O,11,FALSE)=0,"",VLOOKUP($A254,'Annex 2 EHV charges'!$D:$O,11,FALSE)),"") | H254: =IFERROR(IF(VLOOKUP($A254,'Annex 2 EHV charges'!$D:$O,12,FALSE)=0,"",VLOOKUP($A254,'Annex 2 EHV charges'!$D:$O,12,FALSE)),"")

Sheet Annex 3 Preserved charges
A1: Back to Overview
A2: =Overview!B4& " - Effective from "&Overview!D4&" - "&Overview!E4&" LV and HV tariffs" -> SP Distribution - Effective from 1 April 2022 - Final LV and HV tariffs
A3: Supercustomer preserved charges/additional LLFCs
B4: Closed LLFCs | C4: PCs | D4: Red/black unit charge p/kWh | E4: Amber/yellow unit charge p/kWh | F4: Green unit charge p/kWh | G4: Fixed charge p/MPAN/day
A5: Domestic Aggregated (Related MPAN) | B5: 130, 134, 135 | C5: 2 | D5: 8.501 | E5: 0.962 | F5: 0.019
A6: Non-Domestic Aggregated No Residual | B6: 201, 204, 221, 260, 280, 200, 202, 203, 220, 222, 400, 401, 402 | C6: 3, 4 or 5-8 | D6: 10.706 | E6: 1.212 | F6: 0.024 | G6: 6.37
A7: Non-Domestic Aggregated Band 1 | B7: 201, 204, 221, 260, 280, 200, 202, 203, 220, 222, 400, 401, 402 | C7: 0, 3, 4, 5-8 | D7: 10.706 | E7: 1.212 | F7: 0.024 | G7: 11.11
A8: Non-Domestic Aggregated Band 2 | B8: 201, 204, 221, 260, 280, 200, 202, 203, 220, 222, 400, 401, 402 | C8: 0, 3, 4, 5-8 | D8: 10.706 | E8: 1.212 | F8: 0.024 | G8: 32.32
A9: Non-Domestic Aggregated Band 3 | B9: 201, 204, 221, 260, 280, 200, 202, 203, 220, 222, 400, 401, 402 | C9: 0, 3, 4, 5-8 | D9: 10.706 | E9: 1.212 | F9: 0.024 | G9: 71.14
A10: Non-Domestic Aggregated Band 4 | B10: 201, 204, 221, 260, 280, 200, 202, 203, 220, 222, 400, 401, 402 | C10: 0, 3, 4, 5-8 | D10: 10.706 | E10: 1.212 | F10: 0.024 | G10: 209.3
A11: Non-Domestic Aggregated (related MPAN) | B11: 223, 242, 243, 245, 246 | C11: 3 or 4 | D11: 10.706 | E11: 1.212 | F11: 0.024
A12: Unmetered Supplies | B12: 904, 905, 906, 907, 908, 909 | C12: 0, 1 or 8 | D12: 21.869 | E12: 2.649 | F12: 1.788
A13: Notes: | B13: Unit time periods are as specified in the SSC.
B14: SP Manweb uses a default tariff for invalid settlement combinations these will be charged at the Domestic Aggregated Unrestricted Rates. The Domestic and Non-Domestic Aggregated (related MPAN) tariffs are supplementary to a standard published tariff and therefore only available under these conditions. Preserved tariffs are only available to existing supplies, subject to certain conditions: a) Suppliers may not normally transfer a meter point from one preserved tariff to another preserved tariff; b) If a supply under a preserved tariff should cease, other than on change of tenancy, the preserved tariff may not normally be restored; c) Any additional load requried to be supplied on the preserved tariff must be within the existing supply capacity.
A18: Site Specific preserved charges/additional LLFCs
B19: Closed LLFCs | C19: PCs | D19: Red/black unit charge p/kWh | E19: Amber/yellow unit charge p/kWh | F19: Green unit charge p/kWh | G19: Fixed charge p/MPAN/day | H19: Capacity charge p/kVA/day | I19: Exceeded capacity charge p/kVA/day | J19: Reactive power charge p/kVArh
A20: LV Site Specific No Residual | B20: 500, 502, 504 | C20: 0 | D20: 6.926 | E20: 0.75 | F20: 0.014 | G20: 25.01
A21: LV Site Specific Band 1 | B21: 500, 502, 504 | C21: 0 | D21: 6.926 | E21: 0.75 | F21: 0.014 | G21: 343.29
A22: LV Site Specific Band 2 | B22: 500, 502, 504 | C22: 0 | D22: 6.926 | E22: 0.75 | F22: 0.014 | G22: 684.83
A23: LV Site Specific Band 3 | B23: 500, 502, 504 | C23: 0 | D23: 6.926 | E23: 0.75 | F23: 0.014 | G23: 1126.71
A24: LV Site Specific Band 4 | B24: 500, 502, 504 | C24: 0 | D24: 6.926 | E24: 0.75 | F24: 0.014 | G24: 2465.99
A25: LV Sub Site Specific No Residual | B25: 506, 507, 508 | C25: 0 | D25: 4.073 | E25: 0.383 | F25: 0.005 | G25: 8.85
A26: LV Sub Site Specific Band 1 | B26: 506, 507, 508 | C26: 0 | D26: 4.073 | E26: 0.383 | F26: 0.005 | G26: 327.13
A27: LV Sub Site Specific Band 2 | B27: 506, 507, 508 | C27: 0 | D27: 4.073 | E27: 0.383 | F27: 0.005 | G27: 668.67
A28: LV Sub Site Specific Band 3 | B28: 506, 507, 508 | C28: 0 | D28: 4.073 | E28: 0.383 | F28: 0.005 | G28: 1110.54
A29: LV Sub Site Specific Band 4 | B29: 506, 507, 508 | C29: 0 | D29: 4.073 | E29: 0.383 | F29: 0.005 | G29: 2449.83
A30: HV Site Specific No Residual | B30: 501, 505, 503 | C30: 0 | D30: 3.029 | E30: 0.262 | F30: 0.003 | G30: 133.52
A31: HV Site Specific Band 1 | B31: 501, 505, 503 | C31: 0 | D31: 3.029 | E31: 0.262 | F31: 0.003 | G31: 1603.45
... A34: HV Site Specific Band 4 | B34: 501, 505, 503 | C34: 0 | D34: 3.029 | E34: 0.262 | F34: 0.003 | G34: 31562.57
A35: Notes: | B35: Time periods
B36: As detailed in Annex 1
B38: All times are UK clock-time.
B40: Preserved tariffs are only available to existing supplies, subject to certain conditions: a) Suppliers may not normally transfer a meter point from one preserved tariff to another preserved tariff; b) If a supply under a preserved tariff should cease, other than on change of tenancy, the preserved tariff may not normally be restored; c) Any additional load requried to be supplied on the preserved tariff must be within the existing supply capacity.

Sheet Annex 4 LDNO charges
A1: Back to Overview | B1: Copy from CDCM table 3701 "Tariffs!A42:I84" and paste values into A14 | F1: Copy from EDCM table 6005 "LDNORev!B549:G683" and paste values into D57
A2: =Overview!B4& " - Effective from "&Overview!D4&" - "&Overview!E4&" LDNO tariffs" -> SP Distribution - Effective from 1 April 2022 - Final LDNO tariffs | K2: 1
K3: 1
A4: Time Bands for LV and HV Designated Properties | F4: Time Bands for Unmetered Properties | K4: 1
A5: Time periods | B5: Red Time Band | C5: Amber Time Band | D5: Green Time Band | H5: Black Time Band | I5: Yellow Time Band | J5: Green Time Band | K5: 1
A6: Monday to Friday (Including Bank Holidays) All Year | B6: 16.30 - 19.30 | C6: 08.00 - 16.30 19.30 - 22.30 | D6: 00.00 - 08.00 22.30 - 00.00 | F6: Monday to Friday (Including Bank Holidays) June to August Inclusive | I6: 08.00 - 22.30 | J6: 00.00 - 08.00 22.30 - 00.00 | K6: 1
A7: Saturday and Sunday All Year | C7: 16.00 - 20.00 | D7: 00.00 - 16.00 20.00 - 00.00 | F7: Monday to Friday (Including Bank Holidays) November to February Inclusive | H7: 16.30 - 19.30 | I7: 08.00 - 16.30 19.30 - 22.30 | J7: 00.00 - 08.00 22.30 - 00.00 | K7: 1
A8: Notes | B8: All the above times are in UK Clock time | F8: Monday to Friday (Including Bank Holidays) March to May, & September to October, Inclusive | I8: 08.00 - 22.30 | J8: 00.00 - 08.00 22.30 - 00.00 | K8: 1
F9: Saturday and Sunday All year | I9: 16.00 - 20.00 | J9: 00:00-16:00 20:00-00:00 | K9: 1
F10: Notes | H10: All the above times are in UK Clock time | K10: 1
K11: 1
K12: 1
A13: Tariff name | B13: Unique billing identifier | C13: PCs | D13: Red/black unit charge p/kWh | E13: Amber/yellow unit charge p/kWh | F13: Green unit charge p/kWh | G13: Fixed charge p/MPAN/day | H13: Capacity charge p/kVA/day | I13: Exceeded capacity charge p/kVA/day | J13: Reactive power charge p/kVArh | K13: 1
A14: LDNO LV: Domestic Aggregated with Residual | D14: 5.173 | E14: 0.585 | F14: 0.012 | G14: 20.18 | K14: 1
A15: LDNO LV: Domestic Aggregated (Related MPAN) | D15: 5.173 | E15: 0.585 | F15: 0.012 | K15: 1
A16: LDNO LV: Non-Domestic Aggregated No Residual | D16: 6.516 | E16: 0.737 | F16: 0.015 | G16: 3.89 | K16: 1
A17: LDNO LV: Non-Domestic Aggregated Band 1 | D17: 6.516 | E17: 0.737 | F17: 0.015 | G17: 6.78 | K17: 1
A18: LDNO LV: Non-Domestic Aggregated Band 2 | D18: 6.516 | E18: 0.737 | F18: 0.015 | G18: 19.68 | K18: 1
A19: LDNO LV: Non-Domestic Aggregated Band 3 | D19: 6.516 | E19: 0.737 | F19: 0.015 | G19: 43.31 | K19: 1
A20: LDNO LV: Non-Domestic Aggregated Band 4 | D20: 6.516 | E20: 0.737 | F20: 0.015 | G20: 127.39 | K20: 1
A21: LDNO LV: Non-Domestic Aggregated (related MPAN) | D21: 6.516 | E21: 0.737 | F21: 0.015 | K21: 1
A22: LDNO LV: LV Site Specific No Residual | D22: 4.215 | E22: 0.456 | F22: 0.009 | G22: 15.24 | H22: 1.62 | I22: 2.33 | J22: 0.129 | K22: 1
A23: LDNO LV: LV Site Specific Band 1 | D23: 4.215 | E23: 0.456 | F23: 0.009 | G23: 208.94 | H23: 1.62 | I23: 2.33 | J23: 0.129 | K23: 1
A24: LDNO LV: LV Site Specific Band 2 | D24: 4.215 | E24: 0.456 | F24: 0.009 | G24: 416.79 | H24: 1.62 | I24: 2.33 | J24: 0.129 | K24: 1
A25: LDNO LV: LV Site Specific Band 3 | D25: 4.215 | E25: 0.456 | F25: 0.009 | G25: 685.71 | H25: 1.62 | I25: 2.33 | J25: 0.129 | K25: 1
A26: LDNO LV: LV Site Specific Band 4 | D26: 4.215 | E26: 0.456 | F26: 0.009 | G26: 1500.78 | H26: 1.62 | I26: 2.33 | J26: 0.129 | K26: 1
A27: LDNO LV: Unmetered Supplies | D27: 13.309 | E27: 1.612 | F27: 1.088 | K27: 1
A28: LDNO LV: LV Generation Aggregated | D28: -6.3 | E28: -0.713 | F28: -0.014 | G28: - | K28: 1
A29: LDNO LV: LV Generation Site Specific | D29: -6.3 | E29: -0.713 | F29: -0.014 | G29: - | J29: 0.191 | K29: 1
A30: LDNO HV: Domestic Aggregated with Residual | D30: 3.433 | E30: 0.389 | F30: 0.008 | G30: 16.55 | K30: 1
A31: LDNO HV: Domestic Aggregated (Related MPAN) | D31: 3.433 | E31: 0.389 | F31: 0.008 | K31: 1
A32: LDNO HV: Non-Domestic Aggregated No Residual | D32: 4.324 | E32: 0.489 | F32: 0.01 | G32: 2.59 | K32: 1
A33: LDNO HV: Non-Domestic Aggregated Band 1 | D33: 4.324 | E33: 0.489 | F33: 0.01 | G33: 4.51 | K33: 1
A34: LDNO HV: Non-Domestic Aggregated Band 2 | D34: 4.324 | E34: 0.489 | F34: 0.01 | G34: 13.07 | K34: 1
A35: LDNO HV: Non-Domestic Aggregated Band 3 | D35: 4.324 | E35: 0.489 | F35: 0.01 | G35: 28.75 | K35: 1
A36: LDNO HV: Non-Domestic Aggregated Band 4 | D36: 4.324 | E36: 0.489 | F36: 0.01 | G36: 84.55 | K36: 1
A37: LDNO HV: Non-Domestic Aggregated (related MPAN) | D37: 4.324 | E37: 0.489 | F37: 0.01 | K37: 1
A38: LDNO HV: LV Site Specific No Residual | D38: 2.798 | E38: 0.303 | F38: 0.006 | G38: 10.12 | H38: 1.07 | I38: 1.55 | J38: 0.086 | K38: 1
A39: LDNO HV: LV Site Specific Band 1 | D39: 2.798 | E39: 0.303 | F39: 0.006 | G39: 138.67 | H39: 1.07 | I39: 1.55 | J39: 0.086 | K39: 1
A40: LDNO HV: LV Site Specific Band 2 | D40: 2.798 | E40: 0.303 | F40: 0.006 | G40: 276.62 | H40: 1.07 | I40: 1.55 | J40: 0.086 | K40: 1
A41: LDNO HV: LV Site Specific Band 3 | D41: 2.798 | E41: 0.303 | F41: 0.006 | G41: 455.09 | H41: 1.07 | I41: 1.55 | J41: 0.086 | K41: 1
A42: LDNO HV: LV Site Specific Band 4 | D42: 2.798 | E42: 0.303 | F42: 0.006 | G42: 996.02 | H42: 1.07 | I42: 1.55 | J42: 0.086 | K42: 1
A43: LDNO HV: LV Sub Site Specific No Residual | D43: 2.708 | E43: 0.254 | F43: 0.003 | G43: 5.9 | H43: 3.19 | I43: 3.63 | J43: 0.074 | K43: 1
A44: LDNO HV: LV Sub Site Specific Band 1 | D44: 2.708 | E44: 0.254 | F44: 0.003 | G44: 217.5 | H44: 3.19 | I44: 3.63 | J44: 0.074 | K44: 1
A45: LDNO HV: LV Sub Site Specific Band 2 | D45: 2.708 | E45: 0.254 | F45: 0.003 | G45: 444.57 | H45: 3.19 | I45: 3.63 | J45: 0.074 | K45: 1
A46: LDNO HV: LV Sub Site Specific Band 3 | D46: 2.708 | E46: 0.254 | F46: 0.003 | G46: 738.34 | H46: 3.19 | I46: 3.63 | J46: 0.074 | K46: 1
A47: LDNO HV: LV Sub Site Specific Band 4 | D47: 2.708 | E47: 0.254 | F47: 0.003 | G47: 1628.74 | H47: 3.19 | I47: 3.63 | J47: 0.074 | K47: 1
A48: LDNO HV: HV Site Specific No Residual | D48: 2.313 | E48: 0.2 | F48: 0.002 | G48: 101.95 | H48: 4.05 | I48: 4.96 | J48: 0.059 | K48: 1
A49: LDNO HV: HV Site Specific Band 1 | D49: 2.313 | E49: 0.2 | F49: 0.002 | G49: 1224.25 | H49: 4.05 | I49: 4.96 | J49: 0.059 | K49: 1
... A52: LDNO HV: HV Site Specific Band 4 | D52: 2.313 | E52: 0.2 | F52: 0.002 | G52: 24098.17 | H52: 4.05 | I52: 4.96 | J52: 0.059 | K52: 1
A53: LDNO HV: Unmetered Supplies | D53: 8.833 | E53: 1.07 | F53: 0.722 | K53: 1
A54: LDNO HV: LV Generation Aggregated | D54: -6.3 | E54: -0.713 | F54: -0.014 | G54: - | K54: 1
A55: LDNO HV: LV Sub Generation Aggregated | D55: -5.55 | E55: -0.614 | F55: -0.012 | G55: - | K55: 1
A56: LDNO HV: LV Generation Site Specific | D56: -6.3 | E56: -0.713 | F56: -0.014 | G56: - | J56: 0.191 | K56: 1
A57: LDNO HV: LV Sub Generation Site Specific | D57: -5.55 | E57: -0.614 | F57: -0.012 | G57: - | J57: 0.168 | K57: 1
A58: LDNO HV: HV Generation Site Specific | D58: -3.601 | E58: -0.337 | F58: -0.004 | G58: - | J58: 0.14 | K58: 1
A59: LDNO HVplus: Domestic Aggregated with Residual | D59: 2.014 | E59: 0.228 | F59: 0.005 | G59: 13.59 | K59: 2
A60: LDNO HVplus: Domestic Aggregated (Related MPAN) | D60: 2.014 | E60: 0.228 | F60: 0.005 | G60: - | K60: 2
A61: LDNO HVplus: Non-Domestic Aggregated No Residual | D61: 2.537 | E61: 0.287 | F61: 0.006 | G61: 1.53 | K61: 2
A62: LDNO HVplus: Non-Domestic Aggregated Band 1 | D62: 2.537 | E62: 0.287 | F62: 0.006 | G62: 2.66 | K62: 2
A63: LDNO HVplus: Non-Domestic Aggregated Band 2 | D63: 2.537 | E63: 0.287 | F63: 0.006 | G63: 7.68 | K63: 2
A64: LDNO HVplus: Non-Domestic Aggregated Band 3 | D64: 2.537 | E64: 0.287 | F64: 0.006 | G64: 16.88 | K64: 2
A65: LDNO HVplus: Non-Domestic Aggregated Band 4 | D65: 2.537 | E65: 0.287 | F65: 0.006 | G65: 49.62 | K65: 2
A66: LDNO HVplus: Non-Domestic Aggregated (related MPAN) | D66: 2.537 | E66: 0.287 | F66: 0.006 | K66: 2
A67: LDNO HVplus: LV Site Specific No Residual | D67: 1.641 | E67: 0.178 | F67: 0.003 | G67: 5.95 | H67: 0.63 | I67: 0.91 | J67: 0.05 | K67: 2
A68: LDNO HVplus: LV Site Specific Band 1 | D68: 1.641 | E68: 0.178 | F68: 0.003 | G68: 81.38 | H68: 0.63 | I68: 0.91 | J68: 0.05 | K68: 2
A69: LDNO HVplus: LV Site Specific Band 2 | D69: 1.641 | E69: 0.178 | F69: 0.003 | G69: 162.31 | H69: 0.63 | I69: 0.91 | J69: 0.05 | K69: 2
A70: LDNO HVplus: LV Site Specific Band 3 | D70: 1.641 | E70: 0.178 | F70: 0.003 | G70: 267.02 | H70: 0.63 | I70: 0.91 | J70: 0.05 | K70: 2
A71: LDNO HVplus: LV Site Specific Band 4 | D71: 1.641 | E71: 0.178 | F71: 0.003 | G71: 584.38 | H71: 0.63 | I71: 0.91 | J71: 0.05 | K71: 2
A72: LDNO HVplus: LV Sub Site Specific No Residual | D72: 1.543 | E72: 0.145 | F72: 0.002 | G72: 3.38 | H72: 1.82 | I72: 2.07 | J72: 0.042 | K72: 2
A73: LDNO HVplus: LV Sub Site Specific Band 1 | D73: 1.543 | E73: 0.145 | F73: 0.002 | G73: 123.98 | H73: 1.82 | I73: 2.07 | J73: 0.042 | K73: 2
A74: LDNO HVplus: LV Sub Site Specific Band 2 | D74: 1.543 | E74: 0.145 | F74: 0.002 | G74: 253.4 | H74: 1.82 | I74: 2.07 | J74: 0.042 | K74: 2
A75: LDNO HVplus: LV Sub Site Specific Band 3 | D75: 1.543 | E75: 0.145 | F75: 0.002 | G75: 420.85 | H75: 1.82 | I75: 2.07 | J75: 0.042 | K75: 2
A76: LDNO HVplus: LV Sub Site Specific Band 4 | D76: 1.543 | E76: 0.145 | F76: 0.002 | G76: 928.35 | H76: 1.82 | I76: 2.07 | J76: 0.042 | K76: 2
A77: LDNO HVplus: HV Site Specific No Residual | D77: 1.304 | E77: 0.113 | F77: 0.001 | G77: 57.51 | H77: 2.28 | I77: 2.8 | J77: 0.033 | K77: 2
A78: LDNO HVplus: HV Site Specific Band 1 | D78: 1.304 | E78: 0.113 | F78: 0.001 | G78: 690.49 | H78: 2.28 | I78: 2.8 | J78: 0.033 | K78: 2
... A81: LDNO HVplus: HV Site Specific Band 4 | D81: 1.304 | E81: 0.113 | F81: 0.001 | G81: 13591.35 | H81: 2.28 | I81: 2.8 | J81: 0.033 | K81: 2
A82: LDNO HVplus: Unmetered Supplies | D82: 5.182 | E82: 0.628 | F82: 0.424 | K82: 2
A83: LDNO HVplus: LV Generation Aggregated | D83: -2.387 | E83: -0.27 | F83: -0.005 | G83: - | K83: 2
A84: LDNO HVplus: LV Sub Generation Aggregated | D84: -2.39 | E84: -0.264 | F84: -0.005 | G84: - | K84: 2
A85: LDNO HVplus: LV Generation Site Specific | D85: -2.387 | E85: -0.27 | F85: -0.005 | G85: - | J85: 0.072 | K85: 2
A86: LDNO HVplus: LV Sub Generation Site Specific | D86: -2.39 | E86: -0.264 | F86: -0.005 | G86: - | J86: 0.072 | K86: 2
A87: LDNO HVplus: HV Generation Site Specific | D87: -3.601 | E87: -0.337 | F87: -0.004 | G87: 97.47 | J87: 0.14 | K87: 2
A88: LDNO EHV: Domestic Aggregated with Residual | D88: 0.981 | E88: 0.111 | F88: 0.002 | G88: 11.43 | K88: 2
A89: LDNO EHV: Domestic Aggregated (Related MPAN) | D89: 0.981 | E89: 0.111 | F89: 0.002 | K89: 2
A90: LDNO EHV: Non-Domestic Aggregated No Residual | D90: 1.236 | E90: 0.14 | F90: 0.003 | G90: 0.77 | K90: 2
A91: LDNO EHV: Non-Domestic Aggregated Band 1 | D91: 1.236 | E91: 0.14 | F91: 0.003 | G91: 1.31 | K91: 2
A92: LDNO EHV: Non-Domestic Aggregated Band 2 | D92: 1.236 | E92: 0.14 | F92: 0.003 | G92: 3.76 | K92: 2
A93: LDNO EHV: Non-Domestic Aggregated Band 3 | D93: 1.236 | E93: 0.14 | F93: 0.003 | G93: 8.24 | K93: 2
A94: LDNO EHV: Non-Domestic Aggregated Band 4 | D94: 1.236 | E94: 0.14 | F94: 0.003 | G94: 24.19 | K94: 2
A95: LDNO EHV: Non-Domestic Aggregated (related MPAN) | D95: 1.236 | E95: 0.14 | F95: 0.003 | K95: 2
A96: LDNO EHV: LV Site Specific No Residual | D96: 0.8 | E96: 0.087 | F96: 0.002 | G96: 2.92 | H96: 0.31 | I96: 0.44 | J96: 0.025 | K96: 2
A97: LDNO EHV: LV Site Specific Band 1 | D97: 0.8 | E97: 0.087 | F97: 0.002 | G97: 39.66 | H97: 0.31 | I97: 0.44 | J97: 0.025 | K97: 2
A98: LDNO EHV: LV Site Specific Band 2 | D98: 0.8 | E98: 0.087 | F98: 0.002 | G98: 79.09 | H98: 0.31 | I98: 0.44 | J98: 0.025 | K98: 2
A99: LDNO EHV: LV Site Specific Band 3 | D99: 0.8 | E99: 0.087 | F99: 0.002 | G99: 130.1 | H99: 0.31 | I99: 0.44 | J99: 0.025 | K99: 2
A100: LDNO EHV: LV Site Specific Band 4 | D100: 0.8 | E100: 0.087 | F100: 0.002 | G100: 284.72 | H100: 0.31 | I100: 0.44 | J100: 0.025 | K100: 2
A101: LDNO EHV: LV Sub Site Specific No Residual | D101: 0.752 | E101: 0.071 | F101: 0.001 | G101: 1.66 | H101: 0.89 | I101: 1.01 | J101: 0.021 | K101: 2
A102: LDNO EHV: LV Sub Site Specific Band 1 | D102: 0.752 | E102: 0.071 | F102: 0.001 | G102: 60.42 | H102: 0.89 | I102: 1.01 | J102: 0.021 | K102: 2
A103: LDNO EHV: LV Sub Site Specific Band 2 | D103: 0.752 | E103: 0.071 | F103: 0.001 | G103: 123.47 | H103: 0.89 | I103: 1.01 | J103: 0.021 | K103: 2
A104: LDNO EHV: LV Sub Site Specific Band 3 | D104: 0.752 | E104: 0.071 | F104: 0.001 | G104: 205.04 | H104: 0.89 | I104: 1.01 | J104: 0.021 | K104: 2
...

Sheet Annex 5 LLFs
A1: Back to Overview
A2: This table has intentionally been left blank. The line loss factors that are approved by the BSC Panel for the applicable year and consequently published on the Elexon website will take precedence and be used in Settlement. This annex will be re-published once these values are available.
A3: =Overview!B4& " - Illustrative LLFs for year beginning "&Overview!D4 -> SP Distribution - Illustrative LLFs for year beginning 1 April 2022
A4: Time periods | B4: Period 1 | C4: Period 2 | D4: Period 3 | E4: Period 4
B5: (Name 1) | C5: (Name 2) | D5: (Name 3) | E5: (Name 4)
A6: Monday to Friday March to October | B6: 23:30 – 07:30 | C6: 07:30 – 23:30
A7: Monday to Friday November to February | B7: 23:30 – 07:30 | C7: 20:00 – 23:30 | D7: 07:30 – 16:00 19:00 – 20:00 | E7: 16:00 – 19:00
A8: Saturday and Sunday All Year | B8: 23:30 – 07:30 | C8: 07:30 – 23:30
A9: Notes | B9: All the above times are in UK Clock time
A12: Generic demand and generation LLFs
A13: Metered voltage, respective periods and associated LLFCs
A14: Metered voltage | B14: Period 1 | C14: Period 2 | D14: Period 3 | E14: Period 4 | F14: Associated LLFC
A15: Low-voltage network | B15: 1.089 | C15: 1.105 | D15: 1.122 | E15: 1.135 | F15: 100, 101, 110, 111, 112, 113, 114, 115, 116, 117, 118, 119, 120, 121, 130, 132, 133, 134, 135, 136, 137, 160, 161, 162, 163, 164, 165, 166, 180, 200, 201, 202, 203, 204, 220, 221, 222, 223, 224, 225, 240, 241, 242, 243, 244, 245, 246, 260, 280,400, 402, 500, 502, 504, 603, 604, 607, 608, 781, 782, 783, 784, 785, 794, 795, 900, 901, 902, 903, 910 D00, D01, D02, D03, D04, G00, G01, G02, G03, G04, H00, H01, H02, H03, H04
A16: Low-voltage substation | B16: 1.045 | C16: 1.044 | D16: 1.046 | E16: 1.048 | F16: 506, 507, 508, 602, 609, 610, 796, 797, K00, K01, K02, K03, K04, L00, L01, L02, L03, L04
A17: High-voltage network | B17: 1.023 | C17: 1.025 | D17: 1.028 | E17: 1.03 | F17: 301, 401, 501, 503, 505, 599, 600, 601, 605, 606, 611, 612, 615, 616, 617, 798, 799 F00, F01, F02, F03, M00, M01, M02, M03, M04, N00, N01, N02, N03, N04
A18: High-voltage substation | B18: 1.013 | C18: 1.013 | D18: 1.013 | E18: 1.013 | F18: 310 - 340 inclusive 750 - 765 inclusive 862, 866, 867
A19: 33kV generic Import | B19: 1.003 | C19: 1.004 | D19: 1.004 | E19: 1.005
A20: 33kV generic Export | B20: 1 | C20: 1 | D20: 1 | E20: 1
A21: 132kV generic Import
A22: 132kV generic Export
A24: EHV site specific LLFs
A25: Demand
A26: Site | B26: Period 1 | C26: Period 2 | D26: Period 3 | E26: Period 4 | F26: Associated LLFC
A27: Rhodders | B27: 1.003 | C27: 1.004 | D27: 1.004 | E27: 1.005 | F27: 800
A28: Minsca | B28: 1.003 | C28: 1.004 | D28: 1.005 | E28: 1.005 | F28: 801
A29: Bankend Rig | B29: 1.003 | C29: 1.004 | D29: 1.005 | E29: 1.005 | F29: 802
A30: Barlockhart Moor | B30: 1.003 | C30: 1.004 | D30: 1.005 | E30: 1.005 | F30: 803
A31: Blantyre Muir | B31: 1.003 | C31: 1.004 | D31: 1.005 | E31: 1.005 | F31: 804
A32: Hunterston WF | B32: 1.003 | C32: 1.004 | D32: 1.004 | E32: 1.005 | F32: 805
A33: Middleton Farm | B33: 1.003 | C33: 1.004 | D33: 1.005 | E33: 1.005 | F33: 806
A34: Neilston Community | B34: 1.003 | C34: 1.004 | D34: 1.005 | E34: 1.005 | F34: 807
A35: Garlaff Landfill | B35: 1.003 | C35: 1.004 | D35: 1.005 | E35: 1.005 | F35: 808
A36: Hagshaw Hill Extension | B36: 1.003 | C36: 1.004 | D36: 1.004 | E36: 1.005 | F36: 809
A37: Abbotshaugh Reserve Power Facility | B37: 1.003 | C37: 1.004 | D37: 1.004 | E37: 1.005 | F37: 810
A38: Muirhall | B38: 1.003 | C38: 1.004 | D38: 1.005 | E38: 1.005 | F38: 811
... A117: Harelaw Gas | B117: 1.003 | C117: 1.004 | D117: 1.004 | E117: 1.005 | F117: 911
A118: Dumbarton | B118: 1 | C118: 1 | D118: 1 | E118: 1 | F118: MSID 8083
A119: Stirling Road | B119: 1 | C119: 1 | D119: 1 | E119: 1 | F119: MSID 8085
A120: Markinch | B120: 0.995 | C120: 0.995 | D120: 0.995 | E120: 0.995 | F120: MSID 8334
A121: Harehill Extension | B121: 0.995 | C121: 0.999 | D121: 0.998 | E121: 1 | F121: MSID 8339
A122: Andershaw WF | B122: 0.989 | C122: 0.989 | D122: 0.988 | E122: 0.989 | F122: MSID 8341
A123: Assel Valley | B123: 0.991 | C123: 0.991 | D123: 0.989 | E123: 0.989 | F123: MSID 8347
A124: Auchrobert | B124: 0.989 | C124: 0.989 | D124: 0.987 | E124: 0.987 | F124: MSID 8348
A125: Harburnhead | B125: 0.997 | C125: 0.997 | D125: 0.997 | E125: 0.997 | F125: MSID 8349
A126: Broxburn ESS | B126: 1.003 | C126: 1.004 | D126: 1.004 | E126: 1.005 | F126: MSID 8359
A127: Abercorn Street | B127: 1.003 | C127: 1.004 | D127: 1.004 | E127: 1.005 | F127: TBA 3A
A128: Drumcross ESS | B128: 1.003 | C128: 1.004 | D128: 1.004 | E128: 1.005 | F128: TBA 14A
A129: Easter Drumclair WF | B129: 1.003 | C129: 1.004 | D129: 1.004 | E129: 1.005 | F129: TBA 15A
... A133: Southrigg 2 WF | B133: 1.013 | C133: 1.013 | D133: 1.013 | E133: 1.013 | F133: TBA 12A
A136: EHV site specific LLFs
A137: Generation
A138: Site | B138: Period 1 | C138: Period 2 | D138: Period 3 | E138: Period 4 | F138: Associated LLFC
A139: Craigengelt | B139: 0.983 | C139: 0.983 | D139: 0.979 | E139: 0.979 | F139: 620
A140: Greenknowes | B140: 0.992 | C140: 0.992 | D140: 0.989 | E140: 0.989 | F140: 621
A141: Muirpark Windfarm | B141: 1 | C141: 1 | D141: 1 | E141: 1 | F141: 623
A142: Greendykeside | B142: 0.999 | C142: 0.999 | D142: 0.999 | E142: 0.999 | F142: 624
A143: Aikengall | B143: 0.988 | C143: 0.989 | D143: 0.985 | E143: 0.985 | F143: 625
A144: Hagshaw Hill | B144: 0.999 | C144: 1.001 | D144: 1.002 | E144: 1.003 | F144: 626
A145: Gallow Rig | B145: 1.008 | C145: 1.013 | D145: 1.016 | E145: 1.02 | F145: 627
A146: Polwhat Rig | B146: 1.005 | C146: 1.011 | D146: 1.013 | E146: 1.017 | F146: 628
A147: Hagshaw Hill Extension | B147: 0.992 | C147: 0.992 | D147: 0.99 | E147: 0.99 | F147: 629
A148: Dun Law | B148: 0.981 | C148: 0.982 | D148: 0.978 | E148: 0.982 | F148: 630
A149: EPR Scotland Ltd | B149: 0.999 | C149: 0.999 | D149: 0.999 | E149: 0.999 | F149: 631
A150: Bowbeat (Emly Bank) | B150: 1.006 | C150: 1.014 | D150: 1.018 | E150: 1.024 | F150: 632
... A218: Carmuirs Gas | B218: 1 | C218: 1 | D218: 1 | E218: 1 | F218: 714
A219: Redhouse Energy Storage site (ESS) | B219: =VLOOKUP($F219,'[2]CSAD 2.1a SVA Data'!$C$154:$N$270,9,FALSE) -> 1 | C219: =VLOOKUP($F219,'[2]CSAD 2.1a SVA Data'!$C$154:$N$270,10,FALSE) -> 1 | D219: =VLOOKUP($F219,'[2]CSAD 2.1a SVA Data'!$C$154:$N$270,11,FALSE) -> 1 | E219: =VLOOKUP($F219,'[2]CSAD 2.1a SVA Data'!$C$154:$N$270,12,FALSE) -> 1 | F219: 715
A220: Byers Brae Battery Storage | B220: 1 | C220: 1 | D220: 1 | E220: 1 | F220: 716
A221: Abbotshaugh Reserve Power Facility | B221: 1 | C221: 1 | D221: 1 | E221: 1 | F221: 717
A222: Harelaw Gas | B222: 1 | C222: 1 | D222: 1 | E222: 1 | F222: 950
A223: Minsca | B223: 0.992 | C223: 0.991 | D223: 0.991 | E223: 0.992 | F223: MSID 8182
A224: Dalswinton | B224: 0.995 | C224: 0.995 | D224: 0.995 | E224: 0.996 | F224: MSID 8183
A225: Markinch | B225: 0.995 | C225: 0.995 | D225: 0.995 | E225: 0.995 | F225: MSID 8334
A226: Harehill Extension | B226: 0.995 | C226: 0.999 | D226: 0.998 | E226: 1 | F226: MSID 8339
A227: Aries | B227: 0.981 | C227: 0.982 | D227: 0.976 | E227: 0.978 | F227: MSID 8340
A228: Andershaw WF | B228: 0.989 | C228: 0.989 | D228: 0.988 | E228: 0.989 | F228: MSID 8341
A229: Assel Valley | B229: 0.991 | C229: 0.991 | D229: 0.989 | E229: 0.989 | F229: MSID 8347
A230: Auchrobert | B230: 0.989 | C230: 0.989 | D230: 0.987 | E230: 0.987 | F230: MSID 8348
A231: Harburnhead | B231: 0.997 | C231: 0.997 | D231: 0.997 | E231: 0.997 | F231: MSID 8349
A232: Broxburn ESS | B232: 1.003 | C232: 1.004 | D232: 1.004 | E232: 1.005 | F232: MSID 8360
A233: Solwaybank | B233: 1 | C233: 1 | D233: 1 | E233: 1 | F233: MSID 8366
A234: Glenchamber | B234: 0.995 | C234: 0.996 | D234: 0.995 | E234: 0.995 | F234: MSID 8732
... A242: Abercorn Street | B242: 1 | C242: 1 | D242: 1 | E242: 1 | F242: TBA 3B

Sheet Annex 6 New or Amended EHV
A1: Back to Overview | H1: Note: The list of MPANs/MSIDs provided may be incomplete; the DNO reserves the right to apply the listed charges to any other MPANs/MSIDs associated with the site. If sites appear in both Annex 2 and Annex 6, the charges in Annex 6 take precedence. Where an existing Designated EHV Property is modified and energised in the charging year, we may revise the EDCM charges for the modified Designated EHV Property.
A2: Annex 6 - Charges for New or Amended Designated EHV Properties
A4: =Overview!B4& " - Effective from "&Overview!D4&" - "&Overview!E4&" new designated EHV charges" -> SP Distribution - Effective from 1 April 2022 - Final new designated EHV charges
A5: Effective from date | B5: Import Unique Identifier | C5: LLFC | D5: Import MPANs/MSIDs | E5: Export Unique Identifier | F5: LLFC | G5: Export MPANs/MSIDs | H5: Name | I5: ='Annex 2 EHV charges'!H10 -> Import Super Red unit charge (p/kWh) | J5: ='Annex 2 EHV charges'!I10 -> Import fixed charge (p/day) | K5: ='Annex 2 EHV charges'!J10 -> Import capacity charge (p/kVA/day) | L5: ='Annex 2 EHV charges'!K10 -> Import exceeded capacity charge (p/kVA/day) | M5: ='Annex 2 EHV charges'!L10 -> Export Super Red unit charge (p/kWh) | N5: ='Annex 2 EHV charges'!M10 -> Export fixed charge (p/day) | O5: ='Annex 2 EHV charges'!N10 -> Export capacity charge (p/kVA/day) | P5: ='Annex 2 EHV charges'!O10 -> Export exceeded capacity charge (p/kVA/day)
A6: 44652 | B6: EDCM import 1 | C6: 897 | D6: 1800061146877 | E6: EDCM export 1 | F6: 715 | G6: 1800061146886 | H6: South Redhouse ESS | I6: 0 | J6: 819.09 | K6: 1.57 | L6: 1.57 | M6: -1.274 | N6: 775.96 | O6: 0.05 | P6: 0.05
A7: 44652 | B7: EDCM import 2 | C7: 328 | D7: 1800060586917 | E7: EDCM export 2 | F7: 750 | G7: 1800060586926 | H7: Cathkin Braes Wind Farm | I7: - | J7: 3228.5721 | K7: 0.82 | L7: 0.82 | M7: - | N7: 5573.54 | O7: 0.05 | P7: 0.05
A8: 44652 | B8: EDCM import 3 | C8: 823 | D8: 1800060697223 | E8: EDCM export 3 | F8: 704 | G8: 1800060697232 | H8: Langhope Rig (D) WF | I8: - | J8: 2918.2821 | K8: 1.37 | L8: 1.37 | M8: - | N8: 1400.11 | O8: 0.05 | P8: 0.05
A9: 44652 | B9: EDCM import 4 | C9: 840 | D9: 1800053434271 | E9: EDCM export 4 | F9: 640 | G9: 1800053883993 | H9: Artfield WF | I9: - | J9: 3636.6421 | K9: - | L9: - | M9: - | N9: - | O9: - | P9: -
A10: 44652 | B10: EDCM import 5 | C10: 855 | D10: 1800060241304 | E10: EDCM export 5 | F10: 655 | G10: 1800060241313 | H10: Pateshill | I10: - | J10: 2898.3121 | K10: 0.93 | L10: 0.93 | M10: - | N10: 1272.56 | O10: 0.05 | P10: 0.05
A11: 44652 | B11: EDCM import 7 | C11: 875 | D11: 1800060450524 | E11: EDCM export 7 | F11: 675 | G11: 1800060450533 | H11: Kelburn (A) | I11: - | J11: 3052.3221 | K11: 0.92 | L11: 0.92 | M11: - | N11: 8828.47 | O11: 0.05 | P11: 0.05
A12: 44652 | B12: EDCM import 8 | C12: 876 | D12: 1800060450542 | E12: EDCM export 8 | F12: 676 | G12: 1800060450551 | H12: Kelburn (B) | I12: - | J12: 3052.3221 | K12: 0.92 | L12: 0.92 | M12: - | N12: 8828.47 | O12: 0.05 | P12: 0.05
A13: 44652 | B13: EDCM import 9 | C13: 877 | D13: 1800060450506 | E13: EDCM export 9 | F13: 677 | G13: 1800060450515 | H13: Little Raith | I13: - | J13: 3069.5721 | K13: 0.73 | L13: 0.73 | M13: - | N13: 5334.32 | O13: 0.05 | P13: 0.05
A14: 44652 | B14: EDCM import 10 | C14: 890 | D14: 1800061032840 | E14: EDCM export 10 | F14: MSID 8366 | G14: MSID 8366 | H14: Solwaybank | I14: - | J14: 2935.6721 | K14: 1.05 | L14: 1.05 | M14: - | N14: 21079.68 | O14: 0.05 | P14: 0.05
A15: 44652 | B15: EDCM import 11 | C15: 324 | D15: 1800035334227 | E15: EDCM export 11 | H15: Edinburgh Dock North | I15: - | J15: 31693.822 | K15: 1.49 | L15: 1.49
A16: 44652 | B16: EDCM import 12 | C16: 871 | D16: 1800061211922 | E16: EDCM export 12 | F16: 623 | G16: 1800061211931 | H16: Watsonhead | I16: 0 | J16: 102.83 | K16: 1.23 | L16: 1.23 | M16: 0 | N16: 8720.34 | O16: 0.05 | P16: 0.05
A17: 44652 | B17: EDCM import 13 | C17: 912 | D17: 1800061228633 | E17: EDCM export 13 | F17: 682 | G17: 1800061228642 | H17: Longhill Burn WF | I17: 0 | J17: 257.09 | K17: 1.05 | L17: 1.05 | M17: 0 | N17: 42282.93 | O17: 0.05 | P17: 0.05
A18: 44652 | B18: EDCM import 14 | C18: 919 | D18: 1800061252352 | E18: EDCM export 14 | F18: 619 | G18: 1800061252361 | H18: Caledon Gas | I18: 0 | J18: 227.77 | K18: 1.05 | L18: 1.05 | M18: 0 | N18: 6828.46 | O18: 0.05 | P18: 0.05
A19: 44652 | B19: EDCM import 15 | C19: 857 | D19: 1800061230181 | E19: EDCM export 15 | F19: 647 | G19: 1800061230190 | H19: Howpark Windfarm | I19: 0 | J19: 152.31 | K19: 1.23 | L19: 1.23 | M19: 0 | N19: 13291.45 | O19: 0.05 | P19: 0.05
A20: 44652 | B20: EDCM import 16 | C20: 849 | D20: 1800061236634 | E20: EDCM export 16 | F20: 649 | G20: 1800061236643 | H20: Sorbie Windfarm | I20: 0 | J20: 609.62 | K20: 1.05 | L20: 1.05 | M20: 0 | N20: 6081.1 | O20: 0.05 | P20: 0.05
A21: 44652 | B21: EDCM import 17 | C21: 334 | D21: 1800061268316 | E21: EDCM export 17 | F21: 753 | G21: 1800061268325 | H21: Edinburgh Airport | I21: 0.201 | J21: 9972.52 | K21: 3.87 | L21: 3.87 | M21: - | N21: 17.16 | O21: 0.05 | P21: 0.05
A22: 44652 | B22: EDCM import 1 | C22: 859 | D22: 1800035320127 | E22: EDCM export 18 | F22: 697 | G22: 1800060630637 | H22: GlaxoSmithKline | I22: - | J22: 24804.641 | K22: 1.63 | L22: 1.63 | M22: 0 | N22: 2475.97 | O22: 0.05 | P22: 0.05
A25: =Overview!B4& " - Effective from "&Overview!D4&" - "&Overview!E4&" new designated EHV line loss factors" -> SP Distribution - Effective from 1 April 2022 - Final new designated EHV line loss factors
A26: Effective from date | B26: Import Unique Identifier | C26: LLFC | D26: Import MPANs/MSIDs | E26: Export Unique Identifier | F26: LLFC | G26: Export MPANs/MSIDs | H26: Name | I26: Import LLF period 1 | J26: Import LLF period 2 | K26: Import LLF period 3 | L26: Import LLF period 4 | M26: Export LLF period 1 | N26: Export LLF period 2 | O26: Export LLF period 3 | P26: Export LLF period 4
A27: =IF(A6="","",A6) -> 44652 | B27: =IF(B6="","",B6) -> EDCM import 1 | C27: =IF(C6="","",C6) -> 897 | D27: =IF(D6="","",D6) -> 1800061146877 | E27: =IF(E6="","",E6) -> EDCM export 1 | F27: =IF(F6="","",F6) -> 715 | G27: =IF(G6="","",G6) -> 1800061146886 | H27: =IF(H6="","",H6) -> South Redhouse ESS | I27: 1.003 | J27: 1.004 | K27: 1.004 | L27: 1.005 | M27: 1 | N27: 1 | O27: 1 | P27: 1
A28: =IF(A7="","",A7) -> 44652 | B28: =IF(B7="","",B7) -> EDCM import 2 | C28: =IF(C7="","",C7) -> 328 | D28: =IF(D7="","",D7) -> 1800060586917 | E28: =IF(E7="","",E7) -> EDCM export 2 | F28: =IF(F7="","",F7) -> 750 | G28: =IF(G7="","",G7) -> 1800060586926 | H28: =IF(H7="","",H7) -> Cathkin Braes Wind Farm | I28: 1.003 | J28: 1.004 | K28: 1.004 | L28: 1.005 | M28: 1 | N28: 1 | O28: 1 | P28: 1
A29: =IF(A8="","",A8) -> 44652 | B29: =IF(B8="","",B8) -> EDCM import 3 | C29: =IF(C8="","",C8) -> 823 | D29: =IF(D8="","",D8) -> 1800060697223 | E29: =IF(E8="","",E8) -> EDCM export 3 | F29: =IF(F8="","",F8) -> 704 | G29: =IF(G8="","",G8) -> 1800060697232 | H29: =IF(H8="","",H8) -> Langhope Rig (D) WF | I29: =VLOOKUP($H29,'Annex 5 LLFs'!$A$27:$F$133,2,FALSE) -> 1.003 | J29: =VLOOKUP($H29,'Annex 5 LLFs'!$A$27:$F$133,3,FALSE) -> 1.004 | K29: =VLOOKUP($H29,'Annex 5 LLFs'!$A$27:$F$133,4,FALSE) -> 1.004 | L29: =VLOOKUP($H29,'Annex 5 LLFs'!$A$27:$F$133,5,FALSE) -> 1.005 | M29: =VLOOKUP($H29,'Annex 5 LLFs'!$A$139:$F$242,2,FALSE) -> 1 | N29: =VLOOKUP($H29,'Annex 5 LLFs'!$A$139:$F$242,3,FALSE) -> 1 | O29: =VLOOKUP($H29,'Annex 5 LLFs'!$A$139:$F$242,4,FALSE) -> 1 | P29: =VLOOKUP($H29,'Annex 5 LLFs'!$A$139:$F$242,5,FALSE) -> 1
A30: =IF(A9="","",A9) -> 44652 | B30: =IF(B9="","",B9) -> EDCM import 4 | C30: =IF(C9="","",C9) -> 840 | D30: =IF(D9="","",D9) -> 1800053434271 | E30: =IF(E9="","",E9) -> EDCM export 4 | F30: =IF(F9="","",F9) -> 640 | G30: =IF(G9="","",G9) -> 1800053883993 | H30: =IF(H9="","",H9) -> Artfield WF | I30: =VLOOKUP($H30,'Annex 5 LLFs'!$A$27:$F$133,2,FALSE) -> 1.003 | J30: =VLOOKUP($H30,'Annex 5 LLFs'!$A$27:$F$133,3,FALSE) -> 1.004 | K30: =VLOOKUP($H30,'Annex 5 LLFs'!$A$27:$F$133,4,FALSE) -> 1.005 | L30: =VLOOKUP($H30,'Annex 5 LLFs'!$A$27:$F$133,5,FALSE) -> 1.005 | M30: =VLOOKUP($H30,'Annex 5 LLFs'!$A$139:$F$242,2,FALSE) -> 1 | N30: =VLOOKUP($H30,'Annex 5 LLFs'!$A$139:$F$242,3,FALSE) -> 1 | O30: =VLOOKUP($H30,'Annex 5 LLFs'!$A$139:$F$242,4,FALSE) -> 1 | P30: =VLOOKUP($H30,'Annex 5 LLFs'!$A$139:$F$242,5,FALSE) -> 1
A31: =IF(A10="","",A10) -> 44652 | B31: =IF(B10="","",B10) -> EDCM import 5 | C31: =IF(C10="","",C10) -> 855 | D31: =IF(D10="","",D10) -> 1800060241304 | E31: =IF(E10="","",E10) -> EDCM export 5 | F31: =IF(F10="","",F10) -> 655 | G31: =IF(G10="","",G10) -> 1800060241313 | H31: =IF(H10="","",H10) -> Pateshill | I31: =VLOOKUP($H31,'Annex 5 LLFs'!$A$27:$F$133,2,FALSE) -> 1.003 | J31: =VLOOKUP($H31,'Annex 5 LLFs'!$A$27:$F$133,3,FALSE) -> 1.004 | K31: =VLOOKUP($H31,'Annex 5 LLFs'!$A$27:$F$133,4,FALSE) -> 1.005 | L31: =VLOOKUP($H31,'Annex 5 LLFs'!$A$27:$F$133,5,FALSE) -> 1.005 | M31: =VLOOKUP($H31,'Annex 5 LLFs'!$A$139:$F$242,2,FALSE) -> 0.998 | N31: =VLOOKUP($H31,'Annex 5 LLFs'!$A$139:$F$242,3,FALSE) -> 0.998 | O31: =VLOOKUP($H31,'Annex 5 LLFs'!$A$139:$F$242,4,FALSE) -> 0.997 | P31: =VLOOKUP($H31,'Annex 5 LLFs'!$A$139:$F$242,5,FALSE) -> 0.997
A32: =IF(A11="","",A11) -> 44652 | B32: =IF(B11="","",B11) -> EDCM import 7 | C32: =IF(C11="","",C11) -> 875 | D32: =IF(D11="","",D11) -> 1800060450524 | E32: =IF(E11="","",E11) -> EDCM export 7 | F32: =IF(F11="","",F11) -> 675 | G32: =IF(G11="","",G11) -> 1800060450533 | H32: =IF(H11="","",H11) -> Kelburn (A) | I32: =VLOOKUP($H32,'Annex 5 LLFs'!$A$27:$F$133,2,FALSE) -> 1.003 | J32: =VLOOKUP($H32,'Annex 5 LLFs'!$A$27:$F$133,3,FALSE) -> 1.004 | K32: =VLOOKUP($H32,'Annex 5 LLFs'!$A$27:$F$133,4,FALSE) -> 1.005 | L32: =VLOOKUP($H32,'Annex 5 LLFs'!$A$27:$F$133,5,FALSE) -> 1.005 | M32: =VLOOKUP($H32,'Annex 5 LLFs'!$A$139:$F$242,2,FALSE) -> 0.985 | N32: =VLOOKUP($H32,'Annex 5 LLFs'!$A$139:$F$242,3,FALSE) -> 0.986 | O32: =VLOOKUP($H32,'Annex 5 LLFs'!$A$139:$F$242,4,FALSE) -> 0.986 | P32: =VLOOKUP($H32,'Annex 5 LLFs'!$A$139:$F$242,5,FALSE) -> 0.987
A33: =IF(A12="","",A12) -> 44652 | B33: =IF(B12="","",B12) -> EDCM import 8 | C33: =IF(C12="","",C12) -> 876 | D33: =IF(D12="","",D12) -> 1800060450542 | E33: =IF(E12="","",E12) -> EDCM export 8 | F33: =IF(F12="","",F12) -> 676 | G33: =IF(G12="","",G12) -> 1800060450551 | H33: =IF(H12="","",H12) -> Kelburn (B) | I33: =VLOOKUP($H33,'Annex 5 LLFs'!$A$27:$F$133,2,FALSE) -> 1.003 | J33: =VLOOKUP($H33,'Annex 5 LLFs'!$A$27:$F$133,3,FALSE) -> 1.004 | K33: =VLOOKUP($H33,'Annex 5 LLFs'!$A$27:$F$133,4,FALSE) -> 1.005 | L33: =VLOOKUP($H33,'Annex 5 LLFs'!$A$27:$F$133,5,FALSE) -> 1.005 | M33: =VLOOKUP($H33,'Annex 5 LLFs'!$A$139:$F$242,2,FALSE) -> 1.005 | N33: =VLOOKUP($H33,'Annex 5 LLFs'!$A$139:$F$242,3,FALSE) -> 1.013 | O33: =VLOOKUP($H33,'Annex 5 LLFs'!$A$139:$F$242,4,FALSE) -> 1.02 | P33: =VLOOKUP($H33,'Annex 5 LLFs'!$A$139:$F$242,5,FALSE) -> 1.027
A34: =IF(A13="","",A13) -> 44652 | B34: =IF(B13="","",B13) -> EDCM import 9 | C34: =IF(C13="","",C13) -> 877 | D34: =IF(D13="","",D13) -> 1800060450506 | E34: =IF(E13="","",E13) -> EDCM export 9 | F34: =IF(F13="","",F13) -> 677 | G34: =IF(G13="","",G13) -> 1800060450515 | H34: =IF(H13="","",H13) -> Little Raith | I34: =VLOOKUP($H34,'Annex 5 LLFs'!$A$27:$F$133,2,FALSE) -> 1.003 | J34: =VLOOKUP($H34,'Annex 5 LLFs'!$A$27:$F$133,3,FALSE) -> 1.004 | K34: =VLOOKUP($H34,'Annex 5 LLFs'!$A$27:$F$133,4,FALSE) -> 1.005 | L34: =VLOOKUP($H34,'Annex 5 LLFs'!$A$27:$F$133,5,FALSE) -> 1.005 | M34: =VLOOKUP($H34,'Annex 5 LLFs'!$A$139:$F$242,2,FALSE) -> 0.999 | N34: =VLOOKUP($H34,'Annex 5 LLFs'!$A$139:$F$242,3,FALSE) -> 0.999 | O34: =VLOOKUP($H34,'Annex 5 LLFs'!$A$139:$F$242,4,FALSE) -> 0.998 | P34: =VLOOKUP($H34,'Annex 5 LLFs'!$A$139:$F$242,5,FALSE) -> 0.998
A35: =IF(A14="","",A14) -> 44652 | B35: =IF(B14="","",B14) -> EDCM import 10 | C35: =IF(C14="","",C14) -> 890 | D35: =IF(D14="","",D14) -> 1800061032840 | E35: =IF(E14="","",E14) -> EDCM export 10 | F35: =IF(F14="","",F14) -> MSID 8366 | G35: =IF(G14="","",G14) -> MSID 8366 | H35: =IF(H14="","",H14) -> Solwaybank | I35: =VLOOKUP($H35,'Annex 5 LLFs'!$A$27:$F$133,2,FALSE) -> 1.003 | J35: =VLOOKUP($H35,'Annex 5 LLFs'!$A$27:$F$133,3,FALSE) -> 1.004 | K35: =VLOOKUP($H35,'Annex 5 LLFs'!$A$27:$F$133,4,FALSE) -> 1.004 | L35: =VLOOKUP($H35,'Annex 5 LLFs'!$A$27:$F$133,5,FALSE) -> 1.005 | M35: =VLOOKUP($H35,'Annex 5 LLFs'!$A$139:$F$242,2,FALSE) -> 1 | N35: =VLOOKUP($H35,'Annex 5 LLFs'!$A$139:$F$242,3,FALSE) -> 1 | O35: =VLOOKUP($H35,'Annex 5 LLFs'!$A$139:$F$242,4,FALSE) -> 1 | P35: =VLOOKUP($H35,'Annex 5 LLFs'!$A$139:$F$242,5,FALSE) -> 1
A36: =IF(A15="","",A15) -> 44652 | B36: =IF(B15="","",B15) -> EDCM import 11 | C36: =IF(C15="","",C15) -> 324 | D36: =IF(D15="","",D15) -> 1800035334227 | E36: =IF(E15="","",E15) -> EDCM export 11 | F36: =IF(F15="","",F15) | G36: =IF(G15="","",G15) | H36: =IF(H15="","",H15) -> Edinburgh Dock North | I36: 1.013 | J36: 1.013 | K36: 1.013 | L36: 1.013
A37: =IF(A16="","",A16) -> 44652 | B37: =IF(B16="","",B16) -> EDCM import 12 | C37: =IF(C16="","",C16) -> 871 | D37: =IF(D16="","",D16) -> 1800061211922 | E37: =IF(E16="","",E16) -> EDCM export 12 | F37: =IF(F16="","",F16) -> 623 | G37: =IF(G16="","",G16) -> 1800061211931 | H37: =IF(H16="","",H16) -> Watsonhead | I37: 1.003 | J37: 1.004 | K37: 1.004 | L37: 1.005 | M37: 1 | N37: 1 | O37: 1 | P37: 1
A38: =IF(A17="","",A17) -> 44652 | B38: =IF(B17="","",B17) -> EDCM import 13 | C38: =IF(C17="","",C17) -> 912 | D38: =IF(D17="","",D17) -> 1800061228633 | E38: =IF(E17="","",E17) -> EDCM export 13 | F38: =IF(F17="","",F17) -> 682 | G38: =IF(G17="","",G17) -> 1800061228642 | H38: =IF(H17="","",H17) -> Longhill Burn WF | I38: 1.003 | J38: 1.004 | K38: 1.004 | L38: 1.005 | M38: 1 | N38: 1 | O38: 1 | P38: 1
A39: =IF(A18="","",A18) -> 44652 | B39: =IF(B18="","",B18) -> EDCM import 14 | C39: =IF(C18="","",C18) -> 919 | D39: =IF(D18="","",D18) -> 1800061252352 | E39: =IF(E18="","",E18) -> EDCM export 14 | F39: =IF(F18="","",F18) -> 619 | G39: =IF(G18="","",G18) -> 1800061252361 | H39: =IF(H18="","",H18) -> Caledon Gas | I39: 1.003 | J39: 1.004 | K39: 1.004 | L39: 1.005 | M39: 1 | N39: 1 | O39: 1 | P39: 1
A40: =IF(A19="","",A19) -> 44652 | B40: =IF(B19="","",B19) -> EDCM import 15 | C40: =IF(C19="","",C19) -> 857 | D40: =IF(D19="","",D19) -> 1800061230181 | E40: =IF(E19="","",E19) -> EDCM export 15 | F40: =IF(F19="","",F19) -> 647 | G40: =IF(G19="","",G19) -> 1800061230190 | H40: =IF(H19="","",H19) -> Howpark Windfarm | I40: 1.003 | J40: 1.004 | K40: 1.004 | L40: 1.005 | M40: 1 | N40: 1 | O40: 1 | P40: 1
A41: =IF(A20="","",A20) -> 44652 | B41: =IF(B20="","",B20) -> EDCM import 16 | C41: =IF(C20="","",C20) -> 849 | D41: =IF(D20="","",D20) -> 1800061236634 | E41: =IF(E20="","",E20) -> EDCM export 16 | F41: =IF(F20="","",F20) -> 649 | G41: =IF(G20="","",G20) -> 1800061236643 | H41: =IF(H20="","",H20) -> Sorbie Windfarm | I41: 1.003 | J41: 1.004 | K41: 1.004 | L41: 1.005 | M41: 1 | N41: 1 | O41: 1 | P41: 1
A42: =IF(A21="","",A21) -> 44652 | B42: =IF(B21="","",B21) -> EDCM import 17 | C42: =IF(C21="","",C21) -> 334 | D42: =IF(D21="","",D21) -> 1800061268316 | E42: =IF(E21="","",E21) -> EDCM export 17 | F42: =IF(F21="","",F21) -> 753 | G42: =IF(G21="","",G21) -> 1800061268325 | H42: =IF(H21="","",H21) -> Edinburgh Airport

Sheet Annex 7 Pass-Through Costs
A1: Back to Overview
A2: =Overview!B4& " - Effective from "&Overview!D4&" - "&Overview!E4&" Supplier of Last Resort and Eligible Bad Debt Pass-Through Costs" -> SP Distribution - Effective from 1 April 2022 - Final Supplier of Last Resort and Eligible Bad Debt Pass-Through Costs
A4: Tariff name | B4: Open LLFCs / LDNO unique billing identifier | C4: PCs | D4: Supplier of Last Resort Fixed charge adder* p/MPAN/day | E4: Excess Supplier of Last Resort Fixed charge adder** p/MPAN/day | F4: Eligible Bad Debt Fixed charge adder*** p/MPAN/day | G4: 1
A5: Domestic Aggregated | C5: 0, 1, 2 | D5: 0.079771088 | E5: 9.263345 | F5: 0.034491697 | G5: 1
A6: Non-Domestic Aggregated No Residual | C6: 0, 3, 4, 5-8 | F6: 0.034491697 | G6: 1
A7: Non-Domestic Aggregated Band 1 | C7: 0, 3, 4, 5-8 | F7: 0.034491697 | G7: 1
A8: Non-Domestic Aggregated Band 2 | C8: 0, 3, 4, 5-8 | F8: 0.034491697 | G8: 1
A9: Non-Domestic Aggregated Band 3 | C9: 0, 3, 4, 5-8 | F9: 0.034491697 | G9: 1
A10: Non-Domestic Aggregated Band 4 | C10: 0, 3, 4, 5-8 | F10: 0.034491697 | G10: 1
A11: LV Site Specific No Residual | C11: 0 | F11: 0.034491697 | G11: 1
A12: LV Site Specific Band 1 | C12: 0 | F12: 0.034491697 | G12: 1
A13: LV Site Specific Band 2 | C13: 0 | F13: 0.034491697 | G13: 1
A14: LV Site Specific Band 3 | C14: 0 | F14: 0.034491697 | G14: 1
A15: LV Site Specific Band 4 | C15: 0 | F15: 0.034491697 | G15: 1
A16: LV Sub Site Specific No Residual | C16: 0 | F16: 0.034491697 | G16: 1
A17: LV Sub Site Specific Band 1 | C17: 0 | F17: 0.034491697 | G17: 1
A18: LV Sub Site Specific Band 2 | C18: 0 | F18: 0.034491697 | G18: 1
A19: LV Sub Site Specific Band 3 | C19: 0 | F19: 0.034491697 | G19: 1
A20: LV Sub Site Specific Band 4 | C20: 0 | F20: 0.034491697 | G20: 1
A21: HV Site Specific No Residual | C21: 0 | F21: 0.034491697 | G21: 1
A22: HV Site Specific Band 1 | C22: 0 | F22: 0.034491697 | G22: 1
... A25: HV Site Specific Band 4 | C25: 0 | F25: 0.034491697 | G25: 1
A26: LDNO LV: Domestic Aggregated | C26: 0, 1, 2 | D26: 0.079771088 | E26: 9.263345 | F26: 0.034491697 | G26: 1
A27: LDNO LV: Non-Domestic Aggregated No Residual | C27: 0, 3, 4, 5-8 | F27: 0.034491697 | G27: 1
A28: LDNO LV: Non-Domestic Aggregated Band 1 | C28: 0, 3, 4, 5-8 | F28: 0.034491697 | G28: 1
A29: LDNO LV: Non-Domestic Aggregated Band 2 | C29: 0, 3, 4, 5-8 | F29: 0.034491697 | G29: 1
A30: LDNO LV: Non-Domestic Aggregated Band 3 | C30: 0, 3, 4, 5-8 | F30: 0.034491697 | G30: 1
A31: LDNO LV: Non-Domestic Aggregated Band 4 | C31: 0, 3, 4, 5-8 | F31: 0.034491697 | G31: 1
A32: LDNO LV: LV Site Specific No Residual | C32: 0 | F32: 0.034491697 | G32: 1
A33: LDNO LV: LV Site Specific Band 1 | C33: 0 | F33: 0.034491697 | G33: 1
A34: LDNO LV: LV Site Specific Band 2 | C34: 0 | F34: 0.034491697 | G34: 1
A35: LDNO LV: LV Site Specific Band 3 | C35: 0 | F35: 0.034491697 | G35: 1
A36: LDNO LV: LV Site Specific Band 4 | C36: 0 | F36: 0.034491697 | G36: 1
A37: LDNO HV: Domestic Aggregated | C37: 0, 1, 2 | D37: 0.079771088 | E37: 9.263345 | F37: 0.034491697 | G37: 1
A38: LDNO HV: Non-Domestic Aggregated No Residual | C38: 0, 3, 4, 5-8 | F38: 0.034491697 | G38: 2
A39: LDNO HV: Non-Domestic Aggregated Band 1 | C39: 0, 3, 4, 5-8 | F39: 0.034491697 | G39: 2
A40: LDNO HV: Non-Domestic Aggregated Band 2 | C40: 0, 3, 4, 5-8 | F40: 0.034491697 | G40: 2
A41: LDNO HV: Non-Domestic Aggregated Band 3 | C41: 0, 3, 4, 5-8 | F41: 0.034491697 | G41: 2
A42: LDNO HV: Non-Domestic Aggregated Band 4 | C42: 0, 3, 4, 5-8 | F42: 0.034491697 | G42: 2
A43: LDNO HV: LV Site Specific No Residual | C43: 0 | F43: 0.034491697 | G43: 2
A44: LDNO HV: LV Site Specific Band 1 | C44: 0 | F44: 0.034491697 | G44: 2
A45: LDNO HV: LV Site Specific Band 2 | C45: 0 | F45: 0.034491697 | G45: 2
A46: LDNO HV: LV Site Specific Band 3 | C46: 0 | F46: 0.034491697 | G46: 2
A47: LDNO HV: LV Site Specific Band 4 | C47: 0 | F47: 0.034491697 | G47: 2
A48: LDNO HV: LV Sub Site Specific No Residual | C48: 0 | F48: 0.034491697 | G48: 2
A49: LDNO HV: LV Sub Site Specific Band 1 | C49: 0 | F49: 0.034491697 | G49: 2
A50: LDNO HV: LV Sub Site Specific Band 2 | C50: 0 | F50: 0.034491697 | G50: 2
A51: LDNO HV: LV Sub Site Specific Band 3 | C51: 0 | F51: 0.034491697 | G51: 2
A52: LDNO HV: LV Sub Site Specific Band 4 | C52: 0 | F52: 0.034491697 | G52: 2
A53: LDNO HV: HV Site Specific No Residual | C53: 0 | F53: 0.034491697 | G53: 2
A54: LDNO HV: HV Site Specific Band 1 | C54: 0 | F54: 0.034491697 | G54: 2
... A57: LDNO HV: HV Site Specific Band 4 | C57: 0 | F57: 0.034491697 | G57: 2
A58: LDNO HVplus: Domestic Aggregated | C58: 0, 1, 2 | D58: 0.079771088 | E58: 9.263345 | F58: 0.034491697 | G58: 2
A59: LDNO HVplus: Non-Domestic Aggregated No Residual | C59: 0, 3, 4, 5-8 | F59: 0.034491697 | G59: 2
A60: LDNO HVplus: Non-Domestic Aggregated Band 1 | C60: 0, 3, 4, 5-8 | F60: 0.034491697 | G60: 2
A61: LDNO HVplus: Non-Domestic Aggregated Band 2 | C61: 0, 3, 4, 5-8 | F61: 0.034491697 | G61: 2
A62: LDNO HVplus: Non-Domestic Aggregated Band 3 | C62: 0, 3, 4, 5-8 | F62: 0.034491697 | G62: 2
A63: LDNO HVplus: Non-Domestic Aggregated Band 4 | C63: 0, 3, 4, 5-8 | F63: 0.034491697 | G63: 2
A64: LDNO HVplus: LV Site Specific No Residual | C64: 0 | F64: 0.034491697 | G64: 2
A65: LDNO HVplus: LV Site Specific Band 1 | C65: 0 | F65: 0.034491697 | G65: 2
A66: LDNO HVplus: LV Site Specific Band 2 | C66: 0 | F66: 0.034491697 | G66: 2
A67: LDNO HVplus: LV Site Specific Band 3 | C67: 0 | F67: 0.034491697 | G67: 2
A68: LDNO HVplus: LV Site Specific Band 4 | C68: 0 | F68: 0.034491697 | G68: 2
A69: LDNO HVplus: LV Sub Site Specific No Residual | C69: 0 | F69: 0.034491697 | G69: 2
A70: LDNO HVplus: LV Sub Site Specific Band 1 | C70: 0 | F70: 0.034491697 | G70: 2
A71: LDNO HVplus: LV Sub Site Specific Band 2 | C71: 0 | F71: 0.034491697 | G71: 2
A72: LDNO HVplus: LV Sub Site Specific Band 3 | C72: 0 | F72: 0.034491697 | G72: 2
A73: LDNO HVplus: LV Sub Site Specific Band 4 | C73: 0 | F73: 0.034491697 | G73: 3
A74: LDNO HVplus: HV Site Specific No Residual | C74: 0 | F74: 0.034491697 | G74: 3
A75: LDNO HVplus: HV Site Specific Band 1 | C75: 0 | F75: 0.034491697 | G75: 3
... A78: LDNO HVplus: HV Site Specific Band 4 | C78: 0 | F78: 0.034491697 | G78: 3
A79: LDNO EHV: Domestic Aggregated | C79: 0, 1, 2 | D79: 0.079771088 | E79: 9.263345 | F79: 0.034491697 | G79: 3
A80: LDNO EHV: Non-Domestic Aggregated No Residual | C80: 0, 3, 4, 5-8 | F80: 0.034491697 | G80: 3
A81: LDNO EHV: Non-Domestic Aggregated Band 1 | C81: 0, 3, 4, 5-8 | F81: 0.034491697 | G81: 3
A82: LDNO EHV: Non-Domestic Aggregated Band 2 | C82: 0, 3, 4, 5-8 | F82: 0.034491697 | G82: 3
A83: LDNO EHV: Non-Domestic Aggregated Band 3 | C83: 0, 3, 4, 5-8 | F83: 0.034491697 | G83: 3
A84: LDNO EHV: Non-Domestic Aggregated Band 4 | C84: 0, 3, 4, 5-8 | F84: 0.034491697 | G84: 3
A85: LDNO EHV: LV Site Specific No Residual | C85: 0 | F85: 0.034491697 | G85: 3
A86: LDNO EHV: LV Site Specific Band 1 | C86: 0 | F86: 0.034491697 | G86: 3
A87: LDNO EHV: LV Site Specific Band 2 | C87: 0 | F87: 0.034491697 | G87: 3
A88: LDNO EHV: LV Site Specific Band 3 | C88: 0 | F88: 0.034491697 | G88: 3
A89: LDNO EHV: LV Site Specific Band 4 | C89: 0 | F89: 0.034491697 | G89: 3
A90: LDNO EHV: LV Sub Site Specific No Residual | C90: 0 | F90: 0.034491697 | G90: 3
A91: LDNO EHV: LV Sub Site Specific Band 1 | C91: 0 | F91: 0.034491697 | G91: 3
A92: LDNO EHV: LV Sub Site Specific Band 2 | C92: 0 | F92: 0.034491697 | G92: 3
A93: LDNO EHV: LV Sub Site Specific Band 3 | C93: 0 | F93: 0.034491697 | G93: 3
A94: LDNO EHV: LV Sub Site Specific Band 4 | C94: 0 | F94: 0.034491697 | G94: 3
A95: LDNO EHV: HV Site Specific No Residual | C95: 0 | F95: 0.034491697 | G95: 3
A96: LDNO EHV: HV Site Specific Band 1 | C96: 0 | F96: 0.034491697 | G96: 3
... A99: LDNO EHV: HV Site Specific Band 4 | C99: 0 | F99: 0.034491697 | G99: 3
A100: LDNO 132kV/EHV: Domestic Aggregated | C100: 0, 1, 2 | D100: 0.079771088 | E100: 9.263345 | F100: 0.034491697 | G100: 3
A101: LDNO 132kV/EHV: Non-Domestic Aggregated No Residual | C101: 0, 3, 4, 5-8 | F101: 0.034491697 | G101: 3
A102: LDNO 132kV/EHV: Non-Domestic Aggregated Band 1 | C102: 0, 3, 4, 5-8 | F102: 0.034491697 | G102: 3
A103: LDNO 132kV/EHV: Non-Domestic Aggregated Band 2 | C103: 0, 3, 4, 5-8 | F103: 0.034491697 | G103: 3
A104: LDNO 132kV/EHV: Non-Domestic Aggregated Band 3 | C104: 0, 3, 4, 5-8 | F104: 0.034491697 | G104: 3
A105: LDNO 132kV/EHV: Non-Domestic Aggregated Band 4 | C105: 0, 3, 4, 5-8 | F105: 0.034491697 | G105: 3
A106: LDNO 132kV/EHV: LV Site Specific No Residual | C106: 0 | F106: 0.034491697 | G106: 3
A107: LDNO 132kV/EHV: LV Site Specific Band 1 | C107: 0 | F107: 0.034491697 | G107: 3
A108: LDNO 132kV/EHV: LV Site Specific Band 2 | C108: 0 | F108: 0.034491697 | G108: 4
A109: LDNO 132kV/EHV: LV Site Specific Band 3 | C109: 0 | F109: 0.034491697 | G109: 4
...

Sheet Nodal prices
A1: Back to Overview
A2: =Overview!B4& " - Effective from "&Overview!D4&" - "&Overview!E4&" Nodal/Zonal charges" -> SP Distribution - Effective from 1 April 2022 - Final Nodal/Zonal charges
A3: Node/Zone ID | B3: Geographical name | C3: Local charge 1 £/kVA | D3: Remote charge 1 £/kVA
A4: KILBOWIE 33kV | B4: 2 | D4: 0
A5: CUMBERNAULD | B5: 2 | D5: 0
A6: ST ANDREWS CROSS | B6: 2 | D6: 0
A7: COATBRIDGE | B7: 2 | D7: 0
A8: GLENLUCE & NEWTON STEWART | B8: 2 | D8: 0.0056164102
A9: DEVONSIDE | B9: 2 | D9: 0
A10: CHAPELCROSS | B10: 2 | D10: 0
A11: LINMILL & NEWARTHILL | B11: 2 | D11: 0
A12: SHRUBHILL | B12: 2 | D12: 0
A13: LEVEN | B13: 2 | D13: 0
A14: DRUMCHAPEL | B14: 2 | D14: 0
A15: JOHNSTONE | B15: 2 | D15: 0
... A79: TONGLAND 11kV GSP | B79: 2 | D79: 0
A80: ABBEY/ABBE5-11.000 | B80: 3 | C80: KILBOWIE 33kV | D80: 0
A81: ABRON/ABRL5-11.000 | B81: 3 | C81: CUMBERNAULD | D81: 0
A82: ADMIR/ADMS6-6.6000 | B82: 3 | C82: ST ANDREWS CROSS | D82: 0
A83: AIRDR/AIRD5-11.000 | B83: 3 | C83: COATBRIDGE | D83: 0
A84: ALLOA/ALGA5-11.000 | B84: 3 | C84: DEVONSIDE | D84: 1.9689063
A85: ANNAN/ANAN5-11.000 | B85: 3 | C85: CHAPELCROSS | D85: 2.6481428
A86: ANNFI/ANNF6-6.6000 | B86: 3 | C86: SHRUBHILL | D86: 0
A87: ANSTR/ANST5-11.000 | B87: 3 | C87: LEVEN | D87: 0
A88: ARCHE/ARCR5-11.000 | B88: 3 | C88: DRUMCHAPEL | D88: 0
A89: ARDGO/ARDD5-11.000 | B89: 3 | C89: JOHNSTONE | D89: 0
A90: ARMAD/ARMA5-11.000 | B90: 3 | C90: BATHGATE | D90: 0
A91: ATHLE/ATHL0G11.000 | B91: 3 | C91: CARNTYNE | D91: 0
... A458: AUCHEN1A 11.000 | B458: 3 | C458: STRATHLEVEN | D458: 0

Sheet SSC unit rate lookup
A1: Back to Overview
A28: Standard Settlement Configuration Id | B28: Standard Settlement Configuration Desc | C28: Common Decode | F28: Change implemented | G28: Date | H28: Comments
A29: 3 | B29: 10-hour OP | C29: A/R | F29: Notes updated | G29: 43626 | H29: Updated to reflect DCP 268 which delinks all tariffs from the TPR bands
A30: 4 | B30: 10-hour OP | C30: A/R | F30: Code 1 & 2 changed to A | G30: 43626 | H30: Updated to reflect DCP 268 which delinks all tariffs from the TPR bands
A31: 5 | B31: 10-hour OP + w/e | C31: A/R | F31: Code O changed to A/R | G31: 43626 | H31: Updated to reflect DCP 268 which delinks all tariffs from the TPR bands
A32: 6 | B32: 10.5-hour OP | C32: A/R | F32: Removed TPR | G32: 43626 | H32: Removed TPR lookup element as this no longer effects which rate to apply
A33: 7 | B33: 10.5-hour OP | C33: A/R
A34: 8 | B34: 10.5-hour OP | C34: A/R
A35: 9 | B35: 10.5-hour OP | C35: A/R
A36: 10 | B36: 10.5-hour OP | C36: A/R
A37: 11 | B37: 10.5-hour OP | C37: A/R
A38: 12 | B38: 10.5-hour OP | C38: A/R
A39: 13 | B39: 11 Hour OP | C39: A/R
A40: 15 | B40: 11 Hour OP | C40: A/R
A41: 16 | B41: 11.5-hour OP | C41: A/R
A42: 17 | B42: 11.5-hour OP | C42: A/R
A43: 18 | B43: 11.5-hour OP | C43: A/R
A44: 19 | B44: 11.5-hour OP | C44: A/R
... A764: 997 | B764: Evening/Weekend - BST | C764: A

Sheet Residual Charging Bands
A1: Back to Overview
A2: =Overview!B4& " - Effective from "&Overview!C4&" - "&Overview!E4&" Residual Charging Bands" -> SP Distribution - Effective from 2022/23 - Final Residual Charging Bands
A4: Voltage of Connection | B4: Band | C4: Units | D4: Lower Threshold* | E4: Upper Threshold* | F4: Residual Charge per MPAN (£)
A5: Domestic Aggregated | B5: Single band | C5: - | D5: - | E5: - | F5: 46.7209
A6: Designated Properties connected at LV, billing with no MIC | B6: 1 | C6: kWh | D6: 0 | E6: 3571 | F6: 17.32231
B7: 2 | C7: kWh | D7: 3571 | E7: 12553 | F7: 94.723011
B8: 3 | C8: kWh | D8: 12553 | E8: 25279 | F8: 236.40982
B9: 4 | C9: kWh | D9: 25279 | E9: ∞ | F9: 740.70195
A10: Designated Properties connected at LV, billing with MIC | B10: 1 | C10: kVA | D10: 0 | E10: 80 | F10: 1161.7153
B11: 2 | C11: kVA | D11: 80 | E11: 150 | F11: 2408.3321
B12: 3 | C12: kVA | D12: 150 | E12: 231 | F12: 4021.1739
B13: 4 | C13: kVA | D13: 231 | E13: ∞ | F13: 8909.5694
A14: Designated Properties connected at HV | B14: 1 | C14: kVA | D14: 0 | E14: 422 | F14: 5365.2724
B15: 2 | C15: kVA | D15: 422 | E15: 1000 | F15: 22571.171
B16: 3 | C16: kVA | D16: 1000 | E16: 1800 | F16: 45653.257
B17: 4 | C17: kVA | D17: 1800 | E17: ∞ | F17: 114716.04
A18: Designated EHV Properties | B18: 1 | C18: kVA | D18: 0 | E18: 5000 | F18: 10495.911
B19: 2 | C19: kVA | D19: 5000 | E19: 12000 | F19: 34523.513
B20: 3 | C20: kVA | D20: 12000 | E20: 21500 | F20: 73479.628
B21: 4 | C21: kVA | D21: 21500 | E21: ∞ | F21: 57146.825
A22: * All boundaries are inclusive of the upper threshold and exclusive of the lower threshold i.e. Lower < x ≤ Upper.

Sheet Charge Calculator
B1: Back to Overview
B2: =Overview!B4& " - Effective from "&Overview!D4&" - "&Overview!E4 -> SP Distribution - Effective from 1 April 2022 - Final | AC2: Red/black unit charge p/kWh | AD2: Amber/yellow unit charge p/kWh | AE2: Green unit charge p/kWh | AF2: Fixed charge p/MPAN/day | AG2: Capacity charge p/kVA/day | AH2: Exceeded capacity charge p/kVA/day | AI2: Reactive power charge p/kVArh
AB3: Domestic Aggregated | AC3: Red unit charge p/kWh | AD3: Amber unit charge p/kWh | AE3: Green unit charge p/kWh | AF3: Fixed charge p/MPAN/day | AG3: n/a | AH3: n/a | AI3: n/a
B4: LV and HV designated properties and Unmetered Supplies tariff calculator | L4: EHV designated property calculator | AB4: Domestic Aggregated (related MPAN) | AC4: Red unit charge p/kWh | AD4: Amber unit charge p/kWh | AE4: Green unit charge p/kWh | AF4: n/a | AG4: n/a | AH4: n/a | AI4: n/a
B5: Step 1, Choose your tariff using the drop down list in cell B10 | L5: Step 1, Choose your tariff using the drop down list in cell L10 | AB5: Non-Domestic Aggregated | AC5: Red unit charge p/kWh | AD5: Amber unit charge p/kWh | AE5: Green unit charge p/kWh | AF5: Fixed charge p/MPAN/day | AG5: n/a | AH5: n/a | AI5: n/a
B6: Step 2, After selecting a tariff in step 1, Cells C12-I12 will generate headings, please enter your consumption in cells C13:I13 underneath each heading generated (if no heading leave cell blank) | L6: Step 2, After selecting a tariff in step 1, Cells M12-T12 will generate headings, please enter your consumption in cells M13:T13 underneath each heading generated (if no heading leave cell blank) | AB6: Non-Domestic Aggregated (related MPAN) | AC6: Red unit charge p/kWh | AD6: Amber unit charge p/kWh | AE6: Green unit charge p/kWh | AF6: n/a | AG6: n/a | AH6: n/a | AI6: n/a
B7: Step 3, Enter a forecast of consumption if required in cells C14:I14 | L7: Step 3, Enter a forecast of consumption if required in cells M14:T14 | AB7: LV Site Specific | AC7: Red unit charge p/kWh | AD7: Amber unit charge p/kWh | AE7: Green unit charge p/kWh | AF7: Fixed charge p/MPAN/day | AG7: Capacity charge p/kVA/day | AH7: Exceeded Capacity charge p/kVA/day | AI7: Reactive power charge p/kVArh
AB8: LV Sub Site Specific | AC8: Red unit charge p/kWh | AD8: Amber unit charge p/kWh | AE8: Green unit charge p/kWh | AF8: Fixed charge p/MPAN/day | AG8: Capacity charge p/kVA/day | AH8: Exceeded Capacity charge p/kVA/day | AI8: Reactive power charge p/kVArh
B9: Tariff details Choose tariff name from drop down box below | C9: =IFERROR(VLOOKUP($B$10,$AB$2:$AI$18,2,FALSE),AC2) -> Red unit charge p/kWh | D9: =IFERROR(VLOOKUP($B$10,$AB$2:$AI$18,3,FALSE),AD2) -> Amber unit charge p/kWh | E9: =IFERROR(VLOOKUP($B$10,$AB$2:$AI$18,4,FALSE),AE2) -> Green unit charge p/kWh | F9: =IFERROR(VLOOKUP($B$10,$AB$2:$AI$18,5,FALSE),AF2) -> Fixed charge p/MPAN/day | G9: =IFERROR(VLOOKUP($B$10,$AB$2:$AI$18,6,FALSE),AG2) -> Capacity charge p/kVA/day | H9: =IFERROR(VLOOKUP($B$10,$AB$2:$AI$18,7,FALSE),AH2) -> Exceeded Capacity charge p/kVA/day | I9: =IFERROR(VLOOKUP($B$10,$AB$2:$AI$18,8,FALSE),AI2) -> Reactive power charge p/kVArh | L9: Site details Choose the site name from the drop down box below | M9: ='Annex 2 EHV charges'!H10 -> Import Super Red unit charge (p/kWh) | N9: ='Annex 2 EHV charges'!I10 -> Import fixed charge (p/day) | O9: ='Annex 2 EHV charges'!J10 -> Import capacity charge (p/kVA/day) | P9: ='Annex 2 EHV charges'!K10 -> Import exceeded capacity charge (p/kVA/day) | Q9: ='Annex 2 EHV charges'!L10 -> Export Super Red unit charge (p/kWh) | R9: ='Annex 2 EHV charges'!M10 -> Export fixed charge (p/day) | S9: ='Annex 2 EHV charges'!N10 -> Export capacity charge (p/kVA/day) | T9: ='Annex 2 EHV charges'!O10 -> Export exceeded capacity charge (p/kVA/day) | AB9: HV Site Specific | AC9: Red unit charge p/kWh | AD9: Amber unit charge p/kWh | AE9: Green unit charge p/kWh | AF9: Fixed charge p/MPAN/day | AG9: Capacity charge p/kVA/day | AH9: Exceeded Capacity charge p/kVA/day | AI9: Reactive power charge p/kVArh
B10: LV Site Specific | C10: =IFERROR(VLOOKUP($B$10,'Annex 1 LV, HV and UMS charges'!$A:$K,4,FALSE),"") | D10: =IFERROR(VLOOKUP($B$10,'Annex 1 LV, HV and UMS charges'!$A:$K,5,FALSE),"") | E10: =IFERROR(VLOOKUP($B$10,'Annex 1 LV, HV and UMS charges'!$A:$K,6,FALSE),"") | F10: =IFERROR(VLOOKUP($B$10,'Annex 1 LV, HV and UMS charges'!$A:$K,7,FALSE),"") | G10: =IFERROR(VLOOKUP($B$10,'Annex 1 LV, HV and UMS charges'!$A:$K,8,FALSE),"") | H10: =IFERROR(VLOOKUP($B$10,'Annex 1 LV, HV and UMS charges'!$A:$K,9,FALSE),"") | I10: =IFERROR(VLOOKUP($B$10,'Annex 1 LV, HV and UMS charges'!$A:$K,10,FALSE),"") | M10: =IFERROR(VLOOKUP($L$10,'Annex 2 EHV charges'!$G:$O,2,FALSE),"") | N10: =IFERROR(VLOOKUP($L$10,'Annex 2 EHV charges'!$G:$O,3,FALSE),"") | O10: =IFERROR(VLOOKUP($L$10,'Annex 2 EHV charges'!$G:$O,4,FALSE),"") | P10: =IFERROR(VLOOKUP($L$10,'Annex 2 EHV charges'!$G:$O,5,FALSE),"") | Q10: =IFERROR(VLOOKUP($L$10,'Annex 2 EHV charges'!$G:$O,6,FALSE),"") | R10: =IFERROR(VLOOKUP($L$10,'Annex 2 EHV charges'!$G:$O,7,FALSE),"") | S10: =IFERROR(VLOOKUP($L$10,'Annex 2 EHV charges'!$G:$O,8,FALSE),"") | T10: =IFERROR(VLOOKUP($L$10,'Annex 2 EHV charges'!$G:$O,9,FALSE),"") | AB10: Unmetered Supplies | AC10: Black unit charge p/kWh | AD10: Yellow unit charge p/kWh | AE10: Green unit charge p/kWh | AF10: n/a | AG10: n/a | AH10: n/a | AI10: n/a
AB11: LV Generation Aggregated | AC11: Red unit charge p/kWh | AD11: Amber unit charge p/kWh | AE11: Green unit charge p/kWh | AF11: Fixed charge p/MPAN/day | AG11: n/a | AH11: n/a | AI11: n/a
B12: Tariff components | C12: =C9 -> Red unit charge p/kWh | D12: =D9 -> Amber unit charge p/kWh | E12: =E9 -> Green unit charge p/kWh | F12: Number of days in consumption period i.e. 365 if one year | G12: Maximum import or export capacity kVA | H12: Average daily exceeded capacity kVA | I12: Excess reactive units kVArh | L12: Tariff components | M12: Import super red kWh | N12: Number of days in consumption period i.e. 365 if one year | O12: Maximum import capacity kVA | P12: Average daily exceeded capacity kVA | Q12: Export Super Red kWh | R12: Number of days in consumption period i.e. 365 if one year | S12: Maximum export capacity kVA | T12: Average daily exceeded capacity kVA | AB12: LV Sub Generation Aggregated | AC12: Red unit charge p/kWh | AD12: Amber unit charge p/kWh | AE12: Green unit charge p/kWh | AF12: Fixed charge p/MPAN/day | AG12: n/a | AH12: n/a | AI12: n/a
B13: Enter current consumption details | L13: Enter current consumption details | R13: =N13 -> 0 | AB13: LV Generation Site Specific | AC13: Red unit charge p/kWh | AD13: Amber unit charge p/kWh | AE13: Green unit charge p/kWh | AF13: Fixed charge p/MPAN/day | AG13: n/a | AH13: n/a | AI13: Reactive power charge p/kVArh
B14: Enter forecast consumption details (if different) | C14: =C13 -> 0 | D14: =D13 -> 0 | E14: =E13 -> 0 | F14: =F13 -> 0 | G14: =G13 -> 0 | H14: =H13 -> 0 | I14: =I13 -> 0 | L14: Enter forecast consumption details (if different) | M14: =M13 -> 0 | N14: =N13 -> 0 | O14: =O13 -> 0 | P14: =P13 -> 0 | Q14: =Q13 -> 0 | R14: =R13 -> 0 | S14: =S13 -> 0 | T14: =T13 -> 0 | AB14: LV Generation Site Specific no RP charge | AC14: Red unit charge p/kWh | AD14: Amber unit charge p/kWh | AE14: Green unit charge p/kWh | AF14: Fixed charge p/MPAN/day | AG14: n/a | AH14: n/a | AI14: n/a
AB15: LV Sub Generation Site Specific | AC15: Red unit charge p/kWh | AD15: Amber unit charge p/kWh | AE15: Green unit charge p/kWh | AF15: Fixed charge p/MPAN/day | AG15: n/a | AH15: n/a | AI15: Reactive power charge p/kVArh
B16: Charge components | C16: Unit 1 £ | D16: Unit 2 £ | E16: Unit 3 £ | F16: Fixed charge £ | G16: Capacity charge £ | H16: Exceeded capacity charge £ | I16: Reactive power charge £ | L16: Charge components | M16: Import super red charge £ | N16: Import fixed charge £ | O16: Import capacity charge £ | P16: Import exceeded capacity charge £ | Q16: Export super red charge £ | R16: Export fixed charge £ | S16: Export capacity charge £ | T16: Export exceeded capacity charge £ | AB16: LV Sub Generation Site Specific no RP charge | AC16: Red unit charge p/kWh | AD16: Amber unit charge p/kWh | AE16: Green unit charge p/kWh | AF16: Fixed charge p/MPAN/day | AG16: n/a | AH16: n/a | AI16: n/a
B17: Current consumption period charges | C17: =IFERROR(C10*C13/100,"") | D17: =IFERROR(D10*D13/100,"") | E17: =IFERROR(E10*E13/100,"") | F17: =IFERROR(F10*F13/100,"") | G17: =IFERROR(G10*G13*F13/100,"") | H17: =IFERROR(H10*H13*F13/100,"") | I17: =IFERROR(I10*I13/100,"") | L17: Current consumption period charges | M17: =IFERROR(M10*M13/100,"") | N17: =IFERROR(N10*N13/100,"") | O17: =IFERROR(O10*O13*N13/100,"") | P17: =IFERROR(P10*P13*N13/100,"") | Q17: =IFERROR(Q10*Q13/100,"") | R17: =IFERROR(R10*R13/100,"") | S17: =IFERROR(S10*S13*R13/100,"") | T17: =IFERROR(T10*T13*R13/100,"") | AB17: HV Generation Site Specific | AC17: Red unit charge p/kWh | AD17: Amber unit charge p/kWh | AE17: Green unit charge p/kWh | AF17: Fixed charge p/MPAN/day | AG17: n/a | AH17: n/a | AI17: Reactive power charge p/kVArh
B18: Forecast consumption period charges | C18: =IFERROR(C10*C14/100,"") | D18: =IFERROR(D10*D14/100,"") | E18: =IFERROR(E10*E14/100,"") | F18: =IFERROR(F10*F14/100,"") | G18: =IFERROR(G10*G14*F14/100,"") | H18: =IFERROR(H10*H14*F14/100,"") | I18: =IFERROR(I10*I14/100,"") | L18: Forecast consumption period charges | M18: =IFERROR(M10*M14/100,"") | N18: =IFERROR(N10*N14/100,"") | O18: =IFERROR(O10*O14*N14/100,"") | P18: =IFERROR(P10*P14*N14/100,"") | Q18: =IFERROR(Q10*Q14/100,"") | R18: =IFERROR(R10*R14/100,"") | S18: =IFERROR(S10*S14*R14/100,"") | T18: =IFERROR(T10*T14*R14/100,"") | AB18: HV Generation Site Specific no RP charge | AC18: Red unit charge p/kWh | AD18: Amber unit charge p/kWh | AE18: Green unit charge p/kWh | AF18: Fixed charge p/MPAN/day | AG18: n/a | AH18: n/a | AI18: n/a
C20: Total charge £ | M20: Import total charge £ | N20: Export total charge £
B21: Current consumption period charges | C21: =SUM(C17:I17) -> 0 | L21: Current consumption period charges | M21: =SUM(M17:P17) -> 0 | N21: =SUM(Q17:T17) -> 0
B22: Forecast consumption period charges | C22: =SUM(C18:I18) -> 0 | L22: Forecast consumption period charges | M22: =SUM(M18:P18) -> 0 | N22: =SUM(Q18:T18) -> 0
B24: These charges are estimates based on tariff selected and consumption values entered. | L24: These charges are estimates based on site selected and consumption values entered.
