Workbook
Name OLE_LINK1: 'Annex 3 Preserved charges'!#REF!

Sheet Overview
A2: Company and Licence name, charging year, effective from, status
B3: Company and Licence name | C3: Year | D3: Effective From | E3: Status
A4: Company and Licence name, charging year, effective from, status | B4: SP Manweb | C4: 2019/20 | D4: 1 April 2019 | E4: Final
A6: List of data tables in this workbook
A7: Worksheet | B7: Information
A8: Annex 1 LV and HV charges | B8: Annex 1 contains the charges to LV and HV Designated Properties.
A9: Annex 2 EHV charges | B9: ="Annex 2 contains the charges to Designated EHV Properties and charges applied to LDNOs with Designated EHV Properties/end-users embedded in networks within the " &B4 &" Licence area." -> Annex 2 contains the charges to Designated EHV Properties and charges applied to LDNOs with Designated EHV Properties/end-users embedded in networks within the SP Manweb Licence area.
A10: Annex 3 Preserved charges | B10: Annex 3 contains details of any preserved and additional charges that are valid at this time.
A11: Annex 4 LDNO charges | B11: ="Annex 4 contains charges that are levied on the owner of an embedded network within the "&B4&" Licence area. "&"Electricity suppliers and consumers who have properties connected to an embedded network should contact the embedded network owner to determine their distribution charges."&" The charges listed in this table are not payable by domestic consumers, business consumers or electricity suppliers." -> Annex 4 contains charges that are levied on the owner of an embedded network within the SP Manweb Licence area. Electricity suppliers and consumers who have properties connected to an embedded network should contact the embedded network owner to determine their distribution charges. The charges listed in this table are not payable by domestic consumers, business consumers or electricity suppliers.
A12: Annex 5 LLFs | B12: Annex 5 has been intentionally left blank as this charging statement is published a complete year before the LLFs have been audited. The line loss factors that are approved by the BSC Panel for the applicable year and consequently published on the Elexon website will take precedence and be used in Settlement. This annex will be re-published with these values once they are available.
A13: Annex 6 Charges for New or Amended Designated EHV Properties | B13: ="Annex 6 contains the charges for new or amended Designated EHV Properties and charges applied to LDNOs with new or amended Designated EHV Properties/end-users embedded in networks within the " &B4 &" Licence area." -> Annex 6 contains the charges for new or amended Designated EHV Properties and charges applied to LDNOs with new or amended Designated EHV Properties/end-users embedded in networks within the SP Manweb Licence area.
A14: Nodal prices | B14: Contains the underlying [nodal/network group] costs used to calculate the current EDCM charges.
A15: SSC TPR to unit rate lookup table | B15: The time periods for the non half hourly metered charge rates in Annex 1 are as specified by the SSC. To determine the appropriate charge rate for each SSC/TPR a lookup table is provided.
A16: Charge calculator | B16: Charge calculator is a tool to help you estimate your distribution charges using current consumption data and forecast consumption data.
A18: Notes to users of this spreadsheet
A20: Please use this spreadsheet with reference to the LC14 use of system charging statement.
A22: Notes to DNOs populating this spreadsheet
A24: DNOs must endeavour to maintain consistency in the structure of this spreadsheet. Any changes to the structure must be noted in the 'Notes to users of this spreadsheet'
A25: The drop down list on the charge calculator can be expanded by unprotecting the charge calculator sheet and selecting 'data', 'data validation...' and then expanding the 'source' data range. The sheet can then be protected.

Sheet Annex 1 LV and HV charges
A1: Back to Overview | B1: 'DNOs paste value cells A15:J47 from CDCM 3701 into cells A14:J46 | E1: Note: Where a tariff only has a p/kWh unit rate in Unit Charge 1 then this unit rate applies at all times.
A2: SP Manweb - Effective from 1 April 2019 - Final LV and HV charges
A4: Time Bands for Half Hourly Metered Properties | G4: Time Bands for Half Hourly Unmetered Properties
A5: Time periods | B5: Red Time Band | C5: Amber Time Band | E5: Green Time Band | I5: Black Time Band | J5: Yellow Time Band | K5: Green Time Band
A6: Monday to Friday (Including Bank Holidays) All Year | B6: 16.30 - 19.30 | C6: 08.00 - 16.30 19.30 - 22.30 | E6: 00.00 - 08.00 22.30 - 00.00 | G6: Monday to Friday (Including Bank Holidays) June to August Inclusive | J6: 08.00 - 22.30 | K6: 00.00 - 08.00 22.30 - 00.00
A7: Saturday and Sunday All Year | C7: 16.00 - 20.00 | E7: 00.00 - 16.00 20.00 - 00.00 | G7: Monday to Friday (Including Bank Holidays) November to February Inclusive | I7: 16.30 - 19.30 | J7: 08.00 - 16.30 19.30 - 22.30 | K7: 00.00 - 08.00 22.30 - 00.00
A8: Notes | B8: All the above times are in UK Clock time | G8: Monday to Friday (Including Bank Holidays) March, April, May and September, October | J8: 08.00 - 22.30 | K8: 00.00 - 08.00 22.30 - 00.00
G9: Saturday and Sunday All year | J9: 16.00 - 20.00 | K9: 00:00-16:00 20:00-00:00
G10: Notes | I10: All the above times are in UK Clock time
A13: Tariff name | B13: Open LLFCs | C13: PCs | D13: Unit charge 1 (NHH) or red/black charge (HH) p/kWh | E13: Unit charge 2 (NHH) or amber/yellow charge (HH) p/kWh | F13: Green charge(HH) p/kWh | G13: Fixed charge p/MPAN/day | H13: Capacity charge p/kVA/day | I13: Exceeded capacity charge p/kVA/day | J13: Reactive power charge p/kVArh | K13: Closed LLFCs
A14: Domestic Unrestricted* | B14: 101, 102 | C14: 1 | D14: 3.356 | G14: 3.68
A15: Domestic Two Rate* | B15: 103, 105, 111, 112, 113, 114, 115, 116, 117, 118, 119, 120, 131, 132, 133, 134, 147, 148, 149, 150 | C15: 2 | D15: 3.686 | E15: 1.545 | G15: 3.68 | K15: 145, 146
A16: Domestic Off Peak (related MPAN) | B16: 104, 106, 130, 153, 155 | C16: 2 | D16: 1.556 | K16: 135, 136, 137, 138, 140, 141, 142, 143
A17: Small Non Domestic Unrestricted | B17: 201, 202, 203, 209 | C17: 3 | D17: 3.367 | G17: 4.63 | K17: 207
A18: Small Non Domestic Two Rate | B18: 205, 211, 231, 232 | C18: 4 | D18: 3.515 | E18: 1.466 | G18: 4.63 | K18: 208, 210
A19: Small Non Domestic Off Peak (related MPAN) | B19: 212 | C19: 4 | D19: 1.498 | K19: 233, 234, 235, 236, 237
A20: LV Network Domestic* | B20: 180 | C20: 0 | D20: 12.266 | E20: 2.621 | F20: 1.453 | G20: 3.68
A21: LV Network Non-Domestic Non-CT | B21: 280 | C21: 0 | D21: 12.568 | E21: 2.659 | F21: 1.458 | G21: 4.63
A22: LV HH Metered | B22: 511, 591 | C22: 0 | D22: 10.481 | E22: 2.305 | F22: 1.423 | G22: 18.71 | H22: 2.51 | I22: 4.46 | J22: 0.367 | K22: 501
A23: LV Sub HH Metered | B23: 513, 592 | C23: 0 | D23: 8.066 | E23: 1.869 | F23: 1.383 | G23: 6.6 | H23: 5.15 | I23: 7.12 | J23: 0.232 | K23: 503
A24: HV HH Metered | B24: 515, 593 | C24: 0 | D24: 6.54 | E24: 1.653 | F24: 1.352 | G24: 99.97 | H24: 4.05 | I24: 6.63 | J24: 0.161 | K24: 505
A25: NHH UMS category A | B25: 900 | C25: 8 | D25: 2.707 | K25: 904, 912, 913
A26: NHH UMS category B | B26: 901 | C26: 1 | D26: 2.974 | K26: 905
A27: NHH UMS category C | B27: 902 | C27: 1 | D27: 4.108 | K27: 906
A28: NHH UMS category D | B28: 903 | C28: 1 | D28: 2.521 | K28: 907
A29: LV UMS (Pseudo HH Metered) | B29: 910 | C29: 0 | D29: 20.912 | E29: 2.645 | F29: 1.731
A30: LV Generation NHH or Aggregate HH | B30: 781, 782, 783, 784, 785 | C30: 8&0 | D30: -1.228 | G30: 0
A31: LV Sub Generation NHH | B31: 780 | C31: 8 | D31: -1.098 | G31: 0
A32: LV Generation Intermittent | B32: 786, 787 | C32: 0 | D32: -1.228 | G32: 0 | J32: 0.302
A33: LV Generation Intermittent no RP charge | B33: 764 | C33: 0 | D33: -1.228 | G33: 0
A34: LV Generation Non-Intermittent | B34: 791, 795 | C34: 0 | D34: -8.287 | E34: -1.036 | F34: -0.158 | G34: 0 | J34: 0.302
A35: LV Generation Non-Intermittent no RP charge | B35: 765 | C35: 0 | D35: -8.287 | E35: -1.036 | F35: -0.158 | G35: 0
A36: LV Sub Generation Intermittent | B36: 788, 789 | C36: 0 | D36: -1.098 | G36: 0 | J36: 0.28
A37: LV Sub Generation Intermittent no RP charge | B37: 766 | C37: 0 | D37: -1.098 | G37: 0
A38: LV Sub Generation Non-Intermittent | B38: 792, 796 | C38: 0 | D38: -7.514 | E38: -0.898 | F38: -0.145 | G38: 0 | J38: 0.28
A39: LV Sub Generation Non-Intermittent no RP charge | B39: 767 | C39: 0 | D39: -7.514 | E39: -0.898 | F39: -0.145 | G39: 0
A40: HV Generation Intermittent | B40: 770, 771 | C40: 0 | D40: -0.723 | G40: 73 | J40: 0.214
A41: HV Generation Intermittent no RP charge | B41: 768 | C41: 0 | D41: -0.723 | G41: 73
A42: HV Generation Non-Intermittent | B42: 793, 797 | C42: 0 | D42: -5.385 | E42: -0.471 | F42: -0.11 | G42: 73 | J42: 0.214
A43: HV Generation Non-Intermittent no RP charge | B43: 769 | C43: 0 | D43: -5.385 | E43: -0.471 | F43: -0.11 | G43: 73
A45: *Supplier of Last Resort increases to the Fixed Charges for the Domestic Unrestricted, Domestic Two Rate and LV Domestic Network tariffs. The increase for each of these tariffs is 0.08p/MPAN/day. No other tariffs affected by this change.

Sheet Annex 2 EHV charges
A1: Back to Overview | C1: Copy EDCM table 5001 range starting B101 and paste into G11. Extend or reduce print area as required. | F1: Note: The list of MPANs / MSIDs provided may be incomplete; the DNO reserves the right to apply the listed charges to any other MPANs / MSIDs associated with the site.
A2: SP Manweb - Effective from 1 April 2019 - Final EDCM charges
A4: Time Periods for Designated EHV Properties
A5: Time periods | D5: Super Red Time Band
A6: Monday to Friday (Including Bank Holidays) June to August Inclusive
A7: Monday to Friday (Including Bank Holidays) November to February Inclusive | D7: 16:30 - 19:30
A8: Notes | D8: All the above times are in UK Clock time
A10: Import Unique Identifier | B10: LLFC | C10: Import MPANs/MSIDs | D10: Export Unique Identifier | E10: LLFC | F10: Export MPANs/MSIDs | G10: Name | H10: Import Super Red unit charge (p/kWh) | I10: Import fixed charge (p/day) | J10: Import capacity charge (p/kVA/day) | K10: Import exceeded capacity charge (p/kVA/day) | L10: Export Super Red unit charge (p/kWh) | M10: Export fixed charge (p/day) | N10: Export capacity charge (p/kVA/day) | O10: Export exceeded capacity charge (p/kVA/day)
A11: 803 | B11: 803 | C11: 1300035361194 | D11: 603 | E11: 603 | F11: 1300050649372 | G11: Shell Stanlow | I11: 19306.088 | J11: 6.6 | K11: 6.6 | L11: -0.262 | M11: 2382.34 | N11: 0.05 | O11: 0.05
A12: 804 | B12: 804 | C12: 1300035352942 | G12: Jaguar & Land Rover | H12: 0.302 | I12: 8711.76 | J12: 8.49 | K12: 8.49
A13: 805 | B13: 805 | C13: 1300035359423 | G13: Innospec | H13: 0.263 | I13: 844.42 | J13: 4.65 | K13: 4.65
A14: 806 | B14: 806 | C14: 1300051060972 | D14: 606 | E14: 606 | F14: 1300051060981 | G14: Bridgewater Paper | I14: 98.14 | J14: 3.14 | K14: 3.14
A15: 807 | B15: 807 | C15: 1300035359752 | G15: General Motors | H15: 0.266 | I15: 14550.17 | J15: 4.52 | K15: 4.52
A16: 808 | B16: 808 | C16: 1300035360066 | G16: TATA Steel | I16: 38475.65 | J16: 5.07 | K16: 5.07
A17: 809 | B17: 809 | C17: 1300035362480 | G17: Urenco | J17: 4.09 | K17: 4.09
A18: 810 | B18: 810 | C18: 1300051694818 | D18: 618 | E18: 618 | F18: 1300060704603 | G18: Ineos Chlor Ltd (Lostock) | I18: 13181.11 | J18: 1.56 | K18: 1.56 | M18: 2015.58 | N18: 0.05 | O18: 0.05
A19: 811 | B19: 811 | C19: 1300060704073 | D19: 655 | E19: 655 | F19: 1300060704082 | G19: SafeGuard Bradwell | H19: 1.713 | I19: 45.24 | J19: 4.42 | K19: 4.42 | M19: 3528.34 | N19: 0.05 | O19: 0.05
A20: 812 | B20: 812 | C20: 1300035356130 | G20: Knauf Insulation | H20: 0.305 | I20: 1697.93 | J20: 7.75 | K20: 7.75
A21: 813 | B21: 813 | C21: 1300035359585 | G21: Air Products | H21: 0.34 | I21: 384.2 | J21: 4.42 | K21: 4.42
A22: 814 | B22: 814 | C22: 1300035359619 | G22: Shell Chemicals | H22: 0.275 | I22: 1697.93 | J22: 8.79 | K22: 8.79
A23: 815 | B23: 815 | C23: 1300035359780 | G23: GrowHow | H23: 0.27 | I23: 8712.75 | J23: 9.18 | K23: 9.18
A24: 816 | B24: 816 | C24: 1300053536398 | G24: Castle Cement | I24: 954.31 | J24: 3.98 | K24: 3.98
A25: 817 | B25: 817 | C25: 1300035361992 | D25: 648 | E25: 648 | F25: 1300060640474 | G25: Kronospan | I25: 3839.5651 | J25: 14.85 | K25: 14.88 | M25: 388.97 | N25: 0.05 | O25: 0.05
A26: 819 | B26: 819 | C26: 1300035365082 | D26: 619 | E26: 619 | F26: 1300051136210 | G26: Albion Inorganic | H26: 1.956 | I26: 203.72 | J26: 1.91 | K26: 1.91
A27: 820 | B27: 820 | C27: 1300060563740 | D27: 658 | E27: 658 | F27: 1300060563759 | G27: Tyn dryfol PV | I27: 8.05 | J27: 3.68 | K27: 3.68 | M27: 2414.17 | N27: 0.05 | O27: 0.05
A28: 821 | B28: 821 | C28: 1300035367967 | D28: 621 | E28: 621 | F28: 1300050649336 | G28: BHP | I28: 8456.6218 | J28: 2.89 | K28: 2.89
A29: 822 | B29: 822 | C29: 1300060251601 | G29: Hole House Farm | I29: 9536.12 | J29: 6.33 | K29: 6.33
A30: 823 | B30: 823 | C30: 1300060652610 | D30: 659 | E30: 659 | F30: 1300060652629 | G30: Williams Farm Solar Park | I30: 6.76 | J30: 3.78 | K30: 3.78 | M30: 743.42 | N30: 0.05 | O30: 0.05
A31: 824 | B31: 824 | C31: 1300054940674 | D31: 604 | E31: 604 | F31: 1300054940683 | G31: Port of Liverpool | I31: 27.66 | J31: 2.62 | K31: 2.62 | M31: 1659.61 | N31: 0.05 | O31: 0.05
A32: 826 | B32: 826 | C32: 1300060579173 | D32: 661 | E32: 661 | F32: 1300060579182 | G32: Combermere Abbey PV | I32: 14.3 | J32: 5.02 | K32: 5.02 | M32: 2496.2 | N32: 0.05 | O32: 0.05
A33: 827 | B33: 827 | C33: 1300052785147 | G33: Kimberley Clark | I33: 677.72 | J33: 14.05 | K33: 14.05
A34: 828 | B34: 828 | C34: 1300060075390 | D34: 628 | E34: 628 | F34: 1300060075405 | G34: Amegni | I34: 7.96 | J34: 2.28 | K34: 2.28 | M34: 620.7 | N34: 0.05 | O34: 0.05
A35: 829 | B35: 829 | C35: 1300035400611 | D35: 629 | E35: 629 | F35: 1300038004507 | G35: Salt Union | I35: 348.62 | J35: 2.75 | K35: 2.75
A36: 830 | B36: 830 | C36: 1300060584270 | D36: 681 | E36: 681 | F36: 1300060584280 | G36: Parciau Solar Park | I36: 6.35 | J36: 4.18 | K36: 4.18 | M36: 756.47 | N36: 0.05 | O36: 0.05
A37: 831 | B37: 831 | C37: 1300035437700 | G37: Ineos Chlor Ltd (Percival Lane) | I37: 416.27 | J37: 5.85 | K37: 5.85
A38: 833 | B38: 833 | C38: 1300035361803 | G38: Toyota | I38: 2830.69 | J38: 5.57 | K38: 5.57
A39: 834 | B39: 834 | C39: 1300051028551 | G39: Warmingham Gas Storage | I39: 3884.8343 | J39: 6.71 | K39: 6.71
A40: 835 | B40: 835 | C40: 1300050648875 | D40: 635 | E40: 635 | F40: 1300050931602 | G40: Arpley Landfill | H40: 1.713 | I40: 11.68 | J40: 3.29 | K40: 3.29
A41: 836 | B41: 836 | C41: 1300035360800 | G41: Amcor | I41: 2010.87 | J41: 10.64 | K41: 10.64
A42: 838 | B42: 838 | C42: 1300052122840 | D42: 638 | E42: 638 | F42: 1300052122859 | G42: Cemmaes C | I42: 8.94 | J42: 2.78 | K42: 2.78
A43: 839 | B43: 839 | C43: 1300051822667 | D43: 639 | E43: 639 | F43: 1300051821478 | G43: PG Strand Gate | I43: 1848.81 | J43: 2.54 | K43: 2.54
A44: 840 | B44: 840 | C44: 1300052545267 | D44: 640 | E44: 640 | F44: 1300052545276 | G44: Moel Maelogan (A) | I44: 20.74 | J44: 2.9 | K44: 2.9
A45: 841 | B45: 841 | C45: 1300052545285 | D45: 641 | E45: 641 | F45: 1300052545294 | G45: Moel Maelogan (B) | I45: 10.44 | J45: 3.12 | K45: 3.12
A46: 842 | B46: 842 | C46: 1300053022082 | D46: 642 | E46: 642 | F46: 1300053022091 | G46: North Hoyle | I46: 510.18 | J46: 1.43 | K46: 1.43
A47: 843 | B47: 843 | C47: 1300053466350 | D47: 643 | E47: 643 | F47: 1300053466369 | G47: Cefn Croyes (3) | I47: 2747.75 | J47: 2.21 | K47: 2.21
A48: 844 | B48: 844 | C48: 1300053466378 | D48: 644 | E48: 644 | F48: 1300053466387 | G48: Cefn Croyes (4) | I48: 2755.32 | J48: 2.2 | K48: 2.2
A49: 845 | B49: 845 | C49: 1300053834682 | D49: 645 | E49: 645 | F49: 1300053834691 | G49: Tir Mostyn | I49: 379.61 | J49: 2.57 | K49: 2.57
A50: 846 | B50: 846 | C50: 1300053862801 | D50: 646 | E50: 646 | F50: 1300053862796 | G50: Mynydd Clogau | I50: 9.86 | J50: 2.97 | K50: 2.97
A51: 847 | B51: 847 | C51: 1300053962107 | D51: 647 | E51: 647 | F51: 1300053962116 | G51: Granox | H51: 0.404 | I51: 215.88 | J51: 3.57 | K51: 3.57
A52: 848 | B52: 848 | C52: 1300060499085 | D52: 651 | E52: 651 | F52: 1300060499094 | G52: Tai Moelion | I52: 4.01 | J52: 5.02 | K52: 5.02 | M52: 1201.61 | N52: 0.05 | O52: 0.05
A53: 849 | B53: 849 | C53: 1300054624390 | D53: 649 | E53: 649 | F53: 1300054624405 | G53: Braich Ddu | I53: 23.25 | J53: 2.76 | K53: 2.76
A54: 850 | B54: 850 | C54: 1300060668363 | D54: 652 | E54: 652 | F54: 1300060668372 | G54: Widnes Biomass | H54: 0.281 | I54: 713.93 | J54: 4.02 | K54: 4.02 | L54: -0.286 | M54: 4462.51 | N54: 0.05 | O54: 0.05
A55: 851 | B55: 851 | C55: 1300054933348 | D55: 611 | E55: 611 | F55: 1300054914140 | G55: Moel Maelogan 2 | I55: 6.53 | J55: 2.87 | K55: 2.87 | M55: 382.16 | N55: 0.05 | O55: 0.05
A56: 852 | B56: 852 | C56: 1300053310848 | G56: Trafalgar Dock | I56: 2419.63 | J56: 5.51 | K56: 5.51
A57: 854 | B57: 854 | C57: 1300060138720 | D57: 654 | E57: 654 | F57: 1300060138739 | G57: Wern Ddu | I57: 51.05 | J57: 2.54 | K57: 2.54 | M57: 2475.82 | N57: 0.05 | O57: 0.05
A58: 856 | B58: 856 | C58: 1300060102617 | D58: 656 | E58: 656 | F58: 1300060102608 | G58: Rhyl Flats | I58: 166.42 | J58: 2.36 | K58: 2.36 | M58: 15310.49 | N58: 0.05 | O58: 0.05
A59: 857 | B59: 857 | C59: 1300060508758 | G59: Seaforth Liverpool Dock 2 | I59: 67500.36 | J59: 10.87 | K59: 10.87
A60: 865 | B60: 865 | C60: 1300035438944 | D60: 665 | E60: 665 | F60: 1300038004491 | G60: Cemmaes B | I60: 7.77 | J60: 3.17 | K60: 3.17
A61: 866 | B61: 866 | C61: 1300037983737 | D61: 666 | E61: 666 | F61: 1300037983746 | G61: Penrhyddlan | I61: 15.1 | J61: 3.75 | K61: 3.75 | M61: 1761.74 | N61: 0.05 | O61: 0.05
A62: 867 | B62: 867 | C62: 1300037983755 | D62: 667 | E62: 667 | F62: 1300037983764 | G62: Llidartywaun | I62: 14.1 | J62: 3.59 | K62: 3.59 | M62: 1762.73 | N62: 0.05 | O62: 0.05
A63: 868 | B63: 868 | C63: 1300035368906 | D63: 668 | E63: 668 | F63: 1300050649381 | G63: Rhyd y Groes | I63: 87.09 | J63: 2.73 | K63: 2.73 | M63: 711.25 | N63: 0.05 | O63: 0.05
A64: 869 | B64: 869 | C64: 1300035370393 | D64: 669 | E64: 669 | F64: 1300050649070 | G64: Llangwyrfon | I64: 27.1 | J64: 3.39 | K64: 3.39 | M64: 3334 | N64: 0.05 | O64: 0.05
A65: 870 | B65: 870 | C65: 1300060308295 | G65: Storenergy (Lostock) | I65: 1477.32 | J65: 11.74 | K65: 11.74
A66: 871 | B66: 871 | C66: 1300037983996 | D66: 671 | E66: 671 | F66: 1300037984002 | G66: Rheidol | I66: 80.88 | J66: 2.03 | K66: 2.03 | M66: 990.81 | N66: 0.05 | O66: 0.05
A67: 872 | B67: 872 | C67: 1300037983913 | D67: 672 | E67: 672 | F67: 1300037983922 | G67: Carno B | I67: 105.45 | J67: 2.25 | K67: 2.25
A68: 873 | B68: 873 | C68: 1300037983899 | D68: 673 | E68: 673 | F68: 1300037983904 | G68: Carno A | I68: 37.42 | J68: 2.39 | K68: 2.39
A69: 874 | B69: 874 | C69: 1300035438572 | D69: 674 | E69: 674 | F69: 1300050649390 | G69: Trysglwyn | I69: 15.51 | J69: 2.94 | K69: 2.94
A70: 875 | B70: 875 | C70: 1300050649406 | D70: 675 | E70: 675 | F70: 1300050649415 | G70: Llanabo | I70: 7.7 | J70: 3.01 | K70: 3.01
A71: 876 | B71: 876 | C71: 1300060701106 | D71: 676 | E71: 676 | F71: 1300060701115 | G71: Ebnal Lodge PV | I71: 23.23 | J71: 4.2 | K71: 4.2 | M71: 1251.59 | N71: 0.05 | O71: 0.05
A72: 877 | B72: 877 | C72: 1300053593216 | G72: Quinn Glass | H72: 0.272 | I72: 3809.92 | J72: 6.17 | K72: 6.17
A73: 878 | B73: 878 | C73: 1300054122122 | G73: Liverpool Int Bus Park | I73: 4231.88 | J73: 4.8 | K73: 4.8
A74: 880 | B74: 880 | C74: 1300060621588 | D74: 670 | E74: 670 | F74: 1300060621597 | G74: Twemelows Hall PV | I74: 57.42 | J74: 4.9 | K74: 4.9 | M74: 7808.82 | N74: 0.05 | O74: 0.05
A75: 881 | B75: 881 | C75: 1300060626275 | D75: 679 | E75: 679 | F75: 1300060626284 | G75: Teyrdan | I75: 0.86 | J75: 4.22 | K75: 4.22 | M75: 122.16 | N75: 0.05 | O75: 0.05
A76: 882 | B76: 882 | C76: 1300060631656 | D76: 684 | E76: 684 | F76: 1300060631665 | G76: Parc Adfer | I76: 238.45 | J76: 4.02 | K76: 4.02 | M76: 2013.55 | N76: 0.05 | O76: 0.05
A77: 883 | B77: 883 | C77: 1300060621950 | D77: 683 | E77: 683 | F77: 1300060621969 | G77: Hadley Solar Park | I77: 1.02 | J77: 3.85 | K77: 3.85 | M77: 122 | N77: 0.05 | O77: 0.05
A78: 886 | B78: 886 | C78: 1300060657830 | D78: 686 | E78: 686 | F78: 1300060657840 | G78: Charity Farm Solar Park | I78: 0.56 | J78: 4.21 | K78: 4.21 | M78: 122.46 | N78: 0.05 | O78: 0.05
A79: 887 | B79: 887 | C79: 1300035619768 | D79: 687 | E79: 687 | F79: 1300050652905 | G79: Mynydd Gorduu | I79: 99.31 | J79: 3.12 | K79: 3.12
A80: 888 | B80: 888 | C80: TBA | G80: Winsford Salt | H80: 1.713 | I80: 8971.15 | J80: 8.12 | K80: 8.12
A81: 889 | B81: 889 | C81: 1300060626293 | D81: 678 | E81: 678 | F81: 1300060626309 | G81: Nefyn | I81: 0.76 | J81: 3.2 | K81: 3.2 | M81: 122.25 | N81: 0.05 | O81: 0.05
A82: 890 | B82: 890 | C82: 1300060621987 | D82: 697 | E82: 697 | F82: 1300060621996 | G82: Frodsham WF 1 | H82: 0.107 | I82: 2.83 | J82: 4.56 | K82: 4.56 | M82: 4243.42 | N82: 0.05 | O82: 0.05
A83: 891 | B83: 891 | C83: 1300060622002 | D83: 699 | E83: 699 | F83: 1300060622011 | G83: Frodsham WF 2 | H83: 0.034 | I83: 2.83 | J83: 3.74 | K83: 3.74 | M83: 1955.94 | N83: 0.05 | O83: 0.05
A84: 892 | B84: 892 | C84: 1300060609697 | D84: 692 | E84: 692 | F84: 1300060609702 | G84: Ince Biomass | H84: 0.257 | I84: 277.32 | J84: 4.02 | K84: 4.02 | L84: -0.262 | M84: 1993.24 | N84: 0.05 | O84: 0.05
A85: 893 | B85: 893 | C85: 1300060659740 | D85: 693 | E85: 693 | F85: 1300060659759 | G85: Kinmel Estate Solar Park | I85: 4.06 | J85: 4.02 | K85: 4.02 | M85: 365 | N85: 0.05 | O85: 0.05
A86: 894 | B86: 894 | C86: 1300060647600 | D86: 694 | E86: 694 | F86: 1300060647610 | G86: Tirgwynt Wind Farm | I86: 379.77 | J86: 2.19 | K86: 2.19 | M86: 19671.95 | N86: 0.05 | O86: 0.05
A87: 896 | B87: 896 | C87: 1300060673442 | D87: 616 | E87: 616 | F87: 1300060673451 | G87: Percival Lane STOR | I87: 31.72 | J87: 4.02 | K87: 4.02 | M87: 2537.85 | N87: 0.05 | O87: 0.05
A88: 897 | B88: 897 | C88: 1300060673460 | D88: 617 | E88: 617 | F88: 1300060673489 | G88: Stanlow STOR | H88: 0.257 | I88: 62.67 | J88: 2.79 | K88: 2.79 | L88: -0.731 | M88: 2506.9 | N88: 0.05 | O88: 0.05
A89: 898 | B89: 898 | C89: 1300051694552 | D89: 698 | E89: 698 | F89: 1300051694827 | G89: PG Winnington | I89: 595.16 | J89: 2.17 | K89: 3.4
A90: 899 | B90: 899 | C90: 1300060484140 | G90: Airbus UK Ltd (33kV) | I90: 7102.55 | J90: 7.37 | K90: 7.37
A91: 921 | B91: 921 | C91: 1300050654248 | D91: 691 | E91: 691 | F91: 1300060208518 | G91: Network Rail (Crewe) | I91: 9146.26 | J91: 4.03 | K91: 4.03 | M91: 2286.56 | N91: 0.05 | O91: 0.05
A92: 922 | B92: 922 | C92: 1300050654257 | D92: 682 | E92: 682 | F92: 1300060269895 | G92: Network Rail (Speke) | I92: 3337.67 | J92: 8.07 | K92: 8.07 | L92: -0.286 | M92: 1112.56 | N92: 0.05 | O92: 0.05
A93: 923 | B93: 923 | C93: 1300050649994 | G93: Network Rail (Bankhall) | I93: 1450.06 | J93: 9.81 | K93: 9.81
A94: 924 | B94: 924 | C94: 1300050653040 | G94: Network Rail (Bromborough) | I94: 927.98 | J94: 12.5 | K94: 12.5
A95: 925 | B95: 925 | C95: 1300050654220 | G95: Network Rail (Shore Road) | I95: 5415.7 | J95: 6.99 | K95: 6.99
A96: MSID 7120 | B96: MSID 7120 | C96: MSID 7120 | D96: MSID 7120 | E96: MSID 7120 | F96: MSID 7120 | G96: Shotton Paper | I96: 26495.003 | J96: 1.77 | K96: 1.77
A97: MSID 7203 | B97: MSID 7203 | C97: MSID 7203 | D97: MSID 7203 | E97: MSID 7203 | F97: MSID 7203 | G97: Burbo Bank | I97: 4386.06
A98: MSID 0030 | B98: MSID 0030 | C98: MSID 0030 | G98: Risley | J98: 13.2 | K98: 13.2
A99: MSID 0031/32 | B99: MSID 0031/32 | C99: MSID 0031/32 | G99: Bold | J99: 3.9 | K99: 3.9
A100: MSID 4532/33 | B100: MSID 4532/33 | C100: MSID 4532/33 | D100: MSID 4532/33 | E100: MSID 4532/33 | F100: MSID 4532/33 | G100: Dolgarrog PS | J100: 5.15 | K100: 5.15 | L100: -0.306 | N100: 0.05 | O100: 0.05
D101: MSID 6015 | E101: MSID 6015 | F101: MSID 6015 | G101: Maentwrog PS | N101: 0.05 | O101: 0.05
D102: MSID 4054 | E102: MSID 4054 | F102: MSID 4054 | G102: Cwm Dyli PS | N102: 0.05 | O102: 0.05
...

Sheet Annex 2a Import
A1: Note: The list of MPANs / MSIDs provided may be incomplete; the DNO reserves the right to apply the listed charges to any other MPANs / MSIDs associated with the site. Note: This table is automatically populated based on the content of the tab entitled 'Annex 2 EHV Charges'. The timebands are as shown in Annex 2.
A2: =Overview!B4& " - Effective from "&Overview!D4&" - "&Overview!E4&" EDCM import charges" -> SP Manweb - Effective from 1 April 2019 - Final EDCM import charges
A4: Import Unique Identifier | B4: LLFC | C4: Import MPANs/MSIDs | D4: Name | E4: ='Annex 2 EHV charges'!H10 -> Import Super Red unit charge (p/kWh) | F4: ='Annex 2 EHV charges'!I10 -> Import fixed charge (p/day) | G4: ='Annex 2 EHV charges'!J10 -> Import capacity charge (p/kVA/day) | H4: ='Annex 2 EHV charges'!K10 -> Import exceeded capacity charge (p/kVA/day)
A5: {=IFERROR(INDEX('Annex 2 EHV charges'!$A$11:$A$259, MATCH(0, IF(ISBLANK('Annex 2 EHV charges'!$A$11:$A$259),1, COUNTIF(A$4:$A4, 'Annex 2 EHV charges'!$A$11:$A$259)), 0)),"")} -> 803 | B5: =IF($A5="","",VLOOKUP($A5,'Annex 2 EHV charges'!$A:$O,2,0)) -> 803 | C5: =IF($A5="","",VLOOKUP($A5,'Annex 2 EHV charges'!$A:$O,3,0)) -> 1300035361194 | D5: =IF($A5="","",VLOOKUP($A5,'Annex 2 EHV charges'!$A:$O,7,0)) -> Shell Stanlow | E5: =IFERROR(IF(VLOOKUP($A5,'Annex 2 EHV charges'!$A:$O,8,FALSE)=0,"",VLOOKUP($A5,'Annex 2 EHV charges'!$A:$O,8,FALSE)),"") | F5: =IFERROR(IF(VLOOKUP($A5,'Annex 2 EHV charges'!$A:$O,9,FALSE)=0,"",VLOOKUP($A5,'Annex 2 EHV charges'!$A:$O,9,FALSE)),"") -> 19306.088 | G5: =IFERROR(IF(VLOOKUP($A5,'Annex 2 EHV charges'!$A:$O,10,FALSE)=0,"",VLOOKUP($A5,'Annex 2 EHV charges'!$A:$O,10,FALSE)),"") -> 6.6 | H5: =IFERROR(IF(VLOOKUP($A5,'Annex 2 EHV charges'!$A:$O,11,FALSE)=0,"",VLOOKUP($A5,'Annex 2 EHV charges'!$A:$O,11,FALSE)),"") -> 6.6
A6: {=IFERROR(INDEX('Annex 2 EHV charges'!$A$11:$A$259, MATCH(0, IF(ISBLANK('Annex 2 EHV charges'!$A$11:$A$259),1, COUNTIF(A$4:$A5, 'Annex 2 EHV charges'!$A$11:$A$259)), 0)),"")} -> 804 | B6: =IF($A6="","",VLOOKUP($A6,'Annex 2 EHV charges'!$A:$O,2,0)) -> 804 | C6: =IF($A6="","",VLOOKUP($A6,'Annex 2 EHV charges'!$A:$O,3,0)) -> 1300035352942 | D6: =IF($A6="","",VLOOKUP($A6,'Annex 2 EHV charges'!$A:$O,7,0)) -> Jaguar & Land Rover | E6: =IFERROR(IF(VLOOKUP($A6,'Annex 2 EHV charges'!$A:$O,8,FALSE)=0,"",VLOOKUP($A6,'Annex 2 EHV charges'!$A:$O,8,FALSE)),"") -> 0.302 | F6: =IFERROR(IF(VLOOKUP($A6,'Annex 2 EHV charges'!$A:$O,9,FALSE)=0,"",VLOOKUP($A6,'Annex 2 EHV charges'!$A:$O,9,FALSE)),"") -> 8711.76 | G6: =IFERROR(IF(VLOOKUP($A6,'Annex 2 EHV charges'!$A:$O,10,FALSE)=0,"",VLOOKUP($A6,'Annex 2 EHV charges'!$A:$O,10,FALSE)),"") -> 8.49 | H6: =IFERROR(IF(VLOOKUP($A6,'Annex 2 EHV charges'!$A:$O,11,FALSE)=0,"",VLOOKUP($A6,'Annex 2 EHV charges'!$A:$O,11,FALSE)),"") -> 8.49
A7: {=IFERROR(INDEX('Annex 2 EHV charges'!$A$11:$A$259, MATCH(0, IF(ISBLANK('Annex 2 EHV charges'!$A$11:$A$259),1, COUNTIF(A$4:$A6, 'Annex 2 EHV charges'!$A$11:$A$259)), 0)),"")} -> 805 | B7: =IF($A7="","",VLOOKUP($A7,'Annex 2 EHV charges'!$A:$O,2,0)) -> 805 | C7: =IF($A7="","",VLOOKUP($A7,'Annex 2 EHV charges'!$A:$O,3,0)) -> 1300035359423 | D7: =IF($A7="","",VLOOKUP($A7,'Annex 2 EHV charges'!$A:$O,7,0)) -> Innospec | E7: =IFERROR(IF(VLOOKUP($A7,'Annex 2 EHV charges'!$A:$O,8,FALSE)=0,"",VLOOKUP($A7,'Annex 2 EHV charges'!$A:$O,8,FALSE)),"") -> 0.263 | F7: =IFERROR(IF(VLOOKUP($A7,'Annex 2 EHV charges'!$A:$O,9,FALSE)=0,"",VLOOKUP($A7,'Annex 2 EHV charges'!$A:$O,9,FALSE)),"") -> 844.42 | G7: =IFERROR(IF(VLOOKUP($A7,'Annex 2 EHV charges'!$A:$O,10,FALSE)=0,"",VLOOKUP($A7,'Annex 2 EHV charges'!$A:$O,10,FALSE)),"") -> 4.65 | H7: =IFERROR(IF(VLOOKUP($A7,'Annex 2 EHV charges'!$A:$O,11,FALSE)=0,"",VLOOKUP($A7,'Annex 2 EHV charges'!$A:$O,11,FALSE)),"") -> 4.65
A8: {=IFERROR(INDEX('Annex 2 EHV charges'!$A$11:$A$259, MATCH(0, IF(ISBLANK('Annex 2 EHV charges'!$A$11:$A$259),1, COUNTIF(A$4:$A7, 'Annex 2 EHV charges'!$A$11:$A$259)), 0)),"")} -> 806 | B8: =IF($A8="","",VLOOKUP($A8,'Annex 2 EHV charges'!$A:$O,2,0)) -> 806 | C8: =IF($A8="","",VLOOKUP($A8,'Annex 2 EHV charges'!$A:$O,3,0)) -> 1300051060972 | D8: =IF($A8="","",VLOOKUP($A8,'Annex 2 EHV charges'!$A:$O,7,0)) -> Bridgewater Paper | E8: =IFERROR(IF(VLOOKUP($A8,'Annex 2 EHV charges'!$A:$O,8,FALSE)=0,"",VLOOKUP($A8,'Annex 2 EHV charges'!$A:$O,8,FALSE)),"") | F8: =IFERROR(IF(VLOOKUP($A8,'Annex 2 EHV charges'!$A:$O,9,FALSE)=0,"",VLOOKUP($A8,'Annex 2 EHV charges'!$A:$O,9,FALSE)),"") -> 98.14 | G8: =IFERROR(IF(VLOOKUP($A8,'Annex 2 EHV charges'!$A:$O,10,FALSE)=0,"",VLOOKUP($A8,'Annex 2 EHV charges'!$A:$O,10,FALSE)),"") -> 3.14 | H8: =IFERROR(IF(VLOOKUP($A8,'Annex 2 EHV charges'!$A:$O,11,FALSE)=0,"",VLOOKUP($A8,'Annex 2 EHV charges'!$A:$O,11,FALSE)),"") -> 3.14
A9: {=IFERROR(INDEX('Annex 2 EHV charges'!$A$11:$A$259, MATCH(0, IF(ISBLANK('Annex 2 EHV charges'!$A$11:$A$259),1, COUNTIF(A$4:$A8, 'Annex 2 EHV charges'!$A$11:$A$259)), 0)),"")} -> 807 | B9: =IF($A9="","",VLOOKUP($A9,'Annex 2 EHV charges'!$A:$O,2,0)) -> 807 | C9: =IF($A9="","",VLOOKUP($A9,'Annex 2 EHV charges'!$A:$O,3,0)) -> 1300035359752 | D9: =IF($A9="","",VLOOKUP($A9,'Annex 2 EHV charges'!$A:$O,7,0)) -> General Motors | E9: =IFERROR(IF(VLOOKUP($A9,'Annex 2 EHV charges'!$A:$O,8,FALSE)=0,"",VLOOKUP($A9,'Annex 2 EHV charges'!$A:$O,8,FALSE)),"") -> 0.266 | F9: =IFERROR(IF(VLOOKUP($A9,'Annex 2 EHV charges'!$A:$O,9,FALSE)=0,"",VLOOKUP($A9,'Annex 2 EHV charges'!$A:$O,9,FALSE)),"") -> 14550.17 | G9: =IFERROR(IF(VLOOKUP($A9,'Annex 2 EHV charges'!$A:$O,10,FALSE)=0,"",VLOOKUP($A9,'Annex 2 EHV charges'!$A:$O,10,FALSE)),"") -> 4.52 | H9: =IFERROR(IF(VLOOKUP($A9,'Annex 2 EHV charges'!$A:$O,11,FALSE)=0,"",VLOOKUP($A9,'Annex 2 EHV charges'!$A:$O,11,FALSE)),"") -> 4.52
A10: {=IFERROR(INDEX('Annex 2 EHV charges'!$A$11:$A$259, MATCH(0, IF(ISBLANK('Annex 2 EHV charges'!$A$11:$A$259),1, COUNTIF(A$4:$A9, 'Annex 2 EHV charges'!$A$11:$A$259)), 0)),"")} -> 808 | B10: =IF($A10="","",VLOOKUP($A10,'Annex 2 EHV charges'!$A:$O,2,0)) -> 808 | C10: =IF($A10="","",VLOOKUP($A10,'Annex 2 EHV charges'!$A:$O,3,0)) -> 1300035360066 | D10: =IF($A10="","",VLOOKUP($A10,'Annex 2 EHV charges'!$A:$O,7,0)) -> TATA Steel | E10: =IFERROR(IF(VLOOKUP($A10,'Annex 2 EHV charges'!$A:$O,8,FALSE)=0,"",VLOOKUP($A10,'Annex 2 EHV charges'!$A:$O,8,FALSE)),"") | F10: =IFERROR(IF(VLOOKUP($A10,'Annex 2 EHV charges'!$A:$O,9,FALSE)=0,"",VLOOKUP($A10,'Annex 2 EHV charges'!$A:$O,9,FALSE)),"") -> 38475.65 | G10: =IFERROR(IF(VLOOKUP($A10,'Annex 2 EHV charges'!$A:$O,10,FALSE)=0,"",VLOOKUP($A10,'Annex 2 EHV charges'!$A:$O,10,FALSE)),"") -> 5.07 | H10: =IFERROR(IF(VLOOKUP($A10,'Annex 2 EHV charges'!$A:$O,11,FALSE)=0,"",VLOOKUP($A10,'Annex 2 EHV charges'!$A:$O,11,FALSE)),"") -> 5.07
A11: {=IFERROR(INDEX('Annex 2 EHV charges'!$A$11:$A$259, MATCH(0, IF(ISBLANK('Annex 2 EHV charges'!$A$11:$A$259),1, COUNTIF(A$4:$A10, 'Annex 2 EHV charges'!$A$11:$A$259)), 0)),"")} -> 809 | B11: =IF($A11="","",VLOOKUP($A11,'Annex 2 EHV charges'!$A:$O,2,0)) -> 809 | C11: =IF($A11="","",VLOOKUP($A11,'Annex 2 EHV charges'!$A:$O,3,0)) -> 1300035362480 | D11: =IF($A11="","",VLOOKUP($A11,'Annex 2 EHV charges'!$A:$O,7,0)) -> Urenco | E11: =IFERROR(IF(VLOOKUP($A11,'Annex 2 EHV charges'!$A:$O,8,FALSE)=0,"",VLOOKUP($A11,'Annex 2 EHV charges'!$A:$O,8,FALSE)),"") | F11: =IFERROR(IF(VLOOKUP($A11,'Annex 2 EHV charges'!$A:$O,9,FALSE)=0,"",VLOOKUP($A11,'Annex 2 EHV charges'!$A:$O,9,FALSE)),"") | G11: =IFERROR(IF(VLOOKUP($A11,'Annex 2 EHV charges'!$A:$O,10,FALSE)=0,"",VLOOKUP($A11,'Annex 2 EHV charges'!$A:$O,10,FALSE)),"") -> 4.09 | H11: =IFERROR(IF(VLOOKUP($A11,'Annex 2 EHV charges'!$A:$O,11,FALSE)=0,"",VLOOKUP($A11,'Annex 2 EHV charges'!$A:$O,11,FALSE)),"") -> 4.09
A12: {=IFERROR(INDEX('Annex 2 EHV charges'!$A$11:$A$259, MATCH(0, IF(ISBLANK('Annex 2 EHV charges'!$A$11:$A$259),1, COUNTIF(A$4:$A11, 'Annex 2 EHV charges'!$A$11:$A$259)), 0)),"")} -> 810 | B12: =IF($A12="","",VLOOKUP($A12,'Annex 2 EHV charges'!$A:$O,2,0)) -> 810 | C12: =IF($A12="","",VLOOKUP($A12,'Annex 2 EHV charges'!$A:$O,3,0)) -> 1300051694818 | D12: =IF($A12="","",VLOOKUP($A12,'Annex 2 EHV charges'!$A:$O,7,0)) -> Ineos Chlor Ltd (Lostock) | E12: =IFERROR(IF(VLOOKUP($A12,'Annex 2 EHV charges'!$A:$O,8,FALSE)=0,"",VLOOKUP($A12,'Annex 2 EHV charges'!$A:$O,8,FALSE)),"") | F12: =IFERROR(IF(VLOOKUP($A12,'Annex 2 EHV charges'!$A:$O,9,FALSE)=0,"",VLOOKUP($A12,'Annex 2 EHV charges'!$A:$O,9,FALSE)),"") -> 13181.11 | G12: =IFERROR(IF(VLOOKUP($A12,'Annex 2 EHV charges'!$A:$O,10,FALSE)=0,"",VLOOKUP($A12,'Annex 2 EHV charges'!$A:$O,10,FALSE)),"") -> 1.56 | H12: =IFERROR(IF(VLOOKUP($A12,'Annex 2 EHV charges'!$A:$O,11,FALSE)=0,"",VLOOKUP($A12,'Annex 2 EHV charges'!$A:$O,11,FALSE)),"") -> 1.56
A13: {=IFERROR(INDEX('Annex 2 EHV charges'!$A$11:$A$259, MATCH(0, IF(ISBLANK('Annex 2 EHV charges'!$A$11:$A$259),1, COUNTIF(A$4:$A12, 'Annex 2 EHV charges'!$A$11:$A$259)), 0)),"")} -> 811 | B13: =IF($A13="","",VLOOKUP($A13,'Annex 2 EHV charges'!$A:$O,2,0)) -> 811 | C13: =IF($A13="","",VLOOKUP($A13,'Annex 2 EHV charges'!$A:$O,3,0)) -> 1300060704073 | D13: =IF($A13="","",VLOOKUP($A13,'Annex 2 EHV charges'!$A:$O,7,0)) -> SafeGuard Bradwell | E13: =IFERROR(IF(VLOOKUP($A13,'Annex 2 EHV charges'!$A:$O,8,FALSE)=0,"",VLOOKUP($A13,'Annex 2 EHV charges'!$A:$O,8,FALSE)),"") -> 1.713 | F13: =IFERROR(IF(VLOOKUP($A13,'Annex 2 EHV charges'!$A:$O,9,FALSE)=0,"",VLOOKUP($A13,'Annex 2 EHV charges'!$A:$O,9,FALSE)),"") -> 45.24 | G13: =IFERROR(IF(VLOOKUP($A13,'Annex 2 EHV charges'!$A:$O,10,FALSE)=0,"",VLOOKUP($A13,'Annex 2 EHV charges'!$A:$O,10,FALSE)),"") -> 4.42 | H13: =IFERROR(IF(VLOOKUP($A13,'Annex 2 EHV charges'!$A:$O,11,FALSE)=0,"",VLOOKUP($A13,'Annex 2 EHV charges'!$A:$O,11,FALSE)),"") -> 4.42
A14: {=IFERROR(INDEX('Annex 2 EHV charges'!$A$11:$A$259, MATCH(0, IF(ISBLANK('Annex 2 EHV charges'!$A$11:$A$259),1, COUNTIF(A$4:$A13, 'Annex 2 EHV charges'!$A$11:$A$259)), 0)),"")} -> 812 | B14: =IF($A14="","",VLOOKUP($A14,'Annex 2 EHV charges'!$A:$O,2,0)) -> 812 | C14: =IF($A14="","",VLOOKUP($A14,'Annex 2 EHV charges'!$A:$O,3,0)) -> 1300035356130 | D14: =IF($A14="","",VLOOKUP($A14,'Annex 2 EHV charges'!$A:$O,7,0)) -> Knauf Insulation | E14: =IFERROR(IF(VLOOKUP($A14,'Annex 2 EHV charges'!$A:$O,8,FALSE)=0,"",VLOOKUP($A14,'Annex 2 EHV charges'!$A:$O,8,FALSE)),"") -> 0.305 | F14: =IFERROR(IF(VLOOKUP($A14,'Annex 2 EHV charges'!$A:$O,9,FALSE)=0,"",VLOOKUP($A14,'Annex 2 EHV charges'!$A:$O,9,FALSE)),"") -> 1697.93 | G14: =IFERROR(IF(VLOOKUP($A14,'Annex 2 EHV charges'!$A:$O,10,FALSE)=0,"",VLOOKUP($A14,'Annex 2 EHV charges'!$A:$O,10,FALSE)),"") -> 7.75 | H14: =IFERROR(IF(VLOOKUP($A14,'Annex 2 EHV charges'!$A:$O,11,FALSE)=0,"",VLOOKUP($A14,'Annex 2 EHV charges'!$A:$O,11,FALSE)),"") -> 7.75
A15: {=IFERROR(INDEX('Annex 2 EHV charges'!$A$11:$A$259, MATCH(0, IF(ISBLANK('Annex 2 EHV charges'!$A$11:$A$259),1, COUNTIF(A$4:$A14, 'Annex 2 EHV charges'!$A$11:$A$259)), 0)),"")} -> 813 | B15: =IF($A15="","",VLOOKUP($A15,'Annex 2 EHV charges'!$A:$O,2,0)) -> 813 | C15: =IF($A15="","",VLOOKUP($A15,'Annex 2 EHV charges'!$A:$O,3,0)) -> 1300035359585 | D15: =IF($A15="","",VLOOKUP($A15,'Annex 2 EHV charges'!$A:$O,7,0)) -> Air Products | E15: =IFERROR(IF(VLOOKUP($A15,'Annex 2 EHV charges'!$A:$O,8,FALSE)=0,"",VLOOKUP($A15,'Annex 2 EHV charges'!$A:$O,8,FALSE)),"") -> 0.34 | F15: =IFERROR(IF(VLOOKUP($A15,'Annex 2 EHV charges'!$A:$O,9,FALSE)=0,"",VLOOKUP($A15,'Annex 2 EHV charges'!$A:$O,9,FALSE)),"") -> 384.2 | G15: =IFERROR(IF(VLOOKUP($A15,'Annex 2 EHV charges'!$A:$O,10,FALSE)=0,"",VLOOKUP($A15,'Annex 2 EHV charges'!$A:$O,10,FALSE)),"") -> 4.42 | H15: =IFERROR(IF(VLOOKUP($A15,'Annex 2 EHV charges'!$A:$O,11,FALSE)=0,"",VLOOKUP($A15,'Annex 2 EHV charges'!$A:$O,11,FALSE)),"") -> 4.42
A16: {=IFERROR(INDEX('Annex 2 EHV charges'!$A$11:$A$259, MATCH(0, IF(ISBLANK('Annex 2 EHV charges'!$A$11:$A$259),1, COUNTIF(A$4:$A15, 'Annex 2 EHV charges'!$A$11:$A$259)), 0)),"")} -> 814 | B16: =IF($A16="","",VLOOKUP($A16,'Annex 2 EHV charges'!$A:$O,2,0)) -> 814 | C16: =IF($A16="","",VLOOKUP($A16,'Annex 2 EHV charges'!$A:$O,3,0)) -> 1300035359619 | D16: =IF($A16="","",VLOOKUP($A16,'Annex 2 EHV charges'!$A:$O,7,0)) -> Shell Chemicals | E16: =IFERROR(IF(VLOOKUP($A16,'Annex 2 EHV charges'!$A:$O,8,FALSE)=0,"",VLOOKUP($A16,'Annex 2 EHV charges'!$A:$O,8,FALSE)),"") -> 0.275 | F16: =IFERROR(IF(VLOOKUP($A16,'Annex 2 EHV charges'!$A:$O,9,FALSE)=0,"",VLOOKUP($A16,'Annex 2 EHV charges'!$A:$O,9,FALSE)),"") -> 1697.93 | G16: =IFERROR(IF(VLOOKUP($A16,'Annex 2 EHV charges'!$A:$O,10,FALSE)=0,"",VLOOKUP($A16,'Annex 2 EHV charges'!$A:$O,10,FALSE)),"") -> 8.79 | H16: =IFERROR(IF(VLOOKUP($A16,'Annex 2 EHV charges'!$A:$O,11,FALSE)=0,"",VLOOKUP($A16,'Annex 2 EHV charges'!$A:$O,11,FALSE)),"") -> 8.79
... A254: {=IFERROR(INDEX('Annex 2 EHV charges'!$A$11:$A$259, MATCH(0, IF(ISBLANK('Annex 2 EHV charges'!$A$11:$A$259),1, COUNTIF(A$4:$A253, 'Annex 2 EHV charges'!$A$11:$A$259)), 0)),"")} | B254: =IF($A254="","",VLOOKUP($A254,'Annex 2 EHV charges'!$A:$O,2,0)) | C254: =IF($A254="","",VLOOKUP($A254,'Annex 2 EHV charges'!$A:$O,3,0)) | D254: =IF($A254="","",VLOOKUP($A254,'Annex 2 EHV charges'!$A:$O,7,0)) | E254: =IFERROR(IF(VLOOKUP($A254,'Annex 2 EHV charges'!$A:$O,8,FALSE)=0,"",VLOOKUP($A254,'Annex 2 EHV charges'!$A:$O,8,FALSE)),"") | F254: =IFERROR(IF(VLOOKUP($A254,'Annex 2 EHV charges'!$A:$O,9,FALSE)=0,"",VLOOKUP($A254,'Annex 2 EHV charges'!$A:$O,9,FALSE)),"") | G254: =IFERROR(IF(VLOOKUP($A254,'Annex 2 EHV charges'!$A:$O,10,FALSE)=0,"",VLOOKUP($A254,'Annex 2 EHV charges'!$A:$O,10,FALSE)),"") | H254: =IFERROR(IF(VLOOKUP($A254,'Annex 2 EHV charges'!$A:$O,11,FALSE)=0,"",VLOOKUP($A254,'Annex 2 EHV charges'!$A:$O,11,FALSE)),"")

Sheet Annex 2b Export
A1: Note: The list of MPANs / MSIDs provided may be incomplete; the DNO reserves the right to apply the listed charges to any other MPANs / MSIDs associated with the site. Note: This table is automatically populated based on the content of the tab entitled 'Annex 2 EHV Charges'. The timebands are as shown in Annex 2.
A2: =Overview!B4& " - Effective from "&Overview!D4&" - "&Overview!E4&" EDCM export charges" -> SP Manweb - Effective from 1 April 2019 - Final EDCM export charges
A4: Export Unique Identifier | B4: LLFC | C4: Export MPANs/MSIDs | D4: Name | E4: ='Annex 2 EHV charges'!L10 -> Export Super Red unit charge (p/kWh) | F4: ='Annex 2 EHV charges'!M10 -> Export fixed charge (p/day) | G4: ='Annex 2 EHV charges'!N10 -> Export capacity charge (p/kVA/day) | H4: ='Annex 2 EHV charges'!O10 -> Export exceeded capacity charge (p/kVA/day)
A5: {=IFERROR(INDEX('Annex 2 EHV charges'!$D$11:$D$259, MATCH(0, IF(ISBLANK('Annex 2 EHV charges'!$D$11:$D$259),1, COUNTIF(A$4:$A4, 'Annex 2 EHV charges'!$D$11:$D$259)), 0)),"")} -> 603 | B5: =IF($A5="","",VLOOKUP($A5,'Annex 2 EHV charges'!$D:$O,2,0)) -> 603 | C5: =IF($A5="","",VLOOKUP($A5,'Annex 2 EHV charges'!$D:$O,3,0)) -> 1300050649372 | D5: =IF($A5="","",VLOOKUP($A5,'Annex 2 EHV charges'!$D:$O,4,0)) -> Shell Stanlow | E5: =IFERROR(IF(VLOOKUP($A5,'Annex 2 EHV charges'!$D:$O,9,FALSE)=0,"",VLOOKUP($A5,'Annex 2 EHV charges'!$D:$O,9,FALSE)),"") -> -0.262 | F5: =IFERROR(IF(VLOOKUP($A5,'Annex 2 EHV charges'!$D:$O,10,FALSE)=0,"",VLOOKUP($A5,'Annex 2 EHV charges'!$D:$O,10,FALSE)),"") -> 2382.34 | G5: =IFERROR(IF(VLOOKUP($A5,'Annex 2 EHV charges'!$D:$O,11,FALSE)=0,"",VLOOKUP($A5,'Annex 2 EHV charges'!$D:$O,11,FALSE)),"") -> 0.05 | H5: =IFERROR(IF(VLOOKUP($A5,'Annex 2 EHV charges'!$D:$O,12,FALSE)=0,"",VLOOKUP($A5,'Annex 2 EHV charges'!$D:$O,12,FALSE)),"") -> 0.05
A6: {=IFERROR(INDEX('Annex 2 EHV charges'!$D$11:$D$259, MATCH(0, IF(ISBLANK('Annex 2 EHV charges'!$D$11:$D$259),1, COUNTIF(A$4:$A5, 'Annex 2 EHV charges'!$D$11:$D$259)), 0)),"")} -> 606 | B6: =IF($A6="","",VLOOKUP($A6,'Annex 2 EHV charges'!$D:$O,2,0)) -> 606 | C6: =IF($A6="","",VLOOKUP($A6,'Annex 2 EHV charges'!$D:$O,3,0)) -> 1300051060981 | D6: =IF($A6="","",VLOOKUP($A6,'Annex 2 EHV charges'!$D:$O,4,0)) -> Bridgewater Paper | E6: =IFERROR(IF(VLOOKUP($A6,'Annex 2 EHV charges'!$D:$O,9,FALSE)=0,"",VLOOKUP($A6,'Annex 2 EHV charges'!$D:$O,9,FALSE)),"") | F6: =IFERROR(IF(VLOOKUP($A6,'Annex 2 EHV charges'!$D:$O,10,FALSE)=0,"",VLOOKUP($A6,'Annex 2 EHV charges'!$D:$O,10,FALSE)),"") | G6: =IFERROR(IF(VLOOKUP($A6,'Annex 2 EHV charges'!$D:$O,11,FALSE)=0,"",VLOOKUP($A6,'Annex 2 EHV charges'!$D:$O,11,FALSE)),"") | H6: =IFERROR(IF(VLOOKUP($A6,'Annex 2 EHV charges'!$D:$O,12,FALSE)=0,"",VLOOKUP($A6,'Annex 2 EHV charges'!$D:$O,12,FALSE)),"")
A7: {=IFERROR(INDEX('Annex 2 EHV charges'!$D$11:$D$259, MATCH(0, IF(ISBLANK('Annex 2 EHV charges'!$D$11:$D$259),1, COUNTIF(A$4:$A6, 'Annex 2 EHV charges'!$D$11:$D$259)), 0)),"")} -> 618 | B7: =IF($A7="","",VLOOKUP($A7,'Annex 2 EHV charges'!$D:$O,2,0)) -> 618 | C7: =IF($A7="","",VLOOKUP($A7,'Annex 2 EHV charges'!$D:$O,3,0)) -> 1300060704603 | D7: =IF($A7="","",VLOOKUP($A7,'Annex 2 EHV charges'!$D:$O,4,0)) -> Ineos Chlor Ltd (Lostock) | E7: =IFERROR(IF(VLOOKUP($A7,'Annex 2 EHV charges'!$D:$O,9,FALSE)=0,"",VLOOKUP($A7,'Annex 2 EHV charges'!$D:$O,9,FALSE)),"") | F7: =IFERROR(IF(VLOOKUP($A7,'Annex 2 EHV charges'!$D:$O,10,FALSE)=0,"",VLOOKUP($A7,'Annex 2 EHV charges'!$D:$O,10,FALSE)),"") -> 2015.58 | G7: =IFERROR(IF(VLOOKUP($A7,'Annex 2 EHV charges'!$D:$O,11,FALSE)=0,"",VLOOKUP($A7,'Annex 2 EHV charges'!$D:$O,11,FALSE)),"") -> 0.05 | H7: =IFERROR(IF(VLOOKUP($A7,'Annex 2 EHV charges'!$D:$O,12,FALSE)=0,"",VLOOKUP($A7,'Annex 2 EHV charges'!$D:$O,12,FALSE)),"") -> 0.05
A8: {=IFERROR(INDEX('Annex 2 EHV charges'!$D$11:$D$259, MATCH(0, IF(ISBLANK('Annex 2 EHV charges'!$D$11:$D$259),1, COUNTIF(A$4:$A7, 'Annex 2 EHV charges'!$D$11:$D$259)), 0)),"")} -> 655 | B8: =IF($A8="","",VLOOKUP($A8,'Annex 2 EHV charges'!$D:$O,2,0)) -> 655 | C8: =IF($A8="","",VLOOKUP($A8,'Annex 2 EHV charges'!$D:$O,3,0)) -> 1300060704082 | D8: =IF($A8="","",VLOOKUP($A8,'Annex 2 EHV charges'!$D:$O,4,0)) -> SafeGuard Bradwell | E8: =IFERROR(IF(VLOOKUP($A8,'Annex 2 EHV charges'!$D:$O,9,FALSE)=0,"",VLOOKUP($A8,'Annex 2 EHV charges'!$D:$O,9,FALSE)),"") | F8: =IFERROR(IF(VLOOKUP($A8,'Annex 2 EHV charges'!$D:$O,10,FALSE)=0,"",VLOOKUP($A8,'Annex 2 EHV charges'!$D:$O,10,FALSE)),"") -> 3528.34 | G8: =IFERROR(IF(VLOOKUP($A8,'Annex 2 EHV charges'!$D:$O,11,FALSE)=0,"",VLOOKUP($A8,'Annex 2 EHV charges'!$D:$O,11,FALSE)),"") -> 0.05 | H8: =IFERROR(IF(VLOOKUP($A8,'Annex 2 EHV charges'!$D:$O,12,FALSE)=0,"",VLOOKUP($A8,'Annex 2 EHV charges'!$D:$O,12,FALSE)),"") -> 0.05
A9: {=IFERROR(INDEX('Annex 2 EHV charges'!$D$11:$D$259, MATCH(0, IF(ISBLANK('Annex 2 EHV charges'!$D$11:$D$259),1, COUNTIF(A$4:$A8, 'Annex 2 EHV charges'!$D$11:$D$259)), 0)),"")} -> 648 | B9: =IF($A9="","",VLOOKUP($A9,'Annex 2 EHV charges'!$D:$O,2,0)) -> 648 | C9: =IF($A9="","",VLOOKUP($A9,'Annex 2 EHV charges'!$D:$O,3,0)) -> 1300060640474 | D9: =IF($A9="","",VLOOKUP($A9,'Annex 2 EHV charges'!$D:$O,4,0)) -> Kronospan | E9: =IFERROR(IF(VLOOKUP($A9,'Annex 2 EHV charges'!$D:$O,9,FALSE)=0,"",VLOOKUP($A9,'Annex 2 EHV charges'!$D:$O,9,FALSE)),"") | F9: =IFERROR(IF(VLOOKUP($A9,'Annex 2 EHV charges'!$D:$O,10,FALSE)=0,"",VLOOKUP($A9,'Annex 2 EHV charges'!$D:$O,10,FALSE)),"") -> 388.97 | G9: =IFERROR(IF(VLOOKUP($A9,'Annex 2 EHV charges'!$D:$O,11,FALSE)=0,"",VLOOKUP($A9,'Annex 2 EHV charges'!$D:$O,11,FALSE)),"") -> 0.05 | H9: =IFERROR(IF(VLOOKUP($A9,'Annex 2 EHV charges'!$D:$O,12,FALSE)=0,"",VLOOKUP($A9,'Annex 2 EHV charges'!$D:$O,12,FALSE)),"") -> 0.05
A10: {=IFERROR(INDEX('Annex 2 EHV charges'!$D$11:$D$259, MATCH(0, IF(ISBLANK('Annex 2 EHV charges'!$D$11:$D$259),1, COUNTIF(A$4:$A9, 'Annex 2 EHV charges'!$D$11:$D$259)), 0)),"")} -> 619 | B10: =IF($A10="","",VLOOKUP($A10,'Annex 2 EHV charges'!$D:$O,2,0)) -> 619 | C10: =IF($A10="","",VLOOKUP($A10,'Annex 2 EHV charges'!$D:$O,3,0)) -> 1300051136210 | D10: =IF($A10="","",VLOOKUP($A10,'Annex 2 EHV charges'!$D:$O,4,0)) -> Albion Inorganic | E10: =IFERROR(IF(VLOOKUP($A10,'Annex 2 EHV charges'!$D:$O,9,FALSE)=0,"",VLOOKUP($A10,'Annex 2 EHV charges'!$D:$O,9,FALSE)),"") | F10: =IFERROR(IF(VLOOKUP($A10,'Annex 2 EHV charges'!$D:$O,10,FALSE)=0,"",VLOOKUP($A10,'Annex 2 EHV charges'!$D:$O,10,FALSE)),"") | G10: =IFERROR(IF(VLOOKUP($A10,'Annex 2 EHV charges'!$D:$O,11,FALSE)=0,"",VLOOKUP($A10,'Annex 2 EHV charges'!$D:$O,11,FALSE)),"") | H10: =IFERROR(IF(VLOOKUP($A10,'Annex 2 EHV charges'!$D:$O,12,FALSE)=0,"",VLOOKUP($A10,'Annex 2 EHV charges'!$D:$O,12,FALSE)),"")
A11: {=IFERROR(INDEX('Annex 2 EHV charges'!$D$11:$D$259, MATCH(0, IF(ISBLANK('Annex 2 EHV charges'!$D$11:$D$259),1, COUNTIF(A$4:$A10, 'Annex 2 EHV charges'!$D$11:$D$259)), 0)),"")} -> 658 | B11: =IF($A11="","",VLOOKUP($A11,'Annex 2 EHV charges'!$D:$O,2,0)) -> 658 | C11: =IF($A11="","",VLOOKUP($A11,'Annex 2 EHV charges'!$D:$O,3,0)) -> 1300060563759 | D11: =IF($A11="","",VLOOKUP($A11,'Annex 2 EHV charges'!$D:$O,4,0)) -> Tyn dryfol PV | E11: =IFERROR(IF(VLOOKUP($A11,'Annex 2 EHV charges'!$D:$O,9,FALSE)=0,"",VLOOKUP($A11,'Annex 2 EHV charges'!$D:$O,9,FALSE)),"") | F11: =IFERROR(IF(VLOOKUP($A11,'Annex 2 EHV charges'!$D:$O,10,FALSE)=0,"",VLOOKUP($A11,'Annex 2 EHV charges'!$D:$O,10,FALSE)),"") -> 2414.17 | G11: =IFERROR(IF(VLOOKUP($A11,'Annex 2 EHV charges'!$D:$O,11,FALSE)=0,"",VLOOKUP($A11,'Annex 2 EHV charges'!$D:$O,11,FALSE)),"") -> 0.05 | H11: =IFERROR(IF(VLOOKUP($A11,'Annex 2 EHV charges'!$D:$O,12,FALSE)=0,"",VLOOKUP($A11,'Annex 2 EHV charges'!$D:$O,12,FALSE)),"") -> 0.05
A12: {=IFERROR(INDEX('Annex 2 EHV charges'!$D$11:$D$259, MATCH(0, IF(ISBLANK('Annex 2 EHV charges'!$D$11:$D$259),1, COUNTIF(A$4:$A11, 'Annex 2 EHV charges'!$D$11:$D$259)), 0)),"")} -> 621 | B12: =IF($A12="","",VLOOKUP($A12,'Annex 2 EHV charges'!$D:$O,2,0)) -> 621 | C12: =IF($A12="","",VLOOKUP($A12,'Annex 2 EHV charges'!$D:$O,3,0)) -> 1300050649336 | D12: =IF($A12="","",VLOOKUP($A12,'Annex 2 EHV charges'!$D:$O,4,0)) -> BHP | E12: =IFERROR(IF(VLOOKUP($A12,'Annex 2 EHV charges'!$D:$O,9,FALSE)=0,"",VLOOKUP($A12,'Annex 2 EHV charges'!$D:$O,9,FALSE)),"") | F12: =IFERROR(IF(VLOOKUP($A12,'Annex 2 EHV charges'!$D:$O,10,FALSE)=0,"",VLOOKUP($A12,'Annex 2 EHV charges'!$D:$O,10,FALSE)),"") | G12: =IFERROR(IF(VLOOKUP($A12,'Annex 2 EHV charges'!$D:$O,11,FALSE)=0,"",VLOOKUP($A12,'Annex 2 EHV charges'!$D:$O,11,FALSE)),"") | H12: =IFERROR(IF(VLOOKUP($A12,'Annex 2 EHV charges'!$D:$O,12,FALSE)=0,"",VLOOKUP($A12,'Annex 2 EHV charges'!$D:$O,12,FALSE)),"")
A13: {=IFERROR(INDEX('Annex 2 EHV charges'!$D$11:$D$259, MATCH(0, IF(ISBLANK('Annex 2 EHV charges'!$D$11:$D$259),1, COUNTIF(A$4:$A12, 'Annex 2 EHV charges'!$D$11:$D$259)), 0)),"")} -> 659 | B13: =IF($A13="","",VLOOKUP($A13,'Annex 2 EHV charges'!$D:$O,2,0)) -> 659 | C13: =IF($A13="","",VLOOKUP($A13,'Annex 2 EHV charges'!$D:$O,3,0)) -> 1300060652629 | D13: =IF($A13="","",VLOOKUP($A13,'Annex 2 EHV charges'!$D:$O,4,0)) -> Williams Farm Solar Park | E13: =IFERROR(IF(VLOOKUP($A13,'Annex 2 EHV charges'!$D:$O,9,FALSE)=0,"",VLOOKUP($A13,'Annex 2 EHV charges'!$D:$O,9,FALSE)),"") | F13: =IFERROR(IF(VLOOKUP($A13,'Annex 2 EHV charges'!$D:$O,10,FALSE)=0,"",VLOOKUP($A13,'Annex 2 EHV charges'!$D:$O,10,FALSE)),"") -> 743.42 | G13: =IFERROR(IF(VLOOKUP($A13,'Annex 2 EHV charges'!$D:$O,11,FALSE)=0,"",VLOOKUP($A13,'Annex 2 EHV charges'!$D:$O,11,FALSE)),"") -> 0.05 | H13: =IFERROR(IF(VLOOKUP($A13,'Annex 2 EHV charges'!$D:$O,12,FALSE)=0,"",VLOOKUP($A13,'Annex 2 EHV charges'!$D:$O,12,FALSE)),"") -> 0.05
A14: {=IFERROR(INDEX('Annex 2 EHV charges'!$D$11:$D$259, MATCH(0, IF(ISBLANK('Annex 2 EHV charges'!$D$11:$D$259),1, COUNTIF(A$4:$A13, 'Annex 2 EHV charges'!$D$11:$D$259)), 0)),"")} -> 604 | B14: =IF($A14="","",VLOOKUP($A14,'Annex 2 EHV charges'!$D:$O,2,0)) -> 604 | C14: =IF($A14="","",VLOOKUP($A14,'Annex 2 EHV charges'!$D:$O,3,0)) -> 1300054940683 | D14: =IF($A14="","",VLOOKUP($A14,'Annex 2 EHV charges'!$D:$O,4,0)) -> Port of Liverpool | E14: =IFERROR(IF(VLOOKUP($A14,'Annex 2 EHV charges'!$D:$O,9,FALSE)=0,"",VLOOKUP($A14,'Annex 2 EHV charges'!$D:$O,9,FALSE)),"") | F14: =IFERROR(IF(VLOOKUP($A14,'Annex 2 EHV charges'!$D:$O,10,FALSE)=0,"",VLOOKUP($A14,'Annex 2 EHV charges'!$D:$O,10,FALSE)),"") -> 1659.61 | G14: =IFERROR(IF(VLOOKUP($A14,'Annex 2 EHV charges'!$D:$O,11,FALSE)=0,"",VLOOKUP($A14,'Annex 2 EHV charges'!$D:$O,11,FALSE)),"") -> 0.05 | H14: =IFERROR(IF(VLOOKUP($A14,'Annex 2 EHV charges'!$D:$O,12,FALSE)=0,"",VLOOKUP($A14,'Annex 2 EHV charges'!$D:$O,12,FALSE)),"") -> 0.05
A15: {=IFERROR(INDEX('Annex 2 EHV charges'!$D$11:$D$259, MATCH(0, IF(ISBLANK('Annex 2 EHV charges'!$D$11:$D$259),1, COUNTIF(A$4:$A14, 'Annex 2 EHV charges'!$D$11:$D$259)), 0)),"")} -> 661 | B15: =IF($A15="","",VLOOKUP($A15,'Annex 2 EHV charges'!$D:$O,2,0)) -> 661 | C15: =IF($A15="","",VLOOKUP($A15,'Annex 2 EHV charges'!$D:$O,3,0)) -> 1300060579182 | D15: =IF($A15="","",VLOOKUP($A15,'Annex 2 EHV charges'!$D:$O,4,0)) -> Combermere Abbey PV | E15: =IFERROR(IF(VLOOKUP($A15,'Annex 2 EHV charges'!$D:$O,9,FALSE)=0,"",VLOOKUP($A15,'Annex 2 EHV charges'!$D:$O,9,FALSE)),"") | F15: =IFERROR(IF(VLOOKUP($A15,'Annex 2 EHV charges'!$D:$O,10,FALSE)=0,"",VLOOKUP($A15,'Annex 2 EHV charges'!$D:$O,10,FALSE)),"") -> 2496.2 | G15: =IFERROR(IF(VLOOKUP($A15,'Annex 2 EHV charges'!$D:$O,11,FALSE)=0,"",VLOOKUP($A15,'Annex 2 EHV charges'!$D:$O,11,FALSE)),"") -> 0.05 | H15: =IFERROR(IF(VLOOKUP($A15,'Annex 2 EHV charges'!$D:$O,12,FALSE)=0,"",VLOOKUP($A15,'Annex 2 EHV charges'!$D:$O,12,FALSE)),"") -> 0.05
A16: {=IFERROR(INDEX('Annex 2 EHV charges'!$D$11:$D$259, MATCH(0, IF(ISBLANK('Annex 2 EHV charges'!$D$11:$D$259),1, COUNTIF(A$4:$A15, 'Annex 2 EHV charges'!$D$11:$D$259)), 0)),"")} -> 628 | B16: =IF($A16="","",VLOOKUP($A16,'Annex 2 EHV charges'!$D:$O,2,0)) -> 628 | C16: =IF($A16="","",VLOOKUP($A16,'Annex 2 EHV charges'!$D:$O,3,0)) -> 1300060075405 | D16: =IF($A16="","",VLOOKUP($A16,'Annex 2 EHV charges'!$D:$O,4,0)) -> Amegni | E16: =IFERROR(IF(VLOOKUP($A16,'Annex 2 EHV charges'!$D:$O,9,FALSE)=0,"",VLOOKUP($A16,'Annex 2 EHV charges'!$D:$O,9,FALSE)),"") | F16: =IFERROR(IF(VLOOKUP($A16,'Annex 2 EHV charges'!$D:$O,10,FALSE)=0,"",VLOOKUP($A16,'Annex 2 EHV charges'!$D:$O,10,FALSE)),"") -> 620.7 | G16: =IFERROR(IF(VLOOKUP($A16,'Annex 2 EHV charges'!$D:$O,11,FALSE)=0,"",VLOOKUP($A16,'Annex 2 EHV charges'!$D:$O,11,FALSE)),"") -> 0.05 | H16: =IFERROR(IF(VLOOKUP($A16,'Annex 2 EHV charges'!$D:$O,12,FALSE)=0,"",VLOOKUP($A16,'Annex 2 EHV charges'!$D:$O,12,FALSE)),"") -> 0.05
... A254: {=IFERROR(INDEX('Annex 2 EHV charges'!$D$11:$D$259, MATCH(0, IF(ISBLANK('Annex 2 EHV charges'!$D$11:$D$259),1, COUNTIF(A$4:$A253, 'Annex 2 EHV charges'!$D$11:$D$259)), 0)),"")} | B254: =IF($A254="","",VLOOKUP($A254,'Annex 2 EHV charges'!$D:$O,2,0)) | C254: =IF($A254="","",VLOOKUP($A254,'Annex 2 EHV charges'!$D:$O,3,0)) | D254: =IF($A254="","",VLOOKUP($A254,'Annex 2 EHV charges'!$D:$O,4,0)) | E254: =IFERROR(IF(VLOOKUP($A254,'Annex 2 EHV charges'!$D:$O,9,FALSE)=0,"",VLOOKUP($A254,'Annex 2 EHV charges'!$D:$O,9,FALSE)),"") | F254: =IFERROR(IF(VLOOKUP($A254,'Annex 2 EHV charges'!$D:$O,10,FALSE)=0,"",VLOOKUP($A254,'Annex 2 EHV charges'!$D:$O,10,FALSE)),"") | G254: =IFERROR(IF(VLOOKUP($A254,'Annex 2 EHV charges'!$D:$O,11,FALSE)=0,"",VLOOKUP($A254,'Annex 2 EHV charges'!$D:$O,11,FALSE)),"") | H254: =IFERROR(IF(VLOOKUP($A254,'Annex 2 EHV charges'!$D:$O,12,FALSE)=0,"",VLOOKUP($A254,'Annex 2 EHV charges'!$D:$O,12,FALSE)),"")

Sheet Annex 3 Preserved charges
A1: Back to Overview
A2: SP Manweb - Effective from 1 April 2019 - Final LV and HV tariffs
A3: NHH preserved charges/additional LLFCs
B4: Closed LLFCs | C4: PCs | D4: Unit charge 1 (NHH) or red/black charge (HH) p/kWh | E4: Unit charge 2 (NHH) or amber/yellow charge (HH) p/kWh | F4: Green charge(HH) p/kWh | G4: Fixed charge p/MPAN/day | H4: Capacity charge p/kVA/day | I4: Exceeded capacity charge p/kVA/day | J4: Reactive power charge p/kVArh
A5: Domestic Two Rate* | B5: 145, 146 | C5: 2 | D5: 3.686 | E5: 1.545 | G5: 3.68
A6: Domestic Off Peak (related MPAN) | B6: 135, 136, 137, 138, 140, 141, 142, 143 | C6: 2 | D6: 1.556
A7: Small Non Domestic Unrestricted | B7: 207 | C7: 3 | D7: 3.367 | G7: 4.63
A8: Small Non Domestic Two Rate | B8: 208, 210 | C8: 4 | D8: 3.515 | E8: 1.466 | G8: 4.63
A9: Small Non Domestic Off Peak (related MPAN) | B9: 233, 234, 235, 236, 237 | C9: 4 | D9: 1.498
A10: LV Medium Non-Domestic | B10: 401, 402 | C10: 5-8 | D10: 3.452 | E10: 1.434 | G10: 20.58
A11: LV Sub Medium Non-Domestic | B11: 403, 404 | C11: 5-8 | D11: 3.44 | E11: 1.434 | G11: 24.87
A12: HV Medium Non-Domestic | B12: 405 | C12: 5-8 | D12: 2.533 | E12: 1.378 | G12: 190.08
A14: Notes: | B14: Unit time periods are as specified in the SSC.
B15: SP Manweb uses a default tariff for invalid settlement combinations these will be charged at the Domestic Unrestricted Rates. The Domestic and Non-Domestic Off Peak (related MPAN) tariffs are supplementary to a standard published tariff and therefore only available under these conditions. Preserved tariffs are only available to existing supplies, subject to certain conditions: a) Suppliers may not normally transfer a meter point from one preserved tariff to another preserved tariff; b) If a supply under a preserved tariff should cease, other than on change of tenancy, the preserved tariff may not normally be restored; c) Any additional load requried to be supplied on the preserved tariff must be within the existing supply capacity.
B16: *Supplier of Last Resort increases to the Fixed Charges for the Domestic Unrestricted, Domestic Two Rate and LV Domestic Network tariffs. The increase for each of these tariffs is 0.08p/MPAN/day. No other tariffs affected by this change.
A19: HH preserved charges/additional LLFCs
B20: Closed LLFCs | C20: PCs | D20: Red/black charge (HH) p/kWh | E20: Amber/yellow charge (HH) p/kWh | F20: Green charge (HH) p/kWh | G20: Fixed charge p/MPAN/day | H20: Capacity charge p/kVA/day | I20: Exceeded capacity charge p/kVA/day | J20: Reactive power charge p/kVArh
A21: LV HH Metered | B21: 501 | C21: 0 | D21: 10.481 | E21: 2.305 | F21: 1.423 | G21: 18.71 | H21: 2.51 | I21: 4.46 | J21: 0.367
A22: LV Sub HH Metered | B22: 503 | C22: 0 | D22: 8.066 | E22: 1.869 | F22: 1.383 | G22: 6.6 | H22: 5.15 | I22: 7.12 | J22: 0.232
A23: HV HH Metered | B23: 505 | C23: 0 | D23: 6.54 | E23: 1.653 | F23: 1.352 | G23: 99.97 | H23: 4.05 | I23: 6.63 | J23: 0.161
A24: Notes: | B24: Time periods
B26: As detailed in Annex 1
B28: All times are UK clock-time.
B30: Preserved tariffs are only available to existing supplies, subject to certain conditions: a) Suppliers may not normally transfer a meter point from one preserved tariff to another preserved tariff; b) If a supply under a preserved tariff should cease, other than on change of tenancy, the preserved tariff may not normally be restored; c) Any additional load requried to be supplied on the preserved tariff must be within the existing supply capacity.

Sheet Annex 4 LDNO charges
A1: Back to Overview | B1: Copy from CDCM table 3701 "Tariffs!A42:I84" and paste values into A14 | F1: Copy from EDCM table 6005 "LDNORev!B549:G683" and paste values into D57
A2: SP Manweb - Effective from 1 April 2019 - Final LDNO tariffs
A4: Time Bands for Half Hourly Metered Properties | F4: Time Bands for Half Hourly Unmetered Properties
A5: Time periods | B5: Red Time Band | C5: Amber Time Band | D5: Green Time Band | H5: Black Time Band | I5: Yellow Time Band | J5: Green Time Band
A6: Monday to Friday (Including Bank Holidays) All Year | B6: 16.30 - 19.30 | C6: 08.00 - 16.30 19.30 - 22.30 | D6: 00.00 - 08.00 22.30 - 00.00 | F6: Monday to Friday (Including Bank Holidays) June to August Inclusive | I6: 08.00 - 22.30 | J6: 00.00 - 08.00 22.30 - 00.00
A7: Saturday and Sunday All Year | C7: 16.00 - 20.00 | D7: 00.00 - 16.00 20.00 - 00.00 | F7: Monday to Friday (Including Bank Holidays) November to February Inclusive | H7: 16.30 - 19.30 | I7: 08.00 - 16.30 19.30 - 22.30 | J7: 00.00 - 08.00 22.30 - 00.00
A8: Notes | B8: All the above times are in UK Clock time | F8: Monday to Friday (Including Bank Holidays) March to May, & September to October, Inclusive | I8: 08.00 - 22.30 | J8: 00.00 - 08.00 22.30 - 00.00
F9: Saturday and Sunday All year | I9: 16.00 - 20.00 | J9: 00:00-16:00 20:00-00:00
A12: Tariff name | B12: Unique billing identifier | C12: PCs | D12: Unit charge 1 (NHH) or red/black charge (HH) p/kWh | E12: Unit charge 2 (NHH) or amber/yellow charge (HH) p/kWh | F12: Green charge(HH) p/kWh | G12: Fixed charge p/MPAN/day | H12: Capacity charge p/kVA/day | I12: Exceeded capacity charge p/kVA/day | J12: Reactive power charge p/kVArh
A13: LDNO LV: Domestic Unrestricted | D13: 2.09 | G13: 2.24
A14: LDNO LV: Domestic Two Rate | D14: 2.296 | E14: 0.962 | G14: 2.24
A15: LDNO LV: Domestic Off Peak (related MPAN) | D15: 0.969
A16: LDNO LV: Small Non Domestic Unrestricted | D16: 2.097 | G16: 2.88
A17: LDNO LV: Small Non Domestic Two Rate | D17: 2.19 | E17: 0.913 | G17: 2.88
A18: LDNO LV: Small Non Domestic Off Peak (related MPAN) | D18: 0.933
A19: LDNO LV: LV Medium Non-Domestic | D19: 2.15 | E19: 0.893 | G19: 12.82
A20: LDNO LV: LV Network Domestic | D20: 7.641 | E20: 1.633 | F20: 0.905 | G20: 2.24
A21: LDNO LV: LV Network Non-Domestic Non-CT | D21: 7.829 | E21: 1.656 | F21: 0.908 | G21: 2.88
A22: LDNO LV: LV HH Metered | D22: 6.529 | E22: 1.436 | F22: 0.886 | G22: 11.65 | H22: 1.56 | I22: 2.78 | J22: 0.229
A23: LDNO LV: NHH UMS category A | D23: 1.686
A24: LDNO LV: NHH UMS category B | D24: 1.853
A25: LDNO LV: NHH UMS category C | D25: 2.559
A26: LDNO LV: NHH UMS category D | D26: 1.57
A27: LDNO LV: LV UMS (Pseudo HH Metered) | D27: 13.026 | E27: 1.648 | F27: 1.078
A28: LDNO LV: LV Generation NHH or Aggregate HH | D28: -1.228 | G28: 0
A29: LDNO LV: LV Generation Intermittent | D29: -1.228 | G29: 0 | J29: 0.302
A30: LDNO LV: LV Generation Non-Intermittent | D30: -8.287 | E30: -1.036 | F30: -0.158 | G30: 0 | J30: 0.302
A31: LDNO HV: Domestic Unrestricted | D31: 1.353 | G31: 1.45
A32: LDNO HV: Domestic Two Rate | D32: 1.486 | E32: 0.623 | G32: 1.45
A33: LDNO HV: Domestic Off Peak (related MPAN) | D33: 0.627
A34: LDNO HV: Small Non Domestic Unrestricted | D34: 1.358 | G34: 1.87
A35: LDNO HV: Small Non Domestic Two Rate | D35: 1.417 | E35: 0.591 | G35: 1.87
A36: LDNO HV: Small Non Domestic Off Peak (related MPAN) | D36: 0.604
A37: LDNO HV: LV Medium Non-Domestic | D37: 1.392 | E37: 0.578 | G37: 8.3
A38: LDNO HV: LV Network Domestic | D38: 4.946 | E38: 1.057 | F38: 0.586 | G38: 1.45
A39: LDNO HV: LV Network Non-Domestic Non-CT | D39: 5.068 | E39: 1.072 | F39: 0.588 | G39: 1.87
A40: LDNO HV: LV HH Metered | D40: 4.226 | E40: 0.929 | F40: 0.574 | G40: 7.54 | H40: 1.01 | I40: 1.8 | J40: 0.148
A41: LDNO HV: LV Sub HH Metered | D41: 5.232 | E41: 1.212 | F41: 0.897 | G41: 4.28 | H41: 3.34 | I41: 4.62 | J41: 0.15
A42: LDNO HV: HV HH Metered | D42: 4.796 | E42: 1.212 | F42: 0.992 | G42: 73.32 | H42: 2.97 | I42: 4.86 | J42: 0.118
A43: LDNO HV: NHH UMS category A | D43: 1.092
A44: LDNO HV: NHH UMS category B | D44: 1.199
A45: LDNO HV: NHH UMS category C | D45: 1.657
A46: LDNO HV: NHH UMS category D | D46: 1.017
A47: LDNO HV: LV UMS (Pseudo HH Metered) | D47: 8.433 | E47: 1.067 | F47: 0.698
A48: LDNO HV: LV Generation NHH or Aggregate HH | D48: -1.228 | G48: 0
A49: LDNO HV: LV Sub Generation NHH | D49: -1.098 | G49: 0
A50: LDNO HV: LV Generation Intermittent | D50: -1.228 | G50: 0 | J50: 0.302
A51: LDNO HV: LV Generation Non-Intermittent | D51: -8.287 | E51: -1.036 | F51: -0.158 | G51: 0 | J51: 0.302
A52: LDNO HV: LV Sub Generation Intermittent | D52: -1.098 | G52: 0 | J52: 0.28
A53: LDNO HV: LV Sub Generation Non-Intermittent | D53: -7.514 | E53: -0.898 | F53: -0.145 | G53: 0 | J53: 0.28
A54: LDNO HV: HV Generation Intermittent | D54: -0.723 | G54: 0 | J54: 0.214
A55: LDNO HV: HV Generation Non-Intermittent | D55: -5.385 | E55: -0.471 | F55: -0.11 | G55: 0 | J55: 0.214
A56: LDNO HVplus: Domestic Unrestricted | C56: 1 | D56: 1.045 | G56: 1.12
A57: LDNO HVplus: Domestic Two Rate | C57: 2 | D57: 1.148 | E57: 0.481 | G57: 1.12
A58: LDNO HVplus: Domestic Off Peak (related MPAN) | C58: 2 | D58: 0.485
A59: LDNO HVplus: Small Non Domestic Unrestricted | C59: 3 | D59: 1.049 | G59: 1.44
A60: LDNO HVplus: Small Non Domestic Two Rate | C60: 4 | D60: 1.095 | E60: 0.457 | G60: 1.44
A61: LDNO HVplus: Small Non Domestic Off Peak (related MPAN) | C61: 4 | D61: 0.467
A62: LDNO HVplus: LV Medium Non-Domestic | C62: 5-8 | D62: 1.075 | E62: 0.447 | G62: 6.41
A63: LDNO HVplus: LV Sub Medium Non-Domestic | C63: 5-8 | D63: 1.669 | E63: 0.696 | G63: 12.07
A64: LDNO HVplus: HV Medium Non-Domestic | C64: 5-8 | D64: 1.376 | E64: 0.748 | G64: 103.23
A65: LDNO HVplus: LV Network Domestic | C65: - | D65: 3.82 | E65: 0.816 | F65: 0.453 | G65: 1.12
A66: LDNO HVplus: LV Network Non-Domestic Non-CT | C66: - | D66: 3.914 | E66: 0.828 | F66: 0.454 | G66: 1.44
A67: LDNO HVplus: LV HH Metered | C67: 0 | D67: 3.264 | E67: 0.718 | F67: 0.443 | G67: 5.83 | H67: 0.78 | I67: 1.39 | J67: 0.114
A68: LDNO HVplus: LV Sub HH Metered | C68: 0 | D68: 3.914 | E68: 0.907 | F68: 0.671 | G68: 3.2 | H68: 2.5 | I68: 3.46 | J68: 0.113
A69: LDNO HVplus: HV HH Metered | C69: 0 | D69: 3.552 | E69: 0.898 | F69: 0.734 | G69: 54.29 | H69: 2.2 | I69: 3.6 | J69: 0.087
A70: LDNO HVplus: NHH UMS category A | C70: 8 | D70: 0.843
A71: LDNO HVplus: NHH UMS category B | C71: 1 | D71: 0.926
A72: LDNO HVplus: NHH UMS category C | C72: 1 | D72: 1.279
A73: LDNO HVplus: NHH UMS category D | C73: 1 | D73: 0.785
A74: LDNO HVplus: LV UMS (Pseudo HH Metered) | C74: 0 | D74: 6.513 | E74: 0.824 | F74: 0.539
A75: LDNO HVplus: LV Generation NHH or Aggregate HH | C75: 8 | D75: -0.596 | G75: 0
A76: LDNO HVplus: LV Sub Generation NHH | C76: 8 | D76: -0.596 | G76: 0
A77: LDNO HVplus: LV Generation Intermittent | C77: 0 | D77: -0.596 | G77: 0 | J77: 0.147
A78: LDNO HVplus: LV Generation Non-Intermittent | C78: 0 | D78: -4.021 | E78: -0.503 | F78: -0.077 | G78: 0 | J78: 0.147
A79: LDNO HVplus: LV Sub Generation Intermittent | C79: 0 | D79: -0.596 | G79: 0 | J79: 0.152
A80: LDNO HVplus: LV Sub Generation Non-Intermittent | C80: 0 | D80: -4.081 | E80: -0.488 | F80: -0.079 | G80: 0 | J80: 0.152
A81: LDNO HVplus: HV Generation Intermittent | C81: 0 | D81: -0.723 | G81: 73 | J81: 0.214
A82: LDNO HVplus: HV Generation Non-Intermittent | C82: 0 | D82: -5.385 | E82: -0.471 | F82: -0.11 | G82: 73 | J82: 0.214
A83: LDNO EHV: Domestic Unrestricted | C83: 1 | D83: 0.746 | G83: 0.8
A84: LDNO EHV: Domestic Two Rate | C84: 2 | D84: 0.819 | E84: 0.343 | G84: 0.8
A85: LDNO EHV: Domestic Off Peak (related MPAN) | C85: 2 | D85: 0.346
A86: LDNO EHV: Small Non Domestic Unrestricted | C86: 3 | D86: 0.748 | G86: 1.03
A87: LDNO EHV: Small Non Domestic Two Rate | C87: 4 | D87: 0.781 | E87: 0.326 | G87: 1.03
A88: LDNO EHV: Small Non Domestic Off Peak (related MPAN) | C88: 4 | D88: 0.333
A89: LDNO EHV: LV Medium Non-Domestic | C89: 5-8 | D89: 0.767 | E89: 0.319 | G89: 4.57
A90: LDNO EHV: LV Sub Medium Non-Domestic | C90: 5-8 | D90: 1.191 | E90: 0.497 | G90: 8.61
A91: LDNO EHV: HV Medium Non-Domestic | C91: 5-8 | D91: 0.982 | E91: 0.534 | G91: 73.67
A92: LDNO EHV: LV Network Domestic | C92: - | D92: 2.726 | E92: 0.583 | F92: 0.323 | G92: 0.8
A93: LDNO EHV: LV Network Non-Domestic Non-CT | C93: - | D93: 2.794 | E93: 0.591 | F93: 0.324 | G93: 1.03
A94: LDNO EHV: LV HH Metered | C94: 0 | D94: 2.33 | E94: 0.512 | F94: 0.316 | G94: 4.16 | H94: 0.56 | I94: 0.99 | J94: 0.082
A95: LDNO EHV: LV Sub HH Metered | C95: 0 | D95: 2.793 | E95: 0.647 | F95: 0.479 | G95: 2.29 | H95: 1.78 | I95: 2.47 | J95: 0.08
A96: LDNO EHV: HV HH Metered | C96: 0 | D96: 2.535 | E96: 0.641 | F96: 0.524 | G96: 38.75 | H96: 1.57 | I96: 2.57 | J96: 0.062
A97: LDNO EHV: NHH UMS category A | C97: 8 | D97: 0.602
A98: LDNO EHV: NHH UMS category B | C98: 1 | D98: 0.661
A99: LDNO EHV: NHH UMS category C | C99: 1 | D99: 0.913
A100: LDNO EHV: NHH UMS category D | C100: 1 | D100: 0.56
A101: LDNO EHV: LV UMS (Pseudo HH Metered) | C101: 0 | D101: 4.648 | E101: 0.588 | F101: 0.385
A102: LDNO EHV: LV Generation NHH or Aggregate HH | C102: 8 | D102: -0.425 | G102: 0
A103: LDNO EHV: LV Sub Generation NHH | C103: 8 | D103: -0.426 | G103: 0
...

Sheet Annex 5 LLFs
A1: Back to Overview
A2: This table has intentionally been left blank. The line loss factors that are approved by the BSC Panel for the applicable year and consequently published on the Elexon website will take precedence and be used in Settlement. This annex will be re-published once these values are available.
A3: SP Manweb - Illustrative LLFs for year beginning 1 April 2019
A4: Time periods | B4: Period 1 | C4: Period 2 | D4: Period 3 | E4: Period 4
B5: (Name 1) | C5: (Name 2) | D5: (Name 3) | E5: (Name 4)
A6: Monday to Friday March to October | B6: 23:30 – 07:30 | C6: 07:30 – 23:30
A7: Monday to Friday November to February | B7: 23:30 – 07:30 | C7: 20:00 – 23:30 | D7: 07:30 – 16:00 19:00 – 20:00 | E7: 16:00 – 19:00
A8: Saturday and Sunday All Year | B8: 23:30 – 07:30 | C8: 07:30 – 23:30
A9: Notes | B9: All the above times are in UK Clock time
A12: Generic demand and generation LLFs
A13: Metered voltage, respective periods and associated LLFCs
A14: Metered voltage | B14: Period 1 | C14: Period 2 | D14: Period 3 | E14: Period 4 | F14: Associated LLFC
A15: Low-voltage network | B15: 1.087 | C15: 1.105 | D15: 1.118 | E15: 1.138 | F15: 101,102,103,104,105,106,111,112,113,114,115,116,117,118,119,120,130,131,132,133,134,135,136,137,138,140,141,142,143,145,146,147,148,149,150,153,155,180,201,202,203,205,211,212,231,232,233,234,235,236,237,280,401,402,501,511,591,764,765,781,782,783,784,785,786,787,791,795,900,901,902,903,910
A16: Low-voltage substation | B16: 1.057 | C16: 1.06 | D16: 1.065 | E16: 1.069 | F16: 207,208,209,210,403,404,503,513,592,780,788,789,792,796
A17: High-voltage network | B17: 1.032 | C17: 1.038 | D17: 1.043 | E17: 1.047 | F17: 405,505,515,593,768,769,770,771,774,775,776,777,778,779,793,797
A18: High-voltage substation | B18: 1.024 | C18: 1.026 | D18: 1.029 | E18: 1.031 | F18: 300 to 399 Inclusive 445 to 499 Inclusive 700 to 725 Inclusive
A19: 33kV generic Import | B19: 1.016 | C19: 1.018 | D19: 1.02 | E19: 1.022
A20: 33kV generic Export | B20: 1.012 | C20: 1.012 | D20: 1.013 | E20: 1.014
A21: 132kV generic Import | B21: 1.004 | C21: 1.005 | D21: 1.006 | E21: 1.006
A22: 132kV generic Export | B22: 1 | C22: 1 | D22: 1 | E22: 1
A24: EHV site specific LLFs
A25: Demand
A26: Site | B26: Period 1 | C26: Period 2 | D26: Period 3 | E26: Period 4 | F26: Associated LLFC
A27: Shell Stanlow | B27: 1.043 | C27: 1.047 | D27: 1.044 | E27: 1.048 | F27: 803
A28: Jaguar & Land Rover | B28: 1.073 | C28: 1.08 | D28: 1.078 | E28: 1.087 | F28: 804
A29: Innospec | B29: 1.035 | C29: 1.046 | D29: 1.043 | E29: 1.052 | F29: 805
A30: Bridgewater Paper | B30: 1.03 | C30: 1.034 | D30: 1.034 | E30: 1.038 | F30: 806
A31: General Motors | B31: 1.028 | C31: 1.032 | D31: 1.031 | E31: 1.034 | F31: 807
A32: TATA Steel | B32: 1.019 | C32: 1.022 | D32: 1.02 | E32: 1.026 | F32: 808
A33: Urenco | B33: 1.029 | C33: 1.03 | D33: 1.03 | E33: 1.032 | F33: 809
A34: Ineos Chlor Ltd (Lostock) | B34: 1.04 | C34: 1.058 | D34: 1.046 | E34: 1.066 | F34: 810
A35: SafeGuard Bradwell | B35: 1.016 | C35: 1.018 | D35: 1.02 | E35: 1.022 | F35: 811
A36: Knauf Insulation | B36: 1.078 | C36: 1.088 | D36: 1.084 | E36: 1.096 | F36: 812
A37: Air Products | B37: 1.052 | C37: 1.057 | D37: 1.055 | E37: 1.06 | F37: 813
A38: Shell Chemicals | B38: 1.043 | C38: 1.047 | D38: 1.045 | E38: 1.05 | F38: 814
... A123: CEW | B123: 1.016 | C123: 1.018 | D123: 1.02 | E123: 1.022 | F123: 853
A124: Risley DSCP | B124: 1.019 | C124: 1.023 | D124: 1.023 | E124: 1.027 | F124: MSID 0030
A125: Bold DSCP | B125: 1.039 | C125: 1.05 | D125: 1.06 | E125: 1.069 | F125: MSID 0031/32
A126: Dolgarrog PS | B126: 0.986 | C126: 0.991 | D126: 0.985 | E126: 0.991 | F126: MSID 4532/33
A127: Shotton Paper | B127: 1.004 | C127: 1.005 | D127: 1.006 | E127: 1.006 | F127: 802
A128: Burbo Bank Windfarm | B128: 0.997 | C128: 0.999 | D128: 0.997 | E128: 0.999 | F128: MSID 7203
A131: EHV site specific LLFs
A132: Generation
A133: Site | B133: Period 1 | C133: Period 2 | D133: Period 3 | E133: Period 4 | F133: Associated LLFC
A134: Shell Stanlow | B134: 1.031 | C134: 1.031 | D134: 1.033 | E134: 1.033 | F134: 603
A135: Port of Liverpool | B135: 1.008 | C135: 1.014 | D135: 1.012 | E135: 1.018 | F135: 604
A136: Bridgewater Paper | B136: 1.001 | C136: 1.003 | D136: 1.002 | E136: 1.003 | F136: 606
A137: Moel Maelogan 2 | B137: 0.972 | C137: 0.984 | D137: 0.977 | E137: 0.986 | F137: 611
A138: Mersey Warf STOR | B138: 1.012 | C138: 1.012 | D138: 1.013 | E138: 1.014 | F138: 615
A139: Percival Lane STOR | B139: 1.012 | C139: 1.012 | D139: 1.013 | E139: 1.014 | F139: 616
A140: Stanlow STOR | B140: 1.01 | C140: 1.016 | D140: 1.01 | E140: 1.015 | F140: 617
A141: Ineos Chlor Ltd (Lostock) | B141: 1.012 | C141: 1.012 | D141: 1.013 | E141: 1.014 | F141: 618
A142: Albion Inorganic | B142: 1.024 | C142: 1.029 | D142: 1.023 | E142: 1.025 | F142: 619
A143: BHP | B143: 1.023 | C143: 1.044 | D143: 1.039 | E143: 1.058 | F143: 621
A144: Amegni | B144: 0.987 | C144: 0.999 | D144: 1 | E144: 1.01 | F144: 628
A145: Salt Union | B145: 1.032 | C145: 1.032 | D145: 1.033 | E145: 1.033 | F145: 629
... A205: Toyota | B205: 1.012 | C205: 1.012 | D205: 1.013 | E205: 1.014 | F205: 663
A206: Cwm Dyli PS | B206: 0.965 | C206: 0.993 | D206: 0.982 | E206: 0.972 | F206: MSID 4054
A207: Dolgarrog PS | B207: 0.986 | C207: 0.991 | D207: 0.985 | E207: 0.991 | F207: MSID 4532/33
A208: Maentwrog PS | B208: 0.921 | C208: 0.938 | D208: 0.978 | E208: 0.947 | F208: MSID 6015
A209: Shotton Paper | B209: 1 | C209: 1 | D209: 1 | E209: 1 | F209: 601
A210: Burbo Bank Windfarm | B210: 0.997 | C210: 0.999 | D210: 0.997 | E210: 0.999 | F210: MSID 7203

Sheet Annex 6 new or amended EHV
A1: Back to Overview | H1: Note: The list of MPANs/MSIDs provided may be incomplete; the DNO reserves the right to apply the listed charges to any other MPANs/MSIDs associated with the site. If sites appear in both Annex 2 and Annex 6, the charges in Annex 6 take precedence. Where an existing Designated EHV Property is modified and energised in the charging year, we may revise the EDCM charges for the modified Designated EHV Property.
A2: Annex 6 - Charges for New or Amended Designated EHV Properties
A4: =Overview!B4& " - Effective from "&Overview!D4&" - "&Overview!E4&" new designated EHV charges" -> SP Manweb - Effective from 1 April 2019 - Final new designated EHV charges
A5: Effective from date | B5: Import Unique Identifier | C5: LLFC | D5: Import MPANs/MSIDs | E5: Export Unique Identifier | F5: LLFC | G5: Export MPANs/MSIDs | H5: Name | I5: ='Annex 2 EHV charges'!H10 -> Import Super Red unit charge (p/kWh) | J5: ='Annex 2 EHV charges'!I10 -> Import fixed charge (p/day) | K5: ='Annex 2 EHV charges'!J10 -> Import capacity charge (p/kVA/day) | L5: ='Annex 2 EHV charges'!K10 -> Import exceeded capacity charge (p/kVA/day) | M5: ='Annex 2 EHV charges'!L10 -> Export Super Red unit charge (p/kWh) | N5: ='Annex 2 EHV charges'!M10 -> Export fixed charge (p/day) | O5: ='Annex 2 EHV charges'!N10 -> Export capacity charge (p/kVA/day) | P5: ='Annex 2 EHV charges'!O10 -> Export exceeded capacity charge (p/kVA/day)
A6: 01/04/2019 | B6: 895 | C6: 895 | D6: 1300060785462 | E6: 696 | F6: 696 | G6: 1300060785453 | H6: Brenig Wind Farm | I6: 0 | J6: 296.11 | K6: 3.22 | L6: 3.22 | M6: 0 | N6: 23451.82 | O6: 0.05 | P6: 0.05
A7: 01/04/2019 | B7: 911 | C7: 911 | D7: 1300060805612 | E7: 623 | F7: 623 | G7: 1300060805621 | H7: Griffiths Road STOR | I7: 1.713 | J7: 212.44 | K7: 3.19 | L7: 3.19 | M7: -2.32 | N7: 5664.15 | O7: 0.05 | P7: 0.05
A8: 01/04/2019 | B8: 912 | C8: 912 | D8: 1300060805560 | E8: 624 | F8: 624 | G8: 1300060805570 | H8: Warrington Pwr Slutcher | I8: 1.713 | J8: 153.71 | K8: 4.77 | L8: 4.77 | M8: -2.811 | N8: 4100.51 | O8: 0.05 | P8: 0.05
A9: 01/04/2019 | B9: 914 | C9: 914 | D9: 1300060818597 | E9: 626 | F9: 626 | G9: 1300060818602 | H9: Latchford Lane STOR | I9: 1.713 | J9: 16.67 | K9: 4.77 | L9: 4.77 | M9: -2.811 | N9: 1267.98 | O9: 0.05 | P9: 0.05
A10: 01/04/2019 | B10: 853 | C10: 853 | E10: 653 | F10: 653 | H10: CEW | I10: 0.281 | J10: 278.44 | K10: 4.46 | L10: 4.46 | M10: -0.913 | N10: 5822.98 | O10: 0.05 | P10: 0.05
A11: 01/04/2019 | B11: 833 | C11: 833 | D11: 1300035361803 | E11: 663 | F11: 663 | G11: 1300060327224 | H11: Toyota | J11: 1880.85 | K11: 5.56 | L11: 5.56 | M11: 0 | N11: 949.83 | O11: 0.05 | P11: 0.05
A12: 01/04/2019 | B12: 898 | C12: 898 | D12: 1300051694552 | E12: 698 | F12: 698 | G12: 1300051694827 | H12: PG Winnington | I12: 0 | J12: 594.99 | K12: 2.17 | L12: 3.4 | M12: -1.745 | N12: 3545.62 | O12: 0.05 | P12: 0.05
A13: 01/04/2019 | B13: 806 | C13: 806 | D13: 1300051060972 | E13: 606 | F13: 606 | G13: 1300051060981 | H13: Bridgewater Paper | I13: 0 | J13: 54.88 | K13: 3.14 | L13: 3.14 | M13: -0.117 | N13: 4134.92 | O13: 0.05 | P13: 0.05
A14: 01/04/2019 | B14: 312 | C14: 312 | D14: 1300060736891 | H14: Alpoco Orthios Eco Park | I14: 0.232 | J14: 210.49 | K14: 3.58 | L14: 3.58
A15: 01/04/2019 | B15: 336 | C15: 336 | D15: 1300060254338 | H15: Altcar Rifle Range Estate | I15: 0 | J15: 1001.98 | K15: 3.58 | L15: 3.58
A20: =[1]Overview!B4& " - Effective from "&[1]Overview!D4&" - "&[1]Overview!E4&" new designated EHV line loss factors" -> SP Manweb - Effective from 1 April 2019 - Final new designated EHV line loss factors
A21: Effective from date | B21: Import Unique Identifier | C21: LLFC | D21: Import MPANs/MSIDs | E21: Export Unique Identifier | F21: LLFC | G21: Export MPANs/MSIDs | H21: Name | I21: Import LLF period 1 | J21: Import LLF period 2 | K21: Import LLF period 3 | L21: Import LLF period 4 | M21: Import LLF period 5 | N21: Export LLF period 1 | O21: Export LLF period 2 | P21: Export LLF period 3 | Q21: Export LLF period 4 | R21: Export LLF period 5
A22: 01/04/2019 | B22: 895 | C22: 895 | D22: 1300060785462 | E22: 696 | F22: 696 | G22: 1300060785453 | H22: Brenig Wind Farm | I22: 1.016 | J22: 1.018 | K22: 1.02 | L22: 1.022 | N22: 1.012 | O22: 1.012 | P22: 1.013 | Q22: 1.014
A23: 01/04/2019 | B23: 911 | C23: 911 | D23: 1300060805612 | E23: 623 | F23: 623 | G23: 1300060805621 | H23: Griffiths Road STOR | I23: 1.016 | J23: 1.018 | K23: 1.02 | L23: 1.022 | N23: 1.012 | O23: 1.012 | P23: 1.013 | Q23: 1.014
A24: 01/04/2019 | B24: 912 | C24: 912 | D24: 1300060805560 | E24: 624 | F24: 624 | G24: 1300060805570 | H24: Warrington Pwr Slutcher | I24: 1.016 | J24: 1.018 | K24: 1.02 | L24: 1.022 | N24: 1.012 | O24: 1.012 | P24: 1.013 | Q24: 1.014
A25: 01/04/2019 | B25: 914 | C25: 914 | D25: 1300060818597 | E25: 626 | F25: 626 | G25: 1300060818602 | H25: Latchford Lane STOR | I25: 1.016 | J25: 1.018 | K25: 1.02 | L25: 1.022 | N25: 1.012 | O25: 1.012 | P25: 1.013 | Q25: 1.014
A26: 01/04/2019 | B26: 853 | C26: 853 | E26: 653 | F26: 653 | H26: CEW | I26: 1.016 | J26: 1.018 | K26: 1.02 | L26: 1.022 | N26: 1.012 | O26: 1.012 | P26: 1.013 | Q26: 1.014
A27: 01/04/2019 | B27: 833 | C27: 833 | D27: 1300035361803 | E27: 663 | F27: 663 | G27: 1300060327224 | H27: Toyota | I27: 1.022 | J27: 1.028 | K27: 1.023 | L27: 1.031 | N27: 1.012 | O27: 1.012 | P27: 1.013 | Q27: 1.014
A28: 01/04/2019 | B28: 898 | C28: 898 | D28: 1300051694552 | E28: 698 | F28: 698 | G28: 1300051694827 | H28: PG Winnington | I28: 1.038 | J28: 1.047 | K28: 1.043 | L28: 1.052 | N28: 1.015 | O28: 1.021 | P28: 1.017 | Q28: 1.022
A29: 01/04/2019 | B29: 806 | C29: 806 | D29: 1300051060972 | E29: 606 | F29: 606 | G29: 1300051060981 | H29: Bridgewater Paper | I29: 1.03 | J29: 1.034 | K29: 1.034 | L29: 1.038 | N29: 1.001 | O29: 1.003 | P29: 1.002 | Q29: 1.003
A30: 01/04/2019 | B30: 312 | C30: 312 | D30: 1300060736891 | H30: Alpoco Orthios Eco Park | I30: 1.024 | J30: 1.026 | K30: 1.029 | L30: 1.031
A31: 01/04/2019 | B31: 336 | C31: 336 | D31: 1300060254338 | H31: Altcar Rifle Range Estate | I31: 1.024 | J31: 1.026 | K31: 1.029 | L31: 1.031

Sheet Nodal prices
A1: Back to Overview
A2: =Overview!B4& " - Effective from "&Overview!D4&" - "&Overview!E4&" Nodal/Zonal charges" -> SP Manweb - Effective from 1 April 2019 - Final Nodal/Zonal charges
A3: Node/Zone ID | B3: Geographical name | C3: Local charge 1 £/kVA | D3: Remote charge 1 £/kVA
A4: ABER RHYD 132KV | B4: 1
A5: BIRKENHEAD 132KV | B5: 1
A6: CARRINGTON 132KV | B6: 1 | D6: 4.5022747
A7: CONNAHS QUAY PENTIR 132KV | B7: 1 | D7: 0
A8: CREWE 132KV | B8: 1 | D8: 0
A9: FRODSHAM 132KV | B9: 1 | D9: 0
A10: KIRKBY 132KV | B10: 1 | D10: 0
A11: LEGACY 132KV | B11: 1 | D11: 0
A12: LISTER DRIVE 132KV | B12: 1 | D12: 0
A13: RAINHILL 132KV | B13: 1 | D13: 0.73877517
A14: TRAWSFYNYDD 132KV | B14: 1 | D14: 0
A15: WYLFA 132KV | B15: 1 | D15: 0
A16: CONNAHS QUAY (SHOTTON) 132KV | B16: 1 | D16: 0
A17: CAPENHURST and INCE 132KV | B17: 1 | D17: 0.6770084
A18: Aberystwyth - Rhydlydan | B18: 2 | C18: ABER RHYD 132KV | D18: 1.9506434
A19: Bromborough - Rock Ferry | B19: 2 | C19: BIRKENHEAD 132KV | D19: 2.101277
A20: Heswall - Hoylake - Prenton | B20: 2 | C20: BIRKENHEAD 132KV | D20: 0
A21: Prenton - Rock Ferry | B21: 2 | C21: BIRKENHEAD 132KV | D21: 2.4654689
A22: Wallasey - Woodside | B22: 2 | C22: BIRKENHEAD 132KV | D22: 0
A23: Dallam - Sankey Bridges - Warrington | B23: 2 | C23: CARRINGTON 132KV | D23: 2.7493617
A24: Elworth - Hartford - Knutsford - Lostock - Winsford | B24: 2 | C24: CARRINGTON 132KV | D24: 1.4831508
A25: Ineos Chlor Ltd (Lostock) | B25: 2 | C25: CARRINGTON 132KV | D25: 0
A26: Bangor - Caernarvon | B26: 2 | C26: CONNAHS QUAY PENTIR 132KV | D26: 0
A27: Brymbo - Hawarden - Holywell | B27: 2 | C27: CONNAHS QUAY PENTIR 132KV | D27: 4.8970879
A28: Castle Cement - Hawarden - Saltney | B28: 2 | C28: CONNAHS QUAY PENTIR 132KV | D28: 0.40770407
A29: Colwyn Bay - Dolgarrog | B29: 2 | C29: CONNAHS QUAY PENTIR 132KV | D29: 0.79040212
... A182: CORWEN T1 | B182: 3 | C182: Four Crosses - Maentwrog | D182: 0
A183: COUNTESS PK T1 | B183: 3 | D183: 0
A184: CREWE T1 / LEIGHTON HOSPITAL T1 | B184: 3 | C184: Crewe - Radway Green - Whitchurch | D184: 1.340592
A185: CRIGGION RADIO STATION T1 | B185: 3 | C185: Legacy - Newtown - Oswestry - Welshpool - Whitchurch | D185: 0
A186: CROSSFIELDS T1 / CROSSFIELDS T2 / LEVERS CROSSFIELDS T3 / GATEWARTH SEWAGE T1 | B186: 3 | C186: Dallam - Sankey Bridges - Warrington | D186: 0
A187: CROWTON T1 | B187: 3 | C187: Ellesmere Port - Ince | D187: 0
A188: CWM DYLI T1 | B188: 3 | C188: Four Crosses - Maentwrog | D188: 0
A189: DAILY POST & ECHO T1 / DAILY POST & ECHO T2 | B189: 3 | C189: Burlington St - Lister Dv - Paradise St | D189: 0
A190: DARESBURY NPL T1 / DARESBURY PK T1 | B190: 3 | C190: Dutton - Moore - Percival Lane | D190: 0
A191: DAVY WAY T1 / LLAY T1 | B191: 3 | C191: Brymbo T1C - Marchwiel - Wrexham | D191: 0
A192: DEESIDE ALUMINIUM T1 / DUNLOP PLASTICS T1 / FIRESTONE T1 / TETRAPAK T1 | B192: 3 | C192: Brymbo T1C - Marchwiel - Wrexham | D192: 0
A193: DEESIDE IND PK T1 / DEESIDE IND PK 6TH AVE T1 / RAF SEALAND T1 | B193: 3 | C193: Deeside Park - Sixth Avenue | D193: 0
A194: DELAMORE ST T1 / KIRKDALE T1 / WALTON T1 | B194: 3 | C194: Bootle - Lister Dv - Burlington St | D194: 0
A195: DENBIGH T1 | B195: 3 | C195: Holywell - Rhyl - St Asaph | D195: 0
... A428: Canada Dock | B428: 3 | C428: Bootle - Lister Dv - Burlington St | D428: 0

Sheet SSC TPR unit rate lookup
A1: Back to Overview
A28: Standard Settlement Configuration Id | B28: Time Pattern Regime Id | C28: Standard Settlement Configuration Desc | D28: Common Decode | G28: Change implemented | H28: Date | I28: Comments
A29: 3 | B29: 166 | C29: 10-hour OP | D29: O | H29: 40057 | I29: First published spreadsheet
A30: 4 | B30: 168 | C30: 10-hour OP | D30: O | G30: SSC 0330 charge rates corrected | H30: 40275 | I30: Previous Off-peak rate corrected to charge 2
A31: 5 | B31: 100 | C31: 10-hour OP + w/e | D31: O | G31: SSC 0250 charge rate corrected | H31: 40347 | I31: Previous rate 1 corrected to Off Peak O
A32: 6 | B32: 257 | C32: 10.5-hour OP | D32: O | G32: SSC 0134 charge rate corrected | H32: 41166 | I32: TPR 00101 corrected from Off Peak O to Rate 1
A33: 7 | B33: 158 | C33: 10.5-hour OP | D33: O | G33: New SSCs added | H33: 41178 | I33: New SSCs from 0953 added.
A34: 8 | B34: 159 | C34: 10.5-hour OP | D34: O | G34: SSC 0394 charge rate corrected | H34: 41758 | I34: TPR 01177 corrected to rate 2
A35: 9 | B35: 1111 | C35: 10.5-hour OP | D35: O | G35: Table reviewed and updated | H35: 41758 | I35: New SSCs from 0949 to 0952, 0975 & 0976 and 0982 & 0983 added.
A36: 10 | B36: 1104 | C36: 10.5-hour OP | D36: O | G36: Table reviewed and updated | H36: 41944 | I36: New SSCs from 0984 and 0985 added.
A37: 11 | B37: 1112 | C37: 10.5-hour OP | D37: O | G37: SSC 0313 charge code corrected | H37: 42081 | I37: TPR 01006 corrected to code O
A38: 12 | B38: 1116 | C38: 10.5-hour OP | D38: O | G38: SSC 0320 charge code corrected | H38: 42081 | I38: TPR 00072 corrected to code 2
A39: 13 | B39: 139 | C39: 11 Hour OP | D39: EMEB or MIDE only | G39: SSC 0781 charge code corrected | H39: 42081 | I39: TPR 00327 corrected to code O
A40: 15 | B40: 152 | C40: 11 Hour OP | D40: EMEB or MIDE only | G40: SSC 0935 charge code corrected | H40: 42081 | I40: TPR 00375 corrected to code 1 or Unsupported (SWAE and SWEB)
A41: 16 | B41: 113 | C41: 11.5-hour OP | D41: Unsupported (SWEB) | G41: SSC 0953 charge code corrected | H41: 42081 | I41: TPR 00424 corrected to code 1 or Unsupported (SWAE and SWEB)
... A74: 50 | B74: 14 | C74: 12-hour OP + w/e & Summer | D74: O | G74: SSC 0942 charge code corrected | H74: 42166 | I74: TPR 00400 corrected to code 1
A75: 51 | B75: 112 | C75: 12-hour night | D75: 1 | G75: SSC 0943 charge code corrected | H75: 42166 | I75: TPR 00404 corrected to code 1
A76: 51 | B76: 120 | C76: 12-hour night | D76: 2 | G76: SSC 0944 charge code corrected | H76: 42166 | I76: TPR 00406 corrected to code 1
A77: 52 | B77: 114 | C77: 12-hour OP | D77: EMEB or MIDE only | G77: SSC 0945 charge code corrected | H77: 42166 | I77: TPR 00408 corrected to code 1
A78: 53 | B78: 115 | C78: 12-hour OP | D78: EMEB or MIDE only | G78: SSC 0946 charge code corrected | H78: 42166 | I78: TPR 00410 corrected to code 1
A79: 55 | B79: 117 | C79: 12-hour OP | D79: EMEB or MIDE only | G79: SSC 0954 charge code corrected | H79: 42166 | I79: TPR 00426 corrected to code 1
A80: 56 | B80: 118 | C80: 12-hour OP | D80: EMEB or MIDE only | G80: SSC 0967 charge code corrected | H80: 42166 | I80: TPR 00442 corrected to code 1
A81: 57 | B81: 119 | C81: 12-hour OP | D81: O | G81: SSC 0970 charge code corrected | H81: 42166 | I81: TPR 00447 corrected to code 2
A82: 58 | B82: 21 | C82: Key Meter pseudo 2-rate | D82: 1 | G82: SSC 0970 charge code corrected | H82: 42166 | I82: TPR 00448 corrected to code 1
A83: 58 | B83: 175 | C83: Key Meter pseudo 2-rate | D83: 1 | G83: SSC 0971 charge code corrected | H83: 42166 | I83: TPR 00493 corrected to code 1
A84: 59 | B84: 121 | C84: 12-hour OP | D84: EMEB or MIDE only
A85: 60 | B85: 122 | C85: 12-hour OP | D85: O
A86: 62 | B86: 1119 | C86: 8-hour OP (see also SSC 427) | D86: 2 or Unsupported (SWEB)
A87: 63 | B87: 172 | C87: 9-hour OP | D87: EMEB or MIDE only
A88: 64 | B88: 1105 | C88: 12-hour OP | D88: O
A89: 65 | B89: 10 | C89: 12-hour OP + Summer | D89: O
A90: 66 | B90: 1106 | C90: 12-hour OP + Summer | D90: O
A91: 67 | B91: 102 | C91: 12.5-hour OP | D91: Unsupported (SWEB)
A92: 71 | B92: 109 | C92: 12.5-hour OP | D92: O
A93: 72 | B93: 111 | C93: 12.5-hour OP | D93: O
A94: 73 | B94: 156 | C94: 12.5-hour OP | D94: Unsupported (SWEB)
A95: 74 | B95: 17 | C95: 12.5-hour OP + Summer | D95: O
... A99: 78 | B99: 13 | C99: 12.5-hour OP + w/e & Summer | D99: O
A100: 79 | B100: 97 | C100: 14-hour E7 | D100: 2
A101: 79 | B101: 164 | C101: 14-hour E7 | D101: 1
A102: 80 | B102: 96 | C102: 14-hour Off Peak | D102: O
A103: 81 | B103: 60 | C103: 14-hour OP + Sun | D103: O
A104: 82 | B104: 83 | C104: 14.5-hour OP | D104: O
A105: 83 | B105: 84 | C105: 14.5-hour OP | D105: O
A106: 84 | B106: 85 | C106: 14.5-hour OP | D106: O
A107: 85 | B107: 86 | C107: 14.5-hour OP | D107: O
A108: 86 | B108: 1107 | C108: 14.5-hour OP | D108: O
A109: 87 | B109: 1109 | C109: 14.5-hour OP | D109: O
A110: 88 | B110: 1113 | C110: 14.5-hour OP | D110: O
A111: 91 | B111: 3 | C111: 14.5-hour OP + Summer | D111: O
A112: 92 | B112: 4 | C112: 14.5-hour OP + Summer | D112: O
A113: 93 | B113: 30 | C113: split 7-hour E7 | D113: 1
A114: 93 | B114: 214 | C114: split 7-hour E7 | D114: 2
A115: 94 | B115: 1108 | C115: 14.5-hour OP + Summer | D115: O
A116: 95 | B116: 1110 | C116: 14.5-hour OP + Summer | D116: O
A117: 96 | B117: 1114 | C117: 14.5-hour OP + Summer | D117: O
A118: 97 | B118: 54 | C118: 14.5-hour OP + w/e | D118: O
A119: 98 | B119: 12 | C119: 14.5-hour OP + w/e & Summer | D119: O
A120: 99 | B120: 75 | C120: 15-hour OP | D120: EMEB or MIDE only
A121: 100 | B121: 76 | C121: 15-hour OP | D121: EMEB or MIDE only
A122: 101 | B122: 7 | C122: 15-hour OP + w/e & Summer | D122: O
A123: 102 | B123: 8 | C123: 15-hour OP + w/e & Summer | D123: O
A124: 103 | B124: 9 | C124: 15-hour OP + w/e & Summer | D124: O
A125: 104 | B125: 61 | C125: 15.5-hour OP | D125: Unsupported (SWEB)
A126: 105 | B126: 65 | C126: 15.5-hour OP | D126: O
... A140: 120 | B140: 11 | C140: 9-hour OP | D140: O
A141: 121 | B141: 26 | C141: 2-rate terms | D141: 2
A142: 121 | B142: 224 | C142: 2-rate terms | D142: 1
A143: 122 | B143: 201 | C143: 2-rate SToD | D143: 1
A144: 122 | B144: 245 | C144: 2-rate SToD | D144: 2
A145: 123 | B145: 1307 | C145: 2-rate variable SToD | D145: 1
A146: 124 | B146: 1319 | C146: 2-rate variable SToD | D146: 1
A147: 125 | B147: 1315 | C147: 2-rate variable SToD | D147: 1
A148: 126 | B148: 1193 | C148: 7-hour E7 | D148: 1
A149: 126 | B149: 1194 | C149: 7-hour E7 | D149: 2
A150: 127 | B150: 80 | C150: 3-rate SToD | D150: Unsupported (SWEB)
A151: 127 | B151: 148 | C151: 3-rate SToD | D151: 1
A152: 127 | B152: 221 | C152: 3-rate SToD | D152: 2 or Unsupported (SWEB)
A153: 128 | B153: 1120 | C153: Dom/Non-dom Seasonal (link SSC 0342) | D153: 1
A154: 128 | B154: 1121 | C154: Dom/Non-dom Seasonal (link SSC 0342) | D154: 1
A155: 128 | B155: 1122 | C155: Dom/Non-dom Seasonal (link SSC 0342) | D155: 2
A156: 129 | B156: 169 | C156: 3-rate SToD | D156: 1
A157: 129 | B157: 202 | C157: 3-rate SToD | D157: 1
A158: 129 | B158: 222 | C158: 3-rate SToD | D158: 2
A159: 130 | B159: 1308 | C159: 3-rate variable | D159: 1
A160: 130 | B160: 1309 | C160: 3-rate variable | D160: 1
A161: 130 | B161: 1310 | C161: 3-rate variable | D161: 2
A162: 131 | B162: 1311 | C162: 3-rate variable | D162: 1
A163: 131 | B163: 1312 | C163: 3-rate variable | D163: 1
A164: 131 | B164: 1313 | C164: 3-rate variable | D164: 2
A165: 132 | B165: 92 | C165: 4-rate SToD | D165: EMEB or MIDE only
A166: 132 | B166: 210 | C166: 4-rate SToD | D166: 2
A167: 132 | B167: 234 | C167: 4-rate SToD | D167: EMEB or MIDE only
A168: 132 | B168: 236 | C168: 4-rate SToD | D168: EMEB or MIDE only
A169: 133 | B169: 92 | C169: 4-rate SToD | D169: 1
A170: 133 | B170: 210 | C170: 4-rate SToD | D170: 2
A171: 133 | B171: 233 | C171: 4-rate SToD | D171: 1
A172: 133 | B172: 246 | C172: 4-rate SToD | D172: 1
A173: 134 | B173: 101 | C173: 4-rate SToD | D173: 1
A174: 134 | B174: 210 | C174: 4-rate SToD | D174: 2
...

Sheet Charge Calculator
B1: Back to Overview
B2: =Overview!B4& " - Effective from "&Overview!D4&" - "&Overview!E4 -> SP Manweb - Effective from 1 April 2019 - Final
B4: LV and HV tariff calculator | L4: EHV site calculator
B5: Step 1, Choose your tariff using the drop down list in cell B10 | L5: Step 1, Choose your tariff using the drop down list in cell L10
B6: Step 2, After selecting a tariff in step 1, Cells C12-I12 will generate headings, please enter your consumption in cells C13:I13 underneath each heading generated (if no heading leave cell blank) | L6: Step 2, After selecting a tariff in step 1, Cells M12-T12 will generate headings, please enter your consumption in cells M13:T13 underneath each heading generated (if no heading leave cell blank)
B7: Step 3, Enter a forecast of consumption if required in cells C14:I14 | L7: Step 3, Enter a forecast of consumption if required in cells M14:T14
B9: Tariff details Choose tariff name from drop down box below | C9: ='Annex 1 LV and HV charges'!D13 -> Unit charge 1 (NHH) or red/black charge (HH) p/kWh | D9: ='Annex 1 LV and HV charges'!E13 -> Unit charge 2 (NHH) or amber/yellow charge (HH) p/kWh | E9: ='Annex 1 LV and HV charges'!F13 -> Green charge(HH) p/kWh | F9: ='Annex 1 LV and HV charges'!G13 -> Fixed charge p/MPAN/day | G9: ='Annex 1 LV and HV charges'!H13 -> Capacity charge p/kVA/day | H9: ='Annex 1 LV and HV charges'!I13 -> Exceeded capacity charge p/kVA/day | I9: ='Annex 1 LV and HV charges'!J13 -> Reactive power charge p/kVArh | L9: Site details Choose the site name from the drop down box below | M9: ='Annex 2 EHV charges'!H10 -> Import Super Red unit charge (p/kWh) | N9: ='Annex 2 EHV charges'!I10 -> Import fixed charge (p/day) | O9: ='Annex 2 EHV charges'!J10 -> Import capacity charge (p/kVA/day) | P9: ='Annex 2 EHV charges'!K10 -> Import exceeded capacity charge (p/kVA/day) | Q9: ='Annex 2 EHV charges'!L10 -> Export Super Red unit charge (p/kWh) | R9: ='Annex 2 EHV charges'!M10 -> Export fixed charge (p/day) | S9: ='Annex 2 EHV charges'!N10 -> Export capacity charge (p/kVA/day) | T9: ='Annex 2 EHV charges'!O10 -> Export exceeded capacity charge (p/kVA/day)
C10: =IFERROR(VLOOKUP($B$10,'Annex 1 LV and HV charges'!$A:$K,4,FALSE),"") | D10: =IFERROR(VLOOKUP($B$10,'Annex 1 LV and HV charges'!$A:$K,5,FALSE),"") | E10: =IFERROR(VLOOKUP($B$10,'Annex 1 LV and HV charges'!$A:$K,6,FALSE),"") | F10: =IFERROR(VLOOKUP($B$10,'Annex 1 LV and HV charges'!$A:$K,7,FALSE),"") | G10: =IFERROR(VLOOKUP($B$10,'Annex 1 LV and HV charges'!$A:$K,8,FALSE),"") | H10: =IFERROR(VLOOKUP($B$10,'Annex 1 LV and HV charges'!$A:$K,9,FALSE),"") | I10: =IFERROR(VLOOKUP($B$10,'Annex 1 LV and HV charges'!$A:$K,10,FALSE),"") | M10: =IFERROR(VLOOKUP($L$10,'Annex 2 EHV charges'!$G:$O,2,FALSE),"") | N10: =IFERROR(VLOOKUP($L$10,'Annex 2 EHV charges'!$G:$O,3,FALSE),"") | O10: =IFERROR(VLOOKUP($L$10,'Annex 2 EHV charges'!$G:$O,4,FALSE),"") | P10: =IFERROR(VLOOKUP($L$10,'Annex 2 EHV charges'!$G:$O,5,FALSE),"") | Q10: =IFERROR(VLOOKUP($L$10,'Annex 2 EHV charges'!$G:$O,6,FALSE),"") | R10: =IFERROR(VLOOKUP($L$10,'Annex 2 EHV charges'!$G:$O,7,FALSE),"") | S10: =IFERROR(VLOOKUP($L$10,'Annex 2 EHV charges'!$G:$O,8,FALSE),"") | T10: =IFERROR(VLOOKUP($L$10,'Annex 2 EHV charges'!$G:$O,9,FALSE),"")
B12: Tariff components | C12: Unit 1 kWh (red/black/day) | D12: Unit 2 kWh (amber/yellow /night) | E12: Unit 3 kWh (green) | F12: Number of days in consumption period i.e. 365 if one year | G12: Maximum import or export capacity kVA | H12: Average daily exceeded capacity kVA | I12: Excess reactive units kVArh | L12: Tariff components | M12: Import super red kWh | N12: Number of days in consumption period i.e. 365 if one year | O12: Maximum import capacity kVA | P12: Average daily exceeded capacity kVA | Q12: Export Super Red kWh | R12: Number of days in consumption period i.e. 365 if one year | S12: Maximum export capacity kVA | T12: Average daily exceeded capacity kVA
B13: Enter current consumption details | L13: Enter current consumption details | R13: =N13 -> 0
B14: Enter forecast consumption details (if different) | C14: =C13 -> 0 | D14: =D13 -> 0 | E14: =E13 -> 0 | F14: =F13 -> 0 | G14: =G13 -> 0 | H14: =H13 -> 0 | I14: =I13 -> 0 | L14: Enter forecast consumption details (if different) | M14: =M13 -> 0 | N14: =N13 -> 0 | O14: =O13 -> 0 | P14: =P13 -> 0 | Q14: =Q13 -> 0 | R14: =R13 -> 0 | S14: =S13 -> 0 | T14: =T13 -> 0
B16: Charge components | C16: Unit 1 £ | D16: Unit 2 £ | E16: Unit 3 £ | F16: Fixed charge £ | G16: Capacity charge £ | H16: Exceeded capacity charge £ | I16: Reactive power charge £ | L16: Charge components | M16: Import super red charge £ | N16: Import fixed charge £ | O16: Import capacity charge £ | P16: Import exceeded capacity charge £ | Q16: Export super red charge £ | R16: Export fixed charge £ | S16: Export capacity charge £ | T16: Export exceeded capacity charge £
B17: Current consumption period charges | C17: =IFERROR(C10*C13/100,"") | D17: =IFERROR(D10*D13/100,"") | E17: =IFERROR(E10*E13/100,"") | F17: =IFERROR(F10*F13/100,"") | G17: =IFERROR(G10*G13*F13/100,"") | H17: =IFERROR(H10*H13*F13/100,"") | I17: =IFERROR(I10*I13/100,"") | L17: Current consumption period charges | M17: =IFERROR(M10*M13/100,"") | N17: =IFERROR(N10*N13/100,"") | O17: =IFERROR(O10*O13*N13/100,"") | P17: =IFERROR(P10*P13*N13/100,"") | Q17: =IFERROR(Q10*Q13/100,"") | R17: =IFERROR(R10*R13/100,"") | S17: =IFERROR(S10*S13*R13/100,"") | T17: =IFERROR(T10*T13*R13/100,"")
B18: Forecast consumption period charges | C18: =IFERROR(C10*C14/100,"") | D18: =IFERROR(D10*D14/100,"") | E18: =IFERROR(E10*E14/100,"") | F18: =IFERROR(F10*F14/100,"") | G18: =IFERROR(G10*G14*F14/100,"") | H18: =IFERROR(H10*H14*F14/100,"") | I18: =IFERROR(I10*I14/100,"") | L18: Forecast consumption period charges | M18: =IFERROR(M10*M14/100,"") | N18: =IFERROR(N10*N14/100,"") | O18: =IFERROR(O10*O14*N14/100,"") | P18: =IFERROR(P10*P14*N14/100,"") | Q18: =IFERROR(Q10*Q14/100,"") | R18: =IFERROR(R10*R14/100,"") | S18: =IFERROR(S10*S14*R14/100,"") | T18: =IFERROR(T10*T14*R14/100,"")
C20: Total charge £ | M20: Import total charge £ | N20: Export total charge £
B21: Current consumption period charges | C21: =SUM(C17:I17) -> 0 | L21: Current consumption period charges | M21: =SUM(M17:P17) -> 0 | N21: =SUM(Q17:T17) -> 0
B22: Forecast consumption period charges | C22: =SUM(C18:I18) -> 0 | L22: Forecast consumption period charges | M22: =SUM(M18:P18) -> 0 | N22: =SUM(Q18:T18) -> 0
B24: These charges are estimates based on tariff selected and consumption values entered. | L24: These charges are estimates based on site selected and consumption values entered.
