Workbook
Name OLE_LINK1: 'Annex 3 Preserved charges'!#REF!

Sheet Overview
A2: Company and Licence name, charging year, effective from, status
B3: Company and Licence name | C3: Year | D3: Effective From | E3: Status
A4: Company and Licence name, charging year, effective from, status | B4: Northern Powergrid (Northeast) Ltd | C4: 2019/20 | D4: 1 April 2019 | E4: Final
A6: List of data tables in this workbook
A7: Worksheet | B7: Information
A8: Annex 1 LV and HV charges | B8: Annex 1 contains the charges to LV and HV Designated Properties.
A9: Annex 2 EHV charges | B9: ="Annex 2 contains the charges to Designated EHV Properties and charges applied to LDNOs with Designated EHV Properties/end-users embedded in networks within the " &B4 &" Licence area." -> Annex 2 contains the charges to Designated EHV Properties and charges applied to LDNOs with Designated EHV Properties/end-users embedded in networks within the Northern Powergrid (Northeast) Ltd Licence area.
A10: Annex 3 Preserved charges | B10: Annex 3 contains details of any preserved and additional charges that are valid at this time.
A11: Annex 4 LDNO charges | B11: ="Annex 4 contains charges that are levied on the owner of an embedded network within the "&B4&" Licence area. "&"Electricity suppliers and consumers who have properties connected to an embedded network should contact the embedded network owner to determine their distribution charges."&" The charges listed in this table are not payable by domestic consumers, business consumers or electricity suppliers." -> Annex 4 contains charges that are levied on the owner of an embedded network within the Northern Powergrid (Northeast) Ltd Licence area. Electricity suppliers and consumers who have properties connected to an embedded network should contact the embedded network owner to determine their distribution charges. The charges listed in this table are not payable by domestic consumers, business consumers or electricity suppliers.
A12: Annex 5 LLFs | B12: Annex 5 has been intentionally left blank as this charging statement is published a complete year before the LLFs have been audited. The line loss factors that are approved by the BSC Panel for the applicable year and consequently published on the Elexon website will take precedence and be used in Settlement. This annex will be re-published with these values once they are available.
A13: Annex 6 Charges for New or Amended Designated EHV Properties | B13: ="Annex 6 contains the charges for new or amended Designated EHV Properties and charges applied to LDNOs with new or amended Designated EHV Properties/end-users embedded in networks within the " &B4 &" Licence area." -> Annex 6 contains the charges for new or amended Designated EHV Properties and charges applied to LDNOs with new or amended Designated EHV Properties/end-users embedded in networks within the Northern Powergrid (Northeast) Ltd Licence area.
A14: Nodal prices | B14: Contains the underlying nodal costs used to calculate the current EDCM charges.
A15: SSC TPR to unit rate lookup table | B15: The time periods for the non half hourly metered charge rates in Annex 1 are as specified by the SSC. To determine the appropriate charge rate for each SSC/TPR a lookup table is provided.
A16: Charge calculator | B16: Charge calculator is a tool to help you estimate your distribution charges using current consumption data and forecast consumption data.
A18: Notes to users of this spreadsheet
A20: Please use this spreadsheet with reference to the LC14 use of system charging statement.
A22: Notes to DNOs populating this spreadsheet
A24: DNOs must endeavour to maintain consistency in the structure of this spreadsheet. Any changes to the structure must be noted in the 'Notes to users of this spreadsheet'
A25: The drop down list on the charge calculator can be expanded by unprotecting the charge calculator sheet and selecting 'data', 'data validation...' and then expanding the 'source' data range. The sheet can then be protected.

Sheet Annex 1 LV and HV charges
A1: Back to Overview | E1: Note: Where a tariff only has a p/kWh unit rate in Unit Charge 1 then this unit rate applies at all times.
A2: =Overview!B4& " - Effective from "&Overview!D4&" - "&Overview!E4&" LV and HV charges" -> Northern Powergrid (Northeast) Ltd - Effective from 1 April 2019 - Final LV and HV charges
A4: Time Bands for Half Hourly Metered Properties | G4: Time Bands for Half Hourly Unmetered Properties
A5: Time periods | B5: Red Time Band | C5: Amber Time Band | E5: Green Time Band | I5: Black Time Band | J5: Yellow Time Band | K5: Green Time Band
A6: Monday to Friday (Including Bank Holidays) All Year | B6: 16:00 to 19:30 | C6: 08:00 to 16:00 19:30 to 22:00 | E6: 00:00 to 08:00 22:00 to 24:00 | G6: Monday to Friday (Including Bank Holidays) November to February Inclusive | I6: 16:00 to 19:30 | J6: 08:00 to 16:00 19:30 to 22:00 | K6: 00:00 to 08:00 22:00 to 24:00
A7: Saturday and Sunday All Year | E7: 00:00 to 24:00 | G7: Monday to Friday (Including Bank Holidays) April to October Inclusive and March | J7: 08:00 to 22:00 | K7: 00:00 to 08:00 22:00 to 24:00
A8: Notes | B8: All the above times are in UK Clock time | G8: Saturday and Sunday All year | K8: 00:00 to 24:00
G9: Notes | I9: All the above times are in UK Clock time
A11: Tariff name | B11: Open LLFCs | C11: PCs | D11: Unit charge 1 (NHH) or red/black charge (HH) p/kWh | E11: Unit charge 2 (NHH) or amber/yellow charge (HH) p/kWh | F11: Green charge(HH) p/kWh | G11: Fixed charge p/MPAN/day | H11: Capacity charge p/kVA/day | I11: Exceeded capacity charge p/kVA/day | J11: Reactive power charge p/kVArh | K11: Closed LLFCs
A12: Domestic Unrestricted * | B12: 1 | C12: 1 | D12: 2.355 | E12: 0 | F12: 0 | G12: 5.57 | H12: 0 | I12: 0 | J12: 0 | K12: 998, 999
A13: Domestic Two Rate * | B13: 2 | C13: 2 | D13: 2.674 | E13: 1.131 | F13: 0 | G13: 5.57 | H13: 0 | I13: 0 | J13: 0 | K13: 0
A14: Domestic Off Peak (related MPAN) | B14: 12 | C14: 2 | D14: 1.25 | E14: 0 | F14: 0 | G14: 0 | H14: 0 | I14: 0 | J14: 0 | K14: 0
A15: Small Non Domestic Unrestricted | B15: 203 | C15: 3 | D15: 2.379 | E15: 0 | F15: 0 | G15: 5.84 | H15: 0 | I15: 0 | J15: 0 | K15: 0
A16: Small Non Domestic Two Rate | B16: 204 | C16: 4 | D16: 2.6 | E16: 1.166 | F16: 0 | G16: 5.84 | H16: 0 | I16: 0 | J16: 0 | K16: 0
A17: Small Non Domestic Off Peak (related MPAN) | B17: 205 | C17: 4 | D17: 1.311 | E17: 0 | F17: 0 | G17: 0 | H17: 0 | I17: 0 | J17: 0 | K17: 0
A18: LV Medium Non-Domestic | B18: 257 | C18: 5-8 | D18: 2.29 | E18: 1.12 | F18: 0 | G18: 30.49 | H18: 0 | I18: 0 | J18: 0 | K18: 0
A19: LV Sub Medium Non-Domestic | B19: 265 | C19: 5-8 | D19: 2.343 | E19: 1.152 | F19: 0 | G19: 30.5 | H19: 0 | I19: 0 | J19: 0 | K19: 0
A20: HV Medium Non-Domestic | B20: 304 | C20: 5-8 | D20: 1.653 | E20: 1.103 | F20: 0 | G20: 284.23 | H20: 0 | I20: 0 | J20: 0 | K20: 0
A21: LV Network Domestic * | B21: 249 | C21: 0 | D21: 7.567 | E21: 1.91 | F21: 1.117 | G21: 5.57 | H21: 0 | I21: 0 | J21: 0 | K21: 0
A22: LV Network Non-Domestic Non-CT | B22: 278 | C22: 0 | D22: 7.934 | E22: 1.958 | F22: 1.12 | G22: 5.84 | H22: 0 | I22: 0 | J22: 0 | K22: 0
A23: LV HH Metered | B23: 251 | C23: 0 | D23: 5.589 | E23: 1.641 | F23: 1.099 | G23: 15.9 | H23: 1.77 | I23: 4.14 | J23: 0.166 | K23: 0
A24: LV Sub HH Metered | B24: 293 | C24: 0 | D24: 4.01 | E24: 1.419 | F24: 1.086 | G24: 15.9 | H24: 2.49 | I24: 4.11 | J24: 0.097 | K24: 0
A25: HV HH Metered | B25: 301 | C25: 0 | D25: 3.266 | E25: 1.314 | F25: 1.08 | G25: 151.06 | H25: 2.39 | I25: 4.32 | J25: 0.067 | K25: 0
A26: NHH UMS category A | B26: 506 | C26: 8 | D26: 1.972 | E26: 0 | F26: 0 | G26: 0 | H26: 0 | I26: 0 | J26: 0 | K26: 0
A27: NHH UMS category B | B27: 507 | C27: 1 | D27: 2.283 | E27: 0 | F27: 0 | G27: 0 | H27: 0 | I27: 0 | J27: 0 | K27: 0
A28: NHH UMS category C | B28: 508 | C28: 1 | D28: 3.317 | E28: 0 | F28: 0 | G28: 0 | H28: 0 | I28: 0 | J28: 0 | K28: 0
A29: NHH UMS category D | B29: 509 | C29: 1 | D29: 1.762 | E29: 0 | F29: 0 | G29: 0 | H29: 0 | I29: 0 | J29: 0 | K29: 0
A30: LV UMS (Pseudo HH Metered) | B30: 554 & 555 | C30: 0 | D30: 18.384 | E30: 1.815 | F30: 1.112 | G30: 0 | H30: 0 | I30: 0 | J30: 0 | K30: 0
A31: LV Generation NHH or Aggregate HH | B31: 774 | C31: 8&0 | D31: -0.671 | E31: 0 | F31: 0 | G31: 0 | H31: 0 | I31: 0 | J31: 0 | K31: 0
A32: LV Sub Generation NHH | B32: 776 | C32: 8 | D32: -0.595 | E32: 0 | F32: 0 | G32: 0 | H32: 0 | I32: 0 | J32: 0 | K32: 0
A33: LV Generation Intermittent | B33: 792 | C33: 0 | D33: -0.671 | E33: 0 | F33: 0 | G33: 0 | H33: 0 | I33: 0 | J33: 0.141 | K33: 0
A34: LV Generation Intermittent no RP charge | B34: 392 | C34: 0 | D34: -0.671 | E34: 0 | F34: 0 | G34: 0 | H34: 0 | I34: 0 | J34: 0 | K34: 0
A35: LV Generation Non-Intermittent | B35: 794 | C35: 0 | D35: -4.445 | E35: -0.583 | F35: -0.042 | G35: 0 | H35: 0 | I35: 0 | J35: 0.141 | K35: 0
A36: LV Generation Non-Intermittent no RP charge | B36: 394 | C36: 0 | D36: -4.445 | E36: -0.583 | F36: -0.042 | G36: 0 | H36: 0 | I36: 0 | J36: 0 | K36: 0
A37: LV Sub Generation Intermittent | B37: 793 | C37: 0 | D37: -0.595 | E37: 0 | F37: 0 | G37: 0 | H37: 0 | I37: 0 | J37: 0.134 | K37: 0
A38: LV Sub Generation Intermittent no RP charge | B38: 393 | C38: 0 | D38: -0.595 | E38: 0 | F38: 0 | G38: 0 | H38: 0 | I38: 0 | J38: 0 | K38: 0
A39: LV Sub Generation Non-Intermittent | B39: 795 | C39: 0 | D39: -3.947 | E39: -0.514 | F39: -0.038 | G39: 0 | H39: 0 | I39: 0 | J39: 0.134 | K39: 0
A40: LV Sub Generation Non-Intermittent no RP charge | B40: 395 | C40: 0 | D40: -3.947 | E40: -0.514 | F40: -0.038 | G40: 0 | H40: 0 | I40: 0 | J40: 0 | K40: 0
A41: HV Generation Intermittent | B41: 796 | C41: 0 | D41: -0.379 | E41: 0 | F41: 0 | G41: 84.92 | H41: 0 | I41: 0 | J41: 0.104 | K41: 0
A42: HV Generation Intermittent no RP charge | B42: 396 | C42: 0 | D42: -0.379 | E42: 0 | F42: 0 | G42: 84.92 | H42: 0 | I42: 0 | J42: 0 | K42: 0
A43: HV Generation Non-Intermittent | B43: 798 | C43: 0 | D43: -2.548 | E43: -0.311 | F43: -0.027 | G43: 84.92 | H43: 0 | I43: 0 | J43: 0.104 | K43: 0
A44: HV Generation Non-Intermittent no RP charge | B44: 398 | C44: 0 | D44: -2.548 | E44: -0.311 | F44: -0.027 | G44: 84.92 | H44: 0 | I44: 0 | J44: 0 | K44: 0
A45: *The fixed charges for these tariffs are inclusive of the Ofgem approved adjustment (0.08p/day) to recover Octopus Energy Limited’s last resort supply payment claim: https://www.ofgem.gov.uk/publications-and-updates/decision-grant-all-dnos-derogations-charging-years-201920-and-202021-due-last-resort-supply-payment-claim

Sheet Annex 2 EHV charges
A1: Back to Overview | F1: Note: The list of MPANs / MSIDs provided may be incomplete; the DNO reserves the right to apply the listed charges to any other MPANs / MSIDs associated with the site.
A2: =Overview!B4& " - Effective from "&Overview!D4&" - "&Overview!E4&" EDCM charges" -> Northern Powergrid (Northeast) Ltd - Effective from 1 April 2019 - Final EDCM charges
A4: Time Periods for Designated EHV Properties
A5: Time periods | D5: Super Red Time Band
A6: Monday to Friday (Including Bank Holidays) November to February Inclusive | D6: 1600 - 1930
A7: Notes | D7: All the above times are in UK Clock time
A9: Import Unique Identifier | B9: LLFC | C9: Import MPANs/MSIDs | D9: Export Unique Identifier | E9: LLFC | F9: Export MPANs/MSIDs | G9: Name | H9: Import Super Red unit charge (p/kWh) | I9: Import fixed charge (p/day) | J9: Import capacity charge (p/kVA/day) | K9: Import exceeded capacity charge (p/kVA/day) | L9: Export Super Red unit charge (p/kWh) | M9: Export fixed charge (p/day) | N9: Export capacity charge (p/kVA/day) | O9: Export exceeded capacity charge (p/kVA/day)
A10: 601 | B10: 601 | C10: 1592001005770 1592101005776 | D10: 701 | E10: 701 | F10: 1574000216135 1594001005774 | G10: EHV Site Specific - Generation Exempt (LLFC 601 & 701) | H10: 0 | I10: 715.82 | J10: 0.72 | K10: 0.72 | L10: 0 | M10: 0 | N10: 0 | O10: 0
A11: 603 | B11: 603 | C11: 1592001051182 | E11: 0 | F11: 0 | G11: EHV Site Specific (LLFC 603) | H11: 0 | I11: 8053.96 | J11: 1.92 | K11: 1.92 | L11: 0 | M11: 0 | N11: 0 | O11: 0
A12: 604 | B12: 604 | C12: MSID_7299 | D12: 727 | E12: 727 | F12: MSID_7300 | G12: EHV Site Specific (LLFC 604 & 727) | H12: 0 | I12: 52.97 | J12: 0.77 | K12: 0.77 | L12: 0 | M12: 1059.37 | N12: 0.05 | O12: 0.05
A13: 605 | B13: 605 | C13: 1592001092676 | E13: 0 | F13: 0 | G13: EHV Site Specific (LLFC 605) | H13: 0.372 | I13: 1997.93 | J13: 1.75 | K13: 1.75 | L13: 0 | M13: 0 | N13: 0 | O13: 0
A14: 606 | B14: 606 | C14: 1592001092719 | E14: 0 | F14: 0 | G14: EHV Site Specific (LLFC 606) | H14: 0.408 | I14: 3995.86 | J14: 2 | K14: 2 | L14: 0 | M14: 0 | N14: 0 | O14: 0
A15: 607 | B15: 607 | C15: 1592001092728 | E15: 0 | F15: 0 | G15: EHV Site Specific (LLFC 607) | H15: 1.182 | I15: 3995.86 | J15: 2.91 | K15: 2.91 | L15: 0 | M15: 0 | N15: 0 | O15: 0
A16: 608 | B16: 608 | C16: 1592001092737 | E16: 0 | F16: 0 | G16: EHV Site Specific (LLFC 608) | H16: 0.037 | I16: 3995.86 | J16: 2.7 | K16: 2.7 | L16: 0 | M16: 0 | N16: 0 | O16: 0
A17: 609 | B17: 609 | C17: 1592001046085 | E17: 0 | F17: 0 | G17: EHV Site Specific (LLFC 609) | H17: 0 | I17: 703.73 | J17: 3.05 | K17: 3.05 | L17: 0 | M17: 0 | N17: 0 | O17: 0
A18: 611 | B18: 611 | C18: 1592001111628 | E18: 0 | F18: 0 | G18: EHV Site Specific (LLFC 611) | H18: 0 | I18: 3493.87 | J18: 4.97 | K18: 4.97 | L18: 0 | M18: 0 | N18: 0 | O18: 0
A19: 612 | B19: 612 | C19: 1592001073112 | D19: 704 | E19: 704 | F19: 1594001073116 | G19: EHV Site Specific (LLFC 612 & 704) | H19: 0.448 | I19: 184.47 | J19: 1.18 | K19: 1.18 | L19: -0.565 | M19: 1844.66 | N19: 0.05 | O19: 0.05
A20: 613 | B20: 613 | C20: TBC | E20: 0 | F20: 0 | G20: EHV Site Specific (LLFC 613) | H20: 0.982 | I20: 65.85 | J20: 1.16 | K20: 1.16 | L20: 0 | M20: 0 | N20: 0 | O20: 0
A21: 614 | B21: 614 | C21: 1592001055257 | D21: 709 | E21: 709 | F21: 1594001055250 | G21: EHV Site Specific (LLFC 614 & 709) | H21: 0 | I21: 6364.26 | J21: 0.53 | K21: 0.53 | L21: 0 | M21: 1272.85 | N21: 0.05 | O21: 0.05
A22: 615 & 616 | B22: 615 & 616 | C22: 1592001055239 1592001055248 | E22: 0 | F22: 0 | G22: EHV Site Specific (LLFC 615 & 616) | H22: 0.309 | I22: 3313.77 | J22: 2.63 | K22: 2.63 | L22: 0 | M22: 0 | N22: 0 | O22: 0
A23: 617 | B23: 617 | C23: 1592001110572 | E23: 0 | F23: 0 | G23: EHV Site Specific (LLFC 617) | H23: 0 | I23: 9368.64 | J23: 1.8 | K23: 1.8 | L23: 0 | M23: 0 | N23: 0 | O23: 0
A24: 618 | B24: 618 | C24: 1592001094308 | E24: 0 | F24: 0 | G24: EHV Site Specific (LLFC 618) | H24: 0.239 | I24: 3342.48 | J24: 5.17 | K24: 5.17 | L24: 0 | M24: 0 | N24: 0 | O24: 0
A25: 619 | B25: 619 | C25: 1570000150382 | D25: 710 | E25: 710 | F25: 1594000000038 | G25: EHV Site Specific - Generation Exempt (LLFC 619 & 710) | H25: 0.027 | I25: 24 | J25: 1.33 | K25: 1.33 | L25: 0 | M25: 0 | N25: 0 | O25: 0
A26: 620 | B26: 620 | C26: 1592001007476 | E26: 0 | F26: 0 | G26: EHV Site Specific (LLFC 620) | H26: 0 | I26: 1407.46 | J26: 5.02 | K26: 5.02 | L26: 0 | M26: 0 | N26: 0 | O26: 0
A27: 621 | B27: 621 | C27: 1592001007494 | E27: 0 | F27: 0 | G27: EHV Site Specific (LLFC 621) | H27: 0.091 | I27: 65.85 | J27: 2.21 | K27: 2.21 | L27: 0 | M27: 0 | N27: 0 | O27: 0
A28: 622 | B28: 622 | C28: 1592001036574 | D28: 711 | E28: 711 | F28: 1594001036578 | G28: EHV Site Specific - Generation Exempt (LLFC 622 & 711) | H28: 0.163 | I28: 465.53 | J28: 1.5 | K28: 1.5 | L28: 0 | M28: 0 | N28: 0 | O28: 0
A29: 624 | B29: 624 | C29: 1592001063540 | D29: 804 | E29: 804 | F29: 1574000324772 | G29: EHV Site Specific (LLFC 624 & 804) | H29: 0.009 | I29: 3063.56 | J29: 2.46 | K29: 2.46 | L29: 0 | M29: 958.73 | N29: 0.05 | O29: 0.05
A30: 625 | B30: 625 | C30: 1592001006890 | D30: 748 | E30: 748 | F30: 1594001006893 | G30: EHV Site Specific - Generation Exempt (LLFC 625 & 748) | H30: 1.158 | I30: 25.46 | J30: 2.32 | K30: 2.32 | L30: 0 | M30: 0 | N30: 0 | O30: 0
A31: 627 | B31: 627 | C31: 1570000199077 | D31: 729 | E31: 729 | F31: 1574000199083 | G31: EHV Site Specific - Generation Exempt (LLFC 627 & 729) | H31: 0 | I31: 1104.16 | J31: 1.49 | K31: 1.49 | L31: 0 | M31: 0 | N31: 0 | O31: 0
A32: 626 | B32: 626 | C32: 1592001005637 | E32: 0 | F32: 0 | G32: EHV Site Specific (LLFC 626) | H32: 0.237 | I32: 3132.37 | J32: 3.99 | K32: 3.99 | L32: 0 | M32: 0 | N32: 0 | O32: 0
A33: 628 | B33: 628 | C33: 1592001111405 | E33: 0 | F33: 0 | G33: EHV Site Specific (LLFC 628) | H33: 1.081 | I33: 601.63 | J33: 4.06 | K33: 4.06 | L33: 0 | M33: 0 | N33: 0 | O33: 0
A34: 631 | B34: 631 | C34: 1592001110216 | E34: 0 | F34: 0 | G34: EHV Site Specific (LLFC 631) | H34: 0 | I34: 65.85 | J34: 3.38 | K34: 3.38 | L34: 0 | M34: 0 | N34: 0 | O34: 0
A35: 632 | B35: 632 | C35: 1592001007467 | E35: 0 | F35: 0 | G35: EHV Site Specific (LLFC 632) | H35: 0.286 | I35: 256.45 | J35: 4.18 | K35: 4.18 | L35: 0 | M35: 0 | N35: 0 | O35: 0
A36: 633 | B36: 633 | C36: 1580001273940 1580001273950 | E36: 0 | F36: 0 | G36: EHV Site Specific (LLFC 633) | H36: 0.18 | I36: 3439.26 | J36: 2.71 | K36: 2.71 | L36: 0 | M36: 0 | N36: 0 | O36: 0
A37: 637 | B37: 637 | C37: 1592001141543 | D37: 728 | E37: 728 | F37: 1594001141547 | G37: EHV Site Specific - Generation Exempt (LLFC 637 & 728) | H37: 0.053 | I37: 1299.31 | J37: 1.52 | K37: 1.52 | L37: 0 | M37: 0 | N37: 0 | O37: 0
A38: 680 | B38: 680 | C38: 1580000675845 | D38: 759 | E38: 759 | F38: 1574000275033 | G38: EHV Site Specific (LLFC 680 & 759) | H38: 0.25 | I38: 2.96 | J38: 1.17 | K38: 1.17 | L38: 0 | M38: 125.26 | N38: 0.05 | O38: 0.05
A39: 681 | B39: 681 | C39: 1580000872387 | D39: 760 | E39: 760 | F39: 1574000283735 | G39: EHV Site Specific (LLFC 681 & 760) | H39: 0.285 | I39: 106.93 | J39: 1.27 | K39: 1.27 | L39: 0 | M39: 4277.3 | N39: 0.05 | O39: 0.05
A40: 544 | B40: 544 | C40: 1570000124531 | D40: 761 | E40: 761 | F40: 1594000000047 | G40: EHV Site Specific - Generation Exempt (LLFC 544 & 761) | H40: 0 | I40: 11.25 | J40: 0.81 | K40: 0.81 | L40: 0 | M40: 0 | N40: 0 | O40: 0
A41: 682 | B41: 682 | C41: 1580000909309 | D41: 762 | E41: 762 | F41: 1574000285644 | G41: EHV Site Specific (LLFC 682 & 762) | H41: 0.448 | I41: 805.14 | J41: 0.84 | K41: 0.84 | L41: -0.565 | M41: 4391.65 | N41: 0.05 | O41: 0.05
A42: 691 | B42: 691 | C42: 1592101007746 | E42: 0 | F42: 0 | G42: EHV Site Specific (LLFC 691) | H42: 0.062 | I42: 32.92 | J42: 4.59 | K42: 4.59 | L42: 0 | M42: 0 | N42: 0 | O42: 0
A43: 683 | B43: 683 | C43: 1570000166434 | D43: 763 | E43: 763 | F43: 1594000000029 | G43: EHV Site Specific - Generation Exempt (LLFC 683 & 763) | H43: 0 | I43: 6.44 | J43: 1.05 | K43: 1.05 | L43: 0 | M43: 0 | N43: 0 | O43: 0
A44: 692 | B44: 692 | C44: 1580000867554 1580000911799 | E44: 0 | F44: 0 | G44: EHV Site Specific (LLFC 692) | H44: 1.218 | I44: 65.85 | J44: 2.7 | K44: 2.7 | L44: 0 | M44: 0 | N44: 0 | O44: 0
A45: 693 | B45: 693 | C45: 1592001074941 | E45: 0 | F45: 0 | G45: EHV Site Specific (LLFC 693) | H45: 0.813 | I45: 32.92 | J45: 3.71 | K45: 3.71 | L45: 0 | M45: 0 | N45: 0 | O45: 0
A46: 694 | B46: 694 | C46: 1570000190631 | E46: 0 | F46: 0 | G46: EHV Site Specific (LLFC 694) | H46: 0.353 | I46: 65.85 | J46: 5.29 | K46: 5.29 | L46: 0 | M46: 0 | N46: 0 | O46: 0
A47: 695 | B47: 695 | C47: 1580000918163 1580000918172 | E47: 0 | F47: 0 | G47: EHV Site Specific (LLFC 695) | H47: 0.003 | I47: 65.85 | J47: 2.92 | K47: 2.92 | L47: 0 | M47: 0 | N47: 0 | O47: 0
A48: 684 | B48: 684 | C48: 1580001085400 | D48: 764 | E48: 764 | F48: 1574000298500 | G48: EHV Site Specific (LLFC 684 & 764) | H48: 0.006 | I48: 589.61 | J48: 1.33 | K48: 1.33 | L48: -0.148 | M48: 3931.23 | N48: 0.05 | O48: 0.05
A49: 685 | B49: 685 | C49: 1580001132432 | D49: 765 | E49: 765 | F49: 1574000302403 | G49: EHV Site Specific (LLFC 685 & 765) | H49: 0 | I49: 31.91 | J49: 0.66 | K49: 0.66 | L49: 0 | M49: 874.38 | N49: 0.05 | O49: 0.05
A50: 686 | B50: 686 | C50: 1580001150566 1580001150575 | D50: 766 | E50: 766 | F50: 1574000303940 1574000303959 | G50: EHV Site Specific (LLFC 686 & 766) | H50: 0 | I50: 311.53 | J50: 0.53 | K50: 0.53 | L50: 0 | M50: 19339.22 | N50: 0.05 | O50: 0.05
A51: 687 | B51: 687 | C51: TBC | E51: 0 | F51: 0 | G51: EHV Site Specific (LLFC 687) | H51: 0 | I51: 2017.98 | J51: 1.24 | K51: 1.24 | L51: 0 | M51: 0 | N51: 0 | O51: 0
A52: 688 | B52: 688 | C52: 1580001208659 | D52: 767 | E52: 767 | F52: 1574000309384 | G52: EHV Site Specific (LLFC 688 & 767) | H52: 0 | I52: 17.36 | J52: 1.89 | K52: 1.89 | L52: 0 | M52: 1978.85 | N52: 0.05 | O52: 0.05
A53: 689 | B53: 689 | C53: 1580001208668 | D53: 768 | E53: 768 | F53: 1574000309375 | G53: EHV Site Specific (LLFC 689 & 768) | H53: 0 | I53: 90.78 | J53: 1.73 | K53: 1.73 | L53: 0 | M53: 3918 | N53: 0.05 | O53: 0.05
A54: 690 | B54: 690 | C54: 1580001174414 | D54: 782 | E54: 782 | F54: 1574000306374 | G54: EHV Site Specific (LLFC 690 & 782) | H54: 0.241 | I54: 36.8 | J54: 2.71 | K54: 2.71 | L54: 0 | M54: 1324.71 | N54: 0.05 | O54: 0.05
A55: 540 | B55: 540 | C55: 1580001190763 | D55: 783 | E55: 783 | F55: 1574000307917 | G55: EHV Site Specific (LLFC 540 & 783) | H55: 0.001 | I55: 2.12 | J55: 1.25 | K55: 1.25 | L55: -0.035 | M55: 511.47 | N55: 0.05 | O55: 0.05
A56: 541 | B56: 541 | C56: 1580001197945 | D56: 784 | E56: 784 | F56: 1574000308405 | G56: EHV Site Specific (LLFC 541 & 784) | H56: 0.524 | I56: 315.86 | J56: 3.9 | K56: 3.9 | L56: -0.637 | M56: 4667.02 | N56: 0.05 | O56: 0.05
A57: 542 | B57: 542 | C57: 1580001278406 | D57: 785 | E57: 785 | F57: 1574000315040 | G57: EHV Site Specific (LLFC 542 & 785) | H57: 0 | I57: 169.3 | J57: 0.81 | K57: 0.81 | L57: 0 | M57: 313.2 | N57: 0.05 | O57: 0.05
A58: 543 | B58: 543 | C58: 1580001278415 | E58: 0 | F58: 0 | G58: EHV Site Specific (LLFC 543) | H58: 0 | I58: 3992.41 | J58: 0.98 | K58: 0.98 | L58: 0 | M58: 0 | N58: 0 | O58: 0
A59: 545 | B59: 545 | C59: 1580001417656 | E59: 0 | F59: 0 | G59: EHV Site Specific (LLFC 545) | H59: 0.064 | I59: 17393.39 | J59: 1.31 | K59: 1.31 | L59: 0 | M59: 0 | N59: 0 | O59: 0
A60: 547 | B60: 547 | C60: 1580001440530 | D60: 787 | E60: 787 | F60: 1574000324470 | G60: EHV Site Specific (LLFC 547 & 787) | H60: 0 | I60: 32.26 | J60: 1.77 | K60: 1.77 | L60: 0 | M60: 2228.06 | N60: 0.05 | O60: 0.05
A61: 548 | B61: 548 | C61: 1580001440520 | D61: 788 | E61: 788 | F61: 1574000324461 | G61: EHV Site Specific (LLFC 548 & 788) | H61: 0 | I61: 64.28 | J61: 1.76 | K61: 1.76 | L61: 0 | M61: 5563.62 | N61: 0.05 | O61: 0.05
A62: 549 | B62: 549 | C62: 1580001487955 | D62: 789 | E62: 789 | F62: 1574000327286 | G62: EHV Site Specific (LLFC 549 & 789) | H62: 0 | I62: 258.78 | J62: 2.12 | K62: 2.12 | L62: 0 | M62: 18287.13 | N62: 0.05 | O62: 0.05
A63: 560 | B63: 560 | C63: MSID_7331 | D63: 806 | E63: 806 | F63: MSID_7333 | G63: EHV Site Specific (LLFC 560 & 806) | H63: 0 | I63: 32.41 | J63: 1.91 | K63: 1.91 | L63: 0 | M63: 2690.13 | N63: 0.05 | O63: 0.05
A64: 561 | B64: 561 | C64: 1580001519739 | D64: 807 | E64: 807 | F64: 1574000328420 | G64: EHV Site Specific (LLFC 561 & 807) | H64: 0 | I64: 51.34 | J64: 1.7 | K64: 1.7 | L64: 0 | M64: 8899.6 | N64: 0.05 | O64: 0.05
A65: 563 | B65: 563 | C65: 1580001448895 | D65: 802 | E65: 802 | F65: 1574000324790 | G65: EHV Site Specific (LLFC 563 & 802) | H65: 0.723 | I65: 1.34 | J65: 1.93 | K65: 1.93 | L65: 0 | M65: 126.88 | N65: 0.05 | O65: 0.05
A66: 562 | B66: 562 | C66: 1580001448900 | D66: 769 | E66: 769 | F66: 1574000324781 | G66: EHV Site Specific (LLFC 562 & 769) | H66: 0.723 | I66: 1.34 | J66: 1.84 | K66: 1.84 | L66: 0 | M66: 126.88 | N66: 0.05 | O66: 0.05
A67: 564 | B67: 564 | C67: 1580001527952 | D67: 803 | E67: 803 | F67: 1574000328703 | G67: EHV Site Specific (LLFC 564 & 803) | H67: 0 | I67: 248.29 | J67: 1.91 | K67: 1.91 | L67: 0 | M67: 248.29 | N67: 0.05 | O67: 0.05
A68: 565 | B68: 565 | C68: 1580001498380 | D68: 805 | E68: 805 | F68: 1574000327505 | G68: EHV Site Specific (LLFC 565 & 805) | H68: 0.183 | I68: 130.51 | J68: 2.52 | K68: 2.52 | L68: -0.285 | M68: 511.05 | N68: 0.05 | O68: 0.05
A69: 567 | B69: 567 | C69: 1580001531639 | D69: 809 | E69: 809 | F69: 1574000328810 | G69: EHV Site Specific (LLFC 567 & 809) | H69: 0.361 | I69: 7.03 | J69: 3.36 | K69: 3.36 | L69: 0 | M69: 606.91 | N69: 0.05 | O69: 0.05
A70: 566 | B70: 566 | C70: 1580001511800 | D70: 808 | E70: 808 | F70: 1574000328094 | G70: EHV Site Specific (LLFC 566 & 808) | H70: 0.001 | I70: 495.72 | J70: 2.45 | K70: 2.45 | L70: -0.014 | M70: 1990.84 | N70: 0.05 | O70: 0.05

Sheet Annex 2a Import
A1: Note: The list of MPANs / MSIDs provided may be incomplete; the DNO reserves the right to apply the listed charges to any other MPANs / MSIDs associated with the site. Note: This table is automatically populated based on the content of the tab entitled 'Annex 2 EHV Charges'. The timebands are as shown in Annex 2.
A2: =Overview!B4& " - Effective from "&Overview!D4&" - "&Overview!E4&" EDCM import charges" -> Northern Powergrid (Northeast) Ltd - Effective from 1 April 2019 - Final EDCM import charges
A4: Import Unique Identifier | B4: LLFC | C4: Import MPANs/MSIDs | D4: Name | E4: ='Annex 2 EHV charges'!H9 -> Import Super Red unit charge (p/kWh) | F4: ='Annex 2 EHV charges'!I9 -> Import fixed charge (p/day) | G4: ='Annex 2 EHV charges'!J9 -> Import capacity charge (p/kVA/day) | H4: ='Annex 2 EHV charges'!K9 -> Import exceeded capacity charge (p/kVA/day)
A5: {=IFERROR(INDEX('Annex 2 EHV charges'!$A$10:$A$150, MATCH(0, IF(('Annex 2 EHV charges'!$A$10:$A$150=""),1, COUNTIF(A$4:$A4, 'Annex 2 EHV charges'!$A$10:$A$150)), 0)),"")} -> 601 | B5: =IF($A5="","",VLOOKUP($A5,'Annex 2 EHV charges'!$A:$O,2,0)) -> 601 | C5: =IF($A5="","",VLOOKUP($A5,'Annex 2 EHV charges'!$A:$O,3,0)) -> 1592001005770 1592101005776 | D5: =IF($A5="","",VLOOKUP($A5,'Annex 2 EHV charges'!$A:$O,7,0)) -> EHV Site Specific - Generation Exempt (LLFC 601 & 701) | E5: =IFERROR(IF(VLOOKUP($A5,'Annex 2 EHV charges'!$A:$O,8,FALSE)=0,"",VLOOKUP($A5,'Annex 2 EHV charges'!$A:$O,8,FALSE)),"") | F5: =IFERROR(IF(VLOOKUP($A5,'Annex 2 EHV charges'!$A:$O,9,FALSE)=0,"",VLOOKUP($A5,'Annex 2 EHV charges'!$A:$O,9,FALSE)),"") -> 715.82 | G5: =IFERROR(IF(VLOOKUP($A5,'Annex 2 EHV charges'!$A:$O,10,FALSE)=0,"",VLOOKUP($A5,'Annex 2 EHV charges'!$A:$O,10,FALSE)),"") -> 0.72 | H5: =IFERROR(IF(VLOOKUP($A5,'Annex 2 EHV charges'!$A:$O,11,FALSE)=0,"",VLOOKUP($A5,'Annex 2 EHV charges'!$A:$O,11,FALSE)),"") -> 0.72
A6: {=IFERROR(INDEX('Annex 2 EHV charges'!$A$10:$A$150, MATCH(0, IF(('Annex 2 EHV charges'!$A$10:$A$150=""),1, COUNTIF(A$4:$A5, 'Annex 2 EHV charges'!$A$10:$A$150)), 0)),"")} -> 603 | B6: =IF($A6="","",VLOOKUP($A6,'Annex 2 EHV charges'!$A:$O,2,0)) -> 603 | C6: =IF($A6="","",VLOOKUP($A6,'Annex 2 EHV charges'!$A:$O,3,0)) -> 1592001051182 | D6: =IF($A6="","",VLOOKUP($A6,'Annex 2 EHV charges'!$A:$O,7,0)) -> EHV Site Specific (LLFC 603) | E6: =IFERROR(IF(VLOOKUP($A6,'Annex 2 EHV charges'!$A:$O,8,FALSE)=0,"",VLOOKUP($A6,'Annex 2 EHV charges'!$A:$O,8,FALSE)),"") | F6: =IFERROR(IF(VLOOKUP($A6,'Annex 2 EHV charges'!$A:$O,9,FALSE)=0,"",VLOOKUP($A6,'Annex 2 EHV charges'!$A:$O,9,FALSE)),"") -> 8053.96 | G6: =IFERROR(IF(VLOOKUP($A6,'Annex 2 EHV charges'!$A:$O,10,FALSE)=0,"",VLOOKUP($A6,'Annex 2 EHV charges'!$A:$O,10,FALSE)),"") -> 1.92 | H6: =IFERROR(IF(VLOOKUP($A6,'Annex 2 EHV charges'!$A:$O,11,FALSE)=0,"",VLOOKUP($A6,'Annex 2 EHV charges'!$A:$O,11,FALSE)),"") -> 1.92
A7: {=IFERROR(INDEX('Annex 2 EHV charges'!$A$10:$A$150, MATCH(0, IF(('Annex 2 EHV charges'!$A$10:$A$150=""),1, COUNTIF(A$4:$A6, 'Annex 2 EHV charges'!$A$10:$A$150)), 0)),"")} -> 604 | B7: =IF($A7="","",VLOOKUP($A7,'Annex 2 EHV charges'!$A:$O,2,0)) -> 604 | C7: =IF($A7="","",VLOOKUP($A7,'Annex 2 EHV charges'!$A:$O,3,0)) -> MSID_7299 | D7: =IF($A7="","",VLOOKUP($A7,'Annex 2 EHV charges'!$A:$O,7,0)) -> EHV Site Specific (LLFC 604 & 727) | E7: =IFERROR(IF(VLOOKUP($A7,'Annex 2 EHV charges'!$A:$O,8,FALSE)=0,"",VLOOKUP($A7,'Annex 2 EHV charges'!$A:$O,8,FALSE)),"") | F7: =IFERROR(IF(VLOOKUP($A7,'Annex 2 EHV charges'!$A:$O,9,FALSE)=0,"",VLOOKUP($A7,'Annex 2 EHV charges'!$A:$O,9,FALSE)),"") -> 52.97 | G7: =IFERROR(IF(VLOOKUP($A7,'Annex 2 EHV charges'!$A:$O,10,FALSE)=0,"",VLOOKUP($A7,'Annex 2 EHV charges'!$A:$O,10,FALSE)),"") -> 0.77 | H7: =IFERROR(IF(VLOOKUP($A7,'Annex 2 EHV charges'!$A:$O,11,FALSE)=0,"",VLOOKUP($A7,'Annex 2 EHV charges'!$A:$O,11,FALSE)),"") -> 0.77
A8: {=IFERROR(INDEX('Annex 2 EHV charges'!$A$10:$A$150, MATCH(0, IF(('Annex 2 EHV charges'!$A$10:$A$150=""),1, COUNTIF(A$4:$A7, 'Annex 2 EHV charges'!$A$10:$A$150)), 0)),"")} -> 605 | B8: =IF($A8="","",VLOOKUP($A8,'Annex 2 EHV charges'!$A:$O,2,0)) -> 605 | C8: =IF($A8="","",VLOOKUP($A8,'Annex 2 EHV charges'!$A:$O,3,0)) -> 1592001092676 | D8: =IF($A8="","",VLOOKUP($A8,'Annex 2 EHV charges'!$A:$O,7,0)) -> EHV Site Specific (LLFC 605) | E8: =IFERROR(IF(VLOOKUP($A8,'Annex 2 EHV charges'!$A:$O,8,FALSE)=0,"",VLOOKUP($A8,'Annex 2 EHV charges'!$A:$O,8,FALSE)),"") -> 0.372 | F8: =IFERROR(IF(VLOOKUP($A8,'Annex 2 EHV charges'!$A:$O,9,FALSE)=0,"",VLOOKUP($A8,'Annex 2 EHV charges'!$A:$O,9,FALSE)),"") -> 1997.93 | G8: =IFERROR(IF(VLOOKUP($A8,'Annex 2 EHV charges'!$A:$O,10,FALSE)=0,"",VLOOKUP($A8,'Annex 2 EHV charges'!$A:$O,10,FALSE)),"") -> 1.75 | H8: =IFERROR(IF(VLOOKUP($A8,'Annex 2 EHV charges'!$A:$O,11,FALSE)=0,"",VLOOKUP($A8,'Annex 2 EHV charges'!$A:$O,11,FALSE)),"") -> 1.75
A9: {=IFERROR(INDEX('Annex 2 EHV charges'!$A$10:$A$150, MATCH(0, IF(('Annex 2 EHV charges'!$A$10:$A$150=""),1, COUNTIF(A$4:$A8, 'Annex 2 EHV charges'!$A$10:$A$150)), 0)),"")} -> 606 | B9: =IF($A9="","",VLOOKUP($A9,'Annex 2 EHV charges'!$A:$O,2,0)) -> 606 | C9: =IF($A9="","",VLOOKUP($A9,'Annex 2 EHV charges'!$A:$O,3,0)) -> 1592001092719 | D9: =IF($A9="","",VLOOKUP($A9,'Annex 2 EHV charges'!$A:$O,7,0)) -> EHV Site Specific (LLFC 606) | E9: =IFERROR(IF(VLOOKUP($A9,'Annex 2 EHV charges'!$A:$O,8,FALSE)=0,"",VLOOKUP($A9,'Annex 2 EHV charges'!$A:$O,8,FALSE)),"") -> 0.408 | F9: =IFERROR(IF(VLOOKUP($A9,'Annex 2 EHV charges'!$A:$O,9,FALSE)=0,"",VLOOKUP($A9,'Annex 2 EHV charges'!$A:$O,9,FALSE)),"") -> 3995.86 | G9: =IFERROR(IF(VLOOKUP($A9,'Annex 2 EHV charges'!$A:$O,10,FALSE)=0,"",VLOOKUP($A9,'Annex 2 EHV charges'!$A:$O,10,FALSE)),"") -> 2 | H9: =IFERROR(IF(VLOOKUP($A9,'Annex 2 EHV charges'!$A:$O,11,FALSE)=0,"",VLOOKUP($A9,'Annex 2 EHV charges'!$A:$O,11,FALSE)),"") -> 2
A10: {=IFERROR(INDEX('Annex 2 EHV charges'!$A$10:$A$150, MATCH(0, IF(('Annex 2 EHV charges'!$A$10:$A$150=""),1, COUNTIF(A$4:$A9, 'Annex 2 EHV charges'!$A$10:$A$150)), 0)),"")} -> 607 | B10: =IF($A10="","",VLOOKUP($A10,'Annex 2 EHV charges'!$A:$O,2,0)) -> 607 | C10: =IF($A10="","",VLOOKUP($A10,'Annex 2 EHV charges'!$A:$O,3,0)) -> 1592001092728 | D10: =IF($A10="","",VLOOKUP($A10,'Annex 2 EHV charges'!$A:$O,7,0)) -> EHV Site Specific (LLFC 607) | E10: =IFERROR(IF(VLOOKUP($A10,'Annex 2 EHV charges'!$A:$O,8,FALSE)=0,"",VLOOKUP($A10,'Annex 2 EHV charges'!$A:$O,8,FALSE)),"") -> 1.182 | F10: =IFERROR(IF(VLOOKUP($A10,'Annex 2 EHV charges'!$A:$O,9,FALSE)=0,"",VLOOKUP($A10,'Annex 2 EHV charges'!$A:$O,9,FALSE)),"") -> 3995.86 | G10: =IFERROR(IF(VLOOKUP($A10,'Annex 2 EHV charges'!$A:$O,10,FALSE)=0,"",VLOOKUP($A10,'Annex 2 EHV charges'!$A:$O,10,FALSE)),"") -> 2.91 | H10: =IFERROR(IF(VLOOKUP($A10,'Annex 2 EHV charges'!$A:$O,11,FALSE)=0,"",VLOOKUP($A10,'Annex 2 EHV charges'!$A:$O,11,FALSE)),"") -> 2.91
A11: {=IFERROR(INDEX('Annex 2 EHV charges'!$A$10:$A$150, MATCH(0, IF(('Annex 2 EHV charges'!$A$10:$A$150=""),1, COUNTIF(A$4:$A10, 'Annex 2 EHV charges'!$A$10:$A$150)), 0)),"")} -> 608 | B11: =IF($A11="","",VLOOKUP($A11,'Annex 2 EHV charges'!$A:$O,2,0)) -> 608 | C11: =IF($A11="","",VLOOKUP($A11,'Annex 2 EHV charges'!$A:$O,3,0)) -> 1592001092737 | D11: =IF($A11="","",VLOOKUP($A11,'Annex 2 EHV charges'!$A:$O,7,0)) -> EHV Site Specific (LLFC 608) | E11: =IFERROR(IF(VLOOKUP($A11,'Annex 2 EHV charges'!$A:$O,8,FALSE)=0,"",VLOOKUP($A11,'Annex 2 EHV charges'!$A:$O,8,FALSE)),"") -> 0.037 | F11: =IFERROR(IF(VLOOKUP($A11,'Annex 2 EHV charges'!$A:$O,9,FALSE)=0,"",VLOOKUP($A11,'Annex 2 EHV charges'!$A:$O,9,FALSE)),"") -> 3995.86 | G11: =IFERROR(IF(VLOOKUP($A11,'Annex 2 EHV charges'!$A:$O,10,FALSE)=0,"",VLOOKUP($A11,'Annex 2 EHV charges'!$A:$O,10,FALSE)),"") -> 2.7 | H11: =IFERROR(IF(VLOOKUP($A11,'Annex 2 EHV charges'!$A:$O,11,FALSE)=0,"",VLOOKUP($A11,'Annex 2 EHV charges'!$A:$O,11,FALSE)),"") -> 2.7
A12: {=IFERROR(INDEX('Annex 2 EHV charges'!$A$10:$A$150, MATCH(0, IF(('Annex 2 EHV charges'!$A$10:$A$150=""),1, COUNTIF(A$4:$A11, 'Annex 2 EHV charges'!$A$10:$A$150)), 0)),"")} -> 609 | B12: =IF($A12="","",VLOOKUP($A12,'Annex 2 EHV charges'!$A:$O,2,0)) -> 609 | C12: =IF($A12="","",VLOOKUP($A12,'Annex 2 EHV charges'!$A:$O,3,0)) -> 1592001046085 | D12: =IF($A12="","",VLOOKUP($A12,'Annex 2 EHV charges'!$A:$O,7,0)) -> EHV Site Specific (LLFC 609) | E12: =IFERROR(IF(VLOOKUP($A12,'Annex 2 EHV charges'!$A:$O,8,FALSE)=0,"",VLOOKUP($A12,'Annex 2 EHV charges'!$A:$O,8,FALSE)),"") | F12: =IFERROR(IF(VLOOKUP($A12,'Annex 2 EHV charges'!$A:$O,9,FALSE)=0,"",VLOOKUP($A12,'Annex 2 EHV charges'!$A:$O,9,FALSE)),"") -> 703.73 | G12: =IFERROR(IF(VLOOKUP($A12,'Annex 2 EHV charges'!$A:$O,10,FALSE)=0,"",VLOOKUP($A12,'Annex 2 EHV charges'!$A:$O,10,FALSE)),"") -> 3.05 | H12: =IFERROR(IF(VLOOKUP($A12,'Annex 2 EHV charges'!$A:$O,11,FALSE)=0,"",VLOOKUP($A12,'Annex 2 EHV charges'!$A:$O,11,FALSE)),"") -> 3.05
A13: {=IFERROR(INDEX('Annex 2 EHV charges'!$A$10:$A$150, MATCH(0, IF(('Annex 2 EHV charges'!$A$10:$A$150=""),1, COUNTIF(A$4:$A12, 'Annex 2 EHV charges'!$A$10:$A$150)), 0)),"")} -> 611 | B13: =IF($A13="","",VLOOKUP($A13,'Annex 2 EHV charges'!$A:$O,2,0)) -> 611 | C13: =IF($A13="","",VLOOKUP($A13,'Annex 2 EHV charges'!$A:$O,3,0)) -> 1592001111628 | D13: =IF($A13="","",VLOOKUP($A13,'Annex 2 EHV charges'!$A:$O,7,0)) -> EHV Site Specific (LLFC 611) | E13: =IFERROR(IF(VLOOKUP($A13,'Annex 2 EHV charges'!$A:$O,8,FALSE)=0,"",VLOOKUP($A13,'Annex 2 EHV charges'!$A:$O,8,FALSE)),"") | F13: =IFERROR(IF(VLOOKUP($A13,'Annex 2 EHV charges'!$A:$O,9,FALSE)=0,"",VLOOKUP($A13,'Annex 2 EHV charges'!$A:$O,9,FALSE)),"") -> 3493.87 | G13: =IFERROR(IF(VLOOKUP($A13,'Annex 2 EHV charges'!$A:$O,10,FALSE)=0,"",VLOOKUP($A13,'Annex 2 EHV charges'!$A:$O,10,FALSE)),"") -> 4.97 | H13: =IFERROR(IF(VLOOKUP($A13,'Annex 2 EHV charges'!$A:$O,11,FALSE)=0,"",VLOOKUP($A13,'Annex 2 EHV charges'!$A:$O,11,FALSE)),"") -> 4.97
A14: {=IFERROR(INDEX('Annex 2 EHV charges'!$A$10:$A$150, MATCH(0, IF(('Annex 2 EHV charges'!$A$10:$A$150=""),1, COUNTIF(A$4:$A13, 'Annex 2 EHV charges'!$A$10:$A$150)), 0)),"")} -> 612 | B14: =IF($A14="","",VLOOKUP($A14,'Annex 2 EHV charges'!$A:$O,2,0)) -> 612 | C14: =IF($A14="","",VLOOKUP($A14,'Annex 2 EHV charges'!$A:$O,3,0)) -> 1592001073112 | D14: =IF($A14="","",VLOOKUP($A14,'Annex 2 EHV charges'!$A:$O,7,0)) -> EHV Site Specific (LLFC 612 & 704) | E14: =IFERROR(IF(VLOOKUP($A14,'Annex 2 EHV charges'!$A:$O,8,FALSE)=0,"",VLOOKUP($A14,'Annex 2 EHV charges'!$A:$O,8,FALSE)),"") -> 0.448 | F14: =IFERROR(IF(VLOOKUP($A14,'Annex 2 EHV charges'!$A:$O,9,FALSE)=0,"",VLOOKUP($A14,'Annex 2 EHV charges'!$A:$O,9,FALSE)),"") -> 184.47 | G14: =IFERROR(IF(VLOOKUP($A14,'Annex 2 EHV charges'!$A:$O,10,FALSE)=0,"",VLOOKUP($A14,'Annex 2 EHV charges'!$A:$O,10,FALSE)),"") -> 1.18 | H14: =IFERROR(IF(VLOOKUP($A14,'Annex 2 EHV charges'!$A:$O,11,FALSE)=0,"",VLOOKUP($A14,'Annex 2 EHV charges'!$A:$O,11,FALSE)),"") -> 1.18
A15: {=IFERROR(INDEX('Annex 2 EHV charges'!$A$10:$A$150, MATCH(0, IF(('Annex 2 EHV charges'!$A$10:$A$150=""),1, COUNTIF(A$4:$A14, 'Annex 2 EHV charges'!$A$10:$A$150)), 0)),"")} -> 613 | B15: =IF($A15="","",VLOOKUP($A15,'Annex 2 EHV charges'!$A:$O,2,0)) -> 613 | C15: =IF($A15="","",VLOOKUP($A15,'Annex 2 EHV charges'!$A:$O,3,0)) -> TBC | D15: =IF($A15="","",VLOOKUP($A15,'Annex 2 EHV charges'!$A:$O,7,0)) -> EHV Site Specific (LLFC 613) | E15: =IFERROR(IF(VLOOKUP($A15,'Annex 2 EHV charges'!$A:$O,8,FALSE)=0,"",VLOOKUP($A15,'Annex 2 EHV charges'!$A:$O,8,FALSE)),"") -> 0.982 | F15: =IFERROR(IF(VLOOKUP($A15,'Annex 2 EHV charges'!$A:$O,9,FALSE)=0,"",VLOOKUP($A15,'Annex 2 EHV charges'!$A:$O,9,FALSE)),"") -> 65.85 | G15: =IFERROR(IF(VLOOKUP($A15,'Annex 2 EHV charges'!$A:$O,10,FALSE)=0,"",VLOOKUP($A15,'Annex 2 EHV charges'!$A:$O,10,FALSE)),"") -> 1.16 | H15: =IFERROR(IF(VLOOKUP($A15,'Annex 2 EHV charges'!$A:$O,11,FALSE)=0,"",VLOOKUP($A15,'Annex 2 EHV charges'!$A:$O,11,FALSE)),"") -> 1.16
A16: {=IFERROR(INDEX('Annex 2 EHV charges'!$A$10:$A$150, MATCH(0, IF(('Annex 2 EHV charges'!$A$10:$A$150=""),1, COUNTIF(A$4:$A15, 'Annex 2 EHV charges'!$A$10:$A$150)), 0)),"")} -> 614 | B16: =IF($A16="","",VLOOKUP($A16,'Annex 2 EHV charges'!$A:$O,2,0)) -> 614 | C16: =IF($A16="","",VLOOKUP($A16,'Annex 2 EHV charges'!$A:$O,3,0)) -> 1592001055257 | D16: =IF($A16="","",VLOOKUP($A16,'Annex 2 EHV charges'!$A:$O,7,0)) -> EHV Site Specific (LLFC 614 & 709) | E16: =IFERROR(IF(VLOOKUP($A16,'Annex 2 EHV charges'!$A:$O,8,FALSE)=0,"",VLOOKUP($A16,'Annex 2 EHV charges'!$A:$O,8,FALSE)),"") | F16: =IFERROR(IF(VLOOKUP($A16,'Annex 2 EHV charges'!$A:$O,9,FALSE)=0,"",VLOOKUP($A16,'Annex 2 EHV charges'!$A:$O,9,FALSE)),"") -> 6364.26 | G16: =IFERROR(IF(VLOOKUP($A16,'Annex 2 EHV charges'!$A:$O,10,FALSE)=0,"",VLOOKUP($A16,'Annex 2 EHV charges'!$A:$O,10,FALSE)),"") -> 0.53 | H16: =IFERROR(IF(VLOOKUP($A16,'Annex 2 EHV charges'!$A:$O,11,FALSE)=0,"",VLOOKUP($A16,'Annex 2 EHV charges'!$A:$O,11,FALSE)),"") -> 0.53
... A65: {=IFERROR(INDEX('Annex 2 EHV charges'!$A$10:$A$150, MATCH(0, IF(('Annex 2 EHV charges'!$A$10:$A$150=""),1, COUNTIF(A$4:$A64, 'Annex 2 EHV charges'!$A$10:$A$150)), 0)),"")} -> 566 | B65: =IF($A65="","",VLOOKUP($A65,'Annex 2 EHV charges'!$A:$O,2,0)) -> 566 | C65: =IF($A65="","",VLOOKUP($A65,'Annex 2 EHV charges'!$A:$O,3,0)) -> 1580001511800 | D65: =IF($A65="","",VLOOKUP($A65,'Annex 2 EHV charges'!$A:$O,7,0)) -> EHV Site Specific (LLFC 566 & 808) | E65: =IFERROR(IF(VLOOKUP($A65,'Annex 2 EHV charges'!$A:$O,8,FALSE)=0,"",VLOOKUP($A65,'Annex 2 EHV charges'!$A:$O,8,FALSE)),"") -> 0.001 | F65: =IFERROR(IF(VLOOKUP($A65,'Annex 2 EHV charges'!$A:$O,9,FALSE)=0,"",VLOOKUP($A65,'Annex 2 EHV charges'!$A:$O,9,FALSE)),"") -> 495.72 | G65: =IFERROR(IF(VLOOKUP($A65,'Annex 2 EHV charges'!$A:$O,10,FALSE)=0,"",VLOOKUP($A65,'Annex 2 EHV charges'!$A:$O,10,FALSE)),"") -> 2.45 | H65: =IFERROR(IF(VLOOKUP($A65,'Annex 2 EHV charges'!$A:$O,11,FALSE)=0,"",VLOOKUP($A65,'Annex 2 EHV charges'!$A:$O,11,FALSE)),"") -> 2.45

Sheet Annex 2b Export
A1: Note: The list of MPANs / MSIDs provided may be incomplete; the DNO reserves the right to apply the listed charges to any other MPANs / MSIDs associated with the site. Note: This table is automatically populated based on the content of the tab entitled 'Annex 2 EHV Charges'. The timebands are as shown in Annex 2.
A2: =Overview!B4& " - Effective from "&Overview!D4&" - "&Overview!E4&" EDCM export charges" -> Northern Powergrid (Northeast) Ltd - Effective from 1 April 2019 - Final EDCM export charges
A4: Export Unique Identifier | B4: LLFC | C4: Export MPANs/MSIDs | D4: Name | E4: ='Annex 2 EHV charges'!L9 -> Export Super Red unit charge (p/kWh) | F4: ='Annex 2 EHV charges'!M9 -> Export fixed charge (p/day) | G4: ='Annex 2 EHV charges'!N9 -> Export capacity charge (p/kVA/day) | H4: ='Annex 2 EHV charges'!O9 -> Export exceeded capacity charge (p/kVA/day)
A5: {=IFERROR(INDEX('Annex 2 EHV charges'!$D$10:$D$150, MATCH(0, IF(('Annex 2 EHV charges'!$D$10:$D$150=""),1, COUNTIF(A$4:$A4, 'Annex 2 EHV charges'!$D$10:$D$150)), 0)),"")} -> 701 | B5: =IF($A5="","",VLOOKUP($A5,'Annex 2 EHV charges'!$D:$O,2,0)) -> 701 | C5: =IF($A5="","",VLOOKUP($A5,'Annex 2 EHV charges'!$D:$O,3,0)) -> 1574000216135 1594001005774 | D5: =IF($A5="","",VLOOKUP($A5,'Annex 2 EHV charges'!$D:$O,4,0)) -> EHV Site Specific - Generation Exempt (LLFC 601 & 701) | E5: =IFERROR(IF(VLOOKUP($A5,'Annex 2 EHV charges'!$D:$O,9,FALSE)=0,"",VLOOKUP($A5,'Annex 2 EHV charges'!$D:$O,9,FALSE)),"") | F5: =IFERROR(IF(VLOOKUP($A5,'Annex 2 EHV charges'!$D:$O,10,FALSE)=0,"",VLOOKUP($A5,'Annex 2 EHV charges'!$D:$O,10,FALSE)),"") | G5: =IFERROR(IF(VLOOKUP($A5,'Annex 2 EHV charges'!$D:$O,11,FALSE)=0,"",VLOOKUP($A5,'Annex 2 EHV charges'!$D:$O,11,FALSE)),"") | H5: =IFERROR(IF(VLOOKUP($A5,'Annex 2 EHV charges'!$D:$O,12,FALSE)=0,"",VLOOKUP($A5,'Annex 2 EHV charges'!$D:$O,12,FALSE)),"")
A6: {=IFERROR(INDEX('Annex 2 EHV charges'!$D$10:$D$150, MATCH(0, IF(('Annex 2 EHV charges'!$D$10:$D$150=""),1, COUNTIF(A$4:$A5, 'Annex 2 EHV charges'!$D$10:$D$150)), 0)),"")} -> 727 | B6: =IF($A6="","",VLOOKUP($A6,'Annex 2 EHV charges'!$D:$O,2,0)) -> 727 | C6: =IF($A6="","",VLOOKUP($A6,'Annex 2 EHV charges'!$D:$O,3,0)) -> MSID_7300 | D6: =IF($A6="","",VLOOKUP($A6,'Annex 2 EHV charges'!$D:$O,4,0)) -> EHV Site Specific (LLFC 604 & 727) | E6: =IFERROR(IF(VLOOKUP($A6,'Annex 2 EHV charges'!$D:$O,9,FALSE)=0,"",VLOOKUP($A6,'Annex 2 EHV charges'!$D:$O,9,FALSE)),"") | F6: =IFERROR(IF(VLOOKUP($A6,'Annex 2 EHV charges'!$D:$O,10,FALSE)=0,"",VLOOKUP($A6,'Annex 2 EHV charges'!$D:$O,10,FALSE)),"") -> 1059.37 | G6: =IFERROR(IF(VLOOKUP($A6,'Annex 2 EHV charges'!$D:$O,11,FALSE)=0,"",VLOOKUP($A6,'Annex 2 EHV charges'!$D:$O,11,FALSE)),"") -> 0.05 | H6: =IFERROR(IF(VLOOKUP($A6,'Annex 2 EHV charges'!$D:$O,12,FALSE)=0,"",VLOOKUP($A6,'Annex 2 EHV charges'!$D:$O,12,FALSE)),"") -> 0.05
A7: {=IFERROR(INDEX('Annex 2 EHV charges'!$D$10:$D$150, MATCH(0, IF(('Annex 2 EHV charges'!$D$10:$D$150=""),1, COUNTIF(A$4:$A6, 'Annex 2 EHV charges'!$D$10:$D$150)), 0)),"")} -> 704 | B7: =IF($A7="","",VLOOKUP($A7,'Annex 2 EHV charges'!$D:$O,2,0)) -> 704 | C7: =IF($A7="","",VLOOKUP($A7,'Annex 2 EHV charges'!$D:$O,3,0)) -> 1594001073116 | D7: =IF($A7="","",VLOOKUP($A7,'Annex 2 EHV charges'!$D:$O,4,0)) -> EHV Site Specific (LLFC 612 & 704) | E7: =IFERROR(IF(VLOOKUP($A7,'Annex 2 EHV charges'!$D:$O,9,FALSE)=0,"",VLOOKUP($A7,'Annex 2 EHV charges'!$D:$O,9,FALSE)),"") -> -0.565 | F7: =IFERROR(IF(VLOOKUP($A7,'Annex 2 EHV charges'!$D:$O,10,FALSE)=0,"",VLOOKUP($A7,'Annex 2 EHV charges'!$D:$O,10,FALSE)),"") -> 1844.66 | G7: =IFERROR(IF(VLOOKUP($A7,'Annex 2 EHV charges'!$D:$O,11,FALSE)=0,"",VLOOKUP($A7,'Annex 2 EHV charges'!$D:$O,11,FALSE)),"") -> 0.05 | H7: =IFERROR(IF(VLOOKUP($A7,'Annex 2 EHV charges'!$D:$O,12,FALSE)=0,"",VLOOKUP($A7,'Annex 2 EHV charges'!$D:$O,12,FALSE)),"") -> 0.05
A8: {=IFERROR(INDEX('Annex 2 EHV charges'!$D$10:$D$150, MATCH(0, IF(('Annex 2 EHV charges'!$D$10:$D$150=""),1, COUNTIF(A$4:$A7, 'Annex 2 EHV charges'!$D$10:$D$150)), 0)),"")} -> 709 | B8: =IF($A8="","",VLOOKUP($A8,'Annex 2 EHV charges'!$D:$O,2,0)) -> 709 | C8: =IF($A8="","",VLOOKUP($A8,'Annex 2 EHV charges'!$D:$O,3,0)) -> 1594001055250 | D8: =IF($A8="","",VLOOKUP($A8,'Annex 2 EHV charges'!$D:$O,4,0)) -> EHV Site Specific (LLFC 614 & 709) | E8: =IFERROR(IF(VLOOKUP($A8,'Annex 2 EHV charges'!$D:$O,9,FALSE)=0,"",VLOOKUP($A8,'Annex 2 EHV charges'!$D:$O,9,FALSE)),"") | F8: =IFERROR(IF(VLOOKUP($A8,'Annex 2 EHV charges'!$D:$O,10,FALSE)=0,"",VLOOKUP($A8,'Annex 2 EHV charges'!$D:$O,10,FALSE)),"") -> 1272.85 | G8: =IFERROR(IF(VLOOKUP($A8,'Annex 2 EHV charges'!$D:$O,11,FALSE)=0,"",VLOOKUP($A8,'Annex 2 EHV charges'!$D:$O,11,FALSE)),"") -> 0.05 | H8: =IFERROR(IF(VLOOKUP($A8,'Annex 2 EHV charges'!$D:$O,12,FALSE)=0,"",VLOOKUP($A8,'Annex 2 EHV charges'!$D:$O,12,FALSE)),"") -> 0.05
A9: {=IFERROR(INDEX('Annex 2 EHV charges'!$D$10:$D$150, MATCH(0, IF(('Annex 2 EHV charges'!$D$10:$D$150=""),1, COUNTIF(A$4:$A8, 'Annex 2 EHV charges'!$D$10:$D$150)), 0)),"")} -> 710 | B9: =IF($A9="","",VLOOKUP($A9,'Annex 2 EHV charges'!$D:$O,2,0)) -> 710 | C9: =IF($A9="","",VLOOKUP($A9,'Annex 2 EHV charges'!$D:$O,3,0)) -> 1594000000038 | D9: =IF($A9="","",VLOOKUP($A9,'Annex 2 EHV charges'!$D:$O,4,0)) -> EHV Site Specific - Generation Exempt (LLFC 619 & 710) | E9: =IFERROR(IF(VLOOKUP($A9,'Annex 2 EHV charges'!$D:$O,9,FALSE)=0,"",VLOOKUP($A9,'Annex 2 EHV charges'!$D:$O,9,FALSE)),"") | F9: =IFERROR(IF(VLOOKUP($A9,'Annex 2 EHV charges'!$D:$O,10,FALSE)=0,"",VLOOKUP($A9,'Annex 2 EHV charges'!$D:$O,10,FALSE)),"") | G9: =IFERROR(IF(VLOOKUP($A9,'Annex 2 EHV charges'!$D:$O,11,FALSE)=0,"",VLOOKUP($A9,'Annex 2 EHV charges'!$D:$O,11,FALSE)),"") | H9: =IFERROR(IF(VLOOKUP($A9,'Annex 2 EHV charges'!$D:$O,12,FALSE)=0,"",VLOOKUP($A9,'Annex 2 EHV charges'!$D:$O,12,FALSE)),"")
A10: {=IFERROR(INDEX('Annex 2 EHV charges'!$D$10:$D$150, MATCH(0, IF(('Annex 2 EHV charges'!$D$10:$D$150=""),1, COUNTIF(A$4:$A9, 'Annex 2 EHV charges'!$D$10:$D$150)), 0)),"")} -> 711 | B10: =IF($A10="","",VLOOKUP($A10,'Annex 2 EHV charges'!$D:$O,2,0)) -> 711 | C10: =IF($A10="","",VLOOKUP($A10,'Annex 2 EHV charges'!$D:$O,3,0)) -> 1594001036578 | D10: =IF($A10="","",VLOOKUP($A10,'Annex 2 EHV charges'!$D:$O,4,0)) -> EHV Site Specific - Generation Exempt (LLFC 622 & 711) | E10: =IFERROR(IF(VLOOKUP($A10,'Annex 2 EHV charges'!$D:$O,9,FALSE)=0,"",VLOOKUP($A10,'Annex 2 EHV charges'!$D:$O,9,FALSE)),"") | F10: =IFERROR(IF(VLOOKUP($A10,'Annex 2 EHV charges'!$D:$O,10,FALSE)=0,"",VLOOKUP($A10,'Annex 2 EHV charges'!$D:$O,10,FALSE)),"") | G10: =IFERROR(IF(VLOOKUP($A10,'Annex 2 EHV charges'!$D:$O,11,FALSE)=0,"",VLOOKUP($A10,'Annex 2 EHV charges'!$D:$O,11,FALSE)),"") | H10: =IFERROR(IF(VLOOKUP($A10,'Annex 2 EHV charges'!$D:$O,12,FALSE)=0,"",VLOOKUP($A10,'Annex 2 EHV charges'!$D:$O,12,FALSE)),"")
A11: {=IFERROR(INDEX('Annex 2 EHV charges'!$D$10:$D$150, MATCH(0, IF(('Annex 2 EHV charges'!$D$10:$D$150=""),1, COUNTIF(A$4:$A10, 'Annex 2 EHV charges'!$D$10:$D$150)), 0)),"")} -> 804 | B11: =IF($A11="","",VLOOKUP($A11,'Annex 2 EHV charges'!$D:$O,2,0)) -> 804 | C11: =IF($A11="","",VLOOKUP($A11,'Annex 2 EHV charges'!$D:$O,3,0)) -> 1574000324772 | D11: =IF($A11="","",VLOOKUP($A11,'Annex 2 EHV charges'!$D:$O,4,0)) -> EHV Site Specific (LLFC 624 & 804) | E11: =IFERROR(IF(VLOOKUP($A11,'Annex 2 EHV charges'!$D:$O,9,FALSE)=0,"",VLOOKUP($A11,'Annex 2 EHV charges'!$D:$O,9,FALSE)),"") | F11: =IFERROR(IF(VLOOKUP($A11,'Annex 2 EHV charges'!$D:$O,10,FALSE)=0,"",VLOOKUP($A11,'Annex 2 EHV charges'!$D:$O,10,FALSE)),"") -> 958.73 | G11: =IFERROR(IF(VLOOKUP($A11,'Annex 2 EHV charges'!$D:$O,11,FALSE)=0,"",VLOOKUP($A11,'Annex 2 EHV charges'!$D:$O,11,FALSE)),"") -> 0.05 | H11: =IFERROR(IF(VLOOKUP($A11,'Annex 2 EHV charges'!$D:$O,12,FALSE)=0,"",VLOOKUP($A11,'Annex 2 EHV charges'!$D:$O,12,FALSE)),"") -> 0.05
A12: {=IFERROR(INDEX('Annex 2 EHV charges'!$D$10:$D$150, MATCH(0, IF(('Annex 2 EHV charges'!$D$10:$D$150=""),1, COUNTIF(A$4:$A11, 'Annex 2 EHV charges'!$D$10:$D$150)), 0)),"")} -> 748 | B12: =IF($A12="","",VLOOKUP($A12,'Annex 2 EHV charges'!$D:$O,2,0)) -> 748 | C12: =IF($A12="","",VLOOKUP($A12,'Annex 2 EHV charges'!$D:$O,3,0)) -> 1594001006893 | D12: =IF($A12="","",VLOOKUP($A12,'Annex 2 EHV charges'!$D:$O,4,0)) -> EHV Site Specific - Generation Exempt (LLFC 625 & 748) | E12: =IFERROR(IF(VLOOKUP($A12,'Annex 2 EHV charges'!$D:$O,9,FALSE)=0,"",VLOOKUP($A12,'Annex 2 EHV charges'!$D:$O,9,FALSE)),"") | F12: =IFERROR(IF(VLOOKUP($A12,'Annex 2 EHV charges'!$D:$O,10,FALSE)=0,"",VLOOKUP($A12,'Annex 2 EHV charges'!$D:$O,10,FALSE)),"") | G12: =IFERROR(IF(VLOOKUP($A12,'Annex 2 EHV charges'!$D:$O,11,FALSE)=0,"",VLOOKUP($A12,'Annex 2 EHV charges'!$D:$O,11,FALSE)),"") | H12: =IFERROR(IF(VLOOKUP($A12,'Annex 2 EHV charges'!$D:$O,12,FALSE)=0,"",VLOOKUP($A12,'Annex 2 EHV charges'!$D:$O,12,FALSE)),"")
A13: {=IFERROR(INDEX('Annex 2 EHV charges'!$D$10:$D$150, MATCH(0, IF(('Annex 2 EHV charges'!$D$10:$D$150=""),1, COUNTIF(A$4:$A12, 'Annex 2 EHV charges'!$D$10:$D$150)), 0)),"")} -> 729 | B13: =IF($A13="","",VLOOKUP($A13,'Annex 2 EHV charges'!$D:$O,2,0)) -> 729 | C13: =IF($A13="","",VLOOKUP($A13,'Annex 2 EHV charges'!$D:$O,3,0)) -> 1574000199083 | D13: =IF($A13="","",VLOOKUP($A13,'Annex 2 EHV charges'!$D:$O,4,0)) -> EHV Site Specific - Generation Exempt (LLFC 627 & 729) | E13: =IFERROR(IF(VLOOKUP($A13,'Annex 2 EHV charges'!$D:$O,9,FALSE)=0,"",VLOOKUP($A13,'Annex 2 EHV charges'!$D:$O,9,FALSE)),"") | F13: =IFERROR(IF(VLOOKUP($A13,'Annex 2 EHV charges'!$D:$O,10,FALSE)=0,"",VLOOKUP($A13,'Annex 2 EHV charges'!$D:$O,10,FALSE)),"") | G13: =IFERROR(IF(VLOOKUP($A13,'Annex 2 EHV charges'!$D:$O,11,FALSE)=0,"",VLOOKUP($A13,'Annex 2 EHV charges'!$D:$O,11,FALSE)),"") | H13: =IFERROR(IF(VLOOKUP($A13,'Annex 2 EHV charges'!$D:$O,12,FALSE)=0,"",VLOOKUP($A13,'Annex 2 EHV charges'!$D:$O,12,FALSE)),"")
A14: {=IFERROR(INDEX('Annex 2 EHV charges'!$D$10:$D$150, MATCH(0, IF(('Annex 2 EHV charges'!$D$10:$D$150=""),1, COUNTIF(A$4:$A13, 'Annex 2 EHV charges'!$D$10:$D$150)), 0)),"")} -> 728 | B14: =IF($A14="","",VLOOKUP($A14,'Annex 2 EHV charges'!$D:$O,2,0)) -> 728 | C14: =IF($A14="","",VLOOKUP($A14,'Annex 2 EHV charges'!$D:$O,3,0)) -> 1594001141547 | D14: =IF($A14="","",VLOOKUP($A14,'Annex 2 EHV charges'!$D:$O,4,0)) -> EHV Site Specific - Generation Exempt (LLFC 637 & 728) | E14: =IFERROR(IF(VLOOKUP($A14,'Annex 2 EHV charges'!$D:$O,9,FALSE)=0,"",VLOOKUP($A14,'Annex 2 EHV charges'!$D:$O,9,FALSE)),"") | F14: =IFERROR(IF(VLOOKUP($A14,'Annex 2 EHV charges'!$D:$O,10,FALSE)=0,"",VLOOKUP($A14,'Annex 2 EHV charges'!$D:$O,10,FALSE)),"") | G14: =IFERROR(IF(VLOOKUP($A14,'Annex 2 EHV charges'!$D:$O,11,FALSE)=0,"",VLOOKUP($A14,'Annex 2 EHV charges'!$D:$O,11,FALSE)),"") | H14: =IFERROR(IF(VLOOKUP($A14,'Annex 2 EHV charges'!$D:$O,12,FALSE)=0,"",VLOOKUP($A14,'Annex 2 EHV charges'!$D:$O,12,FALSE)),"")
A15: {=IFERROR(INDEX('Annex 2 EHV charges'!$D$10:$D$150, MATCH(0, IF(('Annex 2 EHV charges'!$D$10:$D$150=""),1, COUNTIF(A$4:$A14, 'Annex 2 EHV charges'!$D$10:$D$150)), 0)),"")} -> 759 | B15: =IF($A15="","",VLOOKUP($A15,'Annex 2 EHV charges'!$D:$O,2,0)) -> 759 | C15: =IF($A15="","",VLOOKUP($A15,'Annex 2 EHV charges'!$D:$O,3,0)) -> 1574000275033 | D15: =IF($A15="","",VLOOKUP($A15,'Annex 2 EHV charges'!$D:$O,4,0)) -> EHV Site Specific (LLFC 680 & 759) | E15: =IFERROR(IF(VLOOKUP($A15,'Annex 2 EHV charges'!$D:$O,9,FALSE)=0,"",VLOOKUP($A15,'Annex 2 EHV charges'!$D:$O,9,FALSE)),"") | F15: =IFERROR(IF(VLOOKUP($A15,'Annex 2 EHV charges'!$D:$O,10,FALSE)=0,"",VLOOKUP($A15,'Annex 2 EHV charges'!$D:$O,10,FALSE)),"") -> 125.26 | G15: =IFERROR(IF(VLOOKUP($A15,'Annex 2 EHV charges'!$D:$O,11,FALSE)=0,"",VLOOKUP($A15,'Annex 2 EHV charges'!$D:$O,11,FALSE)),"") -> 0.05 | H15: =IFERROR(IF(VLOOKUP($A15,'Annex 2 EHV charges'!$D:$O,12,FALSE)=0,"",VLOOKUP($A15,'Annex 2 EHV charges'!$D:$O,12,FALSE)),"") -> 0.05
A16: {=IFERROR(INDEX('Annex 2 EHV charges'!$D$10:$D$150, MATCH(0, IF(('Annex 2 EHV charges'!$D$10:$D$150=""),1, COUNTIF(A$4:$A15, 'Annex 2 EHV charges'!$D$10:$D$150)), 0)),"")} -> 760 | B16: =IF($A16="","",VLOOKUP($A16,'Annex 2 EHV charges'!$D:$O,2,0)) -> 760 | C16: =IF($A16="","",VLOOKUP($A16,'Annex 2 EHV charges'!$D:$O,3,0)) -> 1574000283735 | D16: =IF($A16="","",VLOOKUP($A16,'Annex 2 EHV charges'!$D:$O,4,0)) -> EHV Site Specific (LLFC 681 & 760) | E16: =IFERROR(IF(VLOOKUP($A16,'Annex 2 EHV charges'!$D:$O,9,FALSE)=0,"",VLOOKUP($A16,'Annex 2 EHV charges'!$D:$O,9,FALSE)),"") | F16: =IFERROR(IF(VLOOKUP($A16,'Annex 2 EHV charges'!$D:$O,10,FALSE)=0,"",VLOOKUP($A16,'Annex 2 EHV charges'!$D:$O,10,FALSE)),"") -> 4277.3 | G16: =IFERROR(IF(VLOOKUP($A16,'Annex 2 EHV charges'!$D:$O,11,FALSE)=0,"",VLOOKUP($A16,'Annex 2 EHV charges'!$D:$O,11,FALSE)),"") -> 0.05 | H16: =IFERROR(IF(VLOOKUP($A16,'Annex 2 EHV charges'!$D:$O,12,FALSE)=0,"",VLOOKUP($A16,'Annex 2 EHV charges'!$D:$O,12,FALSE)),"") -> 0.05
... A39: {=IFERROR(INDEX('Annex 2 EHV charges'!$D$10:$D$150, MATCH(0, IF(('Annex 2 EHV charges'!$D$10:$D$150=""),1, COUNTIF(A$4:$A38, 'Annex 2 EHV charges'!$D$10:$D$150)), 0)),"")} -> 808 | B39: =IF($A39="","",VLOOKUP($A39,'Annex 2 EHV charges'!$D:$O,2,0)) -> 808 | C39: =IF($A39="","",VLOOKUP($A39,'Annex 2 EHV charges'!$D:$O,3,0)) -> 1574000328094 | D39: =IF($A39="","",VLOOKUP($A39,'Annex 2 EHV charges'!$D:$O,4,0)) -> EHV Site Specific (LLFC 566 & 808) | E39: =IFERROR(IF(VLOOKUP($A39,'Annex 2 EHV charges'!$D:$O,9,FALSE)=0,"",VLOOKUP($A39,'Annex 2 EHV charges'!$D:$O,9,FALSE)),"") -> -0.014 | F39: =IFERROR(IF(VLOOKUP($A39,'Annex 2 EHV charges'!$D:$O,10,FALSE)=0,"",VLOOKUP($A39,'Annex 2 EHV charges'!$D:$O,10,FALSE)),"") -> 1990.84 | G39: =IFERROR(IF(VLOOKUP($A39,'Annex 2 EHV charges'!$D:$O,11,FALSE)=0,"",VLOOKUP($A39,'Annex 2 EHV charges'!$D:$O,11,FALSE)),"") -> 0.05 | H39: =IFERROR(IF(VLOOKUP($A39,'Annex 2 EHV charges'!$D:$O,12,FALSE)=0,"",VLOOKUP($A39,'Annex 2 EHV charges'!$D:$O,12,FALSE)),"") -> 0.05

Sheet Annex 3 Preserved charges
A1: Back to Overview
A2: =Overview!B4& " - Effective from "&Overview!D4&" - "&Overview!E4&" LV and HV tariffs" -> Northern Powergrid (Northeast) Ltd - Effective from 1 April 2019 - Final LV and HV tariffs
A3: NHH preserved charges/additional LLFCs
B4: Closed LLFCs | C4: PCs | D4: Unit charge 1 (NHH) p/kWh | E4: Unit charge 2 (NHH) p/kWh | F4: Fixed charge p/MPAN/day
A6: Notes: | B6: Unit time periods are as specified in the SSC.
A11: HH preserved charges/additional LLFCs
B12: Closed LLFCs | C12: PCs | D12: Red/black charge (HH) p/kWh | E12: Amber/yellow charge (HH) p/kWh | F12: Green charge (HH) p/kWh | G12: Fixed charge p/MPAN/day | H12: Capacity charge p/kVA/day | I12: Exceeded capacity charge p/kVA/day | J12: Reactive power charge p/kVArh
A14: Notes: | B14: Time periods
B15: Unit charges in the red time band apply – between 16:00 and 19:30, Monday to Friday including bank holidays.
B16: Unit charges in the amber time band apply – between 08:00 and 16:00; and between 19:30 and 22:00, Monday to Friday including bank holidays.
B17: Unit charges in the green time band apply – between 00:00 and 08:00; and between 22:00 and 24:00, Monday to Friday including bank holidays, and between 00:00 and 24:00 Saturday and Sunday.
B18: All times are UK clock-time.

Sheet Annex 4 LDNO charges
A1: Back to Overview
A2: =Overview!B4& " - Effective from "&Overview!D4&" - "&Overview!E4&" LDNO tariffs" -> Northern Powergrid (Northeast) Ltd - Effective from 1 April 2019 - Final LDNO tariffs
A4: Time Bands for Half Hourly Metered Properties | F4: Time Bands for Half Hourly Unmetered Properties
A5: Time periods | B5: Red Time Band | C5: Amber Time Band | D5: Green Time Band | H5: Black Time Band | I5: Yellow Time Band | J5: Green Time Band
A6: Monday to Friday (Including Bank Holidays) All Year | B6: 16:00 to 19:30 | C6: 08:00 to 16:00 19:30 to 22:00 | D6: 00:00 to 08:00 22:00 to 24:00 | F6: Monday to Friday (Including Bank Holidays) November to February Inclusive | H6: 16:00 to 19:30 | I6: 08:00 to 16:00 19:30 to 22:00 | J6: 00:00 to 08:00 22:00 to 24:00
A7: Saturday and Sunday All Year | D7: 00:00 to 24:00 | F7: Monday to Friday (Including Bank Holidays) April to October Inclusive and March | I7: 08:00 to 22:00 | J7: 00:00 to 08:00 22:00 to 24:00
A8: Notes | B8: All the above times are in UK Clock time | F8: Saturday and Sunday All year | J8: 00:00 to 24:00
F9: Notes | H9: All the above times are in UK Clock time
A11: Tariff name | B11: Unique billing identifier | C11: PCs | D11: ='Annex 1 LV and HV charges'!D11 -> Unit charge 1 (NHH) or red/black charge (HH) p/kWh | E11: ='Annex 1 LV and HV charges'!E11 -> Unit charge 2 (NHH) or amber/yellow charge (HH) p/kWh | F11: ='Annex 1 LV and HV charges'!F11 -> Green charge(HH) p/kWh | G11: ='Annex 1 LV and HV charges'!G11 -> Fixed charge p/MPAN/day | H11: ='Annex 1 LV and HV charges'!H11 -> Capacity charge p/kVA/day | I11: ='Annex 1 LV and HV charges'!I11 -> Exceeded capacity charge p/kVA/day | J11: ='Annex 1 LV and HV charges'!J11 -> Reactive power charge p/kVArh
A12: LDNO LV: Domestic Unrestricted | B12: 150 | C12: 1 | D12: 1.412 | E12: 0 | F12: 0 | G12: 3.29 | H12: 0 | I12: 0 | J12: 0
A13: LDNO LV: Domestic Two Rate | B13: 151 | C13: 2 | D13: 1.603 | E13: 0.678 | F13: 0 | G13: 3.29 | H13: 0 | I13: 0 | J13: 0
A14: LDNO LV: Domestic Off Peak (related MPAN) | B14: 152 | C14: 2 | D14: 0.749 | E14: 0 | F14: 0 | G14: 0 | H14: 0 | I14: 0 | J14: 0
A15: LDNO LV: Small Non Domestic Unrestricted | B15: 153 | C15: 3 | D15: 1.426 | E15: 0 | F15: 0 | G15: 3.5 | H15: 0 | I15: 0 | J15: 0
A16: LDNO LV: Small Non Domestic Two Rate | B16: 154 | C16: 4 | D16: 1.559 | E16: 0.699 | F16: 0 | G16: 3.5 | H16: 0 | I16: 0 | J16: 0
A17: LDNO LV: Small Non Domestic Off Peak (related MPAN) | B17: 155 | C17: 4 | D17: 0.786 | E17: 0 | F17: 0 | G17: 0 | H17: 0 | I17: 0 | J17: 0
A18: LDNO LV: LV Medium Non-Domestic | B18: 156 | C18: 5-8 | D18: 1.373 | E18: 0.671 | F18: 0 | G18: 18.28 | H18: 0 | I18: 0 | J18: 0
A19: LDNO LV: LV Network Domestic | B19: 199 | C19: 0 | D19: 4.536 | E19: 1.145 | F19: 0.67 | G19: 3.29 | H19: 0 | I19: 0 | J19: 0
A20: LDNO LV: LV Network Non-Domestic Non-CT | B20: 206 | C20: 0 | D20: 4.756 | E20: 1.174 | F20: 0.671 | G20: 3.5 | H20: 0 | I20: 0 | J20: 0
A21: LDNO LV: LV HH Metered | B21: 157 | C21: 0 | D21: 3.351 | E21: 0.984 | F21: 0.659 | G21: 9.53 | H21: 1.06 | I21: 2.48 | J21: 0.1
A22: LDNO LV: NHH UMS category A | B22: 37 | C22: 8 | D22: 1.182 | E22: 0 | F22: 0 | G22: 0 | H22: 0 | I22: 0 | J22: 0
A23: LDNO LV: NHH UMS category B | B23: 38 | C23: 1 | D23: 1.369 | E23: 0 | F23: 0 | G23: 0 | H23: 0 | I23: 0 | J23: 0
A24: LDNO LV: NHH UMS category C | B24: 39 | C24: 1 | D24: 1.989 | E24: 0 | F24: 0 | G24: 0 | H24: 0 | I24: 0 | J24: 0
A25: LDNO LV: NHH UMS category D | B25: 40 | C25: 1 | D25: 1.056 | E25: 0 | F25: 0 | G25: 0 | H25: 0 | I25: 0 | J25: 0
A26: LDNO LV: LV UMS (Pseudo HH Metered) | B26: 170 | C26: 0 | D26: 11.021 | E26: 1.088 | F26: 0.667 | G26: 0 | H26: 0 | I26: 0 | J26: 0
A27: LDNO LV: LV Generation NHH or Aggregate HH | B27: 172 | C27: 8&0 | D27: -0.671 | E27: 0 | F27: 0 | G27: 0 | H27: 0 | I27: 0 | J27: 0
A28: LDNO LV: LV Generation Intermittent | B28: 173 | C28: 0 | D28: -0.671 | E28: 0 | F28: 0 | G28: 0 | H28: 0 | I28: 0 | J28: 0.141
A29: LDNO LV: LV Generation Non-Intermittent | B29: 174 | C29: 0 | D29: -4.445 | E29: -0.583 | F29: -0.042 | G29: 0 | H29: 0 | I29: 0 | J29: 0.141
A30: LDNO HV: Domestic Unrestricted | B30: 158 | C30: 1 | D30: 0.858 | E30: 0 | F30: 0 | G30: 2 | H30: 0 | I30: 0 | J30: 0
A31: LDNO HV: Domestic Two Rate | B31: 159 | C31: 2 | D31: 0.975 | E31: 0.412 | F31: 0 | G31: 2 | H31: 0 | I31: 0 | J31: 0
A32: LDNO HV: Domestic Off Peak (related MPAN) | B32: 160 | C32: 2 | D32: 0.456 | E32: 0 | F32: 0 | G32: 0 | H32: 0 | I32: 0 | J32: 0
A33: LDNO HV: Small Non Domestic Unrestricted | B33: 161 | C33: 3 | D33: 0.867 | E33: 0 | F33: 0 | G33: 2.13 | H33: 0 | I33: 0 | J33: 0
A34: LDNO HV: Small Non Domestic Two Rate | B34: 162 | C34: 4 | D34: 0.948 | E34: 0.425 | F34: 0 | G34: 2.13 | H34: 0 | I34: 0 | J34: 0
A35: LDNO HV: Small Non Domestic Off Peak (related MPAN) | B35: 163 | C35: 4 | D35: 0.478 | E35: 0 | F35: 0 | G35: 0 | H35: 0 | I35: 0 | J35: 0
A36: LDNO HV: LV Medium Non-Domestic | B36: 164 | C36: 5-8 | D36: 0.835 | E36: 0.408 | F36: 0 | G36: 11.11 | H36: 0 | I36: 0 | J36: 0
A37: LDNO HV: LV Network Domestic | B37: 207 | C37: 0 | D37: 2.758 | E37: 0.696 | F37: 0.407 | G37: 2 | H37: 0 | I37: 0 | J37: 0
A38: LDNO HV: LV Network Non-Domestic Non-CT | B38: 208 | C38: 0 | D38: 2.892 | E38: 0.714 | F38: 0.408 | G38: 2.13 | H38: 0 | I38: 0 | J38: 0
A39: LDNO HV: LV HH Metered | B39: 165 | C39: 0 | D39: 2.037 | E39: 0.598 | F39: 0.401 | G39: 5.8 | H39: 0.65 | I39: 1.51 | J39: 0.061
A40: LDNO HV: LV Sub HH Metered | B40: 166 | C40: 0 | D40: 2.457 | E40: 0.869 | F40: 0.665 | G40: 9.74 | H40: 1.53 | I40: 2.52 | J40: 0.059
A41: LDNO HV: HV HH Metered | B41: 167 | C41: 0 | D41: 2.46 | E41: 0.99 | F41: 0.814 | G41: 113.79 | H41: 1.8 | I41: 3.25 | J41: 0.05
A42: LDNO HV: NHH UMS category A | B42: 41 | C42: 8 | D42: 0.719 | E42: 0 | F42: 0 | G42: 0 | H42: 0 | I42: 0 | J42: 0
A43: LDNO HV: NHH UMS category B | B43: 42 | C43: 1 | D43: 0.832 | E43: 0 | F43: 0 | G43: 0 | H43: 0 | I43: 0 | J43: 0
A44: LDNO HV: NHH UMS category C | B44: 43 | C44: 1 | D44: 1.209 | E44: 0 | F44: 0 | G44: 0 | H44: 0 | I44: 0 | J44: 0
A45: LDNO HV: NHH UMS category D | B45: 44 | C45: 1 | D45: 0.642 | E45: 0 | F45: 0 | G45: 0 | H45: 0 | I45: 0 | J45: 0
A46: LDNO HV: LV UMS (Pseudo HH Metered) | B46: 171 | C46: 0 | D46: 6.702 | E46: 0.662 | F46: 0.405 | G46: 0 | H46: 0 | I46: 0 | J46: 0
A47: LDNO HV: LV Generation NHH or Aggregate HH | B47: 175 | C47: 8&0 | D47: -0.671 | E47: 0 | F47: 0 | G47: 0 | H47: 0 | I47: 0 | J47: 0
A48: LDNO HV: LV Sub Generation NHH | B48: 176 | C48: 8 | D48: -0.595 | E48: 0 | F48: 0 | G48: 0 | H48: 0 | I48: 0 | J48: 0
A49: LDNO HV: LV Generation Intermittent | B49: 177 | C49: 0 | D49: -0.671 | E49: 0 | F49: 0 | G49: 0 | H49: 0 | I49: 0 | J49: 0.141
A50: LDNO HV: LV Generation Non-Intermittent | B50: 178 | C50: 0 | D50: -4.445 | E50: -0.583 | F50: -0.042 | G50: 0 | H50: 0 | I50: 0 | J50: 0.141
A51: LDNO HV: LV Sub Generation Intermittent | B51: 179 | C51: 0 | D51: -0.595 | E51: 0 | F51: 0 | G51: 0 | H51: 0 | I51: 0 | J51: 0.134
A52: LDNO HV: LV Sub Generation Non-Intermittent | B52: 180 | C52: 0 | D52: -3.947 | E52: -0.514 | F52: -0.038 | G52: 0 | H52: 0 | I52: 0 | J52: 0.134
A53: LDNO HV: HV Generation Intermittent | B53: 181 | C53: 0 | D53: -0.379 | E53: 0 | F53: 0 | G53: 0 | H53: 0 | I53: 0 | J53: 0.104
A54: LDNO HV: HV Generation Non-Intermittent | B54: 182 | C54: 0 | D54: -2.548 | E54: -0.311 | F54: -0.027 | G54: 0 | H54: 0 | I54: 0 | J54: 0.104
A55: LDNO HVplus: Domestic Unrestricted | B55: 50 | C55: 1 | D55: 0.653 | E55: 0 | F55: 0 | G55: 1.52 | H55: 0 | I55: 0 | J55: 0
A56: LDNO HVplus: Domestic Two Rate | B56: 51 | C56: 2 | D56: 0.741 | E56: 0.314 | F56: 0 | G56: 1.52 | H56: 0 | I56: 0 | J56: 0
A57: LDNO HVplus: Domestic Off Peak (related MPAN) | B57: 52 | C57: 2 | D57: 0.347 | E57: 0 | F57: 0 | G57: 0 | H57: 0 | I57: 0 | J57: 0
A58: LDNO HVplus: Small Non Domestic Unrestricted | B58: 53 | C58: 3 | D58: 0.66 | E58: 0 | F58: 0 | G58: 1.62 | H58: 0 | I58: 0 | J58: 0
A59: LDNO HVplus: Small Non Domestic Two Rate | B59: 54 | C59: 4 | D59: 0.721 | E59: 0.323 | F59: 0 | G59: 1.62 | H59: 0 | I59: 0 | J59: 0
A60: LDNO HVplus: Small Non Domestic Off Peak (related MPAN) | B60: 55 | C60: 4 | D60: 0.363 | E60: 0 | F60: 0 | G60: 0 | H60: 0 | I60: 0 | J60: 0
A61: LDNO HVplus: LV Medium Non-Domestic | B61: 56 | C61: 5-8 | D61: 0.635 | E61: 0.31 | F61: 0 | G61: 8.45 | H61: 0 | I61: 0 | J61: 0
A62: LDNO HVplus: LV Sub Medium Non-Domestic | B62: 0 | C62: 5-8 | D62: 1.077 | E62: 0.53 | F62: 0 | G62: 14.02 | H62: 0 | I62: 0 | J62: 0
A63: LDNO HVplus: HV Medium Non-Domestic | B63: 0 | C63: 5-8 | D63: 0.925 | E63: 0.617 | F63: 0 | G63: 159.03 | H63: 0 | I63: 0 | J63: 0
A64: LDNO HVplus: LV Network Domestic | B64: 209 | C64: 0 | D64: 2.098 | E64: 0.529 | F64: 0.31 | G64: 1.52 | H64: 0 | I64: 0 | J64: 0
A65: LDNO HVplus: LV Network Non-Domestic Non-CT | B65: 210 | C65: 0 | D65: 2.199 | E65: 0.543 | F65: 0.31 | G65: 1.62 | H65: 0 | I65: 0 | J65: 0
A66: LDNO HVplus: LV HH Metered | B66: 57 | C66: 0 | D66: 1.549 | E66: 0.455 | F66: 0.305 | G66: 4.41 | H66: 0.49 | I66: 1.15 | J66: 0.046
A67: LDNO HVplus: LV Sub HH Metered | B67: 58 | C67: 0 | D67: 1.844 | E67: 0.652 | F67: 0.499 | G67: 7.31 | H67: 1.14 | I67: 1.89 | J67: 0.045
A68: LDNO HVplus: HV HH Metered | B68: 59 | C68: 0 | D68: 1.827 | E68: 0.735 | F68: 0.604 | G68: 84.52 | H68: 1.34 | I68: 2.42 | J68: 0.037
A69: LDNO HVplus: NHH UMS category A | B69: 45 | C69: 8 | D69: 0.547 | E69: 0 | F69: 0 | G69: 0 | H69: 0 | I69: 0 | J69: 0
A70: LDNO HVplus: NHH UMS category B | B70: 46 | C70: 1 | D70: 0.633 | E70: 0 | F70: 0 | G70: 0 | H70: 0 | I70: 0 | J70: 0
A71: LDNO HVplus: NHH UMS category C | B71: 47 | C71: 1 | D71: 0.92 | E71: 0 | F71: 0 | G71: 0 | H71: 0 | I71: 0 | J71: 0
A72: LDNO HVplus: NHH UMS category D | B72: 48 | C72: 1 | D72: 0.488 | E72: 0 | F72: 0 | G72: 0 | H72: 0 | I72: 0 | J72: 0
A73: LDNO HVplus: LV UMS (Pseudo HH Metered) | B73: 61 | C73: 0 | D73: 5.096 | E73: 0.503 | F73: 0.308 | G73: 0 | H73: 0 | I73: 0 | J73: 0
A74: LDNO HVplus: LV Generation NHH or Aggregate HH | B74: 62 | C74: 8 | D74: -0.309 | E74: 0 | F74: 0 | G74: 0 | H74: 0 | I74: 0 | J74: 0
A75: LDNO HVplus: LV Sub Generation NHH | B75: 63 | C75: 8 | D75: -0.333 | E75: 0 | F75: 0 | G75: 0 | H75: 0 | I75: 0 | J75: 0
... A87: LDNO EHV: Small Non Domestic Off Peak (related MPAN) | B87: 75 | C87: 4 | D87: 0.253 | E87: 0 | F87: 0 | G87: 0 | H87: 0 | I87: 0 | J87: 0
A88: LDNO EHV: LV Medium Non-Domestic | B88: 76 | C88: 5-8 | D88: 0.441 | E88: 0.216 | F88: 0 | G88: 5.88 | H88: 0 | I88: 0 | J88: 0
A89: LDNO EHV: LV Sub Medium Non-Domestic | B89: 0 | C89: 5-8 | D89: 0.749 | E89: 0.368 | F89: 0 | G89: 9.75 | H89: 0 | I89: 0 | J89: 0
A90: LDNO EHV: HV Medium Non-Domestic | B90: 0 | C90: 5-8 | D90: 0.643 | E90: 0.429 | F90: 0 | G90: 110.55 | H90: 0 | I90: 0 | J90: 0
A91: LDNO EHV: LV Network Domestic | B91: 211 | C91: 0 | D91: 1.458 | E91: 0.368 | F91: 0.215 | G91: 1.06 | H91: 0 | I91: 0 | J91: 0
A92: LDNO EHV: LV Network Non-Domestic Non-CT | B92: 212 | C92: 0 | D92: 1.529 | E92: 0.377 | F92: 0.216 | G92: 1.13 | H92: 0 | I92: 0 | J92: 0
A93: LDNO EHV: LV HH Metered | B93: 77 | C93: 0 | D93: 1.077 | E93: 0.316 | F93: 0.212 | G93: 3.06 | H93: 0.34 | I93: 0.8 | J93: 0.032
A94: LDNO EHV: LV Sub HH Metered | B94: 78 | C94: 0 | D94: 1.282 | E94: 0.454 | F94: 0.347 | G94: 5.08 | H94: 0.8 | I94: 1.31 | J94: 0.031
A95: LDNO EHV: HV HH Metered | B95: 79 | C95: 0 | D95: 1.27 | E95: 0.511 | F95: 0.42 | G95: 58.75 | H95: 0.93 | I95: 1.68 | J95: 0.026
A96: LDNO EHV: NHH UMS category A | B96: 183 | C96: 8 | D96: 0.38 | E96: 0 | F96: 0 | G96: 0 | H96: 0 | I96: 0 | J96: 0
A97: LDNO EHV: NHH UMS category B | B97: 184 | C97: 1 | D97: 0.44 | E97: 0 | F97: 0 | G97: 0 | H97: 0 | I97: 0 | J97: 0
A98: LDNO EHV: NHH UMS category C | B98: 185 | C98: 1 | D98: 0.639 | E98: 0 | F98: 0 | G98: 0 | H98: 0 | I98: 0 | J98: 0
A99: LDNO EHV: NHH UMS category D | B99: 186 | C99: 1 | D99: 0.34 | E99: 0 | F99: 0 | G99: 0 | H99: 0 | I99: 0 | J99: 0
A100: LDNO EHV: LV UMS (Pseudo HH Metered) | B100: 81 | C100: 0 | D100: 3.543 | E100: 0.35 | F100: 0.214 | G100: 0 | H100: 0 | I100: 0 | J100: 0
A101: LDNO EHV: LV Generation NHH or Aggregate HH | B101: 82 | C101: 8 | D101: -0.214 | E101: 0 | F101: 0 | G101: 0 | H101: 0 | I101: 0 | J101: 0
A102: LDNO EHV: LV Sub Generation NHH | B102: 83 | C102: 8 | D102: -0.231 | E102: 0 | F102: 0 | G102: 0 | H102: 0 | I102: 0 | J102: 0
... A114: LDNO 132kV/EHV: Small Non Domestic Off Peak (related MPAN) | B114: 95 | C114: 4 | D114: 0.167 | E114: 0 | F114: 0 | G114: 0 | H114: 0 | I114: 0 | J114: 0
A115: LDNO 132kV/EHV: LV Medium Non-Domestic | B115: 96 | C115: 5-8 | D115: 0.292 | E115: 0.143 | F115: 0 | G115: 3.89 | H115: 0 | I115: 0 | J115: 0
A116: LDNO 132kV/EHV: LV Sub Medium Non-Domestic | B116: 0 | C116: 5-8 | D116: 0.496 | E116: 0.244 | F116: 0 | G116: 6.46 | H116: 0 | I116: 0 | J116: 0
A117: LDNO 132kV/EHV: HV Medium Non-Domestic | B117: 0 | C117: 5-8 | D117: 0.426 | E117: 0.284 | F117: 0 | G117: 73.22 | H117: 0 | I117: 0 | J117: 0
A118: LDNO 132kV/EHV: LV Network Domestic | B118: 213 | C118: 0 | D118: 0.966 | E118: 0.244 | F118: 0.143 | G118: 0.7 | H118: 0 | I118: 0 | J118: 0
A119: LDNO 132kV/EHV: LV Network Non-Domestic Non-CT | B119: 214 | C119: 0 | D119: 1.013 | E119: 0.25 | F119: 0.143 | G119: 0.75 | H119: 0 | I119: 0 | J119: 0
A120: LDNO 132kV/EHV: LV HH Metered | B120: 97 | C120: 0 | D120: 0.713 | E120: 0.209 | F120: 0.14 | G120: 2.03 | H120: 0.23 | I120: 0.53 | J120: 0.021
A121: LDNO 132kV/EHV: LV Sub HH Metered | B121: 98 | C121: 0 | D121: 0.849 | E121: 0.3 | F121: 0.23 | G121: 3.37 | H121: 0.53 | I121: 0.87 | J121: 0.021
A122: LDNO 132kV/EHV: HV HH Metered | B122: 99 | C122: 0 | D122: 0.841 | E122: 0.338 | F122: 0.278 | G122: 38.91 | H122: 0.62 | I122: 1.11 | J122: 0.017
A123: LDNO 132kV/EHV: NHH UMS category A | B123: 187 | C123: 8 | D123: 0.252 | E123: 0 | F123: 0 | G123: 0 | H123: 0 | I123: 0 | J123: 0
A124: LDNO 132kV/EHV: NHH UMS category B | B124: 188 | C124: 1 | D124: 0.291 | E124: 0 | F124: 0 | G124: 0 | H124: 0 | I124: 0 | J124: 0
...

Sheet Annex 5 LLFs
A1: Back to Overview
A2: This table has intentionally been left blank. The line loss factors that are approved by the BSC Panel for the applicable year and consequently published on the Elexon website will take precedence and be used in Settlement. This annex will be re-published once these values are available.
A3: =Overview!B4& " - Illustrative LLFs for year beginning "&Overview!D4 -> Northern Powergrid (Northeast) Ltd - Illustrative LLFs for year beginning 1 April 2019
A4: Time periods | B4: Period 1 | C4: Period 2 | D4: Period 3 | E4: Period 4
A5: Monday – Friday (Apr-Oct) | B5: 0 | C5: 0 | D5: 00:30 – 07:30 | E5: 00:00 – 00:30 07:30 – 24:00
A6: Monday – Friday (Nov) | B6: 0 | C6: 07:30 – 20:00 | D6: 00:30 – 07:30 | E6: 00:00 – 00:30 20:00 – 24:00
A7: Monday – Friday (Dec – Feb) | B7: 16:30 – 18:30 | C7: 07:30 – 16:30 18:30 – 20:00 | D7: 00:30 – 07:30 | E7: 00:00 – 00:30 20:00 – 24:00
A8: Monday – Friday (Mar) | B8: 0 | C8: 0 | D8: 00:30 – 07:30 | E8: 00:00 – 00:30 07:30 – 24:00
A9: Saturday and Sunday All Year | B9: 0 | C9: 0 | D9: 00:30 – 07:30 | E9: 00:00 – 00:30 07:30 – 24:00
A10: Notes | B10: All the above times are in UK Clock time
A13: Generic demand and generation LLFs
A14: Metered voltage, respective periods and associated LLFCs
A15: Metered voltage | B15: Period 1 | C15: Period 2 | D15: Period 3 | E15: Period 4 | F15: Associated LLFC
A16: Low Voltage Network | B16: 1.086 | C16: 1.079 | D16: 1.066 | E16: 1.07 | F16: 1, 12, 2, 203, 204, 205, 249, 251, 257, 278, 392, 394, 506, 507, 508, 509, 554, 555, 774, 792, 794, 998, 999
A17: Low Voltage Substation | B17: 1.04 | C17: 1.039 | D17: 1.042 | E17: 1.039 | F17: 265, 293, 393, 395, 776, 793, 795
A18: High Voltage Network | B18: 1.025 | C18: 1.023 | D18: 1.019 | E18: 1.021 | F18: 301, 304, 396, 398, 796, 798
A19: High Voltage Substation | B19: 1.015 | C19: 1.015 | D19: 1.014 | E19: 1.014 | F19: 691, 692, 693, 694, 695, 696, 697, 698, 699, 700, 777, 778, 779, 780, 781
A20: Greater than 22kV connected - generation | B20: 1.01 | C20: 1.01 | D20: 1.008 | E20: 1.009 | F20: 564, 568, 569, 570, 571, 572, 573, 574, 575, 576, 577, 578, 579, 613
A21: Greater than 22kV connected - demand | B21: 1.01 | C21: 1.01 | D21: 1.008 | E21: 1.009 | F21: 803, 810, 811, 812, 813, 814, 815, 816, 817, 818, 819, 820, 821, 822, 823, 824, 825
A23: EHV site specific LLFs
A24: Demand
A25: Site | B25: Period 1 | C25: Period 2 | D25: Period 3 | E25: Period 4 | F25: Associated LLFC
A26: Site 1 | B26: 1.013 | C26: 1.009 | D26: 1.006 | E26: 1.006 | F26: 601
A27: Site 2 | B27: 1.002 | C27: 1.002 | D27: 1.002 | E27: 1.002 | F27: 603
A28: Site 3 | B28: 1.003 | C28: 1.003 | D28: 1.003 | E28: 1.003 | F28: 604
A29: Site 4 | B29: 1.013 | C29: 1.013 | D29: 1.018 | E29: 1.013 | F29: 605
A30: Site 5 | B30: 1.021 | C30: 1.022 | D30: 1.055 | E30: 1.023 | F30: 606
A31: Site 6 | B31: 1.022 | C31: 1.022 | D31: 1.044 | E31: 1.022 | F31: 607
A32: Site 7 | B32: 1.037 | C32: 1.049 | D32: 1.157 | E32: 1.055 | F32: 608
A33: Site 8 | B33: 1.006 | C33: 1.005 | D33: 1.006 | E33: 1.006 | F33: 609
A34: Site 9 | B34: 1.014 | C34: 1.013 | D34: 1.013 | E34: 1.014 | F34: 611
A35: Site 10 | B35: 1.006 | C35: 1.006 | D35: 1.004 | E35: 1.005 | F35: 612
A36: Site 11 | B36: 1.007 | C36: 1.007 | D36: 1.008 | E36: 1.009 | F36: 614
A37: Site 12 | B37: 1.005 | C37: 1.005 | D37: 1.004 | E37: 1.005 | F37: 615
... A80: Site 55 | B80: 1.01 | C80: 1.01 | D80: 1.008 | E80: 1.009 | F80: 566
A82: EHV site specific LLFs
A83: Generation
A84: Site | B84: Period 1 | C84: Period 2 | D84: Period 3 | E84: Period 4 | F84: Associated LLFC
A85: Site 1 | B85: 1.013 | C85: 1.007 | D85: 1.004 | E85: 1.004 | F85: 701
A86: Site 2 | B86: 0.999 | C86: 0.998 | D86: 0.997 | E86: 0.998 | F86: 727
A87: Site 3 | B87: 1.007 | C87: 1.006 | D87: 1.003 | E87: 1.004 | F87: 704
A88: Site 4 | B88: 0.996 | C88: 0.997 | D88: 0.995 | E88: 0.995 | F88: 709
A89: Site 5 | B89: 1.02 | C89: 1.019 | D89: 1.015 | E89: 1.016 | F89: 710
A90: Site 6 | B90: 0.989 | C90: 0.99 | D90: 0.98 | E90: 0.985 | F90: 711
A91: Site 7 | B91: 1.01 | C91: 1.01 | D91: 1.008 | E91: 1.009 | F91: 804
A92: Site 8 | B92: 1.01 | C92: 1.01 | D92: 1.002 | E92: 1.006 | F92: 748
A93: Site 9 | B93: 1.013 | C93: 1.006 | D93: 1.003 | E93: 1.002 | F93: 729
A94: Site 10 | B94: 1 | C94: 1 | D94: 0.992 | E94: 0.992 | F94: 728
A95: Site 11 | B95: 1.005 | C95: 1.003 | D95: 1.001 | E95: 1.003 | F95: 759
A96: Site 12 | B96: 0.998 | C96: 0.998 | D96: 0.994 | E96: 0.995 | F96: 760
... A118: Site 34 | B118: 1.01 | C118: 1.01 | D118: 1.008 | E118: 1.009 | F118: 808

Sheet Annex 6 New or Amended EHV
A1: Back to Overview | H1: Note: The list of MPANs/MSIDs provided may be incomplete; the DNO reserves the right to apply the listed charges to any other MPANs/MSIDs associated with the site. If sites appear in both Annex 2 and Annex 6, the charges in Annex 6 take precedence. Where an existing Designated EHV Property is modified and energised in the charging year, we may revise the EDCM charges for the modified Designated EHV Property.
A2: Annex 6 - Charges for New or Amended Designated EHV Properties
A4: =Overview!B4& " - Effective from "&Overview!D4&" - "&Overview!E4&" new designated EHV charges" -> Northern Powergrid (Northeast) Ltd - Effective from 1 April 2019 - Final new designated EHV charges
A5: Effective from date | B5: Import Unique Identifier | C5: LLFC | D5: Import MPANs/MSIDs | E5: Export Unique Identifier | F5: LLFC | G5: Export MPANs/MSIDs | H5: Name | I5: ='Annex 2 EHV charges'!H9 -> Import Super Red unit charge (p/kWh) | J5: ='Annex 2 EHV charges'!I9 -> Import fixed charge (p/day) | K5: ='Annex 2 EHV charges'!J9 -> Import capacity charge (p/kVA/day) | L5: ='Annex 2 EHV charges'!K9 -> Import exceeded capacity charge (p/kVA/day) | M5: ='Annex 2 EHV charges'!L9 -> Export Super Red unit charge (p/kWh) | N5: ='Annex 2 EHV charges'!M9 -> Export fixed charge (p/day) | O5: ='Annex 2 EHV charges'!N9 -> Export capacity charge (p/kVA/day) | P5: ='Annex 2 EHV charges'!O9 -> Export exceeded capacity charge (p/kVA/day)
A17: =Overview!B4& " - Effective from "&Overview!D4&" - "&Overview!E4&" new designated EHV line loss factors" -> Northern Powergrid (Northeast) Ltd - Effective from 1 April 2019 - Final new designated EHV line loss factors
A18: Effective from date | B18: Import Unique Identifier | C18: LLFC | D18: Import MPANs/MSIDs | E18: Export Unique Identifier | F18: LLFC | G18: Export MPANs/MSIDs | H18: Name | I18: Import LLF period 1 | J18: Import LLF period 2 | K18: Import LLF period 3 | L18: Import LLF period 4 | M18: Import LLF period 5 | N18: Export LLF period 1 | O18: Export LLF period 2 | P18: Export LLF period 3 | Q18: Export LLF period 4 | R18: Export LLF period 5

Sheet Nodal prices
A1: Back to Overview
A2: =Overview!B4& " - Effective from "&Overview!D4&" - "&Overview!E4&" Nodal/Zonal charges" -> Northern Powergrid (Northeast) Ltd - Effective from 1 April 2019 - Final Nodal/Zonal charges
A3: Node/Zone ID | B3: Geographical name | C3: Local charge 1 £/kVA | D3: Remote charge 1 £/kVA
A4: Cramlington Biomass | B4: Blyth | C4: 0.039508918 | D4: 0.0034016663
A5: alcan | B5: Blyth | C5: 0 | D5: 0
A6: blyth offshore wf | B6: Blyth | C6: 0 | D6: 0
A7: lynemouth wf | B7: Blyth | C7: 0 | D7: 0
A8: middlemoor wf | B8: Blyth | C8: 2.3856557 | D8: -0.012133454
A9: north steads wf | B9: Blyth | C9: 2.3210547 | D9: -0.011859351
A10: sisters wf | B10: Blyth | C10: 2.3210547 | D10: -0.011859351
A11: wandylaw wf | B11: Blyth | C11: 2.3856706 | D11: -0.012133519
A12: alcan (1001) | B12: Blyth | C12: 0 | D12: 0.0014408679
A13: ashington (1002) | B13: Blyth | C13: 2.2323151 | D13: 1.7890227
A14: benton square (1008) | B14: Blyth | C14: 1.727197 | D14: 3.1196441
A15: cramlington t1 t3 (1015) | B15: Blyth | C15: 0.65691511 | D15: 0.046241662
... A246: west southwick (1062) | B246: West Boldon | C246: 0.08636522 | D246: 0.77185292

Sheet SSC TPR unit rate lookup
A1: Back to Overview
A28: Standard Settlement Configuration Id | B28: Time Pattern Regime Id | C28: Standard Settlement Configuration Desc | D28: Common Decode | G28: Change implemented | H28: Date | I28: Comments
A29: 3 | B29: 166 | C29: 10-hour OP | D29: O | H29: 40057 | I29: First published spreadsheet
A30: 4 | B30: 168 | C30: 10-hour OP | D30: O | G30: SSC 0330 charge rates corrected | H30: 40275 | I30: Previous Off-peak rate corrected to charge 2
A31: 5 | B31: 100 | C31: 10-hour OP + w/e | D31: O | G31: SSC 0250 charge rate corrected | H31: 40347 | I31: Previous rate 1 corrected to Off Peak O
A32: 6 | B32: 257 | C32: 10.5-hour OP | D32: O | G32: SSC 0134 charge rate corrected | H32: 41166 | I32: TPR 00101 corrected from Off Peak O to Rate 1
A33: 7 | B33: 158 | C33: 10.5-hour OP | D33: O | G33: New SSCs added | H33: 41178 | I33: New SSCs from 0953 added.
A34: 8 | B34: 159 | C34: 10.5-hour OP | D34: O | G34: SSC 0394 charge rate corrected | H34: 41758 | I34: TPR 01177 corrected to rate 2
A35: 9 | B35: 1111 | C35: 10.5-hour OP | D35: O | G35: Table reviewed and updated | H35: 41758 | I35: New SSCs from 0949 to 0952, 0975 & 0976 and 0982 & 0983 added.
A36: 10 | B36: 1104 | C36: 10.5-hour OP | D36: O | G36: Table reviewed and updated | H36: 41944 | I36: New SSCs from 0984 and 0985 added.
A37: 11 | B37: 1112 | C37: 10.5-hour OP | D37: O | G37: SSC 0313 charge code corrected | H37: 42081 | I37: TPR 01006 corrected to code O
A38: 12 | B38: 1116 | C38: 10.5-hour OP | D38: O | G38: SSC 0320 charge code corrected | H38: 42081 | I38: TPR 00072 corrected to code 2
A39: 13 | B39: 139 | C39: 11 Hour OP | D39: EMEB or MIDE only | G39: SSC 0781 charge code corrected | H39: 42081 | I39: TPR 00327 corrected to code O
A40: 15 | B40: 152 | C40: 11 Hour OP | D40: EMEB or MIDE only | G40: SSC 0935 charge code corrected | H40: 42081 | I40: TPR 00375 corrected to code 1 or Unsupported (SWAE and SWEB)
A41: 16 | B41: 113 | C41: 11.5-hour OP | D41: Unsupported (SWEB) | G41: SSC 0953 charge code corrected | H41: 42081 | I41: TPR 00424 corrected to code 1 or Unsupported (SWAE and SWEB)
... A74: 50 | B74: 14 | C74: 12-hour OP + w/e & Summer | D74: O | G74: SSC 0942 charge code corrected | H74: 42166 | I74: TPR 00400 corrected to code 1
A75: 51 | B75: 112 | C75: 12-hour night | D75: 1 | G75: SSC 0943 charge code corrected | H75: 42166 | I75: TPR 00404 corrected to code 1
A76: 51 | B76: 120 | C76: 12-hour night | D76: 2 | G76: SSC 0944 charge code corrected | H76: 42166 | I76: TPR 00406 corrected to code 1
A77: 52 | B77: 114 | C77: 12-hour OP | D77: EMEB or MIDE only | G77: SSC 0945 charge code corrected | H77: 42166 | I77: TPR 00408 corrected to code 1
A78: 53 | B78: 115 | C78: 12-hour OP | D78: EMEB or MIDE only | G78: SSC 0946 charge code corrected | H78: 42166 | I78: TPR 00410 corrected to code 1
A79: 55 | B79: 117 | C79: 12-hour OP | D79: EMEB or MIDE only | G79: SSC 0954 charge code corrected | H79: 42166 | I79: TPR 00426 corrected to code 1
A80: 56 | B80: 118 | C80: 12-hour OP | D80: EMEB or MIDE only | G80: SSC 0967 charge code corrected | H80: 42166 | I80: TPR 00442 corrected to code 1
A81: 57 | B81: 119 | C81: 12-hour OP | D81: O | G81: SSC 0970 charge code corrected | H81: 42166 | I81: TPR 00447 corrected to code 2
A82: 58 | B82: 21 | C82: Key Meter pseudo 2-rate | D82: 1 | G82: SSC 0970 charge code corrected | H82: 42166 | I82: TPR 00448 corrected to code 1
A83: 58 | B83: 175 | C83: Key Meter pseudo 2-rate | D83: 1 | G83: SSC 0971 charge code corrected | H83: 42166 | I83: TPR 00493 corrected to code 1
A84: 59 | B84: 121 | C84: 12-hour OP | D84: EMEB or MIDE only
A85: 60 | B85: 122 | C85: 12-hour OP | D85: O
A86: 62 | B86: 1119 | C86: 8-hour OP (see also SSC 427) | D86: 2 or Unsupported (SWEB)
A87: 63 | B87: 172 | C87: 9-hour OP | D87: EMEB or MIDE only
A88: 64 | B88: 1105 | C88: 12-hour OP | D88: O
A89: 65 | B89: 10 | C89: 12-hour OP + Summer | D89: O
A90: 66 | B90: 1106 | C90: 12-hour OP + Summer | D90: O
A91: 67 | B91: 102 | C91: 12.5-hour OP | D91: Unsupported (SWEB)
A92: 71 | B92: 109 | C92: 12.5-hour OP | D92: O
A93: 72 | B93: 111 | C93: 12.5-hour OP | D93: O
A94: 73 | B94: 156 | C94: 12.5-hour OP | D94: Unsupported (SWEB)
A95: 74 | B95: 17 | C95: 12.5-hour OP + Summer | D95: O
... A99: 78 | B99: 13 | C99: 12.5-hour OP + w/e & Summer | D99: O
A100: 79 | B100: 97 | C100: 14-hour E7 | D100: 2
A101: 79 | B101: 164 | C101: 14-hour E7 | D101: 1
A102: 80 | B102: 96 | C102: 14-hour Off Peak | D102: O
A103: 81 | B103: 60 | C103: 14-hour OP + Sun | D103: O
A104: 82 | B104: 83 | C104: 14.5-hour OP | D104: O
A105: 83 | B105: 84 | C105: 14.5-hour OP | D105: O
A106: 84 | B106: 85 | C106: 14.5-hour OP | D106: O
A107: 85 | B107: 86 | C107: 14.5-hour OP | D107: O
A108: 86 | B108: 1107 | C108: 14.5-hour OP | D108: O
A109: 87 | B109: 1109 | C109: 14.5-hour OP | D109: O
A110: 88 | B110: 1113 | C110: 14.5-hour OP | D110: O
A111: 91 | B111: 3 | C111: 14.5-hour OP + Summer | D111: O
A112: 92 | B112: 4 | C112: 14.5-hour OP + Summer | D112: O
A113: 93 | B113: 30 | C113: split 7-hour E7 | D113: 1
A114: 93 | B114: 214 | C114: split 7-hour E7 | D114: 2
A115: 94 | B115: 1108 | C115: 14.5-hour OP + Summer | D115: O
A116: 95 | B116: 1110 | C116: 14.5-hour OP + Summer | D116: O
A117: 96 | B117: 1114 | C117: 14.5-hour OP + Summer | D117: O
A118: 97 | B118: 54 | C118: 14.5-hour OP + w/e | D118: O
A119: 98 | B119: 12 | C119: 14.5-hour OP + w/e & Summer | D119: O
A120: 99 | B120: 75 | C120: 15-hour OP | D120: EMEB or MIDE only
A121: 100 | B121: 76 | C121: 15-hour OP | D121: EMEB or MIDE only
A122: 101 | B122: 7 | C122: 15-hour OP + w/e & Summer | D122: O
A123: 102 | B123: 8 | C123: 15-hour OP + w/e & Summer | D123: O
A124: 103 | B124: 9 | C124: 15-hour OP + w/e & Summer | D124: O
A125: 104 | B125: 61 | C125: 15.5-hour OP | D125: Unsupported (SWEB)
A126: 105 | B126: 65 | C126: 15.5-hour OP | D126: O
... A140: 120 | B140: 11 | C140: 9-hour OP | D140: O
A141: 121 | B141: 26 | C141: 2-rate terms | D141: 2
A142: 121 | B142: 224 | C142: 2-rate terms | D142: 1
A143: 122 | B143: 201 | C143: 2-rate SToD | D143: 1
A144: 122 | B144: 245 | C144: 2-rate SToD | D144: 2
A145: 123 | B145: 1307 | C145: 2-rate variable SToD | D145: 1
A146: 124 | B146: 1319 | C146: 2-rate variable SToD | D146: 1
A147: 125 | B147: 1315 | C147: 2-rate variable SToD | D147: 1
A148: 126 | B148: 1193 | C148: 7-hour E7 | D148: 1
A149: 126 | B149: 1194 | C149: 7-hour E7 | D149: 2
A150: 127 | B150: 80 | C150: 3-rate SToD | D150: Unsupported (SWEB)
A151: 127 | B151: 148 | C151: 3-rate SToD | D151: 1
A152: 127 | B152: 221 | C152: 3-rate SToD | D152: 2 or Unsupported (SWEB)
A153: 128 | B153: 1120 | C153: Dom/Non-dom Seasonal (link SSC 0342) | D153: 1
A154: 128 | B154: 1121 | C154: Dom/Non-dom Seasonal (link SSC 0342) | D154: 1
A155: 128 | B155: 1122 | C155: Dom/Non-dom Seasonal (link SSC 0342) | D155: 2
A156: 129 | B156: 169 | C156: 3-rate SToD | D156: 1
A157: 129 | B157: 202 | C157: 3-rate SToD | D157: 1
A158: 129 | B158: 222 | C158: 3-rate SToD | D158: 2
A159: 130 | B159: 1308 | C159: 3-rate variable | D159: 1
A160: 130 | B160: 1309 | C160: 3-rate variable | D160: 1
A161: 130 | B161: 1310 | C161: 3-rate variable | D161: 2
A162: 131 | B162: 1311 | C162: 3-rate variable | D162: 1
A163: 131 | B163: 1312 | C163: 3-rate variable | D163: 1
A164: 131 | B164: 1313 | C164: 3-rate variable | D164: 2
A165: 132 | B165: 92 | C165: 4-rate SToD | D165: EMEB or MIDE only
A166: 132 | B166: 210 | C166: 4-rate SToD | D166: 2
A167: 132 | B167: 234 | C167: 4-rate SToD | D167: EMEB or MIDE only
A168: 132 | B168: 236 | C168: 4-rate SToD | D168: EMEB or MIDE only
A169: 133 | B169: 92 | C169: 4-rate SToD | D169: 1
A170: 133 | B170: 210 | C170: 4-rate SToD | D170: 2
A171: 133 | B171: 233 | C171: 4-rate SToD | D171: 1
A172: 133 | B172: 246 | C172: 4-rate SToD | D172: 1
A173: 134 | B173: 101 | C173: 4-rate SToD | D173: 1
A174: 134 | B174: 210 | C174: 4-rate SToD | D174: 2
...

Sheet Charge Calculator
B1: Back to Overview
B2: =Overview!B4& " - Effective from "&Overview!D4&" - "&Overview!E4 -> Northern Powergrid (Northeast) Ltd - Effective from 1 April 2019 - Final
B4: LV and HV tariff calculator | L4: EHV site calculator
B5: Step 1, Choose your tariff using the drop down list in cell B10 | L5: Step 1, Choose your tariff using the drop down list in cell L10
B6: Step 2, After selecting a tariff in step 1, Cells C12-I12 will generate headings, please enter your consumption in cells C13:I13 underneath each heading generated (if no heading leave cell blank) | L6: Step 2, After selecting a tariff in step 1, Cells M12-T12 will generate headings, please enter your consumption in cells M13:T13 underneath each heading generated (if no heading leave cell blank)
B7: Step 3, Enter a forecast of consumption if required in cells C14:I14 | L7: Step 3, Enter a forecast of consumption if required in cells M14:T14
B9: Tariff details Choose tariff name from drop down box below | C9: ='Annex 1 LV and HV charges'!D11 -> Unit charge 1 (NHH) or red/black charge (HH) p/kWh | D9: ='Annex 1 LV and HV charges'!E11 -> Unit charge 2 (NHH) or amber/yellow charge (HH) p/kWh | E9: ='Annex 1 LV and HV charges'!F11 -> Green charge(HH) p/kWh | F9: ='Annex 1 LV and HV charges'!G11 -> Fixed charge p/MPAN/day | G9: ='Annex 1 LV and HV charges'!H11 -> Capacity charge p/kVA/day | H9: ='Annex 1 LV and HV charges'!I11 -> Exceeded capacity charge p/kVA/day | I9: ='Annex 1 LV and HV charges'!J11 -> Reactive power charge p/kVArh | L9: Site details Choose the site name from the drop down box below | M9: ='Annex 2 EHV charges'!H9 -> Import Super Red unit charge (p/kWh) | N9: ='Annex 2 EHV charges'!I9 -> Import fixed charge (p/day) | O9: ='Annex 2 EHV charges'!J9 -> Import capacity charge (p/kVA/day) | P9: ='Annex 2 EHV charges'!K9 -> Import exceeded capacity charge (p/kVA/day) | Q9: ='Annex 2 EHV charges'!L9 -> Export Super Red unit charge (p/kWh) | R9: ='Annex 2 EHV charges'!M9 -> Export fixed charge (p/day) | S9: ='Annex 2 EHV charges'!N9 -> Export capacity charge (p/kVA/day) | T9: ='Annex 2 EHV charges'!O9 -> Export exceeded capacity charge (p/kVA/day)
C10: =IFERROR(VLOOKUP($B$10,'Annex 1 LV and HV charges'!$A:$K,4,FALSE),"") | D10: =IFERROR(VLOOKUP($B$10,'Annex 1 LV and HV charges'!$A:$K,5,FALSE),"") | E10: =IFERROR(VLOOKUP($B$10,'Annex 1 LV and HV charges'!$A:$K,6,FALSE),"") | F10: =IFERROR(VLOOKUP($B$10,'Annex 1 LV and HV charges'!$A:$K,7,FALSE),"") | G10: =IFERROR(VLOOKUP($B$10,'Annex 1 LV and HV charges'!$A:$K,8,FALSE),"") | H10: =IFERROR(VLOOKUP($B$10,'Annex 1 LV and HV charges'!$A:$K,9,FALSE),"") | I10: =IFERROR(VLOOKUP($B$10,'Annex 1 LV and HV charges'!$A:$K,10,FALSE),"") | M10: =IFERROR(VLOOKUP($L$10,'Annex 2 EHV charges'!$G:$O,2,FALSE),"") | N10: =IFERROR(VLOOKUP($L$10,'Annex 2 EHV charges'!$G:$O,3,FALSE),"") | O10: =IFERROR(VLOOKUP($L$10,'Annex 2 EHV charges'!$G:$O,4,FALSE),"") | P10: =IFERROR(VLOOKUP($L$10,'Annex 2 EHV charges'!$G:$O,5,FALSE),"") | Q10: =IFERROR(VLOOKUP($L$10,'Annex 2 EHV charges'!$G:$O,6,FALSE),"") | R10: =IFERROR(VLOOKUP($L$10,'Annex 2 EHV charges'!$G:$O,7,FALSE),"") | S10: =IFERROR(VLOOKUP($L$10,'Annex 2 EHV charges'!$G:$O,8,FALSE),"") | T10: =IFERROR(VLOOKUP($L$10,'Annex 2 EHV charges'!$G:$O,9,FALSE),"")
B12: Tariff components | C12: Unit 1 kWh (red/black/day) | D12: Unit 2 kWh (amber/yellow /night) | E12: Unit 3 kWh (green) | F12: Number of days in consumption period i.e. 365 if one year | G12: Maximum import or export capacity kVA | H12: Average daily exceeded capacity kVA | I12: Excess reactive units kVArh | L12: Tariff components | M12: Import super red kWh | N12: Number of days in consumption period i.e. 365 if one year | O12: Maximum import capacity kVA | P12: Average daily exceeded capacity kVA | Q12: Export Super Red kWh | R12: Number of days in consumption period i.e. 365 if one year | S12: Maximum export capacity kVA | T12: Average daily exceeded capacity kVA
B13: Enter current consumption details | L13: Enter current consumption details | R13: =N13 -> 0
B14: Enter forecast consumption details (if different) | C14: =C13 -> 0 | D14: =D13 -> 0 | E14: =E13 -> 0 | F14: =F13 -> 0 | G14: =G13 -> 0 | H14: =H13 -> 0 | I14: =I13 -> 0 | L14: Enter forecast consumption details (if different) | M14: =M13 -> 0 | N14: =N13 -> 0 | O14: =O13 -> 0 | P14: =P13 -> 0 | Q14: =Q13 -> 0 | R14: =R13 -> 0 | S14: =S13 -> 0 | T14: =T13 -> 0
B16: Charge components | C16: Unit 1 £ | D16: Unit 2 £ | E16: Unit 3 £ | F16: Fixed charge £ | G16: Capacity charge £ | H16: Exceeded capacity charge £ | I16: Reactive power charge £ | L16: Charge components | M16: Import super red charge £ | N16: Import fixed charge £ | O16: Import capacity charge £ | P16: Import exceeded capacity charge £ | Q16: Export super red charge £ | R16: Export fixed charge £ | S16: Export capacity charge £ | T16: Export exceeded capacity charge £
B17: Current consumption period charges | C17: =IFERROR(C10*C13/100,"") | D17: =IFERROR(D10*D13/100,"") | E17: =IFERROR(E10*E13/100,"") | F17: =IFERROR(F10*F13/100,"") | G17: =IFERROR(G10*G13*F13/100,"") | H17: =IFERROR(H10*H13*F13/100,"") | I17: =IFERROR(I10*I13/100,"") | L17: Current consumption period charges | M17: =IFERROR(M10*M13/100,"") | N17: =IFERROR(N10*N13/100,"") | O17: =IFERROR(O10*O13*N13/100,"") | P17: =IFERROR(P10*P13*N13/100,"") | Q17: =IFERROR(Q10*Q13/100,"") | R17: =IFERROR(R10*R13/100,"") | S17: =IFERROR(S10*S13*R13/100,"") | T17: =IFERROR(T10*T13*R13/100,"")
B18: Forecast consumption period charges | C18: =IFERROR(C10*C14/100,"") | D18: =IFERROR(D10*D14/100,"") | E18: =IFERROR(E10*E14/100,"") | F18: =IFERROR(F10*F14/100,"") | G18: =IFERROR(G10*G14*F14/100,"") | H18: =IFERROR(H10*H14*F14/100,"") | I18: =IFERROR(I10*I14/100,"") | L18: Forecast consumption period charges | M18: =IFERROR(M10*M14/100,"") | N18: =IFERROR(N10*N14/100,"") | O18: =IFERROR(O10*O14*N14/100,"") | P18: =IFERROR(P10*P14*N14/100,"") | Q18: =IFERROR(Q10*Q14/100,"") | R18: =IFERROR(R10*R14/100,"") | S18: =IFERROR(S10*S14*R14/100,"") | T18: =IFERROR(T10*T14*R14/100,"")
C20: Total charge £ | M20: Import total charge £ | N20: Export total charge £
B21: Current consumption period charges | C21: =SUM(C17:I17) -> 0 | L21: Current consumption period charges | M21: =SUM(M17:P17) -> 0 | N21: =SUM(Q17:T17) -> 0
B22: Forecast consumption period charges | C22: =SUM(C18:I18) -> 0 | L22: Forecast consumption period charges | M22: =SUM(M18:P18) -> 0 | N22: =SUM(Q18:T18) -> 0
B24: These charges are estimates based on tariff selected and consumption values entered. | L24: These charges are estimates based on site selected and consumption values entered.
