Workbook
Name OLE_LINK1: 'Annex 3 Preserved charges'!#REF!

Sheet Overview
A2: Company and Licence name, charging year, effective from, status.
B3: Company and Licence name | C3: Year | D3: Effective From | E3: Status
A4: Company and Licence name, charging year, effective from, status | B4: SP Distribution | C4: 2018/19 | D4: 1 April 2018 | E4: Final
A6: List of data tables in this workbook
A7: Worksheet | B7: Information
A8: Annex 1 LV and HV charges | B8: Annex 1 contains charges to LV and HV Designated Properties.
A9: Annex 2 EHV charges | B9: ="Annex 2 contains the charges to Designated EHV Properties and charges applied to LDNOs with Designated EHV Properties/end-users embedded in networks within the " &B4 &" Licence area." -> Annex 2 contains the charges to Designated EHV Properties and charges applied to LDNOs with Designated EHV Properties/end-users embedded in networks within the SP Distribution Licence area.
A10: Annex 3 Preserved charges | B10: Annex 3 contains details of any preserved and additional charges that are valid at this time.
A11: Annex 4 LDNO charges | B11: ="Annex 4 contains charges that are levied on the owner of an embedded network within the "&B4&" Licence area. "&"Electricity suppliers and consumers who have properties connected to an embedded network should contact the embedded network owner to determine their distribution charges."&" The charges listed in this table are not payable by domestic consumers, business consumers or electricity suppliers." -> Annex 4 contains charges that are levied on the owner of an embedded network within the SP Distribution Licence area. Electricity suppliers and consumers who have properties connected to an embedded network should contact the embedded network owner to determine their distribution charges. The charges listed in this table are not payable by domestic consumers, business consumers or electricity suppliers.
A12: Annex 5 LLFs | B12: Annex 5 contains illustrative LLFs. LLFs are used in Settlement to adjust the metering system volumes to take account of losses on the distribution network. Illustrative LLFs are provided with reference to the metered voltage or associated LLFC for generic LLFs and by reference to the LLFCs for site specific LLFs. Each LLF is applicable to a defined time period. The LLFs used in Settlement are published on the Elexon portal website, www.elexonportal.co.uk. The website contains the LLFs in standard industry data formats and in a summary form. A user guide with details on registering and using the portal is also available.
A13: Annex 6 new Designated EHV Properties | B13: ="Annex 6 contains the charges to new Designated EHV Properties and charges applied to LDNOs with new Designated EHV Properties/end-users embedded in networks within the " &B4 &" Licence area." -> Annex 6 contains the charges to new Designated EHV Properties and charges applied to LDNOs with new Designated EHV Properties/end-users embedded in networks within the SP Distribution Licence area.
A14: Nodal prices | B14: Contains the underlying [nodal/network group] costs used to calculate the current EDCM charges.
A15: SSC TPR to unit rate lookup table | B15: The time periods for the non half hourly metered charge rates in Annex 1 are as specified by the SSC. To determine the appropriate charge rate for each SSC/TPR a lookup table is provided.
A16: Charge calculator | B16: Charge calculator is a tool to help you estimate your distribution charges using current consumption data and forecast consumption data.
A18: Notes to users of this spreadsheet
A20: Please use this spreadsheet with reference to the LC14 use of system charging statement.
A22: Notes to DNOs populating this spreadsheet
A24: DNOs must endeavour to maintain consistency in the structure of this spreadsheet. Any changes to the structure must be noted in the 'Notes to users of this spreadsheet'
A25: The drop down list on the charge calculator can be expanded by unprotecting the charge calculator sheet and selecting 'data', 'data validation...' and then expanding the 'source' data range. The sheet can then be protected.

Sheet Annex 1 LV and HV charges
A1: Back to Overview | B1: 'DNOs paste value cells A15:J47 from CDCM 3701 into cells A14:J46 | E1: Note: Where a tariff only has a p/kWh unit rate in Unit Charge 1 then this unit rate applies at all times.
A2: =Overview!B4& " - Effective from "&Overview!D4&" - "&Overview!E4&" LV and HV charges" -> SP Distribution - Effective from 1 April 2018 - Final LV and HV charges
A4: Time Bands for Half Hourly Metered Properties | G4: Time Bands for Half Hourly Unmetered Properties
A5: Time periods | B5: Red Time Band | C5: Amber Time Band | E5: Green Time Band | I5: Black Time Band | J5: Yellow Time Band | K5: Green Time Band
A6: Monday to Friday (Including Bank Holidays) All Year | B6: 16.30 - 19.30 | C6: 08.00 - 16.30 19.30 - 22.30 | E6: 00.00 - 08.00 22.30 - 00.00 | G6: Monday to Friday (Including Bank Holidays) June to August Inclusive | J6: 08.00 - 22.30 | K6: 00.00 - 08.00 22.30 - 00.00
A7: Saturday and Sunday All Year | C7: 16.00 - 20.00 | E7: 00.00 - 16.00 20.00 - 00.00 | G7: Monday to Friday (Including Bank Holidays) November to February Inclusive | I7: 16.30 - 19.30 | J7: 08.00 - 16.30 19.30 - 22.30 | K7: 00.00 - 08.00 22.30 - 00.00
A8: Notes | B8: All the above times are in UK Clock time | G8: Monday to Friday (Including Bank Holidays) March, April, May and September, October | J8: 08.00 - 22.30 | K8: 00.00 - 08.00 22.30 - 00.00
G9: Saturday and Sunday All year | J9: 16.00 - 20.00 | K9: 00:00-16:00 20:00-00:00
G10: Notes | I10: All the above times are in UK Clock time
A13: Tariff name | B13: Open LLFCs | C13: PCs | D13: Unit charge 1 (NHH) or red/black charge (HH) p/kWh | E13: Unit charge 2 (NHH) or amber/yellow charge (HH) p/kWh | F13: Green charge(HH) p/kWh | G13: Fixed charge p/MPAN/day | H13: Capacity charge p/kVA/day | I13: Exceeded capacity charge p/kVA/day | J13: Reactive power charge p/kVArh | K13: Closed LLFCs
A14: Domestic Unrestricted | B14: 100, 101, 110, 111, 160, 161 | C14: 1 | D14: 2.416 | G14: 5.02
A15: Domestic Two Rate | B15: 114, 115, 118, 119, 120, 121, 162, 163 | C15: 2 | D15: 2.854 | E15: 1.117 | G15: 5.02
A16: Domestic Off Peak (related MPAN) | B16: 112, 113, 116, 117, 132, 133, 136, 137, 164, 165, 166 | C16: 2 | D16: 1.097 | K16: 130, 134, 135
A17: Small Non Domestic Unrestricted | B17: 201, 204 | C17: 3 | D17: 2.446 | G17: 6.43 | K17: 200, 202, 203, 205
A18: Small Non Domestic Two Rate | B18: 221, 224, 260 | C18: 3&4 | D18: 2.951 | E18: 1.184 | G18: 6.43 | K18: 220, 222
A19: Small Non Domestic Off Peak (related MPAN) | B19: 225, 240, 241, 301, 302 | C19: 3&4 | D19: 1.472 | K19: 223, 242, 243, 244, 245, 246
A20: LV Medium Non-Domestic | B20: 400, 402 | C20: 5-8 | D20: 2.216 | E20: 1.105 | G20: 30.02
A21: LV Sub Medium Non-Domestic | B21: 404 | C21: 5-8 | D21: 1.829 | E21: 1.066 | G21: 0
A22: HV Medium Non-Domestic | C22: 5-8 | D22: 1.465 | E22: 1.016 | G22: 318.78 | K22: 401
A23: LV Network Domestic | B23: 180 | C23: 0 | D23: 8.906 | E23: 1.856 | F23: 1.056 | G23: 5.02
A24: LV Network Non-Domestic Non-CT | B24: 280 | C24: 0 | D24: 9.336 | E24: 1.903 | F24: 1.06 | G24: 6.43
A25: LV HH Metered | B25: 500, 504 | C25: 0 | D25: 7.046 | E25: 1.608 | F25: 1.035 | G25: 25.48 | H25: 2.45 | I25: 3.59 | J25: 0.186
A26: LV Sub HH Metered | B26: 506, 507 | C26: 0 | D26: 5.118 | E26: 1.325 | F26: 1.009 | G26: 8.99 | H26: 4.46 | I26: 5.08 | J26: 0.098
A27: HV HH Metered | B27: 501, 505 | C27: 0 | D27: 3.835 | E27: 1.191 | F27: 0.999 | G27: 136.14 | H27: 4.92 | I27: 6.05 | J27: 0.057
A28: NHH UMS category A | B28: 900 | C28: 1&8 | D28: 2.147 | K28: 904, 908, 909
A29: NHH UMS category B | B29: 901 | C29: 1 | D29: 2.371 | K29: 905
A30: NHH UMS category C | B30: 902 | C30: 1 | D30: 3.159 | K30: 906
A31: NHH UMS category D | B31: 903 | C31: 1 | D31: 1.986 | K31: 907
A32: LV UMS (Pseudo HH Metered) | B32: 910 | C32: 0 | D32: 15.24 | E32: 2.032 | F32: 1.506
A33: LV Generation NHH or Aggregate HH | B33: 781, 782, 783, 784, 785 | C33: 0&8 | D33: -0.762 | G33: 0
A34: LV Sub Generation NHH | B34: 602 | C34: 8 | D34: -0.673 | G34: 0
A35: LV Generation Intermittent | B35: 603, 608 | C35: 0 | D35: -0.762 | G35: 0 | J35: 0.176
A36: LV Generation Intermittent no RP charge | B36: TBA | C36: 0 | D36: -0.762 | G36: 0
A37: LV Generation Non-Intermittent | B37: 604, 607 | C37: 0 | D37: -5.617 | E37: -0.613 | F37: -0.045 | G37: 0 | J37: 0.176
A38: LV Generation Non-Intermittent no RP charge | B38: TBA | C38: 0 | D38: -5.617 | E38: -0.613 | F38: -0.045 | G38: 0
A39: LV Sub Generation Intermittent | B39: 609 | C39: 0 | D39: -0.673 | G39: 0 | J39: 0.155
A40: LV Sub Generation Intermittent no RP charge | B40: TBA | C40: 0 | D40: -0.673 | G40: 0
A41: LV Sub Generation Non-Intermittent | B41: 610 | C41: 0 | D41: -5.025 | E41: -0.529 | F41: -0.038 | G41: 0 | J41: 0.155
A42: LV Sub Generation Non-Intermittent no RP charge | B42: TBA | C42: 0 | D42: -5.025 | E42: -0.529 | F42: -0.038 | G42: 0
A43: HV Generation Intermittent | B43: 611, 612 | C43: 0 | D43: -0.407 | G43: 99.41 | J43: 0.124
A44: HV Generation Intermittent no RP charge | B44: TBA | C44: 0 | D44: -0.407 | G44: 99.41
A45: HV Generation Non-Intermittent | B45: 605, 606 | C45: 0 | D45: -3.333 | E45: -0.266 | F45: -0.013 | G45: 99.41 | J45: 0.124
A46: HV Generation Non-Intermittent no RP charge | B46: TBA | C46: 0 | D46: -3.333 | E46: -0.266 | F46: -0.013 | G46: 99.41

Sheet Annex 2 EHV charges
A1: Back to Overview | C1: Copy EDCM table 5001 range starting B101 and paste into G11. Extend or reduce print area as required. | F1: Note: The list of MPANs / MSIDs provided may be incomplete; the DNO reserves the right to apply the listed charges to any other MPANs / MSIDs associated with the site.
A2: =Overview!B4& " - Effective from "&Overview!D4&" - "&Overview!E4&" EDCM charges" -> SP Distribution - Effective from 1 April 2018 - Final EDCM charges
A4: Time Periods for Designated EHV Properties
A5: Time periods | D5: Super Red Time Band
A6: Monday to Friday (Including Bank Holidays) June to August Inclusive
A7: Monday to Friday (Including Bank Holidays) November to February Inclusive | D7: 16:30 - 19:30
A8: Notes | D8: All the above times are in UK Clock time
A10: Import Unique Identifier | B10: LLFC | C10: Import MPANs/MSIDs | D10: Export Unique Identifier | E10: LLFC | F10: Export MPANs/MSIDs | G10: Name | H10: Import Super Red unit charge (p/kWh) | I10: Import fixed charge (p/day) | J10: Import capacity charge (p/kVA/day) | K10: Import exceeded capacity charge (p/kVA/day) | L10: Export Super Red unit charge (p/kWh) | M10: Export fixed charge (p/day) | N10: Export capacity charge (p/kVA/day) | O10: Export exceeded capacity charge (p/kVA/day)
A11: 800 | B11: 800 | C11: 1800060775972 | D11: 644 | E11: 644 | F11: 1800060775990 | G11: Rhodders | I11: 352.11 | J11: 1.77 | K11: 1.77 | M11: 5861.03 | N11: 0.05 | O11: 0.05
A12: 801 | B12: 801 | C12: 1800060004220 | D12: MSID 8182 | E12: MSID 8182 | F12: MSID 8182 | G12: Minsca | I12: 504.96
A13: 802 | B13: 802 | C13: 1800060539962 | D13: 683 | E13: 683 | F13: 1800060539971 | G13: Bankend Rig | I13: 144.8 | J13: 4.31 | K13: 4.31 | M13: 5449.73 | N13: 0.05 | O13: 0.05
A14: 803 | B14: 803 | C14: 1800060532708 | D14: 684 | E14: 684 | F14: 1800060532717 | G14: Barlockhart Moor | I14: 176.83 | J14: 2.57 | K14: 2.57 | M14: 9901.7 | N14: 0.05 | O14: 0.05
A15: 804 | B15: 804 | C15: 1800060532726 | D15: 685 | E15: 685 | F15: 1800060532735 | G15: Blantyre Muir | I15: 408.53 | J15: 0.82 | K15: 0.82 | M15: 6437.57 | N15: 0.05 | O15: 0.05
A16: 805 | B16: 805 | C16: 1800060587850 | D16: 693 | E16: 693 | F16: 1800060587869 | G16: Hunterston WF | I16: 117.17 | J16: 0.95 | K16: 0.95 | M16: 8746.35 | N16: 0.05 | O16: 0.05
A17: 806 | B17: 806 | C17: 1800060532647 | D17: 688 | E17: 688 | F17: 1800060532656 | G17: Middleton Farm | I17: 253.36 | J17: 2.55 | K17: 2.55 | M17: 5756.23 | N17: 0.05 | O17: 0.05
A18: 807 | B18: 807 | C18: 1800060532665 | D18: 689 | E18: 689 | F18: 1800060532674 | G18: Neilston Community | I18: 149.6 | J18: 2.65 | K18: 2.65 | M18: 7061.91 | N18: 0.05 | O18: 0.05
A19: 808 | B19: 808 | C19: 1800053653870 | D19: 681 | E19: 681 | F19: 1800053653880 | G19: Garlaff Landfill | I19: 121.27 | J19: 0.8 | K19: 0.8
A20: 809 | B20: 809 | C20: 1800054992968 | D20: 629 | E20: 629 | F20: 1800054992977 | G20: Hagshaw Hill Extension | I20: 792.43 | J20: 0.83 | K20: 0.83 | M20: 20011.69 | N20: 0.05 | O20: 0.05
A21: 811 | B21: 811 | C21: 1800060328035 | D21: 671 | E21: 671 | F21: 1800060328044 | G21: Muirhall | I21: 376.81 | J21: 2.54 | K21: 2.54 | M21: 9043.53 | N21: 0.05 | O21: 0.05
A22: 812 | B22: 812 | C22: 1800060372113 | D22: 672 | E22: 672 | F22: 1800060372122 | G22: Burnfoot | I22: 126.65 | J22: 0.88 | K22: 0.88 | M22: 8837.86 | N22: 0.05 | O22: 0.05
A23: 813 | B23: 813 | C23: 1800060532498 | D23: 690 | E23: 690 | F23: 1800060532503 | G23: Westfield WF | I23: 66.98 | J23: 1.17 | K23: 1.17 | M23: 7868.41 | N23: 0.05 | O23: 0.05
A24: 814 | B24: 814 | C24: 1800060532683 | D24: 691 | E24: 691 | F24: 1800060532692 | G24: Barmoor WF | I24: 222.3 | J24: 2.78 | K24: 2.78 | M24: 21017.15 | N24: 0.05 | O24: 0.05
A25: 815 | B25: 815 | C25: 1800060566984 | D25: 692 | E25: 692 | F25: 1800060566993 | G25: Nutberry WF | I25: 894.83 | J25: 2.53 | K25: 2.53 | M25: 16940.53 | N25: 0.05 | O25: 0.05
A26: 816 | B26: 816 | C26: 1800060652454 | D26: 695 | E26: 695 | F26: 1800060652463 | G26: Carcreugh WF | I26: 346.87 | J26: 0.84 | K26: 0.84 | M26: 7080.28 | N26: 0.05 | O26: 0.05
A27: 817 | B27: 817 | C27: 1800060567668 | G27: Magnox | I27: 408.42 | J27: 1.22 | K27: 1.22
A28: 818 | B28: 818 | C28: 1800060642767 | D28: 700 | E28: 700 | F28: 1800060642776 | G28: West Browncastle WF | I28: 559.7 | J28: 0.86 | K28: 0.86 | M28: 31684.48 | N28: 0.05 | O28: 0.05
A29: 819 | B29: 819 | C29: 1800060632661 | D29: 699 | E29: 699 | F29: 1800060632670 | G29: Viridor (Waste energy) | I29: 1637.93 | J29: 2.63 | K29: 2.63 | M29: 9813.91 | N29: 0.05 | O29: 0.05
A30: 820 | B30: 820 | C30: 1800060289486 | D30: 620 | E30: 620 | F30: 1800060289510 | G30: Craigengelt | I30: 166.72 | J30: 0.94 | K30: 0.94 | M30: 22773.33 | N30: 0.05 | O30: 0.05
A31: 821 | B31: 821 | C31: 1800054865132 | D31: 621 | E31: 621 | F31: 1800054865141 | G31: Greenknowes | I31: 685.59 | J31: 0.91 | K31: 0.91 | M31: 41135.66 | N31: 0.05 | O31: 0.05
A32: 822 | B32: 822 | C32: 1800060683754 | D32: 703 | E32: 703 | F32: 1800060683763 | G32: Ewe Hill Dumfries WF | I32: 522.92 | J32: 2.57 | K32: 2.57 | M32: 23590.95 | N32: 0.05 | O32: 0.05
A33: 823 | B33: 823 | C33: 1800060697223 | D33: 704 | E33: 704 | F33: 1800060697232 | G33: Langhope Rig (D) WF | I33: 47.06 | J33: 1.65 | K33: 1.65 | M33: 1543.31 | N33: 0.05 | O33: 0.05
A34: 824 | B34: 824 | C34: 1800060674253 | D34: 705 | E34: 705 | F34: 1800060674262 | G34: Muirhall Extention WF | I34: 60.32 | J34: 2.62 | K34: 2.62 | M34: 3594.62 | N34: 0.05 | O34: 0.05
A35: 825 | B35: 825 | C35: 1800060159192 | D35: 625 | E35: 625 | F35: 1800060159208 | G35: Aikengall | I35: 1622.47 | M35: 40970.78 | N35: 0.05 | O35: 0.05
A36: 826 | B36: 826 | C36: 1800053646251 | D36: 626 | E36: 626 | F36: 1800053646260 | G36: Hagshaw Hill | I36: 44.62 | J36: 2.62 | K36: 2.62
A37: 827 | B37: 827 | C37: 1800053646190 | D37: 627 | E37: 627 | F37: 1800053646206 | G37: Gallow Rig | I37: 155.6 | J37: 2.54 | K37: 2.54
A38: 828 | B38: 828 | C38: 1800053646172 | D38: 628 | E38: 628 | F38: 1800053646181 | G38: Polwhat Rig | I38: 185.09 | J38: 2.53 | K38: 2.53
A39: 829 | B39: 829 | C39: 1800054738267 | D39: 624 | E39: 624 | F39: 1800054738276 | G39: Greendykeside | I39: 58.62 | J39: 2.65 | K39: 2.65 | M39: 4113.18 | N39: 0.05 | O39: 0.05
A40: 830 | B40: 830 | C40: 1800053647237 | D40: 630 | E40: 630 | F40: 1800053647246 | G40: Dun Law | I40: 38.8 | J40: 2.61 | K40: 2.61
A41: 831 | B41: 831 | C41: 1800053647194 | D41: 631 | E41: 631 | F41: 1800053647200 | G41: EPR Scotland Ltd | I41: 310.1 | J41: 2.71 | K41: 2.71
A42: 832 | B42: 832 | C42: 1800053648027 | D42: 632 | E42: 632 | F42: 1800053648036 | G42: Bowbeat (Emly Bank) | I42: 200.95 | J42: 2.55 | K42: 2.55
A43: 833 | B43: 833 | C43: 1800053648045 | D43: 633 | E43: 633 | F43: 1800053648054 | G43: Bowbeat (Roughsidehill) | I43: 140.26 | J43: 2.58 | K43: 2.58
A44: 834 | B44: 834 | C44: 1800053647380 | D44: 634 | E44: 634 | F44: 1800053647399 | G44: Harehill | I44: 139.77 | J44: 2.57 | K44: 2.57
A45: 835 | B45: 835 | C45: 1800053647618 | D45: 635 | E45: 635 | F45: 1800053647627 | G45: Shanks & McEwan 3&4 | I45: 131.06 | J45: 2.68 | K45: 2.68
A46: 836 | B46: 836 | C46: 1800053647636 | D46: 636 | E46: 636 | F46: 1800053647645 | G46: Shanks & McEwan 5 | I46: 30.76 | J46: 2.52 | K46: 2.52
A47: 837 | B47: 837 | C47: 1800053653843 | D47: 637 | E47: 637 | F47: 1800053653852 | G47: Crystal Rig | I47: 717.25 | J47: 0.81 | K47: 0.81
A48: 838 | B48: 838 | C48: 1800053694167 | D48: 638 | E48: 638 | F48: 1800053694440 | G48: Haupland Muir (Ardrossan) | I48: 8.12 | J48: 0.9 | K48: 0.9 | M48: 235.31 | N48: 0.05 | O48: 0.05
A49: 839 | B49: 839 | C49: 1800053950949 | D49: 639 | E49: 639 | F49: 1800053950958 | G49: Wetherhill | I49: 1409.51
A50: 840 | B50: 840 | C50: 1800053434271 | D50: 640 | E50: 640 | F50: 1800053883993 | G50: Artfield WF | I50: 912.25
A51: 841 | B51: 841 | C51: 1800054152982 | D51: 641 | E51: 641 | F51: 1800054152991 | G51: Wardlaw Wood | I51: 93.58 | J51: 2.69 | K51: 2.69
A52: 842 | B52: 842 | C52: 1800054198365 | D52: 642 | E52: 642 | F52: 1800054198374 | G52: Earlsburn | I52: 764.48
A53: 843 | B53: 843 | C53: 1800054244570 | D53: 643 | E53: 643 | F53: 1800054244598 | G53: Blackhill | I53: 2071.36 | M53: 25005.71 | N53: 0.05 | O53: 0.05
A54: 844 | B54: 844 | C54: 1800054451603 | D54: MSID 8183 | E54: MSID 8183 | F54: MSID 8183 | G54: Dalswinton | I54: 521.04 | J54: 0.86 | K54: 0.86
A55: 845 | B55: 845 | C55: 1800054498470 | D55: 645 | E55: 645 | F55: 1800054498480 | G55: Steven's Croft Biomass | I55: 5080.33 | J55: 0.83 | K55: 0.83
A56: 849 | B56: 849 | C56: TBA | D56: 649 | E56: 649 | F56: TBA | G56: Sorbie Windfarm | I56: 146.64 | J56: 1.77 | K56: 1.77 | M56: 7231.39 | N56: 0.05 | O56: 0.05
A57: 850 | B57: 850 | C57: 1800060251872 | D57: 650 | E57: 650 | F57: 1800060251881 | G57: Longpark | I57: 903.35 | M57: 22623.64 | N57: 0.05 | O57: 0.05
A58: 851 | B58: 851 | C58: 1800035140431 | G58: BOC | I58: 8249.12 | J58: 2.51 | K58: 2.51
A59: 852 | B59: 852 | C59: 1800060642702 | D59: 696 | E59: 696 | F59: 1800060642711 | G59: Calder Water WF | I59: 248.41 | J59: 0.99 | K59: 0.99 | M59: 30287.27 | N59: 0.05 | O59: 0.05
A60: 853 | B60: 853 | C60: 1800035234188 | G60: Babcock Thorn | I60: 22306.78 | J60: 4.3 | K60: 4.3
A61: 854 | B61: 854 | C61: 1800035261359 | D61: 654 | E61: 654 | F61: 1800053946507 | G61: Lafarge UK | I61: 11533.62 | J61: 3.66 | K61: 3.66
A62: 855 | B62: 855 | C62: 1800060241304 | D62: 655 | E62: 655 | F62: 1800060241313 | G62: Pateshill | I62: 25.05 | J62: 2.6 | K62: 2.6 | M62: 1402.7 | N62: 0.05 | O62: 0.05
A63: 856 | B63: 856 | C63: 1800035239460 | G63: Clydeport | I63: 30251.05 | J63: 1.39 | K63: 1.39
A64: 857 | B64: 857 | C64: 1800035313389 | G64: Freescale | I64: 11781.84 | J64: 3.51 | K64: 3.51
A65: 858 | B65: 858 | C65: 1800035327257 | G65: Tesco | I65: 1042.28 | J65: 2.96 | K65: 2.96
A66: 859 | B66: 859 | C66: 1800035320127 | D66: 697 | E66: 697 | F66: 1800060630637 | G66: GlaxoSmithKline | I66: 28215.67 | J66: 2.14 | K66: 2.14 | M66: 2731.14 | N66: 0.05 | O66: 0.05
A67: 860 | B67: 860 | C67: 1800060852030 | D67: 666 | E67: 666 | F67: 1800060852049 | G67: Gevens Wind Farm | I67: 23.38 | J67: 1.77 | K67: 1.77 | M67: 5660.98 | N67: 0.05 | O67: 0.05
A68: 861 | B68: 861 | C68: 1800035324780 | G68: Weir Pumps | I68: 1880.08 | J68: 4.8 | K68: 4.8
A69: 862 | B69: 862 | C69: 1800035317453 | G69: Dupont (UK) Ltd | I69: 78043.07 | J69: 2.99 | K69: 2.99
A70: 863 | B70: 863 | C70: 1800060207438 | D70: 663 | E70: 663 | F70: 1800060207447 | G70: North Rhins | I70: 326.72 | J70: 2.54 | K70: 2.54 | M70: 9819.38 | N70: 0.05 | O70: 0.05
A71: 864 | B71: 864 | C71: 1800060709038 | D71: 698 | E71: 698 | F71: 1800060709047 | G71: Tod Hills Windfarm | I71: 82.58 | J71: 2.19 | K71: 2.19 | M71: 9072.76 | N71: 0.05 | O71: 0.05
A72: 865 | B72: 865 | C72: 1800060877284 | D72: 670 | E72: 670 | F72: 1800060877293 | G72: Hoprigshiels | I72: 656.53 | J72: 3.5 | K72: 3.5 | M72: 14083.18 | N72: 0.05 | O72: 0.05
A73: 866 | B73: 866 | C73: 1800051523646 | G73: Calachem | I73: 10876.81 | J73: 10.46 | K73: 10.46
A74: 867 | B74: 867 | C74: 1800035325436 | G74: Norbord | I74: 21991.37 | J74: 1.33 | K74: 1.33
A75: 868 | B75: 868 | C75: 1800060809025 | D75: 664 | E75: 664 | F75: 1800060809034 | G75: MuirHall Extension II WF | I75: 58.37 | J75: 2.91 | K75: 2.91 | M75: 5266.83 | N75: 0.05 | O75: 0.05
A76: 872 | B76: 872 | C76: 1800060749680 | D76: 694 | E76: 694 | F76: 1800060749699 | G76: Polmadie (Waste energy B) | I76: 257.78 | J76: 2.9 | K76: 2.9 | L76: -0.522 | M76: 2637.22 | N76: 0.05 | O76: 0.05
A77: 886 | B77: 886 | C77: TBA | D77: 686 | E77: 686 | F77: TBA | G77: Sneddon Law WF | I77: 536.96 | J77: 0.81 | K77: 0.81 | M77: 32210.37 | N77: 0.05 | O77: 0.05
A78: 887 | B78: 887 | C78: 1800060749661 | D78: 706 | E78: 706 | F78: 1800060749670 | G78: Polmadie (Waste energy A) | I78: 1291.61 | J78: 2.99 | K78: 2.99 | L78: -0.522 | M78: 5463.38 | N78: 0.05 | O78: 0.05
A79: 873 | B79: 873 | C79: 1800060450481 | D79: 673 | E79: 673 | F79: 1800060450490 | G79: Millour Hill | I79: 238.51 | J79: 0.87 | K79: 0.87 | M79: 16418.25 | N79: 0.05 | O79: 0.05
A80: 874 | B80: 874 | C80: 1800060441380 | D80: 674 | E80: 674 | F80: 1800060441399 | G80: Glenkerie | I80: 422.38 | J80: 2.6 | K80: 2.6 | M80: 16362.26 | N80: 0.05 | O80: 0.05
A81: 875 | B81: 875 | C81: 1800060450524 | D81: 675 | E81: 675 | F81: 1800060450533 | G81: Kelburn (A) | I81: 194.8 | J81: 2.62 | K81: 2.62 | M81: 9731.36 | N81: 0.05 | O81: 0.05
A82: 876 | B82: 876 | C82: 1800060450542 | D82: 676 | E82: 676 | F82: 1800060450551 | G82: Kelburn (B) | I82: 194.8 | J82: 2.64 | K82: 2.64 | M82: 9731.36 | N82: 0.05 | O82: 0.05
A83: 877 | B83: 877 | C83: 1800060450506 | D83: 677 | E83: 677 | F83: 1800060450515 | G83: Little Raith | I83: 213.81 | J83: 0.9 | K83: 0.9 | M83: 5879.86 | N83: 0.05 | O83: 0.05
A84: 878 | B84: 878 | C84: 1800060445640 | D84: 678 | E84: 678 | F84: 1800060445659 | G84: Drone Hill | I84: 591 | J84: 1.02 | K84: 1.02 | M84: 28985.11 | N84: 0.05 | O84: 0.05
A85: 879 | B85: 879 | C85: 1800060845812 | D85: 680 | E85: 680 | F85: 1800060845821 | G85: Pearie Law Wind Farm | I85: 309.23 | J85: 3.5 | K85: 3.5 | M85: 17595.32 | N85: 0.05 | O85: 0.05
A86: 880 | B86: 880 | C86: 1800060673222 | D86: 701 | E86: 701 | F86: 1800060673231 | G86: Earlseat WF | I86: 174.85 | J86: 2.63 | K86: 2.63 | M86: 13265.73 | N86: 0.05 | O86: 0.05
A87: 881 | B87: 881 | C87: 1800060740288 | D87: 702 | E87: 702 | F87: 1800060740297 | G87: Dungavel WF | I87: 583.72 | J87: 0.93 | K87: 0.93 | M87: 34906.22 | N87: 0.05 | O87: 0.05
A88: 882 | B88: 882 | C88: 1800060769738 | D88: 687 | E88: 687 | F88: 1800060769747 | G88: Burnhead Bathgate WF | I88: 69.92 | J88: 2.67 | K88: 2.67 | M88: 4712.99 | N88: 0.05 | O88: 0.05
A89: 883 | B89: 883 | C89: 1800053647742 | D89: 636 | E89: 636 | F89: 1800053647751 | G89: Shanks & McEwan 6 | I89: 88.95 | J89: 2.52 | K89: 2.52
A90: 884 | B90: 884 | C90: 1800060683693 | D90: 679 | E90: 679 | F90: 1800060683709 | G90: Ardoch & Over Enoch WF | I90: 122.44 | J90: 1.04 | K90: 1.04 | M90: 13352.2 | N90: 0.05 | O90: 0.05
A91: 885 | B91: 885 | C91: TBA | D91: 623 | E91: 623 | F91: TBA | G91: Muirpark Wind Farm | I91: 127.77 | J91: 1.77 | K91: 1.77 | M91: 17419.69 | N91: 0.05 | O91: 0.05
A92: 888 | B92: 888 | C92: 1800060817230 | D92: MSID 8732 | E92: MSID 8732 | F92: MSID 8732 | G92: Glenchamber | I92: 123.06 | J92: 0.84 | K92: 0.84 | M92: 15974.55 | N92: 0.05 | O92: 0.05
A93: 889 | B93: 889 | C93: 1800060819273 | D93: 708 | E93: 708 | F93: 1800060819282 | G93: Penmansheill | I93: 261.83 | J93: 0.85 | K93: 0.85 | M93: 39549.89 | N93: 0.05 | O93: 0.05
A94: 891 | B94: 891 | C94: 1800060863723 | D94: 668 | E94: 668 | F94: 1800060863732 | G94: Tormywheel | I94: 64.28 | J94: 3.5 | K94: 3.5 | M94: 11413.87 | N94: 0.05 | O94: 0.05
A95: 892 | B95: 892 | C95: 1800060872755 | D95: 669 | E95: 669 | F95: 1800060872764 | G95: Quixwood Wind Farm | I95: 330.61 | J95: 1.77 | K95: 1.77 | M95: 29825.51 | N95: 0.05 | O95: 0.05
A96: MSID 8083 | B96: MSID 8083 | C96: MSID 8083 | G96: Dumbarton | I96: 0 | J96: 2.63 | K96: 2.63
A97: MSID 8085 | B97: MSID 8085 | C97: MSID 8085 | G97: Stirling Road | I97: 0 | J97: 3.13 | K97: 3.13
A98: MSID 8334 | B98: MSID 8334 | C98: MSID 8334 | D98: MSID 8334 | E98: MSID 8334 | F98: MSID 8334 | G98: Markinch | I98: 3248.25 | J98: 1.02 | K98: 1.02 | M98: 24767.93 | N98: 0.05 | O98: 0.05
A99: MSID 8339 | B99: MSID 8339 | C99: MSID 8339 | D99: MSID 8339 | E99: MSID 8339 | F99: MSID 8339 | G99: Harehill Extension | I99: 63.71 | J99: 3.5 | K99: 3.5 | M99: 9500.47 | N99: 0.05 | O99: 0.05
A100: MSID 8340 | B100: MSID 8340 | C100: MSID 8340 | D100: MSID 8340 | E100: MSID 8340 | F100: MSID 8340 | G100: Aries | I100: 77.8 | J100: 1.77 | K100: 1.77 | M100: 14699.78 | N100: 0.05 | O100: 0.05
A101: MSID 8341 | B101: MSID 8341 | C101: MSID 8341 | D101: MSID 8341 | E101: MSID 8341 | F101: MSID 8341 | G101: Andershaw WF | I101: 211.67 | J101: 2.57 | K101: 2.57 | M101: 28882.65 | N101: 0.05 | O101: 0.05
A102: MSID 8347 | B102: MSID 8347 | C102: MSID 8347 | D102: MSID 8347 | E102: MSID 8347 | F102: MSID 8347 | G102: Assel Valley | I102: 1707.41 | J102: 0.85 | K102: 0.85 | M102: 52955.71 | N102: 0.05 | O102: 0.05
...

Sheet Annex 2a Import
A1: Note: The list of MPANs / MSIDs provided may be incomplete; the DNO reserves the right to apply the listed charges to any other MPANs / MSIDs associated with the site. Note: This table is automatically populated based on the content of the tab entitled 'Annex 2 EHV Charges'. The timebands are as shown in Annex 2.
A2: =Overview!B4& " - Effective from "&Overview!D4&" - "&Overview!E4&" EDCM import charges" -> SP Distribution - Effective from 1 April 2018 - Final EDCM import charges
A4: Import Unique Identifier | B4: LLFC | C4: Import MPANs/MSIDs | D4: Name | E4: ='Annex 2 EHV charges'!H10 -> Import Super Red unit charge (p/kWh) | F4: ='Annex 2 EHV charges'!I10 -> Import fixed charge (p/day) | G4: ='Annex 2 EHV charges'!J10 -> Import capacity charge (p/kVA/day) | H4: ='Annex 2 EHV charges'!K10 -> Import exceeded capacity charge (p/kVA/day)
A5: {=IFERROR(INDEX('Annex 2 EHV charges'!$A$11:$A$260, MATCH(0, IF(ISBLANK('Annex 2 EHV charges'!$A$11:$A$260),1, COUNTIF(A$4:$A4, 'Annex 2 EHV charges'!$A$11:$A$260)), 0)),"")} -> 800 | B5: =IF($A5="","",VLOOKUP($A5,'Annex 2 EHV charges'!$A:$O,2,0)) -> 800 | C5: =IF($A5="","",VLOOKUP($A5,'Annex 2 EHV charges'!$A:$O,3,0)) -> 1800060775972 | D5: =IF($A5="","",VLOOKUP($A5,'Annex 2 EHV charges'!$A:$O,7,0)) -> Rhodders | E5: =IFERROR(IF(VLOOKUP($A5,'Annex 2 EHV charges'!$A:$O,8,FALSE)=0,"",VLOOKUP($A5,'Annex 2 EHV charges'!$A:$O,8,FALSE)),"") | F5: =IFERROR(IF(VLOOKUP($A5,'Annex 2 EHV charges'!$A:$O,9,FALSE)=0,"",VLOOKUP($A5,'Annex 2 EHV charges'!$A:$O,9,FALSE)),"") -> 352.11 | G5: =IFERROR(IF(VLOOKUP($A5,'Annex 2 EHV charges'!$A:$O,10,FALSE)=0,"",VLOOKUP($A5,'Annex 2 EHV charges'!$A:$O,10,FALSE)),"") -> 1.77 | H5: =IFERROR(IF(VLOOKUP($A5,'Annex 2 EHV charges'!$A:$O,11,FALSE)=0,"",VLOOKUP($A5,'Annex 2 EHV charges'!$A:$O,11,FALSE)),"") -> 1.77
A6: {=IFERROR(INDEX('Annex 2 EHV charges'!$A$11:$A$260, MATCH(0, IF(ISBLANK('Annex 2 EHV charges'!$A$11:$A$260),1, COUNTIF(A$4:$A5, 'Annex 2 EHV charges'!$A$11:$A$260)), 0)),"")} -> 801 | B6: =IF($A6="","",VLOOKUP($A6,'Annex 2 EHV charges'!$A:$O,2,0)) -> 801 | C6: =IF($A6="","",VLOOKUP($A6,'Annex 2 EHV charges'!$A:$O,3,0)) -> 1800060004220 | D6: =IF($A6="","",VLOOKUP($A6,'Annex 2 EHV charges'!$A:$O,7,0)) -> Minsca | E6: =IFERROR(IF(VLOOKUP($A6,'Annex 2 EHV charges'!$A:$O,8,FALSE)=0,"",VLOOKUP($A6,'Annex 2 EHV charges'!$A:$O,8,FALSE)),"") | F6: =IFERROR(IF(VLOOKUP($A6,'Annex 2 EHV charges'!$A:$O,9,FALSE)=0,"",VLOOKUP($A6,'Annex 2 EHV charges'!$A:$O,9,FALSE)),"") -> 504.96 | G6: =IFERROR(IF(VLOOKUP($A6,'Annex 2 EHV charges'!$A:$O,10,FALSE)=0,"",VLOOKUP($A6,'Annex 2 EHV charges'!$A:$O,10,FALSE)),"") | H6: =IFERROR(IF(VLOOKUP($A6,'Annex 2 EHV charges'!$A:$O,11,FALSE)=0,"",VLOOKUP($A6,'Annex 2 EHV charges'!$A:$O,11,FALSE)),"")
A7: {=IFERROR(INDEX('Annex 2 EHV charges'!$A$11:$A$260, MATCH(0, IF(ISBLANK('Annex 2 EHV charges'!$A$11:$A$260),1, COUNTIF(A$4:$A6, 'Annex 2 EHV charges'!$A$11:$A$260)), 0)),"")} -> 802 | B7: =IF($A7="","",VLOOKUP($A7,'Annex 2 EHV charges'!$A:$O,2,0)) -> 802 | C7: =IF($A7="","",VLOOKUP($A7,'Annex 2 EHV charges'!$A:$O,3,0)) -> 1800060539962 | D7: =IF($A7="","",VLOOKUP($A7,'Annex 2 EHV charges'!$A:$O,7,0)) -> Bankend Rig | E7: =IFERROR(IF(VLOOKUP($A7,'Annex 2 EHV charges'!$A:$O,8,FALSE)=0,"",VLOOKUP($A7,'Annex 2 EHV charges'!$A:$O,8,FALSE)),"") | F7: =IFERROR(IF(VLOOKUP($A7,'Annex 2 EHV charges'!$A:$O,9,FALSE)=0,"",VLOOKUP($A7,'Annex 2 EHV charges'!$A:$O,9,FALSE)),"") -> 144.8 | G7: =IFERROR(IF(VLOOKUP($A7,'Annex 2 EHV charges'!$A:$O,10,FALSE)=0,"",VLOOKUP($A7,'Annex 2 EHV charges'!$A:$O,10,FALSE)),"") -> 4.31 | H7: =IFERROR(IF(VLOOKUP($A7,'Annex 2 EHV charges'!$A:$O,11,FALSE)=0,"",VLOOKUP($A7,'Annex 2 EHV charges'!$A:$O,11,FALSE)),"") -> 4.31
A8: {=IFERROR(INDEX('Annex 2 EHV charges'!$A$11:$A$260, MATCH(0, IF(ISBLANK('Annex 2 EHV charges'!$A$11:$A$260),1, COUNTIF(A$4:$A7, 'Annex 2 EHV charges'!$A$11:$A$260)), 0)),"")} -> 803 | B8: =IF($A8="","",VLOOKUP($A8,'Annex 2 EHV charges'!$A:$O,2,0)) -> 803 | C8: =IF($A8="","",VLOOKUP($A8,'Annex 2 EHV charges'!$A:$O,3,0)) -> 1800060532708 | D8: =IF($A8="","",VLOOKUP($A8,'Annex 2 EHV charges'!$A:$O,7,0)) -> Barlockhart Moor | E8: =IFERROR(IF(VLOOKUP($A8,'Annex 2 EHV charges'!$A:$O,8,FALSE)=0,"",VLOOKUP($A8,'Annex 2 EHV charges'!$A:$O,8,FALSE)),"") | F8: =IFERROR(IF(VLOOKUP($A8,'Annex 2 EHV charges'!$A:$O,9,FALSE)=0,"",VLOOKUP($A8,'Annex 2 EHV charges'!$A:$O,9,FALSE)),"") -> 176.83 | G8: =IFERROR(IF(VLOOKUP($A8,'Annex 2 EHV charges'!$A:$O,10,FALSE)=0,"",VLOOKUP($A8,'Annex 2 EHV charges'!$A:$O,10,FALSE)),"") -> 2.57 | H8: =IFERROR(IF(VLOOKUP($A8,'Annex 2 EHV charges'!$A:$O,11,FALSE)=0,"",VLOOKUP($A8,'Annex 2 EHV charges'!$A:$O,11,FALSE)),"") -> 2.57
A9: {=IFERROR(INDEX('Annex 2 EHV charges'!$A$11:$A$260, MATCH(0, IF(ISBLANK('Annex 2 EHV charges'!$A$11:$A$260),1, COUNTIF(A$4:$A8, 'Annex 2 EHV charges'!$A$11:$A$260)), 0)),"")} -> 804 | B9: =IF($A9="","",VLOOKUP($A9,'Annex 2 EHV charges'!$A:$O,2,0)) -> 804 | C9: =IF($A9="","",VLOOKUP($A9,'Annex 2 EHV charges'!$A:$O,3,0)) -> 1800060532726 | D9: =IF($A9="","",VLOOKUP($A9,'Annex 2 EHV charges'!$A:$O,7,0)) -> Blantyre Muir | E9: =IFERROR(IF(VLOOKUP($A9,'Annex 2 EHV charges'!$A:$O,8,FALSE)=0,"",VLOOKUP($A9,'Annex 2 EHV charges'!$A:$O,8,FALSE)),"") | F9: =IFERROR(IF(VLOOKUP($A9,'Annex 2 EHV charges'!$A:$O,9,FALSE)=0,"",VLOOKUP($A9,'Annex 2 EHV charges'!$A:$O,9,FALSE)),"") -> 408.53 | G9: =IFERROR(IF(VLOOKUP($A9,'Annex 2 EHV charges'!$A:$O,10,FALSE)=0,"",VLOOKUP($A9,'Annex 2 EHV charges'!$A:$O,10,FALSE)),"") -> 0.82 | H9: =IFERROR(IF(VLOOKUP($A9,'Annex 2 EHV charges'!$A:$O,11,FALSE)=0,"",VLOOKUP($A9,'Annex 2 EHV charges'!$A:$O,11,FALSE)),"") -> 0.82
A10: {=IFERROR(INDEX('Annex 2 EHV charges'!$A$11:$A$260, MATCH(0, IF(ISBLANK('Annex 2 EHV charges'!$A$11:$A$260),1, COUNTIF(A$4:$A9, 'Annex 2 EHV charges'!$A$11:$A$260)), 0)),"")} -> 805 | B10: =IF($A10="","",VLOOKUP($A10,'Annex 2 EHV charges'!$A:$O,2,0)) -> 805 | C10: =IF($A10="","",VLOOKUP($A10,'Annex 2 EHV charges'!$A:$O,3,0)) -> 1800060587850 | D10: =IF($A10="","",VLOOKUP($A10,'Annex 2 EHV charges'!$A:$O,7,0)) -> Hunterston WF | E10: =IFERROR(IF(VLOOKUP($A10,'Annex 2 EHV charges'!$A:$O,8,FALSE)=0,"",VLOOKUP($A10,'Annex 2 EHV charges'!$A:$O,8,FALSE)),"") | F10: =IFERROR(IF(VLOOKUP($A10,'Annex 2 EHV charges'!$A:$O,9,FALSE)=0,"",VLOOKUP($A10,'Annex 2 EHV charges'!$A:$O,9,FALSE)),"") -> 117.17 | G10: =IFERROR(IF(VLOOKUP($A10,'Annex 2 EHV charges'!$A:$O,10,FALSE)=0,"",VLOOKUP($A10,'Annex 2 EHV charges'!$A:$O,10,FALSE)),"") -> 0.95 | H10: =IFERROR(IF(VLOOKUP($A10,'Annex 2 EHV charges'!$A:$O,11,FALSE)=0,"",VLOOKUP($A10,'Annex 2 EHV charges'!$A:$O,11,FALSE)),"") -> 0.95
A11: {=IFERROR(INDEX('Annex 2 EHV charges'!$A$11:$A$260, MATCH(0, IF(ISBLANK('Annex 2 EHV charges'!$A$11:$A$260),1, COUNTIF(A$4:$A10, 'Annex 2 EHV charges'!$A$11:$A$260)), 0)),"")} -> 806 | B11: =IF($A11="","",VLOOKUP($A11,'Annex 2 EHV charges'!$A:$O,2,0)) -> 806 | C11: =IF($A11="","",VLOOKUP($A11,'Annex 2 EHV charges'!$A:$O,3,0)) -> 1800060532647 | D11: =IF($A11="","",VLOOKUP($A11,'Annex 2 EHV charges'!$A:$O,7,0)) -> Middleton Farm | E11: =IFERROR(IF(VLOOKUP($A11,'Annex 2 EHV charges'!$A:$O,8,FALSE)=0,"",VLOOKUP($A11,'Annex 2 EHV charges'!$A:$O,8,FALSE)),"") | F11: =IFERROR(IF(VLOOKUP($A11,'Annex 2 EHV charges'!$A:$O,9,FALSE)=0,"",VLOOKUP($A11,'Annex 2 EHV charges'!$A:$O,9,FALSE)),"") -> 253.36 | G11: =IFERROR(IF(VLOOKUP($A11,'Annex 2 EHV charges'!$A:$O,10,FALSE)=0,"",VLOOKUP($A11,'Annex 2 EHV charges'!$A:$O,10,FALSE)),"") -> 2.55 | H11: =IFERROR(IF(VLOOKUP($A11,'Annex 2 EHV charges'!$A:$O,11,FALSE)=0,"",VLOOKUP($A11,'Annex 2 EHV charges'!$A:$O,11,FALSE)),"") -> 2.55
A12: {=IFERROR(INDEX('Annex 2 EHV charges'!$A$11:$A$260, MATCH(0, IF(ISBLANK('Annex 2 EHV charges'!$A$11:$A$260),1, COUNTIF(A$4:$A11, 'Annex 2 EHV charges'!$A$11:$A$260)), 0)),"")} -> 807 | B12: =IF($A12="","",VLOOKUP($A12,'Annex 2 EHV charges'!$A:$O,2,0)) -> 807 | C12: =IF($A12="","",VLOOKUP($A12,'Annex 2 EHV charges'!$A:$O,3,0)) -> 1800060532665 | D12: =IF($A12="","",VLOOKUP($A12,'Annex 2 EHV charges'!$A:$O,7,0)) -> Neilston Community | E12: =IFERROR(IF(VLOOKUP($A12,'Annex 2 EHV charges'!$A:$O,8,FALSE)=0,"",VLOOKUP($A12,'Annex 2 EHV charges'!$A:$O,8,FALSE)),"") | F12: =IFERROR(IF(VLOOKUP($A12,'Annex 2 EHV charges'!$A:$O,9,FALSE)=0,"",VLOOKUP($A12,'Annex 2 EHV charges'!$A:$O,9,FALSE)),"") -> 149.6 | G12: =IFERROR(IF(VLOOKUP($A12,'Annex 2 EHV charges'!$A:$O,10,FALSE)=0,"",VLOOKUP($A12,'Annex 2 EHV charges'!$A:$O,10,FALSE)),"") -> 2.65 | H12: =IFERROR(IF(VLOOKUP($A12,'Annex 2 EHV charges'!$A:$O,11,FALSE)=0,"",VLOOKUP($A12,'Annex 2 EHV charges'!$A:$O,11,FALSE)),"") -> 2.65
A13: {=IFERROR(INDEX('Annex 2 EHV charges'!$A$11:$A$260, MATCH(0, IF(ISBLANK('Annex 2 EHV charges'!$A$11:$A$260),1, COUNTIF(A$4:$A12, 'Annex 2 EHV charges'!$A$11:$A$260)), 0)),"")} -> 808 | B13: =IF($A13="","",VLOOKUP($A13,'Annex 2 EHV charges'!$A:$O,2,0)) -> 808 | C13: =IF($A13="","",VLOOKUP($A13,'Annex 2 EHV charges'!$A:$O,3,0)) -> 1800053653870 | D13: =IF($A13="","",VLOOKUP($A13,'Annex 2 EHV charges'!$A:$O,7,0)) -> Garlaff Landfill | E13: =IFERROR(IF(VLOOKUP($A13,'Annex 2 EHV charges'!$A:$O,8,FALSE)=0,"",VLOOKUP($A13,'Annex 2 EHV charges'!$A:$O,8,FALSE)),"") | F13: =IFERROR(IF(VLOOKUP($A13,'Annex 2 EHV charges'!$A:$O,9,FALSE)=0,"",VLOOKUP($A13,'Annex 2 EHV charges'!$A:$O,9,FALSE)),"") -> 121.27 | G13: =IFERROR(IF(VLOOKUP($A13,'Annex 2 EHV charges'!$A:$O,10,FALSE)=0,"",VLOOKUP($A13,'Annex 2 EHV charges'!$A:$O,10,FALSE)),"") -> 0.8 | H13: =IFERROR(IF(VLOOKUP($A13,'Annex 2 EHV charges'!$A:$O,11,FALSE)=0,"",VLOOKUP($A13,'Annex 2 EHV charges'!$A:$O,11,FALSE)),"") -> 0.8
A14: {=IFERROR(INDEX('Annex 2 EHV charges'!$A$11:$A$260, MATCH(0, IF(ISBLANK('Annex 2 EHV charges'!$A$11:$A$260),1, COUNTIF(A$4:$A13, 'Annex 2 EHV charges'!$A$11:$A$260)), 0)),"")} -> 809 | B14: =IF($A14="","",VLOOKUP($A14,'Annex 2 EHV charges'!$A:$O,2,0)) -> 809 | C14: =IF($A14="","",VLOOKUP($A14,'Annex 2 EHV charges'!$A:$O,3,0)) -> 1800054992968 | D14: =IF($A14="","",VLOOKUP($A14,'Annex 2 EHV charges'!$A:$O,7,0)) -> Hagshaw Hill Extension | E14: =IFERROR(IF(VLOOKUP($A14,'Annex 2 EHV charges'!$A:$O,8,FALSE)=0,"",VLOOKUP($A14,'Annex 2 EHV charges'!$A:$O,8,FALSE)),"") | F14: =IFERROR(IF(VLOOKUP($A14,'Annex 2 EHV charges'!$A:$O,9,FALSE)=0,"",VLOOKUP($A14,'Annex 2 EHV charges'!$A:$O,9,FALSE)),"") -> 792.43 | G14: =IFERROR(IF(VLOOKUP($A14,'Annex 2 EHV charges'!$A:$O,10,FALSE)=0,"",VLOOKUP($A14,'Annex 2 EHV charges'!$A:$O,10,FALSE)),"") -> 0.83 | H14: =IFERROR(IF(VLOOKUP($A14,'Annex 2 EHV charges'!$A:$O,11,FALSE)=0,"",VLOOKUP($A14,'Annex 2 EHV charges'!$A:$O,11,FALSE)),"") -> 0.83
A15: {=IFERROR(INDEX('Annex 2 EHV charges'!$A$11:$A$260, MATCH(0, IF(ISBLANK('Annex 2 EHV charges'!$A$11:$A$260),1, COUNTIF(A$4:$A14, 'Annex 2 EHV charges'!$A$11:$A$260)), 0)),"")} -> 811 | B15: =IF($A15="","",VLOOKUP($A15,'Annex 2 EHV charges'!$A:$O,2,0)) -> 811 | C15: =IF($A15="","",VLOOKUP($A15,'Annex 2 EHV charges'!$A:$O,3,0)) -> 1800060328035 | D15: =IF($A15="","",VLOOKUP($A15,'Annex 2 EHV charges'!$A:$O,7,0)) -> Muirhall | E15: =IFERROR(IF(VLOOKUP($A15,'Annex 2 EHV charges'!$A:$O,8,FALSE)=0,"",VLOOKUP($A15,'Annex 2 EHV charges'!$A:$O,8,FALSE)),"") | F15: =IFERROR(IF(VLOOKUP($A15,'Annex 2 EHV charges'!$A:$O,9,FALSE)=0,"",VLOOKUP($A15,'Annex 2 EHV charges'!$A:$O,9,FALSE)),"") -> 376.81 | G15: =IFERROR(IF(VLOOKUP($A15,'Annex 2 EHV charges'!$A:$O,10,FALSE)=0,"",VLOOKUP($A15,'Annex 2 EHV charges'!$A:$O,10,FALSE)),"") -> 2.54 | H15: =IFERROR(IF(VLOOKUP($A15,'Annex 2 EHV charges'!$A:$O,11,FALSE)=0,"",VLOOKUP($A15,'Annex 2 EHV charges'!$A:$O,11,FALSE)),"") -> 2.54
A16: {=IFERROR(INDEX('Annex 2 EHV charges'!$A$11:$A$260, MATCH(0, IF(ISBLANK('Annex 2 EHV charges'!$A$11:$A$260),1, COUNTIF(A$4:$A15, 'Annex 2 EHV charges'!$A$11:$A$260)), 0)),"")} -> 812 | B16: =IF($A16="","",VLOOKUP($A16,'Annex 2 EHV charges'!$A:$O,2,0)) -> 812 | C16: =IF($A16="","",VLOOKUP($A16,'Annex 2 EHV charges'!$A:$O,3,0)) -> 1800060372113 | D16: =IF($A16="","",VLOOKUP($A16,'Annex 2 EHV charges'!$A:$O,7,0)) -> Burnfoot | E16: =IFERROR(IF(VLOOKUP($A16,'Annex 2 EHV charges'!$A:$O,8,FALSE)=0,"",VLOOKUP($A16,'Annex 2 EHV charges'!$A:$O,8,FALSE)),"") | F16: =IFERROR(IF(VLOOKUP($A16,'Annex 2 EHV charges'!$A:$O,9,FALSE)=0,"",VLOOKUP($A16,'Annex 2 EHV charges'!$A:$O,9,FALSE)),"") -> 126.65 | G16: =IFERROR(IF(VLOOKUP($A16,'Annex 2 EHV charges'!$A:$O,10,FALSE)=0,"",VLOOKUP($A16,'Annex 2 EHV charges'!$A:$O,10,FALSE)),"") -> 0.88 | H16: =IFERROR(IF(VLOOKUP($A16,'Annex 2 EHV charges'!$A:$O,11,FALSE)=0,"",VLOOKUP($A16,'Annex 2 EHV charges'!$A:$O,11,FALSE)),"") -> 0.88
... A254: {=IFERROR(INDEX('Annex 2 EHV charges'!$A$11:$A$260, MATCH(0, IF(ISBLANK('Annex 2 EHV charges'!$A$11:$A$260),1, COUNTIF(A$4:$A253, 'Annex 2 EHV charges'!$A$11:$A$260)), 0)),"")} | B254: =IF($A254="","",VLOOKUP($A254,'Annex 2 EHV charges'!$A:$O,2,0)) | C254: =IF($A254="","",VLOOKUP($A254,'Annex 2 EHV charges'!$A:$O,3,0)) | D254: =IF($A254="","",VLOOKUP($A254,'Annex 2 EHV charges'!$A:$O,7,0)) | E254: =IFERROR(IF(VLOOKUP($A254,'Annex 2 EHV charges'!$A:$O,8,FALSE)=0,"",VLOOKUP($A254,'Annex 2 EHV charges'!$A:$O,8,FALSE)),"") | F254: =IFERROR(IF(VLOOKUP($A254,'Annex 2 EHV charges'!$A:$O,9,FALSE)=0,"",VLOOKUP($A254,'Annex 2 EHV charges'!$A:$O,9,FALSE)),"") | G254: =IFERROR(IF(VLOOKUP($A254,'Annex 2 EHV charges'!$A:$O,10,FALSE)=0,"",VLOOKUP($A254,'Annex 2 EHV charges'!$A:$O,10,FALSE)),"") | H254: =IFERROR(IF(VLOOKUP($A254,'Annex 2 EHV charges'!$A:$O,11,FALSE)=0,"",VLOOKUP($A254,'Annex 2 EHV charges'!$A:$O,11,FALSE)),"")

Sheet Annex 2b Export
A1: Note: The list of MPANs / MSIDs provided may be incomplete; the DNO reserves the right to apply the listed charges to any other MPANs / MSIDs associated with the site. Note: This table is automatically populated based on the content of the tab entitled 'Annex 2 EHV Charges'. The timebands are as shown in Annex 2.
A2: =Overview!B4& " - Effective from "&Overview!D4&" - "&Overview!E4&" EDCM export charges" -> SP Distribution - Effective from 1 April 2018 - Final EDCM export charges
A4: Export Unique Identifier | B4: LLFC | C4: Export MPANs/MSIDs | D4: Name | E4: ='Annex 2 EHV charges'!L10 -> Export Super Red unit charge (p/kWh) | F4: ='Annex 2 EHV charges'!M10 -> Export fixed charge (p/day) | G4: ='Annex 2 EHV charges'!N10 -> Export capacity charge (p/kVA/day) | H4: ='Annex 2 EHV charges'!O10 -> Export exceeded capacity charge (p/kVA/day)
A5: {=IFERROR(INDEX('Annex 2 EHV charges'!$D$11:$D$260, MATCH(0, IF(ISBLANK('Annex 2 EHV charges'!$D$11:$D$260),1, COUNTIF(A$4:$A4, 'Annex 2 EHV charges'!$D$11:$D$260)), 0)),"")} -> 644 | B5: =IF($A5="","",VLOOKUP($A5,'Annex 2 EHV charges'!$D:$O,2,0)) -> 644 | C5: =IF($A5="","",VLOOKUP($A5,'Annex 2 EHV charges'!$D:$O,3,0)) -> 1800060775990 | D5: =IF($A5="","",VLOOKUP($A5,'Annex 2 EHV charges'!$D:$O,4,0)) -> Rhodders | E5: =IFERROR(IF(VLOOKUP($A5,'Annex 2 EHV charges'!$D:$O,9,FALSE)=0,"",VLOOKUP($A5,'Annex 2 EHV charges'!$D:$O,9,FALSE)),"") | F5: =IFERROR(IF(VLOOKUP($A5,'Annex 2 EHV charges'!$D:$O,10,FALSE)=0,"",VLOOKUP($A5,'Annex 2 EHV charges'!$D:$O,10,FALSE)),"") -> 5861.03 | G5: =IFERROR(IF(VLOOKUP($A5,'Annex 2 EHV charges'!$D:$O,11,FALSE)=0,"",VLOOKUP($A5,'Annex 2 EHV charges'!$D:$O,11,FALSE)),"") -> 0.05 | H5: =IFERROR(IF(VLOOKUP($A5,'Annex 2 EHV charges'!$D:$O,12,FALSE)=0,"",VLOOKUP($A5,'Annex 2 EHV charges'!$D:$O,12,FALSE)),"") -> 0.05
A6: {=IFERROR(INDEX('Annex 2 EHV charges'!$D$11:$D$260, MATCH(0, IF(ISBLANK('Annex 2 EHV charges'!$D$11:$D$260),1, COUNTIF(A$4:$A5, 'Annex 2 EHV charges'!$D$11:$D$260)), 0)),"")} -> MSID 8182 | B6: =IF($A6="","",VLOOKUP($A6,'Annex 2 EHV charges'!$D:$O,2,0)) -> MSID 8182 | C6: =IF($A6="","",VLOOKUP($A6,'Annex 2 EHV charges'!$D:$O,3,0)) -> MSID 8182 | D6: =IF($A6="","",VLOOKUP($A6,'Annex 2 EHV charges'!$D:$O,4,0)) -> Minsca | E6: =IFERROR(IF(VLOOKUP($A6,'Annex 2 EHV charges'!$D:$O,9,FALSE)=0,"",VLOOKUP($A6,'Annex 2 EHV charges'!$D:$O,9,FALSE)),"") | F6: =IFERROR(IF(VLOOKUP($A6,'Annex 2 EHV charges'!$D:$O,10,FALSE)=0,"",VLOOKUP($A6,'Annex 2 EHV charges'!$D:$O,10,FALSE)),"") | G6: =IFERROR(IF(VLOOKUP($A6,'Annex 2 EHV charges'!$D:$O,11,FALSE)=0,"",VLOOKUP($A6,'Annex 2 EHV charges'!$D:$O,11,FALSE)),"") | H6: =IFERROR(IF(VLOOKUP($A6,'Annex 2 EHV charges'!$D:$O,12,FALSE)=0,"",VLOOKUP($A6,'Annex 2 EHV charges'!$D:$O,12,FALSE)),"")
A7: {=IFERROR(INDEX('Annex 2 EHV charges'!$D$11:$D$260, MATCH(0, IF(ISBLANK('Annex 2 EHV charges'!$D$11:$D$260),1, COUNTIF(A$4:$A6, 'Annex 2 EHV charges'!$D$11:$D$260)), 0)),"")} -> 683 | B7: =IF($A7="","",VLOOKUP($A7,'Annex 2 EHV charges'!$D:$O,2,0)) -> 683 | C7: =IF($A7="","",VLOOKUP($A7,'Annex 2 EHV charges'!$D:$O,3,0)) -> 1800060539971 | D7: =IF($A7="","",VLOOKUP($A7,'Annex 2 EHV charges'!$D:$O,4,0)) -> Bankend Rig | E7: =IFERROR(IF(VLOOKUP($A7,'Annex 2 EHV charges'!$D:$O,9,FALSE)=0,"",VLOOKUP($A7,'Annex 2 EHV charges'!$D:$O,9,FALSE)),"") | F7: =IFERROR(IF(VLOOKUP($A7,'Annex 2 EHV charges'!$D:$O,10,FALSE)=0,"",VLOOKUP($A7,'Annex 2 EHV charges'!$D:$O,10,FALSE)),"") -> 5449.73 | G7: =IFERROR(IF(VLOOKUP($A7,'Annex 2 EHV charges'!$D:$O,11,FALSE)=0,"",VLOOKUP($A7,'Annex 2 EHV charges'!$D:$O,11,FALSE)),"") -> 0.05 | H7: =IFERROR(IF(VLOOKUP($A7,'Annex 2 EHV charges'!$D:$O,12,FALSE)=0,"",VLOOKUP($A7,'Annex 2 EHV charges'!$D:$O,12,FALSE)),"") -> 0.05
A8: {=IFERROR(INDEX('Annex 2 EHV charges'!$D$11:$D$260, MATCH(0, IF(ISBLANK('Annex 2 EHV charges'!$D$11:$D$260),1, COUNTIF(A$4:$A7, 'Annex 2 EHV charges'!$D$11:$D$260)), 0)),"")} -> 684 | B8: =IF($A8="","",VLOOKUP($A8,'Annex 2 EHV charges'!$D:$O,2,0)) -> 684 | C8: =IF($A8="","",VLOOKUP($A8,'Annex 2 EHV charges'!$D:$O,3,0)) -> 1800060532717 | D8: =IF($A8="","",VLOOKUP($A8,'Annex 2 EHV charges'!$D:$O,4,0)) -> Barlockhart Moor | E8: =IFERROR(IF(VLOOKUP($A8,'Annex 2 EHV charges'!$D:$O,9,FALSE)=0,"",VLOOKUP($A8,'Annex 2 EHV charges'!$D:$O,9,FALSE)),"") | F8: =IFERROR(IF(VLOOKUP($A8,'Annex 2 EHV charges'!$D:$O,10,FALSE)=0,"",VLOOKUP($A8,'Annex 2 EHV charges'!$D:$O,10,FALSE)),"") -> 9901.7 | G8: =IFERROR(IF(VLOOKUP($A8,'Annex 2 EHV charges'!$D:$O,11,FALSE)=0,"",VLOOKUP($A8,'Annex 2 EHV charges'!$D:$O,11,FALSE)),"") -> 0.05 | H8: =IFERROR(IF(VLOOKUP($A8,'Annex 2 EHV charges'!$D:$O,12,FALSE)=0,"",VLOOKUP($A8,'Annex 2 EHV charges'!$D:$O,12,FALSE)),"") -> 0.05
A9: {=IFERROR(INDEX('Annex 2 EHV charges'!$D$11:$D$260, MATCH(0, IF(ISBLANK('Annex 2 EHV charges'!$D$11:$D$260),1, COUNTIF(A$4:$A8, 'Annex 2 EHV charges'!$D$11:$D$260)), 0)),"")} -> 685 | B9: =IF($A9="","",VLOOKUP($A9,'Annex 2 EHV charges'!$D:$O,2,0)) -> 685 | C9: =IF($A9="","",VLOOKUP($A9,'Annex 2 EHV charges'!$D:$O,3,0)) -> 1800060532735 | D9: =IF($A9="","",VLOOKUP($A9,'Annex 2 EHV charges'!$D:$O,4,0)) -> Blantyre Muir | E9: =IFERROR(IF(VLOOKUP($A9,'Annex 2 EHV charges'!$D:$O,9,FALSE)=0,"",VLOOKUP($A9,'Annex 2 EHV charges'!$D:$O,9,FALSE)),"") | F9: =IFERROR(IF(VLOOKUP($A9,'Annex 2 EHV charges'!$D:$O,10,FALSE)=0,"",VLOOKUP($A9,'Annex 2 EHV charges'!$D:$O,10,FALSE)),"") -> 6437.57 | G9: =IFERROR(IF(VLOOKUP($A9,'Annex 2 EHV charges'!$D:$O,11,FALSE)=0,"",VLOOKUP($A9,'Annex 2 EHV charges'!$D:$O,11,FALSE)),"") -> 0.05 | H9: =IFERROR(IF(VLOOKUP($A9,'Annex 2 EHV charges'!$D:$O,12,FALSE)=0,"",VLOOKUP($A9,'Annex 2 EHV charges'!$D:$O,12,FALSE)),"") -> 0.05
A10: {=IFERROR(INDEX('Annex 2 EHV charges'!$D$11:$D$260, MATCH(0, IF(ISBLANK('Annex 2 EHV charges'!$D$11:$D$260),1, COUNTIF(A$4:$A9, 'Annex 2 EHV charges'!$D$11:$D$260)), 0)),"")} -> 693 | B10: =IF($A10="","",VLOOKUP($A10,'Annex 2 EHV charges'!$D:$O,2,0)) -> 693 | C10: =IF($A10="","",VLOOKUP($A10,'Annex 2 EHV charges'!$D:$O,3,0)) -> 1800060587869 | D10: =IF($A10="","",VLOOKUP($A10,'Annex 2 EHV charges'!$D:$O,4,0)) -> Hunterston WF | E10: =IFERROR(IF(VLOOKUP($A10,'Annex 2 EHV charges'!$D:$O,9,FALSE)=0,"",VLOOKUP($A10,'Annex 2 EHV charges'!$D:$O,9,FALSE)),"") | F10: =IFERROR(IF(VLOOKUP($A10,'Annex 2 EHV charges'!$D:$O,10,FALSE)=0,"",VLOOKUP($A10,'Annex 2 EHV charges'!$D:$O,10,FALSE)),"") -> 8746.35 | G10: =IFERROR(IF(VLOOKUP($A10,'Annex 2 EHV charges'!$D:$O,11,FALSE)=0,"",VLOOKUP($A10,'Annex 2 EHV charges'!$D:$O,11,FALSE)),"") -> 0.05 | H10: =IFERROR(IF(VLOOKUP($A10,'Annex 2 EHV charges'!$D:$O,12,FALSE)=0,"",VLOOKUP($A10,'Annex 2 EHV charges'!$D:$O,12,FALSE)),"") -> 0.05
A11: {=IFERROR(INDEX('Annex 2 EHV charges'!$D$11:$D$260, MATCH(0, IF(ISBLANK('Annex 2 EHV charges'!$D$11:$D$260),1, COUNTIF(A$4:$A10, 'Annex 2 EHV charges'!$D$11:$D$260)), 0)),"")} -> 688 | B11: =IF($A11="","",VLOOKUP($A11,'Annex 2 EHV charges'!$D:$O,2,0)) -> 688 | C11: =IF($A11="","",VLOOKUP($A11,'Annex 2 EHV charges'!$D:$O,3,0)) -> 1800060532656 | D11: =IF($A11="","",VLOOKUP($A11,'Annex 2 EHV charges'!$D:$O,4,0)) -> Middleton Farm | E11: =IFERROR(IF(VLOOKUP($A11,'Annex 2 EHV charges'!$D:$O,9,FALSE)=0,"",VLOOKUP($A11,'Annex 2 EHV charges'!$D:$O,9,FALSE)),"") | F11: =IFERROR(IF(VLOOKUP($A11,'Annex 2 EHV charges'!$D:$O,10,FALSE)=0,"",VLOOKUP($A11,'Annex 2 EHV charges'!$D:$O,10,FALSE)),"") -> 5756.23 | G11: =IFERROR(IF(VLOOKUP($A11,'Annex 2 EHV charges'!$D:$O,11,FALSE)=0,"",VLOOKUP($A11,'Annex 2 EHV charges'!$D:$O,11,FALSE)),"") -> 0.05 | H11: =IFERROR(IF(VLOOKUP($A11,'Annex 2 EHV charges'!$D:$O,12,FALSE)=0,"",VLOOKUP($A11,'Annex 2 EHV charges'!$D:$O,12,FALSE)),"") -> 0.05
A12: {=IFERROR(INDEX('Annex 2 EHV charges'!$D$11:$D$260, MATCH(0, IF(ISBLANK('Annex 2 EHV charges'!$D$11:$D$260),1, COUNTIF(A$4:$A11, 'Annex 2 EHV charges'!$D$11:$D$260)), 0)),"")} -> 689 | B12: =IF($A12="","",VLOOKUP($A12,'Annex 2 EHV charges'!$D:$O,2,0)) -> 689 | C12: =IF($A12="","",VLOOKUP($A12,'Annex 2 EHV charges'!$D:$O,3,0)) -> 1800060532674 | D12: =IF($A12="","",VLOOKUP($A12,'Annex 2 EHV charges'!$D:$O,4,0)) -> Neilston Community | E12: =IFERROR(IF(VLOOKUP($A12,'Annex 2 EHV charges'!$D:$O,9,FALSE)=0,"",VLOOKUP($A12,'Annex 2 EHV charges'!$D:$O,9,FALSE)),"") | F12: =IFERROR(IF(VLOOKUP($A12,'Annex 2 EHV charges'!$D:$O,10,FALSE)=0,"",VLOOKUP($A12,'Annex 2 EHV charges'!$D:$O,10,FALSE)),"") -> 7061.91 | G12: =IFERROR(IF(VLOOKUP($A12,'Annex 2 EHV charges'!$D:$O,11,FALSE)=0,"",VLOOKUP($A12,'Annex 2 EHV charges'!$D:$O,11,FALSE)),"") -> 0.05 | H12: =IFERROR(IF(VLOOKUP($A12,'Annex 2 EHV charges'!$D:$O,12,FALSE)=0,"",VLOOKUP($A12,'Annex 2 EHV charges'!$D:$O,12,FALSE)),"") -> 0.05
A13: {=IFERROR(INDEX('Annex 2 EHV charges'!$D$11:$D$260, MATCH(0, IF(ISBLANK('Annex 2 EHV charges'!$D$11:$D$260),1, COUNTIF(A$4:$A12, 'Annex 2 EHV charges'!$D$11:$D$260)), 0)),"")} -> 681 | B13: =IF($A13="","",VLOOKUP($A13,'Annex 2 EHV charges'!$D:$O,2,0)) -> 681 | C13: =IF($A13="","",VLOOKUP($A13,'Annex 2 EHV charges'!$D:$O,3,0)) -> 1800053653880 | D13: =IF($A13="","",VLOOKUP($A13,'Annex 2 EHV charges'!$D:$O,4,0)) -> Garlaff Landfill | E13: =IFERROR(IF(VLOOKUP($A13,'Annex 2 EHV charges'!$D:$O,9,FALSE)=0,"",VLOOKUP($A13,'Annex 2 EHV charges'!$D:$O,9,FALSE)),"") | F13: =IFERROR(IF(VLOOKUP($A13,'Annex 2 EHV charges'!$D:$O,10,FALSE)=0,"",VLOOKUP($A13,'Annex 2 EHV charges'!$D:$O,10,FALSE)),"") | G13: =IFERROR(IF(VLOOKUP($A13,'Annex 2 EHV charges'!$D:$O,11,FALSE)=0,"",VLOOKUP($A13,'Annex 2 EHV charges'!$D:$O,11,FALSE)),"") | H13: =IFERROR(IF(VLOOKUP($A13,'Annex 2 EHV charges'!$D:$O,12,FALSE)=0,"",VLOOKUP($A13,'Annex 2 EHV charges'!$D:$O,12,FALSE)),"")
A14: {=IFERROR(INDEX('Annex 2 EHV charges'!$D$11:$D$260, MATCH(0, IF(ISBLANK('Annex 2 EHV charges'!$D$11:$D$260),1, COUNTIF(A$4:$A13, 'Annex 2 EHV charges'!$D$11:$D$260)), 0)),"")} -> 629 | B14: =IF($A14="","",VLOOKUP($A14,'Annex 2 EHV charges'!$D:$O,2,0)) -> 629 | C14: =IF($A14="","",VLOOKUP($A14,'Annex 2 EHV charges'!$D:$O,3,0)) -> 1800054992977 | D14: =IF($A14="","",VLOOKUP($A14,'Annex 2 EHV charges'!$D:$O,4,0)) -> Hagshaw Hill Extension | E14: =IFERROR(IF(VLOOKUP($A14,'Annex 2 EHV charges'!$D:$O,9,FALSE)=0,"",VLOOKUP($A14,'Annex 2 EHV charges'!$D:$O,9,FALSE)),"") | F14: =IFERROR(IF(VLOOKUP($A14,'Annex 2 EHV charges'!$D:$O,10,FALSE)=0,"",VLOOKUP($A14,'Annex 2 EHV charges'!$D:$O,10,FALSE)),"") -> 20011.69 | G14: =IFERROR(IF(VLOOKUP($A14,'Annex 2 EHV charges'!$D:$O,11,FALSE)=0,"",VLOOKUP($A14,'Annex 2 EHV charges'!$D:$O,11,FALSE)),"") -> 0.05 | H14: =IFERROR(IF(VLOOKUP($A14,'Annex 2 EHV charges'!$D:$O,12,FALSE)=0,"",VLOOKUP($A14,'Annex 2 EHV charges'!$D:$O,12,FALSE)),"") -> 0.05
A15: {=IFERROR(INDEX('Annex 2 EHV charges'!$D$11:$D$260, MATCH(0, IF(ISBLANK('Annex 2 EHV charges'!$D$11:$D$260),1, COUNTIF(A$4:$A14, 'Annex 2 EHV charges'!$D$11:$D$260)), 0)),"")} -> 671 | B15: =IF($A15="","",VLOOKUP($A15,'Annex 2 EHV charges'!$D:$O,2,0)) -> 671 | C15: =IF($A15="","",VLOOKUP($A15,'Annex 2 EHV charges'!$D:$O,3,0)) -> 1800060328044 | D15: =IF($A15="","",VLOOKUP($A15,'Annex 2 EHV charges'!$D:$O,4,0)) -> Muirhall | E15: =IFERROR(IF(VLOOKUP($A15,'Annex 2 EHV charges'!$D:$O,9,FALSE)=0,"",VLOOKUP($A15,'Annex 2 EHV charges'!$D:$O,9,FALSE)),"") | F15: =IFERROR(IF(VLOOKUP($A15,'Annex 2 EHV charges'!$D:$O,10,FALSE)=0,"",VLOOKUP($A15,'Annex 2 EHV charges'!$D:$O,10,FALSE)),"") -> 9043.53 | G15: =IFERROR(IF(VLOOKUP($A15,'Annex 2 EHV charges'!$D:$O,11,FALSE)=0,"",VLOOKUP($A15,'Annex 2 EHV charges'!$D:$O,11,FALSE)),"") -> 0.05 | H15: =IFERROR(IF(VLOOKUP($A15,'Annex 2 EHV charges'!$D:$O,12,FALSE)=0,"",VLOOKUP($A15,'Annex 2 EHV charges'!$D:$O,12,FALSE)),"") -> 0.05
A16: {=IFERROR(INDEX('Annex 2 EHV charges'!$D$11:$D$260, MATCH(0, IF(ISBLANK('Annex 2 EHV charges'!$D$11:$D$260),1, COUNTIF(A$4:$A15, 'Annex 2 EHV charges'!$D$11:$D$260)), 0)),"")} -> 672 | B16: =IF($A16="","",VLOOKUP($A16,'Annex 2 EHV charges'!$D:$O,2,0)) -> 672 | C16: =IF($A16="","",VLOOKUP($A16,'Annex 2 EHV charges'!$D:$O,3,0)) -> 1800060372122 | D16: =IF($A16="","",VLOOKUP($A16,'Annex 2 EHV charges'!$D:$O,4,0)) -> Burnfoot | E16: =IFERROR(IF(VLOOKUP($A16,'Annex 2 EHV charges'!$D:$O,9,FALSE)=0,"",VLOOKUP($A16,'Annex 2 EHV charges'!$D:$O,9,FALSE)),"") | F16: =IFERROR(IF(VLOOKUP($A16,'Annex 2 EHV charges'!$D:$O,10,FALSE)=0,"",VLOOKUP($A16,'Annex 2 EHV charges'!$D:$O,10,FALSE)),"") -> 8837.86 | G16: =IFERROR(IF(VLOOKUP($A16,'Annex 2 EHV charges'!$D:$O,11,FALSE)=0,"",VLOOKUP($A16,'Annex 2 EHV charges'!$D:$O,11,FALSE)),"") -> 0.05 | H16: =IFERROR(IF(VLOOKUP($A16,'Annex 2 EHV charges'!$D:$O,12,FALSE)=0,"",VLOOKUP($A16,'Annex 2 EHV charges'!$D:$O,12,FALSE)),"") -> 0.05
... A254: {=IFERROR(INDEX('Annex 2 EHV charges'!$D$11:$D$260, MATCH(0, IF(ISBLANK('Annex 2 EHV charges'!$D$11:$D$260),1, COUNTIF(A$4:$A253, 'Annex 2 EHV charges'!$D$11:$D$260)), 0)),"")} | B254: =IF($A254="","",VLOOKUP($A254,'Annex 2 EHV charges'!$D:$O,2,0)) | C254: =IF($A254="","",VLOOKUP($A254,'Annex 2 EHV charges'!$D:$O,3,0)) | D254: =IF($A254="","",VLOOKUP($A254,'Annex 2 EHV charges'!$D:$O,4,0)) | E254: =IFERROR(IF(VLOOKUP($A254,'Annex 2 EHV charges'!$D:$O,9,FALSE)=0,"",VLOOKUP($A254,'Annex 2 EHV charges'!$D:$O,9,FALSE)),"") | F254: =IFERROR(IF(VLOOKUP($A254,'Annex 2 EHV charges'!$D:$O,10,FALSE)=0,"",VLOOKUP($A254,'Annex 2 EHV charges'!$D:$O,10,FALSE)),"") | G254: =IFERROR(IF(VLOOKUP($A254,'Annex 2 EHV charges'!$D:$O,11,FALSE)=0,"",VLOOKUP($A254,'Annex 2 EHV charges'!$D:$O,11,FALSE)),"") | H254: =IFERROR(IF(VLOOKUP($A254,'Annex 2 EHV charges'!$D:$O,12,FALSE)=0,"",VLOOKUP($A254,'Annex 2 EHV charges'!$D:$O,12,FALSE)),"")

Sheet Annex 3 Preserved charges
A1: Back to Overview
A2: =Overview!B4& " - Effective from "&Overview!D4&" - "&Overview!E4&" LV and HV tariffs" -> SP Distribution - Effective from 1 April 2018 - Final LV and HV tariffs
A3: NHH preserved charges/additional LLFCs
B4: Closed LLFCs | C4: PCs | D4: Unit charge 1 (NHH) p/kWh | E4: Unit charge 2 (NHH) p/kWh | F4: Unit charge 3 (NHH) p/kWh | G4: Fixed charge p/MPAN/day
A5: Domestic Off Peak (related MPAN) | B5: 130, 134,135 | C5: 2 | D5: 1.097 | F5: 0 | H5: 0 | I5: 0 | J5: 0
A6: Small Non Domestic Unrestricted | B6: 200, 202,203, 205 | C6: 3 | D6: 2.446 | E6: 0 | F6: 0 | G6: 6.43 | H6: 0 | I6: 0 | J6: 0
A7: Small Non Domestic Two Rate | B7: 220, 222 | C7: 4 | D7: 2.951 | E7: 1.184 | F7: 0 | G7: 6.43 | H7: 0 | I7: 0 | J7: 0
A8: Small Non Domestic Off Peak (related MPAN) | B8: 223, 242, 243, 244, 245, 246 | C8: 3&4 | D8: 1.472 | F8: 0 | H8: 0 | I8: 0 | J8: 0
A9: HV Medium Non-Domestic | B9: 401 | C9: 5-8 | D9: 1.465 | E9: 1.016 | F9: 0 | G9: 318.78 | H9: 0 | I9: 0 | J9: 0
A10: Notes: | B10: Unit time periods are as specified in the SSC.
B11: SP Distribution uses a default tariff for invalid settlement combinations these will be charged at the Domestic Unrestricted Rates. The Domestic and Non-Domestic Off Peak (related MPAN) tariffs are supplementary to a standard published tariff and therefore only available under these conditions. Preserved tariffs are only available to existing supplies, subject to certain conditions: a) Suppliers may not normally transfer a meter point from one preserved tariff to another preserved tariff; b) If a supply under a preserved tariff should cease, other than on change of tenancy, the preserved tariff may not normally be restored; c) Any additional load requried to be supplied on the preserved tariff must be within the existing supply capacity.

Sheet Annex 4 LDNO charges
A1: Back to Overview | B1: Copy from CDCM table 3701 "Tariffs!A42:I84" and paste values into A14 | F1: Copy from EDCM table 6005 "LDNORev!B549:G683" and paste values into D57
A2: =Overview!B4& " - Effective from "&Overview!D4&" - "&Overview!E4&" LDNO tariffs" -> SP Distribution - Effective from 1 April 2018 - Final LDNO tariffs
A4: Time Bands for Half Hourly Metered Properties | F4: Time Bands for Half Hourly Unmetered Properties
A5: Time periods | B5: Red Time Band | C5: Amber Time Band | D5: Green Time Band | H5: Black Time Band | I5: Yellow Time Band | J5: Green Time Band
A6: Monday to Friday (Including Bank Holidays) All Year | B6: 16.30 - 19.30 | C6: 08.00 - 16.30 19.30 - 22.30 | D6: 00.00 - 08.00 22.30 - 00.00 | F6: Monday to Friday (Including Bank Holidays) June to August Inclusive | I6: 08.00 - 22.30 | J6: 00.00 - 08.00 22.30 - 00.00
A7: Saturday and Sunday All Year | C7: 16.00 - 20.00 | D7: 00.00 - 16.00 20.00 - 00.00 | F7: Monday to Friday (Including Bank Holidays) November to February Inclusive | H7: 16.30 - 19.30 | I7: 08.00 - 16.30 19.30 - 22.30 | J7: 00.00 - 08.00 22.30 - 00.00
A8: Notes | B8: All the above times are in UK Clock time | F8: Monday to Friday (Including Bank Holidays) March to May, & September to October, Inclusive | I8: 08.00 - 22.30 | J8: 00.00 - 08.00 22.30 - 00.00
F9: Saturday and Sunday | I9: 16.00 - 20.00 | J9: 00:00-16:00 20:00-00:00
F10: Notes | H10: All the above times are in UK Clock time
A13: Tariff name | B13: Unique billing identifier | C13: PCs | D13: ='Annex 1 LV and HV charges'!D13 -> Unit charge 1 (NHH) or red/black charge (HH) p/kWh | E13: ='Annex 1 LV and HV charges'!E13 -> Unit charge 2 (NHH) or amber/yellow charge (HH) p/kWh | F13: ='Annex 1 LV and HV charges'!F13 -> Green charge(HH) p/kWh | G13: ='Annex 1 LV and HV charges'!G13 -> Fixed charge p/MPAN/day | H13: ='Annex 1 LV and HV charges'!H13 -> Capacity charge p/kVA/day | I13: ='Annex 1 LV and HV charges'!I13 -> Exceeded capacity charge p/kVA/day | J13: ='Annex 1 LV and HV charges'!J13 -> Reactive power charge p/kVArh
A14: LDNO LV: Domestic Unrestricted | C14: 1 | D14: 1.481 | G14: 3.08
A15: LDNO LV: Domestic Two Rate | C15: 2 | D15: 1.749 | E15: 0.685 | G15: 3.08
A16: LDNO LV: Domestic Off Peak (related MPAN) | C16: 2 | D16: 0.672
A17: LDNO LV: Small Non Domestic Unrestricted | C17: 3 | D17: 1.499 | G17: 3.94
A18: LDNO LV: Small Non Domestic Two Rate | C18: 4 | D18: 1.809 | E18: 0.726 | G18: 3.94
A19: LDNO LV: Small Non Domestic Off Peak (related MPAN) | C19: 4 | D19: 0.902
A20: LDNO LV: LV Medium Non-Domestic | C20: 5-8 | D20: 1.358 | E20: 0.677 | G20: 18.4
A21: LDNO LV: LV Network Domestic | C21: 0 | D21: 5.459 | E21: 1.138 | F21: 0.647 | G21: 3.08
A22: LDNO LV: LV Network Non-Domestic Non-CT | C22: 0 | D22: 5.723 | E22: 1.166 | F22: 0.65 | G22: 3.94
A23: LDNO LV: LV HH Metered | C23: 0 | D23: 4.319 | E23: 0.986 | F23: 0.634 | G23: 15.62 | H23: 1.5 | I23: 2.2 | J23: 0.114
A24: LDNO LV: NHH UMS category A | C24: 8 | D24: 1.316
A25: LDNO LV: NHH UMS category B | C25: 1 | D25: 1.453
A26: LDNO LV: NHH UMS category C | C26: 1 | D26: 1.936
A27: LDNO LV: NHH UMS category D | C27: 1 | D27: 1.217
A28: LDNO LV: LV UMS (Pseudo HH Metered) | C28: 0 | D28: 9.341 | E28: 1.246 | F28: 0.923
A29: LDNO LV: LV Generation NHH or Aggregate HH | C29: 8&0 | D29: -0.762 | G29: 0
A30: LDNO LV: LV Generation Intermittent | C30: 0 | D30: -0.762 | G30: 0 | J30: 0.176
A31: LDNO LV: LV Generation Non-Intermittent | C31: 0 | D31: -5.617 | E31: -0.613 | F31: -0.045 | G31: 0 | J31: 0.176
A32: LDNO HV: Domestic Unrestricted | C32: 1 | D32: 0.838 | G32: 1.74
A33: LDNO HV: Domestic Two Rate | C33: 2 | D33: 0.99 | E33: 0.387 | G33: 1.74
A34: LDNO HV: Domestic Off Peak (related MPAN) | C34: 2 | D34: 0.38
A35: LDNO HV: Small Non Domestic Unrestricted | C35: 3 | D35: 0.848 | G35: 2.23
A36: LDNO HV: Small Non Domestic Two Rate | C36: 4 | D36: 1.023 | E36: 0.411 | G36: 2.23
A37: LDNO HV: Small Non Domestic Off Peak (related MPAN) | C37: 4 | D37: 0.51
A38: LDNO HV: LV Medium Non-Domestic | C38: 5-8 | D38: 0.768 | E38: 0.383 | G38: 10.41
A39: LDNO HV: LV Network Domestic | C39: 0 | D39: 3.089 | E39: 0.644 | F39: 0.366 | G39: 1.74
A40: LDNO HV: LV Network Non-Domestic Non-CT | C40: 0 | D40: 3.238 | E40: 0.66 | F40: 0.368 | G40: 2.23
A41: LDNO HV: LV HH Metered | C41: 0 | D41: 2.443 | E41: 0.558 | F41: 0.359 | G41: 8.84 | H41: 0.85 | I41: 1.24 | J41: 0.065
A42: LDNO HV: LV Sub HH Metered | C42: 0 | D42: 2.903 | E42: 0.752 | F42: 0.572 | G42: 5.1 | H42: 2.53 | I42: 2.88 | J42: 0.056
A43: LDNO HV: HV HH Metered | C43: 0 | D43: 2.498 | E43: 0.776 | F43: 0.651 | G43: 88.68 | H43: 3.2 | I43: 3.94 | J43: 0.037
A44: LDNO HV: NHH UMS category A | C44: 8 | D44: 0.745
A45: LDNO HV: NHH UMS category B | C45: 1 | D45: 0.822
A46: LDNO HV: NHH UMS category C | C46: 1 | D46: 1.096
A47: LDNO HV: NHH UMS category D | C47: 1 | D47: 0.689
A48: LDNO HV: LV UMS (Pseudo HH Metered) | C48: 0 | D48: 5.285 | E48: 0.705 | F48: 0.522
A49: LDNO HV: LV Generation NHH or Aggregate HH | C49: 8&0 | D49: -0.762 | G49: 0
A50: LDNO HV: LV Sub Generation NHH | C50: 8 | D50: -0.673 | G50: 0
A51: LDNO HV: LV Generation Intermittent | C51: 0 | D51: -0.762 | G51: 0 | J51: 0.176
A52: LDNO HV: LV Generation Non-Intermittent | C52: 0 | D52: -5.617 | E52: -0.613 | F52: -0.045 | G52: 0 | J52: 0.176
A53: LDNO HV: LV Sub Generation Intermittent | C53: 0 | D53: -0.673 | G53: 0 | J53: 0.155
A54: LDNO HV: LV Sub Generation Non-Intermittent | C54: 0 | D54: -5.025 | E54: -0.529 | F54: -0.038 | G54: 0 | J54: 0.155
A55: LDNO HV: HV Generation Intermittent | C55: 0 | D55: -0.407 | G55: 0 | J55: 0.124
A56: LDNO HV: HV Generation Non-Intermittent | C56: 0 | D56: -3.333 | E56: -0.266 | F56: -0.013 | G56: 0 | J56: 0.124
A57: LDNO HVplus: Domestic Unrestricted | D57: 0.575 | E57: 0 | G57: 1.19
A58: LDNO HVplus: Domestic Two Rate | D58: 0.679 | E58: 0.266 | G58: 1.19
A59: LDNO HVplus: Domestic Off Peak (related MPAN) | D59: 0.261
A60: LDNO HVplus: Small Non Domestic Unrestricted | D60: 0.582 | G60: 1.53
A61: LDNO HVplus: Small Non Domestic Two Rate | D61: 0.702 | E61: 0.282 | G61: 1.53
A62: LDNO HVplus: Small Non Domestic Off Peak (related MPAN) | D62: 0.35
A63: LDNO HVplus: LV Medium Non-Domestic | D63: 0.527 | E63: 0.263 | G63: 7.14
A64: LDNO HVplus: LV Sub Medium Non-Domestic | D64: 0.692 | E64: 0.403 | G64: 0
A65: LDNO HVplus: HV Medium Non-Domestic | D65: 0.63 | E65: 0.437 | G65: 137.13
A66: LDNO HVplus: LV Network Domestic | D66: 2.118 | E66: 0.441 | F66: 0.251 | G66: 1.19
A67: LDNO HVplus: LV Network Non-Domestic Non-CT | D67: 2.22 | E67: 0.453 | F67: 0.252 | G67: 1.53
A68: LDNO HVplus: LV HH Metered | D68: 1.675 | E68: 0.382 | F68: 0.246 | G68: 6.06 | H68: 0.58 | I68: 0.85 | J68: 0.044
A69: LDNO HVplus: LV Sub HH Metered | D69: 1.936 | E69: 0.501 | F69: 0.382 | G69: 3.4 | H69: 1.69 | I69: 1.92 | J69: 0.037
A70: LDNO HVplus: HV HH Metered | D70: 1.65 | E70: 0.512 | F70: 0.43 | G70: 58.57 | H70: 2.12 | I70: 2.6 | J70: 0.025
A71: LDNO HVplus: NHH UMS category A | D71: 0.511
A72: LDNO HVplus: NHH UMS category B | D72: 0.564
A73: LDNO HVplus: NHH UMS category C | D73: 0.751
A74: LDNO HVplus: NHH UMS category D | D74: 0.472
A75: LDNO HVplus: LV UMS (Pseudo HH Metered) | D75: 3.624 | E75: 0.483 | F75: 0.358
A76: LDNO HVplus: LV Generation NHH or Aggregate HH | D76: -0.288 | G76: 0
A77: LDNO HVplus: LV Sub Generation NHH | D77: -0.29 | G77: 0
A78: LDNO HVplus: LV Generation Intermittent | D78: -0.288 | G78: 0 | J78: 0.067
A79: LDNO HVplus: LV Generation Non-Intermittent | D79: -2.125 | E79: -0.232 | F79: -0.017 | G79: 0 | J79: 0.067
A80: LDNO HVplus: LV Sub Generation Intermittent | D80: -0.29 | G80: 0 | J80: 0.067
A81: LDNO HVplus: LV Sub Generation Non-Intermittent | D81: -2.162 | E81: -0.228 | F81: -0.016 | G81: 0 | J81: 0.067
A82: LDNO HVplus: HV Generation Intermittent | D82: -0.407 | G82: 99.41 | J82: 0.124
A83: LDNO HVplus: HV Generation Non-Intermittent | D83: -3.333 | E83: -0.266 | F83: -0.013 | G83: 99.41 | J83: 0.124
A84: LDNO EHV: Domestic Unrestricted | D84: 0.28 | G84: 0.58
A85: LDNO EHV: Domestic Two Rate | D85: 0.331 | E85: 0.129 | G85: 0.58
A86: LDNO EHV: Domestic Off Peak (related MPAN) | D86: 0.127
A87: LDNO EHV: Small Non Domestic Unrestricted | D87: 0.283 | G87: 0.74
A88: LDNO EHV: Small Non Domestic Two Rate | D88: 0.342 | E88: 0.137 | G88: 0.74
A89: LDNO EHV: Small Non Domestic Off Peak (related MPAN) | D89: 0.171
A90: LDNO EHV: LV Medium Non-Domestic | D90: 0.257 | E90: 0.128 | G90: 3.48
A91: LDNO EHV: LV Sub Medium Non-Domestic | D91: 0.337 | E91: 0.196 | G91: 0
A92: LDNO EHV: HV Medium Non-Domestic | D92: 0.307 | E92: 0.213 | G92: 66.81
A93: LDNO EHV: LV Network Domestic | D93: 1.032 | E93: 0.215 | F93: 0.122 | G93: 0.58
A94: LDNO EHV: LV Network Non-Domestic Non-CT | D94: 1.082 | E94: 0.22 | F94: 0.123 | G94: 0.74
A95: LDNO EHV: LV HH Metered | D95: 0.816 | E95: 0.186 | F95: 0.12 | G95: 2.95 | H95: 0.28 | I95: 0.42 | J95: 0.022
A96: LDNO EHV: LV Sub HH Metered | D96: 0.943 | E96: 0.244 | F96: 0.186 | G96: 1.66 | H96: 0.82 | I96: 0.94 | J96: 0.018
A97: LDNO EHV: HV HH Metered | D97: 0.804 | E97: 0.25 | F97: 0.209 | G97: 28.53 | H97: 1.03 | I97: 1.27 | J97: 0.012
A98: LDNO EHV: NHH UMS category A | D98: 0.249
A99: LDNO EHV: NHH UMS category B | D99: 0.275
A100: LDNO EHV: NHH UMS category C | D100: 0.366
A101: LDNO EHV: NHH UMS category D | D101: 0.23
A102: LDNO EHV: LV UMS (Pseudo HH Metered) | D102: 1.766 | E102: 0.235 | F102: 0.174
A103: LDNO EHV: LV Generation NHH or Aggregate HH | D103: -0.14 | G103: 0
...

Sheet Annex 5 LLFs
A1: Back to Overview
A2: These line loss factors are illustrative based on the latest calculated values and are published in good faith. However, the line loss factors that are approved by the BSC Panel for the applicable year and consequently published on the Elexon website will take precedence and be used in Settlement if they differ from these values.
A3: =Overview!B4& " - Illustrative LLFs for year beginning "&Overview!D4 -> SP Distribution - Illustrative LLFs for year beginning 1 April 2018
A4: Time periods | B4: Period 1 | C4: Period 2 | D4: Period 3 | E4: Period 4
A6: Monday to Friday March to October | B6: 23:30 – 07:30 | C6: 07:30 – 23:30
A7: Monday to Friday November to February | B7: 23:30 – 07:30 | C7: 20:00 – 23:30 | D7: 07:30 – 16:00 19:00 – 20:00 | E7: 16:00 – 19:00
A8: Saturday and Sunday All Year | B8: 23:30 – 07:30 | C8: 07:30 – 23:30
A9: Notes | B9: All the above times are in UK Clock time
A12: Generic demand and generation LLFs
A13: Metered voltage, respective periods and associated LLFCs
A14: Metered voltage | B14: Period 1 | C14: Period 2 | D14: Period 3 | E14: Period 4 | F14: Associated LLFC
A15: Low-voltage network | B15: 1.082 | C15: 1.098 | D15: 1.112 | E15: 1.126 | F15: 100,101,110,111,112,113,114,115,116,117,118,119,120,121,130,132,133,134,135,136,137,160,161,162,163,164,165,166,180,200,201,202,203,204,205,220,221,222,223,224,225,240,241,242,243,244,245,246,260,280,400,402,500,504,603,604,607,608,781,782,783,784,785,900,901,902,903,910
A16: Low-voltage substation | B16: 1.045 | C16: 1.044 | D16: 1.046 | E16: 1.049 | F16: 404,506,507,602,609,610
A17: High-voltage network | B17: 1.023 | C17: 1.026 | D17: 1.029 | E17: 1.031 | F17: 301,302,401,501,505,599,600,601,605,606,611,612,615,616,617
A18: High-voltage substation | B18: 1.013 | C18: 1.012 | D18: 1.013 | E18: 1.013 | F18: 310,311,312,313,314,315,316,317,318,319,320,321,322,323,324,325,326,327,328,329,330,331,332,333,334,335,336,337,338,339,340,750,751,752,753,754,755,756,757,758,759,760,761,762,763,764,765,862,866,867
A19: 33kV generic (demand) | B19: 1.003 | C19: 1.004 | D19: 1.005 | E19: 1.005
A20: 33kV generic (generation) | B20: 1 | C20: 1 | D20: 1 | E20: 1
A21: 132kV generic
A22: 132kV generic
A24: EHV site specific LLFs
A25: Demand
A26: Site | B26: Period 1 | C26: Period 2 | D26: Period 3 | E26: Period 4 | F26: Associated LLFC
A27: Rhodders | B27: 1.003 | C27: 1.004 | D27: 1.005 | E27: 1.005 | F27: 800
A28: Minsca | B28: 1 | C28: 1.001 | D28: 1.001 | E28: 1.002 | F28: 801
A29: Bankend Rig | B29: 1.006 | C29: 1.01 | D29: 1.012 | E29: 1.014 | F29: 802
A30: Barlockhart Moor | B30: 1 | C30: 1 | D30: 1 | E30: 1.002 | F30: 803
A31: Blantyre Muir | B31: 1 | C31: 1 | D31: 1 | E31: 1.001 | F31: 804
A32: Hunteston WF | B32: 1 | C32: 1 | D32: 1 | E32: 1 | F32: 805
A33: Middleton Farm | B33: 1.001 | C33: 1.001 | D33: 1.002 | E33: 1.002 | F33: 806
A34: Neilston Community | B34: 1.001 | C34: 1.002 | D34: 1.002 | E34: 1.003 | F34: 807
A35: Garlaff Landfill | B35: 0.999 | C35: 1 | D35: 1.001 | E35: 1.019 | F35: 808
A36: Hagshaw Hill Extension | B36: 1 | C36: 1.001 | D36: 1.002 | E36: 1.002 | F36: 809
A37: Muirhall | B37: 1 | C37: 1 | D37: 1 | E37: 1 | F37: 811
A38: Burnfoot | B38: 1 | C38: 1 | D38: 1 | E38: 1 | F38: 812
... A111: Quixwood Windfarm | B111: 1.003 | C111: 1.004 | D111: 1.005 | E111: 1.005 | F111: 892
A112: Millerhill Windfarm | B112: 1.003 | C112: 1.004 | D112: 1.005 | E112: 1.005 | F112: TBC
A113: Drymen | B113: 0.998 | C113: 0.998 | D113: 0.998 | E113: 0.998 | F113: MSID 8083
A114: Killearn | B114: 1 | C114: 1 | D114: 1 | E114: 1 | F114: MSID 8085
A115: Markinch | B115: 0.999 | C115: 0.999 | D115: 0.998 | E115: 0.997 | F115: MSID 8334
A116: Auchrobert | B116: 1 | C116: 1 | D116: 1 | E116: 1 | F116: MSID 8348
A117: Andershaw WF | B117: 1 | C117: 1 | D117: 1 | E117: 1 | F117: MSID 8341
A118: HareHill Extension | B118: 1 | C118: 1 | D118: 1 | E118: 1 | F118: MSID 8339
A119: Assel Valley | B119: 1 | C119: 1 | D119: 1 | E119: 1 | F119: MSID 8347
A120: Aries | B120: 1 | C120: 1 | D120: 1 | E120: 1 | F120: MSID 8340
A121: Harburnhead | B121: 1 | C121: 1 | D121: 1 | E121: 1 | F121: MSID 8349
A122: Twenty Shilling Hill | B122: 1 | C122: 1 | D122: 1 | E122: 1 | F122: MSID TBC
A124: EHV site specific LLFs
A125: Generation
A126: Site | B126: Period 1 | C126: Period 2 | D126: Period 3 | E126: Period 4 | F126: Associated LLFC
A127: Craigengelt Windfarm Export | B127: 0.99 | C127: 0.99 | D127: 0.987 | E127: 0.987 | F127: 620
A128: Greenknowes Windfarm Export | B128: 0.992 | C128: 0.992 | D128: 0.99 | E128: 0.989 | F128: 621
A129: Muirpark Windfarm | B129: 1 | C129: 1 | D129: 1 | E129: 1 | F129: 623
A130: Greendykeside Windfarm Export | B130: 0.999 | C130: 0.999 | D130: 0.999 | E130: 0.999 | F130: 624
A131: Aikengall Community WF Export | B131: 0.993 | C131: 0.993 | D131: 0.991 | E131: 0.991 | F131: 625
A132: Hagshaw Hill Windfarm Export | B132: 1.001 | C132: 1.003 | D132: 1.003 | E132: 1.005 | F132: 626
A133: Gallow Rig Windfarm Export | B133: 1.008 | C133: 1.014 | D133: 1.017 | E133: 1.022 | F133: 627
A134: Polwhat Rig Windfarm Export | B134: 1.007 | C134: 1.013 | D134: 1.017 | E134: 1.021 | F134: 628
A135: Hagshaw Hill Extension Export | B135: 0.99 | C135: 0.99 | D135: 0.988 | E135: 0.988 | F135: 629
A136: Dun Law - Export | B136: 0.983 | C136: 0.982 | D136: 0.977 | E136: 0.978 | F136: 630
A137: EPR Scotland Ltd | B137: 0.999 | C137: 0.999 | D137: 1 | E137: 1 | F137: 631
A138: Bowbeat (Emly Bank) Export | B138: 1.003 | C138: 1.008 | D138: 1.008 | E138: 1.011 | F138: 632
... A197: Penmansheill | B197: 1 | C197: 1 | D197: 1 | E197: 1 | F197: 708
A198: Millerhill Windfarm Export | B198: 1 | C198: 1 | D198: 1 | E198: 1 | F198: TBC
A199: Minsca Windfarm | B199: 0.991 | C199: 0.991 | D199: 0.989 | E199: 0.989 | F199: MSID 8182
A200: Dalswinton Windfarm | B200: 0.995 | C200: 0.995 | D200: 0.994 | E200: 0.994 | F200: MSID 8183
A201: Markinch | B201: 0.999 | C201: 0.999 | D201: 0.998 | E201: 0.997 | F201: MSID 8334
A202: Assel Valley Windfarm | B202: 1 | C202: 1 | D202: 1 | E202: 1 | F202: MSID 8347
A203: Glenchamber Windfarm | B203: 1 | C203: 1 | D203: 1 | E203: 1 | F203: MSID 8732
A204: Harehill Extension | B204: 1 | C204: 1 | D204: 1 | E204: 1 | F204: MSID 8339
A205: Andershaw Windfarm | B205: 1 | C205: 1 | D205: 1 | E205: 1 | F205: MSID 8341
A206: Aries Windfarm | B206: 1 | C206: 1 | D206: 1 | E206: 1 | F206: MSID 8340
A207: Auchrobert Windfarm | B207: 1 | C207: 1 | D207: 1 | E207: 1 | F207: MSID 8348
A208: Harburnhead Windfarm | B208: 1 | C208: 1 | D208: 1 | E208: 1 | F208: MSID 8349
A209: Twenty Shilling Hill | B209: 1 | C209: 1 | D209: 1 | E209: 1 | F209: MSID TBC

Sheet Annex 6 New Designated EHV Prop
A1: Back to Overview | G1: Note: The list of MPANs/MSIDs provided may be incomplete; the DNO reserves the right to apply the listed charges to any other MPANs/MSIDs associated with the site.
A2: Annex 6 - Addendum to Annex 2 EHV charges
A4: =Overview!B4& " - Effective from "&Overview!D4&" - "&Overview!E4&" new designated EHV charges" -> SP Distribution - Effective from 1 April 2018 - Final new designated EHV charges
A5: Import Unique Identifier | B5: LLFC | C5: Import MPANs/MSIDs | D5: Export Unique Identifier | E5: LLFC | F5: Export MPANs/MSIDs | G5: Name | H5: ='Annex 2 EHV charges'!H10 -> Import Super Red unit charge (p/kWh) | I5: ='Annex 2 EHV charges'!I10 -> Import fixed charge (p/day) | J5: ='Annex 2 EHV charges'!J10 -> Import capacity charge (p/kVA/day) | K5: ='Annex 2 EHV charges'!K10 -> Import exceeded capacity charge (p/kVA/day) | L5: ='Annex 2 EHV charges'!L10 -> Export Super Red unit charge (p/kWh) | M5: ='Annex 2 EHV charges'!M10 -> Export fixed charge (p/day) | N5: ='Annex 2 EHV charges'!N10 -> Export capacity charge (p/kVA/day) | O5: ='Annex 2 EHV charges'!O10 -> Export exceeded capacity charge (p/kVA/day)
A6: EDCM import 1 | B6: 848 | C6: 1800060904910 | D6: EDCM export 1 | E6: 648 | F6: 1800060904929 | G6: Craigannet | H6: 0 | I6: 148.44 | J6: 4.49 | K6: 4.49 | L6: 0 | M6: 3180.83 | N6: 0.05 | O6: 0.05
A7: EDCM import 2 | B7: 810 | C7: 1800060954752 | D7: EDCM export 2 | E7: 619 | F7: 1800060954752 | G7: Broxburn ESS | H7: 0 | I7: 1786.25 | J7: 1.71 | K7: 1.71 | L7: 0 | M7: 1786.25 | N7: 0.05 | O7: 0.05
A8: EDCM import 3 | D8: EDCM export 3
A9: EDCM import 4 | D9: EDCM export 4
A10: EDCM import 5 | D10: EDCM export 5
A11: EDCM import 6 | D11: EDCM export 6
A12: EDCM import 7 | D12: EDCM export 7
A13: EDCM import 8 | D13: EDCM export 8
A14: EDCM import 9 | D14: EDCM export 9
A15: EDCM import 10 | D15: EDCM export 10
A17: =Overview!B4& " - Effective from "&Overview!D4&" - "&Overview!E4&" new designated EHV line loss factors" -> SP Distribution - Effective from 1 April 2018 - Final new designated EHV line loss factors
A18: Import Unique Identifier | B18: LLFC | C18: Import MPANs/MSIDs | D18: Export Unique Identifier | E18: LLFC | F18: Export MPANs/MSIDs | G18: Name | H18: Import LLF period 1 | I18: Import LLF period 2 | J18: Import LLF period 3 | K18: Import LLF period 4 | L18: Import LLF period 5 | M18: Export LLF period 1 | N18: Export LLF period 2 | O18: Export LLF period 3 | P18: Export LLF period 4 | Q18: Export LLF period 5
A19: EDCM Import 1 | B19: 848 | C19: 1800060904910 | D19: EDCM export 1 | E19: 648 | F19: 1800060904929 | G19: Craigannet | H19: 1.003 | I19: 1.004 | J19: 1.005 | K19: 1.005 | M19: 1 | N19: 1 | O19: 1 | P19: 1
A20: EDCM Import 2 | B20: 810 | C20: 1800060954752 | D20: EDCM export 2 | E20: 619 | F20: 1800060954752 | G20: Broxburn ESS | H20: 1 | I20: 1 | J20: 1 | K20: 1 | M20: 1.003 | N20: 1.004 | O20: 1.005 | P20: 1.005
A21: EDCM Import 3 | D21: EDCM Export 3
A22: EDCM Import 4 | D22: EDCM Export 4
A23: EDCM Import 5 | D23: EDCM Export 5
A24: EDCM Import 6 | D24: EDCM Export 6
A25: EDCM Import 7 | D25: EDCM Export 7
A26: EDCM Import 8 | D26: EDCM Export 8
A27: EDCM Import 9 | D27: EDCM Export 9
A28: EDCM Import 10 | D28: EDCM Export 10

Sheet Nodal prices
A1: Back to Overview
A2: =Overview!B4& " - Effective from "&Overview!D4&" - "&Overview!E4&" Nodal/Zonal charges" -> SP Distribution - Effective from 1 April 2018 - Final Nodal/Zonal charges
A3: Node/Zone ID | B3: Geographical name | C3: Local charge 1 £/kVA | D3: Remote charge 1 £/kVA
A4: KILBOWIE 33kV | B4: 2
A5: STRATHLEVEN | B5: 2
A6: CUMBERNAULD | B6: 2
A7: ST ANDREWS CROSS | B7: 2
A8: DUNBAR | B8: 2
A9: COATBRIDGE | B9: 2
A10: GLENLUCE | B10: 2
A11: NEWARTHILL | B11: 2
A12: DEVONSIDE | B12: 2
A13: LIVINGSTON EAST | B13: 2
A14: CHAPELCROSS | B14: 2
A15: LINMILL | B15: 2
A16: DEWAR PLACE & SHRUBHILL | B16: 2 | D16: 1.5745304
A17: LEVEN | B17: 2
A18: DRUMCHAPEL | B18: 2
A19: JOHNSTONE | B19: 2
A20: E KILBRIDE SOUTH | B20: 2
A21: BATHGATE | B21: 2
A22: DALMARNOCK | B22: 2
A23: MAYBOLE | B23: 2
A24: CUPAR | B24: 2 | D24: 12.94645
A25: CROOKSTON A | B25: 2
A26: GRANGEMOUTH A | B26: 2
A27: EASTERHOUSE | B27: 2
A28: AYR | B28: 2 | D28: 4.190074
A29: COYLTON | B29: 2
A30: BERWICK & ECCLES & GALASHIELDS | B30: 2
A31: SIGHTHILL | B31: 2
A32: WESTBURN ROAD | B32: 2
A33: BAINSFORD | B33: 2
A34: DEVOL MOOR | B34: 2
A35: KILLERMONT | B35: 2
A36: DUNFERMLINE | B36: 2
A37: KILMARNOCK SOUTH | B37: 2 | D37: 6.3394456
A38: PAISLEY | B38: 2
A39: KILMARNOCK TOWN | B39: 2
A40: WISHAW | B40: 2
A41: GIFFNOCK | B41: 2
A42: REDHOUSE | B42: 2
A43: STRATHAVEN | B43: 2
A44: RAVENSCRAIG | B44: 2
A45: BONNYBRIDGE | B45: 2 | D45: 3.6143198
A46: KAIMES | B46: 2
A47: WESTFIELD | B47: 2
A48: HELENSBURGH | B48: 2
A49: BRAEHEAD PARK | B49: 2 | D49: 3.364452
A50: BROXBURN | B50: 2
A51: HUNTERSTON FARM | B51: 2
A52: GLENNISTON | B52: 2
A53: HAGGS ROAD | B53: 2
A54: INVERKEITHING | B54: 2 | D54: 1.9063059
A55: SALTCOATS A&B | B55: 2
A56: SPANGO VALLEY | B56: 2
A57: TONGLAND | B57: 2 | D57: 1.4253769
A58: GOVAN | B58: 2
A59: DUMFRIES | B59: 2
A60: CHARLOTTE STREET | B60: 2 | D60: 1.3464772
A61: CARNTYNE | B61: 2
A62: PORT DUNDAS | B62: 2
A63: COCKENZIE | B63: 2 | D63: 9.1060314
A64: GLENROTHES | B64: 2
A65: EAST KILBRIDE | B65: 2
A66: STIRLING | B66: 2
A67: HAWICK | B67: 2 | D67: 2.8669452
A68: WHISTLFIELD | B68: 2
A69: CROOKSTON B | B69: 2
A70: KILWINNING | B70: 2
A71: DRUMCROSS | B71: 2
A72: DUMFRIES ICI | B72: 2
A73: ELDERSLIE | B73: 2
A74: WEST GEORGE ST | B74: 2
A75: ERSKINE | B75: 2
A76: PARTICK | B76: 2
A77: WHITEHOUSE | B77: 2
A78: GORGIE | B78: 2
A79: PORTOBELLO | B79: 2
A80: TELFORD ROAD | B80: 2
A81: ABBE5- 11.000 | B81: 3 | C81: KILBOWIE 33kV
A82: ABERFO1A 11.000 | B82: 3 | C82: STRATHLEVEN
A83: ABRL5- 11.000 | B83: 3 | C83: CUMBERNAULD
A84: AIRD5- 11.000 | B84: 3 | C84: COATBRIDGE
A85: ALBK5- 11.000 | B85: 3 | C85: NEWARTHILL
A86: ALGA5- 11.000 | B86: 3 | C86: DEVONSIDE | D86: 2.2532175
A87: ALMV5- 11.000 | B87: 3 | C87: LIVINGSTON EAST
A88: ANAN5- 11.000 | B88: 3 | C88: CHAPELCROSS
A89: ANST5- 11.000 | B89: 3 | C89: LEVEN
A90: ARCR5- 11.000 | B90: 3 | C90: DRUMCHAPEL
A91: ARDD5- 11.000 | B91: 3 | C91: JOHNSTONE
A92: ARMA5- 11.000 | B92: 3 | C92: BATHGATE
A93: ASHS5- 11.000 | B93: 3 | C93: DALMARNOCK
A94: AUCHEN1A 11.000 | B94: 3 | C94: STRATHLEVEN
A95: AUCM5- 11.000 | B95: 3 | C95: CUPAR
A96: AUCN5- 11.000 | B96: 3 | C96: GLENLUCE
A97: AURR5- 11.000 | B97: 3 | C97: CROOKSTON A
A98: AVEC5- 11.000 | B98: 3 | C98: GRANGEMOUTH A
... A120: BLBU5- 11.000 | B120: 3 | C120: BATHGATE
A121: BONG5- 11.000 | B121: 3 | C121: LINMILL | D121: 6.3860455
...

Sheet SSC TPR unit rate lookup
A1: Back to Overview
A28: Standard Settlement Configuration Id | B28: Time Pattern Regime Id | C28: Standard Settlement Configuration Desc | D28: Common Decode | G28: Change implemented | H28: Date | I28: Comments
A29: 3 | B29: 166 | C29: 10-hour OP | D29: O | H29: 40057 | I29: First published spreadsheet
A30: 4 | B30: 168 | C30: 10-hour OP | D30: O | G30: SSC 0330 charge rates corrected | H30: 40275 | I30: Previous Off-peak rate corrected to charge 2
A31: 5 | B31: 100 | C31: 10-hour OP + w/e | D31: O | G31: SSC 0250 charge rate corrected | H31: 40347 | I31: Previous rate 1 corrected to Off Peak O
A32: 6 | B32: 257 | C32: 10.5-hour OP | D32: O | G32: SSC 0134 charge rate corrected | H32: 41166 | I32: TPR 00101 corrected from Off Peak O to Rate 1
A33: 7 | B33: 158 | C33: 10.5-hour OP | D33: O | G33: New SSCs added | H33: 41178 | I33: New SSCs from 0953 added.
A34: 8 | B34: 159 | C34: 10.5-hour OP | D34: O | G34: SSC 0394 charge rate corrected | H34: 41758 | I34: TPR 01177 corrected to rate 2
A35: 9 | B35: 1111 | C35: 10.5-hour OP | D35: O | G35: Table reviewed and updated | H35: 41758 | I35: New SSCs from 0949 to 0952, 0975 & 0976 and 0982 & 0983 added.
A36: 10 | B36: 1104 | C36: 10.5-hour OP | D36: O | G36: Table reviewed and updated | H36: 41944 | I36: New SSCs from 0984 and 0985 added.
A37: 11 | B37: 1112 | C37: 10.5-hour OP | D37: O | G37: SSC 0313 charge code corrected | H37: 42081 | I37: TPR 01006 corrected to code O
A38: 12 | B38: 1116 | C38: 10.5-hour OP | D38: O | G38: SSC 0320 charge code corrected | H38: 42081 | I38: TPR 00072 corrected to code 2
A39: 13 | B39: 139 | C39: 11 Hour OP | D39: EMEB or MIDE only | G39: SSC 0781 charge code corrected | H39: 42081 | I39: TPR 00327 corrected to code O
A40: 15 | B40: 152 | C40: 11 Hour OP | D40: EMEB or MIDE only | G40: SSC 0935 charge code corrected | H40: 42081 | I40: TPR 00375 corrected to code 1 or Unsupported (SWAE and SWEB)
A41: 16 | B41: 113 | C41: 11.5-hour OP | D41: Unsupported (SWEB) | G41: SSC 0953 charge code corrected | H41: 42081 | I41: TPR 00424 corrected to code 1 or Unsupported (SWAE and SWEB)
... A74: 50 | B74: 14 | C74: 12-hour OP + w/e & Summer | D74: O | G74: SSC 0942 charge code corrected | H74: 42166 | I74: TPR 00400 corrected to code 1
A75: 51 | B75: 112 | C75: 12-hour night | D75: 1 | G75: SSC 0943 charge code corrected | H75: 42166 | I75: TPR 00404 corrected to code 1
A76: 51 | B76: 120 | C76: 12-hour night | D76: 2 | G76: SSC 0944 charge code corrected | H76: 42166 | I76: TPR 00406 corrected to code 1
A77: 52 | B77: 114 | C77: 12-hour OP | D77: EMEB or MIDE only | G77: SSC 0945 charge code corrected | H77: 42166 | I77: TPR 00408 corrected to code 1
A78: 53 | B78: 115 | C78: 12-hour OP | D78: EMEB or MIDE only | G78: SSC 0946 charge code corrected | H78: 42166 | I78: TPR 00410 corrected to code 1
A79: 55 | B79: 117 | C79: 12-hour OP | D79: EMEB or MIDE only | G79: SSC 0954 charge code corrected | H79: 42166 | I79: TPR 00426 corrected to code 1
A80: 56 | B80: 118 | C80: 12-hour OP | D80: EMEB or MIDE only | G80: SSC 0967 charge code corrected | H80: 42166 | I80: TPR 00442 corrected to code 1
A81: 57 | B81: 119 | C81: 12-hour OP | D81: O | G81: SSC 0970 charge code corrected | H81: 42166 | I81: TPR 00447 corrected to code 2
A82: 58 | B82: 21 | C82: Key Meter pseudo 2-rate | D82: 1 | G82: SSC 0970 charge code corrected | H82: 42166 | I82: TPR 00448 corrected to code 1
A83: 58 | B83: 175 | C83: Key Meter pseudo 2-rate | D83: 1 | G83: SSC 0971 charge code corrected | H83: 42166 | I83: TPR 00493 corrected to code 1
A84: 59 | B84: 121 | C84: 12-hour OP | D84: EMEB or MIDE only
A85: 60 | B85: 122 | C85: 12-hour OP | D85: O
A86: 62 | B86: 1119 | C86: 8-hour OP (see also SSC 427) | D86: 2 or Unsupported (SWEB)
A87: 63 | B87: 172 | C87: 9-hour OP | D87: EMEB or MIDE only
A88: 64 | B88: 1105 | C88: 12-hour OP | D88: O
A89: 65 | B89: 10 | C89: 12-hour OP + Summer | D89: O
A90: 66 | B90: 1106 | C90: 12-hour OP + Summer | D90: O
A91: 67 | B91: 102 | C91: 12.5-hour OP | D91: Unsupported (SWEB)
A92: 71 | B92: 109 | C92: 12.5-hour OP | D92: O
A93: 72 | B93: 111 | C93: 12.5-hour OP | D93: O
A94: 73 | B94: 156 | C94: 12.5-hour OP | D94: Unsupported (SWEB)
A95: 74 | B95: 17 | C95: 12.5-hour OP + Summer | D95: O
... A99: 78 | B99: 13 | C99: 12.5-hour OP + w/e & Summer | D99: O
A100: 79 | B100: 97 | C100: 14-hour E7 | D100: 2
A101: 79 | B101: 164 | C101: 14-hour E7 | D101: 1
A102: 80 | B102: 96 | C102: 14-hour Off Peak | D102: O
A103: 81 | B103: 60 | C103: 14-hour OP + Sun | D103: O
A104: 82 | B104: 83 | C104: 14.5-hour OP | D104: O
A105: 83 | B105: 84 | C105: 14.5-hour OP | D105: O
A106: 84 | B106: 85 | C106: 14.5-hour OP | D106: O
A107: 85 | B107: 86 | C107: 14.5-hour OP | D107: O
A108: 86 | B108: 1107 | C108: 14.5-hour OP | D108: O
A109: 87 | B109: 1109 | C109: 14.5-hour OP | D109: O
A110: 88 | B110: 1113 | C110: 14.5-hour OP | D110: O
A111: 91 | B111: 3 | C111: 14.5-hour OP + Summer | D111: O
A112: 92 | B112: 4 | C112: 14.5-hour OP + Summer | D112: O
A113: 93 | B113: 30 | C113: split 7-hour E7 | D113: 1
A114: 93 | B114: 214 | C114: split 7-hour E7 | D114: 2
A115: 94 | B115: 1108 | C115: 14.5-hour OP + Summer | D115: O
A116: 95 | B116: 1110 | C116: 14.5-hour OP + Summer | D116: O
A117: 96 | B117: 1114 | C117: 14.5-hour OP + Summer | D117: O
A118: 97 | B118: 54 | C118: 14.5-hour OP + w/e | D118: O
A119: 98 | B119: 12 | C119: 14.5-hour OP + w/e & Summer | D119: O
A120: 99 | B120: 75 | C120: 15-hour OP | D120: EMEB or MIDE only
A121: 100 | B121: 76 | C121: 15-hour OP | D121: EMEB or MIDE only
A122: 101 | B122: 7 | C122: 15-hour OP + w/e & Summer | D122: O
A123: 102 | B123: 8 | C123: 15-hour OP + w/e & Summer | D123: O
A124: 103 | B124: 9 | C124: 15-hour OP + w/e & Summer | D124: O
A125: 104 | B125: 61 | C125: 15.5-hour OP | D125: Unsupported (SWEB)
A126: 105 | B126: 65 | C126: 15.5-hour OP | D126: O
... A140: 120 | B140: 11 | C140: 9-hour OP | D140: O
A141: 121 | B141: 26 | C141: 2-rate terms | D141: 2
A142: 121 | B142: 224 | C142: 2-rate terms | D142: 1
A143: 122 | B143: 201 | C143: 2-rate SToD | D143: 1
A144: 122 | B144: 245 | C144: 2-rate SToD | D144: 2
A145: 123 | B145: 1307 | C145: 2-rate variable SToD | D145: 1
A146: 124 | B146: 1319 | C146: 2-rate variable SToD | D146: 1
A147: 125 | B147: 1315 | C147: 2-rate variable SToD | D147: 1
A148: 126 | B148: 1193 | C148: 7-hour E7 | D148: 1
A149: 126 | B149: 1194 | C149: 7-hour E7 | D149: 2
A150: 127 | B150: 80 | C150: 3-rate SToD | D150: Unsupported (SWEB)
A151: 127 | B151: 148 | C151: 3-rate SToD | D151: 1
A152: 127 | B152: 221 | C152: 3-rate SToD | D152: 2 or Unsupported (SWEB)
A153: 128 | B153: 1120 | C153: Dom/Non-dom Seasonal (link SSC 0342) | D153: 1
A154: 128 | B154: 1121 | C154: Dom/Non-dom Seasonal (link SSC 0342) | D154: 1
A155: 128 | B155: 1122 | C155: Dom/Non-dom Seasonal (link SSC 0342) | D155: 2
A156: 129 | B156: 169 | C156: 3-rate SToD | D156: 1
A157: 129 | B157: 202 | C157: 3-rate SToD | D157: 1
A158: 129 | B158: 222 | C158: 3-rate SToD | D158: 2
A159: 130 | B159: 1308 | C159: 3-rate variable | D159: 1
A160: 130 | B160: 1309 | C160: 3-rate variable | D160: 1
A161: 130 | B161: 1310 | C161: 3-rate variable | D161: 2
A162: 131 | B162: 1311 | C162: 3-rate variable | D162: 1
A163: 131 | B163: 1312 | C163: 3-rate variable | D163: 1
A164: 131 | B164: 1313 | C164: 3-rate variable | D164: 2
A165: 132 | B165: 92 | C165: 4-rate SToD | D165: EMEB or MIDE only
A166: 132 | B166: 210 | C166: 4-rate SToD | D166: 2
A167: 132 | B167: 234 | C167: 4-rate SToD | D167: EMEB or MIDE only
A168: 132 | B168: 236 | C168: 4-rate SToD | D168: EMEB or MIDE only
A169: 133 | B169: 92 | C169: 4-rate SToD | D169: 1
A170: 133 | B170: 210 | C170: 4-rate SToD | D170: 2
A171: 133 | B171: 233 | C171: 4-rate SToD | D171: 1
A172: 133 | B172: 246 | C172: 4-rate SToD | D172: 1
A173: 134 | B173: 101 | C173: 4-rate SToD | D173: 1
A174: 134 | B174: 210 | C174: 4-rate SToD | D174: 2
...

Sheet Charge Calculator
B1: Back to Overview
B2: =Overview!B4& " - Effective from "&Overview!D4&" - "&Overview!E4 -> SP Distribution - Effective from 1 April 2018 - Final
B4: LV and HV tariff calculator | L4: EHV site calculator
B5: Step 1, Choose your tariff using the drop down list in cell B10 | L5: Step 1, Choose your tariff using the drop down list in cell L10
B6: Step 2, After selecting a tariff in step 1, Cells C12-I12 will generate headings, please enter your consumption in cells C13:I13 underneath each heading generated (if no heading leave cell blank) | L6: Step 2, After selecting a tariff in step 1, Cells M12-T12 will generate headings, please enter your consumption in cells M13:T13 underneath each heading generated (if no heading leave cell blank)
B7: Step 3, Enter a forecast of consumption if required in cells C14:I14 | L7: Step 3, Enter a forecast of consumption if required in cells M14:T14
B9: Tariff details Choose tariff name from drop down box below | C9: ='Annex 1 LV and HV charges'!D13 -> Unit charge 1 (NHH) or red/black charge (HH) p/kWh | D9: ='Annex 1 LV and HV charges'!E13 -> Unit charge 2 (NHH) or amber/yellow charge (HH) p/kWh | E9: ='Annex 1 LV and HV charges'!F13 -> Green charge(HH) p/kWh | F9: ='Annex 1 LV and HV charges'!G13 -> Fixed charge p/MPAN/day | G9: ='Annex 1 LV and HV charges'!H13 -> Capacity charge p/kVA/day | H9: ='Annex 1 LV and HV charges'!I13 -> Exceeded capacity charge p/kVA/day | I9: ='Annex 1 LV and HV charges'!J13 -> Reactive power charge p/kVArh | L9: Site details Choose the site name from the drop down box below | M9: ='Annex 2 EHV charges'!H10 -> Import Super Red unit charge (p/kWh) | N9: ='Annex 2 EHV charges'!I10 -> Import fixed charge (p/day) | O9: ='Annex 2 EHV charges'!J10 -> Import capacity charge (p/kVA/day) | P9: ='Annex 2 EHV charges'!K10 -> Import exceeded capacity charge (p/kVA/day) | Q9: ='Annex 2 EHV charges'!L10 -> Export Super Red unit charge (p/kWh) | R9: ='Annex 2 EHV charges'!M10 -> Export fixed charge (p/day) | S9: ='Annex 2 EHV charges'!N10 -> Export capacity charge (p/kVA/day) | T9: ='Annex 2 EHV charges'!O10 -> Export exceeded capacity charge (p/kVA/day)
C10: =IFERROR(VLOOKUP($B$10,'Annex 1 LV and HV charges'!$A:$K,4,FALSE),"") | D10: =IFERROR(VLOOKUP($B$10,'Annex 1 LV and HV charges'!$A:$K,5,FALSE),"") | E10: =IFERROR(VLOOKUP($B$10,'Annex 1 LV and HV charges'!$A:$K,6,FALSE),"") | F10: =IFERROR(VLOOKUP($B$10,'Annex 1 LV and HV charges'!$A:$K,7,FALSE),"") | G10: =IFERROR(VLOOKUP($B$10,'Annex 1 LV and HV charges'!$A:$K,8,FALSE),"") | H10: =IFERROR(VLOOKUP($B$10,'Annex 1 LV and HV charges'!$A:$K,9,FALSE),"") | I10: =IFERROR(VLOOKUP($B$10,'Annex 1 LV and HV charges'!$A:$K,10,FALSE),"") | M10: =IFERROR(VLOOKUP($L$10,'Annex 2 EHV charges'!$G:$O,2,FALSE),"") | N10: =IFERROR(VLOOKUP($L$10,'Annex 2 EHV charges'!$G:$O,3,FALSE),"") | O10: =IFERROR(VLOOKUP($L$10,'Annex 2 EHV charges'!$G:$O,4,FALSE),"") | P10: =IFERROR(VLOOKUP($L$10,'Annex 2 EHV charges'!$G:$O,5,FALSE),"") | Q10: =IFERROR(VLOOKUP($L$10,'Annex 2 EHV charges'!$G:$O,6,FALSE),"") | R10: =IFERROR(VLOOKUP($L$10,'Annex 2 EHV charges'!$G:$O,7,FALSE),"") | S10: =IFERROR(VLOOKUP($L$10,'Annex 2 EHV charges'!$G:$O,8,FALSE),"") | T10: =IFERROR(VLOOKUP($L$10,'Annex 2 EHV charges'!$G:$O,9,FALSE),"")
B12: Tariff components | C12: Unit 1 kWh (red/black/day) | D12: Unit 2 kWh (amber/yellow /night) | E12: Unit 3 kWh (green) | F12: Number of days in consumption period i.e. 365 if one year | G12: Maximum import or export capacity kVA | H12: Average daily exceeded capacity kVA | I12: Excess reactive units kVArh | L12: Tariff components | M12: Import super red kWh | N12: Number of days in consumption period i.e. 365 if one year | O12: Maximum import capacity kVA | P12: Average daily exceeded capacity kVA | Q12: Export Super Red kWh | R12: Number of days in consumption period i.e. 365 if one year | S12: Maximum export capacity kVA | T12: Average daily exceeded capacity kVA
B13: Enter current consumption details | L13: Enter current consumption details | R13: =N13 -> 0
B14: Enter forecast consumption details (if different) | C14: =C13 -> 0 | D14: =D13 -> 0 | E14: =E13 -> 0 | F14: =F13 -> 0 | G14: =G13 -> 0 | H14: =H13 -> 0 | I14: =I13 -> 0 | L14: Enter forecast consumption details (if different) | M14: =M13 -> 0 | N14: =N13 -> 0 | O14: =O13 -> 0 | P14: =P13 -> 0 | Q14: =Q13 -> 0 | R14: =R13 -> 0 | S14: =S13 -> 0 | T14: =T13 -> 0
B16: Charge components | C16: Unit 1 £ | D16: Unit 2 £ | E16: Unit 3 £ | F16: Fixed charge £ | G16: Capacity charge £ | H16: Exceeded capacity charge £ | I16: Reactive power charge £ | L16: Charge components | M16: Import super red charge £ | N16: Import fixed charge £ | O16: Import capacity charge £ | P16: Import exceeded capacity charge £ | Q16: Export super red charge £ | R16: Export fixed charge £ | S16: Export capacity charge £ | T16: Export exceeded capacity charge £
B17: Current consumption period charges | C17: =IFERROR(C10*C13/100,"") | D17: =IFERROR(D10*D13/100,"") | E17: =IFERROR(E10*E13/100,"") | F17: =IFERROR(F10*F13/100,"") | G17: =IFERROR(G10*G13*F13/100,"") | H17: =IFERROR(H10*H13*F13/100,"") | I17: =IFERROR(I10*I13/100,"") | L17: Current consumption period charges | M17: =IFERROR(M10*M13/100,"") | N17: =IFERROR(N10*N13/100,"") | O17: =IFERROR(O10*O13*N13/100,"") | P17: =IFERROR(P10*P13*N13/100,"") | Q17: =IFERROR(Q10*Q13/100,"") | R17: =IFERROR(R10*R13/100,"") | S17: =IFERROR(S10*S13*R13/100,"") | T17: =IFERROR(T10*T13*R13/100,"")
B18: Forecast consumption period charges | C18: =IFERROR(C10*C14/100,"") | D18: =IFERROR(D10*D14/100,"") | E18: =IFERROR(E10*E14/100,"") | F18: =IFERROR(F10*F14/100,"") | G18: =IFERROR(G10*G14*F14/100,"") | H18: =IFERROR(H10*H14*F14/100,"") | I18: =IFERROR(I10*I14/100,"") | L18: Forecast consumption period charges | M18: =IFERROR(M10*M14/100,"") | N18: =IFERROR(N10*N14/100,"") | O18: =IFERROR(O10*O14*N14/100,"") | P18: =IFERROR(P10*P14*N14/100,"") | Q18: =IFERROR(Q10*Q14/100,"") | R18: =IFERROR(R10*R14/100,"") | S18: =IFERROR(S10*S14*R14/100,"") | T18: =IFERROR(T10*T14*R14/100,"")
C20: Total charge £ | M20: Import total charge £ | N20: Export total charge £
B21: Current consumption period charges | C21: =SUM(C17:I17) -> 0 | L21: Current consumption period charges | M21: =SUM(M17:P17) -> 0 | N21: =SUM(Q17:T17) -> 0
B22: Forecast consumption period charges | C22: =SUM(C18:I18) -> 0 | L22: Forecast consumption period charges | M22: =SUM(M18:P18) -> 0 | N22: =SUM(Q18:T18) -> 0
B24: These charges are estimates based on tariff selected and consumption values entered. | L24: These charges are estimates based on site selected and consumption values entered.
